{
  "type": "Feature",
  "properties": {
    "wof:name":"Cuesta Park",
    "wof:placetype":"neighbourhood"
},
  "geometry": {"coordinates":[-122.08036952762305,37.37836974048481],"type":"Point"}
}