{
  "type": "Feature",
  "properties": {
    "name:ceb_x_preferred":[
        "San Jos\u00e9 del Guaviare"
    ],
    "name:eng_x_preferred":[
        "Jorge Enrique Gonz\u00e1lez Torres Airport"
    ],
    "name:eng_x_variant":[
        "SJE",
        "SKSJ"
    ],
    "name:fas_x_preferred":[
        "\u0641\u0631\u0648\u062f\u06af\u0627\u0647 \u062e\u0648\u0631\u062e\u0647 \u0627\u0646\u0631\u06cc\u06a9\u0647 \u06af\u0648\u0646\u0632\u0627\u0644\u0633 \u062a\u0648\u0631\u0633"
    ],
    "name:fra_x_preferred":[
        "a\u00e9roport Jorge Enrique Gonz\u00e1lez Torres"
    ],
    "name:jpn_x_preferred":[
        "\u30db\u30eb\u30d8\u30fb\u30a8\u30f3\u30ea\u30b1\u30fb\u30b4\u30f3\u30b5\u30ec\u30b9\u30fb\u30c8\u30ec\u30b9\u7a7a\u6e2f"
    ],
    "name:msa_x_preferred":[
        "Lapangan Terbang Jorge E Gonzalez"
    ],
    "name:ron_x_preferred":[
        "Aeroportul Jorge Enrique Gonz\u00e1lez Torres"
    ],
    "name:spa_x_preferred":[
        "Aeropuerto Jorge Enrique Gonz\u00e1lez"
    ],
    "name:swe_x_preferred":[
        "San Jos\u00e9 del Guaviare"
    ],
    "name:tgk_x_preferred":[
        "\u0424\u0443\u0440\u0443\u0434\u0433\u043e\u04b3\u0438 \u0445\u0443\u0440\u0445\u04b3 \u043e\u043d\u0440\u0438\u043a\u04b3 \u0433\u0443\u043d\u0437\u043e\u043b\u0441 \u0442\u0443\u0440\u0441"
    ],
    "name:vie_x_preferred":[
        "S\u00e2n bay Jorge Enrique Gonz\u00e1lez"
    ],
    "oa:elevation_ft":"605",
    "oa:type":"medium_airport",
    "woe:hierarchy":{
        "country_id":23424787,
        "county_id":26797661,
        "planet_id":1,
        "state_id":2345059
    },
    "wof:name":"San Jose del Guaviaro Airport",
    "wof:placetype":"campus"
},
  "geometry": {"coordinates":[-72.63939999999999,2.57969],"type":"Point"}
}