{
  "type": "Feature",
  "properties": {
    "name:fas_x_preferred":[
        "\u0641\u0631\u0648\u062f\u06af\u0627\u0647 \u062c\u0647\u0627\u0631\u0633\u0648\u06af\u0648\u062f\u0627"
    ],
    "name:mar_x_preferred":[
        "\u091d\u0930\u0938\u0941\u0917\u0941\u0921\u093e \u0935\u093f\u092e\u093e\u0928\u0924\u0933"
    ],
    "name:msa_x_preferred":[
        "Lapangan Terbang Jharsuguda"
    ],
    "name:tgk_x_preferred":[
        "\u0424\u0443\u0440\u0443\u0434\u0433\u043e\u04b3\u0438 \u04b7\u04b3\u043e\u0440\u0441\u0443\u0433\u0443\u0434\u043e"
    ],
    "oa:elevation_ft":"751",
    "oa:type":"small_airport",
    "wd:wordcount":348,
    "woe:hierarchy":{
        "country_id":23424848,
        "county_id":12586611,
        "planet_id":1,
        "state_id":2345755
    },
    "wof:name":"Jharsuguda Airport",
    "wof:placetype":"campus"
},
  "geometry": {"coordinates":[84.05029999999999,21.9133],"type":"Point"}
}