{
  "type": "Feature",
  "properties": {
    "name:ben_x_preferred":[
        "\u099d\u09be\u09b0\u09b8\u09c1\u0997\u09c1\u09a1\u09bc\u09be \u09ac\u09bf\u09ae\u09be\u09a8\u09ac\u09a8\u09cd\u09a6\u09b0"
    ],
    "name:ceb_x_preferred":[
        "Jharsuguda Airport"
    ],
    "name:eng_x_preferred":[
        "Jharsuguda Airport"
    ],
    "name:fas_x_preferred":[
        "\u0641\u0631\u0648\u062f\u06af\u0627\u0647 \u062c\u0647\u0627\u0631\u0633\u0648\u06af\u0648\u062f\u0627"
    ],
    "name:hin_x_preferred":[
        "\u091d\u093e\u0930\u0938\u0941\u0917\u0941\u0921\u093e \u0935\u093f\u092e\u093e\u0928\u0915\u094d\u0937\u0947\u0924\u094d\u0930"
    ],
    "name:mar_x_preferred":[
        "\u091d\u0930\u0938\u0941\u0917\u0941\u0921\u093e \u0935\u093f\u092e\u093e\u0928\u0924\u0933"
    ],
    "name:msa_x_preferred":[
        "Lapangan Terbang Jharsuguda"
    ],
    "name:ori_x_preferred":[
        "\u0b1d\u0b3e\u0b30\u0b38\u0b41\u0b17\u0b41\u0b21\u0b3c\u0b3e \u0b2c\u0b3f\u0b2e\u0b3e\u0b28 \u0b2c\u0b28\u0b4d\u0b26\u0b30"
    ],
    "name:ron_x_preferred":[
        "Aeroportul Jharsuguda"
    ],
    "name:sat_x_preferred":[
        "\u1c61\u1c77\u1c5f\u1c68\u1c65\u1c69\u1c5c\u1c69\u1c70\u1c5f \u1c69\u1c70\u1c5f\u1c79\u1c71 \u1c70\u1c5f\u1c79\u1c66\u1c64"
    ],
    "name:swe_x_preferred":[
        "Jharsuguda Airport"
    ],
    "name:tgk_x_preferred":[
        "\u0424\u0443\u0440\u0443\u0434\u0433\u043e\u04b3\u0438 \u04b7\u04b3\u043e\u0440\u0441\u0443\u0433\u0443\u0434\u043e"
    ],
    "oa:elevation_ft":"751",
    "oa:type":"small_airport",
    "wd:wordcount":348,
    "woe:hierarchy":{
        "country_id":23424848,
        "county_id":12586611,
        "planet_id":1,
        "state_id":2345755
    },
    "wof:name":"Jharsuguda Airport",
    "wof:placetype":"campus"
},
  "geometry": {"coordinates":[84.05029999999999,21.9133],"type":"Point"}
}