{
  "type": "Feature",
  "properties": {
    "name:chi_x_preferred":[
        "\u74e6\u52aa\u79d1"
    ],
    "name:eng_x_preferred":[
        "Alf\u00e9rez FAP David Figueroa Fernandini Airport"
    ],
    "name:eng_x_variant":[
        "HUU",
        "SPNC"
    ],
    "name:fas_x_preferred":[
        "\u0641\u0631\u0648\u062f\u06af\u0627\u0647 \u0622\u0644\u0641\u0631\u0632 \u0627\u0641\u200c\u0627\u06cc\u200c\u067e\u06cc \u062f\u06cc\u0648\u06cc\u062f \u0641\u06cc\u06af\u0648\u0631\u0648\u0627 \u0641\u0631\u0646\u0627\u0646\u062f\u06cc\u0646\u06cc"
    ],
    "name:jpn_x_preferred":[
        "\u30a2\u30eb\u30d5\u30a7\u30ec\u30ba\u30fbFAP\u30fb\u30c0\u30d3\u30fb\u30d5\u30a3\u30b2\u30ed\u30fc\u30a2\u30fb\u30d5\u30a7\u30eb\u30ca\u30f3\u30c7\u30a3\u30fc\u30cb\u7a7a\u6e2f"
    ],
    "name:may_x_preferred":[
        "Lapangan Terbang Alferez David Figueroa Fernand"
    ],
    "name:msa_x_preferred":[
        "Lapangan Terbang Alferez David Figueroa Fernand"
    ],
    "name:per_x_preferred":[
        "\u0641\u0631\u0648\u062f\u06af\u0627\u0647 \u0622\u0644\u0641\u0631\u0632 \u0627\u0641\u200c\u0627\u06cc\u200c\u067e\u06cc \u062f\u06cc\u0648\u06cc\u062f \u0641\u06cc\u06af\u0648\u0631\u0648\u0627 \u0641\u0631\u0646\u0627\u0646\u062f\u06cc\u0646\u06cc"
    ],
    "name:pol_x_preferred":[
        "Port lotniczy Huanuco-Alf\u00e9rez FAP David Figueroa Fernandini"
    ],
    "name:que_x_preferred":[
        "David Figueroa Fernandini antanka panpa"
    ],
    "name:spa_x_preferred":[
        "Aeropuerto Alf. FAP David Figueroa Fernandini"
    ],
    "name:tgk_x_preferred":[
        "\u0424\u0443\u0440\u0443\u0434\u0433\u043e\u04b3\u0438 \u043e\u043b\u0444\u0440\u0437 \u0443\u0444\u200c\u0438\u0439\u200c\u043f\u0438\u0439 \u0434\u0438\u0439\u0432\u0435\u0434 \u0444\u0438\u0433\u0443\u0440\u0443\u043e \u0444\u0440\u043d\u043e\u043d\u0434\u0438\u043d\u0438"
    ],
    "name:vie_x_preferred":[
        "S\u00e2n bay Alf\u00e9rez FAP David Figueroa Fernandini"
    ],
    "oa:elevation_ft":"6070",
    "oa:type":"medium_airport",
    "woe:hierarchy":{
        "country_id":23424919,
        "county_id":26805856,
        "planet_id":1,
        "state_id":2346477
    },
    "wof:name":"Huanuco Airport",
    "wof:placetype":"campus"
},
  "geometry": {"coordinates":[-76.204803,-9.87881],"type":"Point"}
}