{
  "type": "Feature",
  "properties": {
    "name:eng_x_preferred":[
        "Monterey Park"
    ],
    "name:hbs_x_preferred":[
        "Monterej Park"
    ],
    "name:srp_x_preferred":[
        "\u041c\u043e\u043d\u0442\u0435\u0440\u0435\u0458 \u041f\u0430\u0440\u043a"
    ],
    "wd:wordcount":24,
    "wof:name":"Monterey Park",
    "wof:placetype":"neighbourhood"
},
  "geometry": {"coordinates":[-113.92938016333413,51.08199322588639],"type":"Point"}
}