{
  "type": "Feature",
  "properties": {
    "name:eng_x_preferred":[
        "Monterey Park"
    ],
    "name:fas_x_preferred":[
        "\u067e\u0627\u0631\u06a9 \u0645\u0648\u0646\u062a\u0631\u06cc"
    ],
    "name:hbs_x_preferred":[
        "Monterej Park"
    ],
    "name:ita_x_preferred":[
        "Monterey Park"
    ],
    "name:jpn_x_preferred":[
        "\u30e2\u30f3\u30c8\u30ec\u30fc\u30fb\u30d1\u30fc\u30af"
    ],
    "name:nld_x_preferred":[
        "Monterey Park"
    ],
    "name:srp_x_preferred":[
        "\u041c\u043e\u043d\u0442\u0435\u0440\u0435\u0458 \u041f\u0430\u0440\u043a"
    ],
    "wd:wordcount":24,
    "wof:name":"Monterey Park",
    "wof:placetype":"neighbourhood"
},
  "geometry": {"coordinates":[-113.92937999999999,51.081993],"type":"Point"}
}