{
  "type": "Feature",
  "properties": {
    "name:deu_x_preferred":[
        "Flughafen Hamilton"
    ],
    "name:eng_x_preferred":[
        "Hamilton International Airport"
    ],
    "name:eng_x_variant":[
        "HLZ",
        "NZHN"
    ],
    "name:fas_x_preferred":[
        "\u0641\u0631\u0648\u062f\u06af\u0627\u0647 \u0628\u06cc\u0646\u200c\u0627\u0644\u0645\u0644\u0644\u06cc \u0647\u0645\u06cc\u0644\u062a\u0648\u0646"
    ],
    "name:jpn_x_preferred":[
        "\u30cf\u30df\u30eb\u30c8\u30f3\u56fd\u969b\u7a7a\u6e2f"
    ],
    "name:kor_x_preferred":[
        "\ud574\ubc00\ud134 \uad6d\uc81c\uacf5\ud56d"
    ],
    "name:msa_x_preferred":[
        "Lapangan Terbang Hamilton"
    ],
    "name:pol_x_preferred":[
        "Port lotniczy Hamilton"
    ],
    "name:ron_x_preferred":[
        "Aeroportul Interna\u021bional Hamilton"
    ],
    "name:rus_x_preferred":[
        "\u0413\u0430\u043c\u0438\u043b\u044c\u0442\u043e\u043d"
    ],
    "name:tgk_x_preferred":[
        "\u0424\u0443\u0440\u0443\u0434\u0433\u043e\u04b3\u0438 \u0431\u0438\u043d\u200c\u0430\u043b\u043c\u0438\u043b\u0430\u043b\u04e3 \u04b3\u043c\u0438\u043b\u0442\u0443\u043d"
    ],
    "name:vie_x_preferred":[
        "S\u00e2n bay qu\u1ed1c t\u1ebf Hamilton"
    ],
    "name:zho_x_preferred":[
        "\u54c8\u5bc6\u5c14\u987f\u56fd\u9645\u673a\u573a"
    ],
    "oa:elevation_ft":"172",
    "oa:type":"medium_airport",
    "wd:wordcount":74,
    "woe:hierarchy":{
        "country_id":23424916,
        "county_id":55875913,
        "planet_id":1,
        "state_id":15021765
    },
    "wof:name":"Hamilton Airport",
    "wof:placetype":"campus"
},
  "geometry": {"coordinates":[175.33200099999999,-37.866699],"type":"Point"}
}