{
  "type": "Feature",
  "properties": {
    "name:ceb_x_preferred":[
        "London Oxford Airport"
    ],
    "name:deu_x_preferred":[
        "London Oxford Airport"
    ],
    "name:eng_x_preferred":[
        "London Oxford Airport"
    ],
    "name:eng_x_variant":[
        "OXF",
        "EGTK"
    ],
    "name:fas_x_preferred":[
        "\u0641\u0631\u0648\u062f\u06af\u0627\u0647 \u0622\u06a9\u0633\u0641\u0648\u0631\u062f \u0644\u0646\u062f\u0646"
    ],
    "name:fra_x_preferred":[
        "a\u00e9roport d'Oxford Kidlington"
    ],
    "name:jpn_x_preferred":[
        "\u30aa\u30c3\u30af\u30b9\u30d5\u30a9\u30fc\u30c9\u304f\u3046\u3046\u3053\u3046"
    ],
    "name:msa_x_preferred":[
        "Lapangan Terbang Kidlington"
    ],
    "name:nld_x_preferred":[
        "Oxford Airport"
    ],
    "name:pms_x_preferred":[
        "Oxford Airport"
    ],
    "name:pol_x_preferred":[
        "Port lotniczy Londyn-Oksford"
    ],
    "name:ron_x_preferred":[
        "Aeroportul London Oxford"
    ],
    "name:spa_x_preferred":[
        "Aeropuerto de Oxford"
    ],
    "name:swe_x_preferred":[
        "London Oxford Airport"
    ],
    "name:tgk_x_preferred":[
        "\u0424\u0443\u0440\u0443\u0434\u0433\u043e\u04b3\u0438 \u043e\u043a\u0441\u0444\u0443\u0440\u0434 \u043b\u043e\u043d\u0434\u0430\u043d"
    ],
    "name:zho_x_preferred":[
        "\u725b\u6d25\u6a5f\u5834"
    ],
    "oa:elevation_ft":"270",
    "oa:type":"medium_airport",
    "wd:wordcount":1651,
    "woe:hierarchy":{
        "country_id":23424975,
        "county_id":12602175,
        "localadmin_id":12696057,
        "planet_id":1,
        "state_id":24554868
    },
    "wof:name":"Oxford Airport",
    "wof:placetype":"campus"
},
  "geometry": {"coordinates":[-1.32,51.836899],"type":"Point"}
}