{
  "type": "Feature",
  "properties": {
    "name:ast_x_preferred":[
        "Aeropuertu Bananera"
    ],
    "name:eng_x_preferred":[
        "Bananera Airport"
    ],
    "name:jpn_x_preferred":[
        "\u30d0\u30ca\u30cd\u30e9\u7a7a\u6e2f"
    ],
    "name:msa_x_preferred":[
        "Lapangan Terbang Bananera"
    ],
    "name:ron_x_preferred":[
        "Aeroportul Bananera"
    ],
    "name:spa_x_preferred":[
        "Aeropuerto Bananera"
    ],
    "oa:elevation_ft":"130",
    "oa:type":"small_airport",
    "wd:wordcount":30,
    "woe:hierarchy":{
        "country_id":23424834,
        "county_id":26807034,
        "planet_id":1,
        "state_id":2345560
    },
    "wof:name":"Bananera Airport",
    "wof:placetype":"campus"
},
  "geometry": {"coordinates":[-88.83722222,15.47333333],"type":"Point"}
}