{
  "type": "Feature",
  "properties": {
    "gn:admin1_code":"21.0",
    "gn:asciiname":"Mecklenburg",
    "gn:dem":1720,
    "gn:feature_class":"P",
    "gn:feature_code":"PPL",
    "gn:name":"Mecklenburg",
    "gn:population":0,
    "gn:timezone":"Africa/Windhoek",
    "name:als_x_preferred":[
        "Mecklenburg"
    ],
    "name:ara_x_preferred":[
        "\u0645\u0643\u0644\u0646\u0628\u0648\u0631\u063a"
    ],
    "name:bel_x_preferred":[
        "\u041c\u0435\u043a\u043b\u0435\u043d\u0431\u0443\u0440\u0433"
    ],
    "name:bre_x_preferred":[
        "Mecklenburg"
    ],
    "name:bul_x_preferred":[
        "\u041c\u0435\u043a\u043b\u0435\u043d\u0431\u0443\u0440\u0433"
    ],
    "name:ces_x_preferred":[
        "Meklenbursko"
    ],
    "name:dan_x_preferred":[
        "Mecklenburg"
    ],
    "name:deu_x_preferred":[
        "Mecklenburg"
    ],
    "name:dsb_x_preferred":[
        "Mecklenburgska"
    ],
    "name:epo_x_preferred":[
        "Meklenburgo"
    ],
    "name:est_x_preferred":[
        "Mecklenburg"
    ],
    "name:fin_x_preferred":[
        "Mecklenburg"
    ],
    "name:fra_x_preferred":[
        "Mecklembourg"
    ],
    "name:hrv_x_preferred":[
        "Mecklenburg"
    ],
    "name:hsb_x_preferred":[
        "Mecklenburgska"
    ],
    "name:hun_x_preferred":[
        "Mecklenburg"
    ],
    "name:hye_x_preferred":[
        "\u0544\u0565\u056f\u056c\u0565\u0576\u0562\u0578\u0582\u0580\u0563"
    ],
    "name:ind_x_preferred":[
        "Mecklenburg"
    ],
    "name:ita_x_preferred":[
        "Meclemburgo"
    ],
    "name:jpn_x_preferred":[
        "\u30e1\u30af\u30ec\u30f3\u30d6\u30eb\u30af"
    ],
    "name:kat_x_preferred":[
        "\u10db\u10d4\u10d9\u10da\u10d4\u10dc\u10d1\u10e3\u10e0\u10d2\u10d8"
    ],
    "name:kor_x_preferred":[
        "\uba54\ud074\ub80c\ubd80\ub974\ud06c"
    ],
    "name:lat_x_preferred":[
        "Megapolis"
    ],
    "name:lit_x_preferred":[
        "Meklenburgas"
    ],
    "name:mkd_x_preferred":[
        "\u041c\u0435\u043a\u043b\u0435\u043d\u0431\u0443\u0440\u0433"
    ],
    "name:nds_x_preferred":[
        "Mekelnborg"
    ],
    "name:nld_x_preferred":[
        "Mecklenburg"
    ],
    "name:nno_x_preferred":[
        "Mecklenburg"
    ],
    "name:nor_x_preferred":[
        "Mecklenburg"
    ],
    "name:pol_x_preferred":[
        "Meklemburgia"
    ],
    "name:por_x_preferred":[
        "Mecklemburgo"
    ],
    "name:ron_x_preferred":[
        "Mecklenburg"
    ],
    "name:rus_x_preferred":[
        "\u041c\u0435\u043a\u043b\u0435\u043d\u0431\u0443\u0440\u0433"
    ],
    "name:sco_x_preferred":[
        "Mecklenburg"
    ],
    "name:spa_x_preferred":[
        "Mecklemburgo"
    ],
    "name:srp_x_preferred":[
        "\u041c\u0435\u043a\u043b\u0435\u043d\u0431\u0443\u0440\u0433"
    ],
    "name:swa_x_preferred":[
        "Mecklenburg"
    ],
    "name:swe_x_preferred":[
        "Mecklenburg"
    ],
    "name:tur_x_preferred":[
        "Mecklenburg"
    ],
    "name:ukr_x_preferred":[
        "\u041c\u0435\u043a\u043b\u0435\u043d\u0431\u0443\u0440\u0433"
    ],
    "name:zho_x_preferred":[
        "\u6885\u514b\u4f26\u5821"
    ],
    "wof:name":"Mecklenburg",
    "wof:placetype":"locality"
},
  "geometry": {"coordinates":[17.65,-22.16667],"type":"Point"}
}