{
  "type": "Feature",
  "properties": {
    "gn:admin1_code":"21.0",
    "gn:asciiname":"Mecklenburg",
    "gn:dem":1720,
    "gn:feature_class":"P",
    "gn:feature_code":"PPL",
    "gn:name":"Mecklenburg",
    "gn:population":0,
    "gn:timezone":"Africa/Windhoek",
    "wof:name":"Mecklenburg",
    "wof:placetype":"locality"
},
  "geometry": {"coordinates":[17.65,-22.16667],"type":"Point"}
}