{
  "type": "Feature",
  "properties": {
    "name:eng_x_variant":[
        "GGI"
    ],
    "oa:elevation_ft":"1008",
    "oa:type":"small_airport",
    "woe:hierarchy":{
        "country_id":23424977,
        "county_id":12588350,
        "planet_id":1,
        "state_id":2347574
    },
    "wof:name":"Grinnell Regional Airport",
    "wof:placetype":"campus"
},
  "geometry": {"coordinates":[-92.73583333000001,41.70972222],"type":"Point"}
}