{
  "type": "Feature",
  "properties": {
    "name:ceb_x_preferred":[
        "Grinnell Regional Airport"
    ],
    "name:eng_x_preferred":[
        "Grinnell Regional Airport"
    ],
    "name:eng_x_variant":[
        "GGI",
        "KGGI"
    ],
    "name:ron_x_preferred":[
        "Aeroportul Regional Grinnell"
    ],
    "name:urd_x_preferred":[
        "\u06af\u0631\u06cc\u0646\u06cc\u0644 \u0631\u06cc\u062c\u0646\u0644 \u06c1\u0648\u0627\u0626\u06cc \u0627\u0688\u0627"
    ],
    "oa:elevation_ft":"1008",
    "oa:type":"small_airport",
    "woe:hierarchy":{
        "country_id":23424977,
        "county_id":12588350,
        "planet_id":1,
        "state_id":2347574
    },
    "wof:name":"Grinnell Regional Airport",
    "wof:placetype":"campus"
},
  "geometry": {"coordinates":[-92.735833,41.709722],"type":"Point"}
}