{
  "type": "Feature",
  "properties": {
    "name:eng_x_preferred":[
        "Ranong Airport"
    ],
    "name:eng_x_variant":[
        "UNN",
        "VTSR"
    ],
    "name:fas_x_preferred":[
        "\u0641\u0631\u0648\u062f\u06af\u0627\u0647 \u0631\u0627\u0646\u0648\u0646\u06af"
    ],
    "name:ind_x_preferred":[
        "Bandar Udara Ranong"
    ],
    "name:jpn_x_preferred":[
        "\u30e9\u30ce\u30fc\u30f3\u7a7a\u6e2f"
    ],
    "name:msa_x_preferred":[
        "Lapangan Terbang Ranong"
    ],
    "name:pol_x_preferred":[
        "Port lotniczy Ranong"
    ],
    "name:tgk_x_preferred":[
        "\u0424\u0443\u0440\u0443\u0434\u0433\u043e\u04b3\u0438 \u0440\u043e\u043d\u0443\u043d\u0433"
    ],
    "name:tha_x_preferred":[
        "\u0e17\u0e48\u0e32\u0e2d\u0e32\u0e01\u0e32\u0e28\u0e22\u0e32\u0e19\u0e23\u0e30\u0e19\u0e2d\u0e07"
    ],
    "name:zho_x_preferred":[
        "\u62c9\u5eca\u6a5f\u5834"
    ],
    "oa:elevation_ft":"57",
    "oa:type":"medium_airport",
    "wd:wordcount":44,
    "woe:hierarchy":{
        "country_id":23424960,
        "county_id":28341585,
        "planet_id":1,
        "state_id":2347183
    },
    "wof:name":"Ranong Airport",
    "wof:placetype":"campus"
},
  "geometry": {"coordinates":[98.585503,9.77762],"type":"Point"}
}