{
  "type": "Feature",
  "properties": {
    "name:ara_x_preferred":[
        "\u0645\u0637\u0627\u0631 \u0639\u0628\u062f \u0627\u0644\u0644\u0647 \u064a\u0648\u0633\u0641"
    ],
    "name:eng_x_preferred":[
        "Abdullahi Yusuf International Airport"
    ],
    "name:eng_x_variant":[
        "GLK",
        "HCMR"
    ],
    "name:fas_x_preferred":[
        "\u0641\u0631\u0648\u062f\u06af\u0627\u0647 \u06af\u0627\u0644\u06a9\u0627\u06cc\u0648"
    ],
    "name:fra_x_preferred":[
        "a\u00e9roport international Abdullahi-Yusuf"
    ],
    "name:heb_x_preferred":[
        "\u05e0\u05de\u05dc \u05d4\u05ea\u05e2\u05d5\u05e4\u05d4 \u05e2\u05d1\u05d3\u05d5\u05dc\u05d0\u05d4\u05d9 \u05d9\u05d5\u05e1\u05d5\u05e3"
    ],
    "name:ind_x_preferred":[
        "Bandar Udara Internasional Abdullahi Yusuf"
    ],
    "name:ita_x_preferred":[
        "Aeroporto di Gallacaio"
    ],
    "name:jpn_x_preferred":[
        "\u30ac\u30eb\u30ab\u30a4\u30aa"
    ],
    "name:msa_x_preferred":[
        "Lapangan Terbang Galcaio"
    ],
    "name:nld_x_preferred":[
        "Abdullahi Yusuf International Airport"
    ],
    "name:pol_x_preferred":[
        "Port lotniczy Gaalkacyo"
    ],
    "name:ron_x_preferred":[
        "Aeroportul Interna\u021bional Abdullahi Yusuf"
    ],
    "name:som_x_preferred":[
        "Gegada diyaaradaha Cabdullahi Yuusuf"
    ],
    "name:tgk_x_preferred":[
        "\u0424\u0443\u0440\u0443\u0434\u0433\u043e\u04b3\u0438 \u0433\u043e\u043b\u043a\u043e\u044e"
    ],
    "name:zho_x_preferred":[
        "\u963f\u535c\u675c\u62c9\u5e0c\u00b7\u512a\u7d20\u798f\u570b\u969b\u6a5f\u5834"
    ],
    "oa:elevation_ft":"975",
    "oa:type":"small_airport",
    "woe:hierarchy":{
        "country_id":23424949,
        "planet_id":1,
        "state_id":2347015
    },
    "wof:name":"Galcaio Airport",
    "wof:placetype":"campus"
},
  "geometry": {"coordinates":[47.4547,6.78083],"type":"Point"}
}