{
  "type": "Feature",
  "properties": {
    "name:ceb_x_preferred":[
        "Guillermo Le\u00f3n Valencia Airport"
    ],
    "name:cym_x_preferred":[
        "Maes Awyr Guillermo Le\u00f3n Valencia"
    ],
    "name:eng_x_preferred":[
        "Guillermo Le\u00f3n Valencia Airport"
    ],
    "name:eng_x_variant":[
        "PPN",
        "SKPP"
    ],
    "name:fas_x_preferred":[
        "\u0641\u0631\u0648\u062f\u06af\u0627\u0647 \u06af\u0648\u06cc\u06cc\u200c\u0644\u0631\u0645\u0648 \u0644\u06cc\u0648\u0646 \u0648\u0627\u0644\u0646\u0633\u06cc\u0627"
    ],
    "name:jpn_x_preferred":[
        "\u30ae\u30b8\u30a7\u30eb\u30e2\u30fb\u30ec\u30aa\u30f3\u30fb\u30d0\u30ec\u30f3\u30b7\u30a2\u7a7a\u6e2f"
    ],
    "name:msa_x_preferred":[
        "Lapangan Terbang Guillermo Leon Valencia"
    ],
    "name:pol_x_preferred":[
        "Port lotniczy Guillermo Le\u00f3n Valencia"
    ],
    "name:por_x_preferred":[
        "Aeroporto Guillermo Le\u00f3n Valencia"
    ],
    "name:ron_x_preferred":[
        "Aeroportul Guillermo Le\u00f3n Valencia"
    ],
    "name:rus_x_preferred":[
        "\u041f\u043e\u043f\u0430\u044f\u043d"
    ],
    "name:rus_x_variant":[
        "\u0410\u044d\u0440\u043e\u043f\u043e\u0440\u0442 \u0438\u043c\u0435\u043d\u0438 \u0413\u0438\u043b\u044c\u0435\u0440\u043c\u043e \u041b\u0435\u043e\u043d\u0430 \u0412\u0430\u043b\u0435\u043d\u0441\u0438\u0438"
    ],
    "name:spa_x_preferred":[
        "Aeropuerto Guillermo Le\u00f3n Valencia"
    ],
    "name:swe_x_preferred":[
        "Guillermo Le\u00f3n Valencia Airport"
    ],
    "name:tgk_x_preferred":[
        "\u0424\u0443\u0440\u0443\u0434\u0433\u043e\u04b3\u0438 \u0433\u0444\u0442\u043d\u043d\u200c\u043b\u0440\u043c\u0443 \u043b\u0435\u044e\u043d \u0432\u043e\u043b\u0438\u043d\u0441\u0435\u0451"
    ],
    "name:vie_x_preferred":[
        "S\u00e2n bay Guillermo Le\u00f3n Valencia"
    ],
    "oa:elevation_ft":"5687",
    "oa:type":"medium_airport",
    "wd:wordcount":64,
    "woe:hierarchy":{
        "country_id":23424787,
        "county_id":26796961,
        "planet_id":1,
        "state_id":2345055
    },
    "wof:name":"Guillermo Leon Valencia Airport",
    "wof:placetype":"campus"
},
  "geometry": {"coordinates":[-76.6093,2.4544],"type":"Point"}
}