{
  "type": "Feature",
  "properties": {
    "gn:admin1_code":"39.0",
    "gn:asciiname":"Twyfelspoort",
    "gn:dem":1197,
    "gn:feature_class":"P",
    "gn:feature_code":"PPL",
    "gn:name":"Twyfelspoort",
    "gn:population":0,
    "gn:timezone":"Africa/Windhoek",
    "wof:name":"Twyfelspoort",
    "wof:placetype":"locality"
},
  "geometry": {"coordinates":[18.73333,-18.88333],"type":"Point"}
}