{
  "type": "Feature",
  "properties": {
    "name:eng_x_preferred":[
        "Upata Airport"
    ],
    "name:msa_x_preferred":[
        "Lapangan Terbang Upata"
    ],
    "name:ron_x_preferred":[
        "Aeroportul Upata"
    ],
    "oa:elevation_ft":"1056",
    "oa:type":"small_airport",
    "woe:hierarchy":{
        "country_id":23424982,
        "county_id":26804699,
        "localadmin_id":26805590,
        "planet_id":1,
        "state_id":2347682
    },
    "wof:name":"Upata Airport",
    "wof:placetype":"campus"
},
  "geometry": {"coordinates":[-62.328787,7.979105],"type":"Point"}
}