{
  "type": "Feature",
  "properties": {
    "name:eng_x_preferred":[
        "Naval Air Station Lemoore"
    ],
    "name:eng_x_variant":[
        "NLC",
        "KNLC"
    ],
    "name:fas_x_preferred":[
        "\u067e\u0627\u06cc\u06af\u0627\u0647 \u0647\u0648\u0627\u06cc\u06cc \u0644\u0645\u0648\u0631"
    ],
    "name:fra_x_preferred":[
        "Naval Air Station Lemoore"
    ],
    "name:swe_x_preferred":[
        "Naval Air Station Lemoore"
    ],
    "name:tgk_x_preferred":[
        "\u041f\u043e\u0439\u0433\u043e\u04b3\u0438 \u04b3\u0430\u0432\u043e\u0438\u0438 \u041b\u0435\u043c\u0443\u0440"
    ],
    "name:tgk_x_variant":[
        "\u041f\u043e\u0439\u0433\u043e\u04b3\u0438 \u04b3\u0430\u0432\u043e\u04e3 \u043b\u043c\u0443\u0440"
    ],
    "name:urd_x_preferred":[
        "\u0646\u06cc\u0648\u0644 \u0627\u06cc\u0626\u0631\u0627\u0633\u0679\u06cc\u0634\u0646 \u0644\u06cc\u0645\u0648\u0631"
    ],
    "oa:elevation_ft":"232",
    "oa:type":"medium_airport",
    "wd:wordcount":779,
    "woe:hierarchy":{
        "country_id":23424977,
        "county_id":12587685,
        "planet_id":1,
        "state_id":2347563
    },
    "wof:name":"Lemoore Naval Air Station",
    "wof:placetype":"campus"
},
  "geometry": {"coordinates":[-119.951944,36.333056],"type":"Point"}
}