{
  "type": "Feature",
  "properties": {
    "name:fas_x_preferred":[
        "\u067e\u0627\u06cc\u06af\u0627\u0647 \u0647\u0648\u0627\u06cc\u06cc \u0644\u0645\u0648\u0631"
    ],
    "name:tgk_x_preferred":[
        "\u041f\u043e\u0439\u0433\u043e\u04b3\u0438 \u04b3\u0430\u0432\u043e\u0438\u0438 \u041b\u0435\u043c\u0443\u0440"
    ],
    "oa:elevation_ft":"232",
    "oa:type":"medium_airport",
    "wd:wordcount":779,
    "woe:hierarchy":{
        "country_id":23424977,
        "county_id":12587685,
        "planet_id":1,
        "state_id":2347563
    },
    "wof:name":"Lemoore Naval Air Station",
    "wof:placetype":"campus"
},
  "geometry": {"coordinates":[-119.95194444444,36.333055555556],"type":"Point"}
}