{
  "type": "Feature",
  "properties": {
    "name:eng_x_preferred":[
        "Victoria Inner Harbour Airport"
    ],
    "name:eng_x_variant":[
        "YWH",
        "CYWH"
    ],
    "name:fas_x_preferred":[
        "\u0641\u0631\u0648\u062f\u06af\u0627\u0647 \u0648\u06cc\u06a9\u062a\u0648\u0631\u06cc\u0627 \u0627\u06cc\u0646\u0631 \u0647\u0627\u0631\u0628\u0631"
    ],
    "name:fra_x_preferred":[
        "A\u00e9roport du Port de Victoria"
    ],
    "name:jpn_x_preferred":[
        "\u30d3\u30af\u30c8\u30ea\u30a2\u30fb\u30cf\u30fc\u30d0\u30fc\u7a7a\u6e2f"
    ],
    "name:pms_x_preferred":[
        "Victoria Harbour Water Aerodrome"
    ],
    "name:ron_x_preferred":[
        "Aeroportul Victoria Inner Harbour"
    ],
    "name:tgk_x_preferred":[
        "\u0424\u0443\u0440\u0443\u0434\u0433\u043e\u04b3\u0438 \u0432\u0435\u043a\u0442\u0443\u0440\u0435\u0451 \u043e\u0438\u043d\u0440 \u04b3\u043e\u0440\u0431\u0440"
    ],
    "name:zho_x_preferred":[
        "\u57df\u591a\u5229\u5185\u6e2f\u6a5f\u5834"
    ],
    "oa:type":"seaplane_base",
    "wd:wordcount":179,
    "woe:hierarchy":{
        "country_id":23424775,
        "county_id":29375230,
        "planet_id":1,
        "state_id":20069920
    },
    "wof:name":"Inner Harbour Airport",
    "wof:placetype":"campus"
},
  "geometry": {"coordinates":[-123.388867,48.424986],"type":"Point"}
}