{
  "type": "Feature",
  "properties": {
    "name:eng_x_preferred":[
        "East Houston"
    ],
    "name:fra_x_preferred":[
        "East Houston"
    ],
    "name:nld_x_preferred":[
        "East Houston"
    ],
    "wof:name":"East Houston",
    "wof:placetype":"neighbourhood"
},
  "geometry": {"coordinates":[-95.25872099999999,29.839494],"type":"Point"}
}