{
  "type": "Feature",
  "properties": {
    "wof:name":"Laie",
    "wof:placetype":"neighbourhood"
},
  "geometry": {"coordinates":[-157.9243321389167,21.64680934112871],"type":"Point"}
}