{
  "type": "Feature",
  "properties": {
    "name:ceb_x_preferred":[
        "Bethlehem"
    ],
    "name:eng_x_preferred":[
        "Bethlehem Airport"
    ],
    "name:fas_x_preferred":[
        "\u0641\u0631\u0648\u062f\u06af\u0627\u0647 \u0628\u06cc\u062a\u200c\u0644\u062d\u0645"
    ],
    "name:jpn_x_preferred":[
        "\u30d9\u30c4\u30ec\u30d8\u30e0\u7a7a\u6e2f"
    ],
    "name:msa_x_preferred":[
        "Lapangan Terbang Bethlehem"
    ],
    "name:ron_x_preferred":[
        "Aeroportul Bethlehem"
    ],
    "name:tgk_x_preferred":[
        "\u0424\u0443\u0440\u0443\u0434\u0433\u043e\u04b3\u0438 \u0411\u0435\u0442\u043b\u0435\u04b3\u0435\u043c"
    ],
    "name:tgk_x_variant":[
        "\u0424\u0443\u0440\u0443\u0434\u0433\u043e\u04b3\u0438 \u0431\u0438\u0439\u0442\u200c\u043b\u0445\u043c"
    ],
    "oa:elevation_ft":"5561",
    "oa:type":"small_airport",
    "wd:wordcount":124,
    "woe:hierarchy":{
        "country_id":23424942,
        "county_id":56189449,
        "localadmin_id":56189513,
        "planet_id":1,
        "state_id":2346980
    },
    "wof:name":"Bethlehem Airport",
    "wof:placetype":"campus"
},
  "geometry": {"coordinates":[28.33611111,-28.24861111],"type":"Point"}
}