{
  "type": "Feature",
  "properties": {
    "wof:name":"Sion",
    "wof:placetype":"neighbourhood"
},
  "geometry": {"coordinates":[72.86427594933116,19.04487145380225],"type":"Point"}
}