{
  "type": "Feature",
  "properties": {
    "name:als_x_preferred":[
        "Sion"
    ],
    "name:bre_x_preferred":[
        "Sion"
    ],
    "name:bul_x_preferred":[
        "\u0421\u0438\u043e\u043d"
    ],
    "name:cat_x_preferred":[
        "Sion"
    ],
    "name:ceb_x_preferred":[
        "Sion"
    ],
    "name:ces_x_preferred":[
        "Sion"
    ],
    "name:cym_x_preferred":[
        "Sion"
    ],
    "name:dan_x_preferred":[
        "Sion"
    ],
    "name:deu_x_preferred":[
        "Sion"
    ],
    "name:eus_x_preferred":[
        "Sion"
    ],
    "name:fin_x_preferred":[
        "Sion"
    ],
    "name:fra_x_preferred":[
        "Sion"
    ],
    "name:hin_x_preferred":[
        "\u0938\u0940\u0911\u0928"
    ],
    "name:hun_x_preferred":[
        "Sion"
    ],
    "name:ind_x_preferred":[
        "Sion"
    ],
    "name:ita_x_preferred":[
        "Sion"
    ],
    "name:jpn_x_preferred":[
        "\u30b7\u30aa\u30f3"
    ],
    "name:kor_x_preferred":[
        "\uc2dc\uc628"
    ],
    "name:lat_x_preferred":[
        "Sion"
    ],
    "name:lit_x_preferred":[
        "Sionas"
    ],
    "name:nld_x_preferred":[
        "Sion"
    ],
    "name:nor_x_preferred":[
        "Sion"
    ],
    "name:pms_x_preferred":[
        "Sion"
    ],
    "name:por_x_preferred":[
        "Sion"
    ],
    "name:ron_x_preferred":[
        "Sion"
    ],
    "name:rus_x_preferred":[
        "\u0421\u0438\u043e\u043d"
    ],
    "name:slk_x_preferred":[
        "Sion"
    ],
    "name:spa_x_preferred":[
        "Sion"
    ],
    "name:swe_x_preferred":[
        "Sion"
    ],
    "wof:name":"Sion",
    "wof:placetype":"neighbourhood"
},
  "geometry": {"coordinates":[72.864276,19.044871],"type":"Point"}
}