{
  "type": "Feature",
  "properties": {
    "wof:name":"Point Cook",
    "wof:placetype":"neighbourhood"
},
  "geometry": {"coordinates":[144.75126694036067,-37.90470491282388],"type":"Point"}
}