{
  "type": "Feature",
  "properties": {
    "gn:admin1_code":"39.0",
    "gn:asciiname":"Fairview",
    "gn:dem":1187,
    "gn:feature_class":"P",
    "gn:feature_code":"PPL",
    "gn:name":"Fairview",
    "gn:population":0,
    "gn:timezone":"Africa/Windhoek",
    "wof:name":"Fairview",
    "wof:placetype":"locality"
},
  "geometry": {"coordinates":[18.26667,-18.93333],"type":"Point"}
}