{
  "type": "Feature",
  "properties": {
    "name:deu_x_preferred":[
        "Flughafen Mytilini"
    ],
    "name:ell_x_preferred":[
        "\u039a\u03c1\u03b1\u03c4\u03b9\u03ba\u03cc\u03c2 \u0391\u03b5\u03c1\u03bf\u03bb\u03b9\u03bc\u03ad\u03bd\u03b1\u03c2 \u039c\u03c5\u03c4\u03b9\u03bb\u03ae\u03bd\u03b7\u03c2 \"\u039f\u03b4\u03c5\u03c3\u03c3\u03ad\u03b1\u03c2 \u0395\u03bb\u03cd\u03c4\u03b7\u03c2\""
    ],
    "name:eng_x_preferred":[
        "Mytilene International Airport"
    ],
    "name:eng_x_variant":[
        "MJT",
        "LGMT"
    ],
    "name:fas_x_preferred":[
        "\u0641\u0631\u0648\u062f\u06af\u0627\u0647 \u0628\u06cc\u0646\u200c\u0627\u0644\u0645\u0644\u0644\u06cc \u0645\u06cc\u062a\u06cc\u0644\u0646"
    ],
    "name:fin_x_preferred":[
        "Mytil\u00ednin kansainv\u00e4linen lentoasema"
    ],
    "name:fra_x_preferred":[
        "a\u00e9roport international de Mytil\u00e8ne"
    ],
    "name:ind_x_preferred":[
        "Bandar Udara Internasional Mytilene"
    ],
    "name:jpn_x_preferred":[
        "\u30df\u30c6\u30a3\u30ea\u30fc\u30cb\u56fd\u969b\u7a7a\u6e2f"
    ],
    "name:msa_x_preferred":[
        "Lapangan Terbang Odysseas Elytis"
    ],
    "name:nld_x_preferred":[
        "Luchthaven Mytilini"
    ],
    "name:nob_x_preferred":[
        "Mytilene internasjonale lufthavn"
    ],
    "name:pol_x_preferred":[
        "Port lotniczy Mitylena"
    ],
    "name:rus_x_preferred":[
        "\u041e\u0434\u0438\u0441\u0441\u0435\u0430\u0441 \u042d\u043b\u0438\u0442\u0438\u0441"
    ],
    "name:swe_x_preferred":[
        "Mytilini Airport"
    ],
    "name:tgk_x_preferred":[
        "\u0424\u0443\u0440\u0443\u0434\u0433\u043e\u04b3\u0438 \u0448\u0430\u04b3\u0440\u0438\u0441\u0442\u043e\u043d \u043c\u043e\u0432\u043d\u0442 \u043e\u0441\u0442\u0440\u043b\u0438\u043d\u0433\u2013\u043c\u0443\u043d\u0442\u0433\u0443\u043c\u0440\u0438"
    ],
    "name:ukr_x_preferred":[
        "\u041c\u0456\u0436\u043d\u0430\u0440\u043e\u0434\u043d\u0438\u0439 \u0430\u0435\u0440\u043e\u043f\u043e\u0440\u0442 \u041c\u0456\u0442\u0456\u043b\u0456\u043d\u0456"
    ],
    "name:vie_x_preferred":[
        "S\u00e2n bay qu\u1ed1c t\u1ebf Mytilene"
    ],
    "name:zho_x_preferred":[
        "\u7c73\u8482\u5229\u5c3c"
    ],
    "oa:elevation_ft":"60",
    "oa:type":"medium_airport",
    "woe:hierarchy":{
        "country_id":23424833,
        "county_id":12591133,
        "localadmin_id":24544210,
        "planet_id":1,
        "state_id":12577890
    },
    "wof:name":"Mitilini Airport",
    "wof:placetype":"campus"
},
  "geometry": {"coordinates":[26.598301,39.056702],"type":"Point"}
}