{
  "type": "Feature",
  "properties": {
    "name:eng_x_variant":[
        "ULL",
        "GB-ULL"
    ],
    "oa:elevation_ft":"15",
    "oa:type":"small_airport",
    "woe:hierarchy":{
        "country_id":23424975,
        "county_id":12602207,
        "localadmin_id":12696185,
        "planet_id":1,
        "state_id":12578048
    },
    "wof:name":"Mull Airport",
    "wof:placetype":"campus"
},
  "geometry": {"coordinates":[-5.91417,56.517502],"type":"Point"}
}