{
  "type": "Feature",
  "properties": {
    "name:ast_x_preferred":[
        "Aeropuertu Internacional Ernesto Cortissoz"
    ],
    "name:cym_x_preferred":[
        "Maes Awyr Rhyngwladol Ernesto Cortissoz"
    ],
    "name:deu_x_preferred":[
        "Flughafen Barranquilla"
    ],
    "name:eng_x_preferred":[
        "Ernesto Cortissoz International Airport"
    ],
    "name:eng_x_variant":[
        "BAQ",
        "SKBQ"
    ],
    "name:fas_x_preferred":[
        "\u0641\u0631\u0648\u062f\u06af\u0627\u0647 \u0628\u06cc\u0646\u200c\u0627\u0644\u0645\u0644\u0644\u06cc \u0627\u0631\u0646\u0633\u062a\u0648 \u06a9\u0648\u0631\u062a\u06cc\u0633\u0648\u0632"
    ],
    "name:fra_x_preferred":[
        "a\u00e9roport international Ernesto Cortissoz"
    ],
    "name:ind_x_preferred":[
        "Bandar Udara Internasional Ernesto Cortissoz"
    ],
    "name:ita_x_preferred":[
        "Aeroporto di Barranquilla-Ernesto Cortissoz"
    ],
    "name:jpn_x_preferred":[
        "\u30d0\u30e9\u30f3\u30ad\u30fc\u30b8\u30e3"
    ],
    "name:jpn_x_variant":[
        "\u30a8\u30eb\u30cd\u30b9\u30c8\u30fb\u30b3\u30eb\u30c6\u30a3\u30bd\u30b9\u56fd\u969b\u7a7a\u6e2f"
    ],
    "name:msa_x_preferred":[
        "Lapangan Terbang Ernesto Cortissoz"
    ],
    "name:nld_x_preferred":[
        "Ernesto Cortissoz International Airport"
    ],
    "name:pol_x_preferred":[
        "Port lotniczy Ernesto Cortissoz"
    ],
    "name:por_x_preferred":[
        "Aeroporto Internacional Ernesto Cortissoz"
    ],
    "name:ron_x_preferred":[
        "Aeroportul Interna\u021bional Ernesto Cortissoz"
    ],
    "name:rus_x_preferred":[
        "\u0411\u0430\u0440\u0440\u0430\u043d\u043a\u0438\u043b\u044c\u044f"
    ],
    "name:spa_x_preferred":[
        "Aeropuerto Internacional Ernesto Cortissoz"
    ],
    "name:swe_x_preferred":[
        "Ernesto Cortissoz International Airport"
    ],
    "name:tgk_x_preferred":[
        "\u0424\u0443\u0440\u0443\u0434\u0433\u043e\u04b3\u0438 \u0431\u0438\u043d\u200c\u0430\u043b\u043c\u0438\u043b\u0430\u043b\u04e3 \u043e\u0440\u043d\u0441\u0442\u0443 \u043a\u0443\u0440\u0442\u0438\u0441\u0443\u0437"
    ],
    "name:ukr_x_preferred":[
        "\u041c\u0456\u0436\u043d\u0430\u0440\u043e\u0434\u043d\u0438\u0439 \u0430\u0435\u0440\u043e\u043f\u043e\u0440\u0442 \u0415\u0440\u043d\u0435\u0441\u0442\u043e \u041a\u043e\u0440\u0442\u0456\u0441\u0441\u043e\u0441"
    ],
    "name:vie_x_preferred":[
        "S\u00e2n bay qu\u1ed1c t\u1ebf Ernesto Cortissoz"
    ],
    "name:zho_x_preferred":[
        "Ernesto Cortissoz\u570b\u969b\u6a5f\u5834"
    ],
    "oa:elevation_ft":"98",
    "oa:type":"medium_airport",
    "woe:hierarchy":{
        "country_id":23424787,
        "county_id":26796750,
        "planet_id":1,
        "state_id":2345050
    },
    "wof:name":"Ernesto Cortissoz Airport",
    "wof:placetype":"campus"
},
  "geometry": {"coordinates":[-74.7808,10.8896],"type":"Point"}
}