{
  "type": "Feature",
  "properties": {
    "name:deu_x_preferred":[
        "Flughafen Santa Cruz Do Sul"
    ],
    "name:eng_x_preferred":[
        "Santa Cruz do Sul Airport"
    ],
    "name:eng_x_variant":[
        "CSU",
        "SSSC"
    ],
    "name:msa_x_preferred":[
        "Lapangan Terbang Santa Cruz Do Sul"
    ],
    "name:por_x_preferred":[
        "Aeroporto de Santa Cruz do Sul"
    ],
    "name:swe_x_preferred":[
        "Santa Cruz do Sul Airport"
    ],
    "oa:elevation_ft":"646",
    "oa:type":"small_airport",
    "woe:hierarchy":{
        "country_id":23424768,
        "county_id":12581473,
        "planet_id":1,
        "state_id":2344864
    },
    "wof:name":"Aeroporto Santa Cruz do Sul",
    "wof:placetype":"campus"
},
  "geometry": {"coordinates":[-52.412201,-29.684099],"type":"Point"}
}