{
  "type": "Feature",
  "properties": {
    "name:ara_x_preferred":[
        "\u0645\u0637\u0627\u0631 \u0631\u0623\u0633 \u062a\u0646\u0627\u062c\u064a\u0628"
    ],
    "name:ceb_x_preferred":[
        "Tanajib Airport"
    ],
    "name:eng_x_preferred":[
        "Tanajib Airport"
    ],
    "name:fas_x_preferred":[
        "\u0641\u0631\u0648\u062f\u06af\u0627\u0647 \u062a\u0646\u0627\u062c\u06cc\u0628"
    ],
    "name:fra_x_preferred":[
        "A\u00e9roport de Tanajib"
    ],
    "name:jpn_x_preferred":[
        "\u30bf\u30ca\u30b8\u30d6\u7a7a\u6e2f"
    ],
    "name:msa_x_preferred":[
        "Lapangan Terbang Ras Tanajib"
    ],
    "name:ron_x_preferred":[
        "Aeroportul Tanajib"
    ],
    "name:tgk_x_preferred":[
        "\u0424\u0443\u0440\u0443\u0434\u0433\u043e\u04b3\u0438 \u0442\u043e\u043d\u043e\u04b7\u0438\u0431"
    ],
    "name:urd_x_preferred":[
        "\u0631\u0627\u0633 \u062a\u0646\u0627\u062c\u06cc\u0628 \u06c1\u0648\u0627\u0626\u06cc \u0627\u0688\u0627"
    ],
    "oa:elevation_ft":"30",
    "oa:type":"medium_airport",
    "wd:wordcount":130,
    "woe:hierarchy":{
        "country_id":23424938,
        "county_id":56120137,
        "planet_id":1,
        "state_id":2346954
    },
    "wof:name":"Tanajib Airport",
    "wof:placetype":"campus"
},
  "geometry": {"coordinates":[48.769111111111,27.867805555556],"type":"Point"}
}