{
  "type": "Feature",
  "properties": {
    "name:deu_x_preferred":[
        "Flughafen Magadan"
    ],
    "name:eng_x_preferred":[
        "Sokol Airport"
    ],
    "name:eng_x_variant":[
        "GDX",
        "UHMM"
    ],
    "name:fas_x_preferred":[
        "\u0641\u0631\u0648\u062f\u06af\u0627\u0647 \u0633\u0648\u06a9\u0648\u0644"
    ],
    "name:fin_x_preferred":[
        "Sokolin lentoasema"
    ],
    "name:ind_x_preferred":[
        "Bandar Udara Sokol"
    ],
    "name:ita_x_preferred":[
        "Aeroporto di Magadan-Sokol"
    ],
    "name:jpn_x_preferred":[
        "\u30bd\u30b3\u30eb\u7a7a\u6e2f"
    ],
    "name:kat_x_preferred":[
        "\u10e1\u10dd\u10d9\u10dd\u10da\u10d8\u10e1 \u10d0\u10d4\u10e0\u10dd\u10de\u10dd\u10e0\u10e2\u10d8"
    ],
    "name:kor_x_preferred":[
        "\uc18c\ucf54\uc774 \uacf5\ud56d"
    ],
    "name:msa_x_preferred":[
        "Lapangan Terbang Sokol"
    ],
    "name:nld_x_preferred":[
        "Luchthaven Sokol"
    ],
    "name:nno_x_preferred":[
        "Magadan lufthamn"
    ],
    "name:nob_x_preferred":[
        "Magadan lufthavn"
    ],
    "name:pol_x_preferred":[
        "Port lotniczy Magadan"
    ],
    "name:rus_x_preferred":[
        "\u041c\u0430\u0433\u0430\u0434\u0430\u043d"
    ],
    "name:spa_x_preferred":[
        "Aeropuerto Internacional de Magad\u00e1n-Sokol"
    ],
    "name:tgk_x_preferred":[
        "\u0424\u0443\u0440\u0443\u0434\u0433\u043e\u04b3\u0438 \u0441\u0443\u043a\u0443\u043b"
    ],
    "name:vie_x_preferred":[
        "S\u00e2n bay Sokol"
    ],
    "name:zho_x_preferred":[
        "\u7d22\u79d1\u723e\u6a5f\u5834"
    ],
    "oa:elevation_ft":"574",
    "oa:type":"medium_airport",
    "woe:hierarchy":{
        "country_id":23424936,
        "county_id":12598699,
        "planet_id":1,
        "state_id":20070512
    },
    "wof:name":"Magadan Northwest Airport",
    "wof:placetype":"campus"
},
  "geometry": {"coordinates":[150.720001,59.910999],"type":"Point"}
}