{
  "type": "Feature",
  "properties": {
    "name:ceb_x_preferred":[
        "Miller Municipal Airport"
    ],
    "name:eng_x_preferred":[
        "Miller Municipal Airport"
    ],
    "name:jpn_x_preferred":[
        "Miller\u5e02\u55b6\u7a7a\u6e2f"
    ],
    "name:ron_x_preferred":[
        "Aeroportul Municipal Miller"
    ],
    "name:urd_x_preferred":[
        "\u0645\u0644\u0631 \u0645\u06cc\u0648\u0646\u0633\u067e\u0644 \u06c1\u0648\u0627\u0626\u06cc \u0627\u0688\u0627"
    ],
    "oa:elevation_ft":"1569",
    "oa:type":"small_airport",
    "wd:wordcount":331,
    "woe:hierarchy":{
        "country_id":23424977,
        "county_id":12589874,
        "planet_id":1,
        "state_id":2347600
    },
    "wof:name":"Miller Municipal Airport",
    "wof:placetype":"campus"
},
  "geometry": {"coordinates":[-98.9581,44.5253],"type":"Point"}
}