{
  "type": "Feature",
  "properties": {
    "name:deu_x_preferred":[
        "Grapeland Heights"
    ],
    "name:eng_x_preferred":[
        "Grapeland Heights"
    ],
    "name:fra_x_preferred":[
        "Grapeland Heights"
    ],
    "name:nld_x_preferred":[
        "Grapeland Heights"
    ],
    "wd:wordcount":282,
    "wof:name":"Grapeland Heights",
    "wof:placetype":"neighbourhood"
},
  "geometry": {"coordinates":[-80.25266259520956,25.79010958161212],"type":"Point"}
}