{
  "type": "Feature",
  "properties": {
    "name:ceb_x_preferred":[
        "Dolbeau-Saint-F\u00e9licien Airport"
    ],
    "name:eng_x_preferred":[
        "Dolbeau-Saint-F\u00e9licien Airport"
    ],
    "name:eng_x_variant":[
        "YDO",
        "CYDO"
    ],
    "name:fas_x_preferred":[
        "\u0641\u0631\u0648\u062f\u06af\u0627\u0647 \u062f\u0648\u0644\u0628\u0622-\u0633\u0646\u062a-\u0641\u0644\u0633\u06cc\u0646"
    ],
    "name:msa_x_preferred":[
        "Lapangan Terbang Dolbeau-St-Felicien"
    ],
    "name:pms_x_preferred":[
        "Dolbeau-St-F\u00e9licien Airport"
    ],
    "name:swe_x_preferred":[
        "Dolbeau-Saint-F\u00e9licien Airport"
    ],
    "name:tgk_x_preferred":[
        "\u0424\u0443\u0440\u0443\u0434\u0433\u043e\u04b3\u0438 \u0434\u0443\u043b\u0431\u043e-\u0441\u0443\u043d\u043d\u0430\u0442-\u0444\u043b\u0441\u0438\u043d"
    ],
    "oa:elevation_ft":"372",
    "oa:type":"medium_airport",
    "woe:hierarchy":{
        "country_id":23424775,
        "county_id":29375173,
        "planet_id":1,
        "state_id":2344924
    },
    "wof:name":"Dolbeau St Methode Airport",
    "wof:placetype":"campus"
},
  "geometry": {"coordinates":[-72.375,48.7785],"type":"Point"}
}