{
  "type": "Feature",
  "properties": {
    "wof:name":"South Acres/Crestmont Park",
    "wof:placetype":"neighbourhood"
},
  "geometry": {"coordinates":[-95.35572412111453,29.63235462443186],"type":"Point"}
}