{
  "type": "Feature",
  "properties": {
    "name:dan_x_preferred":[
        "L\u00e6s\u00f8 flyveplads"
    ],
    "name:deu_x_preferred":[
        "Flughafen L\u00e6s\u00f8"
    ],
    "name:eng_x_preferred":[
        "L\u00e6s\u00f8 Airport"
    ],
    "name:eng_x_variant":[
        "BYR",
        "EKLS"
    ],
    "name:fas_x_preferred":[
        "\u0641\u0631\u0648\u062f\u06af\u0627\u0647 \u0644\u0633\u0648"
    ],
    "name:ind_x_preferred":[
        "Bandar Udara L\u00e6s\u00f8"
    ],
    "name:jpn_x_preferred":[
        "\u30ec\u30b9\u7a7a\u6e2f"
    ],
    "name:msa_x_preferred":[
        "Lapangan Terbang Laeso"
    ],
    "name:nob_x_preferred":[
        "L\u00e6s\u00f8 flyplass"
    ],
    "name:pol_x_preferred":[
        "Port lotniczy L\u00e6s\u00f8"
    ],
    "name:ron_x_preferred":[
        "Aeroportul L\u00e6s\u00f8"
    ],
    "name:rus_x_preferred":[
        "\u041b\u0435\u0441\u0451"
    ],
    "name:tgk_x_preferred":[
        "\u0424\u0443\u0440\u0443\u0434\u0433\u043e\u04b3\u0438 \u043b\u0441\u0443"
    ],
    "name:zho_x_preferred":[
        "\u83b1\u65af\u673a\u573a"
    ],
    "oa:elevation_ft":"25",
    "oa:type":"small_airport",
    "woe:hierarchy":{
        "country_id":23424796,
        "county_id":12582731,
        "planet_id":1,
        "state_id":28362579
    },
    "wof:name":"L\u00e6s\u00f8 Lufthavn",
    "wof:placetype":"campus"
},
  "geometry": {"coordinates":[11.0001,57.277199],"type":"Point"}
}