{
  "type": "Feature",
  "properties": {
    "gn:admin1_code":"33.0",
    "gn:asciiname":"Ehafo",
    "gn:dem":1112,
    "gn:feature_class":"P",
    "gn:feature_code":"PPL",
    "gn:name":"Ehafo",
    "gn:population":0,
    "gn:timezone":"Africa/Windhoek",
    "wof:name":"Ehafo",
    "wof:placetype":"locality"
},
  "geometry": {"coordinates":[16.05,-17.48333],"type":"Point"}
}