{
  "type": "Feature",
  "properties": {
    "name:eng_x_variant":[
        "MTE",
        "SNMA"
    ],
    "oa:elevation_ft":"325",
    "oa:type":"small_airport",
    "woe:hierarchy":{
        "country_id":23424768,
        "county_id":12580182,
        "planet_id":1,
        "state_id":2344857
    },
    "wof:name":"Aeroporto Monte Alegre",
    "wof:placetype":"campus"
},
  "geometry": {"coordinates":[-54.0742,-1.9958],"type":"Point"}
}