{
  "type": "Feature",
  "properties": {
    "name:ceb_x_preferred":[
        "Monte Alegre Airport"
    ],
    "name:deu_x_preferred":[
        "Flughafen Monte Alegre"
    ],
    "name:eng_x_preferred":[
        "Monte Alegre Airport"
    ],
    "name:eng_x_variant":[
        "MTE",
        "SNMA"
    ],
    "name:msa_x_preferred":[
        "Lapangan Terbang Monte Alegre"
    ],
    "name:por_x_preferred":[
        "Aer\u00f3dromo Monte Alegre"
    ],
    "name:ron_x_preferred":[
        "Aeroportul Monte Alegre"
    ],
    "name:swe_x_preferred":[
        "Monte Alegre Airport"
    ],
    "oa:elevation_ft":"325",
    "oa:type":"small_airport",
    "woe:hierarchy":{
        "country_id":23424768,
        "county_id":12580182,
        "planet_id":1,
        "state_id":2344857
    },
    "wof:name":"Aeroporto Monte Alegre",
    "wof:placetype":"campus"
},
  "geometry": {"coordinates":[-54.0742,-1.9958],"type":"Point"}
}