{
  "type": "Feature",
  "properties": {
    "name:ceb_x_preferred":[
        "Vereeniging"
    ],
    "name:cym_x_preferred":[
        "Maes Awyr Vereeniging"
    ],
    "name:eng_x_preferred":[
        "Vereeniging Airport"
    ],
    "name:eng_x_variant":[
        "FAVV"
    ],
    "name:msa_x_preferred":[
        "Lapangan Terbang Vereeniging"
    ],
    "name:ron_x_preferred":[
        "Aeroportul Vereeniging"
    ],
    "oa:elevation_ft":"4846",
    "oa:type":"medium_airport",
    "woe:hierarchy":{
        "country_id":23424942,
        "county_id":56189408,
        "localadmin_id":56189548,
        "planet_id":1,
        "state_id":2346981
    },
    "wof:name":"Vereeniging Airport",
    "wof:placetype":"campus"
},
  "geometry": {"coordinates":[27.9625,-26.575],"type":"Point"}
}