{
  "type": "Feature",
  "properties": {
    "name:dan_x_preferred":[
        "Frogner"
    ],
    "name:deu_x_preferred":[
        "Frogner"
    ],
    "name:eng_x_preferred":[
        "Frogner"
    ],
    "name:est_x_preferred":[
        "Frogneri linnaosa"
    ],
    "name:fra_x_preferred":[
        "Frogner"
    ],
    "name:nld_x_preferred":[
        "Frogner"
    ],
    "name:nno_x_preferred":[
        "Frogner"
    ],
    "name:nob_x_preferred":[
        "Frogner"
    ],
    "name:nor_x_preferred":[
        "Bydel Frogner"
    ],
    "name:spa_x_preferred":[
        "Frogner"
    ],
    "name:swe_x_preferred":[
        "Frogner"
    ],
    "name:zho_x_preferred":[
        "\u5f17\u6717\u7d0d"
    ],
    "wd:wordcount":954,
    "wof:name":"Frogner",
    "wof:placetype":"neighbourhood"
},
  "geometry": {"coordinates":[10.70432056272747,59.92197863249518],"type":"Point"}
}