{
  "type": "Feature",
  "properties": {
    "name:ara_x_preferred":[
        "\u0645\u0637\u0627\u0631 \u062c\u0646\u0631\u0627\u0644 \u0633\u0627\u0646\u062a\u0648\u0633 \u0627\u0644\u062f\u0648\u0644\u064a"
    ],
    "name:eng_x_preferred":[
        "General Santos International Airport"
    ],
    "name:eng_x_variant":[
        "GES",
        "RPMR"
    ],
    "name:fas_x_preferred":[
        "\u0641\u0631\u0648\u062f\u06af\u0627\u0647 \u0628\u06cc\u0646\u200c\u0627\u0644\u0645\u0644\u0644\u06cc \u0698\u0646\u0631\u0627\u0644 \u0633\u0627\u0646\u062a\u0648\u0633"
    ],
    "name:fra_x_preferred":[
        "A\u00e9roport international de General Santos"
    ],
    "name:ita_x_preferred":[
        "aeroporto di Tambler"
    ],
    "name:jpn_x_preferred":[
        "\u30bf\u30f3\u30d6\u30e9\u30fc\u7a7a\u6e2f"
    ],
    "name:msa_x_preferred":[
        "Lapangan Terbang General Santos"
    ],
    "name:nld_x_preferred":[
        "General Santos International Airport"
    ],
    "name:nob_x_preferred":[
        "General Santos internasjonale lufthavn"
    ],
    "name:pol_x_preferred":[
        "Port lotniczy General Santos"
    ],
    "name:ron_x_preferred":[
        "Aeroportul General Santos"
    ],
    "name:spa_x_preferred":[
        "Aeropuerto Internacional General Santos"
    ],
    "name:tgk_x_preferred":[
        "\u0424\u0443\u0440\u0443\u0434\u0433\u043e\u04b3\u0438 \u0431\u0438\u043d\u200c\u0430\u043b\u043c\u0438\u043b\u0430\u043b\u04e3 \u0436\u0438\u043d\u0438\u0440\u043e\u043b \u0441\u043e\u043d\u0442\u0443\u0441"
    ],
    "name:tgl_x_preferred":[
        "Paliparang Pandaigdig ng Heneral Santos"
    ],
    "name:tha_x_preferred":[
        "\u0e17\u0e48\u0e32\u0e2d\u0e32\u0e01\u0e32\u0e28\u0e22\u0e32\u0e19\u0e19\u0e32\u0e19\u0e32\u0e0a\u0e32\u0e15\u0e34\u0e40\u0e2e\u0e40\u0e19\u0e23\u0e31\u0e25\u0e0b\u0e31\u0e19\u0e42\u0e15\u0e2a"
    ],
    "name:war_x_preferred":[
        "Luparan Panlangyaw han Heneral Santos"
    ],
    "name:zho_x_preferred":[
        "\u4e09\u6295\u65af\u5c07\u8ecd\u570b\u969b\u6a5f\u5834"
    ],
    "oa:elevation_ft":"505",
    "oa:type":"medium_airport",
    "woe:hierarchy":{
        "country_id":23424934,
        "county_id":2346723,
        "planet_id":1,
        "state_id":23424728
    },
    "wof:name":"General Santos Airport",
    "wof:placetype":"campus"
},
  "geometry": {"coordinates":[125.096001,6.058],"type":"Point"}
}