{
  "type": "Feature",
  "properties": {
    "oa:elevation_ft":"4350",
    "oa:type":"small_airport",
    "woe:hierarchy":{
        "country_id":23425003,
        "planet_id":1,
        "state_id":2347802
    },
    "wof:name":"Mufulira Airport",
    "wof:placetype":"campus"
},
  "geometry": {"coordinates":[28.283333,-12.566667],"type":"Point"}
}