{
  "type": "Feature",
  "properties": {
    "name:ceb_x_preferred":[
        "North Eleuthera Airport"
    ],
    "name:chi_x_preferred":[
        "\u5317\u4f0a\u67f3\u585e\u62c9\u6a5f\u5834"
    ],
    "name:eng_x_preferred":[
        "North Eleuthera Airport"
    ],
    "name:eng_x_variant":[
        "ELH",
        "MYEH"
    ],
    "name:fas_x_preferred":[
        "\u0641\u0631\u0648\u062f\u06af\u0627\u0647 \u0646\u0648\u0631\u062b \u0627\u0644\u0648\u062b\u0631\u0627"
    ],
    "name:jpn_x_preferred":[
        "\u30ce\u30fc\u30b9\u30fb\u30a8\u30eb\u30fc\u30bb\u30e9\u7a7a\u6e2f"
    ],
    "name:may_x_preferred":[
        "Lapangan Terbang North Eleuthera"
    ],
    "name:per_x_preferred":[
        "\u0641\u0631\u0648\u062f\u06af\u0627\u0647 \u0646\u0648\u0631\u062b \u0627\u0644\u0648\u062b\u0631\u0627"
    ],
    "name:pol_x_preferred":[
        "Port lotniczy North Eleuthera"
    ],
    "name:swe_x_preferred":[
        "North Eleuthera Airport"
    ],
    "oa:elevation_ft":"13",
    "oa:type":"medium_airport",
    "wd:wordcount":54,
    "woe:hierarchy":{
        "country_id":23424758,
        "planet_id":1,
        "state_id":24551251
    },
    "wof:name":"North Eleuthera Airport",
    "wof:placetype":"campus"
},
  "geometry": {"coordinates":[-76.683502,25.474899],"type":"Point"}
}