{
  "type": "Feature",
  "properties": {
    "name:chi_x_preferred":[
        "Penggung\u6a5f\u5834"
    ],
    "name:eng_x_preferred":[
        "Penggung Airport"
    ],
    "name:eng_x_variant":[
        "CBN",
        "WICD"
    ],
    "name:ind_x_preferred":[
        "Bandar Udara Cakrabhuwana"
    ],
    "name:may_x_preferred":[
        "Lapangan Terbang Penggung"
    ],
    "name:per_x_preferred":[
        "\u0641\u0631\u0648\u062f\u06af\u0627\u0647 \u067e\u0646\u06af\u200c\u06af\u0648\u0646\u06af"
    ],
    "name:pol_x_preferred":[
        "Port lotniczy Penggung"
    ],
    "name:swe_x_preferred":[
        "Penggung Airport"
    ],
    "name:tgk_x_preferred":[
        "\u0424\u0443\u0440\u0443\u0434\u0433\u043e\u04b3\u0438 \u043f\u0430\u043d\u0433\u200c\u0433\u0443\u043d\u0433"
    ],
    "oa:elevation_ft":"89",
    "oa:type":"small_airport",
    "woe:hierarchy":{
        "country_id":23424793,
        "planet_id":1,
        "state_id":2345120
    },
    "wof:name":"Caibarien Airport",
    "wof:placetype":"campus"
},
  "geometry": {"coordinates":[108.540001,-6.75614],"type":"Point"}
}