{
  "type": "Feature",
  "properties": {
    "name:eng_x_preferred":[
        "SLAF China Bay"
    ],
    "name:eng_x_variant":[
        "TRR",
        "VCCT"
    ],
    "name:fas_x_preferred":[
        "\u0641\u0631\u0648\u062f\u06af\u0627\u0647 \u0627\u0633\u200c\u0627\u0644\u200c\u0627\u06cc\u200c\u0627\u0641 \u0686\u0627\u06cc\u0646\u0627 \u0628\u06cc"
    ],
    "name:jpn_x_preferred":[
        "\u30c8\u30ea\u30f3\u30b3\u30de\u30ea\u30fc\u7a7a\u6e2f"
    ],
    "name:may_x_preferred":[
        "Pengkalan Udara Teluk China"
    ],
    "name:per_x_preferred":[
        "\u0641\u0631\u0648\u062f\u06af\u0627\u0647 \u0627\u0633\u200c\u0627\u0644\u200c\u0627\u06cc\u200c\u0627\u0641 \u0686\u0627\u06cc\u0646\u0627 \u0628\u06cc"
    ],
    "name:pol_x_preferred":[
        "Port lotniczy China Bay"
    ],
    "name:swe_x_preferred":[
        "Trincomalee Airport"
    ],
    "name:tam_x_preferred":[
        "\u0b9a\u0bc0\u0ba9\u0b95\u0bcd\u0b95\u0bc1\u0b9f\u0bbe \u0bb5\u0bbe\u0ba9\u0bc2\u0bb0\u0bcd\u0ba4\u0bbf \u0ba8\u0bbf\u0bb2\u0bc8\u0baf\u0bae\u0bcd"
    ],
    "name:tgk_x_preferred":[
        "\u0424\u0443\u0440\u0443\u0434\u0433\u043e\u04b3\u0438 \u0438\u0441\u200c\u0438\u043b\u200c\u0438\u0439\u200c\u0443\u0444 \u0447\u043e\u0438\u043d\u043e \u0431\u0435"
    ],
    "oa:elevation_ft":"6",
    "oa:type":"medium_airport",
    "wd:wordcount":481,
    "woe:hierarchy":{
        "country_id":23424778,
        "county_id":23706507,
        "planet_id":1,
        "state_id":2344961
    },
    "wof:name":"China Bay Airport",
    "wof:placetype":"campus"
},
  "geometry": {"coordinates":[81.1819,8.53851],"type":"Point"}
}