{
  "type": "Feature",
  "properties": {
    "name:ceb_x_preferred":[
        "Basa Air Base"
    ],
    "name:fas_x_preferred":[
        "\u067e\u0627\u06cc\u06af\u0627\u0647 \u0647\u0648\u0627\u06cc\u06cc \u0628\u0627\u0633\u0627"
    ],
    "name:nld_x_preferred":[
        "Basa Air Base"
    ],
    "name:tgk_x_preferred":[
        "\u041f\u043e\u0439\u0433\u043e\u04b3\u0438 \u04b3\u0430\u0432\u043e\u0438\u0438 \u0411\u0430\u0441\u0430"
    ],
    "oa:elevation_ft":"151",
    "oa:type":"small_airport",
    "wd:wordcount":1551,
    "woe:hierarchy":{
        "country_id":23424934,
        "county_id":2346704,
        "planet_id":1,
        "state_id":23424722
    },
    "wof:name":"Basa Air Base",
    "wof:placetype":"campus"
},
  "geometry": {"coordinates":[120.48333332999999,14.98333333],"type":"Point"}
}