{
  "type": "Feature",
  "properties": {
    "gn:admin1_code":"29.0",
    "gn:asciiname":"Otjivero",
    "gn:dem":1094,
    "gn:feature_class":"P",
    "gn:feature_code":"PPL",
    "gn:name":"Otjivero",
    "gn:population":0,
    "gn:timezone":"Africa/Windhoek",
    "wof:name":"Otjivero",
    "wof:placetype":"locality"
},
  "geometry": {"coordinates":[15.35,-20.86667000000001],"type":"Point"}
}