{
  "type": "Feature",
  "properties": {
    "name:ceb_x_preferred":[
        "Sandakan Airport"
    ],
    "name:deu_x_preferred":[
        "Flughafen Sandakan"
    ],
    "name:eng_x_preferred":[
        "Sandakan Airport"
    ],
    "name:eng_x_variant":[
        "SDK",
        "WBKS"
    ],
    "name:fas_x_preferred":[
        "\u0641\u0631\u0648\u062f\u06af\u0627\u0647 \u0633\u0627\u0646\u062f\u0627\u06a9\u0627\u0646"
    ],
    "name:fra_x_preferred":[
        "A\u00e9roport de Sandakan"
    ],
    "name:fra_x_variant":[
        "a\u00e9roport de Sandakan"
    ],
    "name:ind_x_preferred":[
        "Bandar Udara Sandakan"
    ],
    "name:ita_x_preferred":[
        "Aeroporto di Sandakan"
    ],
    "name:jpn_x_preferred":[
        "\u30b5\u30f3\u30c0\u30ab\u30f3\u7a7a\u6e2f"
    ],
    "name:msa_x_preferred":[
        "Lapangan Terbang Sandakan"
    ],
    "name:nld_x_preferred":[
        "Sandakan Airport"
    ],
    "name:pol_x_preferred":[
        "Port lotniczy Sandakan"
    ],
    "name:ron_x_preferred":[
        "Aeroportul Sandakan"
    ],
    "name:tgk_x_preferred":[
        "\u0424\u0443\u0440\u0443\u0434\u0433\u043e\u04b3\u0438 \u0441\u043e\u043d\u0434\u043e\u043a\u043e\u043d"
    ],
    "name:vie_x_preferred":[
        "S\u00e2n bay Sandakan"
    ],
    "name:zho_x_preferred":[
        "\u5c71\u6253\u6839\u56fd\u9645\u673a\u573a"
    ],
    "oa:elevation_ft":"46",
    "oa:type":"medium_airport",
    "wd:wordcount":103,
    "woe:hierarchy":{
        "country_id":23424901,
        "county_id":56013611,
        "localadmin_id":56014185,
        "planet_id":1,
        "state_id":2346310
    },
    "wof:name":"Sandakan Airport",
    "wof:placetype":"campus"
},
  "geometry": {"coordinates":[118.058998,5.9009],"type":"Point"}
}