{
  "type": "Feature",
  "properties": {
    "gn:admin1_code":"29.0",
    "gn:asciiname":"Birkenfels",
    "gn:dem":121,
    "gn:feature_class":"P",
    "gn:feature_code":"PPL",
    "gn:name":"Birkenfels",
    "gn:population":0,
    "gn:timezone":"Africa/Windhoek",
    "wof:name":"Birkenfels",
    "wof:placetype":"locality"
},
  "geometry": {"coordinates":[14.73333,-22.63333],"type":"Point"}
}