{
  "type": "Feature",
  "properties": {
    "name:eng_x_preferred":[
        "Bogorodskoye Airport"
    ],
    "name:eng_x_variant":[
        "BQG",
        "UHNB"
    ],
    "name:fra_x_preferred":[
        "\u0411\u043e\u0433\u043e\u0440\u043e\u0434\u0441\u043a\u043e\u0435"
    ],
    "name:ron_x_preferred":[
        "Aeroportul Bogorodskoye"
    ],
    "name:rus_x_preferred":[
        "\u0411\u043e\u0433\u043e\u0440\u043e\u0434\u0441\u043a\u043e\u0435"
    ],
    "name:zho_x_preferred":[
        "\u535a\u6208\u7f85\u5b63\u8328\u79d1\u8036\u6a5f\u5834"
    ],
    "oa:type":"small_airport",
    "wd:wordcount":105,
    "woe:hierarchy":{
        "country_id":23424936,
        "county_id":12597760,
        "planet_id":1,
        "state_id":2346883
    },
    "wof:name":"Bogorodskoye Airport",
    "wof:placetype":"campus"
},
  "geometry": {"coordinates":[140.448611,52.380556],"type":"Point"}
}