{
  "type": "Feature",
  "properties": {
    "name:rus_x_preferred":[
        "\u0411\u043e\u0433\u043e\u0440\u043e\u0434\u0441\u043a\u043e\u0435"
    ],
    "oa:type":"small_airport",
    "wd:wordcount":105,
    "woe:hierarchy":{
        "country_id":23424936,
        "county_id":12597760,
        "planet_id":1,
        "state_id":2346883
    },
    "wof:name":"Bogorodskoye Airport",
    "wof:placetype":"campus"
},
  "geometry": {"coordinates":[140.44861111,52.38055556],"type":"Point"}
}