{
  "type": "Feature",
  "properties": {
    "name:ceb_x_preferred":[
        "Erfurt\u2013Weimar Airport"
    ],
    "name:dan_x_preferred":[
        "Flughafen Erfurt-Weimar"
    ],
    "name:deu_x_preferred":[
        "Flughafen Erfurt-Weimar"
    ],
    "name:eng_x_preferred":[
        "Erfurt-Weimar Airport"
    ],
    "name:eng_x_variant":[
        "ERF",
        "EDDE"
    ],
    "name:epo_x_preferred":[
        "Flughaveno Erfurt-Weimar"
    ],
    "name:fas_x_preferred":[
        "\u0641\u0631\u0648\u062f\u06af\u0627\u0647 \u0627\u0631\u0641\u0648\u0631\u062a-\u0648\u0627\u06cc\u0645\u0627\u0631"
    ],
    "name:hun_x_preferred":[
        "Erfurt-Weimari rep\u00fcl\u0151t\u00e9r"
    ],
    "name:jpn_x_preferred":[
        "\u30a8\u30a2\u30d5\u30eb\u30c8\u7a7a\u6e2f"
    ],
    "name:mkd_x_preferred":[
        "\u0410\u0435\u0440\u043e\u0434\u0440\u043e\u043c \u0415\u0440\u0444\u0443\u0440\u0442/\u0412\u0430\u0458\u043c\u0430\u0440"
    ],
    "name:msa_x_preferred":[
        "Lapangan Terbang Erfurt"
    ],
    "name:nld_x_preferred":[
        "Flughafen Erfurt Weimar"
    ],
    "name:nld_x_variant":[
        "Luchthaven Erfurt Weimar"
    ],
    "name:pol_x_preferred":[
        "Port lotniczy Erfurt"
    ],
    "name:rus_x_preferred":[
        "\u042d\u0440\u0444\u0443\u0440\u0442-\u0412\u0435\u0439\u043c\u0430\u0440"
    ],
    "name:spa_x_preferred":[
        "Aeropuerto de Erfurt"
    ],
    "name:swe_x_preferred":[
        "Flughafen Erfurt"
    ],
    "name:tgk_x_preferred":[
        "\u0424\u0443\u0440\u0443\u0434\u0433\u043e\u04b3\u0438 \u043e\u0440\u0444\u0443\u0440\u0442-\u0432\u043e\u0438\u043c\u043e\u0440"
    ],
    "name:tur_x_preferred":[
        "Erfurt Havaliman\u0131"
    ],
    "name:vie_x_preferred":[
        "S\u00e2n bay Erfurt"
    ],
    "name:zho_x_preferred":[
        "\u57c3\u5c14\u798f\u7279-\u9b4f\u739b\u673a\u573a"
    ],
    "oa:elevation_ft":"1036",
    "oa:type":"medium_airport",
    "wd:wordcount":503,
    "woe:hierarchy":{
        "country_id":23424829,
        "county_id":12596925,
        "planet_id":1,
        "state_id":2345495
    },
    "wof:name":"Erfurt Airport",
    "wof:placetype":"campus"
},
  "geometry": {"coordinates":[10.9581,50.979801],"type":"Point"}
}