{
  "type": "Feature",
  "properties": {
    "name:eng_x_variant":[
        "SVD",
        "TVSV"
    ],
    "name:fas_x_preferred":[
        "\u0641\u0631\u0648\u062f\u06af\u0627\u0647\u200c\u0627\u06cc. \u062a\u06cc. \u062c\u0627\u0634\u0648\u0627"
    ],
    "name:jpn_x_preferred":[
        "E.T.\u30b8\u30e7\u30b7\u30e5\u30a2\u56fd\u969b\u7a7a\u6e2f"
    ],
    "name:lit_x_preferred":[
        "E. T. Joshua oro uostas"
    ],
    "name:pol_x_preferred":[
        "Port lotniczy E. T. Joshua"
    ],
    "name:spa_x_preferred":[
        "Aeropuerto E. T. Joshua"
    ],
    "name:tgk_x_preferred":[
        "\u0424\u0443\u0440\u0443\u0434\u0433\u043e\u04b3\u0438 \u0438\u0439. \u0442\u04e3. \u04b7\u043e\u0448\u0443\u043e"
    ],
    "oa:elevation_ft":"66",
    "oa:type":"medium_airport",
    "wd:wordcount":131,
    "woe:hierarchy":{
        "country_id":23424981,
        "planet_id":1,
        "state_id":2347674
    },
    "wof:name":"E T Joshua Airport",
    "wof:placetype":"campus"
},
  "geometry": {"coordinates":[-61.210899,13.1443],"type":"Point"}
}