{
  "type": "Feature",
  "properties": {
    "name:eng_x_variant":[
        "SPH",
        "AYQO"
    ],
    "oa:elevation_ft":"6580",
    "oa:type":"small_airport",
    "woe:hierarchy":{
        "country_id":23424977,
        "county_id":12588655,
        "planet_id":1,
        "state_id":2347577
    },
    "wof:name":"Springhill Airport",
    "wof:placetype":"campus"
},
  "geometry": {"coordinates":[147.16589999999999,-8.3038],"type":"Point"}
}