{
  "type": "Feature",
  "properties": {
    "name:ceb_x_preferred":[
        "Dien Bien Phu Airport"
    ],
    "name:eng_x_preferred":[
        "Dien Bien Phu Airport"
    ],
    "name:eng_x_variant":[
        "DIN",
        "VVDB"
    ],
    "name:fas_x_preferred":[
        "\u0641\u0631\u0648\u062f\u06af\u0627\u0647 \u062f\u06cc\u0646\u200c\u0628\u06cc\u0646\u200c\u0641\u0648"
    ],
    "name:fra_x_preferred":[
        "A\u00e9roport de Di\u00ean Bi\u00ean Phu"
    ],
    "name:ind_x_preferred":[
        "Bandar Udara Dien Bien Phu"
    ],
    "name:kor_x_preferred":[
        "\ub514\uc5d4\ube44\uc5d4\ud478 \uacf5\ud56d"
    ],
    "name:msa_x_preferred":[
        "Lapangan Terbang Dienbien"
    ],
    "name:pol_x_preferred":[
        "Port lotniczy \u0110i\u1ec7n Bi\u00ean Ph\u1ee7"
    ],
    "name:ron_x_preferred":[
        "Aeroportul Dien Bien Phu"
    ],
    "name:rus_x_preferred":[
        "\u0414\u044c\u0435\u043d\u0431\u044c\u0435\u043d\u0444\u0443"
    ],
    "name:tgk_x_preferred":[
        "\u0424\u0443\u0440\u0443\u0434\u0433\u043e\u04b3\u0438 \u0434\u0438\u043d\u200c\u0431\u0438\u043d\u200c\u0444\u0443"
    ],
    "name:ukr_x_preferred":[
        "\u0414\u044c\u0454\u043d\u0431'\u0454\u043d\u0444\u0443"
    ],
    "name:vie_x_preferred":[
        "S\u00e2n bay \u0110i\u1ec7n Bi\u00ean Ph\u1ee7"
    ],
    "name:zho_x_preferred":[
        "\u5960\u908a\u5e9c\u6a5f\u5834"
    ],
    "oa:elevation_ft":"1611",
    "oa:type":"medium_airport",
    "wd:wordcount":41,
    "woe:hierarchy":{
        "country_id":23424984,
        "planet_id":1,
        "state_id":28301718
    },
    "wof:name":"Dien Bien Phu Airport",
    "wof:placetype":"campus"
},
  "geometry": {"coordinates":[103.007778,21.397222],"type":"Point"}
}