{
  "type": "Feature",
  "properties": {
    "name:ceb_x_preferred":[
        "Ca\u00e7ador Airport"
    ],
    "name:eng_x_variant":[
        "CFC",
        "SBCD"
    ],
    "name:fas_x_preferred":[
        "\u0641\u0631\u0648\u062f\u06af\u0627\u0647 \u06a9\u0627\u0686\u0627\u062f\u0648\u0631"
    ],
    "name:por_x_preferred":[
        "Aeroporto de Ca\u00e7ador"
    ],
    "name:swe_x_preferred":[
        "Ca\u00e7ador Airport"
    ],
    "name:tgk_x_preferred":[
        "\u0424\u0443\u0440\u0443\u0434\u0433\u043e\u04b3\u0438 \u043a\u043e\u0447\u043e\u0434\u0443\u0440"
    ],
    "oa:elevation_ft":"3376",
    "oa:type":"small_airport",
    "woe:hierarchy":{
        "country_id":23424768,
        "county_id":12581627,
        "planet_id":1,
        "state_id":2344867
    },
    "wof:name":"Aeroporto Cacador",
    "wof:placetype":"campus"
},
  "geometry": {"coordinates":[-50.9398,-26.788401],"type":"Point"}
}