{
  "type": "Feature",
  "properties": {
    "name:dan_x_preferred":[
        "Mafia Lufthavn"
    ],
    "name:eng_x_preferred":[
        "Mafia Airport"
    ],
    "name:eng_x_variant":[
        "MFA",
        "HTMA"
    ],
    "name:ind_x_preferred":[
        "Bandar Udara Mafia"
    ],
    "name:jpn_x_preferred":[
        "\u30de\u30d5\u30a3\u30a2\u7a7a\u6e2f"
    ],
    "name:msa_x_preferred":[
        "Lapangan Terbang Mafia"
    ],
    "name:nob_x_preferred":[
        "Mafia lufthavn"
    ],
    "name:nor_x_preferred":[
        "Mafia lufthavn"
    ],
    "name:pol_x_preferred":[
        "Port lotniczy Mafia"
    ],
    "name:swa_x_preferred":[
        "Uwanja wa ndege wa Mafia"
    ],
    "oa:elevation_ft":"60",
    "oa:type":"small_airport",
    "wd:wordcount":67,
    "woe:hierarchy":{
        "country_id":23424973,
        "county_id":56025142,
        "planet_id":1,
        "state_id":2347353
    },
    "wof:name":"Mafia Airport",
    "wof:placetype":"campus"
},
  "geometry": {"coordinates":[39.667,-7.917],"type":"Point"}
}