{
  "type": "Feature",
  "properties": {
    "name:ara_x_preferred":[
        "\u0645\u0637\u0627\u0631 \u0645\u0627\u0641\u064a\u0627"
    ],
    "name:ceb_x_preferred":[
        "Mafia Island Airport"
    ],
    "name:dan_x_preferred":[
        "Mafia Lufthavn"
    ],
    "name:deu_x_preferred":[
        "Flughafen Mafia"
    ],
    "name:ell_x_preferred":[
        "\u0391\u03b5\u03c1\u03bf\u03b4\u03c1\u03cc\u03bc\u03b9\u03bf \u039c\u03b1\u03c6\u03af\u03b1"
    ],
    "name:eng_x_preferred":[
        "Mafia Airport"
    ],
    "name:eng_x_variant":[
        "MFA",
        "HTMA"
    ],
    "name:ind_x_preferred":[
        "Bandar Udara Mafia"
    ],
    "name:jpn_x_preferred":[
        "\u30de\u30d5\u30a3\u30a2\u7a7a\u6e2f"
    ],
    "name:msa_x_preferred":[
        "Lapangan Terbang Mafia"
    ],
    "name:nob_x_preferred":[
        "Mafia lufthavn"
    ],
    "name:nor_x_preferred":[
        "Mafia lufthavn"
    ],
    "name:pol_x_preferred":[
        "Port lotniczy Mafia"
    ],
    "name:ron_x_preferred":[
        "Aeroportul Mafia"
    ],
    "name:swa_x_preferred":[
        "Uwanja wa ndege wa Mafia"
    ],
    "oa:elevation_ft":"60",
    "oa:type":"small_airport",
    "wd:wordcount":67,
    "woe:hierarchy":{
        "country_id":23424973,
        "county_id":56025142,
        "planet_id":1,
        "state_id":2347353
    },
    "wof:name":"Mafia Airport",
    "wof:placetype":"campus"
},
  "geometry": {"coordinates":[39.667,-7.917],"type":"Point"}
}