{
  "type": "Feature",
  "properties": {
    "name:arz_x_preferred":[
        "\u0645\u0637\u0627\u0631 \u0628\u0644\u0648 \u0643\u0627\u0646\u064a\u0648\u0646 \u0646\u064a\u0627\u0643"
    ],
    "name:ceb_x_preferred":[
        "Blue Canyon-Nyack Airport"
    ],
    "name:cym_x_preferred":[
        "Maes Awyr Blue Canyon\u2013Nyack"
    ],
    "name:eng_x_preferred":[
        "Blue Canyon\u2013Nyack Airport"
    ],
    "name:eng_x_variant":[
        "BLU",
        "KBLU"
    ],
    "name:fas_x_preferred":[
        "\u0641\u0631\u0648\u062f\u06af\u0627\u0647 \u0628\u0644\u0648 \u06a9\u0646\u06cc\u0648\u0646-\u0646\u0627\u06cc\u06a9"
    ],
    "name:ron_x_preferred":[
        "Aeroportul Blue Canyon\u2013Nyack"
    ],
    "name:tgk_x_preferred":[
        "\u0424\u0443\u0440\u0443\u0434\u0433\u043e\u04b3\u0438 \u0411\u043b\u0443 \u041a\u0435\u043d\u0439\u043e\u043d-\u041d\u0439\u0430\u043a"
    ],
    "name:tgk_x_variant":[
        "\u0424\u0443\u0440\u0443\u0434\u0433\u043e\u04b3\u0438 \u0431\u043b\u0443 \u043a\u043d\u044e\u043d-\u043d\u043e\u0438\u043a"
    ],
    "name:urd_x_preferred":[
        "\u0628\u0644\u06cc\u0648 \u06a9\u06cc\u0646\u06cc\u0646\u2013\u0646\u0627\u0626\u06cc\u06a9 \u06c1\u0648\u0627\u0626\u06cc \u0627\u0688\u0627"
    ],
    "name:zho_x_preferred":[
        "\u85cd\u5cfd\u8c37-\u5948\u4e9e\u514b\u6a5f\u5834"
    ],
    "oa:elevation_ft":"5284",
    "oa:type":"small_airport",
    "wd:wordcount":151,
    "woe:hierarchy":{
        "country_id":23424977,
        "county_id":12587700,
        "planet_id":1,
        "state_id":2347563
    },
    "wof:name":"Blue Canyon-Nyack Airport",
    "wof:placetype":"campus"
},
  "geometry": {"coordinates":[-120.709999,39.275002],"type":"Point"}
}