{
  "type": "Feature",
  "properties": {
    "name:deu_x_preferred":[
        "Flughafen Siirt"
    ],
    "name:eng_x_preferred":[
        "Siirt Airport"
    ],
    "name:eng_x_variant":[
        "SXZ",
        "LTCL"
    ],
    "name:fas_x_preferred":[
        "\u0641\u0631\u0648\u062f\u06af\u0627\u0647 \u0633\u06cc\u0631\u062a"
    ],
    "name:ger_x_preferred":[
        "Flughafen Siirt"
    ],
    "name:jpn_x_preferred":[
        "\u30b9\u30a3\u30a4\u30eb\u30c8\u7a7a\u6e2f"
    ],
    "name:may_x_preferred":[
        "Lapangan Terbang Siirt"
    ],
    "name:per_x_preferred":[
        "\u0641\u0631\u0648\u062f\u06af\u0627\u0647 \u0633\u06cc\u0631\u062a"
    ],
    "name:tgk_x_preferred":[
        "\u0424\u0443\u0440\u0443\u0434\u0433\u043e\u04b3\u0438 \u0441\u0438\u0440\u0442"
    ],
    "name:tur_x_preferred":[
        "Siirt Havaliman\u0131"
    ],
    "oa:elevation_ft":"2001",
    "oa:type":"medium_airport",
    "wd:wordcount":33,
    "woe:hierarchy":{
        "country_id":23424969,
        "county_id":29390612,
        "planet_id":1,
        "state_id":2347324
    },
    "wof:name":"Siirt Airport",
    "wof:placetype":"campus"
},
  "geometry": {"coordinates":[41.840401,37.978901],"type":"Point"}
}