{
  "type": "Feature",
  "properties": {
    "gn:admin1_code":"28.0",
    "gn:asciiname":"Mamili",
    "gn:dem":940,
    "gn:feature_class":"P",
    "gn:feature_code":"PPL",
    "gn:name":"Mamili",
    "gn:population":0,
    "gn:timezone":"Africa/Windhoek",
    "name:und_x_variant":[
        "Mamili\u2019s",
        "Mamili"
    ],
    "wof:name":"Mamili",
    "wof:placetype":"locality"
},
  "geometry": {"coordinates":[24.01667,-18.03333],"type":"Point"}
}