{
  "type": "Feature",
  "properties": {
    "name:ceb_x_preferred":[
        "Sukhumi Dranda Airport"
    ],
    "name:ces_x_preferred":[
        "Leti\u0161t\u011b Suchumi-Babu\u0161ara"
    ],
    "name:cze_x_preferred":[
        "Leti\u0161t\u011b Suchumi-Babu\u0161ara"
    ],
    "name:eng_x_preferred":[
        "Sukhumi Babushara Airport"
    ],
    "name:eng_x_variant":[
        "SUI",
        "UGSS"
    ],
    "name:fas_x_preferred":[
        "\u0641\u0631\u0648\u062f\u06af\u0627\u0647 \u0633\u0648\u062e\u0648\u0645\u06cc \u062f\u0631\u0646\u062f\u0627"
    ],
    "name:fra_x_preferred":[
        "A\u00e9roport de Soukhoumi-Dranda"
    ],
    "name:fre_x_preferred":[
        "a\u00e9roport de Soukhoumi-Dranda"
    ],
    "name:geo_x_preferred":[
        "\u10d1\u10d0\u10d1\u10e3\u10e8\u10d0\u10e0\u10d8\u10e1 \u10d0\u10d4\u10e0\u10dd\u10de\u10dd\u10e0\u10e2\u10d8"
    ],
    "name:heb_x_preferred":[
        "\u05e0\u05de\u05dc \u05d4\u05ea\u05e2\u05d5\u05e4\u05d4 \u05e1\u05d5\u05d7\u05d5\u05de\u05d9 \u05d3\u05e8\u05e0\u05d3\u05d4"
    ],
    "name:jpn_x_preferred":[
        "\u30b9\u30d5\u30df\u7a7a\u6e2f"
    ],
    "name:kat_x_preferred":[
        "\u10d1\u10d0\u10d1\u10e3\u10e8\u10d0\u10e0\u10d8\u10e1 \u10d0\u10d4\u10e0\u10dd\u10de\u10dd\u10e0\u10e2\u10d8"
    ],
    "name:may_x_preferred":[
        "Lapangan Terbang Babushara"
    ],
    "name:msa_x_preferred":[
        "Lapangan Terbang Babushara"
    ],
    "name:per_x_preferred":[
        "\u0641\u0631\u0648\u062f\u06af\u0627\u0647 \u0633\u0648\u062e\u0648\u0645\u06cc \u062f\u0631\u0646\u062f\u0627"
    ],
    "name:pol_x_preferred":[
        "Port lotniczy Suchumi-Dranda"
    ],
    "name:por_x_preferred":[
        "Aeroporto de Sukhumi-Babushara"
    ],
    "name:rus_x_preferred":[
        "\u0411\u0430\u0431\u0443\u0448\u0430\u0440\u0430"
    ],
    "name:spa_x_preferred":[
        "Aeropuerto de Babushara"
    ],
    "name:swe_x_preferred":[
        "Suchumi Dranda flygplats"
    ],
    "name:tgk_x_preferred":[
        "\u0424\u0443\u0440\u0443\u0434\u0433\u043e\u04b3\u0438 \u0441\u0443\u0445\u0443\u043c\u0438 \u0434\u0440\u043d\u0434\u043e"
    ],
    "name:tur_x_preferred":[
        "Sohum Dranda Havaalan\u0131"
    ],
    "name:ukr_x_preferred":[
        "\u0410\u0435\u0440\u043e\u043f\u043e\u0440\u0442 \u00ab\u0421\u0443\u0445\u0443\u043c\u0456-\u0414\u0440\u0430\u043d\u0434\u0430\u00bb"
    ],
    "name:xmf_x_preferred":[
        "\u10d1\u10d0\u10d1\u10e3\u10e8\u10d0\u10e0\u10d0\u10e8 \u10d0\u10d4\u10e0\u10dd\u10de\u10dd\u10e0\u10e2\u10d8"
    ],
    "oa:elevation_ft":"53",
    "oa:type":"medium_airport",
    "wd:wordcount":270,
    "woe:hierarchy":{
        "country_id":23424823,
        "planet_id":1,
        "state_id":20070401
    },
    "wof:name":"Sukhumi-Dranda Airport",
    "wof:placetype":"campus"
},
  "geometry": {"coordinates":[41.128101,42.8582],"type":"Point"}
}