{
  "type": "Feature",
  "properties": {
    "wof:name":"Embarcadero Oaks",
    "wof:placetype":"neighbourhood"
},
  "geometry": {"coordinates":[-122.13844470255523,37.44225124427174],"type":"Point"}
}