{
  "type": "Feature",
  "properties": {
    "name:ara_x_preferred":[
        "\u0645\u0637\u0627\u0631 \u0628\u0647\u0627\u0641\u0627 \u0646\u062c\u0631"
    ],
    "name:ben_x_preferred":[
        "\u09ad\u09be\u09ac\u09a8\u0997\u09b0 \u09ac\u09bf\u09ae\u09be\u09a8\u09ac\u09a8\u09cd\u09a6\u09b0"
    ],
    "name:ceb_x_preferred":[
        "Bhaunagar"
    ],
    "name:eng_x_preferred":[
        "Bhavnagar Airport"
    ],
    "name:eng_x_variant":[
        "BHU",
        "VABV"
    ],
    "name:fas_x_preferred":[
        "\u0641\u0631\u0648\u062f\u06af\u0627\u0647 \u0628\u0627\u0648\u0646\u06af\u0631"
    ],
    "name:guj_x_preferred":[
        "\u0aad\u0abe\u0ab5\u0aa8\u0a97\u0ab0 \u0ab9\u0ab5\u0abe\u0a88 \u0aae\u0aa5\u0a95"
    ],
    "name:hin_x_preferred":[
        "\u092d\u093e\u0935\u0928\u0917\u0930 \u0935\u093f\u092e\u093e\u0928\u0915\u094d\u0937\u0947\u0924\u094d\u0930"
    ],
    "name:jpn_x_preferred":[
        "\u30d0\u30fc\u30f4\u30ca\u30ac\u30eb\u7a7a\u6e2f"
    ],
    "name:mar_x_preferred":[
        "\u092d\u093e\u0935\u0928\u0917\u0930 \u0935\u093f\u092e\u093e\u0928\u0924\u0933"
    ],
    "name:msa_x_preferred":[
        "Lapangan Terbang Bhavnagar"
    ],
    "name:ron_x_preferred":[
        "Aeroportul Bhavnagar"
    ],
    "name:spa_x_preferred":[
        "Aeropuerto de Bhavnagar"
    ],
    "name:tgk_x_preferred":[
        "\u0424\u0443\u0440\u0443\u0434\u0433\u043e\u04b3\u0438 \u0411\u04b3\u0430\u0432\u043d\u0430\u0433\u0430\u0440"
    ],
    "name:tgk_x_variant":[
        "\u0424\u0443\u0440\u0443\u0434\u0433\u043e\u04b3\u0438 \u0431\u043e\u0432\u043d\u0433\u0440"
    ],
    "name:vie_x_preferred":[
        "S\u00e2n bay Bhavnagar"
    ],
    "name:zho_x_preferred":[
        "\u5df4\u592b\u90a3\u52a0\u723e\u6a5f\u5834"
    ],
    "oa:elevation_ft":"44",
    "oa:type":"medium_airport",
    "wd:wordcount":344,
    "woe:hierarchy":{
        "country_id":23424848,
        "county_id":12586420,
        "planet_id":1,
        "state_id":2345743
    },
    "wof:name":"Bhavnagar Airport",
    "wof:placetype":"campus"
},
  "geometry": {"coordinates":[72.185278,21.752222],"type":"Point"}
}