{
  "type": "Feature",
  "properties": {
    "name:fas_x_preferred":[
        "\u0641\u0631\u0648\u062f\u06af\u0627\u0647 \u0628\u0627\u0648\u0646\u06af\u0631"
    ],
    "name:guj_x_preferred":[
        "\u0aad\u0abe\u0ab5\u0aa8\u0a97\u0ab0 \u0ab9\u0ab5\u0abe\u0a88 \u0aae\u0aa5\u0a95"
    ],
    "name:mar_x_preferred":[
        "\u092d\u093e\u0935\u0928\u0917\u0930 \u0935\u093f\u092e\u093e\u0928\u0924\u0933"
    ],
    "name:spa_x_preferred":[
        "Aeropuerto de Bhavnagar"
    ],
    "name:tgk_x_preferred":[
        "\u0424\u0443\u0440\u0443\u0434\u0433\u043e\u04b3\u0438 \u0411\u04b3\u0430\u0432\u043d\u0430\u0433\u0430\u0440"
    ],
    "name:vie_x_preferred":[
        "S\u00e2n bay Bhavnagar"
    ],
    "oa:elevation_ft":"44",
    "oa:type":"medium_airport",
    "wd:wordcount":344,
    "woe:hierarchy":{
        "country_id":23424848,
        "county_id":12586420,
        "planet_id":1,
        "state_id":2345743
    },
    "wof:name":"Bhavnagar Airport",
    "wof:placetype":"campus"
},
  "geometry": {"coordinates":[72.185277777778,21.752222222222],"type":"Point"}
}