{
  "type": "Feature",
  "properties": {
    "gn:admin1_code":"39.0",
    "gn:asciiname":"Hantam",
    "gn:dem":1189,
    "gn:feature_class":"P",
    "gn:feature_code":"PPL",
    "gn:name":"Hantam",
    "gn:population":0,
    "gn:timezone":"Africa/Windhoek",
    "wof:name":"Hantam",
    "wof:placetype":"locality"
},
  "geometry": {"coordinates":[18.41667,-18.96667],"type":"Point"}
}