{
  "type": "Feature",
  "properties": {
    "name:bar_x_preferred":[
        "Midtown"
    ],
    "name:bul_x_preferred":[
        "\u041c\u0438\u0434\u0442\u0430\u0443\u043d"
    ],
    "name:deu_x_preferred":[
        "Midtown"
    ],
    "name:fra_x_preferred":[
        "Midtown"
    ],
    "name:kor_x_preferred":[
        "\ubbf8\ub4dc\ud0c0\uc6b4"
    ],
    "name:por_x_preferred":[
        "Midtown"
    ],
    "name:spa_x_preferred":[
        "Midtown"
    ],
    "name:zho_x_preferred":[
        "\u4e2d\u57ce"
    ],
    "wd:wordcount":142,
    "wof:name":"Midtown",
    "wof:placetype":"neighbourhood"
},
  "geometry": {"coordinates":[-87.9448808605641,43.05307942212242],"type":"Point"}
}