{
  "type": "Feature",
  "properties": {
    "name:afr_x_preferred":[
        "Doornfontein"
    ],
    "name:deu_x_preferred":[
        "Doornfontein"
    ],
    "name:nso_x_preferred":[
        "Doornfontein"
    ],
    "wof:name":"Doornfontein",
    "wof:placetype":"neighbourhood"
},
  "geometry": {"coordinates":[28.05785684292405,-26.19395413225455],"type":"Point"}
}