{
  "type": "Feature",
  "properties": {
    "name:ara_x_preferred":[
        "\u0627\u0644\u0633\u0627\u0644\u0645\u064a\u0629-\u0642\u0637\u0639\u0629 9"
    ],
    "name:eng_x_preferred":[
        "Salmiya-block 9"
    ],
    "name:eng_x_variant":[
        "Salmiya-block 9"
    ],
    "qs:gn_local":0,
    "qs:local_max":1015,
    "qs:local_sum":3961,
    "qs:localhoods":9,
    "qs:name":"\u0627\u0644\u0633\u0627\u0644\u0645\u064a\u0629-\u0642\u0637\u0639\u0629 9",
    "qs:name_adm0":"\u0627\u0644\u0643\u0648\u064a\u062a",
    "qs:name_adm1":"\u062d\u0648\u0644\u0649",
    "qs:name_adm2":"\u062d\u0648\u0644\u0649",
    "qs:name_en":"Salmiya-block 9",
    "qs:name_local":"Salmiya",
    "qs:photo_max":157,
    "qs:photo_sum":644,
    "qs:placetype":"Suburb",
    "qs:quad_count":29,
    "qs:woe_adm0":23424870,
    "qs:woe_adm1":20070167,
    "qs:woe_adm2":55943084,
    "qs:woe_lau":0,
    "qs:woe_local":22724741,
    "qs:woe_ver":"7.10.0",
    "wof:lang":[
        "ara"
    ],
    "wof:name":"\u0627\u0644\u0633\u0627\u0644\u0645\u064a\u0629-\u0642\u0637\u0639\u0629 9",
    "wof:placetype":"neighbourhood"
},
  "geometry": {"coordinates":[48.054698,29.336383],"type":"Point"}
}