{
  "type": "Feature",
  "properties": {
    "name:ara_x_preferred":[
        "\u0645\u0637\u0627\u0631 \u064a\u0627\u0634 \u0627\u0644\u062f\u0648\u0644\u064a"
    ],
    "name:deu_x_preferred":[
        "Flughafen Ia\u0219i"
    ],
    "name:eng_x_preferred":[
        "Ia\u0219i International Airport"
    ],
    "name:eng_x_variant":[
        "IAS",
        "LRIA"
    ],
    "name:fas_x_preferred":[
        "\u0641\u0631\u0648\u062f\u06af\u0627\u0647 \u0628\u06cc\u0646\u200c\u0627\u0644\u0645\u0644\u0644\u06cc \u06cc\u0627\u0634"
    ],
    "name:fra_x_preferred":[
        "a\u00e9roport international de Ia\u0219i"
    ],
    "name:heb_x_preferred":[
        "\u05e0\u05de\u05dc \u05d4\u05ea\u05e2\u05d5\u05e4\u05d4 \u05d4\u05d1\u05d9\u05e0\u05dc\u05d0\u05d5\u05de\u05d9 \u05d9\u05d0\u05e9\u05d9"
    ],
    "name:ita_x_preferred":[
        "Aeroporto Internazionale di Ia\u015fi"
    ],
    "name:jpn_x_preferred":[
        "\u30e4\u30b7\u56fd\u969b\u7a7a\u6e2f"
    ],
    "name:msa_x_preferred":[
        "Lapangan Terbang Iasi"
    ],
    "name:nld_x_preferred":[
        "Luchthaven Ia\u0219i"
    ],
    "name:pol_x_preferred":[
        "Port lotniczy Jassy"
    ],
    "name:ron_x_preferred":[
        "Aeroportul Ia\u0219i"
    ],
    "name:ron_x_variant":[
        "Aeroportul Interna\u021bional Ia\u0219i"
    ],
    "name:rus_x_preferred":[
        "\u041c\u0435\u0436\u0434\u0443\u043d\u0430\u0440\u043e\u0434\u043d\u044b\u0439 \u0430\u044d\u0440\u043e\u043f\u043e\u0440\u0442 \u042f\u0448\u0438"
    ],
    "name:spa_x_preferred":[
        "Aeropuerto Internacional de Ia\u0219i"
    ],
    "name:tgk_x_preferred":[
        "\u0424\u0443\u0440\u0443\u0434\u0433\u043e\u04b3\u0438 \u0431\u0438\u043d\u200c\u0430\u043b\u043c\u0438\u043b\u0430\u043b\u04e3 \u0438\u043e\u0448"
    ],
    "name:ukr_x_preferred":[
        "\u042f\u0441\u0441\u0438"
    ],
    "name:vie_x_preferred":[
        "S\u00e2n bay qu\u1ed1c t\u1ebf Ia\u015fi"
    ],
    "name:vie_x_variant":[
        "S\u00e2n bay qu\u1ed1c t\u1ebf Ia\u0219i"
    ],
    "name:zho_x_preferred":[
        "\u96c5\u897f"
    ],
    "oa:elevation_ft":"397",
    "oa:type":"medium_airport",
    "woe:hierarchy":{
        "country_id":23424933,
        "planet_id":1,
        "state_id":2346637
    },
    "wof:name":"Iasi North Airport",
    "wof:placetype":"campus"
},
  "geometry": {"coordinates":[27.6206,47.178501],"type":"Point"}
}