{
  "type": "Feature",
  "properties": {
    "gn:admin1_code":"35.0",
    "gn:asciiname":"Drimiopsis",
    "gn:dem":1532,
    "gn:feature_class":"P",
    "gn:feature_code":"PPL",
    "gn:name":"Drimiopsis",
    "gn:population":0,
    "gn:timezone":"Africa/Windhoek",
    "wof:name":"Drimiopsis",
    "wof:placetype":"locality"
},
  "geometry": {"coordinates":[19.05,-22.08333],"type":"Point"}
}