{
  "type": "Feature",
  "properties": {
    "gn:admin1_code":"35.0",
    "gn:asciiname":"Drimiopsis",
    "gn:dem":1532,
    "gn:feature_class":"P",
    "gn:feature_code":"PPL",
    "gn:name":"Drimiopsis",
    "gn:population":0,
    "gn:timezone":"Africa/Windhoek",
    "name:ceb_x_preferred":[
        "Drimiopsis"
    ],
    "name:nld_x_preferred":[
        "Drimiopsis"
    ],
    "name:por_x_preferred":[
        "Drimiopsis"
    ],
    "name:rus_x_preferred":[
        "\u0414\u0440\u0438\u043c\u0438\u043e\u043f\u0441\u0438\u0441"
    ],
    "name:spa_x_preferred":[
        "Drimiopsis"
    ],
    "name:swe_x_preferred":[
        "Drimiopsis"
    ],
    "name:vie_x_preferred":[
        "Drimiopsis"
    ],
    "name:war_x_preferred":[
        "Drimiopsis"
    ],
    "wof:name":"Drimiopsis",
    "wof:placetype":"locality"
},
  "geometry": {"coordinates":[19.05,-22.08333],"type":"Point"}
}