{
  "type": "Feature",
  "properties": {
    "name:eng_x_variant":[
        "EWY"
    ],
    "oa:elevation_ft":"400",
    "oa:type":"closed",
    "woe:hierarchy":{
        "country_id":23424975,
        "county_id":26821262,
        "localadmin_id":12696165,
        "planet_id":1,
        "state_id":24554868
    },
    "wof:name":"Greenham Common Airport",
    "wof:placetype":"campus"
},
  "geometry": {"coordinates":[-1.281,51.379],"type":"Point"}
}