{
  "type": "Feature",
  "properties": {
    "name:ceb_x_preferred":[
        "Batken Airport"
    ],
    "name:eng_x_preferred":[
        "Batken Airport"
    ],
    "name:jpn_x_preferred":[
        "\u30d0\u30c8\u30b1\u30f3\u7a7a\u6e2f"
    ],
    "name:msa_x_preferred":[
        "Lapangan Terbang Batken"
    ],
    "name:pol_x_preferred":[
        "Port lotniczy Batken"
    ],
    "name:ron_x_preferred":[
        "Aeroportul Batken"
    ],
    "name:rus_x_preferred":[
        "\u0411\u0430\u0442\u043a\u0435\u043d"
    ],
    "name:spa_x_preferred":[
        "Aeropuerto de Batken"
    ],
    "name:swe_x_preferred":[
        "Batkenskij aeroport"
    ],
    "name:ukr_x_preferred":[
        "\u0411\u0430\u0442\u043a\u0435\u043d"
    ],
    "name:zho_x_preferred":[
        "\u5df4\u7279\u80af"
    ],
    "oa:elevation_ft":"3517",
    "oa:type":"medium_airport",
    "wd:wordcount":193,
    "woe:hierarchy":{
        "country_id":23424864,
        "planet_id":1,
        "state_id":20070196
    },
    "wof:name":"Batken Airport",
    "wof:placetype":"campus"
},
  "geometry": {"coordinates":[70.83805556,40.0425],"type":"Point"}
}