{
  "type": "Feature",
  "properties": {
    "gn:admin1_code":"17.0",
    "gn:asciiname":"Anelda Woonstel",
    "gn:dem":16,
    "gn:feature_class":"P",
    "gn:feature_code":"PPL",
    "gn:name":"Anelda Woonstel",
    "gn:population":0,
    "gn:timezone":"Africa/Windhoek",
    "wof:name":"Anelda Woonstel",
    "wof:placetype":"locality"
},
  "geometry": {"coordinates":[14.53048,-22.64053],"type":"Point"}
}