{
  "type": "Feature",
  "properties": {
    "gn:admin1_code":"30.0",
    "gn:asciiname":"Schlip",
    "gn:dem":1334,
    "gn:feature_class":"P",
    "gn:feature_code":"PPL",
    "gn:name":"Schlip",
    "gn:population":0,
    "gn:timezone":"Africa/Windhoek",
    "wof:name":"Schlip",
    "wof:placetype":"locality"
},
  "geometry": {"coordinates":[17.16667,-24.03333],"type":"Point"}
}