{
  "type": "Feature",
  "properties": {
    "name:ceb_x_preferred":[
        "Festus Memorial Airport"
    ],
    "name:eng_x_preferred":[
        "Festus Memorial Airport"
    ],
    "name:ron_x_preferred":[
        "Aeroportul Festus Memorial"
    ],
    "name:urd_x_preferred":[
        "\u0641\u06cc\u0633\u0679\u0633 \u0645\u06cc\u0645\u0648\u0631\u06cc\u0644 \u06c1\u0648\u0627\u0626\u06cc \u0627\u0688\u0627"
    ],
    "oa:elevation_ft":"433",
    "oa:type":"small_airport",
    "wd:wordcount":253,
    "woe:hierarchy":{
        "country_id":23424977,
        "county_id":12589015,
        "planet_id":1,
        "state_id":2347584
    },
    "wof:name":"Festus Memorial Airport",
    "wof:placetype":"campus"
},
  "geometry": {"coordinates":[-90.3856,38.195],"type":"Point"}
}