{
  "type": "Feature",
  "properties": {
    "name:ceb_x_preferred":[
        "Colonel Hill Airport"
    ],
    "name:eng_x_preferred":[
        "Colonel Hill Airport"
    ],
    "name:eng_x_variant":[
        "CRI",
        "MYCI"
    ],
    "name:fas_x_preferred":[
        "\u0641\u0631\u0648\u062f\u06af\u0627\u0647 \u06a9\u0648\u0644\u0646\u0644 \u0647\u06cc\u0644"
    ],
    "name:jpn_x_preferred":[
        "\u30b3\u30ed\u30cd\u30eb\u30fb\u30d2\u30eb\u7a7a\u6e2f"
    ],
    "name:msa_x_preferred":[
        "Lapangan Terbang Colonel Hill"
    ],
    "name:pol_x_preferred":[
        "Port lotniczy Colonel Hill"
    ],
    "name:swe_x_preferred":[
        "Colonel Hill Airport"
    ],
    "name:tgk_x_preferred":[
        "\u0424\u0443\u0440\u0443\u0434\u0433\u043e\u04b3\u0438 \u043a\u0443\u043b\u043d\u043b \u04b3\u0438\u043b"
    ],
    "name:zho_x_preferred":[
        "Colonel Hill\u6a5f\u5834"
    ],
    "oa:elevation_ft":"5",
    "oa:type":"medium_airport",
    "wd:wordcount":41,
    "woe:hierarchy":{
        "country_id":23424758,
        "planet_id":1,
        "state_id":24551238
    },
    "wof:name":"Colonel Hill Airport",
    "wof:placetype":"campus"
},
  "geometry": {"coordinates":[-74.18240400000001,22.7456],"type":"Point"}
}