{
  "type": "Feature",
  "properties": {
    "name:eng_x_preferred":[
        "Rancho Del Oro"
    ],
    "wd:wordcount":35,
    "wof:name":"Rancho Del Oro",
    "wof:placetype":"neighbourhood"
},
  "geometry": {"coordinates":[-117.28897304305788,33.21493615083574],"type":"Point"}
}