{
  "type": "Feature",
  "properties": {
    "name:eng_x_preferred":[
        "Rancho Del Oro"
    ],
    "name:fra_x_preferred":[
        "Rancho Del Oro"
    ],
    "wd:wordcount":35,
    "wof:name":"Rancho Del Oro",
    "wof:placetype":"neighbourhood"
},
  "geometry": {"coordinates":[-117.288973,33.214936],"type":"Point"}
}