{
  "type": "Feature",
  "properties": {
    "name:eng_x_preferred":[
        "Bergen-Lafayette"
    ],
    "wof:name":"Bergen-Lafayette",
    "wof:placetype":"neighbourhood"
},
  "geometry": {"coordinates":[-74.06988873939414,40.71679013493122],"type":"Point"}
}