{
  "type": "Feature",
  "properties": {
    "name:ceb_x_preferred":[
        "Tjilik Riwut Airport"
    ],
    "name:deu_x_preferred":[
        "Flughafen Palangka Raya"
    ],
    "name:eng_x_preferred":[
        "Tjilik Riwut Airport"
    ],
    "name:eng_x_variant":[
        "PKY",
        "WAOP"
    ],
    "name:fas_x_preferred":[
        "\u0641\u0631\u0648\u062f\u06af\u0627\u0647 \u062a\u06cc\u0644\u06cc\u06a9 \u0631\u06cc\u0648\u0648\u062a"
    ],
    "name:fra_x_preferred":[
        "Tjilik Riwut Airport"
    ],
    "name:ind_x_preferred":[
        "Bandar Udara Tjilik Riwut"
    ],
    "name:jpn_x_preferred":[
        "\u30c8\u30a5\u30b8\u30ea\u30af\u30fb\u30ea\u30a6\u30c8\u30a5\u7a7a\u6e2f"
    ],
    "name:msa_x_preferred":[
        "Lapangan Terbang Tjilik Riwut"
    ],
    "name:pol_x_preferred":[
        "Port lotniczy Palangkaraya-Tjilik Riwut"
    ],
    "name:ron_x_preferred":[
        "Aeroportul Tjilik Riwut"
    ],
    "name:swe_x_preferred":[
        "Tjilik Riwut Airport"
    ],
    "name:tgk_x_preferred":[
        "\u0424\u0443\u0440\u0443\u0434\u0433\u043e\u04b3\u0438 \u0442\u0438\u043b\u0438\u043a \u0440\u044e\u0432\u0442"
    ],
    "name:vie_x_preferred":[
        "S\u00e2n bay Tjilik Riwut"
    ],
    "name:zho_x_preferred":[
        "\u5409\u5229\u91cc\u4e4c\u673a\u573a"
    ],
    "oa:elevation_ft":"82",
    "oa:type":"small_airport",
    "wd:wordcount":80,
    "woe:hierarchy":{
        "country_id":23424846,
        "county_id":56000089,
        "planet_id":1,
        "state_id":2345722
    },
    "wof:name":"Tjilik Riwut Airport",
    "wof:placetype":"campus"
},
  "geometry": {"coordinates":[113.943001,-2.22513],"type":"Point"}
}