{
  "type": "Feature",
  "properties": {
    "name:ceb_x_preferred":[
        "First Flight Airport"
    ],
    "name:eng_x_preferred":[
        "First Flight Airport"
    ],
    "name:eng_x_variant":[
        "FFA",
        "KFFA"
    ],
    "name:fas_x_preferred":[
        "\u0641\u0631\u0648\u062f\u06af\u0627\u0647 \u0641\u0631\u0633\u062a \u0641\u0644\u0627\u06cc\u062a"
    ],
    "name:heb_x_preferred":[
        "\u05e0\u05de\u05dc \u05d4\u05ea\u05e2\u05d5\u05e4\u05d4 \u05e4\u05e8\u05e1\u05d8 \u05e4\u05dc\u05d9\u05d9\u05d8"
    ],
    "name:jpn_x_preferred":[
        "\u30d5\u30a1\u30fc\u30b9\u30c8\u30d5\u30e9\u30a4\u30c8\u7a7a\u6e2f"
    ],
    "name:ron_x_preferred":[
        "Aeroportul First Flight"
    ],
    "name:tgk_x_preferred":[
        "\u0424\u0443\u0440\u0443\u0434\u0433\u043e\u04b3\u0438 \u0444\u0440\u0441\u0442\u043e\u0434\u043d \u0444\u043b\u043e\u0438\u0442"
    ],
    "name:urd_x_preferred":[
        "\u0641\u0631\u0633\u0679 \u0641\u0644\u0627\u0626\u06cc\u0679 \u06c1\u0648\u0627\u0626\u06cc \u0627\u0688\u0627"
    ],
    "name:zho_x_preferred":[
        "\u9996\u822a\u6a5f\u5834"
    ],
    "oa:elevation_ft":"13",
    "oa:type":"small_airport",
    "wd:wordcount":392,
    "woe:hierarchy":{
        "country_id":23424977,
        "county_id":12589401,
        "planet_id":1,
        "state_id":2347592
    },
    "wof:name":"First Flight Airport",
    "wof:placetype":"campus"
},
  "geometry": {"coordinates":[-75.671389,36.018333],"type":"Point"}
}