{
  "type": "Feature",
  "properties": {
    "name:eng_x_variant":[
        "HIG",
        "YHHY"
    ],
    "oa:type":"small_airport",
    "woe:hierarchy":{
        "country_id":23424977,
        "county_id":12589019,
        "planet_id":1,
        "state_id":2347584
    },
    "wof:name":"Higginsville Industrial Municipal Airport",
    "wof:placetype":"campus"
},
  "geometry": {"coordinates":[143.145996,-16.4244],"type":"Point"}
}