{
  "type": "Feature",
  "properties": {
    "gn:admin1_code":"33.0",
    "gn:asciiname":"Efinde",
    "gn:dem":1153,
    "gn:feature_class":"P",
    "gn:feature_code":"PPL",
    "gn:name":"Efinde",
    "gn:population":0,
    "gn:timezone":"Africa/Windhoek",
    "wof:name":"Efinde",
    "wof:placetype":"locality"
},
  "geometry": {"coordinates":[17.03333,-17.45],"type":"Point"}
}