{
  "type": "Feature",
  "properties": {
    "wof:name":"Miatorp",
    "wof:placetype":"neighbourhood"
},
  "geometry": {"coordinates":[12.71579086768732,56.01823532329335],"type":"Point"}
}