{
  "type": "Feature",
  "properties": {
    "name:deu_x_preferred":[
        "Marion County Airport"
    ],
    "name:ind_x_preferred":[
        "Bandar Udara Kabupaten Marion"
    ],
    "oa:elevation_ft":"92",
    "oa:type":"small_airport",
    "wd:wordcount":65,
    "woe:hierarchy":{
        "country_id":23424977,
        "county_id":12589832,
        "planet_id":1,
        "state_id":2347599
    },
    "wof:name":"Marion County Airport",
    "wof:placetype":"campus"
},
  "geometry": {"coordinates":[-79.3347,34.1811],"type":"Point"}
}