{
  "type": "Feature",
  "properties": {
    "name:ceb_x_preferred":[
        "Marion County Airport"
    ],
    "name:deu_x_preferred":[
        "Marion County Airport"
    ],
    "name:eng_x_preferred":[
        "Marion County Airport"
    ],
    "name:ind_x_preferred":[
        "Bandar Udara Kabupaten Marion"
    ],
    "name:urd_x_preferred":[
        "\u0645\u0627\u0631\u06cc\u0648\u0646 \u06a9\u0627\u0624\u0646\u0679\u06cc \u06c1\u0648\u0627\u0626\u06cc \u0627\u0688\u0627"
    ],
    "oa:elevation_ft":"92",
    "oa:type":"small_airport",
    "wd:wordcount":65,
    "woe:hierarchy":{
        "country_id":23424977,
        "county_id":12589832,
        "planet_id":1,
        "state_id":2347599
    },
    "wof:name":"Marion County Airport",
    "wof:placetype":"campus"
},
  "geometry": {"coordinates":[-79.3347,34.1811],"type":"Point"}
}