{
  "type": "Feature",
  "properties": {
    "name:ceb_x_preferred":[
        "Lucca / Tassignano Airport"
    ],
    "name:deu_x_preferred":[
        "Flugplatz Lucca"
    ],
    "name:eng_x_preferred":[
        "Lucca-Tassignano Airport"
    ],
    "name:eng_x_variant":[
        "LCV",
        "LIQL"
    ],
    "name:est_x_preferred":[
        "Lucca Tassignano lennujaam"
    ],
    "name:hun_x_preferred":[
        "Lucca rep\u00fcl\u0151t\u00e9r"
    ],
    "name:ita_x_preferred":[
        "Aeroporto di Lucca-Tassignano"
    ],
    "name:jpn_x_preferred":[
        "\u30eb\u30c3\u30ab\uff1d\u30bf\u30c3\u30b7\u30cb\u30e3\u30ce\u7a7a\u6e2f"
    ],
    "name:msa_x_preferred":[
        "Lapangan Terbang Tassignano"
    ],
    "name:nld_x_preferred":[
        "Lucca-Tassignano Airport"
    ],
    "name:ron_x_preferred":[
        "Aeroportul Lucca-Tassignano"
    ],
    "oa:elevation_ft":"39",
    "oa:type":"small_airport",
    "wd:wordcount":463,
    "woe:hierarchy":{
        "country_id":23424853,
        "county_id":12591888,
        "localadmin_id":12676401,
        "planet_id":1,
        "state_id":7153345
    },
    "wof:name":"Tassignano Airport",
    "wof:placetype":"campus"
},
  "geometry": {"coordinates":[10.5781,43.828201],"type":"Point"}
}