{
  "type": "Feature",
  "properties": {
    "gn:admin1_code":"33.0",
    "gn:asciiname":"Okauva",
    "gn:dem":1150,
    "gn:feature_class":"P",
    "gn:feature_code":"PPL",
    "gn:name":"Okauva",
    "gn:population":0,
    "gn:timezone":"Africa/Windhoek",
    "wof:name":"Okauva",
    "wof:placetype":"locality"
},
  "geometry": {"coordinates":[17.01667,-17.53333],"type":"Point"}
}