{
  "type": "Feature",
  "properties": {
    "name:eng_x_preferred":[
        "Monkey Mountain Airport"
    ],
    "name:eng_x_variant":[
        "MYM",
        "SYMM"
    ],
    "name:swe_x_preferred":[
        "Monkey Mountain Airport"
    ],
    "oa:elevation_ft":"1456",
    "oa:type":"small_airport",
    "wd:wordcount":52,
    "woe:hierarchy":{
        "country_id":23424836,
        "planet_id":1,
        "state_id":2345610
    },
    "wof:name":"Monkey Mountain Airport",
    "wof:placetype":"campus"
},
  "geometry": {"coordinates":[-59.6833,4.48333],"type":"Point"}
}