{
  "type": "Feature",
  "properties": {
    "name:cat_x_preferred":[
        "Aeroport de Chingozi"
    ],
    "name:deu_x_preferred":[
        "Flughafen Chingozi"
    ],
    "name:eng_x_preferred":[
        "Chingozi Airport"
    ],
    "name:eng_x_variant":[
        "TET",
        "FQTT"
    ],
    "name:fas_x_preferred":[
        "\u0641\u0631\u0648\u062f\u06af\u0627\u0647 \u0686\u06cc\u0646\u06af\u0648\u0632\u06cc"
    ],
    "name:fra_x_preferred":[
        "a\u00e9rodrome de Tete-Chingozi"
    ],
    "name:jpn_x_preferred":[
        "\u30c6\u30c6"
    ],
    "name:msa_x_preferred":[
        "Lapangan Terbang Chingozi"
    ],
    "name:pol_x_preferred":[
        "Port lotniczy Chingozi"
    ],
    "name:por_x_preferred":[
        "Aeroporto de Chingozi"
    ],
    "name:tgk_x_preferred":[
        "\u0424\u0443\u0440\u0443\u0434\u0433\u043e\u04b3\u0438 \u0447\u0438\u043d\u0433\u0443\u0437\u0438"
    ],
    "name:zho_x_preferred":[
        "\u592a\u7279"
    ],
    "oa:elevation_ft":"525",
    "oa:type":"medium_airport",
    "woe:hierarchy":{
        "country_id":23424902,
        "planet_id":1,
        "state_id":2346318
    },
    "wof:name":"Tete Chingozi Airport",
    "wof:placetype":"campus"
},
  "geometry": {"coordinates":[33.640202,-16.104799],"type":"Point"}
}