{
  "type": "Feature",
  "properties": {
    "name:ara_x_preferred":[
        "\u0645\u0637\u0627\u0631 \u0628\u064a\u0634\u0629 \u0627\u0644\u0645\u062d\u0644\u064a"
    ],
    "name:ceb_x_preferred":[
        "Bisha"
    ],
    "name:ckb_x_preferred":[
        "\u0641\u0695\u06c6\u06a9\u06d5\u062e\u0627\u0646\u06d5\u06cc \u0646\u0627\u0648\u062e\u06c6\u06cc\u06cc\u06cc \u0628\u06cc\u0634\u06d5"
    ],
    "name:eng_x_preferred":[
        "Bisha Domestic Airport"
    ],
    "name:eng_x_variant":[
        "BHH",
        "OEBH"
    ],
    "name:fas_x_preferred":[
        "\u0641\u0631\u0648\u062f\u06af\u0627\u0647 \u062f\u0627\u062e\u0644\u06cc \u0628\u06cc\u0634\u0647"
    ],
    "name:fra_x_preferred":[
        "a\u00e9roport de Bisha"
    ],
    "name:ind_x_preferred":[
        "Bandar Udara Domestik Bisha"
    ],
    "name:jpn_x_preferred":[
        "\u30d3\u30fc\u30b7\u30e3"
    ],
    "name:msa_x_preferred":[
        "Lapangan Terbang Bisha"
    ],
    "name:pol_x_preferred":[
        "Port lotniczy Bisza"
    ],
    "name:ron_x_preferred":[
        "Aeroportul Bisha Domestic"
    ],
    "name:rus_x_preferred":[
        "\u0411\u0438\u0448\u0430"
    ],
    "name:tgk_x_preferred":[
        "\u0424\u0443\u0440\u0443\u0434\u0433\u043e\u04b3\u0438 \u0434\u043e\u0445\u0438\u043b \u0431\u0438\u0448\u04b3"
    ],
    "name:urd_x_preferred":[
        "\u0628\u06cc\u0634\u06c1 \u062f\u0627\u062e\u0644\u06cc \u06c1\u0648\u0627\u0626\u06cc \u0627\u0688\u0627"
    ],
    "name:zho_x_preferred":[
        "\u6bd4\u6c99\u5821\u672c\u5730\u6a5f\u5834"
    ],
    "oa:elevation_ft":"3887",
    "oa:type":"medium_airport",
    "woe:hierarchy":{
        "country_id":23424938,
        "county_id":56120149,
        "planet_id":1,
        "state_id":2346955
    },
    "wof:name":"Bisha Airport",
    "wof:placetype":"campus"
},
  "geometry": {"coordinates":[42.620899,19.9844],"type":"Point"}
}