{
  "type": "Feature",
  "properties": {
    "name:eng_x_preferred":[
        "Gweru-Thornhill Air Base"
    ],
    "name:eng_x_variant":[
        "GWE",
        "FVTL"
    ],
    "name:jpn_x_preferred":[
        "\u30b0\u30a6\u30a7\u30eb\uff1d\u30c8\u30ed\u30f3\u30d2\u30eb\u7a7a\u8ecd\u57fa\u5730"
    ],
    "name:msa_x_preferred":[
        "Pengkalan Udara Thornhill"
    ],
    "name:tur_x_preferred":[
        "Gweru-Thornhill Hava Alan\u0131"
    ],
    "oa:elevation_ft":"4680",
    "oa:type":"medium_airport",
    "woe:hierarchy":{
        "country_id":23425004,
        "county_id":56048478,
        "planet_id":1,
        "state_id":2347811
    },
    "wof:name":"Thornhill Airport",
    "wof:placetype":"campus"
},
  "geometry": {"coordinates":[29.8619,-19.436399],"type":"Point"}
}