{
  "type": "Feature",
  "properties": {
    "gn:admin1_code":"21.0",
    "gn:asciiname":"Ongord Gotjari",
    "gn:dem":1751,
    "gn:feature_class":"P",
    "gn:feature_code":"PPL",
    "gn:name":"Ongord Gotjari",
    "gn:population":0,
    "gn:timezone":"Africa/Windhoek",
    "wof:name":"Ongord Gotjari",
    "wof:placetype":"locality"
},
  "geometry": {"coordinates":[17.65,-22.08333],"type":"Point"}
}