{
  "type": "Feature",
  "properties": {
    "gn:admin1_code":"40.0",
    "gn:asciiname":"Mbumbi",
    "gn:dem":1104,
    "gn:feature_class":"P",
    "gn:feature_code":"PPL",
    "gn:name":"Mbumbi",
    "gn:population":0,
    "gn:timezone":"Africa/Windhoek",
    "wof:name":"Mbumbi",
    "wof:placetype":"locality"
},
  "geometry": {"coordinates":[19.91667,-18.36667000000001],"type":"Point"}
}