{
  "type": "Feature",
  "properties": {
    "name:chi_x_preferred":[
        "Boswell\u7063\u6a5f\u5834"
    ],
    "name:eng_x_preferred":[
        "Boswell Bay Airport"
    ],
    "name:eng_x_variant":[
        "BSW",
        "AK97"
    ],
    "name:fas_x_preferred":[
        "\u0641\u0631\u0648\u062f\u06af\u0627\u0647 \u0628\u0627\u0632\u0648\u0644 \u0628\u06cc"
    ],
    "name:per_x_preferred":[
        "\u0641\u0631\u0648\u062f\u06af\u0627\u0647 \u0628\u0627\u0632\u0648\u0644 \u0628\u06cc"
    ],
    "name:rus_x_preferred":[
        "\u0411\u043e\u0441\u0443\u044d\u043b\u043b-\u0411\u0435\u0439"
    ],
    "name:tgk_x_preferred":[
        "\u0424\u0443\u0440\u0443\u0434\u0433\u043e\u04b3\u0438 \u0431\u043e\u0437\u0443\u043b \u0431\u0435"
    ],
    "oa:elevation_ft":"230",
    "oa:type":"small_airport",
    "wd:wordcount":153,
    "woe:hierarchy":{
        "country_id":23424977,
        "county_id":12587576,
        "planet_id":1,
        "state_id":2347560
    },
    "wof:name":"Boswell Bay Airport",
    "wof:placetype":"campus"
},
  "geometry": {"coordinates":[-146.145996,60.4231],"type":"Point"}
}