{
  "type": "Feature",
  "properties": {
    "gn:admin1_code":"29.0",
    "gn:asciiname":"Ovehotua",
    "gn:dem":1308,
    "gn:feature_class":"P",
    "gn:feature_code":"PPL",
    "gn:name":"Ovehotua",
    "gn:population":0,
    "gn:timezone":"Africa/Windhoek",
    "wof:name":"Ovehotua",
    "wof:placetype":"locality"
},
  "geometry": {"coordinates":[15.63333,-20.98333],"type":"Point"}
}