{
  "type": "Feature",
  "properties": {
    "name:eng_x_variant":[
        "HLB",
        "KHLB"
    ],
    "oa:elevation_ft":"973",
    "oa:type":"small_airport",
    "woe:hierarchy":{
        "country_id":23424977,
        "county_id":12588248,
        "planet_id":1,
        "state_id":2347573
    },
    "wof:name":"Hillenbrand Industries Airport",
    "wof:placetype":"campus"
},
  "geometry": {"coordinates":[-85.258301,39.344501],"type":"Point"}
}