{
  "type": "Feature",
  "properties": {
    "gn:admin1_code":"28.0",
    "gn:asciiname":"Matengu",
    "gn:dem":937,
    "gn:feature_class":"P",
    "gn:feature_code":"PPL",
    "gn:name":"Matengu",
    "gn:population":0,
    "gn:timezone":"Africa/Windhoek",
    "name:und_x_variant":[
        "Matengus",
        "Matengu"
    ],
    "wof:name":"Matengu",
    "wof:placetype":"locality"
},
  "geometry": {"coordinates":[23.93333,-18.16667],"type":"Point"}
}