{
  "type": "Feature",
  "properties": {
    "gn:admin1_code":"28.0",
    "gn:asciiname":"Yaka",
    "gn:dem":940,
    "gn:feature_class":"P",
    "gn:feature_code":"PPL",
    "gn:name":"Yaka",
    "gn:population":0,
    "gn:timezone":"Africa/Windhoek",
    "name:ceb_x_preferred":[
        "Yaka"
    ],
    "name:deu_x_preferred":[
        "Yaka"
    ],
    "name:fra_x_preferred":[
        "Yaka"
    ],
    "name:hrv_x_preferred":[
        "Yaka"
    ],
    "name:ita_x_preferred":[
        "Yaka"
    ],
    "name:swe_x_preferred":[
        "Yaka"
    ],
    "wof:name":"Yaka",
    "wof:placetype":"locality"
},
  "geometry": {"coordinates":[23.95,-18.11667000000001],"type":"Point"}
}