{
  "type": "Feature",
  "properties": {
    "name:ceb_x_preferred":[
        "Oban Airport"
    ],
    "name:deu_x_preferred":[
        "Flughafen Oban"
    ],
    "name:eng_x_preferred":[
        "Oban Airport"
    ],
    "name:eng_x_variant":[
        "OBN",
        "EGEO"
    ],
    "name:fas_x_preferred":[
        "\u0641\u0631\u0648\u062f\u06af\u0627\u0647 \u0627\u0648\u0628\u0627\u0646"
    ],
    "name:fra_x_preferred":[
        "A\u00e9rodrome d'Oban"
    ],
    "name:fra_x_variant":[
        "a\u00e9rodrome d'Oban"
    ],
    "name:jpn_x_preferred":[
        "\u30aa\u30fc\u30d0\u30f3\u7a7a\u6e2f"
    ],
    "name:msa_x_preferred":[
        "Lapangan Terbang North Connel"
    ],
    "name:pms_x_preferred":[
        "Oban Airport"
    ],
    "name:ron_x_preferred":[
        "Aeroportul Oban"
    ],
    "name:rus_x_preferred":[
        "\u041e\u0431\u0430\u043d"
    ],
    "name:swe_x_preferred":[
        "Oban Airport"
    ],
    "name:tgk_x_preferred":[
        "\u0424\u0443\u0440\u0443\u0434\u0433\u043e\u04b3\u0438 \u043e\u0432\u0431\u043e\u043d"
    ],
    "oa:elevation_ft":"20",
    "oa:type":"small_airport",
    "wd:wordcount":418,
    "woe:hierarchy":{
        "country_id":23424975,
        "county_id":12602207,
        "localadmin_id":12696185,
        "planet_id":1,
        "state_id":12578048
    },
    "wof:name":"Oban Connel Airport",
    "wof:placetype":"campus"
},
  "geometry": {"coordinates":[-5.39967,56.463501],"type":"Point"}
}