{
  "type": "Feature",
  "properties": {
    "wof:name":"Banglatown",
    "wof:placetype":"neighbourhood"
},
  "geometry": {"coordinates":[-83.06962032089436,42.4087305098446],"type":"Point"}
}