{
  "type": "Feature",
  "properties": {
    "oa:elevation_ft":"1089",
    "oa:type":"small_airport",
    "woe:hierarchy":{
        "country_id":23424810,
        "county_id":12582567,
        "localadmin_id":12606634,
        "planet_id":1,
        "state_id":20070499
    },
    "wof:name":"Most Airport",
    "wof:placetype":"campus"
},
  "geometry": {"coordinates":[13.6831,50.525],"type":"Point"}
}