{
  "type": "Feature",
  "properties": {
    "name:ast_x_preferred":[
        "Aeropuertu Matsapha"
    ],
    "name:ceb_x_preferred":[
        "Manzini - Matsapha Airport"
    ],
    "name:deu_x_preferred":[
        "Flughafen Matsapha"
    ],
    "name:eng_x_preferred":[
        "Matsapha Airport"
    ],
    "name:eng_x_variant":[
        "MTS",
        "FDMS"
    ],
    "name:fas_x_preferred":[
        "\u0641\u0631\u0648\u062f\u06af\u0627\u0647 \u0645\u0627\u062a\u0633\u0627\u067e\u0647\u0627"
    ],
    "name:fra_x_preferred":[
        "a\u00e9roport international de Matsapha"
    ],
    "name:ind_x_preferred":[
        "Bandar Udara Matsapha"
    ],
    "name:ita_x_preferred":[
        "Aeroporto di Matsapha"
    ],
    "name:jpn_x_preferred":[
        "\u30de\u30c4\u30a1\u30d1\u7a7a\u6e2f"
    ],
    "name:lit_x_preferred":[
        "Matsafos oro uostas"
    ],
    "name:msa_x_preferred":[
        "Lapangan Terbang Antarabangsa Matsapha"
    ],
    "name:nld_x_preferred":[
        "Matsapha Airport"
    ],
    "name:pol_x_preferred":[
        "Port lotniczy Matsapha"
    ],
    "name:ron_x_preferred":[
        "Aeroportul Matsapha"
    ],
    "name:rus_x_preferred":[
        "\u041c\u0430\u0442\u0441\u0430\u0444\u0430"
    ],
    "name:spa_x_preferred":[
        "Aeropuerto Matsapha"
    ],
    "name:swe_x_preferred":[
        "Matsapha Airport"
    ],
    "name:tgk_x_preferred":[
        "\u0424\u0443\u0440\u0443\u0434\u0433\u043e\u04b3\u0438 \u043c\u043e\u0442\u0441\u043e\u043f\u04b3\u043e"
    ],
    "name:ukr_x_preferred":[
        "\u041c\u0430\u0442\u0448\u0430\u0444\u0430"
    ],
    "name:vie_x_preferred":[
        "S\u00e2n bay Matsapha"
    ],
    "name:zho_x_preferred":[
        "\u66fc\u9f4a\u5c3c\u6a5f\u5834"
    ],
    "oa:elevation_ft":"2075",
    "oa:type":"medium_airport",
    "woe:hierarchy":{
        "country_id":23424993,
        "county_id":55921273,
        "planet_id":1,
        "state_id":20069892
    },
    "wof:name":"Matsapha International Airport",
    "wof:placetype":"campus"
},
  "geometry": {"coordinates":[31.307501,-26.528999],"type":"Point"}
}