{
  "type": "Feature",
  "properties": {
    "name:ceb_x_preferred":[
        "Stafsberg Airport"
    ],
    "name:eng_x_preferred":[
        "Hamar Airport"
    ],
    "name:eng_x_variant":[
        "HMR",
        "ENHA"
    ],
    "name:fas_x_preferred":[
        "\u0641\u0631\u0648\u062f\u06af\u0627\u0647 \u0627\u0633\u062a\u0627\u0641\u0633\u0628\u0631\u06af \u0647\u0627\u0645\u0627\u0631"
    ],
    "name:jpn_x_preferred":[
        "\u30cf\u30fc\u30de\u30eb\u7a7a\u6e2f"
    ],
    "name:msa_x_preferred":[
        "Lapangan Terbang Stafsberg"
    ],
    "name:nob_x_preferred":[
        "Hamar flyplass"
    ],
    "name:nor_x_preferred":[
        "Hamar flyplass"
    ],
    "name:swe_x_preferred":[
        "Hamars flygplats"
    ],
    "name:swe_x_variant":[
        "Hamar flygplats"
    ],
    "name:tgk_x_preferred":[
        "\u0424\u0443\u0440\u0443\u0434\u0433\u043e\u04b3\u0438 \u043e\u0441\u0442\u043e\u0444\u0441\u0431\u0440\u0433 \u04b3\u043e\u043c\u043e\u0440"
    ],
    "oa:elevation_ft":"713",
    "oa:type":"small_airport",
    "wd:wordcount":1629,
    "woe:hierarchy":{
        "country_id":23424910,
        "county_id":12592970,
        "planet_id":1,
        "state_id":2346389
    },
    "wof:name":"Hamar flyplass Stafsberg",
    "wof:placetype":"campus"
},
  "geometry": {"coordinates":[11.068,60.8181],"type":"Point"}
}