{
  "type": "Feature",
  "properties": {
    "name:ceb_x_preferred":[
        "Armidale Airport"
    ],
    "name:deu_x_preferred":[
        "Flughafen Armidale"
    ],
    "name:eng_x_preferred":[
        "Armidale Airport"
    ],
    "name:eng_x_variant":[
        "ARM",
        "YARM"
    ],
    "name:fas_x_preferred":[
        "\u0641\u0631\u0648\u062f\u06af\u0627\u0647 \u0622\u0631\u0645\u06cc\u062f\u0627\u0644"
    ],
    "name:fra_x_preferred":[
        "a\u00e9roport de Armidale"
    ],
    "name:fra_x_variant":[
        "a\u00e9roport d'Armidale"
    ],
    "name:ita_x_preferred":[
        "aeroporto di Armidale"
    ],
    "name:jpn_x_preferred":[
        "\u30a2\u30fc\u30df\u30c7\u30a4\u30eb\u7a7a\u6e2f"
    ],
    "name:msa_x_preferred":[
        "Lapangan Terbang Armidale"
    ],
    "name:nld_x_preferred":[
        "Armidale Airport"
    ],
    "name:ron_x_preferred":[
        "Aeroportul Armidale"
    ],
    "name:spa_x_preferred":[
        "Aeropuerto de Armidale"
    ],
    "name:swe_x_preferred":[
        "Armidale Airport"
    ],
    "name:tgk_x_preferred":[
        "\u0424\u0443\u0440\u0443\u0434\u0433\u043e\u04b3\u0438 \u043e\u0440\u043c\u0438\u0434\u043e\u043b"
    ],
    "name:zho_x_preferred":[
        "\u963f\u7c73\u4ee3\u723e\u6a5f\u5834"
    ],
    "oa:elevation_ft":"3556",
    "oa:type":"medium_airport",
    "wd:wordcount":632,
    "woe:hierarchy":{
        "country_id":23424748,
        "county_id":55863780,
        "planet_id":1,
        "state_id":2344700
    },
    "wof:name":"Armidale Airport",
    "wof:placetype":"campus"
},
  "geometry": {"coordinates":[151.61700400000001,-30.528099],"type":"Point"}
}