{
  "type": "Feature",
  "properties": {
    "name:ceb_x_preferred":[
        "For\u016bdg\u0101h-e L\u0101merd"
    ],
    "name:eng_x_preferred":[
        "Lamerd Airport"
    ],
    "name:eng_x_variant":[
        "LFM",
        "OISR"
    ],
    "name:fas_x_preferred":[
        "\u0641\u0631\u0648\u062f\u06af\u0627\u0647 \u0644\u0627\u0645\u0631\u062f"
    ],
    "name:fra_x_preferred":[
        "A\u00e9roport de Lamard"
    ],
    "name:hbs_x_preferred":[
        "Aerodrom Lamerd"
    ],
    "name:hrv_x_preferred":[
        "Zra\u010dna luka Lamerd"
    ],
    "name:ind_x_preferred":[
        "Bandar Udara Lamerd"
    ],
    "name:jpn_x_preferred":[
        "\u30e9\u30fc\u30de\u30eb\u30c9\u7a7a\u6e2f"
    ],
    "name:msa_x_preferred":[
        "Lapangan Terbang Lamerd"
    ],
    "name:pol_x_preferred":[
        "Port lotniczy Lamerd"
    ],
    "name:ron_x_preferred":[
        "Aeroportul Lamerd"
    ],
    "name:swe_x_preferred":[
        "For\u016bdg\u0101h-e L\u0101merd"
    ],
    "name:tur_x_preferred":[
        "Lamerd Havaliman\u0131"
    ],
    "name:zho_x_preferred":[
        "\u62c9\u9ed8\u723e\u5fb7"
    ],
    "oa:elevation_ft":"1337",
    "oa:type":"small_airport",
    "wd:wordcount":30,
    "woe:hierarchy":{
        "country_id":23424851,
        "planet_id":1,
        "state_id":2345772
    },
    "wof:name":"Lamerd Airport",
    "wof:placetype":"campus"
},
  "geometry": {"coordinates":[53.188801,27.3727],"type":"Point"}
}