{
  "type": "Feature",
  "properties": {
    "name:fas_x_preferred":[
        "\u0641\u0631\u0648\u062f\u06af\u0627\u0647 \u0627\u0633\u0648\u0648\u0628\u0648\u062f\u0646\u06cc"
    ],
    "name:ukr_x_preferred":[
        "\u0410\u0435\u0440\u043e\u043f\u043e\u0440\u0442 \u00ab\u0421\u0432\u043e\u0431\u043e\u0434\u043d\u0438\u0439\u00bb"
    ],
    "oa:elevation_ft":"600",
    "oa:type":"small_airport",
    "wd:wordcount":21,
    "woe:hierarchy":{
        "country_id":23424936,
        "county_id":12598001,
        "planet_id":1,
        "state_id":2346888
    },
    "wof:name":"Svobodny Airport",
    "wof:placetype":"campus"
},
  "geometry": {"coordinates":[128.09833333333,51.455],"type":"Point"}
}