{
  "type": "Feature",
  "properties": {
    "gn:admin1_code":"31.0",
    "gn:asciiname":"Rooi Veldskoen",
    "gn:dem":449,
    "gn:feature_class":"P",
    "gn:feature_code":"PPL",
    "gn:name":"Rooi Veldskoen",
    "gn:population":0,
    "gn:timezone":"Africa/Windhoek",
    "name:und_x_variant":[
        "Veldschoen",
        "Rooi Veldskoea",
        "Rooi Veldskoen"
    ],
    "wof:name":"Rooi Veldskoen",
    "wof:placetype":"locality"
},
  "geometry": {"coordinates":[19.83333,-28.46667],"type":"Point"}
}