{
  "type": "Feature",
  "properties": {
    "name:ceb_x_preferred":[
        "Skardu Airport"
    ],
    "name:eng_x_preferred":[
        "Skardu Airport"
    ],
    "name:fas_x_preferred":[
        "\u0641\u0631\u0648\u062f\u06af\u0627\u0647 \u0627\u0633\u06a9\u0627\u0631\u062f\u0648"
    ],
    "name:fra_x_preferred":[
        "KDU"
    ],
    "name:hin_x_preferred":[
        "\u0938\u094d\u0915\u0930\u094d\u0926\u0942 \u0939\u0935\u093e\u0908 \u0905\u0921\u094d\u0921\u093e"
    ],
    "name:jpn_x_preferred":[
        "\u30b9\u30ab\u30eb\u30c9\u30a5\u7a7a\u6e2f"
    ],
    "name:msa_x_preferred":[
        "Lapangan Terbang Skardu"
    ],
    "name:pnb_x_preferred":[
        "\u0633\u06a9\u0631\u062f\u0648 \u0627\u06cc\u0626\u0631 \u067e\u0648\u0631\u0679"
    ],
    "name:pol_x_preferred":[
        "Port lotniczy Skardu"
    ],
    "name:ron_x_preferred":[
        "Aeroportul Skardu"
    ],
    "name:rus_x_preferred":[
        "\u0421\u043a\u0430\u0440\u0434\u0443"
    ],
    "name:tgk_x_preferred":[
        "\u0424\u0443\u0440\u0443\u0434\u0433\u043e\u04b3\u0438 \u043e\u0441\u043a\u043e\u0440\u0434\u0443"
    ],
    "name:urd_x_preferred":[
        "\u0633\u06a9\u0631\u062f\u0648 \u06c1\u0648\u0627\u0626\u06cc \u0627\u0688\u0627"
    ],
    "name:zho_x_preferred":[
        "\u65af\u5361\u675c\u673a\u573a"
    ],
    "oa:elevation_ft":"7316",
    "oa:type":"medium_airport",
    "wd:wordcount":187,
    "woe:hierarchy":{
        "country_id":23424848,
        "county_id":12586457,
        "planet_id":1,
        "state_id":2345746
    },
    "wof:name":"Skardu Airport",
    "wof:placetype":"campus"
},
  "geometry": {"coordinates":[75.536111111111,35.335555555556],"type":"Point"}
}