{
  "type": "Feature",
  "properties": {
    "name:ara_x_preferred":[
        "\u0645\u0637\u0627\u0631 \u0642\u0627\u0644\u064a\u0648\u0631"
    ],
    "name:ben_x_preferred":[
        "\u0997\u09cb\u09af\u09bc\u09be\u09b2\u09bf\u09af\u09bc\u09b0 \u09ac\u09bf\u09ae\u09be\u09a8\u09ac\u09a8\u09cd\u09a6\u09b0"
    ],
    "name:ceb_x_preferred":[
        "Gwalior Airport"
    ],
    "name:deu_x_preferred":[
        "Flughafen Gwalior"
    ],
    "name:eng_x_preferred":[
        "Gwalior Airport"
    ],
    "name:eng_x_variant":[
        "GWL",
        "VIGR"
    ],
    "name:fas_x_preferred":[
        "\u0641\u0631\u0648\u062f\u06af\u0627\u0647 \u06af\u0648\u0627\u0644\u06cc\u0648\u0631"
    ],
    "name:hin_x_preferred":[
        "\u0917\u094d\u0935\u093e\u0932\u093f\u092f\u0930 \u0935\u093f\u092e\u093e\u0928\u0915\u094d\u0937\u0947\u0924\u094d\u0930"
    ],
    "name:jpn_x_preferred":[
        "\u30b0\u30ef\u30fc\u30ea\u30e4\u30eb\u7a7a\u6e2f"
    ],
    "name:mar_x_preferred":[
        "\u0917\u094d\u0935\u093e\u0932\u094d\u0939\u0947\u0930 \u0935\u093f\u092e\u093e\u0928\u0924\u0933"
    ],
    "name:msa_x_preferred":[
        "Lapangan Terbang Maharajpur AB"
    ],
    "name:msa_x_variant":[
        "Lapangan Terbang Maharajpur"
    ],
    "name:pol_x_preferred":[
        "Port lotniczy Gwalior"
    ],
    "name:ron_x_preferred":[
        "Aeroportul Gwalior"
    ],
    "name:swe_x_preferred":[
        "Gwalior Airport"
    ],
    "name:tam_x_preferred":[
        "\u0b95\u0bc1\u0bb5\u0bbe\u0bb2\u0bbf\u0baf\u0bb0\u0bcd \u0bb5\u0bbe\u0ba9\u0bc2\u0bb0\u0bcd\u0ba4\u0bbf \u0ba8\u0bbf\u0bb2\u0bc8\u0baf\u0bae\u0bcd"
    ],
    "name:tgk_x_preferred":[
        "\u0424\u0443\u0440\u0443\u0434\u0433\u043e\u04b3\u0438 \u0433\u0443\u043e\u043b\u044e\u0440"
    ],
    "name:vie_x_preferred":[
        "S\u00e2n bay Gwalior"
    ],
    "name:zho_x_preferred":[
        "\u74dc\u5ed6\u723e"
    ],
    "oa:elevation_ft":"617",
    "oa:type":"medium_airport",
    "woe:hierarchy":{
        "country_id":23424848,
        "county_id":12586494,
        "planet_id":1,
        "state_id":2345749
    },
    "wof:name":"Gwalior Airport",
    "wof:placetype":"campus"
},
  "geometry": {"coordinates":[78.22779800000001,26.293301],"type":"Point"}
}