{
  "type": "Feature",
  "properties": {
    "gn:admin1_code":"36.0",
    "gn:asciiname":"Omuthitugwonyama",
    "gn:dem":1115,
    "gn:feature_class":"P",
    "gn:feature_code":"PPL",
    "gn:name":"Omuthitugwonyama",
    "gn:population":0,
    "gn:timezone":"Africa/Windhoek",
    "wof:name":"Omuthitugwonyama",
    "wof:placetype":"locality"
},
  "geometry": {"coordinates":[15.26667,-17.51667],"type":"Point"}
}