{
  "type": "Feature",
  "properties": {
    "wof:name":"Rolling Green",
    "wof:placetype":"neighbourhood"
},
  "geometry": {"coordinates":[-88.01257269760185,42.97743629358678],"type":"Point"}
}