{
  "type": "Feature",
  "properties": {
    "gn:admin1_code":"36.0",
    "gn:asciiname":"Oshikiyu",
    "gn:dem":1108,
    "gn:feature_class":"P",
    "gn:feature_code":"PPL",
    "gn:name":"Oshikiyu",
    "gn:population":0,
    "gn:timezone":"Africa/Windhoek",
    "wof:name":"Oshikiyu",
    "wof:placetype":"locality"
},
  "geometry": {"coordinates":[15.13333,-17.55],"type":"Point"}
}