{
  "type": "Feature",
  "properties": {
    "gn:admin1_code":"21.0",
    "gn:asciiname":"Otjihase",
    "gn:dem":1877,
    "gn:feature_class":"P",
    "gn:feature_code":"PPL",
    "gn:name":"Otjihase",
    "gn:population":0,
    "gn:timezone":"Africa/Windhoek",
    "wof:name":"Otjihase",
    "wof:placetype":"locality"
},
  "geometry": {"coordinates":[17.24,-22.38556],"type":"Point"}
}