{
  "type": "Feature",
  "properties": {
    "name:ara_x_preferred":[
        "\u0645\u0637\u0627\u0631 \u0622\u0628\u0631\u0646\u0627\u0648\u064a\u0643"
    ],
    "name:ceb_x_preferred":[
        "Upernavik Airport"
    ],
    "name:dan_x_preferred":[
        "Upernavik Lufthavn"
    ],
    "name:deu_x_preferred":[
        "Flughafen Upernavik"
    ],
    "name:eng_x_preferred":[
        "Upernavik Airport"
    ],
    "name:eng_x_variant":[
        "JUV",
        "BGUK"
    ],
    "name:fas_x_preferred":[
        "\u0641\u0631\u0648\u062f\u06af\u0627\u0647 \u0622\u067e\u0631\u0646\u0627\u0648\u06cc\u06a9"
    ],
    "name:fra_x_preferred":[
        "a\u00e9roport d'Upernavik"
    ],
    "name:jpn_x_preferred":[
        "\u30a6\u30da\u30eb\u30ca\u30d3\u30af\u7a7a\u6e2f"
    ],
    "name:lav_x_preferred":[
        "Upernavikas lidosta"
    ],
    "name:msa_x_preferred":[
        "Lapangan Terbang Upernavik"
    ],
    "name:nob_x_preferred":[
        "Upernavik lufthavn"
    ],
    "name:pol_x_preferred":[
        "Port lotniczy Upernavik"
    ],
    "name:por_x_preferred":[
        "Aeroporto de Upernavik"
    ],
    "name:ron_x_preferred":[
        "Aeroportul Upernavik"
    ],
    "name:spa_x_preferred":[
        "Aeropuerto de Upernavik"
    ],
    "name:swe_x_preferred":[
        "Upernavik Airport"
    ],
    "name:tgk_x_preferred":[
        "\u0424\u0443\u0440\u0443\u0434\u0433\u043e\u04b3\u0438 \u043e\u043f\u0440\u043d\u043e\u0432\u0438\u043a"
    ],
    "name:zho_x_preferred":[
        "\u70cf\u57f9\u723e\u7d0d\u7dad\u514b\u6a5f\u5834"
    ],
    "oa:elevation_ft":"414",
    "oa:type":"small_airport",
    "woe:hierarchy":{
        "country_id":23424828,
        "planet_id":1,
        "state_id":20069858
    },
    "wof:name":"Upernavik Heliport",
    "wof:placetype":"campus"
},
  "geometry": {"coordinates":[-56.1306,72.790199],"type":"Point"}
}