{
  "type": "Feature",
  "properties": {
    "gn:admin1_code":"21.0",
    "gn:asciiname":"Heimat",
    "gn:dem":1452,
    "gn:feature_class":"P",
    "gn:feature_code":"PPL",
    "gn:name":"Heimat",
    "gn:population":0,
    "gn:timezone":"Africa/Windhoek",
    "name:bar_x_preferred":[
        "Hoamat"
    ],
    "name:cat_x_preferred":[
        "Heimat"
    ],
    "name:deu_x_preferred":[
        "Heimat"
    ],
    "name:fra_x_preferred":[
        "Heimat"
    ],
    "name:heb_x_preferred":[
        "\u05de\u05d5\u05dc\u05d3\u05ea"
    ],
    "name:hin_x_preferred":[
        "\u092e\u093e\u0924\u0943\u092d\u0942\u092e\u093f"
    ],
    "name:hrv_x_preferred":[
        "Domovina"
    ],
    "name:ido_x_preferred":[
        "Patrio"
    ],
    "name:ita_x_preferred":[
        "Heimat"
    ],
    "name:ltz_x_preferred":[
        "Heemecht"
    ],
    "name:nep_x_preferred":[
        "\u092e\u093e\u0924\u0943\u092d\u0942\u092e\u093f"
    ],
    "name:nld_x_preferred":[
        "Heimat"
    ],
    "name:pdc_x_preferred":[
        "Heemet"
    ],
    "name:swe_x_preferred":[
        "Hembygd"
    ],
    "name:tam_x_preferred":[
        "\u0bae\u0bb0\u0baa\u0bc1\u0bb5\u0bb4\u0bbf\u0ba4\u0bcd \u0ba4\u0bbe\u0baf\u0b95\u0bae\u0bcd"
    ],
    "name:tgl_x_preferred":[
        "Bayang sinilangan"
    ],
    "wof:name":"Heimat",
    "wof:placetype":"locality"
},
  "geometry": {"coordinates":[17.98333,-22.91667],"type":"Point"}
}