{
  "type": "Feature",
  "properties": {
    "gn:admin1_code":"21.0",
    "gn:asciiname":"Heimat",
    "gn:dem":1452,
    "gn:feature_class":"P",
    "gn:feature_code":"PPL",
    "gn:name":"Heimat",
    "gn:population":0,
    "gn:timezone":"Africa/Windhoek",
    "wof:name":"Heimat",
    "wof:placetype":"locality"
},
  "geometry": {"coordinates":[17.98333,-22.91667],"type":"Point"}
}