{
  "type": "Feature",
  "properties": {
    "gn:admin1_code":"32.0",
    "gn:asciiname":"Okavakwa",
    "gn:dem":874,
    "gn:feature_class":"P",
    "gn:feature_code":"PPL",
    "gn:name":"Okavakwa",
    "gn:population":0,
    "gn:timezone":"Africa/Windhoek",
    "wof:name":"Okavakwa",
    "wof:placetype":"locality"
},
  "geometry": {"coordinates":[15.35,-20.51667],"type":"Point"}
}