{
  "type": "Feature",
  "properties": {
    "name:eng_x_preferred":[
        "Denver Harbor"
    ],
    "name:fra_x_preferred":[
        "Denver Harbor"
    ],
    "name:nld_x_preferred":[
        "Denver Harbor"
    ],
    "name:spa_x_preferred":[
        "Denver Harbor"
    ],
    "wd:wordcount":1595,
    "wof:name":"Denver Harbor/Port Houston",
    "wof:placetype":"neighbourhood"
},
  "geometry": {"coordinates":[-95.296944,29.76879],"type":"Point"}
}