{
  "type": "Feature",
  "properties": {
    "name:ceb_x_preferred":[
        "Port Hope Simpson Airport"
    ],
    "name:eng_x_preferred":[
        "Port Hope Simpson Airport"
    ],
    "name:eng_x_variant":[
        "YHA",
        "CCP4"
    ],
    "name:fas_x_preferred":[
        "\u0641\u0631\u0648\u062f\u06af\u0627\u0647 \u067e\u0648\u0631\u062a \u0647\u0648\u067e \u0633\u06cc\u0645\u067e\u0633\u0648\u0646"
    ],
    "name:fra_x_preferred":[
        "A\u00e9roport de Port Hope Simpson"
    ],
    "name:fra_x_variant":[
        "a\u00e9roport de Port Hope Simpson"
    ],
    "name:msa_x_preferred":[
        "Lapangan Terbang Port Hope Simpson"
    ],
    "name:pms_x_preferred":[
        "Port Hope Simpson Airport"
    ],
    "name:ron_x_preferred":[
        "Aeroportul Port Hope Simpson"
    ],
    "name:swe_x_preferred":[
        "Port Hope Simpson Airport"
    ],
    "name:tgk_x_preferred":[
        "\u0424\u0443\u0440\u0443\u0434\u0433\u043e\u04b3\u0438 \u043f\u04ef\u0440 \u04b3\u0443\u043f \u0441\u0438\u043c\u043f\u0441\u0443\u043d"
    ],
    "oa:elevation_ft":"347",
    "oa:type":"small_airport",
    "woe:hierarchy":{
        "country_id":23424775,
        "county_id":29375216,
        "planet_id":1,
        "state_id":2344919
    },
    "wof:name":"Port Hope Simpson Aerodrome",
    "wof:placetype":"campus"
},
  "geometry": {"coordinates":[-56.286098,52.528099],"type":"Point"}
}