{
  "type": "Feature",
  "properties": {
    "name:ceb_x_preferred":[
        "Portland Municipal Airport"
    ],
    "name:eng_x_preferred":[
        "Portland Municipal Airport"
    ],
    "name:ron_x_preferred":[
        "Aeroportul Municipal Portland"
    ],
    "name:urd_x_preferred":[
        "\u067e\u0648\u0631\u0679\u0644\u06cc\u0646\u0688 \u0645\u06cc\u0648\u0646\u0633\u067e\u0644 \u0627\u06cc\u0626\u0631\u067e\u0648\u0631\u0679"
    ],
    "oa:elevation_ft":"925",
    "oa:type":"small_airport",
    "wd:wordcount":105,
    "woe:hierarchy":{
        "country_id":23424977,
        "county_id":12588217,
        "planet_id":1,
        "state_id":2347573
    },
    "wof:name":"Portland Municipal Airport",
    "wof:placetype":"campus"
},
  "geometry": {"coordinates":[-84.9889,40.4517],"type":"Point"}
}