{
  "type": "Feature",
  "properties": {
    "name:eng_x_preferred":[
        "Buona Vista"
    ],
    "name:ind_x_preferred":[
        "Buona Vista"
    ],
    "name:jpn_x_preferred":[
        "\u30d6\u30aa\u30ca\u30fb\u30d3\u30b9\u30bf"
    ],
    "name:mar_x_preferred":[
        "\u092c\u0941\u0913\u0928\u093e \u0935\u093f\u0938\u094d\u091f\u093e"
    ],
    "name:msa_x_preferred":[
        "Buona Vista"
    ],
    "name:ukr_x_preferred":[
        "\u0411\u0443\u043e\u043d\u0430-\u0412\u0456\u0441\u0442\u0430"
    ],
    "name:zho_x_preferred":[
        "\u6ce2\u5a1c\u7ef4\u65af\u8fbe"
    ],
    "qs:name":"Buona Vista",
    "qs:name_adm0":"Singapore",
    "qs:name_adm1":"South West",
    "qs:photos":1172,
    "qs:photos_1k":237,
    "qs:photos_9k":5,
    "qs:photos_9r":7,
    "qs:photos_all":1172,
    "qs:photos_sr":11,
    "qs:placetype":"Town",
    "qs:pop_sr":"0",
    "wd:wordcount":276,
    "wof:name":"Buona Vista",
    "wof:placetype":"locality"
},
  "geometry": {"coordinates":[103.77668300000001,1.278277],"type":"Point"}
}