{
  "type": "Feature",
  "properties": {
    "qs:name":"Buona Vista",
    "qs:name_adm0":"Singapore",
    "qs:name_adm1":"South West",
    "qs:photos":1172,
    "qs:photos_1k":237,
    "qs:photos_9k":5,
    "qs:photos_9r":7,
    "qs:photos_all":1172,
    "qs:photos_sr":11,
    "qs:placetype":"Town",
    "qs:pop_sr":"0",
    "wd:wordcount":276,
    "wof:name":"Buona Vista",
    "wof:placetype":"locality"
},
  "geometry": {"coordinates":[103.77668300000001,1.278277],"type":"Point"}
}