{
  "type": "Feature",
  "properties": {
    "name:fra_x_preferred":[
        "Pier Head"
    ],
    "name:pol_x_preferred":[
        "Pier Head"
    ],
    "name:spa_x_preferred":[
        "Pier Head"
    ],
    "name:zho_x_preferred":[
        "\u76ae\u723e\u5e0c\u5fb7"
    ],
    "wd:wordcount":1680,
    "wof:name":"Pier Head",
    "wof:placetype":"neighbourhood"
},
  "geometry": {"coordinates":[-2.99665507880057,53.40504489571063],"type":"Point"}
}