{
  "type": "Feature",
  "properties": {
    "name:ara_x_preferred":[
        "\u0642\u0627\u0639\u062f\u0629 \u0625\u0646\u062c\u0631\u0644\u064a\u0643 \u0627\u0644\u062c\u0648\u064a\u0629"
    ],
    "name:aze_x_preferred":[
        "\u0130ncirlik H\u0259rbi Hava Bazas\u0131"
    ],
    "name:bul_x_preferred":[
        "\u0412\u043e\u0435\u043d\u043d\u043e\u0432\u044a\u0437\u0434\u0443\u0448\u043d\u0430 \u0431\u0430\u0437\u0430 \u0418\u043d\u0434\u0436\u0438\u0440\u043b\u0438\u043a"
    ],
    "name:cat_x_preferred":[
        "Base a\u00e8ria d'\u0130ncirlik"
    ],
    "name:deu_x_preferred":[
        "Incirlik Air Base"
    ],
    "name:fas_x_preferred":[
        "\u067e\u0627\u06cc\u06af\u0627\u0647 \u0647\u0648\u0627\u06cc\u06cc \u0627\u06cc\u0646\u062c\u0631\u0644\u06cc\u06a9"
    ],
    "name:fin_x_preferred":[
        "Incirlikin lentotukikohta"
    ],
    "name:fra_x_preferred":[
        "Incirlik Air Base"
    ],
    "name:heb_x_preferred":[
        "\u05d1\u05e1\u05d9\u05e1 \u05d7\u05d9\u05dc \u05d4\u05d0\u05d5\u05d5\u05d9\u05e8 \u05d0\u05d9\u05e0\u05d2'\u05d9\u05e8\u05dc\u05d9\u05e7"
    ],
    "name:hun_x_preferred":[
        "\u0130ncirlik l\u00e9git\u00e1maszpont"
    ],
    "name:ita_x_preferred":[
        "Base aerea di Incirlik"
    ],
    "name:kor_x_preferred":[
        "\uc778\uc2dc\ub97c\ub9ad \uacf5\uad70 \uae30\uc9c0"
    ],
    "name:nor_x_preferred":[
        "Incirlik Air Base"
    ],
    "name:por_x_preferred":[
        "Base A\u00e9rea de \u0130ncirlik"
    ],
    "name:rus_x_preferred":[
        "\u0411\u0430\u0437\u0430 \u0412\u0412\u0421 \u0421\u0428\u0410 \u0418\u043d\u0434\u0436\u0438\u0440\u043b\u0438\u043a"
    ],
    "name:spa_x_preferred":[
        "Base \u00e1erea de Incirlik"
    ],
    "name:tgk_x_preferred":[
        "\u041f\u043e\u0439\u0433\u043e\u04b3\u0438 \u04b3\u0430\u0432\u043e\u0438\u0438 \u0418\u043d\u04b7\u0438\u0440\u043b\u0438\u043a"
    ],
    "name:tur_x_preferred":[
        "\u0130ncirlik Hava \u00dcss\u00fc"
    ],
    "oa:elevation_ft":"238",
    "oa:type":"medium_airport",
    "wd:wordcount":2912,
    "woe:hierarchy":{
        "country_id":23424969,
        "county_id":29390905,
        "planet_id":1,
        "state_id":2347258
    },
    "wof:name":"Incirlik Air Base",
    "wof:placetype":"campus"
},
  "geometry": {"coordinates":[35.425833333333,37.001944444444],"type":"Point"}
}