{
  "type": "Feature",
  "properties": {
    "name:ara_x_preferred":[
        "\u0645\u0637\u0627\u0631 \u063a\u0627\u062a"
    ],
    "name:ceb_x_preferred":[
        "Ghat"
    ],
    "name:deu_x_preferred":[
        "Flughafen Ghat"
    ],
    "name:eng_x_preferred":[
        "Ghat Airport"
    ],
    "name:eng_x_variant":[
        "GHT",
        "HLGT"
    ],
    "name:fra_x_preferred":[
        "GHT"
    ],
    "name:jpn_x_preferred":[
        "\u30ac\u30fc\u30c8\u7a7a\u6e2f"
    ],
    "name:kat_x_preferred":[
        "\u10e6\u10d0\u10d7\u10d8\u10e1 \u10d0\u10d4\u10e0\u10dd\u10de\u10dd\u10e0\u10e2\u10d8"
    ],
    "name:msa_x_preferred":[
        "Lapangan Terbang Ghat"
    ],
    "name:pol_x_preferred":[
        "Port lotniczy Ghat"
    ],
    "name:ron_x_preferred":[
        "Aeroportul Ghat"
    ],
    "name:spa_x_preferred":[
        "aeropuerto de Ghat"
    ],
    "name:swe_x_preferred":[
        "Ghat"
    ],
    "name:vie_x_preferred":[
        "S\u00e2n bay Ghat"
    ],
    "name:zho_x_preferred":[
        "\u52a0\u7279\u6a5f\u5834"
    ],
    "oa:elevation_ft":"2296",
    "oa:type":"medium_airport",
    "wd:wordcount":60,
    "woe:hierarchy":{
        "country_id":23424882,
        "planet_id":1,
        "state_id":2346135
    },
    "wof:name":"Ghat Airport",
    "wof:placetype":"campus"
},
  "geometry": {"coordinates":[10.1426,25.145599],"type":"Point"}
}