{
  "type": "Feature",
  "properties": {
    "name:deu_x_preferred":[
        "Flughafen Oscar Laranjeiras"
    ],
    "name:eng_x_preferred":[
        "Caruaru Airport"
    ],
    "name:eng_x_variant":[
        "CAU",
        "SNRU"
    ],
    "name:fas_x_preferred":[
        "\u0641\u0631\u0648\u062f\u06af\u0627\u0647 \u06a9\u0627\u0631\u0648\u0631\u0648"
    ],
    "name:jpn_x_preferred":[
        "\u30ab\u30eb\u30a2\u30eb\u7a7a\u6e2f"
    ],
    "name:msa_x_preferred":[
        "Lapangan Terbang Caruaru"
    ],
    "name:por_x_preferred":[
        "Aeroporto de Caruaru"
    ],
    "name:swe_x_preferred":[
        "Caruaru Airport"
    ],
    "name:tgk_x_preferred":[
        "\u0424\u0443\u0440\u0443\u0434\u0433\u043e\u04b3\u0438 \u043a\u043e\u0440\u0443\u0440\u0443"
    ],
    "name:zho_x_preferred":[
        "\u5361\u9b6f\u963f\u9b6f\u6a5f\u5834"
    ],
    "oa:elevation_ft":"1891",
    "oa:type":"small_airport",
    "wd:wordcount":157,
    "woe:hierarchy":{
        "country_id":23424768,
        "county_id":12580847,
        "planet_id":1,
        "state_id":2344860
    },
    "wof:name":"Aeroporto Caruaru",
    "wof:placetype":"campus"
},
  "geometry": {"coordinates":[-36.0135,-8.28239],"type":"Point"}
}