{
  "type": "Feature",
  "properties": {
    "name:ceb_x_preferred":[
        "Limnos Airport"
    ],
    "name:deu_x_preferred":[
        "Flughafen Limnos"
    ],
    "name:ell_x_preferred":[
        "\u039a\u03c1\u03b1\u03c4\u03b9\u03ba\u03cc\u03c2 \u0391\u03b5\u03c1\u03bf\u03bb\u03b9\u03bc\u03ad\u03bd\u03b1\u03c2 \u039b\u03ae\u03bc\u03bd\u03bf\u03c5 \u00ab\u0389\u03c6\u03b1\u03b9\u03c3\u03c4\u03bf\u03c2\u00bb"
    ],
    "name:eng_x_preferred":[
        "Lemnos International Airport"
    ],
    "name:eng_x_variant":[
        "LXS",
        "LGLM"
    ],
    "name:fas_x_preferred":[
        "\u0641\u0631\u0648\u062f\u06af\u0627\u0647 \u0628\u06cc\u0646\u200c\u0627\u0644\u0645\u0644\u0644\u06cc \u0644\u0645\u0646\u0632"
    ],
    "name:fin_x_preferred":[
        "L\u00edmnoksen kansainv\u00e4linen lentoasema"
    ],
    "name:fra_x_preferred":[
        "a\u00e9roport de Lemnos"
    ],
    "name:ind_x_preferred":[
        "Bandar Udara Internasional Lemnos"
    ],
    "name:jpn_x_preferred":[
        "\u30ea\u30e0\u30ce\u30b9\u56fd\u969b\u7a7a\u6e2f"
    ],
    "name:msa_x_preferred":[
        "Lapangan Terbang Limnos"
    ],
    "name:pol_x_preferred":[
        "Port lotniczy Lemnos"
    ],
    "name:ron_x_preferred":[
        "Aeroportul Interna\u021bional Lemnos"
    ],
    "name:spa_x_preferred":[
        "Aeropuerto Internacional de Lemnos"
    ],
    "name:swe_x_preferred":[
        "Limnos Airport"
    ],
    "name:tgk_x_preferred":[
        "\u0424\u0443\u0440\u0443\u0434\u0433\u043e\u04b3\u0438 \u0431\u0438\u043d\u200c\u0430\u043b\u043c\u0438\u043b\u0430\u043b\u04e3 \u043b\u043c\u043d\u0437"
    ],
    "name:tur_x_preferred":[
        "Limni Uluslararas\u0131 Havaliman\u0131"
    ],
    "name:ukr_x_preferred":[
        "\u041c\u0456\u0436\u043d\u0430\u0440\u043e\u0434\u043d\u0438\u0439 \u0430\u0435\u0440\u043e\u043f\u043e\u0440\u0442 \u041b\u0435\u043c\u043d\u043e\u0441"
    ],
    "name:vie_x_preferred":[
        "S\u00e2n bay qu\u1ed1c t\u1ebf Lemnos"
    ],
    "name:zho_x_preferred":[
        "\u5229\u59c6\u8afe\u65af\u5cf6"
    ],
    "oa:elevation_ft":"14",
    "oa:type":"small_airport",
    "woe:hierarchy":{
        "country_id":23424833,
        "county_id":12591133,
        "localadmin_id":24544062,
        "planet_id":1,
        "state_id":12577890
    },
    "wof:name":"Limnos Airport",
    "wof:placetype":"campus"
},
  "geometry": {"coordinates":[25.2363,39.917099],"type":"Point"}
}