{
  "type": "Feature",
  "properties": {
    "name:ara_x_preferred":[
        "\u0645\u0637\u0627\u0631 \u062c\u0648\u062f\u0628\u0648\u0631"
    ],
    "name:ben_x_preferred":[
        "\u09af\u09cb\u09a7\u09aa\u09c1\u09b0 \u09ac\u09bf\u09ae\u09be\u09a8\u09ac\u09a8\u09cd\u09a6\u09b0"
    ],
    "name:ceb_x_preferred":[
        "Jodhpur Airport"
    ],
    "name:cym_x_preferred":[
        "Maes Awyr Jodhpur"
    ],
    "name:deu_x_preferred":[
        "Flughafen Jodhpur"
    ],
    "name:eng_x_preferred":[
        "Jodhpur Airport"
    ],
    "name:eng_x_variant":[
        "JDH",
        "VIJO"
    ],
    "name:fas_x_preferred":[
        "\u0641\u0631\u0648\u062f\u06af\u0627\u0647 \u062c\u0648\u062f\u0627\u067e\u0648\u0631"
    ],
    "name:hin_x_preferred":[
        "\u091c\u094b\u0927\u092a\u0941\u0930 \u0939\u0935\u093e\u0908 \u0905\u0921\u094d\u0921\u093e"
    ],
    "name:jpn_x_preferred":[
        "\u30b8\u30e7\u30fc\u30c9\u30d7\u30eb\u7a7a\u6e2f"
    ],
    "name:mar_x_preferred":[
        "\u091c\u094b\u0927\u092a\u0942\u0930 \u0935\u093f\u092e\u093e\u0928\u0924\u0933"
    ],
    "name:msa_x_preferred":[
        "Lapangan Terbang Jodhpur AB"
    ],
    "name:msa_x_variant":[
        "Lapangan Terbang Jodhpur"
    ],
    "name:ori_x_preferred":[
        "\u0b2f\u0b4b\u0b27\u0b2a\u0b41\u0b30 \u0b0f\u0b5f\u0b3e\u0b30 \u0b2a\u0b4b\u0b30\u0b4d\u0b1f"
    ],
    "name:pol_x_preferred":[
        "Port lotniczy D\u017aodhpur"
    ],
    "name:ron_x_preferred":[
        "Aeroportul Jodhpur"
    ],
    "name:spa_x_preferred":[
        "Aeropuerto de Jodhpur"
    ],
    "name:swe_x_preferred":[
        "Jodhpur Airport"
    ],
    "name:tam_x_preferred":[
        "\u0b9c\u0bcb\u0ba4\u0bcd\u0baa\u0bc2\u0bb0\u0bcd \u0bb5\u0bbf\u0bae\u0bbe\u0ba9 \u0ba8\u0bbf\u0bb2\u0bc8\u0baf\u0bae\u0bcd"
    ],
    "name:tgk_x_preferred":[
        "\u0424\u0443\u0440\u0443\u0434\u0433\u043e\u04b3\u0438 \u04b7\u0443\u0434\u043e\u043f\u0443\u0440"
    ],
    "name:zho_x_preferred":[
        "\u7126\u7279\u5e03\u5c14\u673a\u573a"
    ],
    "oa:elevation_ft":"717",
    "oa:type":"medium_airport",
    "wd:wordcount":360,
    "woe:hierarchy":{
        "country_id":23424848,
        "county_id":12586667,
        "planet_id":1,
        "state_id":2345757
    },
    "wof:name":"Jodhpur Airport",
    "wof:placetype":"campus"
},
  "geometry": {"coordinates":[73.048889,26.251111],"type":"Point"}
}