{
  "type": "Feature",
  "properties": {
    "name:ceb_x_preferred":[
        "Bartica A Airport"
    ],
    "name:eng_x_preferred":[
        "Bartica Airport"
    ],
    "name:eng_x_variant":[
        "GFO",
        "SYBT"
    ],
    "name:pol_x_preferred":[
        "Port lotniczy Bartica"
    ],
    "name:ron_x_preferred":[
        "Aeroportul Bartica"
    ],
    "name:swe_x_preferred":[
        "Bartica A Airport"
    ],
    "oa:elevation_ft":"3",
    "oa:type":"small_airport",
    "wd:wordcount":53,
    "woe:hierarchy":{
        "country_id":23424836,
        "planet_id":1,
        "state_id":2345604
    },
    "wof:name":"Bartica Airport",
    "wof:placetype":"campus"
},
  "geometry": {"coordinates":[-58.6381,6.37477],"type":"Point"}
}