{
  "type": "Feature",
  "properties": {
    "qs:name":"\u65b0\u6771\u6d8c\u5751",
    "qs:name_adm0":"\u9999\u6e2f",
    "qs:name_adm1":"\u96e2\u5cf6",
    "qs:photos":4998,
    "qs:photos_1k":1000,
    "qs:photos_9k":22,
    "qs:photos_9r":14,
    "qs:photos_all":4998,
    "qs:photos_sr":24,
    "qs:placetype":"Town",
    "qs:pop_sr":"0",
    "wof:name":"\u65b0\u6771\u6d8c\u5751",
    "wof:placetype":"locality"
},
  "geometry": {"coordinates":[113.940614,22.288639],"type":"Point"}
}