{
  "type": "Feature",
  "properties": {
    "wof:name":"Mayfield Gardens",
    "wof:placetype":"neighbourhood"
},
  "geometry": {"coordinates":[77.06043739613744,28.4242820920615],"type":"Point"}
}