{
  "type": "Feature",
  "properties": {
    "wof:name":"Greenway/Upper Kirby",
    "wof:placetype":"neighbourhood"
},
  "geometry": {"coordinates":[-95.42995339888041,29.736158024287],"type":"Point"}
}