{
  "type": "Feature",
  "properties": {
    "name:dan_x_preferred":[
        "Hyllie"
    ],
    "name:deu_x_preferred":[
        "Hyllie"
    ],
    "name:eng_x_preferred":[
        "Hyllie"
    ],
    "name:lat_x_preferred":[
        "Hyllie"
    ],
    "name:nld_x_preferred":[
        "Hyllie"
    ],
    "name:nob_x_preferred":[
        "Hyllie"
    ],
    "name:spa_x_preferred":[
        "Hyllie"
    ],
    "name:swe_x_preferred":[
        "Hyllie"
    ],
    "name:zho_x_preferred":[
        "\u5e0c\u5c14\u8389\u533a"
    ],
    "wd:wordcount":103,
    "wof:name":"Hyllie",
    "wof:placetype":"neighbourhood"
},
  "geometry": {"coordinates":[12.959164,55.569752],"type":"Point"}
}