{
  "type": "Feature",
  "properties": {
    "name:dan_x_preferred":[
        "Hyllie"
    ],
    "name:eng_x_preferred":[
        "Hyllie"
    ],
    "name:lat_x_preferred":[
        "Hyllie"
    ],
    "name:nld_x_preferred":[
        "Hyllie"
    ],
    "name:swe_x_preferred":[
        "Hyllie"
    ],
    "wd:wordcount":103,
    "wof:name":"Hyllie",
    "wof:placetype":"neighbourhood"
},
  "geometry": {"coordinates":[12.9591639073159,55.56975209165207],"type":"Point"}
}