{
  "type": "Feature",
  "properties": {
    "name:ceb_x_preferred":[
        "Lensk Airport"
    ],
    "name:eng_x_preferred":[
        "Lensk Airport"
    ],
    "name:fas_x_preferred":[
        "\u0641\u0631\u0648\u062f\u06af\u0627\u0647 \u0644\u0646\u0632\u06a9"
    ],
    "name:jpn_x_preferred":[
        "\u30ec\u30f3\u30b9\u30af\u7a7a\u6e2f"
    ],
    "name:nld_x_preferred":[
        "Lensk"
    ],
    "name:pol_x_preferred":[
        "Port lotniczy Le\u0144sk"
    ],
    "name:ron_x_preferred":[
        "Aeroportul Lensk"
    ],
    "name:rus_x_preferred":[
        "\u041b\u0435\u043d\u0441\u043a"
    ],
    "name:tgk_x_preferred":[
        "\u0424\u0443\u0440\u0443\u0434\u0433\u043e\u04b3\u0438 \u043b\u043d\u0437\u043a"
    ],
    "name:ukr_x_preferred":[
        "\u041b\u0435\u043d\u0441\u044c\u043a"
    ],
    "name:zho_x_preferred":[
        "\u9023\u65af\u514b\u6a5f\u5834"
    ],
    "oa:elevation_ft":"801",
    "oa:type":"medium_airport",
    "wd:wordcount":129,
    "woe:hierarchy":{
        "country_id":23424936,
        "county_id":12597633,
        "planet_id":1,
        "state_id":2346881
    },
    "wof:name":"Lensk Airport",
    "wof:placetype":"campus"
},
  "geometry": {"coordinates":[114.82583333333,60.720555555556],"type":"Point"}
}