{
  "type": "Feature",
  "properties": {
    "name:ceb_x_preferred":[
        "Ayr Airport"
    ],
    "name:eng_x_preferred":[
        "Ayr Airport"
    ],
    "name:eng_x_variant":[
        "AYR",
        "YAYR"
    ],
    "name:msa_x_preferred":[
        "Lapangan Terbang Ayr"
    ],
    "name:ron_x_preferred":[
        "Aeroportul Ayr"
    ],
    "name:swe_x_preferred":[
        "Ayr Airport"
    ],
    "oa:elevation_ft":"41",
    "oa:type":"small_airport",
    "woe:hierarchy":{
        "country_id":23424748,
        "county_id":55864327,
        "planet_id":1,
        "state_id":2344702
    },
    "wof:name":"Ayr Airport",
    "wof:placetype":"campus"
},
  "geometry": {"coordinates":[147.33000000000001,-19.585],"type":"Point"}
}