{
  "type": "Feature",
  "properties": {
    "gn:admin1_code":"38.0",
    "gn:asciiname":"Wildernis",
    "gn:dem":1170,
    "gn:feature_class":"P",
    "gn:feature_code":"PPL",
    "gn:name":"Wildernis",
    "gn:population":0,
    "gn:timezone":"Africa/Windhoek",
    "wof:name":"Wildernis",
    "wof:placetype":"locality"
},
  "geometry": {"coordinates":[18.01667,-18.83333],"type":"Point"}
}