{
  "type": "Feature",
  "properties": {
    "name:fas_x_preferred":[
        "\u0641\u0631\u0648\u062f\u06af\u0627\u0647 \u0646\u0648\u0631\u06cc\u0644\u0633\u06a9 \u0648\u0627\u0644\u06a9"
    ],
    "name:rus_x_preferred":[
        "\u0412\u0430\u043b\u0451\u043a"
    ],
    "oa:elevation_ft":"108",
    "oa:type":"medium_airport",
    "wd:wordcount":27,
    "woe:hierarchy":{
        "country_id":23424936,
        "county_id":12597846,
        "planet_id":1,
        "state_id":20070524
    },
    "wof:name":"Valek Airport",
    "wof:placetype":"campus"
},
  "geometry": {"coordinates":[88.355,69.395],"type":"Point"}
}