{
  "type": "Feature",
  "properties": {
    "name:deu_x_preferred":[
        "Flughafen Mae Sot"
    ],
    "name:eng_x_preferred":[
        "Mae Sot Airport"
    ],
    "name:eng_x_variant":[
        "MAQ",
        "VTPM"
    ],
    "name:fas_x_preferred":[
        "\u0641\u0631\u0648\u062f\u06af\u0627\u0647 \u0645\u0627\u0626\u0647 \u0633\u0648\u062a"
    ],
    "name:ger_x_preferred":[
        "Flughafen Mae Sot"
    ],
    "name:ind_x_preferred":[
        "Bandar Udara Mae Sot"
    ],
    "name:jpn_x_preferred":[
        "\u30e1\u30fc\u30bd\u30fc\u30c8\u7a7a\u6e2f"
    ],
    "name:may_x_preferred":[
        "Lapangan Terbang Mae Sot Aero"
    ],
    "name:per_x_preferred":[
        "\u0641\u0631\u0648\u062f\u06af\u0627\u0647 \u0645\u0627\u0626\u0647 \u0633\u0648\u062a"
    ],
    "name:pol_x_preferred":[
        "Port lotniczy Mae Sot"
    ],
    "name:rus_x_preferred":[
        "\u041c\u044d\u0441\u043e\u0442"
    ],
    "name:tha_x_preferred":[
        "\u0e17\u0e48\u0e32\u0e2d\u0e32\u0e01\u0e32\u0e28\u0e22\u0e32\u0e19\u0e41\u0e21\u0e48\u0e2a\u0e2d\u0e14"
    ],
    "name:vie_x_preferred":[
        "S\u00e2n bay Mae Sot"
    ],
    "oa:elevation_ft":"690",
    "oa:type":"medium_airport",
    "wd:wordcount":86,
    "woe:hierarchy":{
        "country_id":23424960,
        "county_id":28340880,
        "planet_id":1,
        "state_id":2347135
    },
    "wof:name":"Mae Sot Airport",
    "wof:placetype":"campus"
},
  "geometry": {"coordinates":[98.545097,16.6999],"type":"Point"}
}