{
  "type": "Feature",
  "properties": {
    "gn:admin1_code":"36.0",
    "gn:asciiname":"Wakashamane",
    "gn:dem":1114,
    "gn:feature_class":"P",
    "gn:feature_code":"PPL",
    "gn:name":"Wakashamane",
    "gn:population":0,
    "gn:timezone":"Africa/Windhoek",
    "wof:name":"Wakashamane",
    "wof:placetype":"locality"
},
  "geometry": {"coordinates":[15.25,-17.38332999999999],"type":"Point"}
}