{
  "type": "Feature",
  "properties": {
    "gn:admin1_code":"28.0",
    "gn:asciiname":"Ngoma",
    "gn:dem":934,
    "gn:feature_class":"P",
    "gn:feature_code":"PPL",
    "gn:name":"Ngoma",
    "gn:population":0,
    "gn:timezone":"Africa/Windhoek",
    "name:deu_x_preferred":[
        "Ngoma"
    ],
    "name:jpn_x_preferred":[
        "\u30f3\u30b4\u30de"
    ],
    "name:und_x_variant":[
        "Koma"
    ],
    "wof:name":"Ngoma",
    "wof:placetype":"locality"
},
  "geometry": {"coordinates":[24.71667,-17.88332999999999],"type":"Point"}
}