{
  "type": "Feature",
  "properties": {
    "name:eng_x_variant":[
        "MFB",
        "SK-481"
    ],
    "oa:elevation_ft":"630",
    "oa:type":"small_airport",
    "woe:hierarchy":{
        "country_id":23424787,
        "county_id":26797669,
        "planet_id":1,
        "state_id":2345075
    },
    "wof:name":"Monfort Airport",
    "wof:placetype":"campus"
},
  "geometry": {"coordinates":[-69.75,0.633333],"type":"Point"}
}