{
  "type": "Feature",
  "properties": {
    "wof:name":"Yarra's Edge",
    "wof:placetype":"neighbourhood"
},
  "geometry": {"coordinates":[144.94550188611296,-37.82427341707475],"type":"Point"}
}