{
  "type": "Feature",
  "properties": {
    "name:ceb_x_preferred":[
        "Arapongas Airport"
    ],
    "name:deu_x_preferred":[
        "Flughafen Arapongas"
    ],
    "name:eng_x_preferred":[
        "Arapongas Airport"
    ],
    "name:eng_x_variant":[
        "APX",
        "SSOG"
    ],
    "name:fas_x_preferred":[
        "\u0641\u0631\u0648\u062f\u06af\u0627\u0647 \u0622\u0631\u0627\u067e\u0648\u0646\u06af\u0627\u0633"
    ],
    "name:fra_x_preferred":[
        "a\u00e9roport d'Arapongas"
    ],
    "name:jpn_x_preferred":[
        "\u30a2\u30e9\u30dd\u30f3\u30ac\u30b9\u7a7a\u6e2f"
    ],
    "name:msa_x_preferred":[
        "Lapangan Terbang Arapongas"
    ],
    "name:por_x_preferred":[
        "Aeroporto de Arapongas"
    ],
    "name:ron_x_preferred":[
        "Aeroportul Arapongas"
    ],
    "name:swe_x_preferred":[
        "Arapongas Airport"
    ],
    "name:tgk_x_preferred":[
        "\u0424\u0443\u0440\u0443\u0434\u0433\u043e\u04b3\u0438 \u043e\u0440\u043e\u043f\u0443\u043d\u0433\u043e\u0441"
    ],
    "name:zho_x_preferred":[
        "\u963f\u62c9\u84ec\u52a0\u65af\u6a5f\u5834"
    ],
    "oa:elevation_ft":"2599",
    "oa:type":"small_airport",
    "wd:wordcount":143,
    "woe:hierarchy":{
        "country_id":23424768,
        "county_id":12580418,
        "planet_id":1,
        "state_id":2344859
    },
    "wof:name":"Aeroporto Arapongas",
    "wof:placetype":"campus"
},
  "geometry": {"coordinates":[-51.491699,-23.3529],"type":"Point"}
}