{
  "type": "Feature",
  "properties": {
    "name:ara_x_preferred":[
        "\u0645\u0637\u0627\u0631 \u062c\u0648\u0644\u0648"
    ],
    "name:eng_x_preferred":[
        "Jolo Airport"
    ],
    "name:eng_x_variant":[
        "JOL",
        "RPMJ"
    ],
    "name:fas_x_preferred":[
        "\u0641\u0631\u0648\u062f\u06af\u0627\u0647 \u062c\u0648\u0644\u0648"
    ],
    "name:jpn_x_preferred":[
        "\u30db\u30ed\u7a7a\u6e2f"
    ],
    "name:msa_x_preferred":[
        "Lapangan Terbang Jolo"
    ],
    "name:ron_x_preferred":[
        "Aeroportul Jolo"
    ],
    "name:spa_x_preferred":[
        "Aeropuerto de Jol\u00f3"
    ],
    "name:tgk_x_preferred":[
        "\u0424\u0443\u0440\u0443\u0434\u0433\u043e\u04b3\u0438 \u04b7\u0443\u043b\u0443"
    ],
    "name:vie_x_preferred":[
        "S\u00e2n bay Jolo"
    ],
    "name:zho_x_preferred":[
        "\u7ea6\u9646\u673a\u573a"
    ],
    "oa:elevation_ft":"118",
    "oa:type":"medium_airport",
    "wd:wordcount":472,
    "woe:hierarchy":{
        "country_id":23424934,
        "county_id":2346713,
        "planet_id":1,
        "state_id":23424729
    },
    "wof:name":"Jolo Airport",
    "wof:placetype":"campus"
},
  "geometry": {"coordinates":[121.011002,6.05367],"type":"Point"}
}