{
  "type": "Feature",
  "properties": {
    "name:ceb_x_preferred":[
        "Ramona Airport"
    ],
    "name:eng_x_preferred":[
        "Ramona Airport"
    ],
    "name:eng_x_variant":[
        "KRNM"
    ],
    "name:fas_x_preferred":[
        "\u0641\u0631\u0648\u062f\u06af\u0627\u0647 \u0631\u0627\u0645\u0648\u0646\u0627"
    ],
    "name:jpn_x_preferred":[
        "\u30e9\u30e2\u30ca\u7a7a\u6e2f"
    ],
    "name:ron_x_preferred":[
        "Aeroportul Ramona"
    ],
    "name:spa_x_preferred":[
        "Aeropuerto de Ramona"
    ],
    "name:tgk_x_preferred":[
        "\u0424\u0443\u0440\u0443\u0434\u0433\u043e\u04b3\u0438 \u0440\u043e\u043c\u0443\u043d\u043e"
    ],
    "name:urd_x_preferred":[
        "\u0631\u0627\u0645\u0648\u0646\u0627 \u06c1\u0648\u0627\u0626\u06cc \u0627\u0688\u0627"
    ],
    "oa:elevation_ft":"1395",
    "oa:type":"small_airport",
    "wd:wordcount":375,
    "woe:hierarchy":{
        "country_id":23424977,
        "county_id":12587706,
        "planet_id":1,
        "state_id":2347563
    },
    "wof:name":"Ramona Airport",
    "wof:placetype":"campus"
},
  "geometry": {"coordinates":[-116.915278,33.039167],"type":"Point"}
}