{
  "type": "Feature",
  "properties": {
    "name:ceb_x_preferred":[
        "Sultan Muhammad Salahudin Airport"
    ],
    "name:eng_x_preferred":[
        "Bima Airport"
    ],
    "name:eng_x_variant":[
        "BMU",
        "WADB"
    ],
    "name:fas_x_preferred":[
        "\u0641\u0631\u0648\u062f\u06af\u0627\u0647 \u0628\u06cc\u0645\u0627"
    ],
    "name:ind_x_preferred":[
        "Bandar Udara Sultan Muhammad Salahudin"
    ],
    "name:jpn_x_preferred":[
        "\u30d3\u30de\u7a7a\u6e2f"
    ],
    "name:swe_x_preferred":[
        "Sultan Muhammad Salahudin Airport"
    ],
    "name:tgk_x_preferred":[
        "\u0424\u0443\u0440\u0443\u0434\u0433\u043e\u04b3\u0438 \u0411\u0438\u043c\u0430"
    ],
    "name:vie_x_preferred":[
        "S\u00e2n bay Bima"
    ],
    "name:zho_x_preferred":[
        "\u7a46\u7f55\u9ed8\u5fb7Salahudin\u8607\u4e39\u6a5f\u5834"
    ],
    "oa:elevation_ft":"3",
    "oa:type":"small_airport",
    "woe:hierarchy":{
        "country_id":23424846,
        "county_id":56000054,
        "planet_id":1,
        "state_id":2345726
    },
    "wof:name":"Mohammad Salahuddin Airport",
    "wof:placetype":"campus"
},
  "geometry": {"coordinates":[118.68699599999999,-8.53965],"type":"Point"}
}