{
  "type": "Feature",
  "properties": {
    "name:eng_x_preferred":[
        "Samb\u00fa Airport"
    ],
    "name:eng_x_variant":[
        "SAX",
        "PA-SAX"
    ],
    "name:jpn_x_preferred":[
        "\u30b5\u30e0\u30d6\u7a7a\u6e2f"
    ],
    "oa:elevation_ft":"32",
    "oa:type":"small_airport",
    "wd:wordcount":47,
    "woe:hierarchy":{
        "country_id":23424924,
        "county_id":26793100,
        "localadmin_id":26793354,
        "planet_id":1,
        "state_id":2346555
    },
    "wof:name":"Sambu Airport",
    "wof:placetype":"campus"
},
  "geometry": {"coordinates":[-78.199997,8.017],"type":"Point"}
}