{
  "type": "Feature",
  "properties": {
    "name:ceb_x_preferred":[
        "Noshahr Airport"
    ],
    "name:eng_x_preferred":[
        "Noshahr Airport"
    ],
    "name:fas_x_preferred":[
        "\u0641\u0631\u0648\u062f\u06af\u0627\u0647 \u0646\u0648\u0634\u0647\u0631"
    ],
    "name:fra_x_preferred":[
        "NSH"
    ],
    "name:hbs_x_preferred":[
        "Aerodrom Nov\u0161aher"
    ],
    "name:hrv_x_preferred":[
        "Zra\u010dna luka Nov\u0161aher"
    ],
    "name:ind_x_preferred":[
        "Bandar Udara Noshahr"
    ],
    "name:msa_x_preferred":[
        "Lapangan Terbang Noshahr"
    ],
    "name:ron_x_preferred":[
        "Aeroportul Noshahr"
    ],
    "name:srp_x_preferred":[
        "\u0410\u0435\u0440\u043e\u0434\u0440\u043e\u043c \u041d\u043e\u0432\u0448\u0430\u0445\u0435\u0440"
    ],
    "name:swe_x_preferred":[
        "Noshahr Airport"
    ],
    "name:tur_x_preferred":[
        "Nu\u015fehr Havaalan\u0131"
    ],
    "oa:elevation_ft":"-61",
    "oa:type":"medium_airport",
    "wd:wordcount":20,
    "woe:hierarchy":{
        "country_id":23424851,
        "planet_id":1,
        "state_id":2345780
    },
    "wof:name":"Noshahr Airport",
    "wof:placetype":"campus"
},
  "geometry": {"coordinates":[51.464722222222,36.663333333333],"type":"Point"}
}