{
  "type": "Feature",
  "properties": {
    "name:ceb_x_preferred":[
        "Arax\u00e1 Airport"
    ],
    "name:deu_x_preferred":[
        "Flughafen Romeu Zema"
    ],
    "name:eng_x_preferred":[
        "Arax\u00e1 Airport"
    ],
    "name:eng_x_variant":[
        "AAX",
        "SBAX"
    ],
    "name:fas_x_preferred":[
        "\u0641\u0631\u0648\u062f\u06af\u0627\u0647 \u0622\u0631\u0627\u06a9\u0633\u0627"
    ],
    "name:fra_x_preferred":[
        "A\u00e9roport d'Arax\u00e1"
    ],
    "name:jpn_x_preferred":[
        "\u30a2\u30e9\u30b7\u30e3\u7a7a\u6e2f"
    ],
    "name:msa_x_preferred":[
        "Lapangan Terbang Araxa"
    ],
    "name:nob_x_preferred":[
        "Arax\u00e1 lufthavn"
    ],
    "name:por_x_preferred":[
        "Aeroporto de Arax\u00e1"
    ],
    "name:swe_x_preferred":[
        "Arax\u00e1 Airport"
    ],
    "name:tgk_x_preferred":[
        "\u0424\u0443\u0440\u0443\u0434\u0433\u043e\u04b3\u0438 \u043e\u0440\u043e\u043a\u0441\u043e"
    ],
    "name:zho_x_preferred":[
        "\u963f\u62c9\u6c99\u6a5f\u5834"
    ],
    "oa:elevation_ft":"3276",
    "oa:type":"small_airport",
    "woe:hierarchy":{
        "country_id":23424768,
        "county_id":12579443,
        "planet_id":1,
        "state_id":2344856
    },
    "wof:name":"Aeroporto Romeu Zuma",
    "wof:placetype":"campus"
},
  "geometry": {"coordinates":[-46.9604,-19.5632],"type":"Point"}
}