{
  "type": "Feature",
  "properties": {
    "name:ceb_x_preferred":[
        "Patos de Minas Airport"
    ],
    "name:deu_x_preferred":[
        "Flughafen Patos De Minas"
    ],
    "name:eng_x_preferred":[
        "Patos de Minas Airport"
    ],
    "name:eng_x_variant":[
        "POJ",
        "SNPD"
    ],
    "name:fas_x_preferred":[
        "\u0641\u0631\u0648\u062f\u06af\u0627\u0647 \u067e\u0627\u062a\u0648\u0633 \u062f\u0648 \u0645\u06cc\u0646\u0627\u0633"
    ],
    "name:jpn_x_preferred":[
        "\u30d1\u30c8\u30b9\u30fb\u30c7\u30fb\u30df\u30ca\u30b9"
    ],
    "name:msa_x_preferred":[
        "Lapangan Terbang Patos De Minas"
    ],
    "name:por_x_preferred":[
        "Aeroporto de Patos de Minas"
    ],
    "name:swe_x_preferred":[
        "Patos de Minas Airport"
    ],
    "name:tgk_x_preferred":[
        "\u0424\u0443\u0440\u0443\u0434\u0433\u043e\u04b3\u0438 \u043f\u043e\u0442\u0443\u0441 \u0434\u0443 \u043c\u0438\u043d\u043e\u0441"
    ],
    "oa:elevation_ft":"2793",
    "oa:type":"small_airport",
    "wd:wordcount":158,
    "woe:hierarchy":{
        "country_id":23424768,
        "county_id":12579884,
        "planet_id":1,
        "state_id":2344856
    },
    "wof:name":"Aeroporto Patos de Minas",
    "wof:placetype":"campus"
},
  "geometry": {"coordinates":[-46.491199,-18.6728],"type":"Point"}
}