{
  "type": "Feature",
  "properties": {
    "gn:admin1_code":"32.0",
    "gn:asciiname":"Halali",
    "gn:dem":1113,
    "gn:feature_class":"P",
    "gn:feature_code":"PPL",
    "gn:name":"Halali",
    "gn:population":0,
    "gn:timezone":"Africa/Windhoek",
    "name:eng_x_preferred":[
        "Halali Rest Camp"
    ],
    "name:eng_x_variant":[
        "Halali Ruskamp",
        "Halali"
    ],
    "wof:name":"Halali",
    "wof:placetype":"locality"
},
  "geometry": {"coordinates":[16.47031,-19.03616],"type":"Point"}
}