{
  "type": "Feature",
  "properties": {
    "wof:name":"Tripoli Park",
    "wof:placetype":"neighbourhood"
},
  "geometry": {"coordinates":[-87.96153202250662,43.15184390857901],"type":"Point"}
}