{
  "type": "Feature",
  "properties": {
    "name:ara_x_preferred":[
        "\u0645\u0637\u0627\u0631 \u062d\u0627\u0626\u0644 \u0627\u0644\u0625\u0642\u0644\u064a\u0645\u064a"
    ],
    "name:ckb_x_preferred":[
        "\u0641\u0695\u06c6\u06a9\u06d5\u062e\u0627\u0646\u06d5\u06cc \u06be\u06d5\u0631\u06ce\u0645\u06cc\u06cc \u062d\u0627\u0626\u06cc\u0644"
    ],
    "name:eng_x_preferred":[
        "Ha'il Regional Airport"
    ],
    "name:eng_x_variant":[
        "HAS",
        "OEHL"
    ],
    "name:fas_x_preferred":[
        "\u0641\u0631\u0648\u062f\u06af\u0627\u0647 \u0645\u0646\u0637\u0642\u0647\u200c\u0627\u06cc \u0647\u0627\u0626\u06cc\u0644"
    ],
    "name:fra_x_preferred":[
        "a\u00e9roport r\u00e9gional d'Ha'il"
    ],
    "name:ind_x_preferred":[
        "Bandar Udara Regional Ha'il"
    ],
    "name:ita_x_preferred":[
        "Aeroporto di Ha'il"
    ],
    "name:jpn_x_preferred":[
        "\u30cf\u30fc\u30a4\u30eb"
    ],
    "name:msa_x_preferred":[
        "Lapangan Terbang Hail"
    ],
    "name:nld_x_preferred":[
        "Ha'il Regional Airport"
    ],
    "name:pol_x_preferred":[
        "Port lotniczy Hail"
    ],
    "name:tgk_x_preferred":[
        "\u0424\u0443\u0440\u0443\u0434\u0433\u043e\u04b3\u0438 \u043c\u0430\u043d\u0442\u0430\u049b\u0430\u200c\u0438\u0439 \u04b3\u043e\u0435\u04b3\u0438\u043b"
    ],
    "oa:elevation_ft":"3331",
    "oa:type":"medium_airport",
    "woe:hierarchy":{
        "country_id":23424938,
        "county_id":56120141,
        "planet_id":1,
        "state_id":2346957
    },
    "wof:name":"Hail Airport",
    "wof:placetype":"campus"
},
  "geometry": {"coordinates":[41.686298,27.437901],"type":"Point"}
}