{
  "type": "Feature",
  "properties": {
    "name:ceb_x_preferred":[
        "Carnarvon Airport"
    ],
    "name:eng_x_preferred":[
        "Carnarvon Airport"
    ],
    "name:eng_x_variant":[
        "CVQ",
        "YCAR"
    ],
    "name:fas_x_preferred":[
        "\u0641\u0631\u0648\u062f\u06af\u0627\u0647 \u06a9\u0627\u0631\u0646\u0627\u0631\u0648\u0646"
    ],
    "name:msa_x_preferred":[
        "Lapangan Terbang Carnarvon"
    ],
    "name:ron_x_preferred":[
        "Aeroportul Carnarvon"
    ],
    "name:rus_x_preferred":[
        "\u041a\u0430\u0440\u043d\u0430\u0440\u0432\u043e\u043d"
    ],
    "name:swe_x_preferred":[
        "Carnarvon Airport"
    ],
    "name:tgk_x_preferred":[
        "\u0424\u0443\u0440\u0443\u0434\u0433\u043e\u04b3\u0438 \u043a\u043e\u0440\u043d\u043e\u0440\u0443\u043d"
    ],
    "name:zho_x_preferred":[
        "\u52a0\u62ff\u5206\u6a5f\u5834"
    ],
    "oa:elevation_ft":"13",
    "oa:type":"medium_airport",
    "wd:wordcount":20,
    "woe:hierarchy":{
        "country_id":23424748,
        "county_id":55864377,
        "planet_id":1,
        "state_id":2344706,
        "suburb_id":28676626
    },
    "wof:name":"Carnarvon Airport",
    "wof:placetype":"campus"
},
  "geometry": {"coordinates":[113.671997,-24.8806],"type":"Point"}
}