{
  "type": "Feature",
  "properties": {
    "gn:admin1_code":"35.0",
    "gn:asciiname":"Otjikorondo",
    "gn:dem":1393,
    "gn:feature_class":"P",
    "gn:feature_code":"PPL",
    "gn:name":"Otjikorondo",
    "gn:population":0,
    "gn:timezone":"Africa/Windhoek",
    "wof:name":"Otjikorondo",
    "wof:placetype":"locality"
},
  "geometry": {"coordinates":[18.91667,-20.98333],"type":"Point"}
}