{
  "type": "Feature",
  "properties": {
    "name:ceb_x_preferred":[
        "Icabar\u00fa Airport"
    ],
    "name:eng_x_preferred":[
        "Icabaru Airport"
    ],
    "name:eng_x_variant":[
        "ICA",
        "SVIC"
    ],
    "name:msa_x_preferred":[
        "Lapangan Terbang Icabaru"
    ],
    "name:ron_x_preferred":[
        "Aeroportul Icabaru"
    ],
    "oa:elevation_ft":"1574",
    "oa:type":"small_airport",
    "woe:hierarchy":{
        "country_id":23424982,
        "county_id":26804568,
        "localadmin_id":26805588,
        "planet_id":1,
        "state_id":2347682
    },
    "wof:name":"Icabaru Airport",
    "wof:placetype":"campus"
},
  "geometry": {"coordinates":[-61.739601,4.33632],"type":"Point"}
}