{
  "type": "Feature",
  "properties": {
    "name:dut_x_preferred":[
        "Luchthaven van Pontes e Lacerda"
    ],
    "name:eng_x_preferred":[
        "Pontes e Lacerda Airport"
    ],
    "name:eng_x_variant":[
        "LCB",
        "SWBG"
    ],
    "name:ger_x_preferred":[
        "Flughafen Pontes E Lacerda"
    ],
    "name:por_x_preferred":[
        "Aeroporto de Pontes e Lacerda"
    ],
    "oa:elevation_ft":"870",
    "oa:type":"small_airport",
    "woe:hierarchy":{
        "country_id":23424768,
        "county_id":12579376,
        "planet_id":1,
        "state_id":2344855
    },
    "wof:name":"Aeroporto Pontes E Lacerda",
    "wof:placetype":"campus"
},
  "geometry": {"coordinates":[-59.3848,-15.1934],"type":"Point"}
}