{
  "type": "Feature",
  "properties": {
    "name:ceb_x_preferred":[
        "Patreksfjordur Airport"
    ],
    "name:cym_x_preferred":[
        "Maes Awyr Patreksfj\u00f6r\u00f0ur"
    ],
    "name:eng_x_preferred":[
        "Patreksfj\u00f6r\u00f0ur Airport"
    ],
    "name:eng_x_variant":[
        "PFJ",
        "BIPA"
    ],
    "name:fas_x_preferred":[
        "\u0641\u0631\u0648\u062f\u06af\u0627\u0647 \u067e\u0627\u062a\u0631\u06cc\u06a9\u0633 \u0641\u06cc\u0648\u0631\u062f"
    ],
    "name:fra_x_preferred":[
        "A\u00e9rodrome de Patreksfj\u00f6r\u00f0ur"
    ],
    "name:fra_x_variant":[
        "a\u00e9roport de Patreksfj\u00f6r\u00f0ur"
    ],
    "name:jpn_x_preferred":[
        "\u30d1\u30c8\u30ec\u30af\u30b9\u30d5\u30a3\u30e8\u30eb\u30ba\u30eb\u7a7a\u6e2f"
    ],
    "name:msa_x_preferred":[
        "Lapangan Terbang Patreksfjordur"
    ],
    "name:pol_x_preferred":[
        "Port lotniczy Patreksfj\u00f6r\u00f0ur"
    ],
    "name:ron_x_preferred":[
        "Aeroportul Patreksfj\u00f6r\u00f0ur"
    ],
    "name:swe_x_preferred":[
        "Patreksfjordur Airport"
    ],
    "name:tgk_x_preferred":[
        "\u0424\u0443\u0440\u0443\u0434\u0433\u043e\u04b3\u0438 \u043f\u043e\u0442\u0440\u0438\u043a\u0441 \u0444\u044e\u0440\u0434"
    ],
    "oa:elevation_ft":"11",
    "oa:type":"medium_airport",
    "wd:wordcount":52,
    "woe:hierarchy":{
        "country_id":23424845,
        "planet_id":1,
        "state_id":2345706
    },
    "wof:name":"Patreksfjordur Airport",
    "wof:placetype":"campus"
},
  "geometry": {"coordinates":[-23.965,65.555801],"type":"Point"}
}