{
  "type": "Feature",
  "properties": {
    "name:ara_x_preferred":[
        "\u0645\u0637\u0627\u0631 \u0648\u0627\u0648"
    ],
    "name:ceb_x_preferred":[
        "Wau Airport"
    ],
    "name:eng_x_preferred":[
        "Wau Airport"
    ],
    "name:eng_x_variant":[
        "WUG",
        "AYWU"
    ],
    "name:fas_x_preferred":[
        "\u0641\u0631\u0648\u062f\u06af\u0627\u0647 \u0648\u0622\u0648"
    ],
    "name:fas_x_variant":[
        "\u0641\u0631\u0648\u062f\u06af\u0627\u0647 \u067e\u0627\u067e\u0648\u0622 \u06af\u06cc\u0646\u0647 \u0646\u0648 \u0648\u0622\u0648"
    ],
    "name:pol_x_preferred":[
        "Port lotniczy Wau"
    ],
    "name:spa_x_preferred":[
        "Aeropuerto de Wau"
    ],
    "name:srp_x_preferred":[
        "\u0410\u0435\u0440\u043e\u0434\u0440\u043e\u043c \u0412\u0430\u0432"
    ],
    "name:swe_x_preferred":[
        "Wau Airport"
    ],
    "name:tgk_x_preferred":[
        "\u0424\u0443\u0440\u0443\u0434\u0433\u043e\u04b3\u0438 \u0432\u043e\u0432"
    ],
    "name:ukr_x_preferred":[
        "\u0412\u0430\u0443"
    ],
    "oa:elevation_ft":"3600",
    "oa:type":"small_airport",
    "wd:wordcount":241,
    "woe:hierarchy":{
        "country_id":23424926,
        "planet_id":1,
        "state_id":2346594
    },
    "wof:name":"Wau Airport",
    "wof:placetype":"campus"
},
  "geometry": {"coordinates":[146.71861100000001,-7.345556],"type":"Point"}
}