{
  "type": "Feature",
  "properties": {
    "name:eng_x_variant":[
        "EPG",
        "NE69"
    ],
    "oa:elevation_ft":"1183",
    "oa:type":"small_airport",
    "woe:hierarchy":{
        "country_id":23424977,
        "county_id":12589150,
        "planet_id":1,
        "state_id":2347586
    },
    "wof:name":"Browns Airport",
    "wof:placetype":"campus"
},
  "geometry": {"coordinates":[-96.110001,40.8675],"type":"Point"}
}