{
  "type": "Feature",
  "properties": {
    "wof:name":"Varsity Estates",
    "wof:placetype":"neighbourhood"
},
  "geometry": {"coordinates":[-114.16801820759959,51.09374618772196],"type":"Point"}
}