{
  "type": "Feature",
  "properties": {
    "gn:admin1_code":"33.0",
    "gn:asciiname":"Onamasila",
    "gn:dem":1150,
    "gn:feature_class":"P",
    "gn:feature_code":"PPL",
    "gn:name":"Onamasila",
    "gn:population":0,
    "gn:timezone":"Africa/Windhoek",
    "wof:name":"Onamasila",
    "wof:placetype":"locality"
},
  "geometry": {"coordinates":[17.08333,-17.66667],"type":"Point"}
}