{
  "type": "Feature",
  "properties": {
    "wof:name":"Somerset",
    "wof:placetype":"neighbourhood"
},
  "geometry": {"coordinates":[-122.15612998476256,47.56315930729667],"type":"Point"}
}