{
  "type": "Feature",
  "properties": {
    "name:eng_x_preferred":[
        "Bocas del Toro \"Isla Col\u00f3n\" International Airport"
    ],
    "name:eng_x_variant":[
        "BOC",
        "MPBO"
    ],
    "name:fas_x_preferred":[
        "\u0641\u0631\u0648\u062f\u06af\u0627\u0647 \u0628\u06cc\u0646\u200c\u0627\u0644\u0645\u0644\u0644\u06cc \u0628\u0648\u06a9\u0627\u0633 \u062f\u0644 \u062a\u0631\u0648 \u0627\u06cc\u0633\u0644\u0627 \u06a9\u0648\u0644\u0648\u0646"
    ],
    "name:ind_x_preferred":[
        "Bandar Udara Internasional Bocas del Toro \"Isla Col\u00f3n\""
    ],
    "name:jpn_x_preferred":[
        "\u30dc\u30ab\u30b9\u30fb\u30c7\u30eb\u30fb\u30c8\u30fc\u30ed \"\u30a4\u30b9\u30e9\u30fb\u30b3\u30ed\u30f3\"\u56fd\u969b\u7a7a\u6e2f"
    ],
    "name:msa_x_preferred":[
        "Lapangan Terbang Antarabangsa Bocas Del Toro"
    ],
    "name:pol_x_preferred":[
        "Port lotniczy Bocas del Toro \"Wyspa Colon\""
    ],
    "name:spa_x_preferred":[
        "Aeropuerto Internacional de Bocas del Toro Isla Col\u00f3n"
    ],
    "name:tgk_x_preferred":[
        "\u0424\u0443\u0440\u0443\u0434\u0433\u043e\u04b3\u0438 \u0431\u0438\u043d\u200c\u0430\u043b\u043c\u0438\u043b\u0430\u043b\u04e3 \u0431\u0443\u043a\u043e\u0441 \u0434\u0438\u043b \u0442\u0440\u0443 \u043e\u0438\u0441\u043b\u043e \u043a\u0443\u043b\u0443\u043d"
    ],
    "name:zho_x_preferred":[
        "\u535a\u5361\u65af\u5fb7\u723e\u6258\u7f85-\u79d1\u9686\u5cf6\u570b\u969b\u6a5f\u5834"
    ],
    "oa:elevation_ft":"10",
    "oa:type":"medium_airport",
    "woe:hierarchy":{
        "country_id":23424924,
        "county_id":26793089,
        "localadmin_id":26793152,
        "planet_id":1,
        "state_id":2346551
    },
    "wof:name":"Bocas del Toro Airport",
    "wof:placetype":"campus"
},
  "geometry": {"coordinates":[-82.250801,9.34085],"type":"Point"}
}