{
  "type": "Feature",
  "properties": {
    "gn:admin1_code":"38.0",
    "gn:asciiname":"Oshigambo",
    "gn:dem":1102,
    "gn:feature_class":"P",
    "gn:feature_code":"PPL",
    "gn:name":"Oshigambo",
    "gn:population":0,
    "gn:timezone":"Africa/Windhoek",
    "name:deu_x_preferred":[
        "Oshigambo"
    ],
    "name:fin_x_preferred":[
        "Oshigambo"
    ],
    "name:zho_x_preferred":[
        "\u5967\u5e0c\u7518\u535a"
    ],
    "wof:name":"Oshigambo",
    "wof:placetype":"locality"
},
  "geometry": {"coordinates":[16.06667,-17.78333],"type":"Point"}
}