{
  "type": "Feature",
  "properties": {
    "name:ceb_x_preferred":[
        "Naracoorte Airport"
    ],
    "name:deu_x_preferred":[
        "Naracoorte Airport"
    ],
    "name:eng_x_preferred":[
        "Naracoorte Airport"
    ],
    "name:eng_x_variant":[
        "NAC",
        "YNRC"
    ],
    "name:fra_x_preferred":[
        "a\u00e9roport de Naracoorte"
    ],
    "name:ita_x_preferred":[
        "aeroporto di Naracoorte"
    ],
    "name:msa_x_preferred":[
        "Lapangan Terbang Naracoorte"
    ],
    "name:spa_x_preferred":[
        "Aeropuerto de Naracoorte"
    ],
    "name:swe_x_preferred":[
        "Naracoorte Airport"
    ],
    "oa:elevation_ft":"169",
    "oa:type":"small_airport",
    "wd:wordcount":51,
    "woe:hierarchy":{
        "country_id":23424748,
        "county_id":55864113,
        "planet_id":1,
        "state_id":2344703
    },
    "wof:name":"Naracoorte Airport",
    "wof:placetype":"campus"
},
  "geometry": {"coordinates":[140.72500600000001,-36.985298],"type":"Point"}
}