{
  "type": "Feature",
  "properties": {
    "wof:name":"Jefferson Corridor",
    "wof:placetype":"neighbourhood"
},
  "geometry": {"coordinates":[-82.97702326655254,42.36216551998958],"type":"Point"}
}