{
  "type": "Feature",
  "properties": {
    "name:cat_x_preferred":[
        "Aeroport de Geelong"
    ],
    "name:ceb_x_preferred":[
        "Geelong Airport"
    ],
    "name:chi_x_preferred":[
        "\u5409\u6717\u6a5f\u5834"
    ],
    "name:eng_x_preferred":[
        "Geelong Airport"
    ],
    "name:eng_x_variant":[
        "GEX",
        "YGLG"
    ],
    "name:fas_x_preferred":[
        "\u0641\u0631\u0648\u062f\u06af\u0627\u0647 \u062c\u06cc\u0644\u0646\u06af"
    ],
    "name:glg_x_preferred":[
        "Aeroporto de Geelong"
    ],
    "name:per_x_preferred":[
        "\u0641\u0631\u0648\u062f\u06af\u0627\u0647 \u062c\u06cc\u0644\u0646\u06af"
    ],
    "name:spa_x_preferred":[
        "Aeropuerto de Geelong"
    ],
    "name:swe_x_preferred":[
        "Geelong Airport"
    ],
    "name:tgk_x_preferred":[
        "\u0424\u0443\u0440\u0443\u0434\u0433\u043e\u04b3\u0438 \u04b7\u0438\u043b\u043d\u0433"
    ],
    "oa:elevation_ft":"43",
    "oa:type":"small_airport",
    "wd:wordcount":203,
    "woe:hierarchy":{
        "country_id":23424748,
        "county_id":55864254,
        "planet_id":1,
        "state_id":2344705
    },
    "wof:name":"Geelong Airport",
    "wof:placetype":"campus"
},
  "geometry": {"coordinates":[144.33299299999999,-38.224998],"type":"Point"}
}