{
  "type": "Feature",
  "properties": {
    "name:chi_x_preferred":[
        "\u514b\u62c9\u7d04\u74e6\u570b\u969b\u6a5f\u5834"
    ],
    "name:dut_x_preferred":[
        "Vliegveld Craiova"
    ],
    "name:eng_x_preferred":[
        "Craiova Airport"
    ],
    "name:eng_x_variant":[
        "CRA",
        "LRCV"
    ],
    "name:ger_x_preferred":[
        "Flughafen Craiova"
    ],
    "name:ita_x_preferred":[
        "Aeroporto di Craiova"
    ],
    "name:jpn_x_preferred":[
        "\u30af\u30e9\u30e8\u30fc\u30f4\u30a1"
    ],
    "name:may_x_preferred":[
        "Lapangan Terbang Craiova"
    ],
    "name:per_x_preferred":[
        "\u0641\u0631\u0648\u062f\u06af\u0627\u0647 \u06a9\u0631\u0627\u06cc\u0648\u0648\u0627"
    ],
    "name:pol_x_preferred":[
        "Port lotniczy Krajowa"
    ],
    "name:rum_x_preferred":[
        "Aeroportul Interna\u021bional Craiova"
    ],
    "name:spa_x_preferred":[
        "Aeropuerto de Craiova"
    ],
    "name:tgk_x_preferred":[
        "\u0424\u0443\u0440\u0443\u0434\u0433\u043e\u04b3\u0438 \u043a\u0440\u043e\u044e\u0432\u043e"
    ],
    "name:vie_x_preferred":[
        "S\u00e2n bay Craiova"
    ],
    "oa:elevation_ft":"626",
    "oa:type":"medium_airport",
    "woe:hierarchy":{
        "country_id":23424933,
        "planet_id":1,
        "state_id":2346631
    },
    "wof:name":"Craiova Airport",
    "wof:placetype":"campus"
},
  "geometry": {"coordinates":[23.888599,44.3181],"type":"Point"}
}