{
  "type": "Feature",
  "properties": {
    "gn:admin1_code":"28.0",
    "gn:asciiname":"Sachona",
    "gn:dem":966,
    "gn:feature_class":"P",
    "gn:feature_code":"PPL",
    "gn:name":"Sachona",
    "gn:population":0,
    "gn:timezone":"Africa/Windhoek",
    "wof:name":"Sachona",
    "wof:placetype":"locality"
},
  "geometry": {"coordinates":[23.33333,-17.93332999999999],"type":"Point"}
}