{
  "type": "Feature",
  "properties": {
    "name:ara_x_preferred":[
        "\u0645\u0637\u0627\u0631 \u0643\u0648\u0646\u064a\u0648 \u0627\u0644\u062f\u0648\u0644\u064a"
    ],
    "name:deu_x_preferred":[
        "Flughafen Cuneo"
    ],
    "name:eng_x_preferred":[
        "Cuneo International Airport"
    ],
    "name:eng_x_variant":[
        "CUF",
        "LIMZ"
    ],
    "name:est_x_preferred":[
        "Cuneo Levaldigi lennujaam"
    ],
    "name:fas_x_preferred":[
        "\u0641\u0631\u0648\u062f\u06af\u0627\u0647 \u06a9\u0648\u0646\u0648 \u0644\u0648\u0627\u0644\u062f\u06cc\u06af\u06cc"
    ],
    "name:fra_x_preferred":[
        "a\u00e9roport international de Coni"
    ],
    "name:hun_x_preferred":[
        "Cuneo-Levaldigi Rep\u00fcl\u0151t\u00e9r"
    ],
    "name:ind_x_preferred":[
        "Bandar Udara Cuneo Levaldigi"
    ],
    "name:ita_x_preferred":[
        "Aeroporto di Cuneo-Levaldigi"
    ],
    "name:jpn_x_preferred":[
        "\u30af\u30fc\u30cd\u30aa\uff1d\u30ec\u30f4\u30a1\u30eb\u30c7\u30a3\u30b8\u7a7a\u6e2f"
    ],
    "name:msa_x_preferred":[
        "Lapangan Terbang Levaldigi"
    ],
    "name:nld_x_preferred":[
        "Cuneo International Airport"
    ],
    "name:pms_x_preferred":[
        "Levaldis"
    ],
    "name:pol_x_preferred":[
        "Port lotniczy Cuneo-Levaldigi"
    ],
    "name:rus_x_preferred":[
        "\u041c\u0435\u0436\u0434\u0443\u043d\u0430\u0440\u043e\u0434\u043d\u044b\u0439 \u0430\u044d\u0440\u043e\u043f\u043e\u0440\u0442 \u041a\u0443\u043d\u0435\u043e"
    ],
    "name:swe_x_preferred":[
        "Cuneos internationella flygplats"
    ],
    "name:tgk_x_preferred":[
        "\u0424\u0443\u0440\u0443\u0434\u0433\u043e\u04b3\u0438 \u043a\u0443\u043d\u0443 \u043b\u0443\u043e\u043b\u0434\u0438\u0433\u0438"
    ],
    "name:vie_x_preferred":[
        "S\u00e2n bay Cuneo Levaldigi"
    ],
    "name:zho_x_preferred":[
        "\u5eab\u5167\u5967\u570b\u969b\u6a5f\u5834"
    ],
    "oa:elevation_ft":"1267",
    "oa:type":"large_airport",
    "woe:hierarchy":{
        "country_id":23424853,
        "county_id":12591824,
        "localadmin_id":12679381,
        "planet_id":1,
        "state_id":7153341
    },
    "wof:name":"Levaldigi Airport",
    "wof:placetype":"campus"
},
  "geometry": {"coordinates":[7.62322,44.547001],"type":"Point"}
}