{
  "type": "Feature",
  "properties": {
    "name:eng_x_preferred":[
        "Ubatuba Airport"
    ],
    "name:eng_x_variant":[
        "UBT",
        "SDUB"
    ],
    "name:ger_x_preferred":[
        "Flughafen Gast\u00e3o Madeira"
    ],
    "name:may_x_preferred":[
        "Lapangan Terbang Ubatuba"
    ],
    "name:por_x_preferred":[
        "Aeroporto de Ubatuba"
    ],
    "name:swe_x_preferred":[
        "Ubatuba Airport"
    ],
    "oa:elevation_ft":"13",
    "oa:type":"small_airport",
    "woe:hierarchy":{
        "country_id":23424768,
        "county_id":12582365,
        "planet_id":1,
        "state_id":2344868
    },
    "wof:name":"Aeroporto Ubatuba",
    "wof:placetype":"campus"
},
  "geometry": {"coordinates":[-45.0756,-23.441099],"type":"Point"}
}