{
  "type": "Feature",
  "properties": {
    "gn:admin1_code":"40.0",
    "gn:asciiname":"Sharukwe",
    "gn:dem":1107,
    "gn:feature_class":"P",
    "gn:feature_code":"PPL",
    "gn:name":"Sharukwe",
    "gn:population":0,
    "gn:timezone":"Africa/Windhoek",
    "name:und_x_variant":[
        "Sarukwe",
        "Sharukwe"
    ],
    "wof:name":"Sharukwe",
    "wof:placetype":"locality"
},
  "geometry": {"coordinates":[19.73333,-18.01667],"type":"Point"}
}