{
  "type": "Feature",
  "properties": {
    "gn:admin1_code":"36.0",
    "gn:asciiname":"Uuvudhiya",
    "gn:dem":1090,
    "gn:feature_class":"P",
    "gn:feature_code":"PPL",
    "gn:name":"Uuvudhiya",
    "gn:population":0,
    "gn:timezone":"Africa/Windhoek",
    "wof:name":"Uuvudhiya",
    "wof:placetype":"locality"
},
  "geometry": {"coordinates":[15.48333,-18.13333],"type":"Point"}
}