{
  "type": "Feature",
  "properties": {
    "name:aze_x_preferred":[
        "Sibay hava liman\u0131"
    ],
    "name:ceb_x_preferred":[
        "Sibay Airport"
    ],
    "name:eng_x_preferred":[
        "Sibay Airport"
    ],
    "name:fas_x_preferred":[
        "\u0641\u0631\u0648\u062f\u06af\u0627\u0647 \u0633\u06cc\u0628\u0627\u06cc"
    ],
    "name:ron_x_preferred":[
        "Aeroportul Sibay"
    ],
    "name:rus_x_preferred":[
        "\u0421\u0438\u0431\u0430\u0439"
    ],
    "oa:elevation_ft":"1309",
    "oa:type":"small_airport",
    "wd:wordcount":82,
    "woe:hierarchy":{
        "country_id":23424936,
        "county_id":12597265,
        "planet_id":1,
        "state_id":2346866
    },
    "wof:name":"Sibay Airport",
    "wof:placetype":"campus"
},
  "geometry": {"coordinates":[58.716666666667,52.683333333333],"type":"Point"}
}