{
  "type": "Feature",
  "properties": {
    "name:ceb_x_preferred":[
        "Corowa Airport"
    ],
    "name:eng_x_variant":[
        "COW",
        "SCCQ"
    ],
    "name:fas_x_preferred":[
        "\u0641\u0631\u0648\u062f\u06af\u0627\u0647 \u06a9\u0648\u0631\u0648\u0648\u0627"
    ],
    "name:swe_x_preferred":[
        "Corowa Airport"
    ],
    "name:tgk_x_preferred":[
        "\u0424\u0443\u0440\u0443\u0434\u0433\u043e\u04b3\u0438 \u043a\u0443\u0440\u0443\u0432\u043e"
    ],
    "oa:elevation_ft":"656",
    "oa:type":"small_airport",
    "wd:wordcount":48,
    "woe:hierarchy":{
        "country_id":23424748,
        "county_id":55863836,
        "planet_id":1,
        "state_id":2344700
    },
    "wof:name":"Corowa Airport",
    "wof:placetype":"campus"
},
  "geometry": {"coordinates":[-71.246944,-30.198889],"type":"Point"}
}