{
  "type": "Feature",
  "properties": {
    "name:ceb_x_preferred":[
        "Akita Airport"
    ],
    "name:deu_x_preferred":[
        "Flughafen Akita"
    ],
    "name:eng_x_preferred":[
        "Akita Airport"
    ],
    "name:eng_x_variant":[
        "AXT",
        "RJSK"
    ],
    "name:fas_x_preferred":[
        "\u0641\u0631\u0648\u062f\u06af\u0627\u0647 \u0627\u06a9\u06cc\u062a\u0627"
    ],
    "name:fra_x_preferred":[
        "a\u00e9roport d'Akita"
    ],
    "name:ind_x_preferred":[
        "Bandar Udara Akita"
    ],
    "name:ita_x_preferred":[
        "Aeroporto di Akita"
    ],
    "name:jpn_x_preferred":[
        "\u79cb\u7530\u7a7a\u6e2f"
    ],
    "name:kor_x_preferred":[
        "\uc544\ud0a4\ud0c0 \uacf5\ud56d"
    ],
    "name:msa_x_preferred":[
        "Lapangan Terbang Akita"
    ],
    "name:nld_x_preferred":[
        "Akita Airport"
    ],
    "name:pol_x_preferred":[
        "Port lotniczy Akita"
    ],
    "name:por_x_preferred":[
        "Aeroporto de Akita"
    ],
    "name:ron_x_preferred":[
        "Aeroportul Akita"
    ],
    "name:spa_x_preferred":[
        "Aeropuerto de Akita"
    ],
    "name:tgk_x_preferred":[
        "\u0424\u0443\u0440\u0443\u0434\u0433\u043e\u04b3\u0438 \u043e\u043a\u0438\u0442\u043e"
    ],
    "name:tha_x_preferred":[
        "\u0e17\u0e48\u0e32\u0e2d\u0e32\u0e01\u0e32\u0e28\u0e22\u0e32\u0e19\u0e2d\u0e30\u0e01\u0e34\u0e15\u0e30"
    ],
    "name:ukr_x_preferred":[
        "\u0410\u0435\u0440\u043e\u043f\u043e\u0440\u0442 \u0410\u043a\u0456\u0442\u0430"
    ],
    "name:vie_x_preferred":[
        "S\u00e2n bay Akita"
    ],
    "name:zho_x_preferred":[
        "\u79cb\u7530\u6a5f\u5834"
    ],
    "oa:elevation_ft":"313",
    "oa:type":"medium_airport",
    "woe:hierarchy":{
        "country_id":23424856,
        "planet_id":1,
        "state_id":2345852
    },
    "wof:name":"\u79cb\u7530\u7a7a\u6e2f",
    "wof:placetype":"campus"
},
  "geometry": {"coordinates":[140.21899400000001,39.615601],"type":"Point"}
}