{
  "type": "Feature",
  "properties": {
    "name:ceb_x_preferred":[
        "Yacuiba Airport"
    ],
    "name:eng_x_preferred":[
        "Yacuiba Airport"
    ],
    "name:eng_x_variant":[
        "BYC",
        "SLYA"
    ],
    "name:fas_x_preferred":[
        "\u0641\u0631\u0648\u062f\u06af\u0627\u0647 \u06cc\u0627\u0633\u0648\u0626\u06cc\u0628\u0627"
    ],
    "name:fra_x_preferred":[
        "Yacuiba Airport"
    ],
    "name:jpn_x_preferred":[
        "\u30e4\u30af\u30a4\u30d0\u7a7a\u6e2f"
    ],
    "name:msa_x_preferred":[
        "Lapangan Terbang Yacuiba"
    ],
    "name:pol_x_preferred":[
        "Port lotniczy Yacuiba"
    ],
    "name:ron_x_preferred":[
        "Aeroportul Yacuiba"
    ],
    "name:spa_x_preferred":[
        "Aeropuerto de Yacuiba"
    ],
    "name:swe_x_preferred":[
        "Yacuiba Airport"
    ],
    "name:tgk_x_preferred":[
        "\u0424\u0443\u0440\u0443\u0434\u0433\u043e\u04b3\u0438 \u0438\u043e\u0441\u0443\u0435\u04b3\u0438\u0431\u043e"
    ],
    "name:vie_x_preferred":[
        "S\u00e2n bay Yacu\u00edba"
    ],
    "name:zho_x_preferred":[
        "\u4e9e\u594e\u74e6\u6a5f\u5834"
    ],
    "oa:elevation_ft":"2112",
    "oa:type":"medium_airport",
    "wd:wordcount":39,
    "woe:hierarchy":{
        "country_id":23424762,
        "county_id":55967841,
        "localadmin_id":55968104,
        "planet_id":1,
        "state_id":2344809
    },
    "wof:name":"Yacuiba Airport",
    "wof:placetype":"campus"
},
  "geometry": {"coordinates":[-63.651699,-21.960899],"type":"Point"}
}