{
  "type": "Feature",
  "properties": {
    "name:ceb_x_preferred":[
        "Tarapoto"
    ],
    "name:deu_x_preferred":[
        "Flughafen Tarapoto"
    ],
    "name:eng_x_preferred":[
        "Cad. FAP Guillermo del Castillo Paredes Airport"
    ],
    "name:eng_x_variant":[
        "TPP",
        "SPST"
    ],
    "name:fas_x_preferred":[
        "\u0641\u0631\u0648\u062f\u06af\u0627\u0647 \u06af\u06cc\u0644\u0631\u0645\u0648 \u062f\u0644 \u06a9\u0627\u0633\u062a\u06cc\u0644\u0648 \u067e\u0627\u0631\u062f\u0633"
    ],
    "name:jpn_x_preferred":[
        "\u30b3\u30de\u30f3\u30c0\u30f3\u30c6\u30fbFAP\u30fb\u30ae\u30b8\u30a7\u30eb\u30e2\u30fb\u30c7\u30eb\u30fb\u30ab\u30b9\u30c6\u30a3\u30fc\u30b8\u30e7\u30fb\u30d1\u30ec\u30fc\u30c7\u30b9\u7a7a\u6e2f"
    ],
    "name:msa_x_preferred":[
        "Lapangan Terbang Cadete Fap Guillermo Del Casti"
    ],
    "name:pol_x_preferred":[
        "Port lotniczy Tarapoto-Comandante FAP Guillermo del Castillo Paredes"
    ],
    "name:que_x_preferred":[
        "Guillermo del Castillo Paredes antanka panpa"
    ],
    "name:spa_x_preferred":[
        "Aeropuerto Cadete FAP Guillermo del Castillo Paredes"
    ],
    "name:tgk_x_preferred":[
        "\u0424\u0443\u0440\u0443\u0434\u0433\u043e\u04b3\u0438 \u0433\u0438\u043b\u0440\u043c\u0443 \u0434\u0438\u043b \u043a\u043e\u0441\u0442\u0438\u043b\u0443 \u043f\u043e\u0440\u0434\u0441"
    ],
    "name:vie_x_preferred":[
        "S\u00e2n bay Cad. FAP Guillermo del Castillo Paredes"
    ],
    "name:zho_x_preferred":[
        "\u5854\u62c9\u6ce2\u6258"
    ],
    "oa:elevation_ft":"869",
    "oa:type":"medium_airport",
    "woe:hierarchy":{
        "country_id":23424919,
        "county_id":26805928,
        "planet_id":1,
        "state_id":2346489
    },
    "wof:name":"Tarapoto Airport",
    "wof:placetype":"campus"
},
  "geometry": {"coordinates":[-76.373199,-6.50874],"type":"Point"}
}