{
  "type": "Feature",
  "properties": {
    "name:eng_x_preferred":[
        "Antlers Municipal Airport"
    ],
    "name:eng_x_variant":[
        "ATE",
        "K80F"
    ],
    "name:fas_x_preferred":[
        "\u0641\u0631\u0648\u062f\u06af\u0627\u0647 \u0634\u0647\u0631\u06cc \u0627\u0646\u062a\u0644\u0631"
    ],
    "name:tgk_x_preferred":[
        "\u0424\u0443\u0440\u0443\u0434\u0433\u043e\u04b3\u0438 \u0448\u0430\u04b3\u0440\u0435 \u043e\u043d\u0442\u043b\u0440"
    ],
    "name:zho_x_preferred":[
        "\u5b89\u7279\u52d2\u65af\u5e02\u7acb\u6a5f\u5834"
    ],
    "oa:elevation_ft":"575",
    "oa:type":"small_airport",
    "wd:wordcount":134,
    "woe:hierarchy":{
        "country_id":23424977,
        "county_id":12589678,
        "planet_id":1,
        "state_id":2347595
    },
    "wof:name":"Antlers Municipal Airport",
    "wof:placetype":"campus"
},
  "geometry": {"coordinates":[-95.649902,34.1926],"type":"Point"}
}