{
  "type": "Feature",
  "properties": {
    "gn:admin1_code":"28.0",
    "gn:asciiname":"Sibinda",
    "gn:dem":957,
    "gn:feature_class":"P",
    "gn:feature_code":"PPL",
    "gn:name":"Sibinda",
    "gn:population":0,
    "gn:timezone":"Africa/Windhoek",
    "name:deu_x_preferred":[
        "Sibinda"
    ],
    "name:spa_x_preferred":[
        "Sibinda"
    ],
    "wof:name":"Sibinda",
    "wof:placetype":"locality"
},
  "geometry": {"coordinates":[23.81667,-17.78333],"type":"Point"}
}