{
  "type": "Feature",
  "properties": {
    "name:ceb_x_preferred":[
        "Nanaimo Airport"
    ],
    "name:deu_x_preferred":[
        "Nanaimo Airport"
    ],
    "name:eng_x_preferred":[
        "Nanaimo Airport"
    ],
    "name:eng_x_variant":[
        "YCD",
        "CYCD"
    ],
    "name:fas_x_preferred":[
        "\u0641\u0631\u0648\u062f\u06af\u0627\u0647 \u0646\u0627\u0646\u0627\u06cc\u0645\u0648"
    ],
    "name:fra_x_preferred":[
        "A\u00e9roport de Nanaimo"
    ],
    "name:jpn_x_preferred":[
        "\u30ca\u30ca\u30a4\u30e2\u7a7a\u6e2f"
    ],
    "name:msa_x_preferred":[
        "Lapangan Terbang Nanaimo"
    ],
    "name:pms_x_preferred":[
        "Nanaimo Airport"
    ],
    "name:spa_x_preferred":[
        "Aeropuerto de Nanaimo"
    ],
    "name:swe_x_preferred":[
        "Nanaimo Airport"
    ],
    "name:tgk_x_preferred":[
        "\u0424\u0443\u0440\u0443\u0434\u0433\u043e\u04b3\u0438 \u043d\u043e\u043d\u043e\u0438\u043c\u0443"
    ],
    "name:zho_x_preferred":[
        "\u4e43\u78e8\u6a5f\u5834"
    ],
    "oa:elevation_ft":"92",
    "oa:type":"medium_airport",
    "wd:wordcount":233,
    "woe:hierarchy":{
        "country_id":23424775,
        "county_id":29375073,
        "planet_id":1,
        "state_id":2344916
    },
    "wof:name":"Nanaimo Airport",
    "wof:placetype":"campus"
},
  "geometry": {"coordinates":[-123.869863,49.05497],"type":"Point"}
}