{
  "type": "Feature",
  "properties": {
    "gn:admin1_code":"38.0",
    "gn:asciiname":"Omunkayi",
    "gn:dem":1151,
    "gn:feature_class":"P",
    "gn:feature_code":"PPL",
    "gn:name":"Omunkayi",
    "gn:population":0,
    "gn:timezone":"Africa/Windhoek",
    "wof:name":"Omunkayi",
    "wof:placetype":"locality"
},
  "geometry": {"coordinates":[17.26667,-17.71667],"type":"Point"}
}