{
  "type": "Feature",
  "properties": {
    "wof:name":"Londonderry",
    "wof:placetype":"neighbourhood"
},
  "geometry": {"coordinates":[-84.4018394796109,33.89817177439249],"type":"Point"}
}