{
  "type": "Feature",
  "properties": {
    "name:ceb_x_preferred":[
        "Warrenton-Fauquier Airport"
    ],
    "name:eng_x_preferred":[
        "Warrenton-Fauquier Airport"
    ],
    "name:fas_x_preferred":[
        "\u0641\u0631\u0648\u062f\u06af\u0627\u0647 \u0648\u0627\u0631\u0646\u062a\u0646-\u0641\u0648\u06a9\u06cc\u0631"
    ],
    "name:ron_x_preferred":[
        "Aeroportul Warrenton-Fauquier"
    ],
    "name:tgk_x_preferred":[
        "\u0424\u0443\u0440\u0443\u0434\u0433\u043e\u04b3\u0438 \u0432\u043e\u0440\u043d\u0442\u043d-\u0444\u0443\u043a\u0438\u0440"
    ],
    "name:urd_x_preferred":[
        "\u0648\u0627\u0631\u0646\u0679\u0646\u2013\u0641\u0627\u06a9\u06cc\u0626\u0631 \u06c1\u0648\u0627\u0626\u06cc \u0627\u0688\u0627"
    ],
    "oa:elevation_ft":"336",
    "oa:type":"small_airport",
    "wd:wordcount":225,
    "woe:hierarchy":{
        "country_id":23424977,
        "county_id":12590346,
        "planet_id":1,
        "state_id":2347605
    },
    "wof:name":"Warrenton Fauquier Airport",
    "wof:placetype":"campus"
},
  "geometry": {"coordinates":[-77.7106,38.5864],"type":"Point"}
}