{
  "type": "Feature",
  "properties": {
    "name:ceb_x_preferred":[
        "Mi\u0101nw\u0101li Airfield"
    ],
    "name:eng_x_preferred":[
        "PAF Base Mianwali"
    ],
    "name:eng_x_variant":[
        "MWD",
        "OPMI",
        "PAF Base M.M. Alam"
    ],
    "name:fas_x_preferred":[
        "\u067e\u0627\u06cc\u06af\u0627\u0647 \u0646\u06cc\u0631\u0648\u06cc \u0647\u0648\u0627\u06cc\u06cc \u067e\u0627\u06a9\u0633\u062a\u0627\u0646 \u062f\u0631 \u0645\u06cc\u0627\u0646\u200c\u0648\u0627\u0644\u06cc"
    ],
    "name:jpn_x_preferred":[
        "\u30df\u30ef\u30f3\u30ef\u30ea\u30fc\u98db\u884c\u5834"
    ],
    "name:msa_x_preferred":[
        "Lapangan Terbang Mianwali AB"
    ],
    "name:msa_x_variant":[
        "Lapangan Terbang Mianwali"
    ],
    "name:tgk_x_preferred":[
        "\u041f\u043e\u0439\u0433\u043e\u04b3\u0438 \u043d\u0435\u0440\u04ef\u0435 \u04b3\u0430\u0432\u043e \u041f\u043e\u043a\u0438\u0441\u0442\u043e\u043d \u0434\u0430\u0440 \u043c\u0435\u0451\u043d\u200c\u0432\u043e\u043b"
    ],
    "oa:elevation_ft":"690",
    "oa:type":"medium_airport",
    "woe:hierarchy":{
        "country_id":23424922,
        "planet_id":1,
        "state_id":2346498
    },
    "wof:name":"Mianwali Airport",
    "wof:placetype":"campus"
},
  "geometry": {"coordinates":[71.570702,32.563099],"type":"Point"}
}