{
  "type": "Feature",
  "properties": {
    "name:ceb_x_preferred":[
        "Taloyoak Airport"
    ],
    "name:eng_x_preferred":[
        "Taloyoak Airport"
    ],
    "name:fas_x_preferred":[
        "\u0641\u0631\u0648\u062f\u06af\u0627\u0647 \u062a\u0627\u0644\u0648\u06cc\u0648\u06a9"
    ],
    "name:fin_x_preferred":[
        "Taloyoakin lentoasema"
    ],
    "name:ind_x_preferred":[
        "Bandar Udara Taloyoak"
    ],
    "name:jpn_x_preferred":[
        "\u30bf\u30ed\u30e8\u30fc\u30af\u7a7a\u6e2f"
    ],
    "name:msa_x_preferred":[
        "Lapangan Terbang Taloyoak"
    ],
    "name:pms_x_preferred":[
        "Taloyoak Airport"
    ],
    "name:ron_x_preferred":[
        "Aeroportul Taloyoak"
    ],
    "name:spa_x_preferred":[
        "Aeropuerto de Taloyoak"
    ],
    "name:swe_x_preferred":[
        "Taloyoak Airport"
    ],
    "name:tgk_x_preferred":[
        "\u0424\u0443\u0440\u0443\u0434\u0433\u043e\u04b3\u0438 \u0442\u043e\u043b\u0443\u044e\u043a"
    ],
    "oa:elevation_ft":"92",
    "oa:type":"medium_airport",
    "wd:wordcount":80,
    "woe:hierarchy":{
        "country_id":23424775,
        "county_id":29375230,
        "planet_id":1,
        "state_id":20069920
    },
    "wof:name":"Taloyoak Airport",
    "wof:placetype":"campus"
},
  "geometry": {"coordinates":[-93.576944444444,69.54666666666699],"type":"Point"}
}