{
  "type": "Feature",
  "properties": {
    "name:eng_x_preferred":[
        "Copperfield"
    ],
    "name:nld_x_preferred":[
        "Copperfield"
    ],
    "wd:wordcount":83,
    "wof:name":"Copperfield",
    "wof:placetype":"neighbourhood"
},
  "geometry": {"coordinates":[-113.927166,50.916214],"type":"Point"}
}