{
  "type": "Feature",
  "properties": {
    "name:eng_x_preferred":[
        "Copperfield"
    ],
    "wd:wordcount":83,
    "wof:name":"Copperfield",
    "wof:placetype":"neighbourhood"
},
  "geometry": {"coordinates":[-113.92716597924202,50.91621421769592],"type":"Point"}
}