{
  "type": "Feature",
  "properties": {
    "name:ara_x_preferred":[
        "\u0645\u0637\u0627\u0631 \u0642\u0648\u064a\u0644\u064a\u0646 \u064a\u0627\u0646\u063a \u062c\u064a\u0627\u0646\u063a \u0627\u0644\u062f\u0648\u0644\u064a"
    ],
    "name:arz_x_preferred":[
        "\u0645\u0637\u0627\u0631 \u062c\u0648\u064a\u0644\u064a\u0646 \u064a\u0627\u0646\u062c \u062c\u064a\u0627\u0646\u062c \u0627\u0644\u062f\u0648\u0644\u0649"
    ],
    "name:ces_x_preferred":[
        "Mezin\u00e1rodn\u00ed leti\u0161t\u011b Kuej-lin Liang-\u0165iang"
    ],
    "name:cym_x_preferred":[
        "Maes Awyr Rhyngwladol Guilin Liangjiang"
    ],
    "name:deu_x_preferred":[
        "Flughafen Guilin-Liangjiang"
    ],
    "name:eng_x_preferred":[
        "Guilin Liangjiang International Airport"
    ],
    "name:eng_x_variant":[
        "KWL",
        "ZGKL"
    ],
    "name:eus_x_preferred":[
        "Guilin Liangjiang nazioarteko aireportua"
    ],
    "name:fas_x_preferred":[
        "\u0641\u0631\u0648\u062f\u06af\u0627\u0647 \u0628\u06cc\u0646\u200c\u0627\u0644\u0645\u0644\u0644\u06cc \u06af\u0627\u06cc\u0644\u06cc\u0646 \u0644\u06cc\u0627\u0646\u06af\u200c\u062c\u06cc\u0627\u0646\u06af"
    ],
    "name:fra_x_preferred":[
        "a\u00e9roport international de Guilin Liangjiang"
    ],
    "name:ind_x_preferred":[
        "Bandar Udara Internasional Liangjiang Guilin"
    ],
    "name:jpn_x_preferred":[
        "\u6842\u6797\u4e21\u6c5f\u56fd\u969b\u7a7a\u6e2f"
    ],
    "name:kor_x_preferred":[
        "\uad6c\uc774\ub9b0 \ub7c9\uc7a5 \uad6d\uc81c\uacf5\ud56d"
    ],
    "name:msa_x_preferred":[
        "Lapangan Terbang Liangjiang"
    ],
    "name:nld_x_preferred":[
        "Guilin Liangjiang International Airport"
    ],
    "name:nob_x_preferred":[
        "Guilin Liangjiang internasjonale lufthavn"
    ],
    "name:pol_x_preferred":[
        "Port lotniczy Guilin-Liangjiang"
    ],
    "name:por_x_preferred":[
        "Aeroporto Internacional de Guilin Liangjiang"
    ],
    "name:ron_x_preferred":[
        "Aeroportul Interna\u021bional Guilin Liangjiang"
    ],
    "name:swe_x_preferred":[
        "Guilin Liangjiang International Airport"
    ],
    "name:tgk_x_preferred":[
        "\u0424\u0443\u0440\u0443\u0434\u0433\u043e\u04b3\u0438 \u0411\u0430\u0439\u043d\u200c\u0430\u043b\u043c\u0438\u043b\u043b\u0430\u043b\u0438\u0438 \u0413\u0443\u0438\u043b\u0438\u043d \u041b\u044f\u043d\u04b7\u0438\u044f\u043d"
    ],
    "name:ukr_x_preferred":[
        "\u041c\u0456\u0436\u043d\u0430\u0440\u043e\u0434\u043d\u0438\u0439 \u0430\u0435\u0440\u043e\u043f\u043e\u0440\u0442 \u0413\u0443\u0439\u043b\u0456\u043d\u044c-\u041b\u044f\u043d\u0446\u0437\u044f\u043d"
    ],
    "name:vie_x_preferred":[
        "S\u00e2n bay qu\u1ed1c t\u1ebf L\u01b0\u1ee1ng Giang Qu\u1ebf L\u00e2m"
    ],
    "name:zho_x_preferred":[
        "\u6842\u6797\u5169\u6c5f\u570b\u969b\u6a5f\u5834"
    ],
    "oa:elevation_ft":"570",
    "oa:type":"large_airport",
    "woe:hierarchy":{
        "country_id":23424781,
        "county_id":26198246,
        "localadmin_id":12686601,
        "planet_id":1,
        "state_id":12578006
    },
    "wof:name":"Li Chia Tsun Airport",
    "wof:placetype":"campus"
},
  "geometry": {"coordinates":[110.039001,25.2181],"type":"Point"}
}