{
  "type": "Feature",
  "properties": {
    "name:ceb_x_preferred":[
        "Moyobamba Airport"
    ],
    "name:eng_x_preferred":[
        "Moyobamba Airport"
    ],
    "name:eng_x_variant":[
        "MBP",
        "SPBB"
    ],
    "name:msa_x_preferred":[
        "Lapangan Terbang Moyobamba"
    ],
    "name:ron_x_preferred":[
        "Aeroportul Moyobamba"
    ],
    "oa:elevation_ft":"2749",
    "oa:type":"small_airport",
    "woe:hierarchy":{
        "country_id":23424919,
        "county_id":26805894,
        "planet_id":1,
        "state_id":2346489
    },
    "wof:name":"Moyobamba Airport",
    "wof:placetype":"campus"
},
  "geometry": {"coordinates":[-76.988327,-6.018889],"type":"Point"}
}