{
  "type": "Feature",
  "properties": {
    "name:ceb_x_preferred":[
        "Cafunfo Airport"
    ],
    "name:eng_x_preferred":[
        "Cafunfo Airport"
    ],
    "name:fas_x_preferred":[
        "\u0641\u0631\u0648\u062f\u06af\u0627\u0647 \u06a9\u0627\u0641\u0648\u0646\u0641\u0648"
    ],
    "name:ind_x_preferred":[
        "Bandar Udara Cafunfo"
    ],
    "name:jpn_x_preferred":[
        "\u30ab\u30d5\u30f3\u30d5\u30a9\u30fc\u7a7a\u6e2f"
    ],
    "name:pol_x_preferred":[
        "Port lotniczy Cafunfo"
    ],
    "name:ron_x_preferred":[
        "Aeroportul Cafunfo"
    ],
    "name:swe_x_preferred":[
        "Cafunfo Airport"
    ],
    "name:tgk_x_preferred":[
        "\u0424\u0443\u0440\u0443\u0434\u0433\u043e\u04b3\u0438 \u043a\u043e\u0444\u0443\u043d\u0444\u0443"
    ],
    "name:zho_x_preferred":[
        "Cafunfo\u6a5f\u5834"
    ],
    "oa:type":"small_airport",
    "wd:wordcount":34,
    "woe:hierarchy":{
        "country_id":23424745,
        "planet_id":1,
        "state_id":2344671
    },
    "wof:name":"Cafunfo Airport",
    "wof:placetype":"campus"
},
  "geometry": {"coordinates":[17.9906,-8.78347],"type":"Point"}
}