{
  "type": "Feature",
  "properties": {
    "name:ara_x_preferred":[
        "\u0645\u0637\u0627\u0631 \u0646\u0627\u0646\u0634\u0648\u0646\u063a \u063a\u0627\u0648\u0628\u064a\u0646\u063a"
    ],
    "name:eng_x_preferred":[
        "Nanchong Gaoping Airport"
    ],
    "name:eng_x_variant":[
        "NAO",
        "ZUNC"
    ],
    "name:eus_x_preferred":[
        "Nanchong aireportua"
    ],
    "name:jpn_x_preferred":[
        "\u5357\u5145\u9ad8\u576a\u7a7a\u6e2f"
    ],
    "name:nld_x_preferred":[
        "Nanchong Gaoping Airport"
    ],
    "name:swe_x_preferred":[
        "Nanchong Gaoping Airport"
    ],
    "name:zho_x_preferred":[
        "\u5357\u5145\u9ad8\u576a\u673a\u573a"
    ],
    "oa:type":"small_airport",
    "wd:wordcount":42,
    "woe:hierarchy":{
        "country_id":23424781,
        "county_id":26198295,
        "localadmin_id":20071184,
        "planet_id":1,
        "state_id":12578016
    },
    "wof:name":"Nanchong Airport",
    "wof:placetype":"campus"
},
  "geometry": {"coordinates":[106.1626,30.79545],"type":"Point"}
}