{
  "type": "Feature",
  "properties": {
    "name:ara_x_preferred":[
        "\u0645\u0637\u0627\u0631 \u0633\u0627\u0646\u062a \u0625\u062a\u064a\u0627\u0646"
    ],
    "name:arz_x_preferred":[
        "\u0645\u0637\u0627\u0631 \u0633\u0627\u0646\u062a \u0627\u062a\u064a\u0627\u0646"
    ],
    "name:ceb_x_preferred":[
        "Saint-\u00c9tienne\u2013Bouth\u00e9on Airport"
    ],
    "name:deu_x_preferred":[
        "Flughafen Saint-\u00c9tienne \u2013 Bouth\u00e9on"
    ],
    "name:eng_x_preferred":[
        "Saint-\u00c9tienne \u2013 Bouth\u00e9on Airport"
    ],
    "name:eng_x_variant":[
        "EBU",
        "LFMH"
    ],
    "name:fas_x_preferred":[
        "\u0641\u0631\u0648\u062f\u06af\u0627\u0647 \u0633\u0646-\u0627\u062a\u06cc\u0646"
    ],
    "name:fas_x_variant":[
        "\u0641\u0631\u0648\u062f\u06af\u0627\u0647 \u0633\u0646\u062a \u062a\u06cc \u062a\u06cc\u0646\u0646 \u2013 \u0628\u0648\u062a\u0626\u0648\u0646"
    ],
    "name:fra_x_preferred":[
        "A\u00e9roport de Saint-\u00c9tienne-Loire"
    ],
    "name:fra_x_variant":[
        "a\u00e9roport de Saint-\u00c9tienne-Loire"
    ],
    "name:frc_x_preferred":[
        "Saint-Etienne - Bouth\u00e9on"
    ],
    "name:hun_x_preferred":[
        "Saint-\u00c9tienne \u2013 Bouth\u00e9on rep\u00fcl\u0151t\u00e9r"
    ],
    "name:ind_x_preferred":[
        "Bandar Udara Saint-\u00c9tienne - Bouth\u00e9on"
    ],
    "name:jpn_x_preferred":[
        "\u30b5\u30f3\uff1d\u30c6\u30c6\u30a3\u30a8\u30f3\u30cc\u30fb\u30d6\u30c6\u30aa\u30f3\u7a7a\u6e2f"
    ],
    "name:lav_x_preferred":[
        "Sentetj\u0113nas - Buteonas lidosta"
    ],
    "name:msa_x_preferred":[
        "Lapangan Terbang Boutheon"
    ],
    "name:pol_x_preferred":[
        "Port lotniczy Saint-\u00c9tienne \u2013 Bouth\u00e9on"
    ],
    "name:ron_x_preferred":[
        "Aeroportul Saint-\u00c9tienne \u2013 Bouth\u00e9on"
    ],
    "name:spa_x_preferred":[
        "Aeropuerto de Saint-\u00c9tienne - Bouth\u00e9on"
    ],
    "name:tgk_x_preferred":[
        "\u0424\u0443\u0440\u0443\u0434\u0433\u043e\u04b3\u0438 \u0441\u0443\u043d\u043d\u0430\u0442 \u0442\u04e3\u200c\u0442\u0438\u043d\u043d \u2013 \u0431\u0443\u0442\u0435\u04b3\u0432\u043d"
    ],
    "name:tur_x_preferred":[
        "Saint-\u00c9tienne - Bouth\u00e9on Havaliman\u0131"
    ],
    "name:vie_x_preferred":[
        "S\u00e2n bay Saint-\u00c9tienne - Bouth\u00e9on"
    ],
    "name:zho_x_preferred":[
        "\u8056\u827e\u8482\u5b89-\u5e03\u6cf0\u7fc1\u6a5f\u5834"
    ],
    "oa:elevation_ft":"1325",
    "oa:type":"medium_airport",
    "woe:hierarchy":{
        "country_id":23424819,
        "county_id":12597165,
        "localadmin_id":12655253,
        "planet_id":1,
        "state_id":7153329
    },
    "wof:name":"A\u00e9roport de Saint-Etienne-Bouth\u00e9on",
    "wof:placetype":"campus"
},
  "geometry": {"coordinates":[4.29639,45.5406],"type":"Point"}
}