{
  "type": "Feature",
  "properties": {
    "name:ceb_x_preferred":[
        "Gjoa Haven Airport"
    ],
    "name:cym_x_preferred":[
        "Maes Awyr Gjoa Haven"
    ],
    "name:eng_x_preferred":[
        "Gjoa Haven Airport"
    ],
    "name:eng_x_variant":[
        "YHK",
        "CYHK"
    ],
    "name:fas_x_preferred":[
        "\u0641\u0631\u0648\u062f\u06af\u0627\u0647 \u062c\u0648\u0627 \u0647\u0648\u0646"
    ],
    "name:fin_x_preferred":[
        "Gjoa Havenin lentoasema"
    ],
    "name:ind_x_preferred":[
        "Bandar Udara Gjoa Haven"
    ],
    "name:msa_x_preferred":[
        "Lapangan Terbang Gjoa Haven"
    ],
    "name:pms_x_preferred":[
        "Gjoa Haven Airport"
    ],
    "name:ron_x_preferred":[
        "Aeroportul Gjoa Haven"
    ],
    "name:spa_x_preferred":[
        "Aeropuerto de Gjoa Haven"
    ],
    "name:swe_x_preferred":[
        "Gjoa Haven Airport"
    ],
    "name:tgk_x_preferred":[
        "\u0424\u0443\u0440\u0443\u0434\u0433\u043e\u04b3\u0438 \u04b7\u0443\u043e \u04b3\u0443\u043d"
    ],
    "name:zho_x_preferred":[
        "\u7ea6\u963f\u6e2f\u673a\u573a"
    ],
    "oa:elevation_ft":"152",
    "oa:type":"medium_airport",
    "wd:wordcount":119,
    "woe:hierarchy":{
        "country_id":23424775,
        "county_id":29375230,
        "planet_id":1,
        "state_id":20069920
    },
    "wof:name":"Gjoa Haven Airport",
    "wof:placetype":"campus"
},
  "geometry": {"coordinates":[-95.850278,68.63555599999999],"type":"Point"}
}