{
  "type": "Feature",
  "properties": {
    "gn:admin1_code":"35.0",
    "gn:asciiname":"Gunkas",
    "gn:dem":1251,
    "gn:feature_class":"P",
    "gn:feature_code":"PPL",
    "gn:name":"Gunkas",
    "gn:population":0,
    "gn:timezone":"Africa/Windhoek",
    "wof:name":"Gunkas",
    "wof:placetype":"locality"
},
  "geometry": {"coordinates":[19.65,-23.73333],"type":"Point"}
}