{
  "type": "Feature",
  "properties": {
    "name:ceb_x_preferred":[
        "Summerhill"
    ],
    "name:cym_x_preferred":[
        "Summerhill"
    ],
    "name:deu_x_preferred":[
        "Summerhill"
    ],
    "name:fra_x_preferred":[
        "Summerhill"
    ],
    "name:ita_x_preferred":[
        "Summerhill"
    ],
    "name:kor_x_preferred":[
        "\uc11c\uba38\ud790"
    ],
    "name:mlg_x_preferred":[
        "Summerhill"
    ],
    "name:pol_x_preferred":[
        "Summerhill"
    ],
    "name:por_x_preferred":[
        "Summerhill"
    ],
    "name:slk_x_preferred":[
        "Summerhill"
    ],
    "name:spa_x_preferred":[
        "Summerhill"
    ],
    "name:swe_x_preferred":[
        "Summerhill"
    ],
    "wof:name":"Summerhill",
    "wof:placetype":"neighbourhood"
},
  "geometry": {"coordinates":[-114.01070789139401,51.27617580496715],"type":"Point"}
}