{
  "type": "Feature",
  "properties": {
    "name:eng_x_preferred":[
        "Arlington"
    ],
    "name:fre_x_preferred":[
        "Arlington"
    ],
    "wof:name":"Arlington",
    "wof:placetype":"neighbourhood"
},
  "geometry": {"coordinates":[-79.96897770607097,40.41457855092504],"type":"Point"}
}