{
  "type": "Feature",
  "properties": {
    "name:ceb_x_preferred":[
        "Yuendumu Airport"
    ],
    "name:eng_x_preferred":[
        "Yuendumu Airport"
    ],
    "name:eng_x_variant":[
        "YUE",
        "YYND"
    ],
    "name:msa_x_preferred":[
        "Lapangan Terbang Yuendumu"
    ],
    "name:ron_x_preferred":[
        "Aeroportul Yuendumu"
    ],
    "name:swe_x_preferred":[
        "Yuendumu Airport"
    ],
    "oa:elevation_ft":"2205",
    "oa:type":"small_airport",
    "woe:hierarchy":{
        "country_id":23424748,
        "county_id":56072997,
        "planet_id":1,
        "state_id":2344701
    },
    "wof:name":"Yuendumu Airport",
    "wof:placetype":"campus"
},
  "geometry": {"coordinates":[131.78222199999999,-22.254167],"type":"Point"}
}