{
  "type": "Feature",
  "properties": {
    "name:ceb_x_preferred":[
        "Fountain Park"
    ],
    "name:deu_x_preferred":[
        "Fountain Park"
    ],
    "name:eng_x_preferred":[
        "Fountain Park"
    ],
    "name:fra_x_preferred":[
        "Fountain Park"
    ],
    "name:swe_x_preferred":[
        "Fountain Park"
    ],
    "wd:wordcount":15,
    "wof:name":"Fountain Park",
    "wof:placetype":"neighbourhood"
},
  "geometry": {"coordinates":[-90.2596949897075,38.65599461631374],"type":"Point"}
}