{
  "type": "Feature",
  "properties": {
    "name:ceb_x_preferred":[
        "Villa Gesell Airport"
    ],
    "name:eng_x_preferred":[
        "Villa Gesell Airport"
    ],
    "name:eng_x_variant":[
        "VLG",
        "SAZV"
    ],
    "name:fas_x_preferred":[
        "\u0641\u0631\u0648\u062f\u06af\u0627\u0647 \u0648\u06cc\u0644\u0627 \u06af\u0632\u0644"
    ],
    "name:jpn_x_preferred":[
        "\u30d3\u30b8\u30e3\u30fb\u30d8\u30bb\u30eb\u7a7a\u6e2f"
    ],
    "name:may_x_preferred":[
        "Lapangan Terbang Villa Gesell"
    ],
    "name:per_x_preferred":[
        "\u0641\u0631\u0648\u062f\u06af\u0627\u0647 \u0648\u06cc\u0644\u0627 \u06af\u0632\u0644"
    ],
    "name:spa_x_preferred":[
        "Aeropuerto de Villa Gesell"
    ],
    "name:swe_x_preferred":[
        "Villa Gesell Airport"
    ],
    "name:tgk_x_preferred":[
        "\u0424\u0443\u0440\u0443\u0434\u0433\u043e\u04b3\u0438 \u0432\u0435\u043b\u043e \u0433\u0437\u043b"
    ],
    "name:vie_x_preferred":[
        "S\u00e2n bay qu\u1ed1c t\u1ebf Villa Gesell - Pinamar"
    ],
    "oa:elevation_ft":"32",
    "oa:type":"medium_airport",
    "wd:wordcount":108,
    "woe:hierarchy":{
        "country_id":23424747,
        "county_id":20070630,
        "planet_id":1,
        "state_id":2344675
    },
    "wof:name":"Villa Gesell Airport",
    "wof:placetype":"campus"
},
  "geometry": {"coordinates":[-57.0292,-37.2354],"type":"Point"}
}