{
  "type": "Feature",
  "properties": {
    "name:ceb_x_preferred":[
        "Golden Rock Airport"
    ],
    "name:deu_x_preferred":[
        "Robert L. Bradshaw International Airport"
    ],
    "name:eng_x_preferred":[
        "Robert L. Bradshaw International Airport"
    ],
    "name:eng_x_variant":[
        "SKB",
        "TKPK"
    ],
    "name:fas_x_preferred":[
        "\u0641\u0631\u0648\u062f\u06af\u0627\u0647 \u0628\u06cc\u0646\u200c\u0627\u0644\u0645\u0644\u0644\u06cc \u0631\u0627\u0628\u0631\u062a \u0644. \u0628\u0631\u06cc\u062f\u0634\u0648"
    ],
    "name:fra_x_preferred":[
        "Robert L. Bradshaw International Airport"
    ],
    "name:fra_x_variant":[
        "a\u00e9roport Robert L. Bradshaw"
    ],
    "name:hrv_x_preferred":[
        "Zra\u010dna luka Robert L. Bradshaw"
    ],
    "name:ind_x_preferred":[
        "Bandar Udara Internasional Robert L. Bradshaw"
    ],
    "name:ita_x_preferred":[
        "Aeroporto Internazionale Robert L. Bradshaw"
    ],
    "name:jpn_x_preferred":[
        "\u30ed\u30d0\u30fc\u30c8\u30fbL\u30fb\u30d6\u30e9\u30c3\u30c9\u30b7\u30e7\u30fc\u56fd\u969b\u7a7a\u6e2f"
    ],
    "name:lit_x_preferred":[
        "Robert L. Bradshaw tarptautinis oro uostas"
    ],
    "name:msa_x_preferred":[
        "Lapangan Terbang Antarabangsa Bradshaw"
    ],
    "name:nld_x_preferred":[
        "Robert L. Bradshaw International Airport"
    ],
    "name:pol_x_preferred":[
        "Port lotniczy Robert L. Bradshaw"
    ],
    "name:por_x_preferred":[
        "Aeroporto Internacional Robert L. Bradshaw"
    ],
    "name:ron_x_preferred":[
        "Aeroportul Robert L. Bradshaw"
    ],
    "name:spa_x_preferred":[
        "Aeropuerto Internacional Robert L. Bradshaw"
    ],
    "name:swe_x_preferred":[
        "Golden Rock Airport"
    ],
    "name:tgk_x_preferred":[
        "\u0424\u0443\u0440\u0443\u0434\u0433\u043e\u04b3\u0438 \u0431\u0438\u043d\u200c\u0430\u043b\u043c\u0438\u043b\u0430\u043b\u04e3 \u0440\u043e\u0431\u0438\u0440\u0442 \u043b. \u0431\u0440\u0438\u0434\u0448\u0443"
    ],
    "name:zho_x_preferred":[
        "\u8056\u57fa\u8328\u5cf6"
    ],
    "oa:elevation_ft":"170",
    "oa:type":"medium_airport",
    "wd:wordcount":21,
    "woe:hierarchy":{
        "country_id":23424940,
        "planet_id":1,
        "state_id":2346966
    },
    "wof:name":"Golden Rock Airport",
    "wof:placetype":"campus"
},
  "geometry": {"coordinates":[-62.7187,17.311199],"type":"Point"}
}