{
  "type": "Feature",
  "properties": {
    "name:ceb_x_preferred":[
        "Jorge Wilsterman"
    ],
    "name:deu_x_preferred":[
        "Flughafen Cochabamba"
    ],
    "name:eng_x_preferred":[
        "Jorge Wilstermann International Airport"
    ],
    "name:eng_x_variant":[
        "CBB",
        "SLCB"
    ],
    "name:fas_x_preferred":[
        "\u0641\u0631\u0648\u062f\u06af\u0627\u0647 \u0628\u06cc\u0646\u200c\u0627\u0644\u0645\u0644\u0644\u06cc \u062e\u0648\u0631\u062e\u0647 \u0648\u06cc\u0644\u0633\u062a\u0631\u0645\u0627\u0646"
    ],
    "name:fra_x_preferred":[
        "a\u00e9roport international Jorge Wilstermann"
    ],
    "name:heb_x_preferred":[
        "\u05d7\u05d5\u05e8\u05d7\u05d4 \u05d5\u05d9\u05dc\u05e1\u05d8\u05e8\u05de\u05d0\u05df"
    ],
    "name:ind_x_preferred":[
        "Bandar Udara Internasional Jorge Wilstermann"
    ],
    "name:jpn_x_preferred":[
        "\u30db\u30eb\u30d8\u30fb\u30a6\u30a3\u30eb\u30b9\u30c6\u30eb\u30de\u30f3\u56fd\u969b\u7a7a\u6e2f"
    ],
    "name:msa_x_preferred":[
        "Lapangan Terbang Jorge Wilsterman"
    ],
    "name:nld_x_preferred":[
        "Aeropuerto Internacional Jorge Wilstermann"
    ],
    "name:pol_x_preferred":[
        "Port lotniczy Jorge Wilstermann"
    ],
    "name:por_x_preferred":[
        "Aeroporto Internacional de Cochabamba"
    ],
    "name:que_x_preferred":[
        "Jorge Wilstermann antanka pampa"
    ],
    "name:ron_x_preferred":[
        "Aeroportul Jorge Wilstermann"
    ],
    "name:spa_x_preferred":[
        "Aeropuerto Internacional Jorge Wilstermann"
    ],
    "name:swe_x_preferred":[
        "Jorge Wilstermann"
    ],
    "name:tgk_x_preferred":[
        "\u0424\u0443\u0440\u0443\u0434\u0433\u043e\u04b3\u0438 \u0431\u0438\u043d\u200c\u0430\u043b\u043c\u0438\u043b\u0430\u043b\u04e3 \u0445\u0443\u0440\u0445\u04b3 \u0432\u0438\u043b\u0441\u0442\u0440\u043c\u043e\u043d"
    ],
    "name:vie_x_preferred":[
        "S\u00e2n bay qu\u1ed1c t\u1ebf Jorge Wilstermann"
    ],
    "name:zho_x_preferred":[
        "\u79d1\u6070\u73ed\u5df4"
    ],
    "oa:elevation_ft":"8360",
    "oa:type":"medium_airport",
    "woe:hierarchy":{
        "country_id":23424762,
        "county_id":55967760,
        "localadmin_id":55968170,
        "planet_id":1,
        "state_id":2344802
    },
    "wof:name":"Jorge Wilsterman Airport",
    "wof:placetype":"campus"
},
  "geometry": {"coordinates":[-66.17710099999999,-17.421101],"type":"Point"}
}