{
  "type": "Feature",
  "properties": {
    "name:chi_x_preferred":[
        "\u85a9\u5229\u5167\u65af\u570b\u969b\u6a5f\u5834"
    ],
    "name:eng_x_preferred":[
        "Maurice Bishop International Airport"
    ],
    "name:eng_x_variant":[
        "GND",
        "TGPY"
    ],
    "name:fre_x_preferred":[
        "a\u00e9roport de Pointe Salines"
    ],
    "name:ger_x_preferred":[
        "Flughafen Point Salines"
    ],
    "name:gre_x_preferred":[
        "\u03a0\u03bf\u03c5\u03ac\u03bd\u03c4 \u03a3\u03b1\u03bb\u03af\u03bd"
    ],
    "name:ind_x_preferred":[
        "Bandar Udara Internasional Maurice Bishop"
    ],
    "name:jpn_x_preferred":[
        "\u30dd\u30a4\u30f3\u30c8\u30fb\u30b5\u30ea\u30f3\u30b9\u56fd\u969b\u7a7a\u6e2f"
    ],
    "name:lit_x_preferred":[
        "Mauriso Bi\u0161opo oro uostas"
    ],
    "name:may_x_preferred":[
        "Lapangan Terbang Antarabangsa Point Salines"
    ],
    "name:per_x_preferred":[
        "\u0641\u0631\u0648\u062f\u06af\u0627\u0647 \u0628\u06cc\u0646\u200c\u0627\u0644\u0645\u0644\u0644\u06cc \u0645\u0627\u0631\u06cc\u0633 \u0628\u06cc\u0634\u0627\u067e"
    ],
    "name:pol_x_preferred":[
        "Port lotniczy Point Salines"
    ],
    "name:por_x_preferred":[
        "Aeroporto Internacional Maurice Bishop"
    ],
    "name:spa_x_preferred":[
        "Aeropuerto Internacional Maurice Bishop"
    ],
    "name:swe_x_preferred":[
        "Maurice Bishop International Airport"
    ],
    "name:tgk_x_preferred":[
        "\u0424\u0443\u0440\u0443\u0434\u0433\u043e\u04b3\u0438 \u0431\u0438\u043d\u200c\u0430\u043b\u043c\u0438\u043b\u0430\u043b\u04e3 \u043c\u043e\u0440\u0438\u0441 \u0431\u0438\u0448\u043e\u043f"
    ],
    "oa:elevation_ft":"41",
    "oa:type":"medium_airport",
    "woe:hierarchy":{
        "country_id":23424826,
        "planet_id":1,
        "state_id":2345475
    },
    "wof:name":"Point Salines International Airport",
    "wof:placetype":"campus"
},
  "geometry": {"coordinates":[-61.786201,12.0042],"type":"Point"}
}