{
  "type": "Feature",
  "properties": {
    "name:eng_x_preferred":[
        "Eisenach-Kindel Airport"
    ],
    "name:eng_x_variant":[
        "EIB",
        "EDGE"
    ],
    "name:ger_x_preferred":[
        "Flugplatz Eisenach-Kindel"
    ],
    "name:may_x_preferred":[
        "Lapangan Terbang Eisenach-Kindel"
    ],
    "oa:elevation_ft":"1112",
    "oa:type":"medium_airport",
    "woe:hierarchy":{
        "country_id":23424829,
        "county_id":12597003,
        "localadmin_id":12625007,
        "planet_id":1,
        "state_id":2345495
    },
    "wof:name":"Haina Airport",
    "wof:placetype":"campus"
},
  "geometry": {"coordinates":[10.472778,50.992779],"type":"Point"}
}