{
  "type": "Feature",
  "properties": {
    "name:eng_x_preferred":[
        "Middle Caicos Airport"
    ],
    "name:eng_x_variant":[
        "MDS",
        "KMDS"
    ],
    "name:fas_x_preferred":[
        "\u0641\u0631\u0648\u062f\u06af\u0627\u0647 \u0645\u06cc\u062f\u0644 \u06a9\u0627\u06cc\u06a9\u0648\u0633"
    ],
    "name:jpn_x_preferred":[
        "\u30df\u30c9\u30eb\u30fb\u30ab\u30a4\u30b3\u30b9\u7a7a\u6e2f"
    ],
    "name:may_x_preferred":[
        "Lapangan Terbang Conch Bar"
    ],
    "name:msa_x_preferred":[
        "Lapangan Terbang Conch Bar"
    ],
    "name:per_x_preferred":[
        "\u0641\u0631\u0648\u062f\u06af\u0627\u0647 \u0645\u06cc\u062f\u0644 \u06a9\u0627\u06cc\u06a9\u0648\u0633"
    ],
    "name:pol_x_preferred":[
        "Port lotniczy Middle Caicos"
    ],
    "name:tgk_x_preferred":[
        "\u0424\u0443\u0440\u0443\u0434\u0433\u043e\u04b3\u0438 \u043c\u0438\u0434\u043b \u043a\u043e\u0438\u043a\u0443\u0441"
    ],
    "oa:elevation_ft":"9",
    "oa:type":"small_airport",
    "wd:wordcount":79,
    "woe:hierarchy":{
        "country_id":23424962,
        "planet_id":1,
        "state_id":24549932
    },
    "wof:name":"Middle Caicos Airport",
    "wof:placetype":"campus"
},
  "geometry": {"coordinates":[-71.80249999999999,21.82602],"type":"Point"}
}