{
  "type": "Feature",
  "properties": {
    "name:deu_x_preferred":[
        "Newcomb"
    ],
    "name:fra_x_preferred":[
        "Newcomb"
    ],
    "name:heb_x_preferred":[
        "\u05e0\u05d9\u05d5\u05e7\u05d5\u05dd"
    ],
    "name:ita_x_preferred":[
        "Newcomb"
    ],
    "name:nld_x_preferred":[
        "Newcomb"
    ],
    "name:pol_x_preferred":[
        "Newcomb"
    ],
    "name:spa_x_preferred":[
        "Newcomb"
    ],
    "name:ukr_x_preferred":[
        "\u041d\u044c\u044e\u043a\u043e\u043c\u0431"
    ],
    "wd:wordcount":155,
    "wof:name":"Newcomb",
    "wof:placetype":"neighbourhood"
},
  "geometry": {"coordinates":[144.39549855762016,-38.1629642073305],"type":"Point"}
}