{
  "type": "Feature",
  "properties": {
    "name:ceb_x_preferred":[
        "Toamasina Airport"
    ],
    "name:cym_x_preferred":[
        "Maes Awyr Toamasina"
    ],
    "name:eng_x_preferred":[
        "Toamasina Airport"
    ],
    "name:eng_x_variant":[
        "TMM",
        "FMMT"
    ],
    "name:fas_x_preferred":[
        "\u0641\u0631\u0648\u062f\u06af\u0627\u0647 \u062a\u0648\u0626\u0627\u0645\u0627\u0632\u06cc\u0646\u0627"
    ],
    "name:fra_x_preferred":[
        "A\u00e9rodrome de Tamatave"
    ],
    "name:fra_x_variant":[
        "a\u00e9rodrome de Tamatave"
    ],
    "name:ita_x_preferred":[
        "Aeroporto di Toamasina"
    ],
    "name:jpn_x_preferred":[
        "\u30c8\u30a5\u30a2\u30de\u30b7\u30ca\u7a7a\u6e2f"
    ],
    "name:msa_x_preferred":[
        "Lapangan Terbang Toamasina"
    ],
    "name:nld_x_preferred":[
        "Toamasina Airport"
    ],
    "name:pol_x_preferred":[
        "Port lotniczy Toamasina"
    ],
    "name:swe_x_preferred":[
        "Toamaasina Airport"
    ],
    "name:tgk_x_preferred":[
        "\u0424\u0443\u0440\u0443\u0434\u0433\u043e\u04b3\u0438 \u0442\u0443\u0435\u04b3\u043e\u043c\u043e\u0437\u0438\u043d\u043e"
    ],
    "name:zho_x_preferred":[
        "\u5716\u963f\u99ac\u897f\u7d0d\u6a5f\u5834"
    ],
    "oa:elevation_ft":"22",
    "oa:type":"medium_airport",
    "wd:wordcount":14,
    "woe:hierarchy":{
        "country_id":23424883,
        "county_id":23706579,
        "planet_id":1,
        "state_id":2346149
    },
    "wof:name":"Toamasina Airport",
    "wof:placetype":"campus"
},
  "geometry": {"coordinates":[49.392502,-18.109501],"type":"Point"}
}