{
  "type": "Feature",
  "properties": {
    "gn:admin1_code":"31.0",
    "gn:asciiname":"Khaais",
    "gn:dem":602,
    "gn:feature_class":"P",
    "gn:feature_code":"PPL",
    "gn:name":"Khaais",
    "gn:population":0,
    "gn:timezone":"Africa/Windhoek",
    "wof:name":"Khaais",
    "wof:placetype":"locality"
},
  "geometry": {"coordinates":[19.31667,-28.66667],"type":"Point"}
}