{
  "type": "Feature",
  "properties": {
    "name:ceb_x_preferred":[
        "Chacalluta Arica Airport"
    ],
    "name:deu_x_preferred":[
        "Flughafen Arica"
    ],
    "name:eng_x_preferred":[
        "Chacalluta International Airport"
    ],
    "name:eng_x_variant":[
        "ARI",
        "SCAR"
    ],
    "name:fas_x_preferred":[
        "\u0641\u0631\u0648\u062f\u06af\u0627\u0647 \u0628\u06cc\u0646\u200c\u0627\u0644\u0645\u0644\u0644\u06cc \u0686\u0627\u06a9\u0644\u0648\u062a\u0627"
    ],
    "name:fra_x_preferred":[
        "a\u00e9roport d'Arica Chacalluta"
    ],
    "name:ind_x_preferred":[
        "Bandar Udara Internasional Chacalluta"
    ],
    "name:jpn_x_preferred":[
        "\u30c1\u30e3\u30ab\u30e6\u30bf\u7a7a\u6e2f"
    ],
    "name:msa_x_preferred":[
        "Lapangan Terbang Antarabangsa Chacalluta"
    ],
    "name:nld_x_preferred":[
        "Luchthaven Chacalluta"
    ],
    "name:nob_x_preferred":[
        "Chacalluta internasjonale lufthavn"
    ],
    "name:pol_x_preferred":[
        "Port lotniczy Chacalutta"
    ],
    "name:por_x_preferred":[
        "Aeroporto Internacional Chacalluta"
    ],
    "name:ron_x_preferred":[
        "Aeroportul Interna\u021bional Chacalluta"
    ],
    "name:spa_x_preferred":[
        "Aeropuerto Internacional Chacalluta"
    ],
    "name:swe_x_preferred":[
        "Chacalluta Arica Airport"
    ],
    "name:tgk_x_preferred":[
        "\u0424\u0443\u0440\u0443\u0434\u0433\u043e\u04b3\u0438 \u0431\u0438\u043d\u200c\u0430\u043b\u043c\u0438\u043b\u0430\u043b\u04e3 \u0447\u043e\u043a\u043b\u0443\u0442\u043e"
    ],
    "name:vie_x_preferred":[
        "S\u00e2n bay qu\u1ed1c t\u1ebf Chacalluta"
    ],
    "name:zho_x_preferred":[
        "Chacalluta\u570b\u969b\u6a5f\u5834"
    ],
    "oa:elevation_ft":"167",
    "oa:type":"medium_airport",
    "woe:hierarchy":{
        "country_id":23424782,
        "county_id":26793977,
        "localadmin_id":26794315,
        "planet_id":1,
        "state_id":56043702
    },
    "wof:name":"Chacalluta Airport",
    "wof:placetype":"campus"
},
  "geometry": {"coordinates":[-70.33869900000001,-18.348499],"type":"Point"}
}