{
  "type": "Feature",
  "properties": {
    "name:deu_x_preferred":[
        "Flughafen Bacacheri"
    ],
    "name:eng_x_preferred":[
        "Bacacheri Airport"
    ],
    "name:eng_x_variant":[
        "BFH",
        "SBBI"
    ],
    "name:fas_x_preferred":[
        "\u0641\u0631\u0648\u062f\u06af\u0627\u0647 \u0628\u0627\u06a9\u0686\u0631\u06cc"
    ],
    "name:jpn_x_preferred":[
        "\u30d0\u30ab\u30c1\u30a7\u30ea\u7a7a\u6e2f"
    ],
    "name:por_x_preferred":[
        "Aeroporto do Bacacheri"
    ],
    "name:swe_x_preferred":[
        "Parana Airport"
    ],
    "name:tgk_x_preferred":[
        "\u0424\u0443\u0440\u0443\u0434\u0433\u043e\u04b3\u0438 \u0431\u043e\u043a\u0447\u0440\u0438"
    ],
    "name:zho_x_preferred":[
        "\u5eab\u91cc\u5947\u5df4\u6a5f\u5834"
    ],
    "oa:elevation_ft":"3057",
    "oa:type":"medium_airport",
    "woe:hierarchy":{
        "country_id":23424768,
        "county_id":12580478,
        "planet_id":1,
        "state_id":2344859
    },
    "wof:name":"Aeroporto de Bacacheri",
    "wof:placetype":"campus"
},
  "geometry": {"coordinates":[-49.231998,-25.4051],"type":"Point"}
}