{
  "type": "Feature",
  "properties": {
    "gn:admin1_code":"28.0",
    "gn:asciiname":"Liamissa",
    "gn:dem":935,
    "gn:feature_class":"P",
    "gn:feature_code":"PPL",
    "gn:name":"Liamissa",
    "gn:population":0,
    "gn:timezone":"Africa/Windhoek",
    "wof:name":"Liamissa",
    "wof:placetype":"locality"
},
  "geometry": {"coordinates":[24.26667,-17.81667000000001],"type":"Point"}
}