{
  "type": "Feature",
  "properties": {
    "wof:name":"Corrimal",
    "wof:placetype":"neighbourhood"
},
  "geometry": {"coordinates":[150.89460439619967,-34.36898425917559],"type":"Point"}
}