{
  "type": "Feature",
  "properties": {
    "gn:admin1_code":"32.0",
    "gn:asciiname":"Otjaparakaha",
    "gn:dem":1120,
    "gn:feature_class":"P",
    "gn:feature_code":"PPL",
    "gn:name":"Otjaparakaha",
    "gn:population":0,
    "gn:timezone":"Africa/Windhoek",
    "wof:name":"Otjaparakaha",
    "wof:placetype":"locality"
},
  "geometry": {"coordinates":[13.11667,-17.83333],"type":"Point"}
}