{
  "type": "Feature",
  "properties": {
    "wd:wordcount":1123,
    "wof:name":"Downtown",
    "wof:placetype":"neighbourhood"
},
  "geometry": {"coordinates":[-82.45595873428034,27.94958712761412],"type":"Point"}
}