{
  "type": "Feature",
  "properties": {
    "name:ara_x_preferred":[
        "\u0648\u0633\u0637 \u0627\u0644\u0628\u0644\u062f"
    ],
    "name:arz_x_preferred":[
        "\u0648\u0633\u0637 \u0627\u0644\u0628\u0644\u062f"
    ],
    "name:ast_x_preferred":[
        "Distritu financieru"
    ],
    "name:ben_x_preferred":[
        "\u09b6\u09b9\u09b0\u09c7\u09b0 \u0995\u09c7\u09a8\u09cd\u09a6\u09cd\u09b0\u09b8\u09cd\u09a5\u09b2"
    ],
    "name:bul_x_preferred":[
        "\u0426\u0435\u043d\u0442\u044a\u0440"
    ],
    "name:ces_x_preferred":[
        "Downtown"
    ],
    "name:deu_x_preferred":[
        "Downtown"
    ],
    "name:eng_x_preferred":[
        "downtown"
    ],
    "name:epo_x_preferred":[
        "urbocentro"
    ],
    "name:eus_x_preferred":[
        "Hirigune"
    ],
    "name:fas_x_preferred":[
        "\u0647\u0633\u062a\u0647 \u0634\u0647\u0631"
    ],
    "name:fra_x_preferred":[
        "centre-ville"
    ],
    "name:hun_x_preferred":[
        "belv\u00e1ros"
    ],
    "name:hye_x_preferred":[
        "\u0534\u0561\u0578\u0582\u0576\u0569\u0561\u0578\u0582\u0576"
    ],
    "name:jpn_x_preferred":[
        "\u30c0\u30a6\u30f3\u30bf\u30a6\u30f3"
    ],
    "name:kor_x_preferred":[
        "\ub3c4\uc2ec"
    ],
    "name:kor_x_variant":[
        "\ubc88\ud654\uac00"
    ],
    "name:nld_x_preferred":[
        "downtown"
    ],
    "name:pol_x_preferred":[
        "centrum miasta"
    ],
    "name:por_x_preferred":[
        "centro"
    ],
    "name:por_x_variant":[
        "downtown"
    ],
    "name:ron_x_preferred":[
        "Centru civic"
    ],
    "name:rus_x_preferred":[
        "\u0434\u0430\u0443\u043d\u0442\u0430\u0443\u043d"
    ],
    "name:sco_x_preferred":[
        "Downtown"
    ],
    "name:spa_x_preferred":[
        "downtown"
    ],
    "name:srp_x_preferred":[
        "\u0434\u0430\u0443\u043d\u0442\u0430\u0443\u043d"
    ],
    "name:swe_x_preferred":[
        "Downtown"
    ],
    "name:tur_x_preferred":[
        "Downtown"
    ],
    "name:ukr_x_preferred":[
        "\u0434\u0430\u0443\u043d\u0442\u0430\u0443\u043d"
    ],
    "name:wuu_x_preferred":[
        "\u4e0b\u57ce"
    ],
    "name:yue_x_preferred":[
        "\u4e0b\u57ce"
    ],
    "name:zho_x_preferred":[
        "\u4e0b\u57ce"
    ],
    "wd:wordcount":1123,
    "wof:name":"Downtown",
    "wof:placetype":"neighbourhood"
},
  "geometry": {"coordinates":[-82.45595899999999,27.949587],"type":"Point"}
}