{
  "type": "Feature",
  "properties": {
    "name:eng_x_preferred":[
        "Naval Air Station Joint Reserve Base Fort Worth"
    ],
    "name:fas_x_preferred":[
        "\u067e\u0627\u06cc\u06af\u0627\u0647 \u0647\u0648\u0627\u06cc\u06cc \u0645\u0648\u0642\u062a \u0641\u0631\u062a \u0648\u0631\u062a"
    ],
    "name:ita_x_preferred":[
        "Naval Air Station Joint Reserve Base Fort Worth"
    ],
    "name:tgk_x_preferred":[
        "\u041f\u043e\u0439\u0433\u043e\u04b3\u0438 \u04b3\u0430\u0432\u043e\u0438 \u0437\u0430\u0445\u0438\u0440\u0430\u0432\u0438\u0438 \u043c\u0443\u0448\u0442\u0430\u0440\u0430\u043a\u0438 \u0424\u043e\u0440\u0442 \u0423\u043e\u0440\u0437"
    ],
    "name:urd_x_preferred":[
        "\u0646\u06cc\u0648\u0644 \u0627\u06cc\u0626\u0631\u0627\u0633\u0679\u06cc\u0634\u0646 \u062c\u0648\u0627\u0626\u0646\u0679 \u0631\u06cc\u0632\u0631\u0648 \u0628\u06cc\u0633 \u0641\u0648\u0631\u0679 \u0648\u0631\u062a\u06be"
    ],
    "oa:elevation_ft":"650",
    "oa:type":"medium_airport",
    "wd:wordcount":6252,
    "woe:hierarchy":{
        "country_id":23424977,
        "county_id":12590226,
        "planet_id":1,
        "state_id":2347602,
        "suburb_id":2481885
    },
    "wof:name":"Naval Air Station Joint Reserve Base Fort Worth",
    "wof:placetype":"campus"
},
  "geometry": {"coordinates":[-97.441666666667,32.769166666667],"type":"Point"}
}