{
  "type": "Feature",
  "properties": {
    "name:ceb_x_preferred":[
        "Ouesso"
    ],
    "name:eng_x_preferred":[
        "Ou\u00e9sso Airport"
    ],
    "name:eng_x_variant":[
        "OUE",
        "FCOU"
    ],
    "name:fas_x_preferred":[
        "\u0641\u0631\u0648\u062f\u06af\u0627\u0647 \u0627\u0648\u0626\u0633\u0648"
    ],
    "name:fra_x_preferred":[
        "A\u00e9roport de Ouesso"
    ],
    "name:fra_x_variant":[
        "a\u00e9roport de Ouesso"
    ],
    "name:jpn_x_preferred":[
        "\u30a6\u30a7\u30c3\u30bd\u7a7a\u6e2f"
    ],
    "name:msa_x_preferred":[
        "Lapangan Terbang Ouesso"
    ],
    "name:pol_x_preferred":[
        "Port lotniczy Ouesso"
    ],
    "name:ron_x_preferred":[
        "Aeroportul Ou\u00e9sso"
    ],
    "name:swe_x_preferred":[
        "Ouesso"
    ],
    "name:tgk_x_preferred":[
        "\u0424\u0443\u0440\u0443\u0434\u0433\u043e\u04b3\u0438 \u043e\u0432\u0435\u04b3\u0441\u0443"
    ],
    "oa:elevation_ft":"1158",
    "oa:type":"medium_airport",
    "wd:wordcount":148,
    "woe:hierarchy":{
        "country_id":23424779,
        "county_id":55998419,
        "planet_id":1,
        "state_id":2344974
    },
    "wof:name":"Ouesso Airport",
    "wof:placetype":"campus"
},
  "geometry": {"coordinates":[16.037901,1.61599],"type":"Point"}
}