{
  "type": "Feature",
  "properties": {
    "gn:admin1_code":"36.0",
    "gn:asciiname":"Eehama",
    "gn:dem":1121,
    "gn:feature_class":"P",
    "gn:feature_code":"PPL",
    "gn:name":"Eehama",
    "gn:population":0,
    "gn:timezone":"Africa/Windhoek",
    "wof:name":"Eehama",
    "wof:placetype":"locality"
},
  "geometry": {"coordinates":[15.01667,-17.38332999999999],"type":"Point"}
}