{
  "type": "Feature",
  "properties": {
    "name:eng_x_variant":[
        "SAR",
        "KSAR"
    ],
    "oa:elevation_ft":"538",
    "oa:type":"small_airport",
    "woe:hierarchy":{
        "country_id":23424977,
        "county_id":12588156,
        "planet_id":1,
        "state_id":2347572
    },
    "wof:name":"Sparta Community Airport-Hunter Field",
    "wof:placetype":"campus"
},
  "geometry": {"coordinates":[-89.6987,38.148899],"type":"Point"}
}