{
  "type": "Feature",
  "properties": {
    "name:ceb_x_preferred":[
        "Thangool Airport"
    ],
    "name:eng_x_preferred":[
        "Thangool Airport"
    ],
    "name:eng_x_variant":[
        "THG",
        "YTNG"
    ],
    "name:fas_x_preferred":[
        "\u0641\u0631\u0648\u062f\u06af\u0627\u0647 \u062a\u0646\u06af\u0648\u0644"
    ],
    "name:jpn_x_preferred":[
        "\u30b5\u30f3\u30b4\u30fc\u30eb\u7a7a\u6e2f"
    ],
    "name:msa_x_preferred":[
        "Lapangan Terbang Thangool"
    ],
    "name:swe_x_preferred":[
        "Thangool Airport"
    ],
    "name:tgk_x_preferred":[
        "\u0424\u0443\u0440\u0443\u0434\u0433\u043e\u04b3\u0438 \u0442\u043d\u0433\u0443\u043b"
    ],
    "name:zho_x_preferred":[
        "\u6bd4\u6d1b\u5a01\u62c9"
    ],
    "oa:elevation_ft":"644",
    "oa:type":"medium_airport",
    "wd:wordcount":34,
    "woe:hierarchy":{
        "country_id":23424748,
        "county_id":56072982,
        "planet_id":1,
        "state_id":2344702
    },
    "wof:name":"Thangool Aerodrome",
    "wof:placetype":"campus"
},
  "geometry": {"coordinates":[150.57600400000001,-24.4939],"type":"Point"}
}