{
  "type": "Feature",
  "properties": {
    "name:ceb_x_preferred":[
        "Shahid Ashrafi Esfahani Airport"
    ],
    "name:eng_x_preferred":[
        "Kermanshah Airport"
    ],
    "name:eng_x_variant":[
        "KSH",
        "OICC"
    ],
    "name:fas_x_preferred":[
        "\u0641\u0631\u0648\u062f\u06af\u0627\u0647 \u0634\u0647\u06cc\u062f \u0627\u0634\u0631\u0641\u06cc \u06a9\u0631\u0645\u0627\u0646\u0634\u0627\u0647"
    ],
    "name:hrv_x_preferred":[
        "Zra\u010dna luka \u0160ahid A\u0161rafi Isfahani"
    ],
    "name:ind_x_preferred":[
        "Bandar Udara Kermanshah"
    ],
    "name:jpn_x_preferred":[
        "\u30b1\u30eb\u30de\u30fc\u30f3\u30b7\u30e3\u30fc"
    ],
    "name:msa_x_preferred":[
        "Lapangan Terbang Shahid Ashrafi Esfahani"
    ],
    "name:pol_x_preferred":[
        "Port lotniczy Kermanszah"
    ],
    "name:ron_x_preferred":[
        "Aeroportul Kermanshah"
    ],
    "name:swe_x_preferred":[
        "Shahid Ashrafi Esfahani Airport"
    ],
    "name:tur_x_preferred":[
        "Kirman\u015fah Havaalan\u0131"
    ],
    "name:vie_x_preferred":[
        "S\u00e2n bay Shahid Ashrafi Esfahani"
    ],
    "name:zho_x_preferred":[
        "\u514b\u723e\u66fc\u6c99\u8d6b"
    ],
    "oa:elevation_ft":"4307",
    "oa:type":"medium_airport",
    "woe:hierarchy":{
        "country_id":23424851,
        "planet_id":1,
        "state_id":2345777
    },
    "wof:name":"Bakhtaran Airport",
    "wof:placetype":"campus"
},
  "geometry": {"coordinates":[47.1581,34.345901],"type":"Point"}
}