{
  "type": "Feature",
  "properties": {
    "name:ceb_x_preferred":[
        "Kempsey Airport"
    ],
    "name:deu_x_preferred":[
        "Flughafen Kempsey"
    ],
    "name:eng_x_preferred":[
        "Kempsey Airport"
    ],
    "name:eng_x_variant":[
        "KPS",
        "YKMP"
    ],
    "name:fas_x_preferred":[
        "\u0641\u0631\u0648\u062f\u06af\u0627\u0647 \u06a9\u0645\u067e\u0633\u06cc"
    ],
    "name:fra_x_preferred":[
        "a\u00e9roport de Kempsey"
    ],
    "name:ita_x_preferred":[
        "aeroporto di Kempsey"
    ],
    "name:msa_x_preferred":[
        "Lapangan Terbang Kempsey"
    ],
    "name:spa_x_preferred":[
        "Kempsey"
    ],
    "name:swe_x_preferred":[
        "Kempsey Airport"
    ],
    "name:tgk_x_preferred":[
        "\u0424\u0443\u0440\u0443\u0434\u0433\u043e\u04b3\u0438 \u043a\u043c\u043f\u0441\u0438"
    ],
    "oa:elevation_ft":"54",
    "oa:type":"medium_airport",
    "wd:wordcount":49,
    "woe:hierarchy":{
        "country_id":23424748,
        "county_id":55864427,
        "planet_id":1,
        "state_id":2344700
    },
    "wof:name":"Kempsey Airport",
    "wof:placetype":"campus"
},
  "geometry": {"coordinates":[152.770004,-31.0744],"type":"Point"}
}