{
  "type": "Feature",
  "properties": {
    "name:eng_x_preferred":[
        "Osmanabad Airport"
    ],
    "name:eng_x_variant":[
        "OMN"
    ],
    "name:fas_x_preferred":[
        "\u0641\u0631\u0648\u062f\u06af\u0627\u0647 \u0634\u0647\u0631\u06cc \u0627\u0648\u0631\u0645\u0648\u0646\u062f \u0628\u06cc\u0686"
    ],
    "name:per_x_preferred":[
        "\u0641\u0631\u0648\u062f\u06af\u0627\u0647 \u0639\u062b\u0645\u0627\u0646\u200c\u0622\u0628\u0627\u062f"
    ],
    "name:swe_x_preferred":[
        "Osmanabad Airport"
    ],
    "name:tgk_x_preferred":[
        "\u0424\u0443\u0440\u0443\u0434\u0433\u043e\u04b3\u0438 \u0448\u0430\u04b3\u0440\u0435 \u043e\u0432\u0440\u043c\u0443\u043d\u0434 \u0431\u0438\u0447"
    ],
    "oa:elevation_ft":"2277",
    "oa:type":"small_airport",
    "wd:wordcount":391,
    "woe:hierarchy":{
        "country_id":23424977,
        "county_id":12587866,
        "planet_id":1,
        "state_id":2347568
    },
    "wof:name":"Ormond Beach Municipal Airport",
    "wof:placetype":"campus"
},
  "geometry": {"coordinates":[76.0574,18.281],"type":"Point"}
}