{
  "type": "Feature",
  "properties": {
    "gn:admin1_code":"40.0",
    "gn:asciiname":"Kambowo",
    "gn:dem":1090,
    "gn:feature_class":"P",
    "gn:feature_code":"PPL",
    "gn:name":"Kambowo",
    "gn:population":0,
    "gn:timezone":"Africa/Windhoek",
    "wof:name":"Kambowo",
    "wof:placetype":"locality"
},
  "geometry": {"coordinates":[19.96667,-17.93332999999999],"type":"Point"}
}