{
  "type": "Feature",
  "properties": {
    "wd:wordcount":8882,
    "wof:name":"Upper Westside",
    "wof:placetype":"neighbourhood"
},
  "geometry": {"coordinates":[-122.04842257016286,36.97019788337783],"type":"Point"}
}