{
  "type": "Feature",
  "properties": {
    "gn:admin1_code":"31.0",
    "gn:asciiname":"Velloorsdrift",
    "gn:dem":465,
    "gn:feature_class":"P",
    "gn:feature_code":"PPL",
    "gn:name":"Velloorsdrift",
    "gn:population":0,
    "gn:timezone":"Africa/Windhoek",
    "name:und_x_variant":[
        "Velloor Drift",
        "Vellorsdrift",
        "Velloorsdrift"
    ],
    "wof:name":"Velloorsdrift",
    "wof:placetype":"locality"
},
  "geometry": {"coordinates":[19.25,-28.75],"type":"Point"}
}