{
  "type": "Feature",
  "properties": {
    "wof:name":"South Renton",
    "wof:placetype":"neighbourhood"
},
  "geometry": {"coordinates":[-122.21091519625975,47.47579417241833],"type":"Point"}
}