{
  "type": "Feature",
  "properties": {
    "gn:admin1_code":"28.0",
    "gn:asciiname":"Sikwalo",
    "gn:dem":944,
    "gn:feature_class":"P",
    "gn:feature_code":"PPL",
    "gn:name":"Sikwalo",
    "gn:population":0,
    "gn:timezone":"Africa/Windhoek",
    "wof:name":"Sikwalo",
    "wof:placetype":"locality"
},
  "geometry": {"coordinates":[23.85,-18.21667],"type":"Point"}
}