{
  "type": "Feature",
  "properties": {
    "name:ceb_x_preferred":[
        "Guapiles Airport"
    ],
    "name:eng_x_preferred":[
        "Gu\u00e1piles Airport"
    ],
    "name:eng_x_variant":[
        "GPL",
        "MRGP"
    ],
    "name:fas_x_preferred":[
        "\u0641\u0631\u0648\u062f\u06af\u0627\u0647 \u06af\u0648\u0622\u067e\u06cc\u0644\u0633"
    ],
    "name:jpn_x_preferred":[
        "\u30b0\u30a2\u30d4\u30ec\u30b9\u7a7a\u6e2f"
    ],
    "name:msa_x_preferred":[
        "Lapangan Terbang Guapiles"
    ],
    "name:ron_x_preferred":[
        "Aeroportul Gu\u00e1piles"
    ],
    "name:swe_x_preferred":[
        "Guapiles Airport"
    ],
    "name:tgk_x_preferred":[
        "\u0424\u0443\u0440\u0443\u0434\u0433\u043e\u04b3\u0438 \u0433\u0443\u043e\u043f\u0438\u043b\u0441"
    ],
    "name:zho_x_preferred":[
        "\u74dc\u76ae\u840a\u65af\u6a5f\u5834"
    ],
    "oa:elevation_ft":"883",
    "oa:type":"medium_airport",
    "wd:wordcount":49,
    "woe:hierarchy":{
        "country_id":23424791,
        "county_id":26808839,
        "localadmin_id":26809006,
        "planet_id":1,
        "state_id":2345086
    },
    "wof:name":"Guapiles Airport",
    "wof:placetype":"campus"
},
  "geometry": {"coordinates":[-83.796997,10.2172],"type":"Point"}
}