{
  "type": "Feature",
  "properties": {
    "name:ceb_x_preferred":[
        "Elcho Island Airport"
    ],
    "name:deu_x_preferred":[
        "Elcho Island Airport"
    ],
    "name:eng_x_preferred":[
        "Elcho Island Airport"
    ],
    "name:eng_x_variant":[
        "ELC",
        "YELD"
    ],
    "name:fra_x_preferred":[
        "Elcho Island Airport"
    ],
    "name:msa_x_preferred":[
        "Lapangan Terbang Elcho I"
    ],
    "name:ron_x_preferred":[
        "Aeroportul Elcho Island"
    ],
    "name:rus_x_preferred":[
        "\u042d\u043b\u043a\u043e-\u0410\u0439\u043b\u0435\u043d\u0434"
    ],
    "name:swe_x_preferred":[
        "Elcho Island Airport"
    ],
    "name:zho_x_preferred":[
        "\u57c3\u723e\u79d1\u5cf6\u6a5f\u5834"
    ],
    "oa:elevation_ft":"101",
    "oa:type":"medium_airport",
    "wd:wordcount":43,
    "woe:hierarchy":{
        "country_id":23424748,
        "planet_id":1,
        "state_id":2344701
    },
    "wof:name":"Elcho Island Airport",
    "wof:placetype":"campus"
},
  "geometry": {"coordinates":[135.57065,-12.019338],"type":"Point"}
}