{
  "type": "Feature",
  "properties": {
    "name:eng_x_preferred":[
        "Winston Field Airport"
    ],
    "name:eng_x_variant":[
        "SNK",
        "KSNK"
    ],
    "name:ron_x_preferred":[
        "Aeroportul Winston Field"
    ],
    "oa:elevation_ft":"2430",
    "oa:type":"small_airport",
    "woe:hierarchy":{
        "country_id":23424977,
        "county_id":12590214,
        "planet_id":1,
        "state_id":2347602
    },
    "wof:name":"Winston Field Airport",
    "wof:placetype":"campus"
},
  "geometry": {"coordinates":[-100.949997,32.693401],"type":"Point"}
}