{
  "type": "Feature",
  "properties": {
    "name:cat_x_preferred":[
        "Aeroport de Kirkenes-Hoybuktmon"
    ],
    "name:ceb_x_preferred":[
        "Kirkenes"
    ],
    "name:dan_x_preferred":[
        "Kirkenes Lufthavn"
    ],
    "name:deu_x_preferred":[
        "Flughafen Kirkenes"
    ],
    "name:eng_x_preferred":[
        "Kirkenes Airport"
    ],
    "name:eng_x_variant":[
        "KKN",
        "ENKR"
    ],
    "name:fas_x_preferred":[
        "\u0641\u0631\u0648\u062f\u06af\u0627\u0647 \u06a9\u0631\u06a9\u0646\u0633"
    ],
    "name:fin_x_preferred":[
        "Kirkkoniemen lentoasema"
    ],
    "name:fra_x_preferred":[
        "A\u00e9roport de Kirkenes"
    ],
    "name:fra_x_variant":[
        "a\u00e9roport de Kirkenes"
    ],
    "name:jpn_x_preferred":[
        "\u30d2\u30eb\u30b1\u30cd\u30b9"
    ],
    "name:msa_x_preferred":[
        "Lapangan Terbang Hoybuktmoen"
    ],
    "name:nld_x_preferred":[
        "Luchthaven Kirkenes H\u00f8ybuktmoen"
    ],
    "name:nno_x_preferred":[
        "Kirkenes lufthamn"
    ],
    "name:nob_x_preferred":[
        "Kirkenes lufthavn"
    ],
    "name:nor_x_preferred":[
        "Kirkenes lufthavn"
    ],
    "name:pol_x_preferred":[
        "Port lotniczy Kirkenes"
    ],
    "name:rus_x_preferred":[
        "\u041a\u0438\u0440\u043a\u0435\u043d\u0435\u0441"
    ],
    "name:spa_x_preferred":[
        "Aeropuerto de Kirkenes-H\u00f8ybuktmoen"
    ],
    "name:swe_x_preferred":[
        "Kirkenes flygplats"
    ],
    "name:tgk_x_preferred":[
        "\u0424\u0443\u0440\u0443\u0434\u0433\u043e\u04b3\u0438 \u043a\u0440\u043a\u043d\u0441"
    ],
    "name:vie_x_preferred":[
        "S\u00e2n bay Kirkenes"
    ],
    "oa:elevation_ft":"283",
    "oa:type":"medium_airport",
    "wd:wordcount":3159,
    "woe:hierarchy":{
        "country_id":23424910,
        "county_id":12592966,
        "planet_id":1,
        "state_id":2346388
    },
    "wof:name":"Kirkenes lufthavn H\u00f8ybuktmoen",
    "wof:placetype":"campus"
},
  "geometry": {"coordinates":[29.8913,69.72580000000001],"type":"Point"}
}