{
  "type": "Feature",
  "properties": {
    "oa:elevation_ft":"2461",
    "oa:type":"small_airport",
    "woe:hierarchy":{
        "country_id":23424982,
        "county_id":26804526,
        "localadmin_id":26805498,
        "planet_id":1,
        "state_id":2347687
    },
    "wof:name":"Churuguara Airport",
    "wof:placetype":"campus"
},
  "geometry": {"coordinates":[-69.638378,10.807568],"type":"Point"}
}