{
  "type": "Feature",
  "properties": {
    "name:ceb_x_preferred":[
        "Chongjin Airport"
    ],
    "name:deu_x_preferred":[
        "Flughafen Ch\u2019\u014fngjin"
    ],
    "name:eng_x_preferred":[
        "Chongjin Airport"
    ],
    "name:fas_x_preferred":[
        "\u0641\u0631\u0648\u062f\u06af\u0627\u0647 \u0686\u0648\u0646\u06af\u062c\u06cc\u0646"
    ],
    "name:ind_x_preferred":[
        "Bandar Udara Chongjin"
    ],
    "name:jpn_x_preferred":[
        "\u6e05\u6d25\u7a7a\u6e2f"
    ],
    "name:kor_x_preferred":[
        "\uccad\uc9c4\uacf5\ud56d"
    ],
    "name:pol_x_preferred":[
        "Port lotniczy Ch'\u014fngjin"
    ],
    "name:ron_x_preferred":[
        "Aeroportul Chongjin"
    ],
    "name:spa_x_preferred":[
        "Aeropuerto de Chongjin"
    ],
    "name:swe_x_preferred":[
        "Chongjin Airport"
    ],
    "name:tgk_x_preferred":[
        "\u0424\u0443\u0440\u0443\u0434\u0433\u043e\u04b3\u0438 \u0447\u0443\u043d\u0433\u04b7\u0438\u043d"
    ],
    "name:vie_x_preferred":[
        "S\u00e2n bay Chongjin"
    ],
    "name:zho_x_preferred":[
        "\u6e05\u6d25\u6a5f\u5834"
    ],
    "oa:elevation_ft":"12",
    "oa:type":"medium_airport",
    "wd:wordcount":156,
    "woe:hierarchy":{
        "country_id":23424865,
        "planet_id":1,
        "state_id":2345958
    },
    "wof:name":"Chongjin Airport",
    "wof:placetype":"campus"
},
  "geometry": {"coordinates":[129.64879999999999,41.4297],"type":"Point"}
}