{
  "type": "Feature",
  "properties": {
    "name:ceb_x_preferred":[
        "Jandakot Airport"
    ],
    "name:deu_x_preferred":[
        "Jandakot Airport"
    ],
    "name:eng_x_preferred":[
        "Jandakot Airport"
    ],
    "name:eng_x_variant":[
        "JAD",
        "YPJT"
    ],
    "name:fas_x_preferred":[
        "\u0641\u0631\u0648\u062f\u06af\u0627\u0647 \u062c\u0627\u0646\u062f\u0627\u06a9\u0648\u062a"
    ],
    "name:fra_x_preferred":[
        "A\u00e9roport Jandakot"
    ],
    "name:fra_x_variant":[
        "a\u00e9roport Jandakot"
    ],
    "name:ita_x_preferred":[
        "aeroporto Jandakot"
    ],
    "name:msa_x_preferred":[
        "Lapangan Terbang Jandakot"
    ],
    "name:ron_x_preferred":[
        "Aeroportul Jandakot"
    ],
    "name:swe_x_preferred":[
        "Jandakot Airport"
    ],
    "name:tgk_x_preferred":[
        "\u0424\u0443\u0440\u0443\u0434\u0433\u043e\u04b3\u0438 \u04b7\u043e\u043d\u0434\u043e\u043a\u0443\u0442"
    ],
    "name:zho_x_preferred":[
        "\u8a79\u9054\u79d1\u7279\u6a5f\u5834"
    ],
    "oa:elevation_ft":"99",
    "oa:type":"medium_airport",
    "wd:wordcount":912,
    "woe:hierarchy":{
        "country_id":23424748,
        "planet_id":1,
        "state_id":2344706,
        "suburb_id":7226164
    },
    "wof:name":"Perth Jandakot Airport",
    "wof:placetype":"campus"
},
  "geometry": {"coordinates":[115.88099699999999,-32.0975],"type":"Point"}
}