{
  "type": "Feature",
  "properties": {
    "name:eng_x_preferred":[
        "Chait\u00e9n Airport"
    ],
    "name:eng_x_variant":[
        "WCH",
        "SCTN"
    ],
    "name:jpn_x_preferred":[
        "\u30c1\u30e3\u30a4\u30c6\u30f3\u98db\u884c\u5834"
    ],
    "name:msa_x_preferred":[
        "Lapangan Terbang Chaiten"
    ],
    "name:spa_x_preferred":[
        "Aeropuerto Chait\u00e9n"
    ],
    "name:swe_x_preferred":[
        "Chait\u00e9n Airport"
    ],
    "oa:elevation_ft":"13",
    "oa:type":"medium_airport",
    "wd:wordcount":65,
    "woe:hierarchy":{
        "country_id":23424782,
        "county_id":26794009,
        "localadmin_id":26794175,
        "planet_id":1,
        "state_id":2345026
    },
    "wof:name":"Chaiten Airport",
    "wof:placetype":"campus"
},
  "geometry": {"coordinates":[-72.69909699999999,-42.9328],"type":"Point"}
}