{
  "type": "Feature",
  "properties": {
    "gn:admin1_code":"37.0",
    "gn:asciiname":"Oniimwandi",
    "gn:dem":1098,
    "gn:feature_class":"P",
    "gn:feature_code":"PPL",
    "gn:name":"Oniimwandi",
    "gn:population":0,
    "gn:timezone":"Africa/Windhoek",
    "wof:name":"Oniimwandi",
    "wof:placetype":"locality"
},
  "geometry": {"coordinates":[15.63333,-17.78333],"type":"Point"}
}