{
  "type": "Feature",
  "properties": {
    "name:ceb_x_preferred":[
        "Columbus Park"
    ],
    "wd:wordcount":42,
    "wof:name":"Columbus Park",
    "wof:placetype":"neighbourhood"
},
  "geometry": {"coordinates":[-94.57063541332059,39.11136509525049],"type":"Point"}
}