{
  "type": "Feature",
  "properties": {
    "name:eng_x_preferred":[
        "Hachimanmachi 2 Chome"
    ],
    "name:eng_x_variant":[
        "Hachimanmachi 2 Choume",
        "Hachimanmachi 2 Chome"
    ],
    "name:jpn_x_preferred":[
        "\uff12\u4e01\u76ee"
    ],
    "name:jpn_x_variant":[
        "\u306f\u3061\u307e\u3093\u307e\u3061 \uff12\u3061\u3087\u3046\u3081",
        "\u516b\u5e61\u753a \uff12\u4e01\u76ee",
        "\uff12\u3061\u3087\u3046\u3081"
    ],
    "qs:gn_local":0,
    "qs:local_max":57,
    "qs:local_sum":75,
    "qs:localhoods":2,
    "qs:name":"\uff12\u4e01\u76ee",
    "qs:name_adm0":"\u65e5\u672c",
    "qs:name_adm1":"\u5bcc\u5c71\u770c",
    "qs:name_en":"Hachimanmachi 2 Chome",
    "qs:name_lau":"\u516b\u5e61\u753a",
    "qs:name_local":"\u5c04\u6c34\u5e02",
    "qs:photo_max":20,
    "qs:photo_sum":57,
    "qs:placetype":"Suburb",
    "qs:quad_count":7,
    "qs:woe_adm0":23424856,
    "qs:woe_adm1":2345891,
    "qs:woe_adm2":0,
    "qs:woe_lau":28425397,
    "qs:woe_local":28379200,
    "qs:woe_ver":"7.10.0",
    "wof:lang":[
        "jpn"
    ],
    "wof:name":"\uff12\u4e01\u76ee",
    "wof:placetype":"neighbourhood"
},
  "geometry": {"coordinates":[137.10788099999999,36.780229],"type":"Point"}
}