{
  "type": "Feature",
  "properties": {
    "gn:admin1_code":"31.0",
    "gn:asciiname":"Kronlein",
    "gn:dem":998,
    "gn:feature_class":"P",
    "gn:feature_code":"PPL",
    "gn:name":"Kr\u00f6nlein",
    "gn:population":0,
    "gn:timezone":"Africa/Windhoek",
    "wof:name":"Kronlein",
    "wof:placetype":"locality"
},
  "geometry": {"coordinates":[18.15,-26.58333],"type":"Point"}
}