{
  "type": "Feature",
  "properties": {
    "gn:admin1_code":"28.0",
    "gn:asciiname":"Sapelapela",
    "gn:dem":963,
    "gn:feature_class":"P",
    "gn:feature_code":"PPL",
    "gn:name":"Sapelapela",
    "gn:population":0,
    "gn:timezone":"Africa/Windhoek",
    "name:und_x_variant":[
        "Saperaperas",
        "Sapelapela"
    ],
    "wof:name":"Sapelapela",
    "wof:placetype":"locality"
},
  "geometry": {"coordinates":[23.85,-17.75],"type":"Point"}
}