{
  "type": "Feature",
  "properties": {
    "name:ceb_x_preferred":[
        "Bodrum-Imsik Airport"
    ],
    "name:eng_x_preferred":[
        "Bodrum-Imsik Airport"
    ],
    "name:eng_x_variant":[
        "BXN",
        "LTBV"
    ],
    "name:fas_x_preferred":[
        "\u0641\u0631\u0648\u062f\u06af\u0627\u0647 \u0628\u0648\u062f\u0631\u0648\u0645-\u06cc\u0645\u0633\u06cc\u06a9"
    ],
    "name:jpn_x_preferred":[
        "\u30dc\u30c9\u30eb\u30e0\u30fb\u30a4\u30e0\u30ba\u30a3\u7a7a\u6e2f"
    ],
    "name:msa_x_preferred":[
        "Lapangan Terbang Imsik"
    ],
    "name:ron_x_preferred":[
        "Aeroportul Bodrum-Imsik"
    ],
    "name:tgk_x_preferred":[
        "\u0424\u0443\u0440\u0443\u0434\u0433\u043e\u04b3\u0438 \u0411\u043e\u0434\u0440\u0443\u043c-\u0418\u043c\u0441\u0438\u043a"
    ],
    "name:tgk_x_variant":[
        "\u0424\u0443\u0440\u0443\u0434\u0433\u043e\u04b3\u0438 \u0431\u0443\u0434\u0440\u0443\u043c-\u0438\u043c\u0441\u0438\u043a"
    ],
    "name:tur_x_preferred":[
        "Bodrum-Ims\u0131k Havaalan\u0131"
    ],
    "name:zho_x_preferred":[
        "\u535a\u5fb7\u9b6f\u59c6-Imsik\u6a5f\u5834"
    ],
    "oa:elevation_ft":"202",
    "oa:type":"small_airport",
    "wd:wordcount":29,
    "woe:hierarchy":{
        "country_id":23424969,
        "county_id":29390164,
        "planet_id":1,
        "state_id":2347301
    },
    "wof:name":"Imsik Airport",
    "wof:placetype":"campus"
},
  "geometry": {"coordinates":[27.669701,37.140099],"type":"Point"}
}