{
  "type": "Feature",
  "properties": {
    "gn:admin1_code":"32.0",
    "gn:asciiname":"Otjovasandu",
    "gn:dem":1259,
    "gn:feature_class":"P",
    "gn:feature_code":"PPL",
    "gn:name":"Otjovasandu",
    "gn:population":0,
    "gn:timezone":"Africa/Windhoek",
    "name:und_x_variant":[
        "Otjovasando",
        "Otjovazandu",
        "Otjovasondu",
        "Otjovasandu"
    ],
    "wof:name":"Otjovasandu",
    "wof:placetype":"locality"
},
  "geometry": {"coordinates":[14.48333,-19.23333],"type":"Point"}
}