{
  "type": "Feature",
  "properties": {
    "name:deu_x_preferred":[
        "Flughafen Mtwara"
    ],
    "name:eng_x_preferred":[
        "Mtwara Airport"
    ],
    "name:eng_x_variant":[
        "MYW",
        "HTMT"
    ],
    "name:fas_x_preferred":[
        "\u0641\u0631\u0648\u062f\u06af\u0627\u0647 \u0627\u0645\u062a\u0648\u0627\u0631\u0627"
    ],
    "name:ger_x_preferred":[
        "Flughafen Mtwara"
    ],
    "name:jpn_x_preferred":[
        "\u30e0\u30c8\u30ef\u30e9\u7a7a\u6e2f"
    ],
    "name:may_x_preferred":[
        "Lapangan Terbang Mtwara"
    ],
    "name:msa_x_preferred":[
        "Lapangan Terbang Mtwara"
    ],
    "name:nob_x_preferred":[
        "Mtwara lufthavn"
    ],
    "name:nor_x_preferred":[
        "Mtwara lufthavn"
    ],
    "name:per_x_preferred":[
        "\u0641\u0631\u0648\u062f\u06af\u0627\u0647 \u0627\u0645\u062a\u0648\u0627\u0631\u0627"
    ],
    "name:pol_x_preferred":[
        "Port lotniczy Mtwara"
    ],
    "name:swa_x_preferred":[
        "Uwanja wa ndege wa Mtwara"
    ],
    "oa:elevation_ft":"371",
    "oa:type":"medium_airport",
    "wd:wordcount":99,
    "woe:hierarchy":{
        "country_id":23424973,
        "county_id":56025168,
        "planet_id":1,
        "state_id":2347362
    },
    "wof:name":"Mtwara Airport",
    "wof:placetype":"campus"
},
  "geometry": {"coordinates":[40.181801,-10.3391],"type":"Point"}
}