{
  "type": "Feature",
  "properties": {
    "name:ara_x_preferred":[
        "\u0645\u0637\u0627\u0631 \u0645\u0627\u0631\u064a\u0646\u062f\u0648\u0643"
    ],
    "name:ceb_x_preferred":[
        "Marinduque Airport"
    ],
    "name:cym_x_preferred":[
        "Maes Awyr Marinduque"
    ],
    "name:eng_x_preferred":[
        "Marinduque Airport"
    ],
    "name:eng_x_variant":[
        "MRQ",
        "RPUW"
    ],
    "name:fas_x_preferred":[
        "\u0641\u0631\u0648\u062f\u06af\u0627\u0647 \u0645\u0627\u0631\u06cc\u0646\u062f\u0648\u06a9"
    ],
    "name:jpn_x_preferred":[
        "\u30de\u30ea\u30f3\u30c9\u30a5\u30b1\u7a7a\u6e2f"
    ],
    "name:msa_x_preferred":[
        "Lapangan Terbang Marinduque"
    ],
    "name:ron_x_preferred":[
        "Aeroportul Marinduque"
    ],
    "name:tgl_x_preferred":[
        "Paliparan ng Marinduque"
    ],
    "oa:elevation_ft":"32",
    "oa:type":"medium_airport",
    "wd:wordcount":174,
    "woe:hierarchy":{
        "country_id":23424934,
        "county_id":2346693,
        "planet_id":1,
        "state_id":23424719
    },
    "wof:name":"Marinduque Airport",
    "wof:placetype":"campus"
},
  "geometry": {"coordinates":[121.825256,13.360028],"type":"Point"}
}