{
  "type": "Feature",
  "properties": {
    "name:ceb_x_preferred":[
        "Taylor County Airport"
    ],
    "name:eng_x_preferred":[
        "Taylor County Airport"
    ],
    "name:fas_x_preferred":[
        "\u0641\u0631\u0648\u062f\u06af\u0627\u0647 \u0634\u0647\u0631\u0633\u062a\u0627\u0646 \u062a\u06cc\u0644\u0648\u0631"
    ],
    "name:fra_x_preferred":[
        "MDZ"
    ],
    "name:tgk_x_preferred":[
        "\u0424\u0443\u0440\u0443\u0434\u0433\u043e\u04b3\u0438 \u0448\u0430\u04b3\u0440\u0438\u0441\u0442\u043e\u043d \u0442\u0430\u0431\u0430\u043b\u0432\u0443\u0440"
    ],
    "name:urd_x_preferred":[
        "\u0679\u06cc\u0644\u0631 \u06a9\u0627\u0624\u0646\u0679\u06cc \u0627\u06cc\u0626\u0631\u067e\u0648\u0631\u0679"
    ],
    "oa:elevation_ft":"1478",
    "oa:type":"small_airport",
    "wd:wordcount":37,
    "woe:hierarchy":{
        "country_id":23424977,
        "county_id":12590594,
        "planet_id":1,
        "state_id":2347608
    },
    "wof:name":"Taylor County Airport",
    "wof:placetype":"campus"
},
  "geometry": {"coordinates":[-90.3008,45.1014],"type":"Point"}
}