{
  "type": "Feature",
  "properties": {
    "wof:name":"Woodland Heath",
    "wof:placetype":"neighbourhood"
},
  "geometry": {"coordinates":[-71.14773910115879,42.3195478151954],"type":"Point"}
}