{
  "type": "Feature",
  "properties": {
    "name:ben_x_preferred":[
        "\u0993\u09af\u09bc\u09be\u09b6\u09bf\u0982\u099f\u09a8 \u0995\u09be\u0989\u09a8\u09cd\u099f\u09bf \u09ac\u09bf\u09ae\u09be\u09a8\u09ac\u09a8\u09cd\u09a6\u09b0"
    ],
    "name:ceb_x_preferred":[
        "Washington County Airport"
    ],
    "name:eng_x_preferred":[
        "Washington County Airport"
    ],
    "name:eng_x_variant":[
        "AFJ"
    ],
    "name:fas_x_preferred":[
        "\u0641\u0631\u0648\u062f\u06af\u0627\u0647 \u0648\u0627\u0634\u0646\u06af\u062a\u0646 \u06a9\u0627\u0646\u062a\u06cc"
    ],
    "name:jpn_x_preferred":[
        "\u30ef\u30b7\u30f3\u30c8\u30f3\u90e1\u7a7a\u6e2f"
    ],
    "name:ron_x_preferred":[
        "Aeroportul Washington County"
    ],
    "name:tgk_x_preferred":[
        "\u0424\u0443\u0440\u0443\u0434\u0433\u043e\u04b3\u0438 \u0432\u043e\u0448\u0430\u043d\u0433\u0442\u0443\u043d \u043a\u043e\u043d"
    ],
    "name:urd_x_preferred":[
        "\u0648\u0627\u0634\u0646\u06af\u0679\u0646 \u06a9\u0627\u0624\u0646\u0679\u06cc \u0627\u06cc\u0626\u0631\u067e\u0648\u0631\u0679"
    ],
    "oa:elevation_ft":"1184",
    "oa:type":"small_airport",
    "wd:wordcount":44,
    "woe:hierarchy":{
        "country_id":23424977,
        "county_id":12589790,
        "planet_id":1,
        "state_id":2347597
    },
    "wof:name":"Washington County Airport",
    "wof:placetype":"campus"
},
  "geometry": {"coordinates":[-80.2903,40.1364],"type":"Point"}
}