{
  "type": "Feature",
  "properties": {
    "name:eng_x_variant":[
        "AFJ"
    ],
    "oa:elevation_ft":"1184",
    "oa:type":"small_airport",
    "wd:wordcount":44,
    "woe:hierarchy":{
        "country_id":23424977,
        "county_id":12589790,
        "planet_id":1,
        "state_id":2347597
    },
    "wof:name":"Washington County Airport",
    "wof:placetype":"campus"
},
  "geometry": {"coordinates":[-80.2903,40.1364],"type":"Point"}
}