{
  "type": "Feature",
  "properties": {
    "name:ara_x_preferred":[
        "\u0645\u0637\u0627\u0631 \u0643\u064a\u0641\u0629"
    ],
    "name:fas_x_preferred":[
        "\u0641\u0631\u0648\u062f\u06af\u0627\u0647 \u06a9\u06cc\u0641\u0627"
    ],
    "name:pol_x_preferred":[
        "Port lotniczy Kiffa"
    ],
    "name:tgk_x_preferred":[
        "\u0424\u0443\u0440\u0443\u0434\u0433\u043e\u04b3\u0438 \u043a\u0438\u0444\u043e"
    ],
    "oa:elevation_ft":"424",
    "oa:type":"small_airport",
    "wd:wordcount":47,
    "woe:hierarchy":{
        "country_id":23424896,
        "planet_id":1,
        "state_id":2346243
    },
    "wof:name":"Kiffa Airport",
    "wof:placetype":"campus"
},
  "geometry": {"coordinates":[-11.406111111111,16.589722222222],"type":"Point"}
}