{
  "type": "Feature",
  "properties": {
    "name:ben_x_preferred":[
        "\u09a1\u09bf\u09ae\u09be\u09aa\u09c1\u09b0 \u09ac\u09bf\u09ae\u09be\u09a8\u09ac\u09a8\u09cd\u09a6\u09b0"
    ],
    "name:ceb_x_preferred":[
        "Dimapur Airport"
    ],
    "name:cym_x_preferred":[
        "Maes Awyr Dimapur"
    ],
    "name:deu_x_preferred":[
        "Flughafen Dimapur"
    ],
    "name:eng_x_preferred":[
        "Dimapur Airport"
    ],
    "name:eng_x_variant":[
        "DMU",
        "VEMR"
    ],
    "name:fas_x_preferred":[
        "\u0641\u0631\u0648\u062f\u06af\u0627\u0647 \u062f\u06cc\u0645\u0627\u067e\u0648\u0631"
    ],
    "name:fra_x_preferred":[
        "A\u00e9roport de Dimapur"
    ],
    "name:fra_x_variant":[
        "a\u00e9roport de Dimapur"
    ],
    "name:hin_x_preferred":[
        "\u0926\u0940\u092e\u093e\u092a\u0941\u0930 \u0935\u093f\u092e\u093e\u0928\u0915\u094d\u0937\u0947\u0924\u094d\u0930"
    ],
    "name:jpn_x_preferred":[
        "\u30c7\u30a3\u30de\u30d7\u30eb\u7a7a\u6e2f"
    ],
    "name:mar_x_preferred":[
        "\u0926\u093f\u092e\u093e\u092a\u0942\u0930 \u0935\u093f\u092e\u093e\u0928\u0924\u0933"
    ],
    "name:msa_x_preferred":[
        "Lapangan Terbang Dimapur"
    ],
    "name:nob_x_preferred":[
        "Dimapur flyplass"
    ],
    "name:nor_x_preferred":[
        "Dimapur flyplass"
    ],
    "name:ron_x_preferred":[
        "Aeroportul Dimapur"
    ],
    "name:spa_x_preferred":[
        "Aeropuerto de Dimapur"
    ],
    "name:swe_x_preferred":[
        "Dimapur Airport"
    ],
    "name:tam_x_preferred":[
        "\u0ba4\u0bbf\u0bae\u0bbe\u0baa\u0bc2\u0bb0\u0bcd \u0bb5\u0bbf\u0bae\u0bbe\u0ba9 \u0ba8\u0bbf\u0bb2\u0bc8\u0baf\u0bae\u0bcd"
    ],
    "name:tgk_x_preferred":[
        "\u0424\u0443\u0440\u0443\u0434\u0433\u043e\u04b3\u0438 \u0434\u0438\u043c\u043e\u043f\u0443\u0440"
    ],
    "name:vie_x_preferred":[
        "S\u00e2n bay Dimapur"
    ],
    "name:zho_x_preferred":[
        "\u8fea\u99ac\u666e\u723e\u6a5f\u5834"
    ],
    "oa:elevation_ft":"487",
    "oa:type":"medium_airport",
    "wd:wordcount":96,
    "woe:hierarchy":{
        "country_id":23424848,
        "county_id":28298869,
        "planet_id":1,
        "state_id":2345754
    },
    "wof:name":"Dimapur Airport",
    "wof:placetype":"campus"
},
  "geometry": {"coordinates":[93.771103,25.8839],"type":"Point"}
}