{
  "type": "Feature",
  "properties": {
    "name:chi_x_preferred":[
        "\u82f1\u570b\u7687\u5bb6\u7a7a\u8ecd\u6c83\u4e01\u9813\u57fa\u5730"
    ],
    "name:dut_x_preferred":[
        "RAF Waddington"
    ],
    "name:eng_x_preferred":[
        "RAF Waddington"
    ],
    "name:eng_x_variant":[
        "WTN",
        "EGXW"
    ],
    "name:fre_x_preferred":[
        "RAF Waddington"
    ],
    "name:ger_x_preferred":[
        "RAF Waddington"
    ],
    "name:jpn_x_preferred":[
        "\u30ef\u30c7\u30a3\u30f3\u30c8\u30f3\u7a7a\u8ecd\u57fa\u5730"
    ],
    "name:may_x_preferred":[
        "Pengkalan Udara Waddington"
    ],
    "name:per_x_preferred":[
        "\u0641\u0631\u0648\u062f\u06af\u0627\u0647 \u0646\u06cc\u0631\u0648\u06cc \u0647\u0648\u0627\u06cc\u06cc \u0633\u0644\u0637\u0646\u062a\u06cc \u0648\u062f\u06cc\u0646\u06af\u062a\u0648\u0646"
    ],
    "name:swe_x_preferred":[
        "RAF Waddington"
    ],
    "name:tgk_x_preferred":[
        "\u0424\u0443\u0440\u0443\u0434\u0433\u043e\u04b3\u0438 \u043d\u0435\u0440\u04ef\u0435 \u04b3\u0430\u0432\u043e \u0441\u0430\u043b\u0442\u0430\u043d\u0430\u0442\u0435 \u0432\u0434\u0438\u043d\u0433\u0442\u0443\u043d"
    ],
    "oa:elevation_ft":"231",
    "oa:type":"medium_airport",
    "woe:hierarchy":{
        "country_id":23424975,
        "county_id":12602145,
        "localadmin_id":12696019,
        "planet_id":1,
        "state_id":24554868
    },
    "wof:name":"Waddington Airport",
    "wof:placetype":"campus"
},
  "geometry": {"coordinates":[-0.523811,53.166199],"type":"Point"}
}