{
  "type": "Feature",
  "properties": {
    "name:eng_x_preferred":[
        "Ciudad Piar Airport"
    ],
    "name:msa_x_preferred":[
        "Lapangan Terbang Ciudad Piar"
    ],
    "name:ron_x_preferred":[
        "Aeroportul Ciudad Piar"
    ],
    "oa:elevation_ft":"879",
    "oa:type":"small_airport",
    "woe:hierarchy":{
        "country_id":23424982,
        "county_id":26804566,
        "localadmin_id":26805576,
        "planet_id":1,
        "state_id":2347682
    },
    "wof:name":"Ciudad Piar Airport",
    "wof:placetype":"campus"
},
  "geometry": {"coordinates":[-63.270228,7.492758],"type":"Point"}
}