{
  "type": "Feature",
  "properties": {
    "gn:admin1_code":"40.0",
    "gn:asciiname":"Shinyungwe",
    "gn:dem":1039,
    "gn:feature_class":"P",
    "gn:feature_code":"PPL",
    "gn:name":"Shinyungwe",
    "gn:population":0,
    "gn:timezone":"Africa/Windhoek",
    "name:und_x_variant":[
        "Shinyungwa",
        "Shinyungwe"
    ],
    "wof:name":"Shinyungwe",
    "wof:placetype":"locality"
},
  "geometry": {"coordinates":[20.86667000000001,-18.01667],"type":"Point"}
}