{
  "type": "Feature",
  "properties": {
    "name:ceb_x_preferred":[
        "Matari Airport"
    ],
    "name:eng_x_preferred":[
        "Matari Airport"
    ],
    "name:eng_x_variant":[
        "IRP",
        "FZJH"
    ],
    "name:fas_x_preferred":[
        "\u0641\u0631\u0648\u062f\u06af\u0627\u0647 \u0645\u0627\u062a\u0627\u0631\u06cc"
    ],
    "name:ind_x_preferred":[
        "Bandar Udara Matari"
    ],
    "name:jpn_x_preferred":[
        "\u30a4\u30b7\u30ed\u7a7a\u6e2f"
    ],
    "name:msa_x_preferred":[
        "Lapangan Terbang Isiro-Matari"
    ],
    "name:nld_x_preferred":[
        "Luchthaven Matari"
    ],
    "name:pol_x_preferred":[
        "Port lotniczy Matari"
    ],
    "name:ron_x_preferred":[
        "Aeroportul Matari"
    ],
    "name:swe_x_preferred":[
        "Matari Airport"
    ],
    "name:tgk_x_preferred":[
        "\u0424\u0443\u0440\u0443\u0434\u0433\u043e\u04b3\u0438 \u043c\u043e\u0442\u043e\u0440\u0438"
    ],
    "oa:elevation_ft":"2438",
    "oa:type":"medium_airport",
    "woe:hierarchy":{
        "country_id":23424780,
        "planet_id":1,
        "state_id":2344985
    },
    "wof:name":"Isiro Matari Airport",
    "wof:placetype":"campus"
},
  "geometry": {"coordinates":[27.588301,2.82761],"type":"Point"}
}