{
  "type": "Feature",
  "properties": {
    "name:ceb_x_preferred":[
        "Rotorua Airport"
    ],
    "name:eng_x_preferred":[
        "Rotorua International Airport"
    ],
    "name:eng_x_variant":[
        "ROT",
        "NZRO"
    ],
    "name:fas_x_preferred":[
        "\u0641\u0631\u0648\u062f\u06af\u0627\u0647 \u0628\u06cc\u0646\u200c\u0627\u0644\u0645\u0644\u0644\u06cc \u0631\u062a\u0631\u0648\u0627"
    ],
    "name:fra_x_preferred":[
        "Rotorua airport"
    ],
    "name:ind_x_preferred":[
        "Bandar Udara Internasional Rotorua"
    ],
    "name:jpn_x_preferred":[
        "\u30ed\u30c8\u30eb\u30a2\u56fd\u969b\u7a7a\u6e2f"
    ],
    "name:kor_x_preferred":[
        "\ub85c\ud1a0\ub8e8\uc544 \uacf5\ud56d"
    ],
    "name:kor_x_variant":[
        "\ub85c\ud1a0\ub8e8\uc544 \uad6d\uc81c\uacf5\ud56d"
    ],
    "name:msa_x_preferred":[
        "Lapangan Terbang Antarabangsa Rotorua"
    ],
    "name:pol_x_preferred":[
        "Port lotniczy Rotorua"
    ],
    "name:ron_x_preferred":[
        "Aeroportul Interna\u021bional Rotorua"
    ],
    "name:tgk_x_preferred":[
        "\u0424\u0443\u0440\u0443\u0434\u0433\u043e\u04b3\u0438 \u0431\u0438\u043d\u200c\u0430\u043b\u043c\u0438\u043b\u0430\u043b\u04e3 \u0440\u0442\u0440\u0443\u043e"
    ],
    "name:vie_x_preferred":[
        "S\u00e2n bay qu\u1ed1c t\u1ebf Rotorua"
    ],
    "name:zho_x_preferred":[
        "\u7f85\u6258\u8def\u4e9e\u570b\u969b\u6a5f\u5834"
    ],
    "oa:elevation_ft":"935",
    "oa:type":"medium_airport",
    "wd:wordcount":1187,
    "woe:hierarchy":{
        "country_id":23424916,
        "county_id":55875881,
        "planet_id":1
    },
    "wof:name":"Rotorua Airport",
    "wof:placetype":"campus"
},
  "geometry": {"coordinates":[176.317001,-38.1092],"type":"Point"}
}