{
  "type": "Feature",
  "properties": {
    "name:eng_x_preferred":[
        "Ciudad del Carmen International Airport"
    ],
    "name:eng_x_variant":[
        "CME",
        "MMCE"
    ],
    "name:fas_x_preferred":[
        "\u0641\u0631\u0648\u062f\u06af\u0627\u0647 \u0628\u06cc\u0646\u200c\u0627\u0644\u0645\u0644\u0644\u06cc \u0633\u06cc\u0648\u062f\u0627\u062f \u062f\u0644 \u06a9\u0627\u0631\u0645\u0646"
    ],
    "name:ind_x_preferred":[
        "Bandar Udara Internasional Ciudad del Carmen"
    ],
    "name:jpn_x_preferred":[
        "\u30b7\u30a6\u30c0\u30fc\u30fb\u30c7\u30fb\u30ab\u30eb\u30e1\u30f3\u56fd\u969b\u7a7a\u6e2f"
    ],
    "name:msa_x_preferred":[
        "Lapangan Terbang Antarabangsa Ciudad Del Carmen"
    ],
    "name:pol_x_preferred":[
        "Port lotniczy Ciudad del Carmen"
    ],
    "name:por_x_preferred":[
        "Aeroporto Internacional de Ciudad del Carmen"
    ],
    "name:spa_x_preferred":[
        "Aeropuerto Internacional de Ciudad del Carmen"
    ],
    "name:swe_x_preferred":[
        "Ciudad del Carmen International Airport"
    ],
    "name:tgk_x_preferred":[
        "\u0424\u0443\u0440\u0443\u0434\u0433\u043e\u04b3\u0438 \u0431\u0438\u043d\u200c\u0430\u043b\u043c\u0438\u043b\u0430\u043b\u04e3 \u0441\u044e\u0434\u043e\u0434 \u0434\u0438\u043b \u043a\u043e\u0440\u043c\u043d"
    ],
    "name:vie_x_preferred":[
        "S\u00e2n bay qu\u1ed1c t\u1ebf Ciudad del Carmen"
    ],
    "name:zho_x_preferred":[
        "\u5361\u9580\u57ce\u570b\u969b\u6a5f\u5834"
    ],
    "oa:elevation_ft":"10",
    "oa:type":"medium_airport",
    "woe:hierarchy":{
        "country_id":23424900,
        "county_id":12599701,
        "planet_id":1,
        "state_id":2346267
    },
    "wof:name":"Ciudad del Carmen Airport",
    "wof:placetype":"campus"
},
  "geometry": {"coordinates":[-91.799004,18.6537],"type":"Point"}
}