{
  "type": "Feature",
  "properties": {
    "wof:name":"Springwells",
    "wof:placetype":"neighbourhood"
},
  "geometry": {"coordinates":[-83.19401766131703,42.30790713064228],"type":"Point"}
}