{
  "type": "Feature",
  "properties": {
    "name:deu_x_preferred":[
        "Foxcroft"
    ],
    "wd:wordcount":40,
    "wof:name":"Foxcroft",
    "wof:placetype":"neighbourhood"
},
  "geometry": {"coordinates":[-78.54410418354968,35.8278968109036],"type":"Point"}
}