{
  "type": "Feature",
  "properties": {
    "gn:admin1_code":"39.0",
    "gn:asciiname":"Okambukonde",
    "gn:dem":1384,
    "gn:feature_class":"P",
    "gn:feature_code":"PPL",
    "gn:name":"Okambukonde",
    "gn:population":0,
    "gn:timezone":"Africa/Windhoek",
    "wof:name":"Okambukonde",
    "wof:placetype":"locality"
},
  "geometry": {"coordinates":[17.36667000000001,-20.51667],"type":"Point"}
}