{
  "type": "Feature",
  "properties": {
    "name:ceb_x_preferred":[
        "Isla San Felix Airport"
    ],
    "name:eng_x_variant":[
        "SFX",
        "VE-0207"
    ],
    "name:swe_x_preferred":[
        "Isla San Felix Airport"
    ],
    "oa:elevation_ft":"231",
    "oa:type":"small_airport",
    "wd:wordcount":70,
    "woe:hierarchy":{
        "country_id":23424982,
        "county_id":26804581,
        "localadmin_id":26805585,
        "planet_id":1,
        "state_id":2347682
    },
    "wof:name":"San Felix Airport",
    "wof:placetype":"campus"
},
  "geometry": {"coordinates":[-62.6652,8.2788],"type":"Point"}
}