{
  "type": "Feature",
  "properties": {
    "name:ara_x_preferred":[
        "\u0627\u0644\u062c\u0627\u0646\u0628 \u0627\u0644\u063a\u0631\u0628\u064a \u0627\u0644\u0634\u0645\u0627\u0644\u064a \u0644\u0645\u0646\u0647\u0627\u062a\u0646"
    ],
    "name:cat_x_preferred":[
        "Upper West Side"
    ],
    "name:ces_x_preferred":[
        "Upper West Side"
    ],
    "name:dan_x_preferred":[
        "Upper West Side"
    ],
    "name:deu_x_preferred":[
        "Upper West Side"
    ],
    "name:est_x_preferred":[
        "Upper West Side"
    ],
    "name:eus_x_preferred":[
        "Upper West Side"
    ],
    "name:fas_x_preferred":[
        "\u0622\u067e\u0631 \u0648\u0633\u062a \u0633\u0627\u06cc\u062f"
    ],
    "name:fra_x_preferred":[
        "Upper West Side"
    ],
    "name:heb_x_preferred":[
        "\u05d0\u05e4\u05e8 \u05d5\u05e1\u05d8 \u05e1\u05d9\u05d9\u05d3"
    ],
    "name:ind_x_preferred":[
        "Upper West Side"
    ],
    "name:ita_x_preferred":[
        "Upper West Side"
    ],
    "name:jpn_x_preferred":[
        "\u30a2\u30c3\u30d1\u30fc\u30fb\u30a6\u30a8\u30b9\u30c8\u30fb\u30b5\u30a4\u30c9"
    ],
    "name:kat_x_preferred":[
        "\u10d6\u10d4\u10db\u10dd \u10d5\u10d4\u10e1\u10e2-\u10e1\u10d0\u10d8\u10d3\u10d8"
    ],
    "name:kor_x_preferred":[
        "\uc5b4\ud37c\uc6e8\uc2a4\ud2b8\uc0ac\uc774\ub4dc"
    ],
    "name:lat_x_preferred":[
        "Upper West Side"
    ],
    "name:lit_x_preferred":[
        "Auk\u0161tutinis Vestsaidas"
    ],
    "name:nld_x_preferred":[
        "Upper West Side"
    ],
    "name:oci_x_preferred":[
        "Upper West Side"
    ],
    "name:pol_x_preferred":[
        "Upper West Side"
    ],
    "name:por_x_preferred":[
        "Upper West Side"
    ],
    "name:ron_x_preferred":[
        "Upper West Side"
    ],
    "name:rus_x_preferred":[
        "\u0412\u0435\u0440\u0445\u043d\u0438\u0439 \u0412\u0435\u0441\u0442-\u0421\u0430\u0439\u0434"
    ],
    "name:slk_x_preferred":[
        "Upper West Side"
    ],
    "name:spa_x_preferred":[
        "Upper West Side"
    ],
    "name:swe_x_preferred":[
        "Upper West Side"
    ],
    "name:tha_x_preferred":[
        "\u0e2d\u0e31\u0e1b\u0e40\u0e1b\u0e2d\u0e23\u0e4c\u0e40\u0e27\u0e2a\u0e15\u0e4c\u0e44\u0e0b\u0e14\u0e4c"
    ],
    "name:tur_x_preferred":[
        "Upper West Side"
    ],
    "name:ukr_x_preferred":[
        "\u0412\u0435\u0440\u0445\u043d\u0456\u0439 \u0412\u0435\u0441\u0442-\u0421\u0430\u0439\u0434"
    ],
    "name:yid_x_preferred":[
        "\u05d0\u05e4\u05e2\u05e8 \u05d5\u05d5\u05e2\u05e1\u05d8 \u05e1\u05d9\u05d9\u05d3"
    ],
    "name:zho_x_preferred":[
        "\u4e0a\u897f\u57ce"
    ],
    "wd:wordcount":8882,
    "wof:name":"Upper West Side",
    "wof:placetype":"neighbourhood"
},
  "geometry": {"coordinates":[-97.34405036043864,32.74822091618688],"type":"Point"}
}