{
  "type": "Feature",
  "properties": {
    "wd:wordcount":8882,
    "wof:name":"Upper West Side",
    "wof:placetype":"neighbourhood"
},
  "geometry": {"coordinates":[-97.34405036043864,32.74822091618688],"type":"Point"}
}