{
  "type": "Feature",
  "properties": {
    "gn:admin1_code":"21.0",
    "gn:asciiname":"Korlia",
    "gn:dem":1731,
    "gn:feature_class":"P",
    "gn:feature_code":"PPL",
    "gn:name":"Korlia",
    "gn:population":0,
    "gn:timezone":"Africa/Windhoek",
    "wof:name":"Korlia",
    "wof:placetype":"locality"
},
  "geometry": {"coordinates":[17.14444,-22.58833],"type":"Point"}
}