{
  "type": "Feature",
  "properties": {
    "gn:admin1_code":"31.0",
    "gn:asciiname":"Hakiesdoorn",
    "gn:dem":390,
    "gn:feature_class":"P",
    "gn:feature_code":"PPL",
    "gn:name":"Hakiesdoorn",
    "gn:population":0,
    "gn:timezone":"Africa/Windhoek",
    "name:und_x_variant":[
        "Haakiesdoorn",
        "Hackiesdorn",
        "Hakiesdoorn"
    ],
    "wof:name":"Hakiesdoorn",
    "wof:placetype":"locality"
},
  "geometry": {"coordinates":[18.21667,-28.88333],"type":"Point"}
}