{
  "type": "Feature",
  "properties": {
    "name:ceb_x_preferred":[
        "North Harbour"
    ],
    "name:fra_x_preferred":[
        "North Harbour"
    ],
    "name:swe_x_preferred":[
        "North Harbour"
    ],
    "wof:name":"North Harbour",
    "wof:placetype":"neighbourhood"
},
  "geometry": {"coordinates":[174.69991491664487,-36.74763294779103],"type":"Point"}
}