{
  "type": "Feature",
  "properties": {
    "wof:name":"Riviera",
    "wof:placetype":"neighbourhood"
},
  "geometry": {"coordinates":[28.21559013567341,-25.7344154134225],"type":"Point"}
}