{
  "type": "Feature",
  "properties": {
    "name:ara_x_preferred":[
        "\u0631\u064a\u0641\u064a\u064a\u0631\u0627"
    ],
    "name:bre_x_preferred":[
        "Riviera"
    ],
    "name:bul_x_preferred":[
        "\u0420\u0438\u0432\u0438\u0435\u0440\u0430"
    ],
    "name:deu_x_preferred":[
        "Riviera"
    ],
    "name:ell_x_preferred":[
        "\u03a1\u03b9\u03b2\u03b9\u03ad\u03c1\u03b1"
    ],
    "name:epo_x_preferred":[
        "Riviero"
    ],
    "name:fin_x_preferred":[
        "Riviera"
    ],
    "name:fra_x_preferred":[
        "Riviera"
    ],
    "name:hun_x_preferred":[
        "Rivi\u00e9ra"
    ],
    "name:hye_x_preferred":[
        "\u054c\u056b\u057e\u056b\u0565\u0580\u0561"
    ],
    "name:ita_x_preferred":[
        "Riviera"
    ],
    "name:kir_x_preferred":[
        "\u0420\u0438\u0432\u044c\u0435\u0440\u0430"
    ],
    "name:lav_x_preferred":[
        "Rivj\u0113ra"
    ],
    "name:nld_x_preferred":[
        "Rivi\u00e8ra"
    ],
    "name:nor_x_preferred":[
        "Rivieraen"
    ],
    "name:pol_x_preferred":[
        "Riwiera"
    ],
    "name:ron_x_preferred":[
        "Riviera"
    ],
    "name:rus_x_preferred":[
        "\u0420\u0438\u0432\u044c\u0435\u0440\u0430"
    ],
    "name:spa_x_preferred":[
        "Riviera"
    ],
    "name:swe_x_preferred":[
        "Rivieran"
    ],
    "wof:name":"Riviera",
    "wof:placetype":"neighbourhood"
},
  "geometry": {"coordinates":[28.21559013567341,-25.7344154134225],"type":"Point"}
}