{
  "type": "Feature",
  "properties": {
    "wof:name":"University",
    "wof:placetype":"neighbourhood"
},
  "geometry": {"coordinates":[-83.05040951969472,42.30107696891902],"type":"Point"}
}