{
  "type": "Feature",
  "properties": {
    "name:ceb_x_preferred":[
        "Ylivieska Airport"
    ],
    "name:eng_x_preferred":[
        "Ylivieska Airfield"
    ],
    "name:eng_x_variant":[
        "YLI",
        "EFYL"
    ],
    "name:fas_x_preferred":[
        "\u0641\u0631\u0648\u062f\u06af\u0627\u0647 \u06cc\u0644\u06cc\u0648\u06cc\u0633\u06a9\u0627"
    ],
    "name:fin_x_preferred":[
        "Ylivieskan lentokentt\u00e4"
    ],
    "name:fra_x_preferred":[
        "a\u00e9rodrome d'Ylivieska"
    ],
    "name:msa_x_preferred":[
        "Lapangan Terbang Ylivieska"
    ],
    "name:swe_x_preferred":[
        "Ylivieska Airport"
    ],
    "name:tgk_x_preferred":[
        "\u0424\u0443\u0440\u0443\u0434\u0433\u043e\u04b3\u0438 \u0438\u043b\u044e\u0438\u0441\u043a\u043e"
    ],
    "oa:elevation_ft":"252",
    "oa:type":"medium_airport",
    "woe:hierarchy":{
        "country_id":23424812,
        "county_id":56120892,
        "localadmin_id":12590882,
        "planet_id":1,
        "state_id":29389265
    },
    "wof:name":"Ylivieska lentokentt\u00e4",
    "wof:placetype":"campus"
},
  "geometry": {"coordinates":[24.716,64.060501],"type":"Point"}
}