{
  "type": "Feature",
  "properties": {
    "gn:admin1_code":"41.0",
    "gn:asciiname":"Sikome",
    "gn:dem":1154,
    "gn:feature_class":"P",
    "gn:feature_code":"PPL",
    "gn:name":"Sikome",
    "gn:population":0,
    "gn:timezone":"Africa/Windhoek",
    "wof:name":"Sikome",
    "wof:placetype":"locality"
},
  "geometry": {"coordinates":[18.05,-17.55],"type":"Point"}
}