{
  "type": "Feature",
  "properties": {
    "name:ceb_x_preferred":[
        "Vernon Regional Airport"
    ],
    "name:eng_x_preferred":[
        "Vernon Regional Airport"
    ],
    "name:eng_x_variant":[
        "YVE",
        "CYVK"
    ],
    "name:fas_x_preferred":[
        "\u0641\u0631\u0648\u062f\u06af\u0627\u0647 \u0645\u062d\u0644\u06cc \u0648\u0631\u0646\u0648\u0646"
    ],
    "name:msa_x_preferred":[
        "Lapangan Terbang Vernon"
    ],
    "name:pms_x_preferred":[
        "Vernon Regional Airport"
    ],
    "name:ron_x_preferred":[
        "Aeroportul Regional Vernon"
    ],
    "name:swe_x_preferred":[
        "Vernon Regional Airport"
    ],
    "name:tgk_x_preferred":[
        "\u0424\u0443\u0440\u0443\u0434\u0433\u043e\u04b3\u0438 \u043c\u0430\u04b3\u0430\u043b \u0432\u0440\u043d\u0443\u043d"
    ],
    "name:zho_x_preferred":[
        "\u5f17\u8fb2\u5340\u57df\u6a5f\u5834"
    ],
    "oa:elevation_ft":"1140",
    "oa:type":"medium_airport",
    "wd:wordcount":111,
    "woe:hierarchy":{
        "country_id":23424775,
        "county_id":29375210,
        "planet_id":1,
        "state_id":2344916
    },
    "wof:name":"Vernon Airport",
    "wof:placetype":"campus"
},
  "geometry": {"coordinates":[-119.331001,50.2481],"type":"Point"}
}