{
  "type": "Feature",
  "properties": {
    "name:ceb_x_preferred":[
        "Dyersburg Municipal Airport"
    ],
    "name:eng_x_preferred":[
        "Dyersburg Regional Airport"
    ],
    "name:eng_x_variant":[
        "KDYR"
    ],
    "name:fas_x_preferred":[
        "\u0641\u0631\u0648\u062f\u06af\u0627\u0647 \u0645\u062d\u0644\u06cc \u062f\u0627\u06cc\u0631\u0633\u0628\u0631\u06af"
    ],
    "name:jpn_x_preferred":[
        "Dyersburg\u5730\u57df\u7a7a\u6e2f"
    ],
    "name:ron_x_preferred":[
        "Aeroportul Regional Dyersburg"
    ],
    "name:tgk_x_preferred":[
        "\u0424\u0443\u0440\u0443\u0434\u0433\u043e\u04b3\u0438 \u041c\u0430\u04b3\u0430\u043b\u04e3 \u0434\u043e\u0438\u0440\u0441\u0431\u0440\u0433"
    ],
    "name:urd_x_preferred":[
        "\u0688\u0627\u0626\u0631\u0633\u0628\u0631\u06af \u0631\u06cc\u062c\u0646\u0644 \u06c1\u0648\u0627\u0626\u06cc \u0627\u0688\u0627"
    ],
    "oa:elevation_ft":"338",
    "oa:type":"small_airport",
    "wd:wordcount":361,
    "woe:hierarchy":{
        "country_id":23424977,
        "county_id":12589934,
        "planet_id":1,
        "state_id":2347601
    },
    "wof:name":"Dyersburg Municipal Airport",
    "wof:placetype":"campus"
},
  "geometry": {"coordinates":[-89.4067,35.9981],"type":"Point"}
}