{
  "type": "Feature",
  "properties": {
    "gn:admin1_code":"21.0",
    "gn:asciiname":"Halali",
    "gn:dem":1647,
    "gn:feature_class":"P",
    "gn:feature_code":"PPL",
    "gn:name":"Halali",
    "gn:population":0,
    "gn:timezone":"Africa/Windhoek",
    "wof:name":"Halali",
    "wof:placetype":"locality"
},
  "geometry": {"coordinates":[17.05306,-22.50139],"type":"Point"}
}