{
  "type": "Feature",
  "properties": {
    "name:ceb_x_preferred":[
        "Karratha Airport"
    ],
    "name:eng_x_preferred":[
        "Karratha Airport"
    ],
    "name:eng_x_variant":[
        "KTA",
        "YPKA"
    ],
    "name:fas_x_preferred":[
        "\u0641\u0631\u0648\u062f\u06af\u0627\u0647 \u06a9\u0627\u0631\u0627\u062a\u0627"
    ],
    "name:jpn_x_preferred":[
        "\u30ab\u30e9\u30fc\u30c3\u30b5\u7a7a\u6e2f"
    ],
    "name:msa_x_preferred":[
        "Lapangan Terbang Karratha"
    ],
    "name:pol_x_preferred":[
        "Port lotniczy Karratha"
    ],
    "name:rus_x_preferred":[
        "\u041a\u0430\u0440\u0440\u0430\u0442\u0430"
    ],
    "name:swe_x_preferred":[
        "Karratha Airport"
    ],
    "name:tgk_x_preferred":[
        "\u0424\u0443\u0440\u0443\u0434\u0433\u043e\u04b3\u0438 \u043a\u043e\u0440\u043e\u0442\u043e"
    ],
    "oa:elevation_ft":"29",
    "oa:type":"medium_airport",
    "wd:wordcount":605,
    "woe:hierarchy":{
        "country_id":23424748,
        "county_id":55864369,
        "planet_id":1,
        "state_id":2344706,
        "suburb_id":28645083
    },
    "wof:name":"Karratha Airport",
    "wof:placetype":"campus"
},
  "geometry": {"coordinates":[116.773003,-20.7122],"type":"Point"}
}