{
  "type": "Feature",
  "properties": {
    "gn:admin1_code":"31.0",
    "gn:asciiname":"Groot Schwarzkuppe",
    "gn:dem":1105,
    "gn:feature_class":"P",
    "gn:feature_code":"PPL",
    "gn:name":"Groot Schwarzkuppe",
    "gn:population":0,
    "gn:timezone":"Africa/Windhoek",
    "wof:name":"Groot Schwarzkuppe",
    "wof:placetype":"locality"
},
  "geometry": {"coordinates":[17.03333,-26.63333],"type":"Point"}
}