{
  "type": "Feature",
  "properties": {
    "name:deu_x_preferred":[
        "Flughafen Illawarra"
    ],
    "name:eng_x_preferred":[
        "Illawarra Regional Airport"
    ],
    "name:eng_x_variant":[
        "WOL",
        "YWOL"
    ],
    "name:fas_x_preferred":[
        "\u0641\u0631\u0648\u062f\u06af\u0627\u0647 \u0645\u0646\u0637\u0642\u0647\u200c\u0627\u06cc \u0627\u06cc\u0644\u0627\u0648\u0627\u0631\u0627"
    ],
    "name:fra_x_preferred":[
        "a\u00e9roport r\u00e9gional de Illawarra"
    ],
    "name:ita_x_preferred":[
        "aeroporto regionale di Illawarra"
    ],
    "name:msa_x_preferred":[
        "Lapangan Terbang Wollongong"
    ],
    "name:spa_x_preferred":[
        "Illawarra Regional"
    ],
    "name:swe_x_preferred":[
        "Illawarra Regional Airport"
    ],
    "name:tgk_x_preferred":[
        "\u0424\u0443\u0440\u0443\u0434\u0433\u043e\u04b3\u0438 \u043c\u0430\u043d\u0442\u0430\u049b\u0430\u200c\u0438\u0439 \u043e\u0438\u043b\u043e\u0432\u043e\u0440\u043e"
    ],
    "oa:elevation_ft":"31",
    "oa:type":"medium_airport",
    "woe:hierarchy":{
        "country_id":23424748,
        "planet_id":1,
        "state_id":2344700,
        "suburb_id":22721463
    },
    "wof:name":"Albion Park Aerodrome",
    "wof:placetype":"campus"
},
  "geometry": {"coordinates":[150.78900100000001,-34.5611],"type":"Point"}
}