{
  "type": "Feature",
  "properties": {
    "name:ceb_x_preferred":[
        "Desierto de Atacama Airport"
    ],
    "name:eng_x_preferred":[
        "Chamonate Airport"
    ],
    "name:eng_x_variant":[
        "CPO",
        "SCAT"
    ],
    "name:jpn_x_preferred":[
        "\u30c1\u30e3\u30e2\u30ca\u30c6\u7a7a\u6e2f"
    ],
    "name:msa_x_preferred":[
        "Lapangan Terbang Chamonate"
    ],
    "name:ron_x_preferred":[
        "Aeroportul Chamonate"
    ],
    "name:spa_x_preferred":[
        "Aer\u00f3dromo Chamonate"
    ],
    "name:swe_x_preferred":[
        "Desierto de Atacama Airport"
    ],
    "oa:elevation_ft":"670",
    "oa:type":"medium_airport",
    "wd:wordcount":58,
    "woe:hierarchy":{
        "country_id":23424782,
        "county_id":26793991,
        "localadmin_id":26794077,
        "planet_id":1,
        "state_id":2345022
    },
    "wof:name":"Chamonate Airport",
    "wof:placetype":"campus"
},
  "geometry": {"coordinates":[-70.77919799999999,-27.2612],"type":"Point"}
}