{
  "type": "Feature",
  "properties": {
    "name:ara_x_colloquial":[
        "Camp Militaire d'Ain Bordja",
        "Camp d'Ain Bordja"
    ],
    "name:ara_x_preferred":[
        "Les Camps"
    ],
    "name:ara_x_variant":[
        "Ain Bardja",
        "Camp Militaire d'A\u00efn Bordja",
        "Camp d'Ain Borja",
        "Camp d'A\u00efn Bordja"
    ],
    "name:unk_x_variant":[
        "Les Camps"
    ],
    "qs:gn_adm0_cc":"MA",
    "qs:gn_local":2553604,
    "qs:local_max":5740,
    "qs:local_sum":7075,
    "qs:localhoods":6,
    "qs:name":"Les Camps",
    "qs:name_adm0":"\u0627\u0644\u0645\u063a\u0631\u0628",
    "qs:name_adm1":"\u0627\u0644\u062f\u0627\u0631 \u0627\u0644\u0628\u064a\u0636\u0627\u0621 \u0627\u0644\u0643\u0628\u0631\u0649",
    "qs:name_adm2":"\u0627\u0644\u062f\u0627\u0631 \u0627\u0644\u0628\u064a\u0636\u0627\u0621",
    "qs:name_lau":"\u0627\u0644\u0635\u062e\u0648\u0631 \u0627\u0644\u0633\u0648\u062f\u0627\u0621",
    "qs:name_local":"\u0627\u0644\u062f\u0627\u0631 \u0627\u0644\u0628\u064a\u0636\u0627\u0621",
    "qs:photo_max":36,
    "qs:photo_sum":147,
    "qs:placetype":"Suburb",
    "qs:quad_count":26,
    "qs:woe_adm0":23424893,
    "qs:woe_adm1":56120054,
    "qs:woe_adm2":2346195,
    "qs:woe_lau":56438578,
    "qs:woe_local":1532755,
    "qs:woe_ver":"7.10.0",
    "wof:lang":[
        "ara"
    ],
    "wof:name":"Les Camps",
    "wof:placetype":"neighbourhood"
},
  "geometry": {"coordinates":[-7.594785,33.596459],"type":"Point"}
}