{
  "type": "Feature",
  "properties": {
    "name:ceb_x_preferred":[
        "Nadym Airport"
    ],
    "name:eng_x_preferred":[
        "Nadym Airport"
    ],
    "name:eng_x_variant":[
        "NYM",
        "USMM"
    ],
    "name:fas_x_preferred":[
        "\u0641\u0631\u0648\u062f\u06af\u0627\u0647 \u0646\u0627\u062f\u06cc\u0645"
    ],
    "name:jpn_x_preferred":[
        "\u30ca\u30c7\u30a3\u30e0\u7a7a\u6e2f"
    ],
    "name:nld_x_preferred":[
        "Nadim"
    ],
    "name:pol_x_preferred":[
        "Port lotniczy Nadym"
    ],
    "name:ron_x_preferred":[
        "Aeroportul Nadym"
    ],
    "name:rus_x_preferred":[
        "\u041d\u0430\u0434\u044b\u043c"
    ],
    "name:spa_x_preferred":[
        "Aeropuerto de Nadym"
    ],
    "name:ukr_x_preferred":[
        "\u041d\u0430\u0434\u0438\u043c"
    ],
    "name:vie_x_preferred":[
        "S\u00e2n bay Nadym"
    ],
    "oa:elevation_ft":"49",
    "oa:type":"medium_airport",
    "wd:wordcount":71,
    "woe:hierarchy":{
        "country_id":23424936,
        "county_id":12599460,
        "planet_id":1,
        "state_id":20070525
    },
    "wof:name":"Nadym Airport",
    "wof:placetype":"campus"
},
  "geometry": {"coordinates":[72.698898,65.480904],"type":"Point"}
}