{
  "type": "Feature",
  "properties": {
    "name:ceb_x_preferred":[
        "Salluit Airport"
    ],
    "name:eng_x_preferred":[
        "Salluit Airport"
    ],
    "name:eng_x_variant":[
        "YZG",
        "CYZG"
    ],
    "name:fas_x_preferred":[
        "\u0641\u0631\u0648\u062f\u06af\u0627\u0647 \u0633\u0644\u0644\u0648\u06cc\u062a"
    ],
    "name:fra_x_preferred":[
        "A\u00e9roport de Salluit"
    ],
    "name:msa_x_preferred":[
        "Lapangan Terbang Salluit"
    ],
    "name:pms_x_preferred":[
        "Salluit Airport"
    ],
    "name:ron_x_preferred":[
        "Aeroportul Salluit"
    ],
    "name:spa_x_preferred":[
        "Aeropuerto de Salluit"
    ],
    "name:swe_x_preferred":[
        "Salluit Airport"
    ],
    "name:tgk_x_preferred":[
        "\u0424\u0443\u0440\u0443\u0434\u0433\u043e\u04b3\u0438 \u0441\u043b\u043b\u0443\u0438\u0442"
    ],
    "oa:elevation_ft":"743",
    "oa:type":"medium_airport",
    "wd:wordcount":89,
    "woe:hierarchy":{
        "country_id":23424775,
        "county_id":29375254,
        "planet_id":1,
        "state_id":2344924
    },
    "wof:name":"Salluit Airport",
    "wof:placetype":"campus"
},
  "geometry": {"coordinates":[-75.667222,62.179444],"type":"Point"}
}