{
  "type": "Feature",
  "properties": {
    "label:eng_x_preferred_longname":[
        "Kwajalein State"
    ],
    "label:eng_x_preferred_placetype":[
        "state"
    ],
    "name:eng_x_preferred":[
        "Kwajalein"
    ],
    "qs:name":"Kwajalein",
    "qs:name_adm0":"Marshall Islands",
    "qs:name_adm1":"Kwajalein",
    "qs:photos":491,
    "qs:photos_1k":99,
    "qs:photos_9k":4,
    "qs:photos_9r":6,
    "qs:photos_all":912,
    "qs:photos_sr":7,
    "qs:placetype":"State",
    "qs:pop_sr":"0",
    "wof:name":"Kwajalein",
    "wof:placetype":"region"
},
  "geometry": {"coordinates":[167.484512,9.383524],"type":"Point"}
}