{
  "type": "Feature",
  "properties": {
    "label:eng_x_preferred_longname":[
        "Kwajalein State"
    ],
    "label:eng_x_preferred_placetype":[
        "state"
    ],
    "name:ara_x_preferred":[
        "\u0643\u0648\u0627\u062c\u0627\u0644\u064a\u0646 "
    ],
    "name:ben_x_preferred":[
        "\u0995\u09cb\u0993\u09df\u09be\u099c\u09be\u09b2\u09c7\u09a8"
    ],
    "name:deu_x_preferred":[
        "Kwajalein"
    ],
    "name:ell_x_preferred":[
        "\u039a\u03b2\u03b1\u03c4\u03b6\u03b1\u03bb\u03ad\u03b9\u03bd"
    ],
    "name:eng_x_preferred":[
        "Kwajalein Island"
    ],
    "name:eng_x_variant":[
        "Kwajalein"
    ],
    "name:fas_x_preferred":[
        "\u06a9\u0648\u0627\u062c\u0627\u0644\u06cc\u0646"
    ],
    "name:fra_x_preferred":[
        "Kwajalein"
    ],
    "name:heb_x_preferred":[
        "\u05d4\u05d0\u05d9 \u05e7\u05d5\u05d5\u05d0\u05d9\u05d9\u05d2'\u05dc\u05d9\u05df"
    ],
    "name:hin_x_preferred":[
        "\u0915\u094d\u0935\u093e\u091c\u093e\u0932\u0940\u0928"
    ],
    "name:hun_x_preferred":[
        "Kwajalein"
    ],
    "name:ind_x_preferred":[
        "Kwajalein"
    ],
    "name:ita_x_preferred":[
        "Kwajalein"
    ],
    "name:jpn_x_preferred":[
        "\u30af\u30a7\u30bc\u30ea\u30f3"
    ],
    "name:kor_x_preferred":[
        "\ucf70\uc798\ub808\uc778"
    ],
    "name:nld_x_preferred":[
        "Kwajalein"
    ],
    "name:pol_x_preferred":[
        "Kwajalein"
    ],
    "name:por_x_preferred":[
        "Kwajalein"
    ],
    "name:rus_x_preferred":[
        "\u0430\u0442\u043e\u043b\u043b \u041c\u0435\u043d\u0448\u0438\u043a\u043e\u0432\u0430"
    ],
    "name:spa_x_preferred":[
        "Kwajalein"
    ],
    "name:swe_x_preferred":[
        "Kwajaleinatollen"
    ],
    "name:tur_x_preferred":[
        "Kwajalein"
    ],
    "name:ukr_x_preferred":[
        "\u041a\u0432\u0430\u0434\u0436\u0430\u043b\u0435\u0439\u043d"
    ],
    "name:urd_x_preferred":[
        "\u06a9\u0648\u0627\u062c\u0644\u0627\u06cc\u0646"
    ],
    "name:vie_x_preferred":[
        "\u0110\u1ea3o Kwajalein"
    ],
    "name:zho_cn_x_preferred":[
        "\u5938\u8d3e\u6797\u5c9b"
    ],
    "name:zho_tw_x_preferred":[
        "\u74dc\u52a0\u6797\u5cf6"
    ],
    "qs:name":"Kwajalein",
    "qs:name_adm0":"Marshall Islands",
    "qs:name_adm1":"Kwajalein",
    "qs:photos":491,
    "qs:photos_1k":99,
    "qs:photos_9k":4,
    "qs:photos_9r":6,
    "qs:photos_all":912,
    "qs:photos_sr":7,
    "qs:placetype":"State",
    "qs:pop_sr":"0",
    "wof:name":"Kwajalein",
    "wof:placetype":"region"
},
  "geometry": {"coordinates":[167.484512,9.383524],"type":"Point"}
}