{
  "type": "Feature",
  "properties": {
    "name:ceb_x_preferred":[
        "Portoroz"
    ],
    "name:ces_x_preferred":[
        "Leti\u0161t\u011b Portoro\u017e"
    ],
    "name:deu_x_preferred":[
        "Flughafen Portoro\u017e"
    ],
    "name:eng_x_preferred":[
        "Portoro\u017e Airport"
    ],
    "name:eng_x_variant":[
        "POW",
        "LJPZ"
    ],
    "name:fas_x_preferred":[
        "\u0641\u0631\u0648\u062f\u06af\u0627\u0647 \u067e\u0648\u0631\u062a\u0648\u0631\u0648\u0698"
    ],
    "name:hrv_x_preferred":[
        "Zra\u010dna luka Portoro\u017e"
    ],
    "name:ita_x_preferred":[
        "Aeroporto di Portorose"
    ],
    "name:jpn_x_preferred":[
        "\u30dd\u30eb\u30c8\u30ed\u30ba\u7a7a\u6e2f"
    ],
    "name:msa_x_preferred":[
        "Lapangan Terbang Portoroz"
    ],
    "name:nld_x_preferred":[
        "Portoro\u017e Airport"
    ],
    "name:pol_x_preferred":[
        "Port lotniczy Portoro\u017e"
    ],
    "name:ron_x_preferred":[
        "Aeroportul Portoro\u017e"
    ],
    "name:slv_x_preferred":[
        "Aerodrom Portoro\u017e"
    ],
    "name:srp_x_preferred":[
        "\u0410\u0435\u0440\u043e\u0434\u0440\u043e\u043c \u041f\u043e\u0440\u0442\u043e\u0440\u043e\u0436"
    ],
    "name:tgk_x_preferred":[
        "\u0424\u0443\u0440\u0443\u0434\u0433\u043e\u04b3\u0438 \u043f\u0443\u0440\u0442\u0443\u0440\u0443\u0436"
    ],
    "name:vie_x_preferred":[
        "S\u00e2n bay Portoro\u017e"
    ],
    "name:zho_x_preferred":[
        "\u6ce2\u723e\u6258\u7f85\u65e5\u6a5f\u5834"
    ],
    "oa:elevation_ft":"7",
    "oa:type":"medium_airport",
    "wd:wordcount":1191,
    "woe:hierarchy":{
        "country_id":23424945,
        "county_id":12591597,
        "planet_id":1,
        "state_id":55848375
    },
    "wof:name":"Portoroz Airport",
    "wof:placetype":"campus"
},
  "geometry": {"coordinates":[13.615,45.4734],"type":"Point"}
}