{
  "type": "Feature",
  "properties": {
    "qs:name":"\u0648\u0637\u0649 \u0633\u0644\u0627\u0645",
    "qs:name_adm0":"\u0644\u0628\u0646\u0627\u0646",
    "qs:name_adm1":"\u062c\u0628\u0644 \u0644\u0628\u0646\u0627\u0646",
    "qs:photos":46,
    "qs:photos_1k":9,
    "qs:photos_9k":1,
    "qs:photos_9r":2,
    "qs:photos_all":46,
    "qs:photos_sr":2,
    "qs:placetype":"Town",
    "qs:pop_sr":"0",
    "wof:name":"\u0648\u0637\u0649 \u0633\u0644\u0627\u0645",
    "wof:placetype":"locality"
},
  "geometry": {"coordinates":[35.64525,34.005071],"type":"Point"}
}