{
  "type": "Feature",
  "properties": {
    "name:ara_x_preferred":[
        "\u0645\u0637\u0627\u0631 \u0646\u0648\u0643"
    ],
    "name:ceb_x_preferred":[
        "Nuuk Airport"
    ],
    "name:ces_x_preferred":[
        "Leti\u0161t\u011b Nuuk"
    ],
    "name:dan_x_preferred":[
        "Nuuk Lufthavn"
    ],
    "name:deu_x_preferred":[
        "Flughafen Nuuk"
    ],
    "name:eng_x_preferred":[
        "Nuuk Airport"
    ],
    "name:eng_x_variant":[
        "GOH",
        "BGGH"
    ],
    "name:fas_x_preferred":[
        "\u0641\u0631\u0648\u062f\u06af\u0627\u0647 \u0646\u0648\u06a9"
    ],
    "name:fin_x_preferred":[
        "Nuukin lentoasema"
    ],
    "name:fra_x_preferred":[
        "a\u00e9roport de Nuuk"
    ],
    "name:hun_x_preferred":[
        "Nuuk rep\u00fcl\u0151t\u00e9r"
    ],
    "name:ita_x_preferred":[
        "Aeroporto di Nuuk"
    ],
    "name:jpn_x_preferred":[
        "\u30cc\u30fc\u30af\u7a7a\u6e2f"
    ],
    "name:kal_x_preferred":[
        "Mittarfik Nuuk"
    ],
    "name:lav_x_preferred":[
        "N\u016bkas lidosta"
    ],
    "name:msa_x_preferred":[
        "Lapangan Terbang Nuuk"
    ],
    "name:nld_x_preferred":[
        "Luchthaven Nuuk"
    ],
    "name:nob_x_preferred":[
        "Nuuk lufthavn"
    ],
    "name:pol_x_preferred":[
        "Port lotniczy Nuuk"
    ],
    "name:por_x_preferred":[
        "Aeroporto de Nuuk"
    ],
    "name:ron_x_preferred":[
        "Aeroportul Nuuk"
    ],
    "name:rus_x_preferred":[
        "\u041d\u0443\u043a"
    ],
    "name:spa_x_preferred":[
        "Aeropuerto de Nuuk"
    ],
    "name:swe_x_preferred":[
        "Nuuk flygplats"
    ],
    "name:tgk_x_preferred":[
        "\u0424\u0443\u0440\u0443\u0434\u0433\u043e\u04b3\u0438 \u043d\u0443\u043a"
    ],
    "name:tur_x_preferred":[
        "Nuuk Havaliman\u0131"
    ],
    "name:vie_x_preferred":[
        "S\u00e2n bay Nuuk"
    ],
    "name:zho_x_preferred":[
        "\u52aa\u514b\u673a\u573a"
    ],
    "oa:elevation_ft":"283",
    "oa:type":"medium_airport",
    "woe:hierarchy":{
        "country_id":23424828,
        "planet_id":1,
        "state_id":20069858
    },
    "wof:name":"Godthaab Airport",
    "wof:placetype":"campus"
},
  "geometry": {"coordinates":[-51.678101,64.19090300000001],"type":"Point"}
}