{
  "type": "Feature",
  "properties": {
    "gn:admin1_code":"32.0",
    "gn:asciiname":"Okauwa",
    "gn:dem":1446,
    "gn:feature_class":"P",
    "gn:feature_code":"PPL",
    "gn:name":"Okauwa",
    "gn:population":0,
    "gn:timezone":"Africa/Windhoek",
    "wof:name":"Okauwa",
    "wof:placetype":"locality"
},
  "geometry": {"coordinates":[14.03333,-18.78333],"type":"Point"}
}