{
  "type": "Feature",
  "properties": {
    "wof:name":"East Evergreen",
    "wof:placetype":"neighbourhood"
},
  "geometry": {"coordinates":[-112.06962454911532,33.46134204149759],"type":"Point"}
}