{
  "type": "Feature",
  "properties": {
    "name:ben_x_preferred":[
        "\u09b0\u09be\u099c\u0995\u09cb\u099f \u09ac\u09bf\u09ae\u09be\u09a8\u09ac\u09a8\u09cd\u09a6\u09b0"
    ],
    "name:eng_x_preferred":[
        "Rajkot Airport"
    ],
    "name:eng_x_variant":[
        "RAJ",
        "VARK"
    ],
    "name:fas_x_preferred":[
        "\u0641\u0631\u0648\u062f\u06af\u0627\u0647 \u0631\u0627\u062c\u06a9\u0648\u062a"
    ],
    "name:jpn_x_preferred":[
        "\u30e9\u30fc\u30b8\u30b3\u30fc\u30c8\u7a7a\u6e2f"
    ],
    "name:mar_x_preferred":[
        "\u0930\u093e\u091c\u0915\u094b\u091f \u0935\u093f\u092e\u093e\u0928\u0924\u0933"
    ],
    "name:msa_x_preferred":[
        "Lapangan Terbang Rajkot"
    ],
    "name:swe_x_preferred":[
        "Rajkot Airport"
    ],
    "name:tam_x_preferred":[
        "\u0bb0\u0bbe\u0b9c\u0bcd\u0b95\u0bbe\u0b9f\u0bcd \u0bb5\u0bbf\u0bae\u0bbe\u0ba9 \u0ba8\u0bbf\u0bb2\u0bc8\u0baf\u0bae\u0bcd"
    ],
    "name:tgk_x_preferred":[
        "\u0424\u0443\u0440\u0443\u0434\u0433\u043e\u04b3\u0438 \u0440\u043e\u04b7\u043a\u0443\u0442"
    ],
    "oa:elevation_ft":"441",
    "oa:type":"medium_airport",
    "wd:wordcount":423,
    "woe:hierarchy":{
        "country_id":23424848,
        "county_id":12586430,
        "planet_id":1,
        "state_id":2345743
    },
    "wof:name":"Rajkot Airport",
    "wof:placetype":"campus"
},
  "geometry": {"coordinates":[70.77950300000001,22.3092],"type":"Point"}
}