{
  "type": "Feature",
  "properties": {
    "wof:name":"Margarita Place",
    "wof:placetype":"neighbourhood"
},
  "geometry": {"coordinates":[-112.09279884666417,33.47962325084141],"type":"Point"}
}