{
  "type": "Feature",
  "properties": {
    "gn:admin1_code":"40.0",
    "gn:asciiname":"Ncaute",
    "gn:dem":1113,
    "gn:feature_class":"P",
    "gn:feature_code":"PPL",
    "gn:name":"Ncaute",
    "gn:population":0,
    "gn:timezone":"Africa/Windhoek",
    "wof:name":"Ncaute",
    "wof:placetype":"locality"
},
  "geometry": {"coordinates":[19.81667,-18.36667000000001],"type":"Point"}
}