{
  "type": "Feature",
  "properties": {
    "name:ceb_x_preferred":[
        "Wawa Airport"
    ],
    "name:eng_x_preferred":[
        "Wawa Airport"
    ],
    "name:eng_x_variant":[
        "YXZ",
        "CYXZ"
    ],
    "name:fas_x_preferred":[
        "\u0641\u0631\u0648\u062f\u06af\u0627\u0647 \u0648\u0627\u0648\u0627"
    ],
    "name:msa_x_preferred":[
        "Lapangan Terbang Wawa"
    ],
    "name:pms_x_preferred":[
        "Wawa Airport"
    ],
    "name:ron_x_preferred":[
        "Aeroportul Wawa"
    ],
    "name:swe_x_preferred":[
        "Wawa Airport"
    ],
    "name:tgk_x_preferred":[
        "\u0424\u0443\u0440\u0443\u0434\u0433\u043e\u04b3\u0438 \u0432\u043e\u0432\u043e"
    ],
    "oa:elevation_ft":"942",
    "oa:type":"medium_airport",
    "wd:wordcount":57,
    "woe:hierarchy":{
        "country_id":23424775,
        "county_id":29375191,
        "planet_id":1,
        "state_id":2344922
    },
    "wof:name":"Wawa Airport",
    "wof:placetype":"campus"
},
  "geometry": {"coordinates":[-84.786389,47.966944],"type":"Point"}
}