{
  "type": "Feature",
  "properties": {
    "gn:admin1_code":"33.0",
    "gn:asciiname":"Omutwewonime",
    "gn:dem":1145,
    "gn:feature_class":"P",
    "gn:feature_code":"PPL",
    "gn:name":"Omutwewonime",
    "gn:population":0,
    "gn:timezone":"Africa/Windhoek",
    "wof:name":"Omutwewonime",
    "wof:placetype":"locality"
},
  "geometry": {"coordinates":[16.75,-17.45],"type":"Point"}
}