{
  "type": "Feature",
  "properties": {
    "name:eng_x_preferred":[
        "Hattaro 6chome"
    ],
    "name:eng_x_variant":[
        "Hattarou 6choume",
        "Hattaro 6chome"
    ],
    "name:jpn_x_preferred":[
        "\uff16\u4e01\u76ee"
    ],
    "name:jpn_x_variant":[
        "\u306f\u3063\u305f\u308d\u3046 \uff16\u3061\u3087\u3046\u3081",
        "\u516b\u592a\u90ce \uff16\u4e01\u76ee",
        "\uff16\u3061\u3087\u3046\u3081"
    ],
    "qs:gn_adm0_cc":"JP",
    "qs:gn_local":2130203,
    "qs:local_max":137,
    "qs:local_sum":446,
    "qs:localhoods":8,
    "qs:name":"\uff16\u4e01\u76ee",
    "qs:name_adm0":"\u65e5\u672c",
    "qs:name_adm1":"\u9752\u68ee\u770c",
    "qs:name_en":"Hattaro 6chome",
    "qs:name_lau":"\u516b\u592a\u90ce",
    "qs:name_local":"\u516b\u6238\u5e02",
    "qs:photo_max":7,
    "qs:photo_sum":17,
    "qs:placetype":"Suburb",
    "qs:quad_count":4,
    "qs:woe_adm0":23424856,
    "qs:woe_adm1":2345853,
    "qs:woe_adm2":0,
    "qs:woe_lau":90035280,
    "qs:woe_local":1117142,
    "qs:woe_ver":"7.10.0",
    "wof:lang":[
        "jpn"
    ],
    "wof:name":"\uff16\u4e01\u76ee",
    "wof:placetype":"neighbourhood"
},
  "geometry": {"coordinates":[141.50536,40.545848],"type":"Point"}
}