{
  "type": "Feature",
  "properties": {
    "name:ceb_x_preferred":[
        "Puerto Carreno / A. Guauquea"
    ],
    "name:eng_x_preferred":[
        "Germ\u00e1n Olano Airport"
    ],
    "name:eng_x_variant":[
        "PAL",
        "SKPQ"
    ],
    "name:fas_x_preferred":[
        "\u0641\u0631\u0648\u062f\u06af\u0627\u0647 \u062e\u0631\u0645\u0646 \u0627\u0648\u0644\u0627\u0646\u0648"
    ],
    "name:fra_x_preferred":[
        "a\u00e9roport Germ\u00e1n-Olano"
    ],
    "name:jpn_x_preferred":[
        "\u30d8\u30eb\u30de\u30f3\u30fb\u30aa\u30e9\u30ce\u7a7a\u6e2f"
    ],
    "name:msa_x_preferred":[
        "Lapangan Terbang Puerto Carreno"
    ],
    "name:ron_x_preferred":[
        "Aeroportul Germ\u00e1n Olano"
    ],
    "name:spa_x_preferred":[
        "Aeropuerto Germ\u00e1n Olano"
    ],
    "name:swe_x_preferred":[
        "Puerto Carreno / A. Guauquea"
    ],
    "name:tgk_x_preferred":[
        "\u0424\u0443\u0440\u0443\u0434\u0433\u043e\u04b3\u0438 \u0445\u0440\u043c\u043d \u043e\u0432\u043b\u043e\u043d\u0443"
    ],
    "name:vie_x_preferred":[
        "S\u00e2n bay Puerto Carre\u00f1o"
    ],
    "oa:elevation_ft":"566",
    "oa:type":"medium_airport",
    "wd:wordcount":134,
    "woe:hierarchy":{
        "country_id":23424787,
        "county_id":26797115,
        "planet_id":1,
        "state_id":2345078
    },
    "wof:name":"German Olano Airport",
    "wof:placetype":"campus"
},
  "geometry": {"coordinates":[-74.6574,5.48361],"type":"Point"}
}