{
  "type": "Feature",
  "properties": {
    "name:eng_x_variant":[
        "PAL",
        "SKPQ"
    ],
    "oa:elevation_ft":"566",
    "oa:type":"medium_airport",
    "wd:wordcount":134,
    "woe:hierarchy":{
        "country_id":23424787,
        "county_id":26797115,
        "planet_id":1,
        "state_id":2345078
    },
    "wof:name":"German Olano Airport",
    "wof:placetype":"campus"
},
  "geometry": {"coordinates":[-74.6574,5.48361],"type":"Point"}
}