{
  "type": "Feature",
  "properties": {
    "gn:admin1_code":"31.0",
    "gn:asciiname":"Huniams Wes",
    "gn:dem":843,
    "gn:feature_class":"P",
    "gn:feature_code":"PPL",
    "gn:name":"Huniams Wes",
    "gn:population":0,
    "gn:timezone":"Africa/Windhoek",
    "name:und_x_variant":[
        "Huniam",
        "Huniam West",
        "Huniams Wes"
    ],
    "wof:name":"Huniams Wes",
    "wof:placetype":"locality"
},
  "geometry": {"coordinates":[18.85,-28.31667],"type":"Point"}
}