{
  "type": "Feature",
  "properties": {
    "gn:admin1_code":"37.0",
    "gn:asciiname":"Esati",
    "gn:dem":1092,
    "gn:feature_class":"P",
    "gn:feature_code":"PPL",
    "gn:name":"Esati",
    "gn:population":0,
    "gn:timezone":"Africa/Windhoek",
    "wof:name":"Esati",
    "wof:placetype":"locality"
},
  "geometry": {"coordinates":[15.78333,-18.01667],"type":"Point"}
}