{
  "type": "Feature",
  "properties": {
    "name:eng_x_preferred":[
        "Vallegrande Airport"
    ],
    "name:eng_x_variant":[
        "VAH",
        "SLVG"
    ],
    "name:jpn_x_preferred":[
        "\u30ab\u30d4\u30bf\u30f3\u30fbAv\u30fb\u30d3\u30c0\u30eb\u30fb\u30d3\u30e4\u30db\u30e1\u30b9\u30fb\u30c8\u30ec\u30c9\u7a7a\u6e2f"
    ],
    "name:may_x_preferred":[
        "Lapangan Terbang Vallegrande"
    ],
    "name:swe_x_preferred":[
        "Capit\u00e1n Av. Vidal Villagomez Toledo Airport"
    ],
    "oa:elevation_ft":"6551",
    "oa:type":"small_airport",
    "woe:hierarchy":{
        "country_id":23424762,
        "county_id":55967831,
        "localadmin_id":55968079,
        "planet_id":1,
        "state_id":2344808
    },
    "wof:name":"Vallegrande Airport",
    "wof:placetype":"campus"
},
  "geometry": {"coordinates":[-64.099403,-18.4825],"type":"Point"}
}