{
  "type": "Feature",
  "properties": {
    "gn:admin1_code":"39.0",
    "gn:asciiname":"Okumumbonde",
    "gn:dem":1314,
    "gn:feature_class":"P",
    "gn:feature_code":"PPL",
    "gn:name":"Okumumbonde",
    "gn:population":0,
    "gn:timezone":"Africa/Windhoek",
    "wof:name":"Okumumbonde",
    "wof:placetype":"locality"
},
  "geometry": {"coordinates":[17.75,-20.81667],"type":"Point"}
}