{
  "type": "Feature",
  "properties": {
    "name:eng_x_preferred":[
        "Santa Barbara De Barinas Airport"
    ],
    "name:eng_x_variant":[
        "SBB",
        "SVSB"
    ],
    "name:msa_x_preferred":[
        "Lapangan Terbang Santa Barbara De Barinas"
    ],
    "name:ron_x_preferred":[
        "Aeroportul Santa Barbara De Barinas"
    ],
    "oa:elevation_ft":"590",
    "oa:type":"small_airport",
    "woe:hierarchy":{
        "country_id":23424982,
        "county_id":26804684,
        "localadmin_id":26805593,
        "planet_id":1,
        "state_id":2347681
    },
    "wof:name":"Santa Barbara de Barinas Airport",
    "wof:placetype":"campus"
},
  "geometry": {"coordinates":[-71.165718,7.803514],"type":"Point"}
}