{
  "type": "Feature",
  "properties": {
    "name:eng_x_preferred":[
        "Latrobe Valley Airport"
    ],
    "name:eng_x_variant":[
        "TGN",
        "YLTV"
    ],
    "name:fre_x_preferred":[
        "Latrobe Valley Airport"
    ],
    "name:ger_x_preferred":[
        "Flughafen Latrobe"
    ],
    "name:ita_x_preferred":[
        "aeroporto di Latrobe Valley"
    ],
    "name:may_x_preferred":[
        "Lapangan Terbang Latrobe Valley"
    ],
    "name:per_x_preferred":[
        "\u0641\u0631\u0648\u062f\u06af\u0627\u0647 \u0644\u062a\u0631\u0648\u0628 \u0648\u0644\u06cc"
    ],
    "name:spa_x_preferred":[
        "Latrobe Valley"
    ],
    "name:swe_x_preferred":[
        "Latrobe Valley Airport"
    ],
    "name:tgk_x_preferred":[
        "\u0424\u0443\u0440\u0443\u0434\u0433\u043e\u04b3\u0438 \u043b\u0442\u0440\u0443\u0431 \u0432\u043b\u0438"
    ],
    "oa:elevation_ft":"180",
    "oa:type":"medium_airport",
    "woe:hierarchy":{
        "country_id":23424748,
        "county_id":55863991,
        "planet_id":1,
        "state_id":2344705
    },
    "wof:name":"La Trobe Regional Airport",
    "wof:placetype":"campus"
},
  "geometry": {"coordinates":[146.470001,-38.207199],"type":"Point"}
}