{
  "type": "Feature",
  "properties": {
    "name:ceb_x_preferred":[
        "Coban"
    ],
    "name:eng_x_preferred":[
        "Cob\u00e1n Airport"
    ],
    "name:eng_x_variant":[
        "CBV",
        "MGCB"
    ],
    "name:fas_x_preferred":[
        "\u0641\u0631\u0648\u062f\u06af\u0627\u0647 \u06a9\u0648\u0628\u0627\u0646"
    ],
    "name:jpn_x_preferred":[
        "\u30b3\u30d0\u30f3\u7a7a\u6e2f"
    ],
    "name:msa_x_preferred":[
        "Lapangan Terbang Coban"
    ],
    "name:pol_x_preferred":[
        "Port lotniczy Coban"
    ],
    "name:ron_x_preferred":[
        "Aeroportul Cob\u00e1n"
    ],
    "name:spa_x_preferred":[
        "Aeropuerto de Cob\u00e1n"
    ],
    "name:swe_x_preferred":[
        "Coban"
    ],
    "name:tgk_x_preferred":[
        "\u0424\u0443\u0440\u0443\u0434\u0433\u043e\u04b3\u0438 \u043a\u0443\u0431\u043e\u043d\u0434\u043d"
    ],
    "name:zho_x_preferred":[
        "\u79d1\u842c\u6a5f\u5834"
    ],
    "oa:elevation_ft":"4339",
    "oa:type":"medium_airport",
    "wd:wordcount":86,
    "woe:hierarchy":{
        "country_id":23424834,
        "county_id":26806911,
        "planet_id":1,
        "state_id":2345552
    },
    "wof:name":"Coban Airport",
    "wof:placetype":"campus"
},
  "geometry": {"coordinates":[-90.4067,15.469],"type":"Point"}
}