{
  "type": "Feature",
  "properties": {
    "wof:name":"King's Heights",
    "wof:placetype":"neighbourhood"
},
  "geometry": {"coordinates":[-113.98976519286835,51.26185547155924],"type":"Point"}
}