{
  "type": "Feature",
  "properties": {
    "wd:wordcount":228,
    "wof:name":"Southside",
    "wof:placetype":"neighbourhood"
},
  "geometry": {"coordinates":[-3.18632669065348,55.93535612765956],"type":"Point"}
}