{
  "type": "Feature",
  "properties": {
    "name:ara_x_preferred":[
        "\u0645\u0637\u0627\u0631 \u0646\u064a\u0646\u063a\u0628\u0648 \u0644\u064a\u0634 \u0627\u0644\u062f\u0648\u0644\u064a"
    ],
    "name:ces_x_preferred":[
        "mezin\u00e1rodn\u00ed leti\u0161t\u011b Ning-po Li-\u0161e"
    ],
    "name:eng_x_preferred":[
        "Ningbo Lishe International Airport"
    ],
    "name:eng_x_variant":[
        "NGB",
        "ZSNB"
    ],
    "name:eus_x_preferred":[
        "Ningbo Lishe nazioarteko aireportua"
    ],
    "name:fas_x_preferred":[
        "\u0641\u0631\u0648\u062f\u06af\u0627\u0647 \u0628\u06cc\u0646\u200c\u0627\u0644\u0645\u0644\u0644\u06cc \u0646\u06cc\u0646\u06af\u0628\u0648 \u0644\u06cc\u0634\u0647"
    ],
    "name:fra_x_preferred":[
        "a\u00e9roport international de Ningbo Lishe"
    ],
    "name:ind_x_preferred":[
        "Bandar Udara Internasional Lishe Ningbo"
    ],
    "name:jpn_x_preferred":[
        "\u5be7\u6ce2\u6adf\u793e\u56fd\u969b\u7a7a\u6e2f"
    ],
    "name:kor_x_preferred":[
        "\ub2dd\ubcf4 \ub9ac\uc11c \uad6d\uc81c\uacf5\ud56d"
    ],
    "name:msa_x_preferred":[
        "Lapangan Terbang Lishe"
    ],
    "name:nld_x_preferred":[
        "Ningbo Lishe International Airport"
    ],
    "name:nob_x_preferred":[
        "Ningbo Lishe internasjonale lufthavn"
    ],
    "name:pol_x_preferred":[
        "Port lotniczy Ningbo-Lishe"
    ],
    "name:swe_x_preferred":[
        "Ningbo Lishe International Airport"
    ],
    "name:vie_x_preferred":[
        "S\u00e2n bay qu\u1ed1c t\u1ebf L\u1ecbch X\u00e3 Ninh Ba"
    ],
    "name:zho_x_preferred":[
        "\u5be7\u6ce2\u6adf\u793e\u570b\u969b\u6a5f\u5834"
    ],
    "oa:elevation_ft":"13",
    "oa:type":"large_airport",
    "woe:hierarchy":{
        "country_id":23424781,
        "county_id":26198144,
        "localadmin_id":12685451,
        "planet_id":1,
        "state_id":12577992
    },
    "wof:name":"Ningbo Airport",
    "wof:placetype":"campus"
},
  "geometry": {"coordinates":[121.46199799999999,29.8267],"type":"Point"}
}