{
  "type": "Feature",
  "properties": {
    "wof:name":"Hubbard Farms",
    "wof:placetype":"neighbourhood"
},
  "geometry": {"coordinates":[-83.09067746039555,42.31882390202306],"type":"Point"}
}