{
  "type": "Feature",
  "properties": {
    "name:ceb_x_preferred":[
        "Darnley Island Airport"
    ],
    "name:deu_x_preferred":[
        "Darnley Island Airport"
    ],
    "name:eng_x_preferred":[
        "Darnley Island Airport"
    ],
    "name:eng_x_variant":[
        "NLF",
        "YDNI"
    ],
    "name:swe_x_preferred":[
        "Darnley Island Airport"
    ],
    "name:zho_x_preferred":[
        "\u9054\u6069\u5229\u5cf6\u6a5f\u5834"
    ],
    "oa:type":"small_airport",
    "wd:wordcount":35,
    "woe:hierarchy":{
        "country_id":23424748,
        "planet_id":1,
        "state_id":2344702
    },
    "wof:name":"Darnley Island Airport",
    "wof:placetype":"campus"
},
  "geometry": {"coordinates":[143.766998,-9.58333],"type":"Point"}
}