{
  "type": "Feature",
  "properties": {
    "gn:admin1_code":"39.0",
    "gn:asciiname":"Okatjiparango",
    "gn:dem":1222,
    "gn:feature_class":"P",
    "gn:feature_code":"PPL",
    "gn:name":"Okatjiparango",
    "gn:population":0,
    "gn:timezone":"Africa/Windhoek",
    "name:und_x_variant":[
        "Okatjiparanga",
        "Okatjiparango"
    ],
    "wof:name":"Okatjiparango",
    "wof:placetype":"locality"
},
  "geometry": {"coordinates":[18.58333,-19.71667],"type":"Point"}
}