{
  "type": "Feature",
  "properties": {
    "name:deu_x_preferred":[
        "Flughafen Lu\u00eds Dal Canalle Filho"
    ],
    "name:eng_x_preferred":[
        "Toledo Airport"
    ],
    "name:eng_x_variant":[
        "TOW",
        "SBTD"
    ],
    "name:fas_x_preferred":[
        "\u0641\u0631\u0648\u062f\u06af\u0627\u0647 \u062a\u0648\u0644\u062f\u0648"
    ],
    "name:jpn_x_preferred":[
        "\u30c8\u30ec\u30c9\u7a7a\u6e2f"
    ],
    "name:msa_x_preferred":[
        "Lapangan Terbang Toledo"
    ],
    "name:por_x_preferred":[
        "Aeroporto de Toledo"
    ],
    "name:swe_x_preferred":[
        "Toledo Airport"
    ],
    "name:tgk_x_preferred":[
        "\u0424\u0443\u0440\u0443\u0434\u0433\u043e\u04b3\u0438 \u0442\u0443\u043b\u0434\u0443"
    ],
    "oa:elevation_ft":"1843",
    "oa:type":"small_airport",
    "woe:hierarchy":{
        "country_id":23424768,
        "county_id":12580710,
        "planet_id":1,
        "state_id":2344859
    },
    "wof:name":"Aeroporto Toledo",
    "wof:placetype":"campus"
},
  "geometry": {"coordinates":[-53.697498,-24.6863],"type":"Point"}
}