{
  "type": "Feature",
  "properties": {
    "gn:admin1_code":"32.0",
    "gn:asciiname":"Orjimbarombonga",
    "gn:dem":418,
    "gn:feature_class":"P",
    "gn:feature_code":"PPL",
    "gn:name":"Orjimbarombonga",
    "gn:population":0,
    "gn:timezone":"Africa/Windhoek",
    "wof:name":"Orjimbarombonga",
    "wof:placetype":"locality"
},
  "geometry": {"coordinates":[12.75,-17.15],"type":"Point"}
}