{
  "type": "Feature",
  "properties": {
    "wof:name":"Aspendale Gardens",
    "wof:placetype":"neighbourhood"
},
  "geometry": {"coordinates":[145.11936633821733,-38.02228009493875],"type":"Point"}
}