{
  "type": "Feature",
  "properties": {
    "name:ceb_x_preferred":[
        "New Coalinga Municipal Airport"
    ],
    "name:eng_x_preferred":[
        "New Coalinga Municipal Airport"
    ],
    "name:eng_x_variant":[
        "CLG",
        "KC80"
    ],
    "name:fas_x_preferred":[
        "\u0641\u0631\u0648\u062f\u06af\u0627\u0647 \u0634\u0647\u0631\u06cc \u0646\u06cc\u0648 \u06a9\u0648\u0644\u06cc\u0646\u06af\u0627"
    ],
    "name:ron_x_preferred":[
        "Aeroportul Municipal New Coalinga"
    ],
    "name:zho_x_preferred":[
        "\u65b0\u79d1\u9748\u52a0\u5e02\u7acb\u6a5f\u5834"
    ],
    "oa:elevation_ft":"622",
    "oa:type":"small_airport",
    "woe:hierarchy":{
        "country_id":23424977,
        "county_id":12587679,
        "planet_id":1,
        "state_id":2347563
    },
    "wof:name":"Coalinga Airport",
    "wof:placetype":"campus"
},
  "geometry": {"coordinates":[-120.293999,36.163101],"type":"Point"}
}