{
  "type": "Feature",
  "properties": {
    "name:eng_x_variant":[
        "CLG",
        "KC80"
    ],
    "oa:elevation_ft":"622",
    "oa:type":"small_airport",
    "woe:hierarchy":{
        "country_id":23424977,
        "county_id":12587679,
        "planet_id":1,
        "state_id":2347563
    },
    "wof:name":"Coalinga Airport",
    "wof:placetype":"campus"
},
  "geometry": {"coordinates":[-120.293999,36.163101],"type":"Point"}
}