{
  "type": "Feature",
  "properties": {
    "name:chi_x_preferred":[
        "\u99ac\u52de\u6a5f\u5834"
    ],
    "name:eng_x_preferred":[
        "Marau Airport"
    ],
    "name:eng_x_variant":[
        "RUS",
        "AGGU"
    ],
    "name:fas_x_preferred":[
        "\u0641\u0631\u0648\u062f\u06af\u0627\u0647 \u0645\u0627\u0631\u0627\u0648"
    ],
    "name:hrv_x_preferred":[
        "Zra\u010dna luka Marau"
    ],
    "name:jpn_x_preferred":[
        "\u30de\u30e9\u30a6\u7a7a\u6e2f"
    ],
    "name:per_x_preferred":[
        "\u0641\u0631\u0648\u062f\u06af\u0627\u0647 \u0645\u0627\u0631\u0627\u0648"
    ],
    "name:pol_x_preferred":[
        "Port lotniczy Marau"
    ],
    "name:zho_x_preferred":[
        "\u99ac\u52de\u6a5f\u5834"
    ],
    "oa:type":"small_airport",
    "wd:wordcount":18,
    "woe:hierarchy":{
        "country_id":23424766,
        "planet_id":1,
        "state_id":2344839
    },
    "wof:name":"Marau Airport",
    "wof:placetype":"campus"
},
  "geometry": {"coordinates":[160.824997,-9.86167],"type":"Point"}
}