{
  "type": "Feature",
  "properties": {
    "wof:name":"Henderson",
    "wof:placetype":"neighbourhood"
},
  "geometry": {"coordinates":[-96.78392844404037,32.81426606611171],"type":"Point"}
}