{
  "type": "Feature",
  "properties": {
    "name:ara_x_preferred":[
        "\u0648\u0633\u0637 \u0627\u0644\u0628\u0644\u062f"
    ],
    "name:bul_x_preferred":[
        "\u0426\u0435\u043d\u0442\u044a\u0440"
    ],
    "name:ces_x_preferred":[
        "centrum m\u011bsta"
    ],
    "name:deu_x_preferred":[
        "Stadtkern"
    ],
    "name:ell_x_preferred":[
        "\u03ba\u03ad\u03bd\u03c4\u03c1\u03bf \u03c0\u03cc\u03bb\u03b5\u03c9\u03c2"
    ],
    "name:eng_x_preferred":[
        "city center"
    ],
    "name:epo_x_preferred":[
        "urba centro"
    ],
    "name:fas_x_preferred":[
        "\u0645\u0631\u06a9\u0632 \u0634\u0647\u0631"
    ],
    "name:fra_x_preferred":[
        "centre-ville"
    ],
    "name:fry_x_preferred":[
        "Binnenst\u00ead"
    ],
    "name:ita_x_preferred":[
        "centro citt\u00e0"
    ],
    "name:jpn_x_preferred":[
        "\u30b7\u30c6\u30a3\u30fb\u30bb\u30f3\u30bf\u30fc"
    ],
    "name:kor_x_preferred":[
        "\ub3c4\uc2ec"
    ],
    "name:nan_x_preferred":[
        "Chh\u012b-tiong-sim"
    ],
    "name:nld_x_preferred":[
        "binnenstad"
    ],
    "name:pol_x_preferred":[
        "\u015br\u00f3dmie\u015bcie"
    ],
    "name:por_x_preferred":[
        "centro urbano"
    ],
    "name:rus_x_preferred":[
        "\u0446\u0435\u043d\u0442\u0440 \u0433\u043e\u0440\u043e\u0434\u0430"
    ],
    "name:srp_x_preferred":[
        "\u0446\u0435\u043d\u0442\u0430\u0440 \u0433\u0440\u0430\u0434\u0430"
    ],
    "name:zho_x_preferred":[
        "\u5e02\u4e2d\u5fc3"
    ],
    "wd:wordcount":610,
    "wof:name":"City Center",
    "wof:placetype":"neighbourhood"
},
  "geometry": {"coordinates":[34.77267980351351,32.07779517468779],"type":"Point"}
}