{
  "type": "Feature",
  "properties": {
    "name:ara_x_preferred":[
        "\u0648\u0633\u0637 \u0627\u0644\u0628\u0644\u062f"
    ],
    "name:ben_x_preferred":[
        "\u09b6\u09b9\u09b0\u09c7\u09b0 \u0995\u09c7\u09a8\u09cd\u09a6\u09cd\u09b0\u09b8\u09cd\u09a5\u09b2"
    ],
    "name:bul_x_preferred":[
        "\u0426\u0435\u043d\u0442\u044a\u0440"
    ],
    "name:cat_x_preferred":[
        "centre ciutat"
    ],
    "name:ces_x_preferred":[
        "centrum m\u011bsta"
    ],
    "name:dan_x_preferred":[
        "bykerne"
    ],
    "name:deu_x_preferred":[
        "Stadtkern"
    ],
    "name:ell_x_preferred":[
        "\u03ba\u03ad\u03bd\u03c4\u03c1\u03bf \u03c0\u03cc\u03bb\u03b5\u03c9\u03c2"
    ],
    "name:eng_x_preferred":[
        "city center"
    ],
    "name:epo_x_preferred":[
        "urba centro"
    ],
    "name:est_x_preferred":[
        "Kesklinn"
    ],
    "name:fas_x_preferred":[
        "\u0645\u0631\u06a9\u0632 \u0634\u0647\u0631"
    ],
    "name:fin_x_preferred":[
        "keskusta"
    ],
    "name:fra_x_preferred":[
        "centre-ville"
    ],
    "name:fry_x_preferred":[
        "Binnenst\u00ead"
    ],
    "name:heb_x_preferred":[
        "\u05de\u05e8\u05db\u05d6 \u05d4\u05e2\u05d9\u05e8"
    ],
    "name:hye_x_preferred":[
        "\u0584\u0561\u0572\u0561\u0584\u056b \u056f\u0565\u0576\u057f\u0580\u0578\u0576"
    ],
    "name:ita_x_preferred":[
        "centro citt\u00e0"
    ],
    "name:jpn_x_preferred":[
        "\u30b7\u30c6\u30a3\u30fb\u30bb\u30f3\u30bf\u30fc"
    ],
    "name:kor_x_preferred":[
        "\ub3c4\uc2ec"
    ],
    "name:lav_x_preferred":[
        "pils\u0113tas centrs"
    ],
    "name:lit_x_preferred":[
        "miesto centras"
    ],
    "name:nan_x_preferred":[
        "Chh\u012b-tiong-sim"
    ],
    "name:nld_x_preferred":[
        "binnenstad"
    ],
    "name:nno_x_preferred":[
        "bysentrum"
    ],
    "name:nob_x_preferred":[
        "bysentrum"
    ],
    "name:nrm_x_preferred":[
        "Centre-ville"
    ],
    "name:pol_x_preferred":[
        "\u015br\u00f3dmie\u015bcie"
    ],
    "name:por_x_preferred":[
        "centro urbano"
    ],
    "name:rus_x_preferred":[
        "\u0446\u0435\u043d\u0442\u0440 \u0433\u043e\u0440\u043e\u0434\u0430"
    ],
    "name:sme_x_preferred":[
        "g\u00e1vpotguovdd\u00e1\u0161"
    ],
    "name:sms_x_preferred":[
        "kuvddl\u00f5s"
    ],
    "name:spa_x_preferred":[
        "centro urbano"
    ],
    "name:srp_x_preferred":[
        "\u0446\u0435\u043d\u0442\u0430\u0440 \u0433\u0440\u0430\u0434\u0430"
    ],
    "name:swe_x_preferred":[
        "centrum"
    ],
    "name:tur_x_preferred":[
        "\u015eehir merkezi"
    ],
    "name:ukr_x_preferred":[
        "\u0446\u0435\u043d\u0442\u0440 \u043c\u0456\u0441\u0442\u0430"
    ],
    "name:vie_x_preferred":[
        "Trung t\u00e2m th\u00e0nh ph\u1ed1"
    ],
    "name:yue_x_preferred":[
        "\u5e02\u4e2d\u5fc3"
    ],
    "name:zho_x_preferred":[
        "\u5e02\u4e2d\u5fc3"
    ],
    "wd:wordcount":610,
    "wof:name":"City Center",
    "wof:placetype":"neighbourhood"
},
  "geometry": {"coordinates":[34.77268,32.077795],"type":"Point"}
}