{
  "type": "Feature",
  "properties": {
    "wd:wordcount":610,
    "wof:name":"City Center",
    "wof:placetype":"neighbourhood"
},
  "geometry": {"coordinates":[34.77267980351351,32.07779517468779],"type":"Point"}
}