{
  "type": "Feature",
  "properties": {
    "name:eng_x_preferred":[
        "Myitkyina Airport"
    ],
    "name:eng_x_variant":[
        "MYT",
        "VYMK"
    ],
    "name:fas_x_preferred":[
        "\u0641\u0631\u0648\u062f\u06af\u0627\u0647 \u0645\u06cc\u06cc\u062a\u06a9\u06cc\u06cc\u0646\u0627"
    ],
    "name:jpn_x_preferred":[
        "\u30df\u30c3\u30c1\u30fc\u30ca\u30fc\u7a7a\u6e2f"
    ],
    "name:msa_x_preferred":[
        "Lapangan Terbang Pamti"
    ],
    "name:mya_x_preferred":[
        "\u1019\u103c\u1005\u103a\u1000\u103c\u102e\u1038\u1014\u102c\u1038\u101c\u1031\u1006\u102d\u1015\u103a"
    ],
    "name:pol_x_preferred":[
        "Port lotniczy Myitkyina"
    ],
    "name:swe_x_preferred":[
        "Myitkyina Airport"
    ],
    "name:tgk_x_preferred":[
        "\u0424\u0443\u0440\u0443\u0434\u0433\u043e\u04b3\u0438 \u0448\u0430\u04b3\u0440\u0438\u0441\u0442\u043e\u043d \u043c\u043e\u0432\u043d\u0442 \u043e\u0438\u0440\u0438 \u0441\u04ef\u0440\u04e3"
    ],
    "name:vie_x_preferred":[
        "S\u00e2n bay Myitkyina"
    ],
    "name:zho_x_preferred":[
        "\u5bc6\u652f\u90a3"
    ],
    "oa:elevation_ft":"475",
    "oa:type":"medium_airport",
    "wd:wordcount":279,
    "woe:hierarchy":{
        "country_id":23424763,
        "planet_id":1,
        "state_id":2344813
    },
    "wof:name":"Myitkyina Airport",
    "wof:placetype":"campus"
},
  "geometry": {"coordinates":[97.35189800000001,25.3836],"type":"Point"}
}