{
  "type": "Feature",
  "properties": {
    "name:afr_x_preferred":[
        "Fordsburg"
    ],
    "name:ast_x_preferred":[
        "Fordsburg"
    ],
    "name:eng_x_preferred":[
        "Fordsburg"
    ],
    "name:nld_x_preferred":[
        "Fordsburg"
    ],
    "name:nso_x_preferred":[
        "Fordsburg"
    ],
    "wd:wordcount":277,
    "wof:name":"Fordsburg",
    "wof:placetype":"neighbourhood"
},
  "geometry": {"coordinates":[28.022151,-26.206173],"type":"Point"}
}