{
  "type": "Feature",
  "properties": {
    "name:afr_x_preferred":[
        "Fordsburg"
    ],
    "wd:wordcount":277,
    "wof:name":"Fordsburg",
    "wof:placetype":"neighbourhood"
},
  "geometry": {"coordinates":[28.02215125855247,-26.20617341718201],"type":"Point"}
}