{
  "type": "Feature",
  "properties": {
    "name:eng_x_variant":[
        "DOC",
        "GB-DOC"
    ],
    "oa:elevation_ft":"1",
    "oa:type":"small_airport",
    "woe:hierarchy":{
        "country_id":23424975,
        "county_id":12602203,
        "localadmin_id":12696199,
        "planet_id":1,
        "state_id":12578048
    },
    "wof:name":"Dornoch Airport",
    "wof:placetype":"campus"
},
  "geometry": {"coordinates":[-4.023,57.868999],"type":"Point"}
}