{
  "type": "Feature",
  "properties": {
    "name:ceb_x_preferred":[
        "Ceduna Airport"
    ],
    "name:deu_x_preferred":[
        "Ceduna Airport"
    ],
    "name:eng_x_preferred":[
        "Ceduna Airport"
    ],
    "name:eng_x_variant":[
        "CED",
        "YCDU"
    ],
    "name:fas_x_preferred":[
        "\u0641\u0631\u0648\u062f\u06af\u0627\u0647 \u0633\u062f\u0648\u0646\u0627"
    ],
    "name:fra_x_preferred":[
        "a\u00e9roport de Ceduna"
    ],
    "name:ita_x_preferred":[
        "aeroporto di Ceduna"
    ],
    "name:msa_x_preferred":[
        "Lapangan Terbang Ceduna"
    ],
    "name:ron_x_preferred":[
        "Aeroportul Ceduna"
    ],
    "name:rus_x_preferred":[
        "\u0421\u0435\u0434\u044c\u044e\u043d\u0430"
    ],
    "name:spa_x_preferred":[
        "Ceduna"
    ],
    "name:swe_x_preferred":[
        "Ceduna Airport"
    ],
    "name:tgk_x_preferred":[
        "\u0424\u0443\u0440\u0443\u0434\u0433\u043e\u04b3\u0438 \u0441\u0434\u0443\u043d\u043e"
    ],
    "name:tgk_x_variant":[
        "Moora Airport"
    ],
    "name:ukr_x_preferred":[
        "\u0426\u0435\u0434\u0443\u043d\u0430"
    ],
    "name:zho_x_preferred":[
        "\u585e\u675c\u7d0d\u6a5f\u5834"
    ],
    "oa:elevation_ft":"77",
    "oa:type":"medium_airport",
    "wd:wordcount":51,
    "woe:hierarchy":{
        "country_id":23424748,
        "county_id":55864205,
        "planet_id":1,
        "state_id":2344703
    },
    "wof:name":"Ceduna Airport",
    "wof:placetype":"campus"
},
  "geometry": {"coordinates":[133.71000699999999,-32.1306],"type":"Point"}
}