{
  "type": "Feature",
  "properties": {
    "gn:admin1_code":"31.0",
    "gn:asciiname":"Ysterputs",
    "gn:dem":726,
    "gn:feature_class":"P",
    "gn:feature_code":"PPL",
    "gn:name":"Ysterputs",
    "gn:population":0,
    "gn:timezone":"Africa/Windhoek",
    "name:und_x_variant":[
        "Aup\u00fctz",
        "Ysterputs"
    ],
    "wof:name":"Ysterputs",
    "wof:placetype":"locality"
},
  "geometry": {"coordinates":[18.08333,-28.25],"type":"Point"}
}