{
  "type": "Feature",
  "properties": {
    "name:ceb_x_preferred":[
        "Yechon Ab"
    ],
    "name:eng_x_preferred":[
        "Yecheon Air Base"
    ],
    "name:eng_x_variant":[
        "YEC",
        "RKTY"
    ],
    "name:jpn_x_preferred":[
        "\u91b4\u6cc9\u7a7a\u8ecd\u57fa\u5730"
    ],
    "name:kor_x_preferred":[
        "\uc608\ucc9c\ube44\ud589\uc7a5"
    ],
    "name:msa_x_preferred":[
        "Lapangan Terbang Yecheon Aero"
    ],
    "name:pol_x_preferred":[
        "Port lotniczy Yechon"
    ],
    "name:por_x_preferred":[
        "Aeroporto de Yecheon"
    ],
    "name:swe_x_preferred":[
        "Yechon Ab"
    ],
    "name:vie_x_preferred":[
        "S\u00e2n bay qu\u00e2n s\u1ef1 Yecheon"
    ],
    "name:zho_x_preferred":[
        "\u91b4\u6cc9\u98db\u884c\u5834"
    ],
    "oa:elevation_ft":"354",
    "oa:type":"medium_airport",
    "woe:hierarchy":{
        "country_id":23424868,
        "county_id":28289317,
        "localadmin_id":28808572,
        "planet_id":1,
        "state_id":2345970
    },
    "wof:name":"\uc608\ucc9c\uacf5\ud56d",
    "wof:placetype":"campus"
},
  "geometry": {"coordinates":[128.354996,36.631901],"type":"Point"}
}