{
  "type": "Feature",
  "properties": {
    "gn:admin1_code":"28.0",
    "gn:asciiname":"Shamundambo",
    "gn:dem":1012,
    "gn:feature_class":"P",
    "gn:feature_code":"PPL",
    "gn:name":"Shamundambo",
    "gn:population":0,
    "gn:timezone":"Africa/Windhoek",
    "wof:name":"Shamundambo",
    "wof:placetype":"locality"
},
  "geometry": {"coordinates":[21.51667,-18.08333],"type":"Point"}
}