{
  "type": "Feature",
  "properties": {
    "oa:elevation_ft":"4887",
    "oa:type":"medium_airport",
    "wd:wordcount":975,
    "woe:hierarchy":{
        "country_id":23425004,
        "county_id":56048529,
        "planet_id":1,
        "state_id":24550731
    },
    "wof:name":"Harare International Airport",
    "wof:placetype":"campus"
},
  "geometry": {"coordinates":[31.092847222222,-17.931805555556],"type":"Point"}
}