{
  "type": "Feature",
  "properties": {
    "name:afr_x_preferred":[
        "Robert Gabriel Mugabe Internasionale Lughawe"
    ],
    "name:ara_x_preferred":[
        "\u0645\u0637\u0627\u0631 \u0631\u0648\u0628\u0631\u062a \u063a\u0627\u0628\u0631\u064a\u0644 \u0645\u0648\u062c\u0627\u0628\u064a \u0627\u0644\u062f\u0648\u0644\u064a"
    ],
    "name:cym_x_preferred":[
        "Maes Awyr Rhyngwladol Harare"
    ],
    "name:eng_x_variant":[
        "HRE",
        "FVHA"
    ],
    "name:epo_x_preferred":[
        "Internacia Flughaveno Hararo"
    ],
    "name:est_x_preferred":[
        "Robert Gabriel Mugabe rahvusvaheline lennujaam"
    ],
    "name:fas_x_preferred":[
        "\u0641\u0631\u0648\u062f\u06af\u0627\u0647 \u0628\u06cc\u0646\u200c\u0627\u0644\u0645\u0644\u0644\u06cc \u062d\u0631\u0627\u0631\u0647"
    ],
    "name:fin_x_preferred":[
        "Robert Gabriel Mugaben kansainv\u00e4linen lentoasema"
    ],
    "name:fra_x_preferred":[
        "a\u00e9roport international d'Harare"
    ],
    "name:glg_x_preferred":[
        "Aeroporto Robert Gabriel Mugabe"
    ],
    "name:hun_x_preferred":[
        "Robert Gabriel Mugabe nemzetk\u00f6zi rep\u00fcl\u0151t\u00e9r"
    ],
    "name:ind_x_preferred":[
        "Bandar Udara Internasional Harare"
    ],
    "name:jpn_x_preferred":[
        "\u30cf\u30e9\u30ec\u56fd\u969b\u7a7a\u6e2f"
    ],
    "name:kor_x_preferred":[
        "\ub85c\ubc84\ud2b8 \uac00\ube0c\ub9ac\uc5d8 \ubb34\uac00\ubca0 \uad6d\uc81c\uacf5\ud56d"
    ],
    "name:lit_x_preferred":[
        "Harar\u0117s oro uostas"
    ],
    "name:msa_x_preferred":[
        "Lapangan Terbang Antarabangsa Harare"
    ],
    "name:nob_x_preferred":[
        "Harare internasjonale lufthavn"
    ],
    "name:pol_x_preferred":[
        "Port lotniczy Harare"
    ],
    "name:ron_x_preferred":[
        "Aeroportul Interna\u021bional Harare"
    ],
    "name:rus_x_preferred":[
        "\u041c\u0435\u0436\u0434\u0443\u043d\u0430\u0440\u043e\u0434\u043d\u044b\u0439 \u0430\u044d\u0440\u043e\u043f\u043e\u0440\u0442 \u0438\u043c\u0435\u043d\u0438 \u0420\u043e\u0431\u0435\u0440\u0442\u0430 \u041c\u0443\u0433\u0430\u0431\u0435"
    ],
    "name:tgk_x_preferred":[
        "\u0424\u0443\u0440\u0443\u0434\u0433\u043e\u04b3\u0438 \u0431\u0438\u043d\u200c\u0430\u043b\u043c\u0438\u043b\u0430\u043b\u04e3 \u0445\u0440\u043e\u0440\u04b3"
    ],
    "name:tha_x_preferred":[
        "\u0e17\u0e48\u0e32\u0e2d\u0e32\u0e01\u0e32\u0e28\u0e22\u0e32\u0e19\u0e19\u0e32\u0e19\u0e32\u0e0a\u0e32\u0e15\u0e34\u0e2e\u0e32\u0e23\u0e32\u0e40\u0e23"
    ],
    "name:tur_x_preferred":[
        "Uluslararas\u0131 Harare Havaalan\u0131"
    ],
    "name:vie_x_preferred":[
        "S\u00e2n bay qu\u1ed1c t\u1ebf Harare"
    ],
    "name:zho_x_preferred":[
        "\u54c8\u62c9\u96f7\u56fd\u9645\u673a\u573a"
    ],
    "oa:elevation_ft":"4887",
    "oa:type":"medium_airport",
    "wd:wordcount":975,
    "woe:hierarchy":{
        "country_id":23425004,
        "county_id":56048529,
        "planet_id":1,
        "state_id":24550731
    },
    "wof:name":"Harare International Airport",
    "wof:placetype":"campus"
},
  "geometry": {"coordinates":[31.092847,-17.931806],"type":"Point"}
}