{
  "type": "Feature",
  "properties": {
    "gn:admin1_code":"32.0",
    "gn:asciiname":"Palm",
    "gn:dem":993,
    "gn:feature_class":"P",
    "gn:feature_code":"PPL",
    "gn:name":"Palm",
    "gn:population":0,
    "gn:timezone":"Africa/Windhoek",
    "name:bul_x_preferred":[
        "\u041f\u0430\u043b\u043c"
    ],
    "name:cat_x_preferred":[
        "Palm"
    ],
    "name:deu_x_preferred":[
        "Palm"
    ],
    "name:fas_x_preferred":[
        "\u0646\u062e\u0644"
    ],
    "name:fin_x_preferred":[
        "Palm"
    ],
    "name:fra_x_preferred":[
        "Palm"
    ],
    "name:heb_x_preferred":[
        "\u05e4\u05d0\u05dc\u05dd"
    ],
    "name:ita_x_preferred":[
        "Palm"
    ],
    "name:jpn_x_preferred":[
        "\u30d1\u30fc\u30e0"
    ],
    "name:kor_x_preferred":[
        "\ud31c"
    ],
    "name:nep_x_preferred":[
        "\u0939\u0924\u094d\u0915\u0947\u0932\u093e"
    ],
    "name:nld_x_preferred":[
        "Palm"
    ],
    "name:nor_x_preferred":[
        "Palm"
    ],
    "name:rus_x_preferred":[
        "Palm"
    ],
    "name:slk_x_preferred":[
        "Palm"
    ],
    "name:spa_x_preferred":[
        "Palm"
    ],
    "name:sun_x_preferred":[
        "Dampal leungeun"
    ],
    "name:swe_x_preferred":[
        "Palm"
    ],
    "name:tgl_x_preferred":[
        "Palm"
    ],
    "name:tha_x_preferred":[
        "\u0e1b\u0e32\u0e25\u0e4c\u0e21"
    ],
    "name:tur_x_preferred":[
        "Palm"
    ],
    "name:ukr_x_preferred":[
        "Palm"
    ],
    "wof:name":"Palm",
    "wof:placetype":"locality"
},
  "geometry": {"coordinates":[13.96667,-19.91667],"type":"Point"}
}