{
  "type": "Feature",
  "properties": {
    "gn:admin1_code":"32.0",
    "gn:asciiname":"Palm",
    "gn:dem":993,
    "gn:feature_class":"P",
    "gn:feature_code":"PPL",
    "gn:name":"Palm",
    "gn:population":0,
    "gn:timezone":"Africa/Windhoek",
    "wof:name":"Palm",
    "wof:placetype":"locality"
},
  "geometry": {"coordinates":[13.96667,-19.91667],"type":"Point"}
}