{
  "type": "Feature",
  "properties": {
    "gn:admin1_code":"30.0",
    "gn:asciiname":"Duwisib",
    "gn:dem":1497,
    "gn:feature_class":"P",
    "gn:feature_code":"PPL",
    "gn:name":"Duwisib",
    "gn:population":0,
    "gn:timezone":"Africa/Windhoek",
    "name:und_x_variant":[
        "Alt Duwisib",
        "Duwisib"
    ],
    "wof:name":"Duwisib",
    "wof:placetype":"locality"
},
  "geometry": {"coordinates":[16.51667,-25.25],"type":"Point"}
}