{
  "type": "Feature",
  "properties": {
    "gn:admin1_code":"35.0",
    "gn:asciiname":"Ondjiripumwa",
    "gn:dem":1236,
    "gn:feature_class":"P",
    "gn:feature_code":"PPL",
    "gn:name":"Ondjiripumwa",
    "gn:population":0,
    "gn:timezone":"Africa/Windhoek",
    "wof:name":"Ondjiripumwa",
    "wof:placetype":"locality"
},
  "geometry": {"coordinates":[19.41667,-23.55],"type":"Point"}
}