{
  "type": "Feature",
  "properties": {
    "name:ceb_x_preferred":[
        "Central"
    ],
    "name:deu_x_preferred":[
        "Central"
    ],
    "name:est_x_preferred":[
        "Central"
    ],
    "name:fas_x_preferred":[
        "\u0645\u0631\u06a9\u0632\u06cc"
    ],
    "name:fra_x_preferred":[
        "Central"
    ],
    "name:ita_x_preferred":[
        "Central"
    ],
    "name:jpn_x_preferred":[
        "\u30bb\u30f3\u30c8\u30e9\u30eb"
    ],
    "name:kor_x_preferred":[
        "\uc13c\ud2b8\ub7f4"
    ],
    "name:nld_x_preferred":[
        "Central"
    ],
    "name:pol_x_preferred":[
        "Central"
    ],
    "name:por_x_preferred":[
        "Central"
    ],
    "name:rus_x_preferred":[
        "\u0426\u0435\u043d\u0442\u0440\u0430\u043b\u044c"
    ],
    "name:slk_x_preferred":[
        "Centr\u00e1l"
    ],
    "name:spa_x_preferred":[
        "Central"
    ],
    "name:swe_x_preferred":[
        "Central"
    ],
    "name:tam_x_preferred":[
        "\u0b9a\u0bc6\u0ba9\u0bcd\u0b9f\u0bcd\u0bb0\u0bb2\u0bcd"
    ],
    "name:tha_x_preferred":[
        "\u0e01\u0e25\u0e32\u0e07"
    ],
    "name:ukr_x_preferred":[
        "\u0421\u0435\u043d\u0442\u0440\u0430\u043b"
    ],
    "name:vol_x_preferred":[
        "Central"
    ],
    "name:zho_x_preferred":[
        "\u4e2d"
    ],
    "qs:name":"Central",
    "qs:name_adm0":"US Virgin Islands",
    "qs:name_adm1":"Saint John Island",
    "qs:photos":1390,
    "qs:photos_1k":282,
    "qs:photos_9k":24,
    "qs:photos_9r":14,
    "qs:photos_all":5518,
    "qs:photos_sr":12,
    "qs:placetype":"County",
    "qs:pop_sr":"0",
    "wd:wordcount":599,
    "wof:name":"Central",
    "wof:placetype":"county"
},
  "geometry": {"coordinates":[-64.74867500000001,18.441715],"type":"Point"}
}