{
  "type": "Feature",
  "properties": {
    "qs:name":"Central",
    "qs:name_adm0":"US Virgin Islands",
    "qs:name_adm1":"Saint John Island",
    "qs:photos":1390,
    "qs:photos_1k":282,
    "qs:photos_9k":24,
    "qs:photos_9r":14,
    "qs:photos_all":5518,
    "qs:photos_sr":12,
    "qs:placetype":"County",
    "qs:pop_sr":"0",
    "wd:wordcount":599,
    "wof:name":"Central",
    "wof:placetype":"county"
},
  "geometry": {"coordinates":[-64.74867500000001,18.441715],"type":"Point"}
}