{
  "type": "Feature",
  "properties": {
    "name:ara_x_colloquial":[
        "Anfa-Superieur"
    ],
    "name:ara_x_preferred":[
        "Anfa-Sup\u00e9rieur"
    ],
    "name:unk_x_variant":[
        "Anfa-Sup\u00e9rieur"
    ],
    "qs:gn_adm0_cc":"MA",
    "qs:gn_local":2553604,
    "qs:local_max":5740,
    "qs:local_sum":7075,
    "qs:localhoods":6,
    "qs:name":"Anfa-Sup\u00e9rieur",
    "qs:name_adm0":"\u0627\u0644\u0645\u063a\u0631\u0628",
    "qs:name_adm1":"\u0627\u0644\u062f\u0627\u0631 \u0627\u0644\u0628\u064a\u0636\u0627\u0621 \u0627\u0644\u0643\u0628\u0631\u0649",
    "qs:name_adm2":"\u0627\u0644\u062f\u0627\u0631 \u0627\u0644\u0628\u064a\u0636\u0627\u0621",
    "qs:name_lau":"\u0623\u0646\u0641\u0627",
    "qs:name_local":"\u0627\u0644\u062f\u0627\u0631 \u0627\u0644\u0628\u064a\u0636\u0627\u0621",
    "qs:photo_max":30,
    "qs:photo_sum":104,
    "qs:placetype":"Suburb",
    "qs:quad_count":10,
    "qs:woe_adm0":23424893,
    "qs:woe_adm1":56120054,
    "qs:woe_adm2":2346195,
    "qs:woe_lau":56439167,
    "qs:woe_local":1532755,
    "qs:woe_ver":"7.10.0",
    "wof:lang":[
        "ara"
    ],
    "wof:name":"Anfa-Sup\u00e9rieur",
    "wof:placetype":"neighbourhood"
},
  "geometry": {"coordinates":[-7.666424,33.599311],"type":"Point"}
}