{
  "type": "Feature",
  "properties": {
    "name:ceb_x_preferred":[
        "Chaparral Airport"
    ],
    "name:eng_x_preferred":[
        "General Navas Pardo Airport"
    ],
    "name:eng_x_variant":[
        "CPL",
        "SKHA",
        "Chaparral Airport"
    ],
    "name:ron_x_preferred":[
        "Aeroportul Chaparral"
    ],
    "oa:elevation_ft":"2730",
    "oa:type":"small_airport",
    "woe:hierarchy":{
        "country_id":23424787,
        "county_id":26797552,
        "planet_id":1,
        "state_id":2345073
    },
    "wof:name":"Chaparral Airport",
    "wof:placetype":"campus"
},
  "geometry": {"coordinates":[-75.467,3.717],"type":"Point"}
}