{
  "type": "Feature",
  "properties": {
    "name:ceb_x_preferred":[
        "South Caicos Airport"
    ],
    "name:deu_x_preferred":[
        "South Caicos Airport"
    ],
    "name:eng_x_preferred":[
        "South Caicos Airport"
    ],
    "name:eng_x_variant":[
        "XSC",
        "MBSC"
    ],
    "name:fas_x_preferred":[
        "\u0641\u0631\u0648\u062f\u06af\u0627\u0647 \u0633\u0648\u062a \u06a9\u0627\u06cc\u06a9\u0648\u0632"
    ],
    "name:fra_x_preferred":[
        "a\u00e9rodrome des South Caicos"
    ],
    "name:jpn_x_preferred":[
        "\u30b5\u30a6\u30b9\u30fb\u30ab\u30a4\u30b3\u30b9\u7a7a\u6e2f"
    ],
    "name:msa_x_preferred":[
        "Lapangan Terbang South Caicos"
    ],
    "name:pol_x_preferred":[
        "Port lotniczy South Caicos"
    ],
    "name:ron_x_preferred":[
        "Aeroportul South Caicos"
    ],
    "name:tur_x_preferred":[
        "G\u00fcney Caicos Havaliman\u0131"
    ],
    "oa:elevation_ft":"6",
    "oa:type":"medium_airport",
    "wd:wordcount":92,
    "woe:hierarchy":{
        "country_id":23424962,
        "planet_id":1,
        "state_id":24549931
    },
    "wof:name":"South Caicos Airport",
    "wof:placetype":"campus"
},
  "geometry": {"coordinates":[-71.528611,21.515833],"type":"Point"}
}