{
  "type": "Feature",
  "properties": {
    "name:fas_x_preferred":[
        "\u0641\u0631\u0648\u062f\u06af\u0627\u0647 \u0633\u0648\u062a \u06a9\u0627\u06cc\u06a9\u0648\u0632"
    ],
    "name:msa_x_preferred":[
        "Lapangan Terbang South Caicos"
    ],
    "name:pol_x_preferred":[
        "Port lotniczy South Caicos"
    ],
    "oa:elevation_ft":"6",
    "oa:type":"medium_airport",
    "wd:wordcount":92,
    "woe:hierarchy":{
        "country_id":23424962,
        "planet_id":1,
        "state_id":24549931
    },
    "wof:name":"South Caicos Airport",
    "wof:placetype":"campus"
},
  "geometry": {"coordinates":[-71.528611111111,21.515833333333],"type":"Point"}
}