{
  "type": "Feature",
  "properties": {
    "wof:name":"Heiderberg",
    "wof:placetype":"neighbourhood"
},
  "geometry": {"coordinates":[18.87749626799007,-34.10159753392381],"type":"Point"}
}