{
  "type": "Feature",
  "properties": {
    "name:deu_x_preferred":[
        "Flughafen Pelotas"
    ],
    "name:eng_x_preferred":[
        "Pelotas International Airport"
    ],
    "name:eng_x_variant":[
        "PET",
        "SBPK"
    ],
    "name:fas_x_preferred":[
        "\u0641\u0631\u0648\u062f\u06af\u0627\u0647 \u0628\u06cc\u0646\u200c\u0627\u0644\u0645\u0644\u0644\u06cc \u067e\u0644\u0648\u062a\u0627\u0633"
    ],
    "name:fra_x_preferred":[
        "a\u00e9roport international de Pelotas"
    ],
    "name:jpn_x_preferred":[
        "\u30da\u30ed\u30bf\u30b9\u56fd\u969b\u7a7a\u6e2f"
    ],
    "name:msa_x_preferred":[
        "Lapangan Terbang Antarabangsa Pelotas"
    ],
    "name:por_x_preferred":[
        "Aeroporto Internacional de Pelotas"
    ],
    "name:tgk_x_preferred":[
        "\u0424\u0443\u0440\u0443\u0434\u0433\u043e\u04b3\u0438 \u0431\u0438\u043d\u200c\u0430\u043b\u043c\u0438\u043b\u0430\u043b\u04e3 \u043f\u043b\u0443\u0442\u043e\u0441"
    ],
    "oa:elevation_ft":"59",
    "oa:type":"medium_airport",
    "woe:hierarchy":{
        "country_id":23424768,
        "county_id":12581438,
        "planet_id":1,
        "state_id":2344864
    },
    "wof:name":"Aeroporto Pelotas",
    "wof:placetype":"campus"
},
  "geometry": {"coordinates":[-52.327702,-31.718399],"type":"Point"}
}