{
  "type": "Feature",
  "properties": {
    "gn:admin1_code":"38.0",
    "gn:asciiname":"Okatope",
    "gn:dem":1102,
    "gn:feature_class":"P",
    "gn:feature_code":"PPL",
    "gn:name":"Okatope",
    "gn:population":0,
    "gn:timezone":"Africa/Windhoek",
    "wof:name":"Okatope",
    "wof:placetype":"locality"
},
  "geometry": {"coordinates":[16.26667,-18.08333],"type":"Point"}
}