{
  "type": "Feature",
  "properties": {
    "name:ceb_x_preferred":[
        "Nueva Guinea Airport"
    ],
    "name:eng_x_preferred":[
        "Nueva Guinea Airport"
    ],
    "name:jpn_x_preferred":[
        "\u30cc\u30a8\u30d0\u30fb\u30b0\u30a4\u30cd\u30a2\u7a7a\u6e2f"
    ],
    "name:msa_x_preferred":[
        "Lapangan Terbang N. Guinea"
    ],
    "name:pol_x_preferred":[
        "Port lotniczy Nueva Guinea"
    ],
    "name:ron_x_preferred":[
        "Aeroportul Nueva Guinea"
    ],
    "name:spa_x_preferred":[
        "Aeropuerto de Nueva Guinea"
    ],
    "name:swe_x_preferred":[
        "Nueva Guinea Airport"
    ],
    "oa:elevation_ft":"606",
    "oa:type":"small_airport",
    "wd:wordcount":137,
    "woe:hierarchy":{
        "country_id":23424915,
        "county_id":26813436,
        "planet_id":1,
        "state_id":20069832
    },
    "wof:name":"Nueva Guinea Airport",
    "wof:placetype":"campus"
},
  "geometry": {"coordinates":[-84.4547,11.6972],"type":"Point"}
}