{
  "type": "Feature",
  "properties": {
    "name:fas_x_preferred":[
        "\u0641\u0631\u0648\u062f\u06af\u0627\u0647 \u0633\u0641\u062f\u0631\u062c\u0648\u0646\u06af"
    ],
    "name:hin_x_preferred":[
        "\u0938\u092b\u0926\u0930\u091c\u0902\u0917 \u0935\u093f\u092e\u093e\u0928\u0915\u094d\u0937\u0947\u0924\u094d\u0930"
    ],
    "name:ind_x_preferred":[
        "Bandar Udara Safdarjung"
    ],
    "name:mal_x_preferred":[
        "\u0d38\u0d2b\u0d4d\u200c\u0d26\u0d7c\u0d1c\u0d02\u0d17\u0d4d \u0d35\u0d3f\u0d2e\u0d3e\u0d28\u0d24\u0d4d\u0d24\u0d3e\u0d35\u0d33\u0d02"
    ],
    "name:mar_x_preferred":[
        "\u0938\u092b\u0926\u0930\u091c\u0902\u0917 \u0935\u093f\u092e\u093e\u0928\u0924\u0933"
    ],
    "name:msa_x_preferred":[
        "Lapangan Terbang Safdarjung"
    ],
    "name:tgk_x_preferred":[
        "\u0424\u0443\u0440\u0443\u0434\u0433\u043e\u04b3\u0438 \u0441\u0444\u0434\u0440\u04b7\u0443\u043d\u0433"
    ],
    "name:ukr_x_preferred":[
        "\u0410\u0435\u0440\u043e\u043f\u043e\u0440\u0442 \u0421\u0430\u0444\u0434\u0430\u0440\u0434\u0436\u0430\u043d\u0491"
    ],
    "oa:elevation_ft":"705",
    "oa:type":"medium_airport",
    "wd:wordcount":1437,
    "woe:hierarchy":{
        "country_id":23424848,
        "planet_id":1,
        "state_id":20070458
    },
    "wof:name":"Safdarjung Airport",
    "wof:placetype":"campus"
},
  "geometry": {"coordinates":[77.205833333333,28.584444444444],"type":"Point"}
}