{
  "type": "Feature",
  "properties": {
    "name:eng_x_preferred":[
        "Darab Airport"
    ],
    "name:msa_x_preferred":[
        "Lapangan Terbang Darab"
    ],
    "name:ron_x_preferred":[
        "Aeroportul Darab"
    ],
    "oa:elevation_ft":"3600",
    "oa:type":"small_airport",
    "woe:hierarchy":{
        "country_id":23424851,
        "planet_id":1,
        "state_id":2345772
    },
    "wof:name":"Darab Airport",
    "wof:placetype":"campus"
},
  "geometry": {"coordinates":[54.441333,28.721612],"type":"Point"}
}