{
  "type": "Feature",
  "properties": {
    "wof:name":"Heritage Heights",
    "wof:placetype":"neighbourhood"
},
  "geometry": {"coordinates":[-88.05005211709454,43.14098928449276],"type":"Point"}
}