{
  "type": "Feature",
  "properties": {
    "gn:admin1_code":"35.0",
    "gn:asciiname":"Otjiwarongo",
    "gn:dem":1211,
    "gn:feature_class":"P",
    "gn:feature_code":"PPL",
    "gn:name":"Otjiwarongo",
    "gn:population":0,
    "gn:timezone":"Africa/Windhoek",
    "name:afr_x_preferred":[
        "Otjiwarongo"
    ],
    "name:ara_x_preferred":[
        "\u0623\u0648\u062a\u062c\u064a\u0648\u0627\u0631\u0648\u0646\u063a\u0648"
    ],
    "name:bul_x_preferred":[
        "\u041e\u0447\u0438\u0432\u0430\u0440\u043e\u043d\u0433\u043e"
    ],
    "name:ceb_x_preferred":[
        "Otjiwarongo"
    ],
    "name:dan_x_preferred":[
        "Otjiwarongo"
    ],
    "name:deu_x_preferred":[
        "Otjiwarongo"
    ],
    "name:fra_x_preferred":[
        "Otjiwarongo"
    ],
    "name:frr_x_preferred":[
        "Otjiwarongo"
    ],
    "name:ita_x_preferred":[
        "Otjiwarongo"
    ],
    "name:lit_x_preferred":[
        "O\u010divarongas"
    ],
    "name:nld_x_preferred":[
        "Otjiwarongo"
    ],
    "name:pol_x_preferred":[
        "Otjiwarongo"
    ],
    "name:por_x_preferred":[
        "Otjiwarongo"
    ],
    "name:ron_x_preferred":[
        "Otjiwarongo"
    ],
    "name:rus_x_preferred":[
        "\u041e\u0447\u0438\u0432\u0430\u0440\u043e\u043d\u0433\u043e"
    ],
    "name:sna_x_preferred":[
        "Otjiwarongo"
    ],
    "name:spa_x_preferred":[
        "Otjiwarongo"
    ],
    "name:swa_x_preferred":[
        "Otjiwarongo"
    ],
    "name:swe_x_preferred":[
        "Otjiwarongo"
    ],
    "name:tur_x_preferred":[
        "Otjiwarongo"
    ],
    "name:ukr_x_preferred":[
        "\u041e\u0447\u0438\u0432\u0430\u0440\u043e\u043d\u0433\u043e"
    ],
    "name:urd_x_preferred":[
        "\u0627\u0648\u062a\u062c\u06cc\u0648\u0627\u0631\u0648\u0646\u06af\u0648"
    ],
    "name:zho_x_preferred":[
        "\u5967\u5947\u74e6\u9f8d\u6208"
    ],
    "wof:name":"Otjiwarongo",
    "wof:placetype":"locality"
},
  "geometry": {"coordinates":[19.56667,-23.81667],"type":"Point"}
}