{
  "type": "Feature",
  "properties": {
    "wof:name":"Lakeside Preserve",
    "wof:placetype":"neighbourhood"
},
  "geometry": {"coordinates":[-84.52658014296044,33.65100867599696],"type":"Point"}
}