{
  "type": "Feature",
  "properties": {
    "name:ceb_x_preferred":[
        "Hoskins Airport"
    ],
    "name:eng_x_preferred":[
        "Hoskins Airport"
    ],
    "name:eng_x_variant":[
        "HKN",
        "AYHK"
    ],
    "name:fas_x_preferred":[
        "\u0641\u0631\u0648\u062f\u06af\u0627\u0647 \u0647\u0633\u06a9\u06cc\u0646\u0633"
    ],
    "name:ind_x_preferred":[
        "Bandar Udara Hoskins"
    ],
    "name:jpn_x_preferred":[
        "\u30db\u30b9\u30ad\u30f3\u30ba\u7a7a\u6e2f"
    ],
    "name:msa_x_preferred":[
        "Lapangan Terbang Hoskins"
    ],
    "name:pol_x_preferred":[
        "Port lotniczy Hoskins"
    ],
    "name:ron_x_preferred":[
        "Aeroportul Hoskins"
    ],
    "name:tgk_x_preferred":[
        "\u0424\u0443\u0440\u0443\u0434\u0433\u043e\u04b3\u0438 \u04b3\u0441\u043a\u0438\u043d\u0441"
    ],
    "name:zho_x_preferred":[
        "\u970d\u65af\u91d1\u65af\u6a5f\u5834"
    ],
    "oa:elevation_ft":"66",
    "oa:type":"medium_airport",
    "wd:wordcount":48,
    "woe:hierarchy":{
        "country_id":23424926,
        "planet_id":1,
        "state_id":2346597
    },
    "wof:name":"Hoskins Airport",
    "wof:placetype":"campus"
},
  "geometry": {"coordinates":[150.404999,-5.46217],"type":"Point"}
}