{
  "type": "Feature",
  "properties": {
    "wd:wordcount":1630,
    "wof:name":"Barrel District",
    "wof:placetype":"neighbourhood"
},
  "geometry": {"coordinates":[-112.18595426814039,33.5732779016246],"type":"Point"}
}