{
  "type": "Feature",
  "properties": {
    "name:ceb_x_preferred":[
        "Benito Salas Airport"
    ],
    "name:eng_x_preferred":[
        "Benito Salas Airport"
    ],
    "name:eng_x_variant":[
        "NVA",
        "SKNV"
    ],
    "name:fas_x_preferred":[
        "\u0641\u0631\u0648\u062f\u06af\u0627\u0647 \u0628\u0646\u06cc\u062a\u0648 \u0627\u0633\u0627\u0644\u0627"
    ],
    "name:fra_x_preferred":[
        "A\u00e9roport Benito Salas"
    ],
    "name:fra_x_variant":[
        "a\u00e9roport Benito Salas"
    ],
    "name:jpn_x_preferred":[
        "\u30d9\u30cb\u30fc\u30c8\u30fb\u30b5\u30e9\u30b9\u7a7a\u6e2f"
    ],
    "name:msa_x_preferred":[
        "Lapangan Terbang Benito Salas"
    ],
    "name:nld_x_preferred":[
        "Luchthaven Benito Salas"
    ],
    "name:pol_x_preferred":[
        "Port lotniczy Benito Salas"
    ],
    "name:por_x_preferred":[
        "Aeroporto Benito Salas"
    ],
    "name:ron_x_preferred":[
        "Aeroportul Benito Salas"
    ],
    "name:rus_x_preferred":[
        "\u0410\u044d\u0440\u043e\u043f\u043e\u0440\u0442 \u0438\u043c\u0435\u043d\u0438 \u0411\u0435\u043d\u0438\u0442\u043e \u0421\u0430\u043b\u0430\u0441\u0430"
    ],
    "name:spa_x_preferred":[
        "Aeropuerto Benito Salas"
    ],
    "name:swe_x_preferred":[
        "Benito Salas Airport"
    ],
    "name:tgk_x_preferred":[
        "\u0424\u0443\u0440\u0443\u0434\u0433\u043e\u04b3\u0438 \u0431\u043d\u0438\u0442\u0443 \u043e\u0441\u043e\u043b\u043e"
    ],
    "name:vie_x_preferred":[
        "S\u00e2n bay Benito Salas"
    ],
    "oa:elevation_ft":"1464",
    "oa:type":"medium_airport",
    "woe:hierarchy":{
        "country_id":23424787,
        "county_id":26797182,
        "planet_id":1,
        "state_id":2345061
    },
    "wof:name":"Neiva Lamarguita Airport",
    "wof:placetype":"campus"
},
  "geometry": {"coordinates":[-75.294,2.95015],"type":"Point"}
}