{
  "type": "Feature",
  "properties": {
    "name:ara_x_preferred":[
        "\u0645\u0637\u0627\u0631 \u0631\u064a\u0627\u0644 \u0635\u064a\u062f\u0627\u062f \u0627\u0644\u0645\u0631\u0643\u0632\u064a"
    ],
    "name:cat_x_preferred":[
        "Aeroport de Ciudad Real"
    ],
    "name:ceb_x_preferred":[
        "Ciudad Real Central Airport"
    ],
    "name:deu_x_preferred":[
        "Flughafen Ciudad Real"
    ],
    "name:eng_x_preferred":[
        "Ciudad Real Central Airport"
    ],
    "name:eng_x_variant":[
        "CQM",
        "LERL"
    ],
    "name:est_x_preferred":[
        "Ciudad Reali Kesklennujaam"
    ],
    "name:eus_x_preferred":[
        "Ciudad Realgo aireportua"
    ],
    "name:fas_x_preferred":[
        "\u0641\u0631\u0648\u062f\u06af\u0627\u0647 \u0633\u06cc\u0648\u062f\u0627\u062f \u0631\u06cc\u0644 \u0633\u0646\u062a\u0631\u0627\u0644"
    ],
    "name:fin_x_preferred":[
        "Ciudad Realin lentoasema"
    ],
    "name:fra_x_preferred":[
        "a\u00e9roport Central-Ciudad Real"
    ],
    "name:glg_x_preferred":[
        "Aeroporto de Cidade Real"
    ],
    "name:hun_x_preferred":[
        "Ciudad Real rep\u00fcl\u0151t\u00e9r"
    ],
    "name:ita_x_preferred":[
        "Aeroporto di Ciudad Real"
    ],
    "name:jpn_x_preferred":[
        "\u30b7\u30a6\u30c0\u30fb\u30ec\u30a2\u30eb\u30fb\u30bb\u30f3\u30c8\u30e9\u30eb\u7a7a\u6e2f"
    ],
    "name:kor_x_preferred":[
        "\uc2dc\uc6b0\ub2e4\ub4dc\ub808\uc54c \uc13c\ud2b8\ub784 \uacf5\ud56d"
    ],
    "name:nld_x_preferred":[
        "Ciudad Real Central Airport"
    ],
    "name:pol_x_preferred":[
        "Port lotniczy Ciudad Real"
    ],
    "name:ron_x_preferred":[
        "Aeroportul Ciudad Real Central"
    ],
    "name:spa_x_preferred":[
        "Aeropuerto de Ciudad Real"
    ],
    "name:swe_x_preferred":[
        "Ciudad Reals flygplats"
    ],
    "name:tgk_x_preferred":[
        "\u0424\u0443\u0440\u0443\u0434\u0433\u043e\u04b3\u0438 \u0441\u044e\u0434\u043e\u0434 \u0440\u0438\u043b \u0441\u043d\u0442\u0440\u043e\u043b"
    ],
    "name:tur_x_preferred":[
        "Ciudad Real Havaliman\u0131"
    ],
    "name:vie_x_preferred":[
        "S\u00e2n bay Donquijote"
    ],
    "name:zho_x_preferred":[
        "\u96f7\u963f\u723e\u57ce\u4e2d\u592e\u6a5f\u5834"
    ],
    "oa:type":"closed",
    "woe:hierarchy":{
        "country_id":23424977,
        "county_id":12588868,
        "planet_id":1,
        "state_id":2347582
    },
    "wof:name":"Cook Municipal Airport",
    "wof:placetype":"campus"
},
  "geometry": {"coordinates":[-3.97,38.856389],"type":"Point"}
}