{
  "type": "Feature",
  "properties": {
    "gn:admin1_code":"32.0",
    "gn:asciiname":"Anixab",
    "gn:dem":568,
    "gn:feature_class":"P",
    "gn:feature_code":"PPL",
    "gn:name":"Anixab",
    "gn:population":0,
    "gn:timezone":"Africa/Windhoek",
    "wof:name":"Anixab",
    "wof:placetype":"locality"
},
  "geometry": {"coordinates":[14.85,-20.93333],"type":"Point"}
}