{
  "type": "Feature",
  "properties": {
    "name:ceb_x_preferred":[
        "Narrabri Airport"
    ],
    "name:deu_x_preferred":[
        "Narrabri Airport"
    ],
    "name:eng_x_preferred":[
        "Narrabri Airport"
    ],
    "name:eng_x_variant":[
        "NAA",
        "YNBR"
    ],
    "name:fas_x_preferred":[
        "\u0641\u0631\u0648\u062f\u06af\u0627\u0647 \u0646\u0627\u0631\u0631\u0627\u0628\u0631\u06cc"
    ],
    "name:jpn_x_preferred":[
        "\u30ca\u30e9\u30d6\u30ea\u7a7a\u6e2f"
    ],
    "name:msa_x_preferred":[
        "Lapangan Terbang Narrabri"
    ],
    "name:ron_x_preferred":[
        "Aeroportul Narrabri"
    ],
    "name:spa_x_preferred":[
        "Narrabri"
    ],
    "name:swe_x_preferred":[
        "Narrabri Airport"
    ],
    "name:tgk_x_preferred":[
        "\u0424\u0443\u0440\u0443\u0434\u0433\u043e\u04b3\u0438 \u043d\u043e\u0440\u0440\u043e\u0431\u0440\u0438"
    ],
    "oa:elevation_ft":"788",
    "oa:type":"medium_airport",
    "wd:wordcount":55,
    "woe:hierarchy":{
        "country_id":23424748,
        "county_id":55863796,
        "planet_id":1,
        "state_id":2344700
    },
    "wof:name":"Narrabri Airport",
    "wof:placetype":"campus"
},
  "geometry": {"coordinates":[149.82722200000001,-30.319167],"type":"Point"}
}