{
  "type": "Feature",
  "properties": {
    "name:eng_x_preferred":[
        "South Tampa"
    ],
    "name:fra_x_preferred":[
        "South Tampa"
    ],
    "wd:wordcount":203,
    "wof:name":"South Tampa",
    "wof:placetype":"neighbourhood"
},
  "geometry": {"coordinates":[-82.50928822888663,27.92051908977686],"type":"Point"}
}