{
  "type": "Feature",
  "properties": {
    "name:azb_x_preferred":[
        "\u0633\u0648\u062a \u062a\u0627\u0645\u067e\u0627"
    ],
    "name:eng_x_preferred":[
        "South Tampa"
    ],
    "name:fra_x_preferred":[
        "South Tampa"
    ],
    "name:nld_x_preferred":[
        "South Tampa"
    ],
    "wd:wordcount":203,
    "wof:name":"South Tampa",
    "wof:placetype":"neighbourhood"
},
  "geometry": {"coordinates":[-82.509288,27.920519],"type":"Point"}
}