{
  "type": "Feature",
  "properties": {
    "name:ceb_x_preferred":[
        "West End Airport"
    ],
    "name:eng_x_preferred":[
        "West End Airport"
    ],
    "name:eng_x_variant":[
        "WTD",
        "MYGW"
    ],
    "name:fas_x_preferred":[
        "\u0641\u0631\u0648\u062f\u06af\u0627\u0647 \u0648\u0633\u062a \u0627\u0646\u062f"
    ],
    "name:jpn_x_preferred":[
        "\u30a6\u30a8\u30b9\u30c8\u30fb\u30a8\u30f3\u30c9\u7a7a\u6e2f"
    ],
    "name:msa_x_preferred":[
        "Lapangan Terbang West End"
    ],
    "name:pol_x_preferred":[
        "Port lotniczy West End"
    ],
    "name:swe_x_preferred":[
        "West End Airport"
    ],
    "name:tgk_x_preferred":[
        "\u0424\u0443\u0440\u0443\u0434\u0433\u043e\u04b3\u0438 \u0432\u0438\u0441\u0442 \u04b3\u0430\u0441\u0442\u0430\u043d\u0434"
    ],
    "name:vie_x_preferred":[
        "S\u00e2n bay West End"
    ],
    "oa:elevation_ft":"5",
    "oa:type":"small_airport",
    "wd:wordcount":70,
    "woe:hierarchy":{
        "country_id":23424758,
        "planet_id":1,
        "state_id":24551257
    },
    "wof:name":"West End Airport",
    "wof:placetype":"campus"
},
  "geometry": {"coordinates":[-78.974998,26.685301],"type":"Point"}
}