{
  "type": "Feature",
  "properties": {
    "name:deu_x_preferred":[
        "Flugplatz Nordhorn-Lingen"
    ],
    "name:eng_x_preferred":[
        "Nordhorn-Lingen Airport"
    ],
    "name:msa_x_preferred":[
        "Lapangan Terbang Lingen"
    ],
    "name:nld_x_preferred":[
        "Vliegveld Nordhorn-Lingen"
    ],
    "oa:elevation_ft":"89",
    "oa:type":"small_airport",
    "woe:hierarchy":{
        "country_id":23424829,
        "county_id":12596697,
        "localadmin_id":12629955,
        "planet_id":1,
        "state_id":2345486
    },
    "wof:name":"Nordhorn-Lingen Airport",
    "wof:placetype":"campus"
},
  "geometry": {"coordinates":[7.17583,52.4578],"type":"Point"}
}