{
  "type": "Feature",
  "properties": {
    "name:eng_x_preferred":[
        "Juan Mendoza Airport"
    ],
    "name:eng_x_variant":[
        "ORU",
        "SLOR"
    ],
    "name:fas_x_preferred":[
        "\u0641\u0631\u0648\u062f\u06af\u0627\u0647 \u062e\u0648\u0622\u0646 \u0645\u0646\u062f\u0648\u0633\u0627"
    ],
    "name:fra_x_preferred":[
        "a\u00e9roport international Juan Mendoza"
    ],
    "name:jpn_x_preferred":[
        "\u30db\u30a2\u30f3\u30fb\u30e1\u30f3\u30c9\u30fc\u30b6\u7a7a\u6e2f"
    ],
    "name:msa_x_preferred":[
        "Lapangan Terbang Juan Mendoza"
    ],
    "name:nld_x_preferred":[
        "Aeropuerto Juan Mendoza"
    ],
    "name:pol_x_preferred":[
        "Port lotniczy Juan Mendoza"
    ],
    "name:spa_x_preferred":[
        "Aeropuerto Juan Mendoza"
    ],
    "name:swe_x_preferred":[
        "Oruro Airport"
    ],
    "name:tgk_x_preferred":[
        "\u0424\u0443\u0440\u0443\u0434\u0433\u043e\u04b3\u0438 \u0445\u04ef\u043e\u043d \u043c\u043d\u0434\u0443\u0437\u043e"
    ],
    "oa:elevation_ft":"12152",
    "oa:type":"medium_airport",
    "woe:hierarchy":{
        "country_id":23424762,
        "county_id":55967852,
        "localadmin_id":55968135,
        "planet_id":1,
        "state_id":2344805
    },
    "wof:name":"Oruro Airport",
    "wof:placetype":"campus"
},
  "geometry": {"coordinates":[-67.07620199999999,-17.962601],"type":"Point"}
}