{
  "type": "Feature",
  "properties": {
    "name:ara_x_preferred":[
        "\u0645\u0637\u0627\u0631 \u062f\u0648\u0641\u064a\u0644 \u0646\u0648\u0631\u0645\u0627\u0646\u062f\u064a"
    ],
    "name:chi_x_preferred":[
        "\u591a\u7dad\u723e-\u8056\u52a0\u8482\u5b89\u6a5f\u5834"
    ],
    "name:deu_x_preferred":[
        "Flughafen Deauville"
    ],
    "name:dut_x_preferred":[
        "Deauville \u2013 Saint-Gatien Airport"
    ],
    "name:eng_x_preferred":[
        "Deauville \u2013 Saint-Gatien Airport"
    ],
    "name:eng_x_variant":[
        "DOL",
        "LFRG"
    ],
    "name:fas_x_preferred":[
        "\u0641\u0631\u0648\u062f\u06af\u0627\u0647 \u062f\u0648\u0648\u06cc\u0644 \u0633\u0646\u062a-\u06af\u06cc\u0634\u0646"
    ],
    "name:fra_x_preferred":[
        "A\u00e9roport de Deauville - Normandie"
    ],
    "name:fre_x_preferred":[
        "a\u00e9roport de Deauville - Normandie"
    ],
    "name:ger_x_preferred":[
        "Flughafen Deauville"
    ],
    "name:ind_x_preferred":[
        "Bandar Udara Deauville - Saint-Gatien"
    ],
    "name:ita_x_preferred":[
        "Aeroporto di Deauville Saint-Gatien"
    ],
    "name:may_x_preferred":[
        "Lapangan Terbang St Gatien"
    ],
    "name:per_x_preferred":[
        "\u0641\u0631\u0648\u062f\u06af\u0627\u0647 \u062f\u0648\u0648\u06cc\u0644 \u0633\u0646\u062a-\u06af\u06cc\u0634\u0646"
    ],
    "name:pol_x_preferred":[
        "Port lotniczy Deauville"
    ],
    "name:tgk_x_preferred":[
        "\u0424\u0443\u0440\u0443\u0434\u0433\u043e\u04b3\u0438 \u0434\u0443\u0432\u0438\u043b \u0441\u0443\u043d\u043d\u0430\u0442-\u0433\u0438\u0448\u043d"
    ],
    "name:tur_x_preferred":[
        "Deauville - Saint-Gatien Havaliman\u0131"
    ],
    "name:vie_x_preferred":[
        "S\u00e2n bay Deauville - Saint-Gatien"
    ],
    "oa:elevation_ft":"479",
    "oa:type":"medium_airport",
    "woe:hierarchy":{
        "country_id":23424819,
        "county_id":12597127,
        "localadmin_id":12652472,
        "planet_id":1,
        "state_id":7153311
    },
    "wof:name":"A\u00e9roport de Deauville Saint-G\u00e2tien",
    "wof:placetype":"campus"
},
  "geometry": {"coordinates":[0.154306,49.365299],"type":"Point"}
}