{
  "type": "Feature",
  "properties": {
    "gn:admin1_code":"39.0",
    "gn:asciiname":"Okaokongwinya",
    "gn:dem":1774,
    "gn:feature_class":"P",
    "gn:feature_code":"PPL",
    "gn:name":"Okaokongwinya",
    "gn:population":0,
    "gn:timezone":"Africa/Windhoek",
    "wof:name":"Okaokongwinya",
    "wof:placetype":"locality"
},
  "geometry": {"coordinates":[17.16667,-22.13333],"type":"Point"}
}