{
  "type": "Feature",
  "properties": {
    "name:eng_x_preferred":[
        "Tzaneen Airport"
    ],
    "name:msa_x_preferred":[
        "Lapangan Terbang Tzaneen"
    ],
    "name:ron_x_preferred":[
        "Aeroportul Tzaneen"
    ],
    "oa:elevation_ft":"1914",
    "oa:type":"medium_airport",
    "woe:hierarchy":{
        "country_id":23424942,
        "county_id":56189406,
        "localadmin_id":56189559,
        "planet_id":1,
        "state_id":2346986
    },
    "wof:name":"Tzaneen Airport",
    "wof:placetype":"campus"
},
  "geometry": {"coordinates":[30.329307,-23.824417],"type":"Point"}
}