{
  "type": "Feature",
  "properties": {
    "name:ceb_x_preferred":[
        "Cherbourg \u2013 Maupertus Airport"
    ],
    "name:deu_x_preferred":[
        "Flughafen Cherbourg-Maupertus"
    ],
    "name:eng_x_preferred":[
        "Cherbourg \u2013 Maupertus Airport"
    ],
    "name:eng_x_variant":[
        "CER",
        "LFRC"
    ],
    "name:fas_x_preferred":[
        "\u0641\u0631\u0648\u062f\u06af\u0627\u0647 \u0634\u0631\u0628\u0648\u0631-\u0645\u0648\u067e\u0631\u062a\u0648"
    ],
    "name:fas_x_variant":[
        "\u0641\u0631\u0648\u062f\u06af\u0627\u0647 \u0634\u0631\u0628\u0648\u0631\u06af \u0645\u0627\u0648\u067e\u0631\u062a\u0648\u0633"
    ],
    "name:fra_x_preferred":[
        "A\u00e9roport de Cherbourg - Maupertus"
    ],
    "name:fra_x_variant":[
        "a\u00e9roport de Cherbourg - Maupertus"
    ],
    "name:hun_x_preferred":[
        "Cherbourg-Maupertus rep\u00fcl\u0151t\u00e9r"
    ],
    "name:msa_x_preferred":[
        "Lapangan Terbang Maupertus"
    ],
    "name:nld_x_preferred":[
        "A\u00e9roport de Cherbourg-Maupertus"
    ],
    "name:nld_x_variant":[
        "Luchthaven Cherbourg-Maupertus"
    ],
    "name:pol_x_preferred":[
        "Port lotniczy Cherbourg-Maupertus"
    ],
    "name:tgk_x_preferred":[
        "\u0424\u0443\u0440\u0443\u0434\u0433\u043e\u04b3\u0438 \u0448\u0440\u0431\u0443\u0440\u0433 \u043c\u043e\u0432\u043f\u0440\u0442\u0443\u0441"
    ],
    "name:zho_x_preferred":[
        "\u745f\u5821-\u83ab\u4f69\u723e\u8482\u6a5f\u5834"
    ],
    "name:zho_x_variant":[
        "Ceyzeriat Airport"
    ],
    "oa:elevation_ft":"459",
    "oa:type":"medium_airport",
    "woe:hierarchy":{
        "country_id":23424819,
        "county_id":12591801,
        "localadmin_id":12648924,
        "planet_id":1,
        "state_id":7153311
    },
    "wof:name":"A\u00e9roport de Cherbourg Maupertus",
    "wof:placetype":"campus"
},
  "geometry": {"coordinates":[-1.47028,49.650101],"type":"Point"}
}