{
  "type": "Feature",
  "properties": {
    "name:eng_x_preferred":[
        "Francisco de Orellana Airport"
    ],
    "name:eng_x_variant":[
        "OCC",
        "SECO"
    ],
    "name:fas_x_preferred":[
        "\u0641\u0631\u0648\u062f\u06af\u0627\u0647 \u06a9\u0648\u06a9\u0627\u06a9\u0648\u0644\u0627"
    ],
    "name:fas_x_variant":[
        "\u0641\u0631\u0648\u062f\u06af\u0627\u0647 \u0641\u0631\u0646\u0633\u06cc\u0633\u06a9\u0648 \u062f \u0627\u0648\u0631\u06cc\u0627\u0646\u0627"
    ],
    "name:fra_x_preferred":[
        "a\u00e9roport Francisco de Orellana de Coca"
    ],
    "name:heb_x_preferred":[
        "\u05e4\u05e8\u05e0\u05e1\u05d9\u05e1\u05e7\u05d5 \u05d3\u05d4 \u05d0\u05d5\u05e8\u05dc\u05e0\u05d4"
    ],
    "name:jpn_x_preferred":[
        "\u30b3\u30ab"
    ],
    "name:msa_x_preferred":[
        "Lapangan Terbang Francisco De Orellana"
    ],
    "name:pol_x_preferred":[
        "Port lotniczy Francisco de Orellana"
    ],
    "name:spa_x_preferred":[
        "Aeropuerto Francisco de Orellana"
    ],
    "name:swe_x_preferred":[
        "Francisco De Orellana Airport"
    ],
    "name:tgk_x_preferred":[
        "\u0424\u0443\u0440\u0443\u0434\u0433\u043e\u04b3\u0438 \u043a\u0443\u043a\u043e\u043a\u0443\u043b\u043e"
    ],
    "name:vie_x_preferred":[
        "S\u00e2n bay Francisco de Orellana"
    ],
    "oa:elevation_ft":"834",
    "oa:type":"medium_airport",
    "wd:wordcount":66,
    "woe:hierarchy":{
        "country_id":23424801,
        "county_id":26809525,
        "localadmin_id":26810319,
        "planet_id":1,
        "state_id":20070099
    },
    "wof:name":"Coca Airport",
    "wof:placetype":"campus"
},
  "geometry": {"coordinates":[-76.986801,-0.462886],"type":"Point"}
}