{
  "type": "Feature",
  "properties": {
    "name:eng_x_preferred":[
        "Birch Creek Airport"
    ],
    "name:eng_x_variant":[
        "KBC",
        "Z91"
    ],
    "name:fas_x_preferred":[
        "\u0641\u0631\u0648\u062f\u06af\u0627\u0647 \u0628\u06cc\u0631\u0686 \u06a9\u0631\u06cc\u06a9"
    ],
    "name:per_x_preferred":[
        "\u0641\u0631\u0648\u062f\u06af\u0627\u0647 \u0628\u06cc\u0631\u0686 \u06a9\u0631\u06cc\u06a9"
    ],
    "name:rus_x_preferred":[
        "\u0411\u0435\u0440\u0447-\u041a\u0440\u0438\u043a"
    ],
    "name:tgk_x_preferred":[
        "\u0424\u0443\u0440\u0443\u0434\u0433\u043e\u04b3\u0438 \u0411\u0438\u0440\u0447 \u041a\u0440\u0438\u043a"
    ],
    "oa:elevation_ft":"450",
    "oa:type":"small_airport",
    "wd:wordcount":182,
    "woe:hierarchy":{
        "country_id":23424977,
        "county_id":12590538,
        "planet_id":1,
        "state_id":2347608
    },
    "wof:name":"Birch Creek Airport",
    "wof:placetype":"campus"
},
  "geometry": {"coordinates":[-145.824005,66.274002],"type":"Point"}
}