{
  "type": "Feature",
  "properties": {
    "name:eng_x_variant":[
        "OUK",
        "GB-OUK"
    ],
    "oa:elevation_ft":"76",
    "oa:type":"medium_airport",
    "woe:hierarchy":{
        "country_id":23424975,
        "county_id":12602206,
        "localadmin_id":12696208,
        "planet_id":1,
        "state_id":12578048
    },
    "wof:name":"Outer Skerries Airport",
    "wof:placetype":"campus"
},
  "geometry": {"coordinates":[-0.75,60.4252],"type":"Point"}
}