{
  "type": "Feature",
  "properties": {
    "name:ceb_x_preferred":[
        "Sheep Mountain"
    ],
    "name:swe_x_preferred":[
        "Sheep Mountain"
    ],
    "wd:wordcount":185,
    "wof:name":"Sheep Mountain",
    "wof:placetype":"neighbourhood"
},
  "geometry": {"coordinates":[-115.22096603036601,36.31091569213901],"type":"Point"}
}