{
  "type": "Feature",
  "properties": {
    "name:ceb_x_preferred":[
        "Hastings Airport"
    ],
    "name:deu_x_preferred":[
        "Flughafen Hastings"
    ],
    "name:eng_x_preferred":[
        "Hastings Airport"
    ],
    "name:eng_x_variant":[
        "HGS",
        "GFHA"
    ],
    "name:fas_x_preferred":[
        "\u0641\u0631\u0648\u062f\u06af\u0627\u0647 \u0647\u0627\u0633\u062a\u06cc\u0646\u06af\u0632"
    ],
    "name:jpn_x_preferred":[
        "\u30d8\u30a4\u30b9\u30c6\u30a3\u30f3\u30b0\u30ba\u7a7a\u6e2f"
    ],
    "name:msa_x_preferred":[
        "Lapangan Terbang Hastings"
    ],
    "name:pol_x_preferred":[
        "Port lotniczy Hastings"
    ],
    "name:ron_x_preferred":[
        "Aeroportul Hastings"
    ],
    "name:tgk_x_preferred":[
        "\u0424\u0443\u0440\u0443\u0434\u0433\u043e\u04b3\u0438 \u04b3\u043e\u0441\u0442\u0438\u043d\u0433\u0437"
    ],
    "oa:elevation_ft":"60",
    "oa:type":"small_airport",
    "wd:wordcount":37,
    "woe:hierarchy":{
        "country_id":23424946,
        "planet_id":1,
        "state_id":2347003
    },
    "wof:name":"Hastings Airport",
    "wof:placetype":"campus"
},
  "geometry": {"coordinates":[-13.1291,8.39713],"type":"Point"}
}