{
  "type": "Feature",
  "properties": {
    "wof:name":"H\u014dmai",
    "wof:placetype":"neighbourhood"
},
  "geometry": {"coordinates":[174.8754688529786,-37.01612447558723],"type":"Point"}
}