{
  "type": "Feature",
  "properties": {
    "name:ceb_x_preferred":[
        "Morondava Airport"
    ],
    "name:eng_x_preferred":[
        "Morondava Airport"
    ],
    "name:eng_x_variant":[
        "MOQ",
        "FMMV"
    ],
    "name:fra_x_preferred":[
        "A\u00e9rodrome de Morondava"
    ],
    "name:ita_x_preferred":[
        "Aeroporto di Morondava"
    ],
    "name:jpn_x_preferred":[
        "\u30e2\u30ed\u30f3\u30c0\u30d0\u7a7a\u6e2f"
    ],
    "name:lit_x_preferred":[
        "Morondavos oro uostas"
    ],
    "name:msa_x_preferred":[
        "Lapangan Terbang Morondava"
    ],
    "name:nld_x_preferred":[
        "Morondava Airport"
    ],
    "name:pol_x_preferred":[
        "Port lotniczy Morondava"
    ],
    "name:ron_x_preferred":[
        "Aeroportul Morondava"
    ],
    "name:swe_x_preferred":[
        "Morondava Airport"
    ],
    "name:vie_x_preferred":[
        "S\u00e2n bay Morondava"
    ],
    "name:zho_x_preferred":[
        "\u83ab\u502b\u9054\u74e6\u6a5f\u5834"
    ],
    "oa:elevation_ft":"30",
    "oa:type":"medium_airport",
    "wd:wordcount":54,
    "woe:hierarchy":{
        "country_id":23424883,
        "county_id":23706616,
        "planet_id":1,
        "state_id":2346151
    },
    "wof:name":"Morondava Airport",
    "wof:placetype":"campus"
},
  "geometry": {"coordinates":[44.3174,-20.2848],"type":"Point"}
}