{
  "type": "Feature",
  "properties": {
    "name:eng_x_preferred":[
        "Alberto Carnevalli Airport"
    ],
    "name:eng_x_variant":[
        "MRD",
        "SVMD"
    ],
    "name:fra_x_preferred":[
        "A\u00e9roport Alberto-Carnevalli"
    ],
    "name:fra_x_variant":[
        "a\u00e9roport Alberto-Carnevalli"
    ],
    "name:ita_x_preferred":[
        "Aeroporto di Merida - Alberto Carnevalli"
    ],
    "name:jpn_x_preferred":[
        "\u30a2\u30eb\u30d9\u30eb\u30c8\u30fb\u30ab\u30eb\u30cd\u30d0\u30ea\u7a7a\u6e2f"
    ],
    "name:msa_x_preferred":[
        "Lapangan Terbang Alberto Carnevalli"
    ],
    "name:nld_x_preferred":[
        "Alberto Carnevalli Airport"
    ],
    "name:pol_x_preferred":[
        "Port lotniczy Alberto Carnevalli"
    ],
    "name:por_x_preferred":[
        "Aeroporto Alberto Carnevalli"
    ],
    "name:spa_x_preferred":[
        "Aeropuerto Alberto Carnevalli"
    ],
    "name:vie_x_preferred":[
        "S\u00e2n bay Alberto Carnevalli"
    ],
    "name:zho_x_preferred":[
        "\u963f\u723e\u8c9d\u6258\u5361\u723e\u5167\u74e6\u5229\u6a5f\u5834"
    ],
    "oa:elevation_ft":"5007",
    "oa:type":"medium_airport",
    "wd:wordcount":148,
    "woe:hierarchy":{
        "country_id":23424982,
        "county_id":26804724,
        "localadmin_id":26805282,
        "planet_id":1,
        "state_id":2347690
    },
    "wof:name":"Alberto Carnevalli Airport",
    "wof:placetype":"campus"
},
  "geometry": {"coordinates":[-71.161041,8.582078],"type":"Point"}
}