{
  "type": "Feature",
  "properties": {
    "name:ceb_x_preferred":[
        "Grande Prairie Airport"
    ],
    "name:eng_x_preferred":[
        "Grande Prairie Airport"
    ],
    "name:eng_x_variant":[
        "YQU",
        "CYQU"
    ],
    "name:fas_x_preferred":[
        "\u0641\u0631\u0648\u062f\u06af\u0627\u0647 \u06af\u0631\u0646\u062f\u0647 \u067e\u0631\u06cc\u0631\u06cc"
    ],
    "name:ind_x_preferred":[
        "Bandar Udara Grande Prairie"
    ],
    "name:msa_x_preferred":[
        "Lapangan Terbang Grande Prairie"
    ],
    "name:pms_x_preferred":[
        "Grande Prairie Airport"
    ],
    "name:ron_x_preferred":[
        "Aeroportul Grande Prairie"
    ],
    "name:spa_x_preferred":[
        "Aeropuerto de Grande Prairie"
    ],
    "name:swe_x_preferred":[
        "Grande Prairie Airport"
    ],
    "name:tgk_x_preferred":[
        "\u0424\u0443\u0440\u0443\u0434\u0433\u043e\u04b3\u0438 \u0433\u0440\u043d\u0434\u04b3 \u043f\u0440\u0438\u0440\u0438"
    ],
    "name:vie_x_preferred":[
        "S\u00e2n bay Grande Prairie"
    ],
    "oa:elevation_ft":"2195",
    "oa:type":"medium_airport",
    "wd:wordcount":460,
    "woe:hierarchy":{
        "country_id":23424775,
        "county_id":29375228,
        "planet_id":1,
        "state_id":2344915
    },
    "wof:name":"Grande Prairie Airport",
    "wof:placetype":"campus"
},
  "geometry": {"coordinates":[-118.88500000000001,55.18],"type":"Point"}
}