{
  "type": "Feature",
  "properties": {
    "name:ceb_x_preferred":[
        "Soroti Airport"
    ],
    "name:eng_x_preferred":[
        "Soroti Airport"
    ],
    "name:eng_x_variant":[
        "SRT",
        "HUSO"
    ],
    "name:fas_x_preferred":[
        "\u0641\u0631\u0648\u062f\u06af\u0627\u0647 \u0633\u0627\u0631\u0648\u062a\u06cc"
    ],
    "name:jpn_x_preferred":[
        "\u30bd\u30ed\u30c6\u30a3\u7a7a\u6e2f"
    ],
    "name:msa_x_preferred":[
        "Lapangan Terbang Soroti"
    ],
    "name:pol_x_preferred":[
        "Port lotniczy Soroti"
    ],
    "name:ron_x_preferred":[
        "Aeroportul Soroti"
    ],
    "name:tgk_x_preferred":[
        "\u0424\u0443\u0440\u0443\u0434\u0433\u043e\u04b3\u0438 \u0441\u043e\u0440\u0443\u0442\u0438"
    ],
    "oa:elevation_ft":"3697",
    "oa:type":"medium_airport",
    "wd:wordcount":431,
    "woe:hierarchy":{
        "country_id":23424974,
        "county_id":56190365,
        "planet_id":1,
        "state_id":20070447
    },
    "wof:name":"Soroti Airport",
    "wof:placetype":"campus"
},
  "geometry": {"coordinates":[33.622799,1.72769],"type":"Point"}
}