{
  "type": "Feature",
  "properties": {
    "name:ara_x_preferred":[
        "\u0645\u0637\u0627\u0631 \u062a\u0631\u064a\u0641\u064a\u0632\u0648"
    ],
    "name:cat_x_preferred":[
        "Aeroport de Treviso"
    ],
    "name:dan_x_preferred":[
        "Treviso Lufthavn"
    ],
    "name:deu_x_preferred":[
        "Flughafen Treviso"
    ],
    "name:eng_x_preferred":[
        "Treviso Airport"
    ],
    "name:eng_x_variant":[
        "TSF",
        "LIPH"
    ],
    "name:est_x_preferred":[
        "Treviso Sant'Angelo lennujaam"
    ],
    "name:fas_x_preferred":[
        "\u0641\u0631\u0648\u062f\u06af\u0627\u0647 \u062a\u0631\u0648\u06cc\u0632\u0648"
    ],
    "name:fra_x_preferred":[
        "a\u00e9roport de Tr\u00e9vise"
    ],
    "name:ita_x_preferred":[
        "Aeroporto di Treviso-Sant'Angelo"
    ],
    "name:jpn_x_preferred":[
        "\u30c8\u30ec\u30f4\u30a3\u30fc\u30be\u7a7a\u6e2f"
    ],
    "name:kor_x_preferred":[
        "\ud2b8\ub808\ube44\uc18c \uacf5\ud56d"
    ],
    "name:msa_x_preferred":[
        "Lapangan Terbang S.Angelo Mil"
    ],
    "name:nld_x_preferred":[
        "Luchthaven Veneti\u00eb-Treviso"
    ],
    "name:pol_x_preferred":[
        "Port lotniczy Treviso"
    ],
    "name:rus_x_preferred":[
        "\u0422\u0440\u0435\u0432\u0438\u0437\u043e"
    ],
    "name:spa_x_preferred":[
        "Aeropuerto de Sant'Angelo Treviso"
    ],
    "name:swe_x_preferred":[
        "Treviso flygplats"
    ],
    "name:tgk_x_preferred":[
        "\u0424\u0443\u0440\u0443\u0434\u0433\u043e\u04b3\u0438 \u0442\u0440\u0443\u0438\u0437\u0443"
    ],
    "name:ukr_x_preferred":[
        "\u0422\u0440\u0435\u0432\u0456\u0437\u043e"
    ],
    "name:vie_x_preferred":[
        "S\u00e2n bay Treviso"
    ],
    "name:zho_x_preferred":[
        "\u7279\u96f7\u7dad\u7d22"
    ],
    "oa:elevation_ft":"59",
    "oa:type":"large_airport",
    "woe:hierarchy":{
        "country_id":23424853,
        "county_id":12591811,
        "localadmin_id":12677513,
        "planet_id":1,
        "state_id":7153349
    },
    "wof:name":"Aeroporto di Treviso-Sant'angelo",
    "wof:placetype":"campus"
},
  "geometry": {"coordinates":[12.1944,45.648399],"type":"Point"}
}