{
  "type": "Feature",
  "properties": {
    "name:asm_x_preferred":[
        "\u09a4\u09c7\u099c\u09aa\u09c1\u09f0 \u09ac\u09bf\u09ae\u09be\u09a8\u09ac\u09a8\u09cd\u09a6\u09f0"
    ],
    "name:ben_x_preferred":[
        "\u09a4\u09c7\u099c\u09aa\u09c1\u09b0 \u09ac\u09bf\u09ae\u09be\u09a8\u09ac\u09a8\u09cd\u09a6\u09b0"
    ],
    "name:ceb_x_preferred":[
        "Tezpur Airport"
    ],
    "name:eng_x_preferred":[
        "Tezpur Airport"
    ],
    "name:fas_x_preferred":[
        "\u0641\u0631\u0648\u062f\u06af\u0627\u0647 \u062a\u0632\u067e\u0648\u0631"
    ],
    "name:hin_x_preferred":[
        "\u0924\u0947\u091c\u092a\u0941\u0930 \u0935\u093f\u092e\u093e\u0928\u0915\u094d\u0937\u0947\u0924\u094d\u0930"
    ],
    "name:jpn_x_preferred":[
        "\u30c6\u30ba\u30d7\u30eb\u7a7a\u6e2f"
    ],
    "name:mar_x_preferred":[
        "\u0924\u0947\u091c\u092a\u0942\u0930 \u0935\u093f\u092e\u093e\u0928\u0924\u0933"
    ],
    "name:mar_x_variant":[
        "\u0924\u0947\u091d\u092a\u0942\u0930 \u0935\u093f\u092e\u093e\u0928\u0924\u0933"
    ],
    "name:msa_x_preferred":[
        "Lapangan Terbang Tezpur"
    ],
    "name:ron_x_preferred":[
        "Aeroportul Tezpur"
    ],
    "name:swe_x_preferred":[
        "Tezpur Airport"
    ],
    "name:tgk_x_preferred":[
        "\u0424\u0443\u0440\u0443\u0434\u0433\u043e\u04b3\u0438 \u0442\u0437\u043f\u0443\u0440"
    ],
    "name:vie_x_preferred":[
        "S\u00e2n bay Tezpur"
    ],
    "name:zho_x_preferred":[
        "\u6cf0\u8332\u666e\u723e\u6a5f\u5834"
    ],
    "oa:elevation_ft":"240",
    "oa:type":"medium_airport",
    "wd:wordcount":179,
    "woe:hierarchy":{
        "country_id":23424848,
        "county_id":12586371,
        "planet_id":1,
        "state_id":2345741
    },
    "wof:name":"Tezpur Airport",
    "wof:placetype":"campus"
},
  "geometry": {"coordinates":[92.787222222222,26.712222222222],"type":"Point"}
}