{
  "type": "Feature",
  "properties": {
    "name:ceb_x_preferred":[
        "Prado Airport"
    ],
    "name:deu_x_preferred":[
        "Flughafen Prado"
    ],
    "name:eng_x_preferred":[
        "Prado Airport"
    ],
    "name:eng_x_variant":[
        "PDF",
        "SNRD"
    ],
    "name:msa_x_preferred":[
        "Lapangan Terbang Prado"
    ],
    "name:por_x_preferred":[
        "Aer\u00f3dromo Prado"
    ],
    "name:ron_x_preferred":[
        "Aeroportul Prado"
    ],
    "name:swe_x_preferred":[
        "Prado Airport"
    ],
    "oa:elevation_ft":"66",
    "oa:type":"small_airport",
    "woe:hierarchy":{
        "country_id":23424768,
        "county_id":12578541,
        "planet_id":1,
        "state_id":2344848
    },
    "wof:name":"Aeroporto Prado",
    "wof:placetype":"campus"
},
  "geometry": {"coordinates":[-39.271198,-17.2967],"type":"Point"}
}