{
  "type": "Feature",
  "properties": {
    "gn:admin1_code":"38.0",
    "gn:asciiname":"Oniiwe",
    "gn:dem":1103,
    "gn:feature_class":"P",
    "gn:feature_code":"PPL",
    "gn:name":"Oniiwe",
    "gn:population":0,
    "gn:timezone":"Africa/Windhoek",
    "wof:name":"Oniiwe",
    "wof:placetype":"locality"
},
  "geometry": {"coordinates":[16.26667,-17.93332999999999],"type":"Point"}
}