{
  "type": "Feature",
  "properties": {
    "name:deu_x_preferred":[
        "Flughafen Ciudad Victoria"
    ],
    "name:eng_x_preferred":[
        "General Pedro J. M\u00e9ndez International Airport"
    ],
    "name:eng_x_variant":[
        "CVM",
        "MMCV"
    ],
    "name:fas_x_preferred":[
        "\u0641\u0631\u0648\u062f\u06af\u0627\u0647 \u0628\u06cc\u0646\u200c\u0627\u0644\u0645\u0644\u0644\u06cc \u0698\u0646\u0631\u0627\u0644 \u067e\u062f\u0631\u0648 \u0645\u0646\u062f\u0632"
    ],
    "name:ind_x_preferred":[
        "Bandar Udara Internasional General Pedro J. M\u00e9ndez"
    ],
    "name:jpn_x_preferred":[
        "\u30b7\u30a6\u30c0\u30fc\u30c9\u30fb\u30d3\u30af\u30c8\u30ea\u30a2\u56fd\u969b\u7a7a\u6e2f"
    ],
    "name:msa_x_preferred":[
        "Lapangan Terbang Antarabangsa Gral Pedro Jose Mendez"
    ],
    "name:por_x_preferred":[
        "Aeroporto Internacional General Pedro Jos\u00e9 M\u00e9ndez"
    ],
    "name:ron_x_preferred":[
        "Aeroportul General Pedro J. M\u00e9ndez"
    ],
    "name:rus_x_preferred":[
        "\u0421\u044c\u044e\u0434\u0430\u0434-\u0412\u0438\u043a\u0442\u043e\u0440\u0438\u044f"
    ],
    "name:spa_x_preferred":[
        "Aeropuerto Internacional General Pedro Jos\u00e9 M\u00e9ndez"
    ],
    "name:tgk_x_preferred":[
        "\u0424\u0443\u0440\u0443\u0434\u0433\u043e\u04b3\u0438 \u0431\u0438\u043d\u200c\u0430\u043b\u043c\u0438\u043b\u0430\u043b\u04e3 \u0436\u0438\u043d\u0438\u0440\u043e\u043b \u043f\u0434\u0440\u0443 \u043c\u043d\u0434\u0437"
    ],
    "name:zho_x_preferred":[
        "Pedro J. M\u00e9ndez\u5c07\u8ecd\u570b\u969b\u6a5f\u5834"
    ],
    "oa:elevation_ft":"761",
    "oa:type":"medium_airport",
    "woe:hierarchy":{
        "country_id":23424900,
        "county_id":12601672,
        "planet_id":1,
        "state_id":2346291
    },
    "wof:name":"Ciudad Victoria Airport",
    "wof:placetype":"campus"
},
  "geometry": {"coordinates":[-98.956497,23.7033],"type":"Point"}
}