{
  "type": "Feature",
  "properties": {
    "name:deu_x_preferred":[
        "Flughafen Talara"
    ],
    "name:eng_x_preferred":[
        "Cap. FAP V\u00edctor Montes Arias Airport"
    ],
    "name:eng_x_variant":[
        "TYL",
        "SPYL"
    ],
    "name:fas_x_preferred":[
        "\u0641\u0631\u0648\u062f\u06af\u0627\u0647 \u06a9\u067e. \u0641\u0627\u067e \u0648\u06cc\u06a9\u062a\u0648\u0631 \u0645\u0627\u0646\u0632 \u0622\u0631\u06cc\u0627\u0632"
    ],
    "name:jpn_x_preferred":[
        "\u30ab\u30d4\u30bf\u30f3\u30fbFAP\u30fb\u30d3\u30af\u30c8\u30eb\u30fb\u30e2\u30f3\u30c6\u30b9\u30fb\u30a2\u30ea\u30a2\u30b9\u7a7a\u6e2f"
    ],
    "name:msa_x_preferred":[
        "Lapangan Terbang Capitan Montes"
    ],
    "name:pol_x_preferred":[
        "Port lotniczy Talara-Capitan FAP Victor Montes Arias"
    ],
    "name:por_x_preferred":[
        "Aeroporto Internacional Capit\u00e3o FAP Victor Montes Arias"
    ],
    "name:spa_x_preferred":[
        "Aeropuerto Internacional Capit\u00e1n FAP V\u00edctor Montes Arias"
    ],
    "name:tgk_x_preferred":[
        "\u0424\u0443\u0440\u0443\u0434\u0433\u043e\u04b3\u0438 \u043a\u043f. \u0444\u043e\u043f \u0432\u0435\u043a\u0442\u0443\u0440 \u043c\u043e\u043d\u0437 \u043e\u0440\u0438\u043e\u0437"
    ],
    "name:zho_x_preferred":[
        "\u5854\u62c9\u62c9"
    ],
    "oa:elevation_ft":"282",
    "oa:type":"medium_airport",
    "woe:hierarchy":{
        "country_id":23424919,
        "county_id":26805945,
        "planet_id":1,
        "state_id":2346487
    },
    "wof:name":"El Pato Airport",
    "wof:placetype":"campus"
},
  "geometry": {"coordinates":[-81.254097,-4.57664],"type":"Point"}
}