{
  "type": "Feature",
  "properties": {
    "gn:admin1_code":"21.0",
    "gn:asciiname":"Lichtenstein Mitte",
    "gn:dem":1964,
    "gn:feature_class":"P",
    "gn:feature_code":"PPL",
    "gn:name":"Lichtenstein Mitte",
    "gn:population":0,
    "gn:timezone":"Africa/Windhoek",
    "wof:name":"Lichtenstein Mitte",
    "wof:placetype":"locality"
},
  "geometry": {"coordinates":[16.96667,-22.78333],"type":"Point"}
}