{
  "type": "Feature",
  "properties": {
    "name:ceb_x_preferred":[
        "Utti Airport"
    ],
    "name:eng_x_preferred":[
        "Utti Airport"
    ],
    "name:eng_x_variant":[
        "UTI",
        "EFUT"
    ],
    "name:fas_x_preferred":[
        "\u0641\u0631\u0648\u062f\u06af\u0627\u0647 \u0627\u0648\u062a\u06cc"
    ],
    "name:fin_x_preferred":[
        "Utin lentoasema"
    ],
    "name:fra_x_preferred":[
        "base a\u00e9rienne d'Utti"
    ],
    "name:msa_x_preferred":[
        "Lapangan Terbang Utti AB"
    ],
    "name:nob_x_preferred":[
        "Utti lufthavn"
    ],
    "name:pol_x_preferred":[
        "Port lotniczy Kouvola"
    ],
    "name:rus_x_preferred":[
        "\u0423\u0442\u0442\u0438"
    ],
    "name:swe_x_preferred":[
        "Utti Airport"
    ],
    "name:tgk_x_preferred":[
        "\u0424\u0443\u0440\u0443\u0434\u0433\u043e\u04b3\u0438 \u0430\u0432\u0433\u0443\u0441\u0442\u0435"
    ],
    "name:zho_x_preferred":[
        "\u4e4c\u8482\u673a\u573a"
    ],
    "oa:elevation_ft":"339",
    "oa:type":"medium_airport",
    "woe:hierarchy":{
        "country_id":23424812,
        "county_id":56120863,
        "localadmin_id":12590761,
        "planet_id":1,
        "state_id":29389254
    },
    "wof:name":"Utti lentokentt\u00e4",
    "wof:placetype":"campus"
},
  "geometry": {"coordinates":[26.9384,60.8964],"type":"Point"}
}