{
  "type": "Feature",
  "properties": {
    "name:bar_x_preferred":[
        "Hillside"
    ],
    "name:ceb_x_preferred":[
        "Hillside"
    ],
    "name:cym_x_preferred":[
        "Hillside"
    ],
    "name:deu_x_preferred":[
        "Hillside"
    ],
    "name:ita_x_preferred":[
        "Hillside"
    ],
    "name:mlg_x_preferred":[
        "Hillside"
    ],
    "name:nld_x_preferred":[
        "Hillside"
    ],
    "name:pol_x_preferred":[
        "Hillside"
    ],
    "name:por_x_preferred":[
        "Hillside"
    ],
    "name:srp_x_preferred":[
        "\u0425\u0438\u043b\u0441\u0430\u0458\u0434"
    ],
    "name:swe_x_preferred":[
        "Hillside"
    ],
    "name:ukr_x_preferred":[
        "\u0413\u0456\u043b\u043b\u0441\u0430\u0439\u0434"
    ],
    "name:vol_x_preferred":[
        "Hillside"
    ],
    "wd:wordcount":191,
    "wof:name":"Hillside",
    "wof:placetype":"neighbourhood"
},
  "geometry": {"coordinates":[-87.92213571667355,43.05301670372273],"type":"Point"}
}