{
  "type": "Feature",
  "properties": {
    "wd:wordcount":191,
    "wof:name":"Hillside",
    "wof:placetype":"neighbourhood"
},
  "geometry": {"coordinates":[-87.92213571667355,43.05301670372273],"type":"Point"}
}