{
  "type": "Feature",
  "properties": {
    "wof:name":"Schoolcraft-196",
    "wof:placetype":"neighbourhood"
},
  "geometry": {"coordinates":[-83.21118380764946,42.38360851330381],"type":"Point"}
}