{
  "type": "Feature",
  "properties": {
    "name:eng_x_preferred":[
        "Penza Airport"
    ],
    "name:eng_x_variant":[
        "PEZ",
        "UWPP"
    ],
    "name:fas_x_preferred":[
        "\u0641\u0631\u0648\u062f\u06af\u0627\u0647 \u067e\u0646\u0632\u0627"
    ],
    "name:ita_x_preferred":[
        "Aeroporto di Penza"
    ],
    "name:jpn_x_preferred":[
        "\u30da\u30f3\u30b6\u7a7a\u6e2f"
    ],
    "name:nld_x_preferred":[
        "Penza"
    ],
    "name:nno_x_preferred":[
        "Penza lufthamn"
    ],
    "name:nob_x_preferred":[
        "Penza lufthavn"
    ],
    "name:pol_x_preferred":[
        "Port lotniczy Penza"
    ],
    "name:rus_x_preferred":[
        "\u041f\u0435\u043d\u0437\u0430"
    ],
    "name:spa_x_preferred":[
        "Aeropuerto de Penza"
    ],
    "name:tur_x_preferred":[
        "Penza Havaliman\u0131"
    ],
    "name:vie_x_preferred":[
        "S\u00e2n bay Penza"
    ],
    "oa:elevation_ft":"614",
    "oa:type":"medium_airport",
    "woe:hierarchy":{
        "country_id":23424977,
        "county_id":12590013,
        "planet_id":1,
        "state_id":2347602
    },
    "wof:name":"Pleasanton Municipal Airport",
    "wof:placetype":"campus"
},
  "geometry": {"coordinates":[45.021099,53.1106],"type":"Point"}
}