{
  "type": "Feature",
  "properties": {
    "name:ceb_x_preferred":[
        "Resende Airport"
    ],
    "name:deu_x_preferred":[
        "Flughafen Resende"
    ],
    "name:eng_x_preferred":[
        "Resende Airport"
    ],
    "name:eng_x_variant":[
        "REZ",
        "SDRS"
    ],
    "name:jpn_x_preferred":[
        "\u30ec\u30bc\u30f3\u30b8\u7a7a\u6e2f"
    ],
    "name:msa_x_preferred":[
        "Lapangan Terbang Resende"
    ],
    "name:por_x_preferred":[
        "Aeroporto de Resende"
    ],
    "name:ron_x_preferred":[
        "Aeroportul Resende"
    ],
    "name:swe_x_preferred":[
        "Resende Airport"
    ],
    "oa:elevation_ft":"1320",
    "oa:type":"small_airport",
    "woe:hierarchy":{
        "country_id":23424768,
        "county_id":12581058,
        "planet_id":1,
        "state_id":2344862
    },
    "wof:name":"Aeroporto Resende",
    "wof:placetype":"campus"
},
  "geometry": {"coordinates":[-44.480301,-22.4785],"type":"Point"}
}