{
  "type": "Feature",
  "properties": {
    "name:deu_x_preferred":[
        "Flughafen Victoria Falls"
    ],
    "name:eng_x_preferred":[
        "Victoria Falls Airport"
    ],
    "name:eng_x_variant":[
        "VFA",
        "FVFA"
    ],
    "name:fas_x_preferred":[
        "\u0641\u0631\u0648\u062f\u06af\u0627\u0647 \u0622\u0628\u0634\u0627\u0631 \u0648\u06cc\u06a9\u062a\u0648\u0631\u06cc\u0627"
    ],
    "name:heb_x_preferred":[
        "\u05e0\u05de\u05dc \u05d4\u05ea\u05e2\u05d5\u05e4\u05d4 \u05d4\u05d1\u05d9\u05e0\u05dc\u05d0\u05d5\u05de\u05d9 \u05de\u05e4\u05dc\u05d9 \u05d5\u05d9\u05e7\u05d8\u05d5\u05e8\u05d9\u05d4"
    ],
    "name:jpn_x_preferred":[
        "\u30f4\u30a3\u30af\u30c8\u30ea\u30a2\u30d5\u30a9\u30fc\u30eb\u30ba\u7a7a\u6e2f"
    ],
    "name:msa_x_preferred":[
        "Lapangan Terbang Victoria Falls"
    ],
    "name:nld_x_preferred":[
        "Victoria Falls Airport"
    ],
    "name:nob_x_preferred":[
        "Victoria Falls lufthavn"
    ],
    "name:nor_x_preferred":[
        "Victoria Falls lufthavn"
    ],
    "name:pol_x_preferred":[
        "Port lotniczy Victoria Falls"
    ],
    "name:ron_x_preferred":[
        "Aeroportul Victoria Falls"
    ],
    "name:tgk_x_preferred":[
        "\u0424\u0443\u0440\u0443\u0434\u0433\u043e\u04b3\u0438 \u043e\u0431\u0448\u043e\u0440 \u0432\u0435\u043a\u0442\u0443\u0440\u0435\u0451"
    ],
    "name:tur_x_preferred":[
        "Victoria Falls Havaliman\u0131"
    ],
    "name:tur_x_variant":[
        "Viktorya \u015eelaleleri Havaalan\u0131"
    ],
    "name:zho_x_preferred":[
        "\u7dad\u591a\u5229\u4e9e\u7011\u5e03"
    ],
    "oa:elevation_ft":"3490",
    "oa:type":"medium_airport",
    "wd:wordcount":212,
    "woe:hierarchy":{
        "country_id":23425004,
        "county_id":56048508,
        "planet_id":1,
        "state_id":2347815
    },
    "wof:name":"Victoria Falls Airport",
    "wof:placetype":"campus"
},
  "geometry": {"coordinates":[25.839006,-18.095881],"type":"Point"}
}