{
  "type": "Feature",
  "properties": {
    "name:ara_x_preferred":[
        "\u0645\u0637\u0627\u0631 \u0627\u0644\u0644\u0647 \u0623\u0628\u0627\u062f"
    ],
    "name:ben_x_preferred":[
        "\u098f\u09b2\u09be\u09b9\u09be\u09ac\u09be\u09a6 \u09ac\u09bf\u09ae\u09be\u09a8\u09ac\u09a8\u09cd\u09a6\u09b0"
    ],
    "name:ben_x_variant":[
        "\u09aa\u09cd\u09b0\u09af\u09bc\u09be\u0997\u09b0\u09be\u099c \u09ac\u09bf\u09ae\u09be\u09a8\u09ac\u09a8\u09cd\u09a6\u09b0"
    ],
    "name:ceb_x_preferred":[
        "Allahabad Airport"
    ],
    "name:cym_x_preferred":[
        "Maes Awyr Allahabad"
    ],
    "name:deu_x_preferred":[
        "Flughafen Allahabad"
    ],
    "name:eng_x_preferred":[
        "Allahabad Airport"
    ],
    "name:eng_x_variant":[
        "IXD",
        "VIAL",
        "Prayagraj Airport"
    ],
    "name:fas_x_preferred":[
        "\u0641\u0631\u0648\u062f\u06af\u0627\u0647 \u0627\u0644\u0644\u0647\u200c\u0622\u0628\u0627\u062f"
    ],
    "name:fra_x_preferred":[
        "a\u00e9roport d'Allahabad"
    ],
    "name:hin_x_preferred":[
        "\u0907\u0932\u093e\u0939\u093e\u092c\u093e\u0926 \u0935\u093f\u092e\u093e\u0928\u0915\u094d\u0937\u0947\u0924\u094d\u0930"
    ],
    "name:hin_x_variant":[
        "\u092a\u094d\u0930\u092f\u093e\u0917\u0930\u093e\u091c \u0935\u093f\u092e\u093e\u0928\u0915\u094d\u0937\u0947\u0924\u094d\u0930"
    ],
    "name:jpn_x_preferred":[
        "\u30a4\u30e9\u30fc\u30cf\u30fc\u30d0\u30fc\u30c9\u7a7a\u6e2f"
    ],
    "name:mar_x_preferred":[
        "\u0905\u0932\u093e\u0939\u093e\u092c\u093e\u0926 \u0935\u093f\u092e\u093e\u0928\u0924\u0933"
    ],
    "name:msa_x_preferred":[
        "Lapangan Terbang Allahabad"
    ],
    "name:pol_x_preferred":[
        "Port lotniczy Allahabad"
    ],
    "name:ron_x_preferred":[
        "Aeroportul Allahabad"
    ],
    "name:swe_x_preferred":[
        "Allahabad Airport"
    ],
    "name:tam_x_preferred":[
        "\u0b85\u0bb2\u0b95\u0bbe\u0baa\u0bbe\u0ba4\u0bcd \u0bb5\u0bbe\u0ba9\u0bc2\u0bb0\u0bcd\u0ba4\u0bbf \u0ba8\u0bbf\u0bb2\u0bc8\u0baf\u0bae\u0bcd"
    ],
    "name:tgk_x_preferred":[
        "\u0424\u0443\u0440\u0443\u0434\u0433\u043e\u04b3\u0438 \u0430\u043b\u043b\u043e\u04b3\u200c\u043e\u0431\u043e\u0434"
    ],
    "name:vie_x_preferred":[
        "S\u00e2n bay Allahabad"
    ],
    "name:zho_x_preferred":[
        "\u5b89\u62c9\u963f\u5df4\u5fb7\u6a5f\u5834"
    ],
    "oa:elevation_ft":"322",
    "oa:type":"medium_airport",
    "woe:hierarchy":{
        "country_id":23424848,
        "county_id":12586715,
        "planet_id":1,
        "state_id":2345760
    },
    "wof:name":"Bamrauli Airport",
    "wof:placetype":"campus"
},
  "geometry": {"coordinates":[81.733902,25.4401],"type":"Point"}
}