{
  "type": "Feature",
  "properties": {
    "wof:name":"Sunland Village",
    "wof:placetype":"neighbourhood"
},
  "geometry": {"coordinates":[-111.72750325270874,33.40095803689964],"type":"Point"}
}