{
  "type": "Feature",
  "properties": {
    "name:ceb_x_preferred":[
        "High Level Airport"
    ],
    "name:deu_x_preferred":[
        "High Level Airport"
    ],
    "name:eng_x_preferred":[
        "High Level Airport"
    ],
    "name:eng_x_variant":[
        "YOJ",
        "CYOJ"
    ],
    "name:fas_x_preferred":[
        "\u0641\u0631\u0648\u062f\u06af\u0627\u0647\u200c\u0647\u0627\u06cc \u0644\u0648\u0644"
    ],
    "name:ind_x_preferred":[
        "Bandar Udara High Level"
    ],
    "name:msa_x_preferred":[
        "Lapangan Terbang High Level"
    ],
    "name:pms_x_preferred":[
        "High Level Airport"
    ],
    "name:pol_x_preferred":[
        "Port lotniczy High Level"
    ],
    "name:ron_x_preferred":[
        "Aeroportul High Level"
    ],
    "name:spa_x_preferred":[
        "Aeropuerto de High Level"
    ],
    "name:swe_x_preferred":[
        "High Level Airport"
    ],
    "name:tgk_x_preferred":[
        "\u0424\u0443\u0440\u0443\u0434\u0433\u043e\u04b3\u0438 \u04b3 \u0644\u0432\u043b"
    ],
    "name:zho_x_preferred":[
        "\u9ad8\u6cb3\u9547\u673a\u573a"
    ],
    "oa:elevation_ft":"1110",
    "oa:type":"medium_airport",
    "wd:wordcount":87,
    "woe:hierarchy":{
        "country_id":23424775,
        "county_id":29375228,
        "planet_id":1,
        "state_id":2344915
    },
    "wof:name":"High Level Airport",
    "wof:placetype":"campus"
},
  "geometry": {"coordinates":[-117.16500000000001,58.6217],"type":"Point"}
}