{
  "type": "Feature",
  "properties": {
    "name:ind_x_preferred":[
        "Bandar Udara Kotamadya La Porte"
    ],
    "oa:elevation_ft":"812",
    "oa:type":"small_airport",
    "wd:wordcount":33,
    "woe:hierarchy":{
        "country_id":23424977,
        "county_id":12588223,
        "planet_id":1,
        "state_id":2347573
    },
    "wof:name":"La Porte Municipal Airport",
    "wof:placetype":"campus"
},
  "geometry": {"coordinates":[-86.73439999999999,41.5725],"type":"Point"}
}