{
  "type": "Feature",
  "properties": {
    "name:ceb_x_preferred":[
        "La Porte Municipal Airport"
    ],
    "name:eng_x_preferred":[
        "La Porte Municipal Airport"
    ],
    "name:fas_x_preferred":[
        "\u0641\u0631\u0648\u062f\u06af\u0627\u0647 \u0634\u0647\u0631\u06cc \u0644\u0627 \u067e\u0648\u0631\u062a"
    ],
    "name:ind_x_preferred":[
        "Bandar Udara Kotamadya La Porte"
    ],
    "name:ron_x_preferred":[
        "Aeroportul Municipal La Porte"
    ],
    "name:tgk_x_preferred":[
        "\u0424\u0443\u0440\u0443\u0434\u0433\u043e\u04b3\u0438 \u0448\u0430\u04b3\u0440\u0435 \u043b\u043e \u043f\u04ef\u0440"
    ],
    "name:urd_x_preferred":[
        "\u0644\u0627 \u067e\u0648\u0631\u0679\u06d2 \u0645\u06cc\u0648\u0646\u0633\u067e\u0644 \u0627\u06cc\u0626\u0631\u067e\u0648\u0631\u0679"
    ],
    "oa:elevation_ft":"812",
    "oa:type":"small_airport",
    "wd:wordcount":33,
    "woe:hierarchy":{
        "country_id":23424977,
        "county_id":12588223,
        "planet_id":1,
        "state_id":2347573
    },
    "wof:name":"La Porte Municipal Airport",
    "wof:placetype":"campus"
},
  "geometry": {"coordinates":[-86.73439999999999,41.5725],"type":"Point"}
}