{
  "type": "Feature",
  "properties": {
    "name:deu_x_preferred":[
        "Fairmont Municipal Airport"
    ],
    "oa:elevation_ft":"1162",
    "oa:type":"small_airport",
    "wd:wordcount":26,
    "woe:hierarchy":{
        "country_id":23424977,
        "county_id":12588841,
        "planet_id":1,
        "state_id":2347582
    },
    "wof:name":"Fairmont Municipal Airport",
    "wof:placetype":"campus"
},
  "geometry": {"coordinates":[-94.4156,43.6439],"type":"Point"}
}