{
  "type": "Feature",
  "properties": {
    "name:arz_x_preferred":[
        "\u0645\u0637\u0627\u0631 \u0641\u064a\u0631\u0645\u0648\u0646\u062a \u0627\u0644\u0645\u062d\u0644\u0649"
    ],
    "name:ceb_x_preferred":[
        "Fairmont Municipal Airport"
    ],
    "name:deu_x_preferred":[
        "Fairmont Municipal Airport"
    ],
    "name:eng_x_preferred":[
        "Fairmont Municipal Airport"
    ],
    "name:eng_x_variant":[
        "FRM",
        "KFRM"
    ],
    "name:fas_x_preferred":[
        "\u0641\u0631\u0648\u062f\u06af\u0627\u0647 \u0634\u0647\u0631\u06cc \u0641\u06cc\u0631\u0645\u0648\u0646\u062a"
    ],
    "name:ron_x_preferred":[
        "Aeroportul Municipal Fairmont"
    ],
    "name:tgk_x_preferred":[
        "\u0424\u0443\u0440\u0443\u0434\u0433\u043e\u04b3\u0438 \u0448\u0430\u04b3\u0440\u0435 \u0444\u0438\u0440\u043c\u0443\u043d\u0442"
    ],
    "name:urd_x_preferred":[
        "\u0641\u06cc\u0626\u0631\u0645\u0648\u0646\u0679 \u0645\u06cc\u0648\u0646\u0633\u067e\u0644 \u06c1\u0648\u0627\u0626\u06cc \u0627\u0688\u0627"
    ],
    "name:zho_x_preferred":[
        "\u8cbb\u723e\u8499\u7279\u5e02\u7acb\u6a5f\u5834"
    ],
    "oa:elevation_ft":"1162",
    "oa:type":"small_airport",
    "wd:wordcount":26,
    "woe:hierarchy":{
        "country_id":23424977,
        "county_id":12588841,
        "planet_id":1,
        "state_id":2347582
    },
    "wof:name":"Fairmont Municipal Airport",
    "wof:placetype":"campus"
},
  "geometry": {"coordinates":[-94.4156,43.6439],"type":"Point"}
}