{
  "type": "Feature",
  "properties": {
    "name:ceb_x_preferred":[
        "Anchialos Airport"
    ],
    "name:ces_x_preferred":[
        "Nea Anchialos National Airport"
    ],
    "name:deu_x_preferred":[
        "Flughafen Nea Anchialos"
    ],
    "name:ell_x_preferred":[
        "\u039a\u03c1\u03b1\u03c4\u03b9\u03ba\u03cc\u03c2 \u0391\u03b5\u03c1\u03bf\u03bb\u03b9\u03bc\u03ad\u03bd\u03b1\u03c2 \u039d\u03ad\u03b1\u03c2 \u0391\u03b3\u03c7\u03b9\u03ac\u03bb\u03bf\u03c5"
    ],
    "name:eng_x_preferred":[
        "Nea Anchialos National Airport"
    ],
    "name:eng_x_variant":[
        "VOL",
        "LGBL"
    ],
    "name:fas_x_preferred":[
        "\u0641\u0631\u0648\u062f\u06af\u0627\u0647 \u0645\u0644\u06cc \u0646\u0627 \u0627\u0646\u0686\u06cc\u0627\u0644\u0648\u0633"
    ],
    "name:fin_x_preferred":[
        "N\u00e9a Anch\u00edaloksen lentoasema"
    ],
    "name:jpn_x_preferred":[
        "\u30cd\u30a2\u30fb\u30a2\u30f3\u30d2\u30a2\u30ed\u30b9\u7a7a\u6e2f"
    ],
    "name:msa_x_preferred":[
        "Lapangan Terbang Almiros AB"
    ],
    "name:nld_x_preferred":[
        "Luchthaven Nea Anchialos"
    ],
    "name:pol_x_preferred":[
        "Port lotniczy Nea Anchialos"
    ],
    "name:ron_x_preferred":[
        "Aeroportul Na\u021bional Nea Anchialos"
    ],
    "name:spa_x_preferred":[
        "Aeropuerto Internacional de Volos - Nea Anchialos"
    ],
    "name:swe_x_preferred":[
        "Anchialos Airport"
    ],
    "name:tgk_x_preferred":[
        "\u0424\u0443\u0440\u0443\u0434\u0433\u043e\u04b3\u0438 \u043c\u0438\u043b\u043b\u04e3 \u043d\u043e \u043e\u043d\u0447\u0438\u043e\u043b\u0443\u0441"
    ],
    "name:ukr_x_preferred":[
        "\u041c\u0456\u0436\u043d\u0430\u0440\u043e\u0434\u043d\u0438\u0439 \u0430\u0435\u0440\u043e\u043f\u043e\u0440\u0442 \u0426\u0435\u043d\u0442\u0440\u0430\u043b\u044c\u043d\u0430 \u0413\u0440\u0435\u0446\u0456\u044f"
    ],
    "name:zho_x_preferred":[
        "\u4f5b\u6d1b\u65af"
    ],
    "oa:elevation_ft":"83",
    "oa:type":"medium_airport",
    "wd:wordcount":354,
    "woe:hierarchy":{
        "country_id":23424833,
        "county_id":12591129,
        "localadmin_id":24544442,
        "planet_id":1,
        "state_id":12577889
    },
    "wof:name":"Nea Anchialos Airport",
    "wof:placetype":"campus"
},
  "geometry": {"coordinates":[22.7943,39.219601],"type":"Point"}
}