{
  "type": "Feature",
  "properties": {
    "name:ceb_x_preferred":[
        "Pichoy Airport"
    ],
    "name:deu_x_preferred":[
        "Flughafen Valdivia"
    ],
    "name:eng_x_preferred":[
        "Pichoy Airport"
    ],
    "name:eng_x_variant":[
        "ZAL",
        "SCVD"
    ],
    "name:fas_x_preferred":[
        "\u0641\u0631\u0648\u062f\u06af\u0627\u0647 \u067e\u06cc\u0686\u0648\u06cc"
    ],
    "name:jpn_x_preferred":[
        "\u30d4\u30c1\u30e7\u30a4\u7a7a\u6e2f"
    ],
    "name:msa_x_preferred":[
        "Lapangan Terbang Pichoy"
    ],
    "name:pol_x_preferred":[
        "Port lotniczy Valdivia-Pichoy"
    ],
    "name:ron_x_preferred":[
        "Aeroportul Pichoy"
    ],
    "name:spa_x_preferred":[
        "Aer\u00f3dromo Pichoy"
    ],
    "name:swe_x_preferred":[
        "Pichoy Airport"
    ],
    "name:tgk_x_preferred":[
        "\u0424\u0443\u0440\u0443\u0434\u0433\u043e\u04b3\u0438 \u043f\u0438\u0447\u0443\u0438"
    ],
    "oa:elevation_ft":"59",
    "oa:type":"medium_airport",
    "wd:wordcount":69,
    "woe:hierarchy":{
        "country_id":23424782,
        "county_id":26794021,
        "localadmin_id":26794186,
        "planet_id":1,
        "state_id":56043703
    },
    "wof:name":"Pichoy Airport",
    "wof:placetype":"campus"
},
  "geometry": {"coordinates":[-73.08609800000001,-39.650002],"type":"Point"}
}