{
  "type": "Feature",
  "properties": {
    "wd:wordcount":44,
    "wof:name":"Tech Town",
    "wof:placetype":"neighbourhood"
},
  "geometry": {"coordinates":[-83.07454128284303,42.36390955584564],"type":"Point"}
}