{
  "type": "Feature",
  "properties": {
    "gn:admin1_code":"33.0",
    "gn:asciiname":"Okatope",
    "gn:dem":1102,
    "gn:feature_class":"P",
    "gn:feature_code":"PPL",
    "gn:name":"Okatope",
    "gn:population":0,
    "gn:timezone":"Africa/Windhoek",
    "wof:name":"Okatope",
    "wof:placetype":"locality"
},
  "geometry": {"coordinates":[15.95,-17.51667],"type":"Point"}
}