{
  "type": "Feature",
  "properties": {
    "name:eng_x_preferred":[
        "Salmiya-block 6"
    ],
    "qs:gn_local":0,
    "qs:local_max":1015,
    "qs:local_sum":3961,
    "qs:localhoods":9,
    "qs:name":"Salmiya-block 6",
    "qs:name_adm0":"\u0627\u0644\u0643\u0648\u064a\u062a",
    "qs:name_adm1":"\u062d\u0648\u0644\u0649",
    "qs:name_adm2":"\u062d\u0648\u0644\u0649",
    "qs:name_local":"Salmiya",
    "qs:photo_max":33,
    "qs:photo_sum":144,
    "qs:placetype":"Suburb",
    "qs:quad_count":13,
    "qs:woe_adm0":23424870,
    "qs:woe_adm1":20070167,
    "qs:woe_adm2":55943084,
    "qs:woe_lau":0,
    "qs:woe_local":22724741,
    "qs:woe_ver":"7.10.0",
    "wof:lang":[
        "eng"
    ],
    "wof:name":"Salmiya-block 6",
    "wof:placetype":"neighbourhood"
},
  "geometry": {"coordinates":[48.089084,29.32411],"type":"Point"}
}