{
  "type": "Feature",
  "properties": {
    "name:ceb_x_preferred":[
        "Z\u00fcrich"
    ],
    "name:deu_x_preferred":[
        "Escher Wyss"
    ],
    "name:eng_x_preferred":[
        "Escher Wyss"
    ],
    "name:fra_x_preferred":[
        "Escher Wyss"
    ],
    "name:lat_x_preferred":[
        "Escher Wyss"
    ],
    "name:nld_x_preferred":[
        "Escher Wyss"
    ],
    "name:ukr_x_preferred":[
        "\u0415\u0448\u0435\u0440-\u0412\u0456\u0441\u0441"
    ],
    "wof:name":"Escher-Wyss",
    "wof:placetype":"neighbourhood"
},
  "geometry": {"coordinates":[8.503945,47.392707],"type":"Point"}
}