{
  "type": "Feature",
  "properties": {
    "name:ceb_x_preferred":[
        "Z\u00fcrich"
    ],
    "name:deu_x_preferred":[
        "Escher Wyss"
    ],
    "name:eng_x_preferred":[
        "Escher Wyss"
    ],
    "name:fra_x_preferred":[
        "Escher Wyss"
    ],
    "name:lat_x_preferred":[
        "Escher Wyss"
    ],
    "name:nld_x_preferred":[
        "Escher Wyss"
    ],
    "wof:name":"Escher-Wyss",
    "wof:placetype":"neighbourhood"
},
  "geometry": {"coordinates":[8.50394463307242,47.39270719765138],"type":"Point"}
}