{
  "type": "Feature",
  "properties": {
    "gn:admin1_code":"41.0",
    "gn:asciiname":"Siwi",
    "gn:dem":1147,
    "gn:feature_class":"P",
    "gn:feature_code":"PPL",
    "gn:name":"Siwi",
    "gn:population":0,
    "gn:timezone":"Africa/Windhoek",
    "wof:name":"Siwi",
    "wof:placetype":"locality"
},
  "geometry": {"coordinates":[18.23333,-17.53333],"type":"Point"}
}