{
  "type": "Feature",
  "properties": {
    "name:eng_x_preferred":[
        "Ilo Airport"
    ],
    "name:fas_x_preferred":[
        "\u0641\u0631\u0648\u062f\u06af\u0627\u0647 \u0627\u06cc\u0644\u0648"
    ],
    "name:fra_x_preferred":[
        "a\u00e9roport d'Ilo"
    ],
    "name:jpn_x_preferred":[
        "\u30a4\u30ed\u7a7a\u6e2f"
    ],
    "name:msa_x_preferred":[
        "Lapangan Terbang Ilo"
    ],
    "name:pol_x_preferred":[
        "Port lotniczy Ilo"
    ],
    "name:ron_x_preferred":[
        "Aeroportul Ilo"
    ],
    "name:spa_x_preferred":[
        "Aeropuerto de Ilo"
    ],
    "name:tgk_x_preferred":[
        "\u0424\u0443\u0440\u0443\u0434\u0433\u043e\u04b3\u0438 \u043e\u0438\u043b\u0443"
    ],
    "oa:elevation_ft":"72",
    "oa:type":"medium_airport",
    "wd:wordcount":79,
    "woe:hierarchy":{
        "country_id":23424919,
        "county_id":26805866,
        "planet_id":1,
        "state_id":2346485
    },
    "wof:name":"Ilo Airport",
    "wof:placetype":"campus"
},
  "geometry": {"coordinates":[-71.343888888889,-17.695],"type":"Point"}
}