{
  "type": "Feature",
  "properties": {
    "name:ceb_x_preferred":[
        "Umiujaq"
    ],
    "name:eng_x_preferred":[
        "Umiujaq Airport"
    ],
    "name:eng_x_variant":[
        "YUD",
        "CYMU"
    ],
    "name:fas_x_preferred":[
        "\u0641\u0631\u0648\u062f\u06af\u0627\u0647 \u0627\u0648\u0645\u06cc\u0648\u062c\u0627\u06a9"
    ],
    "name:fra_x_preferred":[
        "a\u00e9roport d\u2019Umiujaq"
    ],
    "name:msa_x_preferred":[
        "Lapangan Terbang Umiujaq"
    ],
    "name:pms_x_preferred":[
        "Umiujaq Airport"
    ],
    "name:ron_x_preferred":[
        "Aeroportul Umiujaq"
    ],
    "name:spa_x_preferred":[
        "Aeropuerto de Umiujaq"
    ],
    "name:swe_x_preferred":[
        "Umiujaq"
    ],
    "name:tgk_x_preferred":[
        "\u0424\u0443\u0440\u0443\u0434\u0433\u043e\u04b3\u0438 \u043e\u0432\u043c\u044e\u04b7\u043e\u043a"
    ],
    "oa:elevation_ft":"250",
    "oa:type":"medium_airport",
    "wd:wordcount":54,
    "woe:hierarchy":{
        "country_id":23424775,
        "county_id":29375254,
        "planet_id":1,
        "state_id":2344924
    },
    "wof:name":"Umiujaq Airport",
    "wof:placetype":"campus"
},
  "geometry": {"coordinates":[-76.518303,56.536098],"type":"Point"}
}