{
  "type": "Feature",
  "properties": {
    "name:eng_x_preferred":[
        "Lic. Miguel de la Madrid Airport"
    ],
    "name:eng_x_variant":[
        "CLQ",
        "MMIA"
    ],
    "name:fas_x_preferred":[
        "\u0641\u0631\u0648\u062f\u06af\u0627\u0647 \u0627\u0644 \u0622\u06cc \u0633\u06cc. \u0645\u06cc\u06af\u0648\u0626\u0644 \u062f\u0644\u0627 \u0645\u0627\u062f\u0631\u06cc\u062f"
    ],
    "name:ind_x_preferred":[
        "Bandar Udara Licenciado Miguel de la Madrid"
    ],
    "name:jpn_x_preferred":[
        "\u30df\u30b2\u30eb\u30fb\u30c7\u30fb\u30e9\u30fb\u30de\u30c9\u30ea\u30c3\u30c9\u7a7a\u6e2f"
    ],
    "name:msa_x_preferred":[
        "Lapangan Terbang Colima"
    ],
    "name:pol_x_preferred":[
        "Port lotniczy Colima"
    ],
    "name:spa_x_preferred":[
        "Aeropuerto Nacional Licenciado Miguel de la Madrid"
    ],
    "name:swe_x_preferred":[
        "Lic. Miguel de la Madrid Airport"
    ],
    "name:tgk_x_preferred":[
        "\u0424\u0443\u0440\u0443\u0434\u0433\u043e\u04b3\u0438 \u0438\u043b \u043e\u0439 \u0441\u0438. \u043c\u0438\u0433\u0443\u0435\u04b3\u043b \u0434\u043b\u043e \u043c\u043e\u0434\u0440\u0435\u0434"
    ],
    "name:vie_x_preferred":[
        "S\u00e2n bay Lic. Miguel de la Madrid"
    ],
    "name:zho_x_preferred":[
        "\u7c73\u683c\u723e\u00b7\u5fb7\u62c9\u99ac\u5fb7\u91cc\u6a5f\u5834"
    ],
    "oa:elevation_ft":"2467",
    "oa:type":"medium_airport",
    "woe:hierarchy":{
        "country_id":23424900,
        "county_id":12599928,
        "planet_id":1,
        "state_id":2346271
    },
    "wof:name":"Colima Airport",
    "wof:placetype":"campus"
},
  "geometry": {"coordinates":[-103.577003,19.277],"type":"Point"}
}