{
  "type": "Feature",
  "properties": {
    "gn:admin1_code":"41.0",
    "gn:asciiname":"Mbunza",
    "gn:dem":1083,
    "gn:feature_class":"P",
    "gn:feature_code":"PPL",
    "gn:name":"Mbunza",
    "gn:population":0,
    "gn:timezone":"Africa/Windhoek",
    "name:spa_x_preferred":[
        "Mbunza"
    ],
    "wof:name":"Mbunza",
    "wof:placetype":"locality"
},
  "geometry": {"coordinates":[19.36667000000001,-17.86667000000001],"type":"Point"}
}