{
  "type": "Feature",
  "properties": {
    "name:arz_x_preferred":[
        "\u0645\u0637\u0627\u0631 \u0628\u0648\u0646\u062a\u0627 \u0628\u0648\u0631\u0627 \u0627\u0644\u062f\u0648\u0644\u0649"
    ],
    "name:ceb_x_preferred":[
        "Ponta Pora Intl"
    ],
    "name:deu_x_preferred":[
        "Flughafen Ponta Por\u00e3"
    ],
    "name:eng_x_preferred":[
        "Ponta Por\u00e3 International Airport"
    ],
    "name:eng_x_variant":[
        "PMG",
        "SBPP"
    ],
    "name:fas_x_preferred":[
        "\u0641\u0631\u0648\u062f\u06af\u0627\u0647 \u0628\u06cc\u0646\u200c\u0627\u0644\u0645\u0644\u0644\u06cc \u067e\u0648\u0646\u062a\u0627 \u067e\u0648\u0631\u0626\u0627"
    ],
    "name:jpn_x_preferred":[
        "\u30dd\u30f3\u30bf\u30fb\u30dd\u30e9\u30f3\u7a7a\u6e2f"
    ],
    "name:msa_x_preferred":[
        "Lapangan Terbang Antarabangsa Ponta Pora"
    ],
    "name:por_x_preferred":[
        "Aeroporto Internacional de Ponta Por\u00e3"
    ],
    "name:rus_x_preferred":[
        "\u041f\u043e\u043d\u0442\u0430-\u041f\u043e\u0440\u0430\u043d"
    ],
    "name:swe_x_preferred":[
        "Ponta Pora Intl"
    ],
    "name:tgk_x_preferred":[
        "\u0424\u0443\u0440\u0443\u0434\u0433\u043e\u04b3\u0438 \u0431\u0438\u043d\u200c\u0430\u043b\u043c\u0438\u043b\u0430\u043b\u04e3 \u043f\u0443\u043d\u0442\u043e \u043f\u0443\u0440\u0435\u04b3\u043e"
    ],
    "oa:elevation_ft":"2156",
    "oa:type":"medium_airport",
    "woe:hierarchy":{
        "country_id":23424768,
        "county_id":12579157,
        "planet_id":1,
        "state_id":2344853
    },
    "wof:name":"Aeroporto Internacional Ponta Pora",
    "wof:placetype":"campus"
},
  "geometry": {"coordinates":[-55.702599,-22.549601],"type":"Point"}
}