{
  "type": "Feature",
  "properties": {
    "name:ceb_x_preferred":[
        "Myeik Airport"
    ],
    "name:eng_x_preferred":[
        "Myeik Airport"
    ],
    "name:eng_x_variant":[
        "MGZ",
        "VYME"
    ],
    "name:fas_x_preferred":[
        "\u0641\u0631\u0648\u062f\u06af\u0627\u0647 \u0645\u06cc\u06cc\u06a9"
    ],
    "name:jpn_x_preferred":[
        "\u30d9\u30a4\u7a7a\u6e2f"
    ],
    "name:kor_x_preferred":[
        "\uba54\ub974\uadc0 \uacf5\ud56d"
    ],
    "name:msa_x_preferred":[
        "Lapangan Terbang Myeik"
    ],
    "name:mya_x_preferred":[
        "\u1019\u103c\u102d\u1010\u103a \u101c\u1031\u1006\u102d\u1015\u103a"
    ],
    "name:pol_x_preferred":[
        "Port lotniczy Myeik"
    ],
    "name:ron_x_preferred":[
        "Aeroportul Myeik"
    ],
    "name:swe_x_preferred":[
        "Myeik Airport"
    ],
    "name:tgk_x_preferred":[
        "\u0424\u0443\u0440\u0443\u0434\u0433\u043e\u04b3\u0438 \u043c\u043e\u0432\u043d\u0434\u0443\u0438\u043b"
    ],
    "name:vie_x_preferred":[
        "S\u00e2n bay Myeik"
    ],
    "name:zho_x_preferred":[
        "\u4e39\u8001\u6a5f\u5834"
    ],
    "oa:elevation_ft":"75",
    "oa:type":"medium_airport",
    "woe:hierarchy":{
        "country_id":23424763,
        "planet_id":1,
        "state_id":2344821
    },
    "wof:name":"Mergui Airport",
    "wof:placetype":"campus"
},
  "geometry": {"coordinates":[98.621498,12.4398],"type":"Point"}
}