{
  "type": "Feature",
  "properties": {
    "gn:admin1_code":"30.0",
    "gn:asciiname":"Gochas",
    "gn:dem":1138,
    "gn:feature_class":"P",
    "gn:feature_code":"PPL",
    "gn:name":"Gochas",
    "gn:population":0,
    "gn:timezone":"Africa/Windhoek",
    "name:afr_x_preferred":[
        "Gochas"
    ],
    "name:deu_x_preferred":[
        "Gochas"
    ],
    "wof:name":"Gochas",
    "wof:placetype":"locality"
},
  "geometry": {"coordinates":[18.81667,-24.78333],"type":"Point"}
}