{
  "type": "Feature",
  "properties": {
    "name:cat_x_preferred":[
        "Homewood"
    ],
    "name:ceb_x_preferred":[
        "Homewood"
    ],
    "name:deu_x_preferred":[
        "Homewood"
    ],
    "name:fra_x_preferred":[
        "Homewood"
    ],
    "name:ido_x_preferred":[
        "Homewood"
    ],
    "name:ita_x_preferred":[
        "Homewood"
    ],
    "name:nld_x_preferred":[
        "Homewood"
    ],
    "name:pol_x_preferred":[
        "Homewood"
    ],
    "name:srp_x_preferred":[
        "\u0425\u043e\u043c\u0432\u0443\u0434"
    ],
    "name:ukr_x_preferred":[
        "\u0413\u043e\u0443\u043c\u0432\u0443\u0434"
    ],
    "name:vol_x_preferred":[
        "Homewood"
    ],
    "wd:wordcount":123,
    "wof:name":"Homewood",
    "wof:placetype":"neighbourhood"
},
  "geometry": {"coordinates":[-79.89793847049832,40.45765168273756],"type":"Point"}
}