{
  "type": "Feature",
  "properties": {
    "name:arz_x_preferred":[
        "\u0645\u0637\u0627\u0631 \u0634\u064a\u0631\u0627\u0648 \u0627\u0644\u0645\u062d\u0644\u0649"
    ],
    "name:eng_x_preferred":[
        "Cheraw Municipal Airport"
    ],
    "name:eng_x_variant":[
        "HCW",
        "KCQW"
    ],
    "name:fas_x_preferred":[
        "\u0641\u0631\u0648\u062f\u06af\u0627\u0647 \u0634\u0647\u0631\u06cc \u0686\u0631\u0627\u0648"
    ],
    "name:jpn_x_preferred":[
        "Cheraw\u5e02\u55b6\u7a7a\u6e2f"
    ],
    "name:ron_x_preferred":[
        "Aeroportul Municipal Cheraw"
    ],
    "name:tgk_x_preferred":[
        "\u0424\u0443\u0440\u0443\u0434\u0433\u043e\u04b3\u0438 \u0427\u0435\u0440\u043e\u0443"
    ],
    "name:tgk_x_variant":[
        "\u0424\u0443\u0440\u0443\u0434\u0433\u043e\u04b3\u0438 \u0448\u0430\u04b3\u0440\u0435 \u0447\u0440\u043e\u0432"
    ],
    "name:urd_x_preferred":[
        "\u0686\u06cc\u0631\u0627 \u0645\u06cc\u0648\u0646\u0633\u067e\u0644 \u06c1\u0648\u0627\u0626\u06cc \u0627\u0688\u0627"
    ],
    "oa:elevation_ft":"239",
    "oa:type":"small_airport",
    "wd:wordcount":248,
    "woe:hierarchy":{
        "country_id":23424977,
        "county_id":12589812,
        "planet_id":1,
        "state_id":2347599
    },
    "wof:name":"Cheraw Municipal Airport",
    "wof:placetype":"campus"
},
  "geometry": {"coordinates":[-79.9569,34.7128],"type":"Point"}
}