{
  "type": "Feature",
  "properties": {
    "name:ceb_x_preferred":[
        "Gettysburg Regional Airport"
    ],
    "name:eng_x_preferred":[
        "Gettysburg Regional Airport"
    ],
    "name:eng_x_variant":[
        "GTY",
        "KW05"
    ],
    "name:fas_x_preferred":[
        "\u0641\u0631\u0648\u062f\u06af\u0627\u0647 \u0645\u062d\u0644\u06cc \u06af\u062a\u06cc\u0632\u0628\u0631\u06af"
    ],
    "name:ron_x_preferred":[
        "Aeroportul Regional Gettysburg"
    ],
    "name:tgk_x_preferred":[
        "\u0424\u0443\u0440\u0443\u0434\u0433\u043e\u04b3\u0438 \u041c\u0430\u04b3\u0430\u043b\u04e3 \u0433\u0442\u0438\u0437\u0431\u0440\u0433"
    ],
    "name:urd_x_preferred":[
        "\u06af\u06cc\u0679\u06cc\u0632\u0628\u0631\u06af \u0631\u06cc\u062c\u0646\u0644 \u0627\u06cc\u0626\u0631\u067e\u0648\u0631\u0679"
    ],
    "oa:elevation_ft":"590",
    "oa:type":"small_airport",
    "woe:hierarchy":{
        "country_id":23424977,
        "county_id":12589728,
        "planet_id":1,
        "state_id":2347597
    },
    "wof:name":"Doersom Airport",
    "wof:placetype":"campus"
},
  "geometry": {"coordinates":[-77.27419999999999,39.8409],"type":"Point"}
}