{
  "type": "Feature",
  "properties": {
    "gn:admin1_code":"39.0",
    "gn:asciiname":"Otjomupanda",
    "gn:dem":1289,
    "gn:feature_class":"P",
    "gn:feature_code":"PPL",
    "gn:name":"Otjomupanda",
    "gn:population":0,
    "gn:timezone":"Africa/Windhoek",
    "wof:name":"Otjomupanda",
    "wof:placetype":"locality"
},
  "geometry": {"coordinates":[18.03333,-20.65],"type":"Point"}
}