{
  "type": "Feature",
  "properties": {
    "name:eng_x_preferred":[
        "Sace Airport"
    ],
    "name:eng_x_variant":[
        "FASU"
    ],
    "name:msa_x_preferred":[
        "Lapangan Terbang Sace"
    ],
    "name:ron_x_preferred":[
        "Aeroportul Sace"
    ],
    "oa:elevation_ft":"5151",
    "oa:type":"small_airport",
    "woe:hierarchy":{
        "country_id":23424942,
        "county_id":56189425,
        "localadmin_id":56189520,
        "planet_id":1,
        "state_id":2346983
    },
    "wof:name":"Sace Airport",
    "wof:placetype":"campus"
},
  "geometry": {"coordinates":[29.211112,-25.955555],"type":"Point"}
}