{
  "type": "Feature",
  "properties": {
    "gn:admin1_code":"29.0",
    "gn:asciiname":"Ondundo",
    "gn:dem":1017,
    "gn:feature_class":"P",
    "gn:feature_code":"PPL",
    "gn:name":"Ondundo",
    "gn:population":0,
    "gn:timezone":"Africa/Windhoek",
    "wof:name":"Ondundo",
    "wof:placetype":"locality"
},
  "geometry": {"coordinates":[15.45,-20.75],"type":"Point"}
}