{
  "type": "Feature",
  "properties": {
    "gn:admin1_code":"33.0",
    "gn:asciiname":"Oshidute",
    "gn:dem":1158,
    "gn:feature_class":"P",
    "gn:feature_code":"PPL",
    "gn:name":"Oshidute",
    "gn:population":0,
    "gn:timezone":"Africa/Windhoek",
    "wof:name":"Oshidute",
    "wof:placetype":"locality"
},
  "geometry": {"coordinates":[17.26667,-17.56667],"type":"Point"}
}