{
  "type": "Feature",
  "properties": {
    "wof:name":"South Gate",
    "wof:placetype":"neighbourhood"
},
  "geometry": {"coordinates":[28.01983884699522,-26.27429863454284],"type":"Point"}
}