{
  "type": "Feature",
  "properties": {
    "name:eng_x_preferred":[
        "Santa Cruz Island Airport"
    ],
    "name:ron_x_preferred":[
        "Aeroportul Santa Cruz Island"
    ],
    "name:urd_x_preferred":[
        "\u0633\u0627\u0646\u062a\u0627 \u06a9\u0631\u0648\u0632 \u062c\u0632\u06cc\u0631\u06c1 \u06c1\u0648\u0627\u0626\u06cc \u0627\u0688\u0627"
    ],
    "oa:elevation_ft":"50",
    "oa:type":"small_airport",
    "wd:wordcount":160,
    "woe:hierarchy":{
        "country_id":23424977,
        "county_id":12587711,
        "planet_id":1,
        "state_id":2347563
    },
    "wof:name":"Santa Cruz Island Airport",
    "wof:placetype":"campus"
},
  "geometry": {"coordinates":[-119.91500000000001,34.0606],"type":"Point"}
}