{
  "type": "Feature",
  "properties": {
    "name:ceb_x_preferred":[
        "Mosj\u00f8en Airport"
    ],
    "name:dan_x_preferred":[
        "Mosj\u00f8en Lufthavn"
    ],
    "name:deu_x_preferred":[
        "Flughafen Mosj\u00f8en"
    ],
    "name:eng_x_preferred":[
        "Mosj\u00f8en Airport"
    ],
    "name:eng_x_variant":[
        "MJF",
        "ENMS"
    ],
    "name:fas_x_preferred":[
        "\u0641\u0631\u0648\u062f\u06af\u0627\u0647 \u0645\u0648\u0634\u0646 \u06a9\u06cc\u0627\u0634\u062a\u0627\u062f"
    ],
    "name:msa_x_preferred":[
        "Lapangan Terbang Kjaerstad"
    ],
    "name:nld_x_preferred":[
        "Luchthaven Mosj\u00f8en Kj\u00e6rstad"
    ],
    "name:nno_x_preferred":[
        "Mosj\u00f8en lufthamn"
    ],
    "name:nob_x_preferred":[
        "Mosj\u00f8en lufthavn"
    ],
    "name:nor_x_preferred":[
        "Mosj\u00f8en lufthavn"
    ],
    "name:pol_x_preferred":[
        "Port lotniczy Mosj\u00f8en"
    ],
    "name:ron_x_preferred":[
        "Aeroportul Mosj\u00f8en"
    ],
    "name:spa_x_preferred":[
        "Aeropuerto de Mosj\u00f8en-Kj\u00e6rstad"
    ],
    "name:swe_x_preferred":[
        "Mosj\u00f8ens flygplats"
    ],
    "name:swe_x_variant":[
        "Mosj\u00f8en flygplats"
    ],
    "name:tgk_x_preferred":[
        "\u0424\u0443\u0440\u0443\u0434\u0433\u043e\u04b3\u0438 \u043c\u0443\u0448\u043d \u043a\u0438\u043e\u0448\u0442\u043e\u0434"
    ],
    "name:vie_x_preferred":[
        "S\u00e2n bay Mosj\u00f8en"
    ],
    "oa:elevation_ft":"237",
    "oa:type":"medium_airport",
    "wd:wordcount":356,
    "woe:hierarchy":{
        "country_id":23424910,
        "county_id":12592891,
        "planet_id":1,
        "state_id":2346392
    },
    "wof:name":"Mosj\u00f8en lufthavn Kj\u00e6rstad",
    "wof:placetype":"campus"
},
  "geometry": {"coordinates":[13.2149,65.783997],"type":"Point"}
}