{
  "type": "Feature",
  "properties": {
    "name:eng_x_preferred":[
        "La Loma Park"
    ],
    "name:fra_x_preferred":[
        "La Loma Park"
    ],
    "wd:wordcount":627,
    "wof:name":"La Loma Park",
    "wof:placetype":"neighbourhood"
},
  "geometry": {"coordinates":[-122.25736157756008,37.8822754413494],"type":"Point"}
}