{
  "type": "Feature",
  "properties": {
    "name:eng_x_preferred":[
        "La Loma Park"
    ],
    "name:fra_x_preferred":[
        "La Loma Park"
    ],
    "name:nld_x_preferred":[
        "La Loma Park"
    ],
    "wd:wordcount":627,
    "wof:name":"La Loma Park",
    "wof:placetype":"neighbourhood"
},
  "geometry": {"coordinates":[-122.257362,37.882275],"type":"Point"}
}