{
  "type": "Feature",
  "properties": {
    "name:ceb_x_preferred":[
        "Colmar-Houssen Airport"
    ],
    "name:deu_x_preferred":[
        "Flughafen Colmar"
    ],
    "name:eng_x_preferred":[
        "Colmar Airport"
    ],
    "name:eng_x_variant":[
        "CMR",
        "LFGA"
    ],
    "name:fra_x_preferred":[
        "a\u00e9roport de Colmar - Houssen"
    ],
    "name:hun_x_preferred":[
        "Colmar rep\u00fcl\u0151t\u00e9r"
    ],
    "name:msa_x_preferred":[
        "Lapangan Terbang Houssen"
    ],
    "name:ron_x_preferred":[
        "Aeroportul Colmar"
    ],
    "oa:elevation_ft":"628",
    "oa:type":"medium_airport",
    "woe:hierarchy":{
        "country_id":23424819,
        "county_id":12597152,
        "localadmin_id":12641935,
        "planet_id":1,
        "state_id":7153330
    },
    "wof:name":"A\u00e9roport de Colmar-Houssen",
    "wof:placetype":"campus"
},
  "geometry": {"coordinates":[7.35901,48.109901],"type":"Point"}
}