{
  "type": "Feature",
  "properties": {
    "name:ceb_x_preferred":[
        "Achutupo Airport"
    ],
    "name:eng_x_preferred":[
        "Achutupo Airport"
    ],
    "name:eng_x_variant":[
        "ACU",
        "PA-0001"
    ],
    "name:fas_x_preferred":[
        "\u0641\u0631\u0648\u062f\u06af\u0627\u0647 \u0627\u0686\u0648\u062a\u0648\u067e\u0648"
    ],
    "name:jpn_x_preferred":[
        "\u30a2\u30c1\u30e5\u30c8\u30a5\u30dd\u7a7a\u6e2f"
    ],
    "name:nob_x_preferred":[
        "Achutupo lufthavn"
    ],
    "name:ron_x_preferred":[
        "Aeroportul Achutupo"
    ],
    "name:tgk_x_preferred":[
        "\u0424\u0443\u0440\u0443\u0434\u0433\u043e\u04b3\u0438 \u0410\u0447\u0443\u0442\u0443\u043f\u043e"
    ],
    "name:zho_x_preferred":[
        "\u963f\u901f\u5716\u6ce2\u6a5f\u5834"
    ],
    "oa:elevation_ft":"1047",
    "oa:type":"small_airport",
    "wd:wordcount":55,
    "woe:hierarchy":{
        "country_id":23424924,
        "county_id":26793106,
        "localadmin_id":26793582,
        "planet_id":1,
        "state_id":2346559
    },
    "wof:name":"Achutupo Airport",
    "wof:placetype":"campus"
},
  "geometry": {"coordinates":[-77.96520200000001,8.43166],"type":"Point"}
}