{
  "type": "Feature",
  "properties": {
    "name:dan_x_preferred":[
        "Uummannaq Helistop"
    ],
    "name:deu_x_preferred":[
        "Heliport Uummannaq"
    ],
    "name:eng_x_preferred":[
        "Uummannaq Heliport"
    ],
    "name:eng_x_variant":[
        "UMD",
        "BGUM"
    ],
    "name:fas_x_preferred":[
        "\u0628\u0627\u0644\u06af\u0631\u062f\u06af\u0627\u0647 \u0627\u0648\u0645\u0627\u0646\u0627\u06a9"
    ],
    "name:jpn_x_preferred":[
        "\u30a6\u30de\u30ca\u30c3\u30af\u30fb\u30d8\u30ea\u30dd\u30fc\u30c8"
    ],
    "name:tgk_x_preferred":[
        "\u0411\u043e\u043b\u0433\u0430\u0440\u0434\u0433\u043e\u04b3\u0438 \u0423\u0443\u043c\u043c\u0430\u043d\u043d\u0430\u043a"
    ],
    "name:zho_x_preferred":[
        "\u70cf\u746a\u7d0d\u514b\u76f4\u5347\u6a5f\u5834"
    ],
    "oa:elevation_ft":"50",
    "oa:type":"heliport",
    "wd:wordcount":24,
    "woe:hierarchy":{
        "country_id":23424828,
        "planet_id":1,
        "state_id":20069858
    },
    "wof:name":"Uummannaq Airport",
    "wof:placetype":"campus"
},
  "geometry": {"coordinates":[-52.11163,70.68042800000001],"type":"Point"}
}