{
  "type": "Feature",
  "properties": {
    "name:ceb_x_preferred":[
        "Alpe d'Huez Airport"
    ],
    "name:eng_x_preferred":[
        "Alpe d'Huez Airport"
    ],
    "name:eng_x_variant":[
        "AHZ",
        "LFHU"
    ],
    "name:fas_x_preferred":[
        "\u0641\u0631\u0648\u062f\u06af\u0627\u0647 \u0622\u0644\u067e \u062f\u0626\u0648\u0632"
    ],
    "name:fra_x_preferred":[
        "Altiport de l'Alpe d'Huez"
    ],
    "name:nob_x_preferred":[
        "Alpe d'Huez lufthavn"
    ],
    "name:tgk_x_preferred":[
        "\u0424\u0443\u0440\u0443\u0434\u0433\u043e\u04b3\u0438 \u043e\u043b\u043f \u0434\u0435\u04b3\u0432\u0437"
    ],
    "name:zho_x_preferred":[
        "\u963f\u723e\u5351\u65af\u00b7\u65bc\u57c3\u6a5f\u5834"
    ],
    "oa:elevation_ft":"6102",
    "oa:type":"small_airport",
    "woe:hierarchy":{
        "country_id":23424819,
        "county_id":12597188,
        "localadmin_id":12662874,
        "planet_id":1,
        "state_id":7153329
    },
    "wof:name":"L'alpe-D'huez Airport",
    "wof:placetype":"campus"
},
  "geometry": {"coordinates":[6.08472,45.088299],"type":"Point"}
}