{
  "type": "Feature",
  "properties": {
    "name:deu_x_preferred":[
        "Lakemont"
    ],
    "wd:wordcount":51,
    "wof:name":"Lakemont",
    "wof:placetype":"neighbourhood"
},
  "geometry": {"coordinates":[-122.11326843387151,47.55303523991733],"type":"Point"}
}