{
  "type": "Feature",
  "properties": {
    "name:ceb_x_preferred":[
        "Red Lake"
    ],
    "name:eng_x_preferred":[
        "Red Lake Airport"
    ],
    "name:eng_x_variant":[
        "YRL",
        "CYRL"
    ],
    "name:fas_x_preferred":[
        "\u0641\u0631\u0648\u062f\u06af\u0627\u0647 \u0631\u062f \u0644\u06cc\u06a9"
    ],
    "name:fra_x_preferred":[
        "A\u00e9roport de Red Lake"
    ],
    "name:fra_x_variant":[
        "a\u00e9roport de Red Lake"
    ],
    "name:msa_x_preferred":[
        "Lapangan Terbang Red Lake"
    ],
    "name:pms_x_preferred":[
        "Red Lake Airport"
    ],
    "name:ron_x_preferred":[
        "Aeroportul Red Lake"
    ],
    "name:spa_x_preferred":[
        "Aeropuerto de Red Lake"
    ],
    "name:swe_x_preferred":[
        "Red Lake"
    ],
    "name:tgk_x_preferred":[
        "\u0424\u0443\u0440\u0443\u0434\u0433\u043e\u04b3\u0438 \u0440\u0430\u0434 \u043b\u0438\u043a"
    ],
    "oa:elevation_ft":"1265",
    "oa:type":"medium_airport",
    "wd:wordcount":413,
    "woe:hierarchy":{
        "country_id":23424775,
        "county_id":29375238,
        "planet_id":1,
        "state_id":2344922
    },
    "wof:name":"Red Lake Airport",
    "wof:placetype":"campus"
},
  "geometry": {"coordinates":[-93.793098,51.066898],"type":"Point"}
}