{
  "type": "Feature",
  "properties": {
    "name:ceb_x_preferred":[
        "Raufarhofn"
    ],
    "name:eng_x_preferred":[
        "Raufarh\u00f6fn Airport"
    ],
    "name:eng_x_variant":[
        "RFN",
        "BIRG"
    ],
    "name:msa_x_preferred":[
        "Lapangan Terbang Raufarhofn"
    ],
    "name:pol_x_preferred":[
        "Port lotniczy Raufarh\u00f6fn"
    ],
    "name:ron_x_preferred":[
        "Aeroportul Raufarh\u00f6fn"
    ],
    "name:swe_x_preferred":[
        "Raufarh\u00f6fns flygplats"
    ],
    "oa:elevation_ft":"39",
    "oa:type":"small_airport",
    "wd:wordcount":32,
    "woe:hierarchy":{
        "country_id":23424845,
        "planet_id":1,
        "state_id":2345699
    },
    "wof:name":"Raufarhofn Airport",
    "wof:placetype":"campus"
},
  "geometry": {"coordinates":[-15.9183,66.406403],"type":"Point"}
}