{
  "type": "Feature",
  "properties": {
    "name:ara_x_preferred":[
        "\u0645\u0637\u0627\u0631 \u0634\u064a\u0627\u0646 \u0632\u064a\u063a\u0648\u0627\u0646"
    ],
    "name:ceb_x_preferred":[
        "Xi'an Xiguan Airport"
    ],
    "name:eng_x_preferred":[
        "Xi'an Xiguan Airport"
    ],
    "name:eng_x_variant":[
        "SIA",
        "ZLSN"
    ],
    "name:jpn_x_preferred":[
        "\u897f\u5b89\u897f\u95a2\u7a7a\u6e2f"
    ],
    "name:ron_x_preferred":[
        "Aeroportul Xi'an Xiguan"
    ],
    "name:swe_x_preferred":[
        "Xi'an Xiguan Airport"
    ],
    "name:zho_x_preferred":[
        "\u897f\u5b89\u897f\u5173\u673a\u573a"
    ],
    "oa:type":"medium_airport",
    "wd:wordcount":48,
    "woe:hierarchy":{
        "country_id":23424781,
        "county_id":26198119,
        "localadmin_id":12687165,
        "planet_id":1,
        "state_id":12578015
    },
    "wof:name":"Xiguan Airport",
    "wof:placetype":"campus"
},
  "geometry": {"coordinates":[109.120003,34.376701],"type":"Point"}
}