{
  "type": "Feature",
  "properties": {
    "wof:name":"Bangholme",
    "wof:placetype":"neighbourhood"
},
  "geometry": {"coordinates":[145.19129249135042,-38.04986181588226],"type":"Point"}
}