{
  "type": "Feature",
  "properties": {
    "name:ceb_x_preferred":[
        "Peterborough Airport"
    ],
    "name:deu_x_preferred":[
        "Flughafen Peterborough"
    ],
    "name:deu_x_variant":[
        "Peterborough Airport"
    ],
    "name:eng_x_preferred":[
        "Peterborough Airport"
    ],
    "name:eng_x_variant":[
        "YPQ",
        "CYPQ"
    ],
    "name:fas_x_preferred":[
        "\u0641\u0631\u0648\u062f\u06af\u0627\u0647 \u067e\u06cc\u062a\u0631\u0632\u0628\u0648\u0631\u06af"
    ],
    "name:fra_x_preferred":[
        "Peterborough Airport"
    ],
    "name:jpn_x_preferred":[
        "\u30d4\u30fc\u30bf\u30fc\u30dc\u30ed\u7a7a\u6e2f"
    ],
    "name:msa_x_preferred":[
        "Lapangan Terbang Peterborough"
    ],
    "name:nld_x_preferred":[
        "Peterborough Airport"
    ],
    "name:pms_x_preferred":[
        "Peterborough Airport"
    ],
    "name:ron_x_preferred":[
        "Aeroportul Peterborough"
    ],
    "name:swe_x_preferred":[
        "Peterborough Airport"
    ],
    "name:tgk_x_preferred":[
        "\u0424\u0443\u0440\u0443\u0434\u0433\u043e\u04b3\u0438 \u043f\u0438\u0442\u0440\u0437\u0431\u0443\u0440\u0433"
    ],
    "oa:elevation_ft":"628",
    "oa:type":"medium_airport",
    "wd:wordcount":564,
    "woe:hierarchy":{
        "country_id":23424775,
        "county_id":29375059,
        "planet_id":1,
        "state_id":2344922
    },
    "wof:name":"Peterborough Airport",
    "wof:placetype":"campus"
},
  "geometry": {"coordinates":[-78.363297,44.23],"type":"Point"}
}