{
  "type": "Feature",
  "properties": {
    "wof:name":"Clinton Park/Tri-Community",
    "wof:placetype":"neighbourhood"
},
  "geometry": {"coordinates":[-95.26020882189616,29.74921828060249],"type":"Point"}
}