{
  "type": "Feature",
  "properties": {
    "wof:name":"South Airways",
    "wof:placetype":"neighbourhood"
},
  "geometry": {"coordinates":[-114.01467814213899,51.07786020905199],"type":"Point"}
}