{
  "type": "Feature",
  "properties": {
    "name:eng_x_preferred":[
        "Necochea Airport"
    ],
    "name:eng_x_variant":[
        "NEC",
        "SAZO"
    ],
    "name:fas_x_preferred":[
        "\u0641\u0631\u0648\u062f\u06af\u0627\u0647 \u0646\u06a9\u0648\u0686\u0627"
    ],
    "name:jpn_x_preferred":[
        "\u30cd\u30b3\u30c1\u30a7\u30a2\u7a7a\u6e2f"
    ],
    "name:msa_x_preferred":[
        "Lapangan Terbang Necochea"
    ],
    "name:spa_x_preferred":[
        "Aeropuerto Edgardo Hugo Yelpo"
    ],
    "name:tgk_x_preferred":[
        "\u0424\u0443\u0440\u0443\u0434\u0433\u043e\u04b3\u0438 \u043d\u043a\u0443\u0447\u043e"
    ],
    "oa:elevation_ft":"72",
    "oa:type":"medium_airport",
    "wd:wordcount":89,
    "woe:hierarchy":{
        "country_id":23424747,
        "county_id":20070983,
        "planet_id":1,
        "state_id":2344675
    },
    "wof:name":"Necochea Airport",
    "wof:placetype":"campus"
},
  "geometry": {"coordinates":[-58.8172,-38.4831],"type":"Point"}
}