{
  "type": "Feature",
  "properties": {
    "name:ceb_x_preferred":[
        "Lask"
    ],
    "name:eng_x_preferred":[
        "Lask Airport"
    ],
    "name:msa_x_preferred":[
        "Lapangan Terbang Lask"
    ],
    "name:pol_x_preferred":[
        "32 Baza Lotnictwa Taktycznego"
    ],
    "name:pol_x_variant":[
        "Lotnisko \u0141ask"
    ],
    "name:ron_x_preferred":[
        "Aeroportul Lask"
    ],
    "oa:elevation_ft":"633",
    "oa:type":"medium_airport",
    "wd:wordcount":192,
    "woe:hierarchy":{
        "country_id":23424923,
        "county_id":12591190,
        "localadmin_id":12617039,
        "planet_id":1,
        "state_id":12577937
    },
    "wof:name":"Lask Airport",
    "wof:placetype":"campus"
},
  "geometry": {"coordinates":[19.1792,51.5517],"type":"Point"}
}