{
  "type": "Feature",
  "properties": {
    "name:ces_x_preferred":[
        "negril"
    ],
    "name:eng_x_preferred":[
        "Negril Aerodrome"
    ],
    "name:eng_x_variant":[
        "NEG",
        "MKNG"
    ],
    "name:fas_x_preferred":[
        "\u067e\u0627\u06cc\u06af\u0627\u0647 \u0647\u0648\u0627\u06cc\u06cc \u0646\u06af\u0631\u06cc\u0644"
    ],
    "name:fra_x_preferred":[
        "a\u00e9rodrome de Negril"
    ],
    "name:jpn_x_preferred":[
        "\u30cd\u30b0\u30ea\u30eb\u98db\u884c\u5834"
    ],
    "name:msa_x_preferred":[
        "Lapangan Terbang Negril Aerodrome"
    ],
    "name:nld_x_preferred":[
        "Negril Aerodrome"
    ],
    "name:pol_x_preferred":[
        "Port lotniczy Negril"
    ],
    "oa:elevation_ft":"9",
    "oa:type":"small_airport",
    "woe:hierarchy":{
        "country_id":23424858,
        "planet_id":1,
        "state_id":2345913
    },
    "wof:name":"Negril Airport",
    "wof:placetype":"campus"
},
  "geometry": {"coordinates":[-78.3321,18.3428],"type":"Point"}
}