{
  "type": "Feature",
  "properties": {
    "gn:admin1_code":"33.0",
    "gn:asciiname":"Ohailinda",
    "gn:dem":1135,
    "gn:feature_class":"P",
    "gn:feature_code":"PPL",
    "gn:name":"Ohailinda",
    "gn:population":0,
    "gn:timezone":"Africa/Windhoek",
    "wof:name":"Ohailinda",
    "wof:placetype":"locality"
},
  "geometry": {"coordinates":[16.81667,-17.66667],"type":"Point"}
}