{
  "type": "Feature",
  "properties": {
    "name:ara_x_preferred":[
        "\u0645\u0637\u0627\u0631 \u0628\u064a\u062d\u0627\u0646"
    ],
    "name:ceb_x_preferred":[
        "Beihan Airport"
    ],
    "name:cym_x_preferred":[
        "Maes Awyr Beihan"
    ],
    "name:deu_x_preferred":[
        "Flughafen Baihan"
    ],
    "name:eng_x_preferred":[
        "Beihan Airport"
    ],
    "name:eng_x_variant":[
        "BHN",
        "OYBN"
    ],
    "name:ind_x_preferred":[
        "Bandar Udara Beihan"
    ],
    "name:jpn_x_preferred":[
        "\u30d9\u30a4\u30cf\u30f3\u7a7a\u6e2f"
    ],
    "name:msa_x_preferred":[
        "Lapangan Terbang Beihan"
    ],
    "name:pol_x_preferred":[
        "Port lotniczy Beihan"
    ],
    "name:ron_x_preferred":[
        "Aeroportul Beihan"
    ],
    "name:tha_x_preferred":[
        "\u0e17\u0e48\u0e32\u0e2d\u0e32\u0e01\u0e32\u0e28\u0e22\u0e32\u0e19\u0e1a\u0e31\u0e22\u0e2e\u0e32\u0e19"
    ],
    "name:zho_x_preferred":[
        "Beihan\u6a5f\u5834"
    ],
    "oa:elevation_ft":"3800",
    "oa:type":"medium_airport",
    "wd:wordcount":100,
    "woe:hierarchy":{
        "country_id":23425002,
        "county_id":56190160,
        "planet_id":1,
        "state_id":20070034
    },
    "wof:name":"Beihan Airport",
    "wof:placetype":"campus"
},
  "geometry": {"coordinates":[45.7201,14.782],"type":"Point"}
}