{
  "type": "Feature",
  "properties": {
    "gn:admin1_code":"37.0",
    "gn:asciiname":"Omagongati",
    "gn:dem":1101,
    "gn:feature_class":"P",
    "gn:feature_code":"PPL",
    "gn:name":"Omagongati",
    "gn:population":0,
    "gn:timezone":"Africa/Windhoek",
    "wof:name":"Omagongati",
    "wof:placetype":"locality"
},
  "geometry": {"coordinates":[15.79834,-17.91112],"type":"Point"}
}