{
  "type": "Feature",
  "properties": {
    "name:ceb_x_preferred":[
        "Nain"
    ],
    "name:eng_x_preferred":[
        "Nain Airport"
    ],
    "name:eng_x_variant":[
        "YDP",
        "CYDP"
    ],
    "name:fas_x_preferred":[
        "\u0641\u0631\u0648\u062f\u06af\u0627\u0647 \u0646\u06cc\u0646"
    ],
    "name:jpn_x_preferred":[
        "\u30cd\u30fc\u30f3\u7a7a\u6e2f"
    ],
    "name:msa_x_preferred":[
        "Lapangan Terbang Nain"
    ],
    "name:pms_x_preferred":[
        "Nain Airport"
    ],
    "name:ron_x_preferred":[
        "Aeroportul Nain"
    ],
    "name:swe_x_preferred":[
        "Nain"
    ],
    "name:tgk_x_preferred":[
        "\u0424\u0443\u0440\u0443\u0434\u0433\u043e\u04b3\u0438 \u043e\u043c\u0442\u0443\u043e\u0440\u043e"
    ],
    "oa:elevation_ft":"22",
    "oa:type":"medium_airport",
    "wd:wordcount":53,
    "woe:hierarchy":{
        "country_id":23424775,
        "county_id":29375216,
        "planet_id":1,
        "state_id":2344919
    },
    "wof:name":"Nain Airport",
    "wof:placetype":"campus"
},
  "geometry": {"coordinates":[-61.680302,56.549198],"type":"Point"}
}