{
  "type": "Feature",
  "properties": {
    "name:eng_x_preferred":[
        "Flat Bush"
    ],
    "name:fra_x_preferred":[
        "Flat Bush"
    ],
    "name:jpn_x_preferred":[
        "\u30d5\u30e9\u30c3\u30c8\u30fb\u30d6\u30c3\u30b7\u30e5"
    ],
    "name:mri_x_preferred":[
        "Flat Bush"
    ],
    "wd:wordcount":460,
    "wof:name":"Flat Bush",
    "wof:placetype":"neighbourhood"
},
  "geometry": {"coordinates":[174.92433500000001,-36.962284],"type":"Point"}
}