{
  "type": "Feature",
  "properties": {
    "gn:admin1_code":"32.0",
    "gn:asciiname":"Petrusfontein Pos",
    "gn:dem":1127,
    "gn:feature_class":"P",
    "gn:feature_code":"PPL",
    "gn:name":"Petrusfontein Pos",
    "gn:population":0,
    "gn:timezone":"Africa/Windhoek",
    "wof:name":"Petrusfontein Pos",
    "wof:placetype":"locality"
},
  "geometry": {"coordinates":[14.86667,-20.21667],"type":"Point"}
}