{
  "type": "Feature",
  "properties": {
    "name:ceb_x_preferred":[
        "Lincoln Park"
    ],
    "name:deu_x_preferred":[
        "Lincoln Park"
    ],
    "name:eng_x_preferred":[
        "Lincoln Park"
    ],
    "name:epo_x_preferred":[
        "Parko Lincoln"
    ],
    "name:eus_x_preferred":[
        "Lincoln Park"
    ],
    "name:fas_x_preferred":[
        "\u067e\u0627\u0631\u06a9 \u0644\u06cc\u0646\u06a9\u0644\u0646"
    ],
    "name:fra_x_preferred":[
        "Lincoln Park"
    ],
    "name:jpn_x_preferred":[
        "\u30ea\u30f3\u30ab\u30fc\u30f3\u30fb\u30d1\u30fc\u30af"
    ],
    "name:kor_x_preferred":[
        "\ub9c1\ucee8 \uacf5\uc6d0"
    ],
    "name:nld_x_preferred":[
        "Lincoln Park"
    ],
    "name:nob_x_preferred":[
        "Lincoln Park"
    ],
    "name:por_x_preferred":[
        "Lincoln Park"
    ],
    "name:spa_x_preferred":[
        "Lincoln Park"
    ],
    "name:zho_x_preferred":[
        "\u6797\u80af\u516c\u5712"
    ],
    "wd:wordcount":3942,
    "wof:name":"Lincoln Park",
    "wof:placetype":"neighbourhood"
},
  "geometry": {"coordinates":[-87.93978823715211,43.10807965289317],"type":"Point"}
}