{
  "type": "Feature",
  "properties": {
    "wd:wordcount":3942,
    "wof:name":"Lincoln Park",
    "wof:placetype":"neighbourhood"
},
  "geometry": {"coordinates":[-87.93978823715211,43.10807965289317],"type":"Point"}
}