{
  "type": "Feature",
  "properties": {
    "name:ceb_x_preferred":[
        "Ca\u00f1al Bajo Carlos - Hott Siebert Airport"
    ],
    "name:eng_x_preferred":[
        "Ca\u00f1al Bajo Carlos Hott Siebert Airport"
    ],
    "name:eng_x_variant":[
        "ZOS",
        "SCJO"
    ],
    "name:fas_x_preferred":[
        "\u0641\u0631\u0648\u062f\u06af\u0627\u0647 \u06a9\u0627\u0646\u0627\u0644 \u0628\u0627\u06cc\u0648 \u06a9\u0627\u0631\u0644\u0648\u0633 \u0647\u0648\u062a \u0633\u06cc\u0628\u0631\u062a"
    ],
    "name:fre_x_preferred":[
        "a\u00e9roport d'Osorno"
    ],
    "name:jpn_x_preferred":[
        "\u30ab\u30cb\u30e3\u30eb\u30fb\u30d0\u30db\u30fb\u30ab\u30eb\u30ed\u30b9\u30fb\u30db\u30c8\u30fb\u30b7\u30fc\u30d9\u30fc\u30c8\u7a7a\u6e2f"
    ],
    "name:may_x_preferred":[
        "Lapangan Terbang Canal Bajo/Carlos H Siebert"
    ],
    "name:per_x_preferred":[
        "\u0641\u0631\u0648\u062f\u06af\u0627\u0647 \u06a9\u0627\u0646\u0627\u0644 \u0628\u0627\u06cc\u0648 \u06a9\u0627\u0631\u0644\u0648\u0633 \u0647\u0648\u062a \u0633\u06cc\u0628\u0631\u062a"
    ],
    "name:pol_x_preferred":[
        "Port lotniczy Ca\u00f1al Bajo Carlos Hott Siebert"
    ],
    "name:por_x_preferred":[
        "Aeroporto Carlos Hott Siebert"
    ],
    "name:spa_x_preferred":[
        "Aer\u00f3dromo Ca\u00f1al Bajo Carlos Hott Siebert"
    ],
    "name:swe_x_preferred":[
        "Ca\u00f1al Bajo Carlos - Hott Siebert Airport"
    ],
    "name:tgk_x_preferred":[
        "\u0424\u0443\u0440\u0443\u0434\u0433\u043e\u04b3\u0438 \u043a\u043e\u043d\u043e\u043b \u0431\u043e\u044e \u043a\u043e\u0440\u043b\u0443\u0441 \u04b3\u0443\u0442 \u0441\u0438\u0431\u0440\u0442"
    ],
    "name:vie_x_preferred":[
        "S\u00e2n bay Ca\u00f1al Bajo Carlos Hott Siebert"
    ],
    "oa:elevation_ft":"187",
    "oa:type":"medium_airport",
    "woe:hierarchy":{
        "country_id":23424782,
        "county_id":26794008,
        "localadmin_id":26794168,
        "planet_id":1,
        "state_id":2345026
    },
    "wof:name":"Canal Bajo Carlos H Siebert Airport",
    "wof:placetype":"campus"
},
  "geometry": {"coordinates":[-73.060997,-40.611198],"type":"Point"}
}