{
  "type": "Feature",
  "properties": {
    "name:deu_x_preferred":[
        "Broome International Airport"
    ],
    "name:eng_x_preferred":[
        "Broome International Airport"
    ],
    "name:eng_x_variant":[
        "BME",
        "YBRM"
    ],
    "name:fas_x_preferred":[
        "\u0641\u0631\u0648\u062f\u06af\u0627\u0647 \u0628\u06cc\u0646\u200c\u0627\u0644\u0645\u0644\u0644\u06cc \u0628\u0631\u0648\u0645"
    ],
    "name:fra_x_preferred":[
        "a\u00e9roport international de Broome"
    ],
    "name:jpn_x_preferred":[
        "\u30d6\u30eb\u30fc\u30e0\u56fd\u969b\u7a7a\u6e2f"
    ],
    "name:msa_x_preferred":[
        "Lapangan Terbang Antarabangsa Broome"
    ],
    "name:nld_x_preferred":[
        "Broome International Airport"
    ],
    "name:pol_x_preferred":[
        "Port lotniczy Broome"
    ],
    "name:rus_x_preferred":[
        "\u0411\u0440\u0443\u043c"
    ],
    "name:spa_x_preferred":[
        "Aeropuerto Internacional de Broome"
    ],
    "name:swe_x_preferred":[
        "Broome International Airport"
    ],
    "name:tgk_x_preferred":[
        "\u0424\u0443\u0440\u0443\u0434\u0433\u043e\u04b3\u0438 \u0431\u0438\u043d\u200c\u0430\u043b\u043c\u0438\u043b\u0430\u043b\u04e3 \u0440\u0430\u0432\u0430\u043c"
    ],
    "name:vie_x_preferred":[
        "S\u00e2n bay qu\u1ed1c t\u1ebf Broome"
    ],
    "name:zho_x_preferred":[
        "\u5e03\u9b6f\u59c6\u570b\u969b\u6a5f\u5834"
    ],
    "oa:elevation_ft":"56",
    "oa:type":"medium_airport",
    "wd:wordcount":340,
    "woe:hierarchy":{
        "country_id":23424748,
        "county_id":55864373,
        "planet_id":1,
        "state_id":2344706,
        "suburb_id":28584824
    },
    "wof:name":"Broome International Airport",
    "wof:placetype":"campus"
},
  "geometry": {"coordinates":[122.23200199999999,-17.9447],"type":"Point"}
}