{
  "type": "Feature",
  "properties": {
    "name:eng_x_variant":[
        "WOK",
        "VE-0209"
    ],
    "oa:elevation_ft":"3250",
    "oa:type":"small_airport",
    "woe:hierarchy":{
        "country_id":23424982,
        "county_id":26804568,
        "localadmin_id":26805588,
        "planet_id":1,
        "state_id":2347682
    },
    "wof:name":"Wonken Airport",
    "wof:placetype":"campus"
},
  "geometry": {"coordinates":[-61.733334,5.25],"type":"Point"}
}