{
  "type": "Feature",
  "properties": {
    "name:dut_x_preferred":[
        "Internationale Luchthaven Ian Fleming"
    ],
    "name:eng_x_preferred":[
        "Ian Fleming International Airport"
    ],
    "name:eng_x_variant":[
        "OCJ",
        "MKBS"
    ],
    "name:fas_x_preferred":[
        "\u0641\u0631\u0648\u062f\u06af\u0627\u0647 \u0628\u0648\u0633\u06a9\u0648\u0628\u0644"
    ],
    "name:ind_x_preferred":[
        "Bandar Udara Internasional Ian Fleming"
    ],
    "name:jpn_x_preferred":[
        "\u30a4\u30a2\u30f3\u30fb\u30d5\u30ec\u30df\u30f3\u30b0\u56fd\u969b\u7a7a\u6e2f"
    ],
    "name:may_x_preferred":[
        "Lapangan Terbang Boscobel"
    ],
    "name:per_x_preferred":[
        "\u0641\u0631\u0648\u062f\u06af\u0627\u0647 \u0628\u06cc\u0646\u200c\u0627\u0644\u0645\u0644\u0644\u06cc \u06cc\u0646 \u0641\u0644\u0645\u06cc\u0646\u06af"
    ],
    "name:pol_x_preferred":[
        "Port lotniczy Boscobel"
    ],
    "name:swe_x_preferred":[
        "Ian Fleming International Airport"
    ],
    "name:tgk_x_preferred":[
        "\u0424\u0443\u0440\u0443\u0434\u0433\u043e\u04b3\u0438 \u0411\u043e\u0441\u043a\u043e\u0431\u0435\u043b"
    ],
    "oa:elevation_ft":"90",
    "oa:type":"medium_airport",
    "wd:wordcount":259,
    "woe:hierarchy":{
        "country_id":23424858,
        "planet_id":1,
        "state_id":2345921
    },
    "wof:name":"Boscobel Airport",
    "wof:placetype":"campus"
},
  "geometry": {"coordinates":[-76.969002,18.4042],"type":"Point"}
}