{
  "type": "Feature",
  "properties": {
    "name:eng_x_preferred":[
        "Manchester"
    ],
    "name:epo_x_preferred":[
        "Man\u0109estro"
    ],
    "name:hun_x_preferred":[
        "Manchester"
    ],
    "name:nld_x_preferred":[
        "Manchester"
    ],
    "name:spa_x_preferred":[
        "Manchester"
    ],
    "wof:name":"Manchester",
    "wof:placetype":"neighbourhood"
},
  "geometry": {"coordinates":[-95.278991,29.718959],"type":"Point"}
}