{
  "type": "Feature",
  "properties": {
    "name:eng_x_preferred":[
        "Manchester"
    ],
    "wof:name":"Manchester",
    "wof:placetype":"neighbourhood"
},
  "geometry": {"coordinates":[-95.27899144700818,29.71895911571213],"type":"Point"}
}