{
  "type": "Feature",
  "properties": {
    "name:che_x_preferred":[
        "\u0421\u043e\u044c\u043b\u0436\u0430-\u0413\u04c0\u0430\u043b\u0430\u043d \u0430\u044d\u0440\u043e\u043f\u043e\u0440\u0442"
    ],
    "name:eng_x_preferred":[
        "Grozny Airport"
    ],
    "name:eng_x_variant":[
        "GRV",
        "RU-0035"
    ],
    "name:fas_x_preferred":[
        "\u0641\u0631\u0648\u062f\u06af\u0627\u0647 \u06af\u0631\u0648\u0632\u0646\u06cc"
    ],
    "name:ita_x_preferred":[
        "Aeroporto di Groznyj-Severnyj"
    ],
    "name:jpn_x_preferred":[
        "\u30b0\u30ed\u30ba\u30cc\u30a4\u7a7a\u6e2f"
    ],
    "name:nld_x_preferred":[
        "Luchthaven Grozny"
    ],
    "name:nob_x_preferred":[
        "Groznyj lufthavn"
    ],
    "name:pol_x_preferred":[
        "Port lotniczy Grozny"
    ],
    "name:rus_x_preferred":[
        "\u0413\u0440\u043e\u0437\u043d\u044b\u0439"
    ],
    "name:spa_x_preferred":[
        "Aeropuerto de Grozni"
    ],
    "name:tgk_x_preferred":[
        "\u0424\u0443\u0440\u0443\u0434\u0433\u043e\u04b3\u0438 \u0433\u0440\u0443\u0437\u043d\u0438"
    ],
    "name:tur_x_preferred":[
        "Grozni Havaliman\u0131"
    ],
    "name:xmf_x_preferred":[
        "\u10d2\u10e0\u10dd\u10d6\u10dc\u10dd\u10e8 \u10d0\u10d4\u10e0\u10dd\u10de\u10dd\u10e0\u10e2\u10d8"
    ],
    "name:zho_x_preferred":[
        "\u683c\u7f85\u8332\u5c3c\u6a5f\u5834"
    ],
    "oa:type":"large_airport",
    "woe:hierarchy":{
        "country_id":23424936,
        "county_id":12597305,
        "planet_id":1,
        "state_id":2346868
    },
    "wof:name":"Groznyy Airport",
    "wof:placetype":"campus"
},
  "geometry": {"coordinates":[45.698601,43.388302],"type":"Point"}
}