{
  "type": "Feature",
  "properties": {
    "name:eng_x_preferred":[
        "Cravo Norte Airport"
    ],
    "name:eng_x_variant":[
        "RAV",
        "SKCN"
    ],
    "name:fra_x_preferred":[
        "CRAVO NORTE"
    ],
    "name:msa_x_preferred":[
        "Lapangan Terbang Cravo Norte"
    ],
    "name:ron_x_preferred":[
        "Aeroportul Cravo Norte"
    ],
    "oa:elevation_ft":"341",
    "oa:type":"small_airport",
    "woe:hierarchy":{
        "country_id":23424787,
        "county_id":26797608,
        "planet_id":1,
        "state_id":2345049
    },
    "wof:name":"Cravo Norte Airport",
    "wof:placetype":"campus"
},
  "geometry": {"coordinates":[-70.2107,6.31684],"type":"Point"}
}