{
  "type": "Feature",
  "properties": {
    "name:eng_x_preferred":[
        "Denham Aerodrome"
    ],
    "name:eng_x_variant":[
        "EGLD"
    ],
    "name:fas_x_preferred":[
        "\u0641\u0631\u0648\u062f\u06af\u0627\u0647 \u062f\u0646\u0647\u0627\u0645"
    ],
    "name:jpn_x_preferred":[
        "\u30c7\u30f3\u30cf\u30e0\u98db\u884c\u5834"
    ],
    "name:msa_x_preferred":[
        "Lapangan Terbang Denham"
    ],
    "name:pms_x_preferred":[
        "Denham Aerodrome"
    ],
    "name:tgk_x_preferred":[
        "\u0424\u0443\u0440\u0443\u0434\u0433\u043e\u04b3\u0438 \u0434\u043d\u04b3\u043e\u043c"
    ],
    "name:urd_x_preferred":[
        "\u0688\u06cc\u0646\u06c1\u0645 \u0627\u06cc\u0631\u0648\u0688\u0631\u0648\u0645"
    ],
    "oa:elevation_ft":"24",
    "oa:type":"small_airport",
    "woe:hierarchy":{
        "country_id":23424975,
        "county_id":12602166,
        "localadmin_id":12695880,
        "planet_id":1,
        "state_id":24554868
    },
    "wof:name":"Denham Aerodrome",
    "wof:placetype":"campus"
},
  "geometry": {"coordinates":[-0.513056,51.588333],"type":"Point"}
}