{
  "type": "Feature",
  "properties": {
    "name:cat_x_preferred":[
        "Forestville"
    ],
    "name:ceb_x_preferred":[
        "Forestville"
    ],
    "name:deu_x_preferred":[
        "Forestville"
    ],
    "name:est_x_preferred":[
        "Forestville"
    ],
    "name:ita_x_preferred":[
        "Forestville"
    ],
    "name:mlg_x_preferred":[
        "Forestville"
    ],
    "name:nld_x_preferred":[
        "Forestville"
    ],
    "name:pol_x_preferred":[
        "Forestville"
    ],
    "name:rus_x_preferred":[
        "\u0424\u043e\u0440\u0435\u0441\u0442\u0432\u0438\u043b\u043b"
    ],
    "name:spa_x_preferred":[
        "Forestville"
    ],
    "name:srp_x_preferred":[
        "\u0424\u043e\u0440\u0435\u0441\u0442\u0432\u0438\u043b"
    ],
    "name:swe_x_preferred":[
        "Forestville"
    ],
    "name:vol_x_preferred":[
        "Forestville"
    ],
    "wof:name":"Forestville",
    "wof:placetype":"neighbourhood"
},
  "geometry": {"coordinates":[-78.54096729684258,35.88823616627718],"type":"Point"}
}