{
  "type": "Feature",
  "properties": {
    "wof:name":"Forestville",
    "wof:placetype":"neighbourhood"
},
  "geometry": {"coordinates":[-78.54096729684258,35.88823616627718],"type":"Point"}
}