{
  "type": "Feature",
  "properties": {
    "oa:elevation_ft":"2413",
    "oa:type":"small_airport",
    "woe:hierarchy":{
        "country_id":23424977,
        "county_id":12589161,
        "planet_id":1,
        "state_id":2347586
    },
    "wof:name":"Jim Kelly Field Airport",
    "wof:placetype":"campus"
},
  "geometry": {"coordinates":[-99.775833333333,40.790555555556],"type":"Point"}
}