{
  "type": "Feature",
  "properties": {
    "name:ceb_x_preferred":[
        "Jim Kelly Field"
    ],
    "name:eng_x_preferred":[
        "Jim Kelly Field"
    ],
    "name:fas_x_preferred":[
        "\u0641\u0631\u0648\u062f\u06af\u0627\u0647 \u0635\u062d\u0631\u0627\u06cc\u06cc \u062c\u06cc\u0645 \u06a9\u0644\u06cc"
    ],
    "name:tgk_x_preferred":[
        "\u0424\u0443\u0440\u0443\u0434\u0433\u043e\u04b3\u0438 \u0441\u0430\u04b3\u0440\u043e \u04b7\u0435\u043c \u043a\u0443\u043b \u0438"
    ],
    "name:urd_x_preferred":[
        "\u062c\u0645 \u06a9\u06cc\u0644\u06cc \u0641\u06cc\u0644\u0688"
    ],
    "oa:elevation_ft":"2413",
    "oa:type":"small_airport",
    "woe:hierarchy":{
        "country_id":23424977,
        "county_id":12589161,
        "planet_id":1,
        "state_id":2347586
    },
    "wof:name":"Jim Kelly Field Airport",
    "wof:placetype":"campus"
},
  "geometry": {"coordinates":[-99.775833333333,40.790555555556],"type":"Point"}
}