{
  "type": "Feature",
  "properties": {
    "name:por_x_preferred":[
        "Kingsgate"
    ],
    "wd:wordcount":77,
    "wof:name":"Kingsgate",
    "wof:placetype":"neighbourhood"
},
  "geometry": {"coordinates":[-122.17437991481513,47.72604434933616],"type":"Point"}
}