{
  "type": "Feature",
  "properties": {
    "qs:name":"Maupiti",
    "qs:name_adm0":"Polyn\u00e9sie Fran\u00e7aise",
    "qs:name_adm1":"\u00celes sous le Vent",
    "qs:photos":191,
    "qs:photos_1k":39,
    "qs:photos_9k":3,
    "qs:photos_9r":5,
    "qs:photos_all":572,
    "qs:photos_sr":4,
    "qs:placetype":"County",
    "qs:pop_sr":"0",
    "wd:wordcount":253,
    "wof:name":"Maupiti",
    "wof:placetype":"county"
},
  "geometry": {"coordinates":[-152.27325400000001,-16.422913],"type":"Point"}
}