{
  "type": "Feature",
  "properties": {
    "label:eng_x_preferred_longname":[
        "Maupiti County"
    ],
    "label:eng_x_preferred_placetype":[
        "county"
    ],
    "name:afr_x_preferred":[
        "Maupiti"
    ],
    "name:ara_x_preferred":[
        "\u0645\u0627\u0648\u0628\u064a\u062a\u064a"
    ],
    "name:arz_x_preferred":[
        "\u0645\u0627\u0648\u0628\u064a\u062a\u0649"
    ],
    "name:cat_x_preferred":[
        "Maupiti"
    ],
    "name:ceb_x_preferred":[
        "Maupiti"
    ],
    "name:dan_x_preferred":[
        "Maupiti"
    ],
    "name:deu_x_preferred":[
        "Maupiti"
    ],
    "name:eng_x_preferred":[
        "Maupiti"
    ],
    "name:epo_x_preferred":[
        "Maupiti"
    ],
    "name:est_x_preferred":[
        "Maupiti"
    ],
    "name:fin_x_preferred":[
        "Maupiti"
    ],
    "name:fra_x_preferred":[
        "Maupiti"
    ],
    "name:glg_x_preferred":[
        "Illa Maupiti"
    ],
    "name:heb_x_preferred":[
        "\u05de\u05d0\u05d5\u05e4\u05d9\u05d8\u05d9"
    ],
    "name:hun_x_preferred":[
        "Maupiti"
    ],
    "name:ita_x_preferred":[
        "Maupiti"
    ],
    "name:jpn_x_preferred":[
        "\u30de\u30a6\u30d4\u30c6\u30a3\u5cf6"
    ],
    "name:lit_x_preferred":[
        "Maupiti"
    ],
    "name:mkd_x_preferred":[
        "\u041c\u0430\u0443\u043f\u0438\u0442\u0438"
    ],
    "name:nld_x_preferred":[
        "Maupiti"
    ],
    "name:nob_x_preferred":[
        "Maupiti"
    ],
    "name:pih_x_preferred":[
        "Maupiti"
    ],
    "name:pol_x_preferred":[
        "Maupiti"
    ],
    "name:por_x_preferred":[
        "Maupiti"
    ],
    "name:rus_x_preferred":[
        "\u041c\u0430\u0443\u043f\u0438\u0442\u0438"
    ],
    "name:spa_x_preferred":[
        "Maupiti"
    ],
    "name:swe_x_preferred":[
        "Maupiti"
    ],
    "name:tah_x_preferred":[
        "Maupiti"
    ],
    "name:zho_x_preferred":[
        "\u83ab\u76ae\u8482\u5cf6"
    ],
    "qs:name":"Maupiti",
    "qs:name_adm0":"Polyn\u00e9sie Fran\u00e7aise",
    "qs:name_adm1":"\u00celes sous le Vent",
    "qs:photos":191,
    "qs:photos_1k":39,
    "qs:photos_9k":3,
    "qs:photos_9r":5,
    "qs:photos_all":572,
    "qs:photos_sr":4,
    "qs:placetype":"County",
    "qs:pop_sr":"0",
    "wd:wordcount":253,
    "wof:name":"Maupiti",
    "wof:placetype":"county"
},
  "geometry": {"coordinates":[-152.27325400000001,-16.422913],"type":"Point"}
}