{
  "type": "Feature",
  "properties": {
    "gn:admin1_code":"21.0",
    "gn:asciiname":"Nauchas",
    "gn:dem":1783,
    "gn:feature_class":"P",
    "gn:feature_code":"PPL",
    "gn:name":"Nauchas",
    "gn:population":0,
    "gn:timezone":"Africa/Windhoek",
    "name:und_x_variant":[
        "Naukhas",
        "Nauchas"
    ],
    "wof:name":"Nauchas",
    "wof:placetype":"locality"
},
  "geometry": {"coordinates":[16.28333,-23.63333],"type":"Point"}
}