{
  "type": "Feature",
  "properties": {
    "name:ceb_x_preferred":[
        "Tortuguero Airport"
    ],
    "name:eng_x_preferred":[
        "Tortuguero Airport"
    ],
    "name:eng_x_variant":[
        "TTQ",
        "MRAO"
    ],
    "name:fas_x_preferred":[
        "\u0641\u0631\u0648\u062f\u06af\u0627\u0647 \u062a\u0631\u062a\u0648\u06af\u0631\u0648"
    ],
    "name:fra_x_preferred":[
        "a\u00e9rodrome de Tortuguero"
    ],
    "name:jpn_x_preferred":[
        "\u30c8\u30eb\u30c8\u30a5\u30b2\u30ed\u7a7a\u6e2f"
    ],
    "name:pol_x_preferred":[
        "Port lotniczy Tortuguero"
    ],
    "name:ron_x_preferred":[
        "Aeroportul Tortuguero"
    ],
    "name:swe_x_preferred":[
        "Tortuguero Airport"
    ],
    "name:tgk_x_preferred":[
        "\u0424\u0443\u0440\u0443\u0434\u0433\u043e\u04b3\u0438 \u0442\u0440\u0442\u0443\u0433\u0440\u0443"
    ],
    "oa:elevation_ft":"92",
    "oa:type":"medium_airport",
    "woe:hierarchy":{
        "country_id":23424791,
        "county_id":26808839,
        "localadmin_id":26808948,
        "planet_id":1,
        "state_id":2345086
    },
    "wof:name":"Tortuquero Airport",
    "wof:placetype":"campus"
},
  "geometry": {"coordinates":[-83.6095,10.42],"type":"Point"}
}