{"id":102537593,"type":"Feature","properties":{"edtf:cessation":"uuuu","edtf:inception":"uuuu","geom:area":0.0,"geom:area_square_m":0.0,"geom:bbox":"-83.6095,10.42,-83.6095,10.42","geom:latitude":10.571558,"geom:longitude":-83.516168,"iso:country":"","mz:hierarchy_label":1,"mz:is_current":1,"mz:min_zoom":13.0,"name:ceb_x_preferred":["Tortuguero Airport"],"name:eng_x_preferred":["Tortuguero Airport"],"name:eng_x_variant":["TTQ","MRAO"],"name:fas_x_preferred":["فرودگاه ترتوگرو"],"name:fra_x_preferred":["aérodrome de Tortuguero"],"name:jpn_x_preferred":["トルトゥゲロ空港"],"name:pol_x_preferred":["Port lotniczy Tortuguero"],"name:ron_x_preferred":["Aeroportul Tortuguero"],"name:swe_x_preferred":["Tortuguero Airport"],"name:tgk_x_preferred":["Фурудгоҳи тртугру"],"name:zho_x_preferred":["托尔图格罗机场"],"oa:elevation_ft":"92","oa:type":"medium_airport","src:geom":"ourairports","src:geom_alt":[],"woe:hierarchy":{"country_id":23424791,"county_id":26808839,"localadmin_id":26808948,"planet_id":1,"state_id":2345086},"wof:belongsto":[102191575,85632487,85670381,421171355],"wof:breaches":[],"wof:concordances":{"gp:id":12524322,"iata:code":"TTQ","icao:code":"MRAO","oa:id":"4795","wd:id":"Q6588233"},"wof:country":"","wof:geomhash":"49d57ab2a8c5b6a74ee69f6b1ea2ef0c","wof:hierarchy":[{"campus_id":102537593,"continent_id":102191575,"country_id":85632487,"county_id":421171355,"region_id":85670381}],"wof:id":102537593,"wof:lastmodified":1690922928,"wof:name":"Tortuquero Airport","wof:parent_id":-1,"wof:placetype":"campus","wof:repo":"whosonfirst-data-admin-xy","wof:superseded_by":[],"wof:supersedes":[],"wof:tags":["airport"]},"bbox":[-83.6095,10.42,-83.6095,10.42],"geometry":{"coordinates":[-83.6095,10.42],"type":"Point"}}