{
  "type": "Feature",
  "properties": {
    "name:nld_x_preferred":[
        "Port Newark\u2013Elizabeth Marine Terminal"
    ],
    "wof:name":"Port Newark",
    "wof:placetype":"neighbourhood"
},
  "geometry": {"coordinates":[-74.14953965837697,40.69377843618939],"type":"Point"}
}