{
  "type": "Feature",
  "properties": {
    "name:ceb_x_preferred":[
        "Coronation Airport"
    ],
    "name:eng_x_preferred":[
        "Coronation Airport"
    ],
    "name:eng_x_variant":[
        "YCT",
        "CYCT"
    ],
    "name:fas_x_preferred":[
        "\u0641\u0631\u0648\u062f\u06af\u0627\u0647 \u06a9\u0648\u0631\u0648\u0646\u06cc\u0634\u0646"
    ],
    "name:msa_x_preferred":[
        "Lapangan Terbang Coronation"
    ],
    "name:pms_x_preferred":[
        "Coronation Airport"
    ],
    "name:ron_x_preferred":[
        "Aeroportul Coronation"
    ],
    "name:swe_x_preferred":[
        "Coronation Airport"
    ],
    "name:tgk_x_preferred":[
        "\u0424\u0443\u0440\u0443\u0434\u0433\u043e\u04b3\u0438 \u043a\u0443\u0440\u0443\u043d\u0438\u0448\u043d"
    ],
    "oa:elevation_ft":"2595",
    "oa:type":"small_airport",
    "wd:wordcount":54,
    "woe:hierarchy":{
        "country_id":23424775,
        "county_id":29375228,
        "planet_id":1,
        "state_id":2344915
    },
    "wof:name":"Coronation Airport",
    "wof:placetype":"campus"
},
  "geometry": {"coordinates":[-111.44499999999999,52.075],"type":"Point"}
}