{
  "type": "Feature",
  "properties": {
    "name:ast_x_preferred":[
        "Aeropuertu Don Edmundo Barrios"
    ],
    "name:ceb_x_preferred":[
        "El Tigre San Tom\u00e9 Airport"
    ],
    "name:eng_x_preferred":[
        "San Tom\u00e9 Airport"
    ],
    "name:eng_x_variant":[
        "SOM",
        "SVST"
    ],
    "name:fas_x_preferred":[
        "\u0641\u0631\u0648\u062f\u06af\u0627\u0647 \u0633\u0646 \u062a\u0648\u0645\u0647"
    ],
    "name:jpn_x_preferred":[
        "\u30b5\u30f3\u30fb\u30c8\u30e1\u7a7a\u6e2f"
    ],
    "name:msa_x_preferred":[
        "Lapangan Terbang San Tome"
    ],
    "name:ron_x_preferred":[
        "Aeroportul San Tom\u00e9"
    ],
    "name:spa_x_preferred":[
        "Aeropuerto Don Edmundo Barrios"
    ],
    "name:tgk_x_preferred":[
        "\u0424\u0443\u0440\u0443\u0434\u0433\u043e\u04b3\u0438 \u0441\u0438\u043d \u0442\u0443\u043c\u04b3"
    ],
    "oa:elevation_ft":"861",
    "oa:type":"medium_airport",
    "wd:wordcount":200,
    "woe:hierarchy":{
        "country_id":23424982,
        "county_id":26804579,
        "localadmin_id":26805722,
        "planet_id":1,
        "state_id":2347678
    },
    "wof:name":"San Tome Airport",
    "wof:placetype":"campus"
},
  "geometry": {"coordinates":[-64.15108499999999,8.945147],"type":"Point"}
}