{
  "type": "Feature",
  "properties": {
    "name:deu_x_preferred":[
        "Capehart"
    ],
    "wd:wordcount":73,
    "wof:name":"Capehart",
    "wof:placetype":"neighbourhood"
},
  "geometry": {"coordinates":[-95.95441873728898,41.12536441338715],"type":"Point"}
}