{
  "type": "Feature",
  "properties": {
    "wd:wordcount":38,
    "wof:name":"Indian Village",
    "wof:placetype":"neighbourhood"
},
  "geometry": {"coordinates":[-96.69793529678823,40.77865476065846],"type":"Point"}
}