{
  "type": "Feature",
  "properties": {
    "name:bel_x_preferred":[
        "\u041d\u043e\u043a\u0441"
    ],
    "name:bre_x_preferred":[
        "Knox"
    ],
    "name:bul_x_preferred":[
        "\u041d\u043e\u043a\u0441"
    ],
    "name:cat_x_preferred":[
        "Knox"
    ],
    "name:ceb_x_preferred":[
        "Knox"
    ],
    "name:ces_x_preferred":[
        "Knox"
    ],
    "name:deu_x_preferred":[
        "Knox"
    ],
    "name:fin_x_preferred":[
        "Knox"
    ],
    "name:fra_x_preferred":[
        "Knox"
    ],
    "name:ita_x_preferred":[
        "Knox"
    ],
    "name:jpn_x_preferred":[
        "\u30ce\u30c3\u30af\u30b9"
    ],
    "name:lav_x_preferred":[
        "Knox"
    ],
    "name:nld_x_preferred":[
        "Knox"
    ],
    "name:pol_x_preferred":[
        "Knox"
    ],
    "name:por_x_preferred":[
        "Knox"
    ],
    "name:rus_x_preferred":[
        "\u041d\u043e\u043a\u0441"
    ],
    "name:slv_x_preferred":[
        "Knox"
    ],
    "name:spa_x_preferred":[
        "Knox"
    ],
    "name:srp_x_preferred":[
        "\u041d\u043e\u043a\u0441"
    ],
    "name:swe_x_preferred":[
        "Knox"
    ],
    "name:ukr_x_preferred":[
        "\u041d\u043e\u043a\u0441"
    ],
    "name:vol_x_preferred":[
        "Knox"
    ],
    "name:zho_x_preferred":[
        "\u8bfa\u514b\u65af"
    ],
    "wof:name":"Knox",
    "wof:placetype":"neighbourhood"
},
  "geometry": {"coordinates":[-96.79216819427995,32.81768038423989],"type":"Point"}
}