{
  "type": "Feature",
  "properties": {
    "wof:name":"Knox",
    "wof:placetype":"neighbourhood"
},
  "geometry": {"coordinates":[-96.79216819427995,32.81768038423989],"type":"Point"}
}