{
  "type": "Feature",
  "properties": {
    "name:ara_x_preferred":[
        "\u0645\u0637\u0627\u0631 \u0628\u064a\u0646\u063a\u062a\u0648\u0646\u063a"
    ],
    "name:chi_x_preferred":[
        "\u5c4f\u6771\u6a5f\u5834"
    ],
    "name:eng_x_preferred":[
        "Pingtung Airport"
    ],
    "name:eng_x_variant":[
        "PIF",
        "RCSQ"
    ],
    "name:jpn_x_preferred":[
        "\u5c4f\u6771\u7a7a\u6e2f"
    ],
    "name:kor_x_preferred":[
        "\ud551\ub465 \uacf5\ud56d"
    ],
    "name:may_x_preferred":[
        "Lapangan Terbang Pingtung North"
    ],
    "name:per_x_preferred":[
        "\u0641\u0631\u0648\u062f\u06af\u0627\u0647 \u067e\u06cc\u0646\u06af\u062a\u0648\u0646\u06af"
    ],
    "name:pol_x_preferred":[
        "Port lotniczy Pingdong"
    ],
    "name:tgk_x_preferred":[
        "\u0424\u0443\u0440\u0443\u0434\u0433\u043e\u04b3\u0438 \u043f\u0438\u043d\u0433\u0442\u0443\u043d\u0433"
    ],
    "name:vie_x_preferred":[
        "S\u00e2n bay B\u00ecnh \u0110\u00f4ng"
    ],
    "oa:elevation_ft":"97",
    "oa:type":"medium_airport",
    "woe:hierarchy":{
        "country_id":23424971,
        "planet_id":1,
        "state_id":2347340
    },
    "wof:name":"\u5c4f\u6771\u822a\u7a7a\u7ad9",
    "wof:placetype":"campus"
},
  "geometry": {"coordinates":[120.48200199999999,22.700199],"type":"Point"}
}