{
  "type": "Feature",
  "properties": {
    "name:ben_x_preferred":[
        "\u09aa\u09cb\u09b0\u09ac\u09a8\u09cd\u09a6\u09b0 \u09ac\u09bf\u09ae\u09be\u09a8\u09ac\u09a8\u09cd\u09a6\u09b0"
    ],
    "name:eng_x_preferred":[
        "Porbandar Airport"
    ],
    "name:eng_x_variant":[
        "PBD",
        "VAPR"
    ],
    "name:fas_x_preferred":[
        "\u0641\u0631\u0648\u062f\u06af\u0627\u0647 \u067e\u0631\u0628\u0646\u062f\u0631"
    ],
    "name:fra_x_preferred":[
        "A\u00e9roport de Porbandar"
    ],
    "name:fra_x_variant":[
        "a\u00e9roport de Porbandar"
    ],
    "name:jpn_x_preferred":[
        "\u30dd\u30eb\u30d0\u30f3\u30c0\u30eb\u7a7a\u6e2f"
    ],
    "name:mar_x_preferred":[
        "\u092a\u094b\u0930\u092c\u0902\u0926\u0930 \u0935\u093f\u092e\u093e\u0928\u0924\u0933"
    ],
    "name:msa_x_preferred":[
        "Lapangan Terbang Porbandar"
    ],
    "name:swe_x_preferred":[
        "Porbandar Airport"
    ],
    "name:tam_x_preferred":[
        "\u0baa\u0bcb\u0bb0\u0bcd\u0baa\u0ba8\u0bcd\u0ba4\u0bb0\u0bcd \u0bb5\u0bbf\u0bae\u0bbe\u0ba9 \u0ba8\u0bbf\u0bb2\u0bc8\u0baf\u0bae\u0bcd"
    ],
    "name:tgk_x_preferred":[
        "\u0424\u0443\u0440\u0443\u0434\u0433\u043e\u04b3\u0438 \u043f\u0440\u0431\u043d\u0434\u0440"
    ],
    "name:vie_x_preferred":[
        "S\u00e2n bay Porbandar"
    ],
    "oa:elevation_ft":"23",
    "oa:type":"medium_airport",
    "wd:wordcount":265,
    "woe:hierarchy":{
        "country_id":23424848,
        "county_id":28298848,
        "planet_id":1,
        "state_id":2345743
    },
    "wof:name":"Porbandar Airport",
    "wof:placetype":"campus"
},
  "geometry": {"coordinates":[69.65720399999999,21.648701],"type":"Point"}
}