{
  "type": "Feature",
  "properties": {
    "name:eng_x_variant":[
        "MSB"
    ],
    "oa:elevation_ft":"0",
    "oa:type":"seaplane_base",
    "woe:hierarchy":{
        "country_id":56042305,
        "planet_id":1
    },
    "wof:name":"Marigot Seaplane Base",
    "wof:placetype":"campus"
},
  "geometry": {"coordinates":[-63.087,18.0696],"type":"Point"}
}