{
  "type": "Feature",
  "properties": {
    "name:ceb_x_preferred":[
        "Edmundo Carvajal Airport"
    ],
    "name:eng_x_preferred":[
        "Edmundo Carvajal Airport"
    ],
    "name:eng_x_variant":[
        "XMS",
        "SEMC"
    ],
    "name:fas_x_preferred":[
        "\u0641\u0631\u0648\u062f\u06af\u0627\u0647 \u0627\u062f\u0645\u0648\u0646\u062f\u0648 \u06a9\u0631\u0648\u0627\u06cc\u0627\u0644"
    ],
    "name:fra_x_preferred":[
        "a\u00e9roport de Macas"
    ],
    "name:jpn_x_preferred":[
        "\u30de\u30ab\u30b9"
    ],
    "name:msa_x_preferred":[
        "Lapangan Terbang Crnl. E. Carvajal"
    ],
    "name:pol_x_preferred":[
        "Port lotniczy Macas"
    ],
    "name:ron_x_preferred":[
        "Aeroportul Edmundo Carvajal"
    ],
    "name:spa_x_preferred":[
        "Aeropuerto Coronel Edmundo Carvajal - Macas"
    ],
    "name:swe_x_preferred":[
        "Edmundo Carvajal Airport"
    ],
    "name:tgk_x_preferred":[
        "\u0424\u0443\u0440\u0443\u0434\u0433\u043e\u04b3\u0438 \u043e\u0434\u043c\u0443\u043d\u0434\u0443 \u043a\u0440\u0443\u0438\u0451\u043b"
    ],
    "oa:elevation_ft":"3452",
    "oa:type":"medium_airport",
    "woe:hierarchy":{
        "country_id":23424801,
        "county_id":26809585,
        "localadmin_id":26809715,
        "planet_id":1,
        "state_id":2345216
    },
    "wof:name":"Macas Airport",
    "wof:placetype":"campus"
},
  "geometry": {"coordinates":[-78.120796,-2.29917],"type":"Point"}
}