{
  "type": "Feature",
  "properties": {
    "name:ceb_x_preferred":[
        "Okhotsk Airport"
    ],
    "name:eng_x_preferred":[
        "Okhotsk Airport"
    ],
    "name:eng_x_variant":[
        "OHO",
        "UHOO"
    ],
    "name:fra_x_preferred":[
        "A\u00e9roport d'Okhotsk"
    ],
    "name:kat_x_preferred":[
        "\u10dd\u10ee\u10dd\u10e2\u10e1\u10d9\u10d8\u10e1 \u10d0\u10d4\u10e0\u10dd\u10de\u10dd\u10e0\u10e2\u10d8"
    ],
    "name:rus_x_preferred":[
        "\u041e\u0445\u043e\u0442\u0441\u043a"
    ],
    "name:zho_x_preferred":[
        "\u9102\u970d\u6b21\u514b"
    ],
    "oa:type":"medium_airport",
    "wd:wordcount":40,
    "woe:hierarchy":{
        "country_id":23424936,
        "county_id":12597752,
        "planet_id":1,
        "state_id":2346883
    },
    "wof:name":"Okhotsk Airport",
    "wof:placetype":"campus"
},
  "geometry": {"coordinates":[143.05888899999999,59.414444],"type":"Point"}
}