{
  "type": "Feature",
  "properties": {
    "name:ceb_x_preferred":[
        "Gastonia Municipal Airport"
    ],
    "name:eng_x_preferred":[
        "Gastonia Municipal Airport"
    ],
    "name:fas_x_preferred":[
        "\u0641\u0631\u0648\u062f\u06af\u0627\u0647 \u0634\u0647\u0631\u06cc \u06af\u0633\u062a\u0648\u0646\u06cc\u0627"
    ],
    "name:jpn_x_preferred":[
        "\u30ac\u30b9\u30c8\u30cb\u30a2\u5e02\u55b6\u7a7a\u6e2f"
    ],
    "name:ron_x_preferred":[
        "Aeroportul Municipal Gastonia"
    ],
    "name:tgk_x_preferred":[
        "\u0424\u0443\u0440\u0443\u0434\u0433\u043e\u04b3\u0438 \u0448\u0430\u04b3\u0440\u0438 \u0413\u0430\u0441\u0442\u043e\u043d\u0438\u0430"
    ],
    "name:urd_x_preferred":[
        "\u06af\u06cc\u0633\u0679\u0648\u0646\u06cc\u0627 \u0645\u06cc\u0648\u0646\u0633\u067e\u0644 \u0627\u06cc\u0626\u0631\u067e\u0648\u0631\u0679"
    ],
    "oa:elevation_ft":"798",
    "oa:type":"small_airport",
    "wd:wordcount":365,
    "woe:hierarchy":{
        "country_id":23424977,
        "county_id":12589409,
        "planet_id":1,
        "state_id":2347592
    },
    "wof:name":"Gastonia Municipal Airport",
    "wof:placetype":"campus"
},
  "geometry": {"coordinates":[-81.149722222222,35.202777777778],"type":"Point"}
}