{
  "type": "Feature",
  "properties": {
    "name:ceb_x_preferred":[
        "Hamilton Airport"
    ],
    "name:deu_x_preferred":[
        "Flughafen Hamilton"
    ],
    "name:eng_x_preferred":[
        "Hamilton Airport"
    ],
    "name:fas_x_preferred":[
        "\u0641\u0631\u0648\u062f\u06af\u0627\u0647 \u0647\u0645\u06cc\u0644\u062a\u0648\u0646"
    ],
    "name:ind_x_preferred":[
        "Bandar Udara Hamilton"
    ],
    "name:msa_x_preferred":[
        "Lapangan Terbang Hamilton Aero"
    ],
    "name:pol_x_preferred":[
        "Port lotniczy Hamilton"
    ],
    "name:ron_x_preferred":[
        "Aeroportul Hamilton"
    ],
    "name:rus_x_preferred":[
        "\u0413\u0430\u043c\u0438\u043b\u044c\u0442\u043e\u043d"
    ],
    "name:spa_x_preferred":[
        "Hamilton"
    ],
    "name:swe_x_preferred":[
        "Hamilton Airport"
    ],
    "name:tgk_x_preferred":[
        "\u0424\u0443\u0440\u0443\u0434\u0433\u043e\u04b3\u0438 \u04b3\u043c\u0438\u043b\u0442\u0443\u043d"
    ],
    "name:ukr_x_preferred":[
        "\u0413\u0430\u043c\u0456\u043b\u044c\u0442\u043e\u043d"
    ],
    "oa:elevation_ft":"803",
    "oa:type":"medium_airport",
    "wd:wordcount":74,
    "woe:hierarchy":{
        "country_id":23424748,
        "county_id":55863970,
        "planet_id":1,
        "state_id":2344705
    },
    "wof:name":"Hamilton Airport",
    "wof:placetype":"campus"
},
  "geometry": {"coordinates":[142.065,-37.6483],"type":"Point"}
}