{
  "type": "Feature",
  "properties": {
    "name:ceb_x_preferred":[
        "Hamilton Airport"
    ],
    "name:deu_x_preferred":[
        "Flughafen Hamilton"
    ],
    "name:ind_x_preferred":[
        "Bandar Udara Hamilton"
    ],
    "name:pol_x_preferred":[
        "Port lotniczy Hamilton"
    ],
    "name:swe_x_preferred":[
        "Hamilton Airport"
    ],
    "oa:elevation_ft":"803",
    "oa:type":"medium_airport",
    "wd:wordcount":74,
    "woe:hierarchy":{
        "country_id":23424748,
        "county_id":55863970,
        "planet_id":1,
        "state_id":2344705
    },
    "wof:name":"Hamilton Airport",
    "wof:placetype":"campus"
},
  "geometry": {"coordinates":[142.065,-37.6483],"type":"Point"}
}