{
  "type": "Feature",
  "properties": {
    "gn:admin1_code":"38.0",
    "gn:asciiname":"Onikila",
    "gn:dem":1090,
    "gn:feature_class":"P",
    "gn:feature_code":"PPL",
    "gn:name":"Onikila",
    "gn:population":0,
    "gn:timezone":"Africa/Windhoek",
    "wof:name":"Onikila",
    "wof:placetype":"locality"
},
  "geometry": {"coordinates":[16.11667000000001,-18.18333],"type":"Point"}
}