{
  "type": "Feature",
  "properties": {
    "name:ara_x_preferred":[
        "\u0645\u0637\u0627\u0631 \u0647\u0627\u0646\u063a \u0646\u062f\u064a\u0645 \u0627\u0644\u062f\u0648\u0644\u064a"
    ],
    "name:ceb_x_preferred":[
        "Hang Nadim Airport"
    ],
    "name:deu_x_preferred":[
        "Flughafen Hang Nadim"
    ],
    "name:eng_x_preferred":[
        "Hang Nadim Airport"
    ],
    "name:eng_x_variant":[
        "BTH",
        "WIDD"
    ],
    "name:fas_x_preferred":[
        "\u0641\u0631\u0648\u062f\u06af\u0627\u0647 \u0647\u0646\u06af \u0646\u0627\u062f\u06cc\u0645"
    ],
    "name:fra_x_preferred":[
        "A\u00e9roport international Hang Nadim"
    ],
    "name:fra_x_variant":[
        "a\u00e9roport de Batam"
    ],
    "name:ind_x_preferred":[
        "Bandar Udara Internasional Hang Nadim"
    ],
    "name:jav_x_preferred":[
        "Papan Anggegana Hang Nadim"
    ],
    "name:jav_x_variant":[
        "Bandhar udhara Hang Nadim"
    ],
    "name:jpn_x_preferred":[
        "\u30cf\u30f3\u30fb\u30ca\u30c7\u30a3\u30e0\u56fd\u969b\u7a7a\u6e2f"
    ],
    "name:min_x_preferred":[
        "Palabuahan udaro Internasional Hang Nadim"
    ],
    "name:msa_x_preferred":[
        "Lapangan Terbang Antarabangsa Hang Nadim"
    ],
    "name:pol_x_preferred":[
        "Port lotniczy Batam-Hang Nadim"
    ],
    "name:ron_x_preferred":[
        "Aeroportul Hang Nadim"
    ],
    "name:swe_x_preferred":[
        "Hang Nadim Airport"
    ],
    "name:tgk_x_preferred":[
        "\u0424\u0443\u0440\u0443\u0434\u0433\u043e\u04b3\u0438 \u04b3\u0430\u043d\u0433 \u043d\u043e\u0434\u0438\u043c"
    ],
    "name:vie_x_preferred":[
        "S\u00e2n bay Hang Nadim"
    ],
    "name:zho_x_preferred":[
        "\u97d3\u90a3\u4e01\u570b\u969b\u6a5f\u5834"
    ],
    "oa:elevation_ft":"126",
    "oa:type":"medium_airport",
    "wd:wordcount":579,
    "woe:hierarchy":{
        "country_id":23424846,
        "county_id":56000255,
        "planet_id":1,
        "state_id":55949082
    },
    "wof:name":"Hang Nadim Airport",
    "wof:placetype":"campus"
},
  "geometry": {"coordinates":[104.11900300000001,1.12103],"type":"Point"}
}