{
  "type": "Feature",
  "properties": {
    "name:ceb_x_preferred":[
        "Mundo Maya Airport"
    ],
    "name:deu_x_preferred":[
        "Flughafen Flores"
    ],
    "name:eng_x_variant":[
        "MCR",
        "MGMM"
    ],
    "name:fas_x_preferred":[
        "\u0641\u0631\u0648\u062f\u06af\u0627\u0647 \u0628\u06cc\u0646\u200c\u0627\u0644\u0645\u0644\u0644\u06cc \u0645\u0648\u0646\u062f\u0648 \u0645\u0627\u06cc\u0627"
    ],
    "name:fra_x_preferred":[
        "a\u00e9roport international Mundo Maya"
    ],
    "name:heb_x_preferred":[
        "\u05e0\u05de\u05dc \u05d4\u05ea\u05e2\u05d5\u05e4\u05d4 \u05d4\u05d1\u05d9\u05e0\u05dc\u05d0\u05d5\u05de\u05d9 \u05e4\u05dc\u05d5\u05e8\u05e1"
    ],
    "name:ind_x_preferred":[
        "Bandar Udara Internasional Mundo Maya"
    ],
    "name:ita_x_preferred":[
        "Aeroporto Internazionale Mundo Maya"
    ],
    "name:msa_x_preferred":[
        "Lapangan Terbang Antarabangsa Anacleto Maza Castellanos"
    ],
    "name:nob_x_preferred":[
        "Mundo Maya internasjonale lufthavn"
    ],
    "name:pol_x_preferred":[
        "Port lotniczy Flores-Mundo Maya"
    ],
    "name:por_x_preferred":[
        "Aeroporto Internacional Mundo Maya"
    ],
    "name:ron_x_preferred":[
        "Aeroportul Interna\u021bional Mundo Maya"
    ],
    "name:spa_x_preferred":[
        "Aeropuerto Internacional Mundo Maya"
    ],
    "name:swe_x_preferred":[
        "Mundo Maya Airport"
    ],
    "name:tgk_x_preferred":[
        "\u0424\u0443\u0440\u0443\u0434\u0433\u043e\u04b3\u0438 \u0431\u0438\u043d\u200c\u0430\u043b\u043c\u0438\u043b\u0430\u043b\u04e3 \u043c\u0443\u043d\u0434\u0443 \u043c\u0438\u0451"
    ],
    "name:vie_x_preferred":[
        "S\u00e2n bay qu\u1ed1c t\u1ebf Mundo Maya"
    ],
    "oa:elevation_ft":"4670",
    "oa:type":"small_airport",
    "woe:hierarchy":{
        "country_id":23424834,
        "county_id":26807061,
        "planet_id":1,
        "state_id":2345563
    },
    "wof:name":"Melchor de Mencos Airport",
    "wof:placetype":"campus"
},
  "geometry": {"coordinates":[-89.15222199999999,17.068609],"type":"Point"}
}