{
  "type": "Feature",
  "properties": {
    "name:eng_x_variant":[
        "MCR",
        "MGMM"
    ],
    "oa:elevation_ft":"4670",
    "oa:type":"small_airport",
    "woe:hierarchy":{
        "country_id":23424834,
        "county_id":26807061,
        "planet_id":1,
        "state_id":2345563
    },
    "wof:name":"Melchor de Mencos Airport",
    "wof:placetype":"campus"
},
  "geometry": {"coordinates":[-89.15222199999999,17.068609],"type":"Point"}
}