{
  "type": "Feature",
  "properties": {
    "name:cat_x_preferred":[
        "Aeroport de Tacuaremb\u00f3"
    ],
    "name:deu_x_preferred":[
        "Flughafen Tacuaremb\u00f3"
    ],
    "name:eng_x_preferred":[
        "Tacuaremb\u00f3 Airport"
    ],
    "name:eng_x_variant":[
        "TAW",
        "SUTB"
    ],
    "name:ger_x_preferred":[
        "Flughafen Tacuaremb\u00f3"
    ],
    "name:jpn_x_preferred":[
        "\u30bf\u30af\u30a2\u30ec\u30f3\u30dc\u30fc\u7a7a\u6e2f"
    ],
    "name:may_x_preferred":[
        "Lapangan Terbang Tacuarembo"
    ],
    "name:msa_x_preferred":[
        "Lapangan Terbang Tacuarembo"
    ],
    "name:nob_x_preferred":[
        "Tacuaremb\u00f3 lufthavn"
    ],
    "name:nor_x_preferred":[
        "Tacuaremb\u00f3 lufthavn"
    ],
    "name:pol_x_preferred":[
        "Port lotniczy Tacuaremb\u00f3"
    ],
    "oa:elevation_ft":"440",
    "oa:type":"small_airport",
    "wd:wordcount":70,
    "woe:hierarchy":{
        "country_id":23424979,
        "planet_id":1,
        "state_id":2347657
    },
    "wof:name":"Tacuarembo Airport",
    "wof:placetype":"campus"
},
  "geometry": {"coordinates":[-55.9258,-31.749001],"type":"Point"}
}