{
  "type": "Feature",
  "properties": {
    "name:ceb_x_preferred":[
        "Yarigu\u00edes Airport"
    ],
    "name:eng_x_preferred":[
        "Yarigu\u00edes Airport"
    ],
    "name:eng_x_variant":[
        "EJA",
        "SKEJ"
    ],
    "name:fas_x_preferred":[
        "\u0641\u0631\u0648\u062f\u06af\u0627\u0647 \u06cc\u0627\u0631\u06cc\u06af\u0648\u06cc\u0633"
    ],
    "name:jpn_x_preferred":[
        "\u30e4\u30ea\u30ae\u30a8\u30b9\u7a7a\u6e2f"
    ],
    "name:msa_x_preferred":[
        "Lapangan Terbang Yariguies"
    ],
    "name:pol_x_preferred":[
        "Port lotniczy Yariguies"
    ],
    "name:por_x_preferred":[
        "Aeroporto Yarigu\u00edes"
    ],
    "name:spa_x_preferred":[
        "Aeropuerto Yarigu\u00edes"
    ],
    "name:swe_x_preferred":[
        "Yarigu\u00edes Airport"
    ],
    "name:tgk_x_preferred":[
        "\u0424\u0443\u0440\u0443\u0434\u0433\u043e\u04b3\u0438 \u0438\u043e\u0440\u0438\u0433\u0443\u0438\u0441"
    ],
    "name:vie_x_preferred":[
        "S\u00e2n bay Yarigu\u00edes"
    ],
    "name:zho_x_preferred":[
        "Yarigu\u00edes\u6a5f\u5834"
    ],
    "oa:elevation_ft":"412",
    "oa:type":"medium_airport",
    "wd:wordcount":75,
    "woe:hierarchy":{
        "country_id":23424787,
        "county_id":26797413,
        "planet_id":1,
        "state_id":2345071
    },
    "wof:name":"Yariguies Airport",
    "wof:placetype":"campus"
},
  "geometry": {"coordinates":[-73.8068,7.02433],"type":"Point"}
}