{
  "type": "Feature",
  "properties": {
    "name:deu_x_preferred":[
        "Flughafen Dijon-Bourgogne"
    ],
    "name:eng_x_preferred":[
        "Dijon Air Base"
    ],
    "name:eng_x_variant":[
        "DIJ",
        "LFSD"
    ],
    "name:fas_x_preferred":[
        "\u067e\u0627\u06cc\u06af\u0627\u0647 \u0647\u0648\u0627\u06cc\u06cc \u062f\u06cc\u0698\u0648\u0646"
    ],
    "name:fra_x_preferred":[
        "base a\u00e9rienne 102 Dijon-Longvic"
    ],
    "name:ita_x_preferred":[
        "Base aerea di Digione"
    ],
    "name:jpn_x_preferred":[
        "\u30c7\u30a3\u30b8\u30e7\u30f3\uff1d\u30ed\u30f3\u30b0\u30f4\u30a3\u30c3\u30af\u7a7a\u8ecd\u57fa\u5730"
    ],
    "name:msa_x_preferred":[
        "Lapangan Terbang Longvic AB"
    ],
    "name:spa_x_preferred":[
        "Base A\u00e9rea de Dijon-Longvic"
    ],
    "name:tgk_x_preferred":[
        "\u041f\u043e\u0439\u0433\u043e\u04b3\u0438 \u04b3\u0430\u0432\u043e\u04e3 \u0434\u0438\u0436\u0443\u043d"
    ],
    "name:zho_x_preferred":[
        "\u7b2c\u620e\u7a7a\u8ecd\u57fa\u5730"
    ],
    "oa:elevation_ft":"726",
    "oa:type":"medium_airport",
    "woe:hierarchy":{
        "country_id":23424819,
        "county_id":12597144,
        "localadmin_id":12648390,
        "planet_id":1,
        "state_id":7153312
    },
    "wof:name":"A\u00e9roport de Dijon-Bourgogne",
    "wof:placetype":"campus"
},
  "geometry": {"coordinates":[5.09,47.268902],"type":"Point"}
}