{
  "type": "Feature",
  "properties": {
    "name:ceb_x_preferred":[
        "Moree Airport"
    ],
    "name:deu_x_preferred":[
        "Moree Airport"
    ],
    "name:eng_x_preferred":[
        "Moree Airport"
    ],
    "name:eng_x_variant":[
        "MRZ",
        "YMOR"
    ],
    "name:fas_x_preferred":[
        "\u0641\u0631\u0648\u062f\u06af\u0627\u0647 \u0645\u0648\u0631\u06cc"
    ],
    "name:fra_x_preferred":[
        "a\u00e9roport de Moree"
    ],
    "name:ita_x_preferred":[
        "aeroporto di Moree"
    ],
    "name:jpn_x_preferred":[
        "\u30e2\u30ea\u30fc\u7a7a\u6e2f"
    ],
    "name:msa_x_preferred":[
        "Lapangan Terbang Moree"
    ],
    "name:spa_x_preferred":[
        "Moree"
    ],
    "name:swe_x_preferred":[
        "Moree Airport"
    ],
    "name:tgk_x_preferred":[
        "\u0424\u0443\u0440\u0443\u0434\u0433\u043e\u04b3\u0438 \u043c\u04ef\u0440"
    ],
    "oa:elevation_ft":"701",
    "oa:type":"medium_airport",
    "wd:wordcount":942,
    "woe:hierarchy":{
        "country_id":23424748,
        "county_id":55863800,
        "planet_id":1,
        "state_id":2344700
    },
    "wof:name":"Moree Airport",
    "wof:placetype":"campus"
},
  "geometry": {"coordinates":[149.845001,-29.498899],"type":"Point"}
}