{
  "type": "Feature",
  "properties": {
    "oa:elevation_ft":"3160",
    "oa:type":"small_airport",
    "wd:wordcount":59,
    "woe:hierarchy":{
        "country_id":23424977,
        "county_id":12589106,
        "planet_id":1,
        "state_id":2347585
    },
    "wof:name":"Liberty County Airport",
    "wof:placetype":"campus"
},
  "geometry": {"coordinates":[-110.991,48.5108],"type":"Point"}
}