{
  "type": "Feature",
  "properties": {
    "name:ceb_x_preferred":[
        "Liberty County Airport"
    ],
    "name:eng_x_preferred":[
        "Liberty County Airport"
    ],
    "name:fas_x_preferred":[
        "\u0641\u0631\u0648\u062f\u06af\u0627\u0647 \u0634\u0647\u0631\u0633\u062a\u0627\u0646 \u0644\u06cc\u0628\u0631\u062a\u06cc"
    ],
    "name:tgk_x_preferred":[
        "\u0424\u0443\u0440\u0443\u0434\u0433\u043e\u04b3\u0438 \u0448\u0430\u04b3\u0440\u0438\u0441\u0442\u043e\u043d \u043b\u0438\u0431\u0440\u0442\u0438"
    ],
    "name:urd_x_preferred":[
        "\u0644\u0628\u0631\u0679\u06cc \u06a9\u0627\u0624\u0646\u0679\u06cc \u06c1\u0648\u0627\u0626\u06cc \u0627\u0688\u0627"
    ],
    "oa:elevation_ft":"3160",
    "oa:type":"small_airport",
    "wd:wordcount":59,
    "woe:hierarchy":{
        "country_id":23424977,
        "county_id":12589106,
        "planet_id":1,
        "state_id":2347585
    },
    "wof:name":"Liberty County Airport",
    "wof:placetype":"campus"
},
  "geometry": {"coordinates":[-110.991,48.5108],"type":"Point"}
}