{
  "type": "Feature",
  "properties": {
    "qs:name":"\u0627\u0644\u0631\u0641\u0627\u0639\u0629",
    "qs:name_adm0":"\u0627\u0644\u0627\u0645\u0627\u0631\u0627\u062a",
    "qs:name_adm1":"\u0631\u0627\u0633 \u0627\u0644\u062e\u064a\u0645\u0629",
    "qs:photos":40,
    "qs:photos_1k":8,
    "qs:photos_9k":1,
    "qs:photos_9r":2,
    "qs:photos_all":40,
    "qs:photos_sr":2,
    "qs:placetype":"Town",
    "qs:pop_sr":"0",
    "wof:name":"\u0627\u0644\u0631\u0641\u0627\u0639\u0629",
    "wof:placetype":"locality"
},
  "geometry": {"coordinates":[55.887047,25.73762],"type":"Point"}
}