{
  "type": "Feature",
  "properties": {
    "gn:admin1_code":"28.0",
    "gn:asciiname":"Muyoba",
    "gn:dem":939,
    "gn:feature_class":"P",
    "gn:feature_code":"PPL",
    "gn:name":"Muyoba",
    "gn:population":0,
    "gn:timezone":"Africa/Windhoek",
    "name:und_x_variant":[
        "Muyombwe",
        "Muyoba"
    ],
    "wof:name":"Muyoba",
    "wof:placetype":"locality"
},
  "geometry": {"coordinates":[24.61667000000001,-17.66667],"type":"Point"}
}