{
  "type": "Feature",
  "properties": {
    "name:ceb_x_preferred":[
        "Laverton Airport"
    ],
    "name:eng_x_preferred":[
        "Laverton Airport"
    ],
    "name:fas_x_preferred":[
        "\u0641\u0631\u0648\u062f\u06af\u0627\u0647 \u0644\u0627\u0648\u0631\u062a\u0646"
    ],
    "name:msa_x_preferred":[
        "Lapangan Terbang Laverton"
    ],
    "name:ron_x_preferred":[
        "Aeroportul Laverton"
    ],
    "name:swe_x_preferred":[
        "Laverton Airport"
    ],
    "name:tgk_x_preferred":[
        "\u0424\u0443\u0440\u0443\u0434\u0433\u043e\u04b3\u0438 \u043b\u043e\u0432\u0440\u0442\u043d"
    ],
    "oa:elevation_ft":"1530",
    "oa:type":"small_airport",
    "wd:wordcount":126,
    "woe:hierarchy":{
        "country_id":23424748,
        "county_id":55864062,
        "planet_id":1,
        "state_id":2344706
    },
    "wof:name":"Laverton Airport",
    "wof:placetype":"campus"
},
  "geometry": {"coordinates":[122.42388888889,-28.613611111111],"type":"Point"}
}