{
  "type": "Feature",
  "properties": {
    "name:deu_x_preferred":[
        "Sembach Air Base"
    ],
    "name:eng_x_preferred":[
        "Sembach Kaserne"
    ],
    "name:eng_x_variant":[
        "SEX",
        "ETAS"
    ],
    "name:fra_x_preferred":[
        "Sembach Air Base"
    ],
    "name:jpn_x_preferred":[
        "\u30bc\u30f3\u30d0\u30c3\u30cf\u7a7a\u8ecd\u57fa\u5730"
    ],
    "oa:elevation_ft":"1050",
    "oa:type":"closed",
    "woe:hierarchy":{
        "country_id":23424829,
        "county_id":12596932,
        "localadmin_id":12627423,
        "planet_id":1,
        "state_id":2345488
    },
    "wof:name":"Sembach Air Force Base",
    "wof:placetype":"campus"
},
  "geometry": {"coordinates":[7.866,49.507],"type":"Point"}
}