{
  "type": "Feature",
  "properties": {
    "gn:admin1_code":"35.0",
    "gn:asciiname":"Otjewe",
    "gn:dem":1237,
    "gn:feature_class":"P",
    "gn:feature_code":"PPL",
    "gn:name":"Otjewe",
    "gn:population":0,
    "gn:timezone":"Africa/Windhoek",
    "wof:name":"Otjewe",
    "wof:placetype":"locality"
},
  "geometry": {"coordinates":[19.53333,-23.56667],"type":"Point"}
}