{
  "type": "Feature",
  "properties": {
    "name:ceb_x_preferred":[
        "Burwash Airport"
    ],
    "name:eng_x_preferred":[
        "Burwash Airport"
    ],
    "name:eng_x_variant":[
        "YDB",
        "CYDB"
    ],
    "name:fas_x_preferred":[
        "\u0641\u0631\u0648\u062f\u06af\u0627\u0647 \u0628\u0631\u0648\u0627\u0634"
    ],
    "name:may_x_preferred":[
        "Lapangan Terbang Burwash"
    ],
    "name:msa_x_preferred":[
        "Lapangan Terbang Burwash"
    ],
    "name:per_x_preferred":[
        "\u0641\u0631\u0648\u062f\u06af\u0627\u0647 \u0628\u0631\u0648\u0627\u0634"
    ],
    "name:pms_x_preferred":[
        "Burwash Airport"
    ],
    "name:swe_x_preferred":[
        "Burwash Airport"
    ],
    "name:tgk_x_preferred":[
        "\u0424\u0443\u0440\u0443\u0434\u0433\u043e\u04b3\u0438 \u0411\u0443\u0440\u0443\u043e\u0448"
    ],
    "oa:elevation_ft":"2647",
    "oa:type":"medium_airport",
    "wd:wordcount":99,
    "woe:hierarchy":{
        "country_id":23424775,
        "county_id":29375157,
        "planet_id":1,
        "state_id":2344926
    },
    "wof:name":"Burwash Landings Airport",
    "wof:placetype":"campus"
},
  "geometry": {"coordinates":[-139.041,61.371101],"type":"Point"}
}