{
  "type": "Feature",
  "properties": {
    "name:eng_x_preferred":[
        "Fort Chipewyan Airport"
    ],
    "name:eng_x_variant":[
        "YPY",
        "CYPY"
    ],
    "name:fas_x_preferred":[
        "\u0641\u0631\u0648\u062f\u06af\u0627\u0647 \u0641\u0648\u0631\u062a \u0686\u06cc\u067e\u0648\u0627\u06cc\u0646"
    ],
    "name:msa_x_preferred":[
        "Lapangan Terbang Ft Chipewyan"
    ],
    "name:pms_x_preferred":[
        "Fort Chipewyan Airport"
    ],
    "name:pol_x_preferred":[
        "Port lotniczy Fort Chipewyan"
    ],
    "name:ron_x_preferred":[
        "Aeroportul Fort Chipewyan"
    ],
    "name:tgk_x_preferred":[
        "\u0424\u0443\u0440\u0443\u0434\u0433\u043e\u04b3\u0438 \u0444\u0443\u0440\u0442 \u0447\u0438\u043f\u0443\u043e\u0438\u043d"
    ],
    "name:zho_x_preferred":[
        "\u5947\u4f69\u7ef4\u6069\u5821\u673a\u573a"
    ],
    "oa:elevation_ft":"761",
    "oa:type":"medium_airport",
    "wd:wordcount":64,
    "woe:hierarchy":{
        "country_id":23424775,
        "county_id":29375228,
        "planet_id":1,
        "state_id":2344915
    },
    "wof:name":"Fort Chipewyan Airport",
    "wof:placetype":"campus"
},
  "geometry": {"coordinates":[-111.11799999999999,58.7675],"type":"Point"}
}