{
  "type": "Feature",
  "properties": {
    "name:arz_x_preferred":[
        "\u0645\u0637\u0627\u0631 \u0633\u0627\u0646\u062a\u0627 \u0628\u0648\u0644\u0627"
    ],
    "name:ceb_x_preferred":[
        "Santa Paula Airport"
    ],
    "name:eng_x_preferred":[
        "Santa Paula Airport"
    ],
    "name:eng_x_variant":[
        "SZP",
        "KSZP"
    ],
    "name:fas_x_preferred":[
        "\u0641\u0631\u0648\u062f\u06af\u0627\u0647 \u0633\u0627\u0646\u062a\u0627 \u067e\u0627\u0626\u0648\u0644\u0627\u060c \u06a9\u0627\u0644\u06cc\u0641\u0631\u0646\u06cc\u0627"
    ],
    "name:fas_x_variant":[
        "\u0641\u0631\u0648\u062f\u06af\u0627\u0647 \u0633\u0627\u0646\u062a\u0627 \u067e\u0627\u0626\u0648\u0644\u0627"
    ],
    "name:ron_x_preferred":[
        "Aeroportul Santa Paula"
    ],
    "name:spa_x_preferred":[
        "Aeropuerto de Santa Paula"
    ],
    "name:tgk_x_preferred":[
        "\u0424\u0443\u0440\u0443\u0434\u0433\u043e\u04b3\u0438 \u0421\u0430\u043d\u0442\u0430 \u041f\u0430\u0443\u043b\u0430"
    ],
    "name:tgk_x_variant":[
        "\u0424\u0443\u0440\u0443\u0434\u0433\u043e\u04b3\u0438 \u0441\u043e\u043d\u0442\u043e \u043f\u043e\u0435\u04b3\u0432\u043b\u043e"
    ],
    "name:urd_x_preferred":[
        "\u0633\u0627\u0646\u062a\u0627 \u067e\u0627\u0648\u0644\u0627 \u06c1\u0648\u0627\u0626\u06cc \u0627\u0688\u0627"
    ],
    "oa:elevation_ft":"243",
    "oa:type":"small_airport",
    "wd:wordcount":1108,
    "woe:hierarchy":{
        "country_id":23424977,
        "county_id":12587725,
        "planet_id":1,
        "state_id":2347563
    },
    "wof:name":"Santa Paula Airport",
    "wof:placetype":"campus"
},
  "geometry": {"coordinates":[-119.061667,34.346944],"type":"Point"}
}