{
  "type": "Feature",
  "properties": {
    "wof:name":"Encanto Terrace",
    "wof:placetype":"neighbourhood"
},
  "geometry": {"coordinates":[-112.09577431202845,33.48234362332254],"type":"Point"}
}