{
  "type": "Feature",
  "properties": {
    "wof:name":"Wahl Park",
    "wof:placetype":"neighbourhood"
},
  "geometry": {"coordinates":[-87.97429219128043,43.10223090954129],"type":"Point"}
}