{
  "type": "Feature",
  "properties": {
    "name:ceb_x_preferred":[
        "Buffalo-Lancaster Regional Airport"
    ],
    "name:eng_x_preferred":[
        "Buffalo-Lancaster Regional Airport"
    ],
    "name:fas_x_preferred":[
        "\u0641\u0631\u0648\u062f\u06af\u0627\u0647 \u0628\u0648\u0641\u0627\u0644\u0648"
    ],
    "name:jpn_x_preferred":[
        "\u30d0\u30c3\u30d5\u30a1\u30ed\u30fc\uff1d\u30e9\u30f3\u30ab\u30b9\u30bf\u30fc\u7a7a\u6e2f"
    ],
    "name:ron_x_preferred":[
        "Aeroportul Regional Buffalo-Lancaster"
    ],
    "name:tgk_x_preferred":[
        "\u0424\u0443\u0440\u0443\u0434\u0433\u043e\u04b3\u0438 \u041c\u0438\u043d\u0442\u0430\u049b\u0430\u0432\u0438\u0438 \u0411\u0443\u0444\u0444\u0430\u043b\u043e-\u041b\u0430\u043d\u043a\u0430\u0441\u0442\u0435\u0440"
    ],
    "name:tgk_x_variant":[
        "\u0424\u0443\u0440\u0443\u0434\u0433\u043e\u04b3\u0438 \u0431\u0443\u0444\u043e\u043b\u0443"
    ],
    "name:urd_x_preferred":[
        "\u0628\u0641\u06cc\u0644\u0648-\u0644\u0646\u06a9\u0627\u0633\u0679\u0631 \u0631\u06cc\u062c\u0646\u0644 \u0627\u06cc\u0626\u0631\u067e\u0648\u0631\u0679"
    ],
    "oa:elevation_ft":"750",
    "oa:type":"small_airport",
    "wd:wordcount":303,
    "woe:hierarchy":{
        "country_id":23424977,
        "county_id":12589326,
        "planet_id":1,
        "state_id":2347591
    },
    "wof:name":"Buffalo Lancaster Airport",
    "wof:placetype":"campus"
},
  "geometry": {"coordinates":[-78.612222222222,42.922222222222],"type":"Point"}
}