{
  "type": "Feature",
  "properties": {
    "name:fas_x_preferred":[
        "\u0641\u0631\u0648\u062f\u06af\u0627\u0647 \u0628\u0648\u0641\u0627\u0644\u0648"
    ],
    "name:tgk_x_preferred":[
        "\u0424\u0443\u0440\u0443\u0434\u0433\u043e\u04b3\u0438 \u041c\u0438\u043d\u0442\u0430\u049b\u0430\u0432\u0438\u0438 \u0411\u0443\u0444\u0444\u0430\u043b\u043e-\u041b\u0430\u043d\u043a\u0430\u0441\u0442\u0435\u0440"
    ],
    "oa:elevation_ft":"750",
    "oa:type":"small_airport",
    "wd:wordcount":303,
    "woe:hierarchy":{
        "country_id":23424977,
        "county_id":12589326,
        "planet_id":1,
        "state_id":2347591
    },
    "wof:name":"Buffalo Lancaster Airport",
    "wof:placetype":"campus"
},
  "geometry": {"coordinates":[-78.612222222222,42.922222222222],"type":"Point"}
}