{
  "type": "Feature",
  "properties": {
    "gn:admin1_code":"28.0",
    "gn:asciiname":"Biro",
    "gn:dem":1032,
    "gn:feature_class":"P",
    "gn:feature_code":"PPL",
    "gn:name":"Biro",
    "gn:population":0,
    "gn:timezone":"Africa/Windhoek",
    "wof:name":"Biro",
    "wof:placetype":"locality"
},
  "geometry": {"coordinates":[21.31667,-17.98333],"type":"Point"}
}