{
  "type": "Feature",
  "properties": {
    "wof:name":"Kops Park",
    "wof:placetype":"neighbourhood"
},
  "geometry": {"coordinates":[-88.01846640784271,43.07883035646526],"type":"Point"}
}