{
  "type": "Feature",
  "properties": {
    "name:ara_x_preferred":[
        "\u0642\u0627\u0639\u062f\u0629 \u0627\u0644\u0645\u0644\u0643 \u0639\u0628\u062f \u0627\u0644\u0639\u0632\u064a\u0632 \u0627\u0644\u062c\u0648\u064a\u0629"
    ],
    "name:ben_x_preferred":[
        "\u09ac\u09be\u09a6\u09b6\u09be\u09b9 \u0986\u09ac\u09cd\u09a6\u09c1\u09b2 \u0986\u099c\u09bf\u099c \u09ac\u09bf\u09ae\u09be\u09a8 \u0998\u09be\u099f\u09bf"
    ],
    "name:ceb_x_preferred":[
        "King Abdulaziz Air Base"
    ],
    "name:eng_x_preferred":[
        "King Abdulaziz Air Base"
    ],
    "name:eng_x_variant":[
        "DHA",
        "OEDR"
    ],
    "name:fas_x_preferred":[
        "\u0641\u0631\u0648\u062f\u06af\u0627\u0647 \u0628\u06cc\u0646\u200c\u0627\u0644\u0645\u0644\u0644\u06cc \u0638\u0647\u0631\u0627\u0646"
    ],
    "name:jpn_x_preferred":[
        "\u30ad\u30f3\u30b0\u30fb\u30a2\u30d6\u30c9\u30e9\u30a2\u30b8\u30ba\u98db\u884c\u5834"
    ],
    "name:msa_x_preferred":[
        "Pangkalan Udara Raja Abdulaziz"
    ],
    "name:tgk_x_preferred":[
        "\u0424\u0443\u0440\u0443\u0434\u0433\u043e\u04b3\u0438 \u0431\u0438\u043d\u200c\u0430\u043b\u043c\u0438\u043b\u0430\u043b\u04e3 \u0437\u04b3\u0440\u043e\u043d"
    ],
    "name:urd_x_preferred":[
        "\u0634\u0627\u06c1 \u0639\u0628\u062f\u0627\u0644\u0639\u0632\u06cc\u0632 \u0627\u06cc\u0626\u0631 \u0628\u06cc\u0633"
    ],
    "name:zho_x_preferred":[
        "Abdulaziz\u570b\u738b\u7a7a\u8ecd\u57fa\u5730"
    ],
    "oa:elevation_ft":"84",
    "oa:type":"large_airport",
    "woe:hierarchy":{
        "country_id":23424938,
        "county_id":56120200,
        "planet_id":1,
        "state_id":2346954
    },
    "wof:name":"Dhahran International Airport",
    "wof:placetype":"campus"
},
  "geometry": {"coordinates":[50.152,26.2654],"type":"Point"}
}