{
  "type": "Feature",
  "properties": {
    "name:eng_x_variant":[
        "DHA",
        "OEDR"
    ],
    "oa:elevation_ft":"84",
    "oa:type":"large_airport",
    "woe:hierarchy":{
        "country_id":23424938,
        "county_id":56120200,
        "planet_id":1,
        "state_id":2346954
    },
    "wof:name":"Dhahran International Airport",
    "wof:placetype":"campus"
},
  "geometry": {"coordinates":[50.152,26.2654],"type":"Point"}
}