{
  "type": "Feature",
  "properties": {
    "name:dan_x_preferred":[
        "Mo i Rana Lufthavn"
    ],
    "name:deu_x_preferred":[
        "Flughafen Mo i Rana"
    ],
    "name:dut_x_preferred":[
        "Luchthaven Mo i Rana Rossvoll"
    ],
    "name:eng_x_preferred":[
        "Mo i Rana Airport"
    ],
    "name:eng_x_variant":[
        "MQN",
        "ENRA"
    ],
    "name:fas_x_preferred":[
        "\u0641\u0631\u0648\u062f\u06af\u0627\u0647 \u0645\u0648 \u0627\u06cc \u0631\u0627\u0646\u0627"
    ],
    "name:fre_x_preferred":[
        "a\u00e9roport de Mo i Rana"
    ],
    "name:ger_x_preferred":[
        "Flughafen Mo i Rana"
    ],
    "name:ita_x_preferred":[
        "aeroporto di Mo i Rana"
    ],
    "name:jpn_x_preferred":[
        "\u30e2\u30fc\u30fb\u30a4\u30fb\u30e9\u30fc\u30ca\u7a7a\u6e2f"
    ],
    "name:may_x_preferred":[
        "Lapangan Terbang Rossvoll"
    ],
    "name:nno_x_preferred":[
        "Mo i Rana lufthamn"
    ],
    "name:nob_x_preferred":[
        "Mo i Rana lufthavn"
    ],
    "name:nor_x_preferred":[
        "Mo i Rana lufthavn"
    ],
    "name:per_x_preferred":[
        "\u0641\u0631\u0648\u062f\u06af\u0627\u0647 \u0645\u0648 \u0627\u06cc \u0631\u0627\u0646\u0627"
    ],
    "name:pol_x_preferred":[
        "Port lotniczy Mo i Rana"
    ],
    "name:spa_x_preferred":[
        "Aeropuerto de Mo i Rana-R\u00f8ssvoll"
    ],
    "name:swe_x_preferred":[
        "Mo i Rana flygplats"
    ],
    "name:tgk_x_preferred":[
        "\u0424\u0443\u0440\u0443\u0434\u0433\u043e\u04b3\u0438 \u043c\u04ef \u0438\u0439 \u0440\u043e\u043d\u043e"
    ],
    "name:vie_x_preferred":[
        "S\u00e2n bay Mo i Rana"
    ],
    "oa:elevation_ft":"229",
    "oa:type":"medium_airport",
    "wd:wordcount":335,
    "woe:hierarchy":{
        "country_id":23424910,
        "county_id":12592661,
        "planet_id":1,
        "state_id":2346392
    },
    "wof:name":"Mo I Rana Lufthavn Rossvoll",
    "wof:placetype":"campus"
},
  "geometry": {"coordinates":[14.3014,66.363899],"type":"Point"}
}