{
  "type": "Feature",
  "properties": {
    "name:eng_x_preferred":[
        "Rosario Seaplane Base"
    ],
    "name:eng_x_variant":[
        "RSJ",
        "W49"
    ],
    "name:fas_x_preferred":[
        "\u0641\u0631\u0648\u062f\u06af\u0627\u0647 \u062f\u0631\u06cc\u0627\u06cc\u06cc \u0631\u0633\u0631\u06cc\u0648"
    ],
    "name:tgk_x_preferred":[
        "\u0424\u0443\u0440\u0443\u0434\u0433\u043e\u04b3\u0438 \u0434\u0430\u0440\u0451 \u0440\u0441\u0440\u044e"
    ],
    "name:urd_x_preferred":[
        "\u0631\u0648\u0633\u0627\u0631\u06cc\u0648 \u0633\u06cc \u067e\u0644\u06cc\u0646 \u0628\u06cc\u0633"
    ],
    "oa:type":"seaplane_base",
    "wd:wordcount":180,
    "woe:hierarchy":{
        "country_id":23424977,
        "county_id":12590467,
        "planet_id":1,
        "state_id":2347606
    },
    "wof:name":"Rosario Seaplane Base",
    "wof:placetype":"campus"
},
  "geometry": {"coordinates":[-122.86799600000001,48.645699],"type":"Point"}
}