{
  "type": "Feature",
  "properties": {
    "name:deu_x_preferred":[
        "Flughafen Merville-Calonne"
    ],
    "name:eng_x_preferred":[
        "Merville \u2013 Calonne Airport"
    ],
    "name:eng_x_variant":[
        "HZB",
        "LFQT"
    ],
    "name:fra_x_preferred":[
        "A\u00e9roport de Merville - Calonne"
    ],
    "name:fra_x_variant":[
        "a\u00e9roport de Merville - Calonne"
    ],
    "name:msa_x_preferred":[
        "Lapangan Terbang Calonne"
    ],
    "oa:elevation_ft":"61",
    "oa:type":"medium_airport",
    "woe:hierarchy":{
        "country_id":23424819,
        "county_id":12597175,
        "localadmin_id":12666613,
        "planet_id":1,
        "state_id":7153324
    },
    "wof:name":"A\u00e9roport Merville-Calonne",
    "wof:placetype":"campus"
},
  "geometry": {"coordinates":[2.64224,50.618401],"type":"Point"}
}