{
  "type": "Feature",
  "properties": {
    "name:eng_x_variant":[
        "HIS",
        "AU-HIS"
    ],
    "oa:type":"seaplane_base",
    "woe:hierarchy":{
        "country_id":23424748,
        "planet_id":1,
        "state_id":2344702
    },
    "wof:name":"Hayman Island Airport",
    "wof:placetype":"campus"
},
  "geometry": {"coordinates":[148.88099700000001,-20.059999],"type":"Point"}
}