{
  "type": "Feature",
  "properties": {
    "name:cym_x_preferred":[
        "Maes Awyr Rhyngwladol Charles Kirkconnell"
    ],
    "name:eng_x_preferred":[
        "Gerrard Smith International Airport"
    ],
    "name:eng_x_variant":[
        "CYB",
        "MWCB"
    ],
    "name:fas_x_preferred":[
        "\u0641\u0631\u0648\u062f\u06af\u0627\u0647 \u0628\u06cc\u0646\u200c\u0627\u0644\u0645\u0644\u0644\u06cc \u062c\u0631\u0627\u0631\u062f \u0627\u0633\u0645\u06cc\u062a"
    ],
    "name:fin_x_preferred":[
        "Charles Kirkconnellin kansainv\u00e4linen lentoasema"
    ],
    "name:fra_x_preferred":[
        "a\u00e9roport Charles Kirkconnell"
    ],
    "name:heb_x_preferred":[
        "\u05e7\u05d9\u05e8\u05e7\u05d5\u05e0\u05dc"
    ],
    "name:ind_x_preferred":[
        "Bandar Udara Internasional Gerrard Smith"
    ],
    "name:jpn_x_preferred":[
        "\u30ad\u30e3\u30d7\u30c6\u30f3\u30fb\u30c1\u30e3\u30fc\u30eb\u30ba\u30fb\u30ab\u30fc\u30af\u30b3\u30fc\u30cd\u30eb\u56fd\u969b\u7a7a\u6e2f"
    ],
    "name:msa_x_preferred":[
        "Lapangan Terbang Antarabangsa Gerrard-Smith"
    ],
    "name:nob_x_preferred":[
        "Charles Kirkconnell internasjonale lufthavn"
    ],
    "name:pol_x_preferred":[
        "Port lotniczy Gerrard Smith"
    ],
    "name:ron_x_preferred":[
        "Aeroportul Charles Kirkconnell"
    ],
    "name:spa_x_preferred":[
        "Aeropuerto Internacional Charles Kirkconnell"
    ],
    "name:swe_x_preferred":[
        "Sir Charles Kirkconnell International Airport"
    ],
    "name:tgk_x_preferred":[
        "\u0424\u0443\u0440\u0443\u0434\u0433\u043e\u04b3\u0438 \u0431\u0438\u043d\u200c\u0430\u043b\u043c\u0438\u043b\u0430\u043b\u04e3 \u04b7\u0440\u043e\u0440\u0434 \u0438\u0441\u043c\u0435\u0442"
    ],
    "name:tur_x_preferred":[
        "Charles Kirkconnell Uluslararas\u0131 Havaliman\u0131"
    ],
    "name:zho_x_preferred":[
        "Charles Kirkconnell\u570b\u969b\u6a5f\u5834"
    ],
    "oa:elevation_ft":"8",
    "oa:type":"medium_airport",
    "woe:hierarchy":{
        "country_id":23424783,
        "planet_id":1,
        "state_id":56189781
    },
    "wof:name":"Gerrard Smith Airport",
    "wof:placetype":"campus"
},
  "geometry": {"coordinates":[-79.882797,19.687],"type":"Point"}
}