{
  "type": "Feature",
  "properties": {
    "gn:admin1_code":"33.0",
    "gn:asciiname":"Omulonga",
    "gn:dem":1146,
    "gn:feature_class":"P",
    "gn:feature_code":"PPL",
    "gn:name":"Omulonga",
    "gn:population":0,
    "gn:timezone":"Africa/Windhoek",
    "wof:name":"Omulonga",
    "wof:placetype":"locality"
},
  "geometry": {"coordinates":[16.86667000000001,-17.56667],"type":"Point"}
}