{
  "type": "Feature",
  "properties": {
    "name:ceb_x_preferred":[
        "Butterworth Airport"
    ],
    "name:deu_x_preferred":[
        "RMAF Base Butterworth"
    ],
    "name:eng_x_preferred":[
        "RMAF Butterworth"
    ],
    "name:eng_x_variant":[
        "BWH",
        "WMKB"
    ],
    "name:fas_x_preferred":[
        "\u0641\u0631\u0648\u062f\u06af\u0627\u0647 \u0622\u0631\u0627\u0645\u200c\u0627\u06cc\u200c\u0627\u0641 \u0628\u0627\u062a\u0631\u0648\u0648\u0631\u062b"
    ],
    "name:fra_x_preferred":[
        "base a\u00e9rienne de Butterworth"
    ],
    "name:jpn_x_preferred":[
        "\u30d0\u30bf\u30fc\u30ef\u30fc\u30b9\u7a7a\u8ecd\u57fa\u5730"
    ],
    "name:msa_x_preferred":[
        "TUDM Butterworth"
    ],
    "name:por_x_preferred":[
        "Base A\u00e9rea de Butterworth"
    ],
    "name:tgk_x_preferred":[
        "\u0424\u0443\u0440\u0443\u0434\u0433\u043e\u04b3\u0438 \u043e\u0440\u043e\u043c\u200c\u0438\u0439\u200c\u0443\u0444 \u0431\u043e\u0442\u0440\u0443\u0432\u0440\u0441"
    ],
    "name:zho_x_preferred":[
        "\u5317\u6d77\u99ac\u4f86\u897f\u4e9e\u7687\u5bb6\u7a7a\u8ecd\u57fa\u5730"
    ],
    "oa:elevation_ft":"11",
    "oa:type":"medium_airport",
    "woe:hierarchy":{
        "country_id":23424901,
        "county_id":56013561,
        "localadmin_id":56014073,
        "planet_id":1,
        "state_id":2346304
    },
    "wof:name":"Butterworth Airport",
    "wof:placetype":"campus"
},
  "geometry": {"coordinates":[100.39099899999999,5.46592],"type":"Point"}
}