{
  "type": "Feature",
  "properties": {
    "name:ceb_x_preferred":[
        "Okondja Airport"
    ],
    "name:eng_x_preferred":[
        "Okondja Airport"
    ],
    "name:eng_x_variant":[
        "OKN",
        "FOGQ"
    ],
    "name:fra_x_preferred":[
        "a\u00e9roport d'Okondja"
    ],
    "name:msa_x_preferred":[
        "Lapangan Terbang Okondja"
    ],
    "name:ron_x_preferred":[
        "Aeroportul Okondja"
    ],
    "name:swe_x_preferred":[
        "Okondja Airport"
    ],
    "oa:elevation_ft":"1325",
    "oa:type":"medium_airport",
    "wd:wordcount":53,
    "woe:hierarchy":{
        "country_id":23424822,
        "county_id":55998457,
        "planet_id":1,
        "state_id":2345450
    },
    "wof:name":"Okondja Airport",
    "wof:placetype":"campus"
},
  "geometry": {"coordinates":[13.6731,-0.665214],"type":"Point"}
}