{
  "type": "Feature",
  "properties": {
    "name:eng_x_variant":[
        "ZFU",
        "SSUO"
    ],
    "oa:elevation_ft":"2641",
    "oa:type":"heliport",
    "woe:hierarchy":{
        "country_id":23424768,
        "county_id":12581852,
        "planet_id":1,
        "state_id":2344868
    },
    "wof:name":"Aeroporto Aruja",
    "wof:placetype":"campus"
},
  "geometry": {"coordinates":[-46.330555,-23.408611],"type":"Point"}
}