{
  "type": "Feature",
  "properties": {
    "gn:admin1_code":"31.0",
    "gn:asciiname":"Aurus",
    "gn:dem":-28,
    "gn:feature_class":"P",
    "gn:feature_code":"PPL",
    "gn:name":"Aurus",
    "gn:population":0,
    "gn:timezone":"Africa/Windhoek",
    "wof:name":"Aurus",
    "wof:placetype":"locality"
},
  "geometry": {"coordinates":[14.98333,-26.11667000000001],"type":"Point"}
}