{
  "type": "Feature",
  "properties": {
    "wd:wordcount":5109,
    "wof:name":"Central Business District",
    "wof:placetype":"neighbourhood"
},
  "geometry": {"coordinates":[-84.51447270854666,39.1024573842009],"type":"Point"}
}