{
  "type": "Feature",
  "properties": {
    "gn:admin1_code":"21.0",
    "gn:asciiname":"Dagbreek",
    "gn:dem":909,
    "gn:feature_class":"P",
    "gn:feature_code":"PPL",
    "gn:name":"Dagbreek",
    "gn:population":0,
    "gn:timezone":"Africa/Windhoek",
    "wof:name":"Dagbreek",
    "wof:placetype":"locality"
},
  "geometry": {"coordinates":[15.91667,-23.48333],"type":"Point"}
}