{
  "type": "Feature",
  "properties": {
    "name:deu_x_preferred":[
        "Flughafen Phitsanulok"
    ],
    "name:eng_x_preferred":[
        "Phitsanulok Airport"
    ],
    "name:eng_x_variant":[
        "PHS",
        "VTPP"
    ],
    "name:fas_x_preferred":[
        "\u0641\u0631\u0648\u062f\u06af\u0627\u0647 \u0641\u06cc\u062a\u0633\u0627\u0646\u0648\u0644\u0648\u06a9"
    ],
    "name:ind_x_preferred":[
        "Bandar Udara Phitsanulok"
    ],
    "name:jpn_x_preferred":[
        "\u30d4\u30c3\u30b5\u30cc\u30ed\u30fc\u30af\u7a7a\u6e2f"
    ],
    "name:kor_x_preferred":[
        "\ud54f\uc0ac\ub20c\ub85d \uacf5\ud56d"
    ],
    "name:msa_x_preferred":[
        "Lapangan Terbang Phitsanulok"
    ],
    "name:pol_x_preferred":[
        "Port lotniczy Phitsanulok"
    ],
    "name:ron_x_preferred":[
        "Aeroportul Phitsanulok"
    ],
    "name:rus_x_preferred":[
        "\u041f\u0445\u0438\u0442\u0441\u0430\u043d\u0443\u043b\u043e\u043a"
    ],
    "name:tgk_x_preferred":[
        "\u0424\u0443\u0440\u0443\u0434\u0433\u043e\u04b3\u0438 \u0444\u0438\u0442\u0441\u043e\u043d\u0443\u043b\u0443\u043a"
    ],
    "name:tha_x_preferred":[
        "\u0e17\u0e48\u0e32\u0e2d\u0e32\u0e01\u0e32\u0e28\u0e22\u0e32\u0e19\u0e1e\u0e34\u0e29\u0e13\u0e38\u0e42\u0e25\u0e01"
    ],
    "name:vie_x_preferred":[
        "S\u00e2n bay Phitsanulok"
    ],
    "name:wuu_x_preferred":[
        "\u5f6d\u4e16\u6d1b\u673a\u573a"
    ],
    "name:zho_x_preferred":[
        "\u5f6d\u4e16\u6d1b\u6a5f\u5834"
    ],
    "oa:elevation_ft":"154",
    "oa:type":"medium_airport",
    "wd:wordcount":133,
    "woe:hierarchy":{
        "country_id":23424960,
        "county_id":28340937,
        "planet_id":1,
        "state_id":2347139
    },
    "wof:name":"Phitsanulok Airport",
    "wof:placetype":"campus"
},
  "geometry": {"coordinates":[100.278999,16.7829],"type":"Point"}
}