{
  "type": "Feature",
  "properties": {
    "name:cat_x_preferred":[
        "Oak Park"
    ],
    "name:ceb_x_preferred":[
        "Oak Park"
    ],
    "name:ces_x_preferred":[
        "Oak Park"
    ],
    "name:dan_x_preferred":[
        "Oak Park"
    ],
    "name:deu_x_preferred":[
        "Oak Park"
    ],
    "name:fra_x_preferred":[
        "Oak Park"
    ],
    "name:ita_x_preferred":[
        "Oak Park"
    ],
    "name:kor_x_preferred":[
        "\uc624\ud06c\ud30c\ud06c"
    ],
    "name:mlg_x_preferred":[
        "Oak Park"
    ],
    "name:nld_x_preferred":[
        "Oak Park"
    ],
    "name:pol_x_preferred":[
        "Oak Park"
    ],
    "name:por_x_preferred":[
        "Oak Park"
    ],
    "name:rus_x_preferred":[
        "\u041e\u043a-\u041f\u0430\u0440\u043a"
    ],
    "name:slk_x_preferred":[
        "Oak Park"
    ],
    "name:spa_x_preferred":[
        "Oak Park"
    ],
    "name:srp_x_preferred":[
        "\u041e\u0443\u043a \u041f\u0430\u0440\u043a"
    ],
    "name:swa_x_preferred":[
        "Oak Park"
    ],
    "name:swe_x_preferred":[
        "Oak Park"
    ],
    "name:urd_x_preferred":[
        "\u0627\u0648\u06a9 \u067e\u0627\u0631\u06a9"
    ],
    "name:vol_x_preferred":[
        "Oak Park"
    ],
    "name:zho_x_preferred":[
        "\u5965\u514b\u5e15\u514b"
    ],
    "wof:name":"Oak Park",
    "wof:placetype":"neighbourhood"
},
  "geometry": {"coordinates":[-78.70569484102616,35.84686934676638],"type":"Point"}
}