{
  "type": "Feature",
  "properties": {
    "name:eng_x_variant":[
        "HSP",
        "KHSP"
    ],
    "oa:elevation_ft":"3793",
    "oa:type":"small_airport",
    "woe:hierarchy":{
        "country_id":23424977,
        "county_id":12590313,
        "planet_id":1,
        "state_id":2347605
    },
    "wof:name":"Ingalls Field Airport",
    "wof:placetype":"campus"
},
  "geometry": {"coordinates":[-79.8339,37.951401],"type":"Point"}
}