{
  "type": "Feature",
  "properties": {
    "name:ara_x_preferred":[
        "\u0645\u0637\u0627\u0631 \u0628\u0642\u064a\u0642"
    ],
    "name:deu_x_preferred":[
        "Abqaiq Flughafen"
    ],
    "name:eng_x_preferred":[
        "Abqaiq Airport"
    ],
    "name:eng_x_variant":[
        "OEBQ"
    ],
    "name:fas_x_preferred":[
        "\u0641\u0631\u0648\u062f\u06af\u0627\u0647 \u0628\u0642\u06cc\u0642"
    ],
    "name:fra_x_preferred":[
        "A\u00e9roport d'Abqa\u00efq"
    ],
    "name:fra_x_variant":[
        "a\u00e9roport d'Abqa\u00efq"
    ],
    "name:jpn_x_preferred":[
        "\u30a2\u30d6\u30ab\u30a4\u30af\u7a7a\u6e2f"
    ],
    "name:msa_x_preferred":[
        "Lapangan Terbang Abqaiq"
    ],
    "name:rus_x_preferred":[
        "\u0410\u0431\u043a\u0430\u0439\u043a"
    ],
    "name:tgk_x_preferred":[
        "\u0424\u0443\u0440\u0443\u0434\u0433\u043e\u04b3\u0438 \u0431\u049b\u0438\u049b"
    ],
    "name:urd_x_preferred":[
        "\u0628\u0642\u06cc\u0642 \u06c1\u0648\u0627\u0626\u06cc \u0627\u0688\u0627"
    ],
    "oa:elevation_ft":"229",
    "oa:type":"small_airport",
    "wd:wordcount":155,
    "woe:hierarchy":{
        "country_id":23424938,
        "county_id":56120201,
        "planet_id":1,
        "state_id":2346954
    },
    "wof:name":"Abqaiq Airport",
    "wof:placetype":"campus"
},
  "geometry": {"coordinates":[49.591667,25.911667],"type":"Point"}
}