{
  "type": "Feature",
  "properties": {
    "gn:admin1_code":"33.0",
    "gn:asciiname":"Omukukutu",
    "gn:dem":1139,
    "gn:feature_class":"P",
    "gn:feature_code":"PPL",
    "gn:name":"Omukukutu",
    "gn:population":0,
    "gn:timezone":"Africa/Windhoek",
    "wof:name":"Omukukutu",
    "wof:placetype":"locality"
},
  "geometry": {"coordinates":[16.88332999999999,-17.48333],"type":"Point"}
}