{
  "type": "Feature",
  "properties": {
    "name:ceb_x_preferred":[
        "Gr\u00fcnerl\u00f8kka District"
    ],
    "name:dan_x_preferred":[
        "Gr\u00fcnerl\u00f8kka"
    ],
    "name:deu_x_preferred":[
        "Gr\u00fcnerl\u00f8kka"
    ],
    "name:eng_x_preferred":[
        "Gr\u00fcnerl\u00f8kka"
    ],
    "name:est_x_preferred":[
        "Gr\u00fcnerl\u00f8kka linnaosa"
    ],
    "name:fin_x_preferred":[
        "Gr\u00fcnerl\u00f8kka"
    ],
    "name:fra_x_preferred":[
        "Gr\u00fcnerl\u00f8kka"
    ],
    "name:nld_x_preferred":[
        "Gr\u00fcnerl\u00f8kka"
    ],
    "name:nno_x_preferred":[
        "Gr\u00fcnerl\u00f8kka"
    ],
    "name:nno_x_variant":[
        "Bydel Gr\u00fcnerl\u00f8kka"
    ],
    "name:nob_x_preferred":[
        "Bydel Gr\u00fcnerl\u00f8kka"
    ],
    "name:nor_x_preferred":[
        "Bydel Gr\u00fcnerl\u00f8kka"
    ],
    "name:pol_x_preferred":[
        "Gr\u00fcnerl\u00f8kka"
    ],
    "name:spa_x_preferred":[
        "Gr\u00fcnerl\u00f8kka"
    ],
    "name:swe_x_preferred":[
        "Gr\u00fcnerl\u00f8kka"
    ],
    "name:zho_x_preferred":[
        "\u845b\u9b6f\u5c3c\u6d1b\u5361"
    ],
    "wd:wordcount":732,
    "wof:name":"Gr\u00fcnerl\u00f8kka",
    "wof:placetype":"neighbourhood"
},
  "geometry": {"coordinates":[10.75759283684597,59.92326910376877],"type":"Point"}
}