{
  "type": "Feature",
  "properties": {
    "name:ara_x_preferred":[
        "\u0645\u0637\u0627\u0631 \u0627\u0648\u0631\u062f\u0648\u0633 \u0625\u064a\u062c\u064a\u0646 \u0647\u0648\u0631\u0648"
    ],
    "name:ceb_x_preferred":[
        "Ordos Ejin Horo Airport"
    ],
    "name:eng_x_preferred":[
        "Ordos Ejin Horo Airport"
    ],
    "name:eng_x_variant":[
        "DSN",
        "ZBDS"
    ],
    "name:eus_x_preferred":[
        "Ordos aireportua"
    ],
    "name:fas_x_preferred":[
        "\u0641\u0631\u0648\u062f\u06af\u0627\u0647 \u0627\u0648\u0631\u062f\u0648\u0633 \u0627\u06cc\u062c\u06cc\u0646 \u0647\u0648\u0631\u0648"
    ],
    "name:fra_x_preferred":[
        "a\u00e9roport d'Ordos Ejin Horo"
    ],
    "name:ind_x_preferred":[
        "Bandar Udara Ordos"
    ],
    "name:jpn_x_preferred":[
        "\u30aa\u30eb\u30c9\u30b9"
    ],
    "name:nld_x_preferred":[
        "Ordos Ejin Horo Airport"
    ],
    "name:pol_x_preferred":[
        "Port lotniczy Ordos"
    ],
    "name:ron_x_preferred":[
        "Aeroportul Ordos Ejin Horo"
    ],
    "name:rus_x_preferred":[
        "\u041e\u0440\u0434\u043e\u0441"
    ],
    "name:spa_x_preferred":[
        "Aeropuerto de Ordos Ejin Horo"
    ],
    "name:swe_x_preferred":[
        "Ordos Ejin Horo Airport"
    ],
    "name:tgk_x_preferred":[
        "\u0424\u0443\u0440\u0443\u0434\u0433\u043e\u04b3\u0438 \u043e\u0432\u0440\u0434\u0443\u0441 \u043e\u0438\u04b7\u0438\u043d \u04b3\u0443\u0440\u0443"
    ],
    "name:vie_x_preferred":[
        "S\u00e2n bay Ng\u1ea1c Nh\u0129 \u0110a T\u01b0"
    ],
    "name:zho_x_preferred":[
        "\u9102\u5c14\u591a\u65af\u4f0a\u91d1\u970d\u6d1b\u673a\u573a"
    ],
    "oa:elevation_ft":"4557",
    "oa:type":"medium_airport",
    "woe:hierarchy":{
        "country_id":23424781,
        "county_id":26198286,
        "localadmin_id":12686824,
        "planet_id":1,
        "state_id":12578009
    },
    "wof:name":"Dongsheng Airport",
    "wof:placetype":"campus"
},
  "geometry": {"coordinates":[109.861389,39.49],"type":"Point"}
}