{
  "type": "Feature",
  "properties": {
    "gn:admin1_code":"31.0",
    "gn:asciiname":"Ukamas",
    "gn:dem":805,
    "gn:feature_class":"P",
    "gn:feature_code":"PPL",
    "gn:name":"Ukamas",
    "gn:population":0,
    "gn:timezone":"Africa/Windhoek",
    "wof:name":"Ukamas",
    "wof:placetype":"locality"
},
  "geometry": {"coordinates":[19.73333,-28.03333],"type":"Point"}
}