{
  "type": "Feature",
  "properties": {
    "gn:admin1_code":"28.0",
    "gn:asciiname":"Katungu",
    "gn:dem":952,
    "gn:feature_class":"P",
    "gn:feature_code":"PPL",
    "gn:name":"Katungu",
    "gn:population":0,
    "gn:timezone":"Africa/Windhoek",
    "name:und_x_variant":[
        "Katonga",
        "Katungu"
    ],
    "wof:name":"Katungu",
    "wof:placetype":"locality"
},
  "geometry": {"coordinates":[24.01667,-17.71667],"type":"Point"}
}