{
  "type": "Feature",
  "properties": {
    "name:cat_x_preferred":[
        "Kailua"
    ],
    "name:ceb_x_preferred":[
        "Kailua"
    ],
    "name:dan_x_preferred":[
        "Kailua"
    ],
    "name:deu_x_preferred":[
        "Kailua"
    ],
    "name:ita_x_preferred":[
        "Kailua"
    ],
    "name:nld_x_preferred":[
        "Kailua"
    ],
    "name:pol_x_preferred":[
        "Kailua"
    ],
    "name:srp_x_preferred":[
        "\u041a\u0430\u0458\u043b\u0443\u0430"
    ],
    "name:ukr_x_preferred":[
        "\u041a\u0430\u0439\u043b\u0443\u0430"
    ],
    "wd:wordcount":62,
    "wof:name":"Kailua",
    "wof:placetype":"neighbourhood"
},
  "geometry": {"coordinates":[-157.74258587917492,21.39233553111267],"type":"Point"}
}