{
  "type": "Feature",
  "properties": {
    "name:ceb_x_preferred":[
        "Mustique Airport"
    ],
    "name:deu_x_preferred":[
        "Mustique Airport"
    ],
    "name:eng_x_preferred":[
        "Mustique Airport"
    ],
    "name:eng_x_variant":[
        "MQS",
        "TVSM"
    ],
    "name:fas_x_preferred":[
        "\u0641\u0631\u0648\u062f\u06af\u0627\u0647 \u0645\u0648\u0633\u062a\u06cc\u06a9"
    ],
    "name:jpn_x_preferred":[
        "\u30de\u30b9\u30c6\u30a3\u30af\u7a7a\u6e2f"
    ],
    "name:lit_x_preferred":[
        "Miustiko oro uostas"
    ],
    "name:msa_x_preferred":[
        "Lapangan Terbang Mustique Is"
    ],
    "name:pol_x_preferred":[
        "Port lotniczy Mustique"
    ],
    "name:ron_x_preferred":[
        "Aeroportul Mustique"
    ],
    "name:tgk_x_preferred":[
        "\u0424\u0443\u0440\u0443\u0434\u0433\u043e\u04b3\u0438 \u041c\u0443\u0441\u0442\u0438\u043a"
    ],
    "name:tgk_x_variant":[
        "\u0424\u0443\u0440\u0443\u0434\u0433\u043e\u04b3\u0438 \u043c\u0441\u0442\u0493\u043e\u043d\u043c"
    ],
    "oa:elevation_ft":"8",
    "oa:type":"medium_airport",
    "wd:wordcount":175,
    "woe:hierarchy":{
        "country_id":23424981,
        "planet_id":1,
        "state_id":2347676
    },
    "wof:name":"Mustique Airport",
    "wof:placetype":"campus"
},
  "geometry": {"coordinates":[-61.180199,12.8879],"type":"Point"}
}