{
  "type": "Feature",
  "properties": {
    "wof:name":"Bedford Dwellings",
    "wof:placetype":"neighbourhood"
},
  "geometry": {"coordinates":[-79.97598721582344,40.45051102945465],"type":"Point"}
}