{
  "type": "Feature",
  "properties": {
    "gn:admin1_code":"28.0",
    "gn:asciiname":"Sakfweba",
    "gn:dem":932,
    "gn:feature_class":"P",
    "gn:feature_code":"PPL",
    "gn:name":"Sakfweba",
    "gn:population":0,
    "gn:timezone":"Africa/Windhoek",
    "wof:name":"Sakfweba",
    "wof:placetype":"locality"
},
  "geometry": {"coordinates":[24.38333,-17.93332999999999],"type":"Point"}
}