{
  "type": "Feature",
  "properties": {
    "name:ceb_x_preferred":[
        "Izumo Airport"
    ],
    "name:deu_x_preferred":[
        "Flughafen Izumo"
    ],
    "name:eng_x_preferred":[
        "Izumo Airport"
    ],
    "name:eng_x_variant":[
        "IZO",
        "RJOC"
    ],
    "name:fas_x_preferred":[
        "\u0641\u0631\u0648\u062f\u06af\u0627\u0647 \u0627\u06cc\u0632\u0648\u0645\u0648"
    ],
    "name:fra_x_preferred":[
        "a\u00e9roport d'Izumo"
    ],
    "name:ind_x_preferred":[
        "Bandar Udara Izumo"
    ],
    "name:jpn_x_preferred":[
        "\u51fa\u96f2\u7a7a\u6e2f"
    ],
    "name:kor_x_preferred":[
        "\uc774\uc988\ubaa8 \uacf5\ud56d"
    ],
    "name:msa_x_preferred":[
        "Lapangan Terbang Izumo"
    ],
    "name:ron_x_preferred":[
        "Aeroportul Izumo"
    ],
    "name:tgk_x_preferred":[
        "\u0424\u0443\u0440\u0443\u0434\u0433\u043e\u04b3\u0438 \u043e\u0438\u0437\u0443\u043c\u0443"
    ],
    "name:vie_x_preferred":[
        "S\u00e2n bay Izumo"
    ],
    "name:zho_x_preferred":[
        "\u51fa\u96f2\u6a5f\u5834"
    ],
    "oa:elevation_ft":"15",
    "oa:type":"medium_airport",
    "woe:hierarchy":{
        "country_id":23424856,
        "county_id":24857832,
        "planet_id":1,
        "state_id":2345885
    },
    "wof:name":"\u51fa\u96f2\u7a7a\u6e2f",
    "wof:placetype":"campus"
},
  "geometry": {"coordinates":[132.88999899999999,35.413601],"type":"Point"}
}