{
  "type": "Feature",
  "properties": {
    "name:eng_x_variant":[
        "PNO",
        "MX-PNO"
    ],
    "oa:type":"small_airport",
    "woe:hierarchy":{
        "country_id":23424900,
        "county_id":12601144,
        "planet_id":1,
        "state_id":2346283
    },
    "wof:name":"Pinotepa Nacional Airport",
    "wof:placetype":"campus"
},
  "geometry": {"coordinates":[-98.06199599999999,16.35],"type":"Point"}
}