{
  "type": "Feature",
  "properties": {
    "gn:admin1_code":"21.0",
    "gn:asciiname":"Donkerhoek",
    "gn:dem":1011,
    "gn:feature_class":"P",
    "gn:feature_code":"PPL",
    "gn:name":"Donkerhoek",
    "gn:population":0,
    "gn:timezone":"Africa/Windhoek",
    "wof:name":"Donkerhoek",
    "wof:placetype":"locality"
},
  "geometry": {"coordinates":[15.96667,-23.63333],"type":"Point"}
}