{
  "type": "Feature",
  "properties": {
    "name:ceb_x_preferred":[
        "Masvingo"
    ],
    "name:eng_x_preferred":[
        "Masvingo Airport"
    ],
    "name:eng_x_variant":[
        "MVZ",
        "FVMV"
    ],
    "name:fas_x_preferred":[
        "\u0641\u0631\u0648\u062f\u06af\u0627\u0647 \u0645\u0627\u0632\u0648\u06cc\u0646\u06af\u0648\u0648"
    ],
    "name:jpn_x_preferred":[
        "\u30de\u30b7\u30f3\u30b4\u7a7a\u6e2f"
    ],
    "name:msa_x_preferred":[
        "Lapangan Terbang Antarabangsa Masvingo"
    ],
    "name:pol_x_preferred":[
        "Port lotniczy Masvingo"
    ],
    "name:ron_x_preferred":[
        "Aeroportul Masvingo"
    ],
    "oa:elevation_ft":"3595",
    "oa:type":"medium_airport",
    "wd:wordcount":108,
    "woe:hierarchy":{
        "country_id":23425004,
        "county_id":56048522,
        "planet_id":1,
        "state_id":2347817
    },
    "wof:name":"Masvingo Airport",
    "wof:placetype":"campus"
},
  "geometry": {"coordinates":[30.8591,-20.0553],"type":"Point"}
}