{
  "type": "Feature",
  "properties": {
    "name:chi_x_preferred":[
        "\u96f7\u7126\u5361\u62c9\u5e03\u91cc\u4e9e\u6a5f\u5834"
    ],
    "name:dut_x_preferred":[
        "Reggio Calabria Airport"
    ],
    "name:eng_x_preferred":[
        "Reggio Calabria Airport"
    ],
    "name:eng_x_variant":[
        "REG",
        "LICR"
    ],
    "name:est_x_preferred":[
        "Reggio Calabria lennujaam"
    ],
    "name:fre_x_preferred":[
        "a\u00e9roport de Reggio de Calabre"
    ],
    "name:ger_x_preferred":[
        "Flughafen Reggio Calabria"
    ],
    "name:ita_x_preferred":[
        "Aeroporto di Reggio Calabria"
    ],
    "name:jpn_x_preferred":[
        "\u30ec\u30c3\u30b8\u30e7\u30fb\u30c7\u30a3\u30fb\u30ab\u30e9\u30d6\u30ea\u30a2\u7a7a\u6e2f"
    ],
    "name:may_x_preferred":[
        "Lapangan Terbang Reggio Calabria"
    ],
    "name:per_x_preferred":[
        "\u0641\u0631\u0648\u062f\u06af\u0627\u0647 \u0631\u062c\u06cc\u0648 \u06a9\u0627\u0644\u0627\u0628\u0631\u06cc\u0627"
    ],
    "name:pol_x_preferred":[
        "Port lotniczy Reggio Calabria"
    ],
    "name:spa_x_preferred":[
        "Aeropuerto de Reggio di Calabria"
    ],
    "name:tgk_x_preferred":[
        "\u0424\u0443\u0440\u0443\u0434\u0433\u043e\u04b3\u0438 \u0440\u04b7\u044e \u043a\u043e\u043b\u043e\u0431\u0440\u0438\u043e"
    ],
    "name:vie_x_preferred":[
        "S\u00e2n bay Reggio Calabria"
    ],
    "oa:elevation_ft":"96",
    "oa:type":"medium_airport",
    "woe:hierarchy":{
        "country_id":23424853,
        "county_id":12591831,
        "localadmin_id":12676175,
        "planet_id":1,
        "state_id":7153332
    },
    "wof:name":"Aeroporto di Reggio Calabria",
    "wof:placetype":"campus"
},
  "geometry": {"coordinates":[15.6516,38.071201],"type":"Point"}
}