{
  "type": "Feature",
  "properties": {
    "name:ceb_x_preferred":[
        "Manihi Airport"
    ],
    "name:eng_x_preferred":[
        "Manihi Airport"
    ],
    "name:eng_x_variant":[
        "XMH",
        "NTGI"
    ],
    "name:fas_x_preferred":[
        "\u0641\u0631\u0648\u062f\u06af\u0627\u0647 \u0645\u0627\u0646\u06cc\u0647\u06cc"
    ],
    "name:fra_x_preferred":[
        "A\u00e9rodrome de Manihi"
    ],
    "name:fra_x_variant":[
        "a\u00e9rodrome de Manihi"
    ],
    "name:hun_x_preferred":[
        "Manihi rep\u00fcl\u0151t\u00e9r"
    ],
    "name:ind_x_preferred":[
        "Bandar Udara Manihi"
    ],
    "name:jpn_x_preferred":[
        "\u30de\u30cb\u30d2\u7a7a\u6e2f"
    ],
    "name:pol_x_preferred":[
        "Port lotniczy Manihi"
    ],
    "name:ron_x_preferred":[
        "Aeroportul Manihi"
    ],
    "oa:elevation_ft":"14",
    "oa:type":"medium_airport",
    "wd:wordcount":65,
    "woe:hierarchy":{
        "country_id":23424817,
        "county_id":28743697,
        "planet_id":1,
        "state_id":24549702
    },
    "wof:name":"Manihi Airport",
    "wof:placetype":"campus"
},
  "geometry": {"coordinates":[-146.070007,-14.4368],"type":"Point"}
}