{
  "type": "Feature",
  "properties": {
    "gn:admin1_code":"28.0",
    "gn:asciiname":"Nuwe Kabbe",
    "gn:dem":934,
    "gn:feature_class":"P",
    "gn:feature_code":"PPL",
    "gn:name":"Nuwe Kabbe",
    "gn:population":0,
    "gn:timezone":"Africa/Windhoek",
    "wof:name":"Nuwe Kabbe",
    "wof:placetype":"locality"
},
  "geometry": {"coordinates":[24.66667,-17.68332999999999],"type":"Point"}
}