{
  "type": "Feature",
  "properties": {
    "gn:admin1_code":"29.0",
    "gn:asciiname":"Homeb",
    "gn:dem":479,
    "gn:feature_class":"P",
    "gn:feature_code":"PPL",
    "gn:name":"Homeb",
    "gn:population":0,
    "gn:timezone":"Africa/Windhoek",
    "wof:name":"Homeb",
    "wof:placetype":"locality"
},
  "geometry": {"coordinates":[15.18333,-23.63333],"type":"Point"}
}