{
  "type": "Feature",
  "properties": {
    "name:ceb_x_preferred":[
        "Sullivan Regional Airport"
    ],
    "name:eng_x_preferred":[
        "Sullivan Regional Airport"
    ],
    "name:ron_x_preferred":[
        "Aeroportul Regional Sullivan"
    ],
    "name:urd_x_preferred":[
        "\u0633\u0648\u0644\u06cc\u0648\u0627\u0646 \u0631\u06cc\u062c\u0646\u0644 \u06c1\u0648\u0627\u0626\u06cc \u0627\u0688\u0627"
    ],
    "oa:elevation_ft":"933",
    "oa:type":"small_airport",
    "wd:wordcount":324,
    "woe:hierarchy":{
        "country_id":23424977,
        "county_id":12589001,
        "planet_id":1,
        "state_id":2347584
    },
    "wof:name":"Sullivan Regional Airport",
    "wof:placetype":"campus"
},
  "geometry": {"coordinates":[-91.16419999999999,38.2333],"type":"Point"}
}