{
  "type": "Feature",
  "properties": {
    "oa:elevation_ft":"933",
    "oa:type":"small_airport",
    "wd:wordcount":324,
    "woe:hierarchy":{
        "country_id":23424977,
        "county_id":12589001,
        "planet_id":1,
        "state_id":2347584
    },
    "wof:name":"Sullivan Regional Airport",
    "wof:placetype":"campus"
},
  "geometry": {"coordinates":[-91.16419999999999,38.2333],"type":"Point"}
}