{
  "type": "Feature",
  "properties": {
    "gn:admin1_code":"32.0",
    "gn:asciiname":"Otjouye",
    "gn:dem":1388,
    "gn:feature_class":"P",
    "gn:feature_code":"PPL",
    "gn:name":"Otjouye",
    "gn:population":0,
    "gn:timezone":"Africa/Windhoek",
    "wof:name":"Otjouye",
    "wof:placetype":"locality"
},
  "geometry": {"coordinates":[13.96667,-18.18333],"type":"Point"}
}