{
  "type": "Feature",
  "properties": {
    "gn:admin1_code":"37.0",
    "gn:asciiname":"Uukwiwongwe",
    "gn:dem":1093,
    "gn:feature_class":"P",
    "gn:feature_code":"PPL",
    "gn:name":"Uukwiwongwe",
    "gn:population":0,
    "gn:timezone":"Africa/Windhoek",
    "name:und_x_variant":[
        "Uukwiwongue",
        "Uukwiwongwe"
    ],
    "wof:name":"Uukwiwongwe",
    "wof:placetype":"locality"
},
  "geometry": {"coordinates":[15.63333,-17.86667000000001],"type":"Point"}
}