{
  "type": "Feature",
  "properties": {
    "gn:admin1_code":"35.0",
    "gn:asciiname":"Otjiwetjombungu",
    "gn:dem":1431,
    "gn:feature_class":"P",
    "gn:feature_code":"PPL",
    "gn:name":"Otjiwetjombungu",
    "gn:population":0,
    "gn:timezone":"Africa/Windhoek",
    "name:und_x_variant":[
        "Otjivetjombungu",
        "Otjiwetjombungu"
    ],
    "wof:name":"Otjiwetjombungu",
    "wof:placetype":"locality"
},
  "geometry": {"coordinates":[19.13333,-21.33333],"type":"Point"}
}