{
  "type": "Feature",
  "properties": {
    "gn:admin1_code":"28.0",
    "gn:asciiname":"Bagani",
    "gn:dem":1007,
    "gn:feature_class":"P",
    "gn:feature_code":"PPL",
    "gn:name":"Bagani",
    "gn:population":2000,
    "gn:timezone":"Africa/Windhoek",
    "wof:name":"Bagani",
    "wof:placetype":"locality",
    "wof:population":2000
},
  "geometry": {"coordinates":[21.61645,-18.11065],"type":"Point"}
}