{
  "type": "Feature",
  "properties": {
    "name:eng_x_variant":[
        "SDZ"
    ],
    "name:fas_x_preferred":[
        "\u0641\u0631\u0648\u062f\u06af\u0627\u0647 \u062f\u0627\u0645\u0627\u0632\u06cc\u0646"
    ],
    "name:ind_x_preferred":[
        "Bandar Udara Damazin"
    ],
    "name:pol_x_preferred":[
        "Port lotniczy Ad-Damazin"
    ],
    "name:por_x_preferred":[
        "Aeroporto de Damazin"
    ],
    "name:tgk_x_preferred":[
        "\u0424\u0443\u0440\u0443\u0434\u0433\u043e\u04b3\u0438 \u0434\u043e\u043c\u043e\u0437\u0438\u043d"
    ],
    "oa:elevation_ft":"1582",
    "oa:type":"small_airport",
    "wd:wordcount":87,
    "woe:hierarchy":{
        "country_id":23424952,
        "planet_id":1,
        "state_id":20069913
    },
    "wof:name":"Damazin Airport",
    "wof:placetype":"campus"
},
  "geometry": {"coordinates":[34.336388888889,11.785833333333],"type":"Point"}
}