{
  "type": "Feature",
  "properties": {
    "name:nor_x_preferred":[
        "Veitvet"
    ],
    "wof:name":"Veitvet",
    "wof:placetype":"neighbourhood"
},
  "geometry": {"coordinates":[10.85252162606464,59.94411043924144],"type":"Point"}
}