{
  "type": "Feature",
  "properties": {
    "name:ceb_x_preferred":[
        "Albertus Airport"
    ],
    "name:deu_x_preferred":[
        "Albertus Airport"
    ],
    "name:eng_x_preferred":[
        "Albertus Airport"
    ],
    "name:fra_x_preferred":[
        "a\u00e9rodrome d'Albertus"
    ],
    "name:ron_x_preferred":[
        "Aeroportul Albertus"
    ],
    "oa:elevation_ft":"859",
    "oa:type":"small_airport",
    "woe:hierarchy":{
        "country_id":23424977,
        "county_id":12588166,
        "planet_id":1,
        "state_id":2347572
    },
    "wof:name":"Albertus Airport",
    "wof:placetype":"campus"
},
  "geometry": {"coordinates":[-89.58194444,42.24611111],"type":"Point"}
}