{
  "type": "Feature",
  "properties": {
    "name:ara_x_preferred":[
        "\u0645\u0637\u0627\u0631 \u0633\u0627\u0646\u062a\u0648\u0631\u064a\u0646\u064a"
    ],
    "name:ceb_x_preferred":[
        "Santorini Airport"
    ],
    "name:dan_x_preferred":[
        "Santorini Lufthavn"
    ],
    "name:deu_x_preferred":[
        "Flughafen Santorin"
    ],
    "name:ell_x_preferred":[
        "\u039a\u03c1\u03b1\u03c4\u03b9\u03ba\u03cc\u03c2 \u0391\u03b5\u03c1\u03bf\u03bb\u03b9\u03bc\u03ad\u03bd\u03b1\u03c2 \u03a3\u03b1\u03bd\u03c4\u03bf\u03c1\u03af\u03bd\u03b7\u03c2"
    ],
    "name:eng_x_preferred":[
        "Santorini"
    ],
    "name:eng_x_variant":[
        "JTR",
        "LGSR"
    ],
    "name:fas_x_preferred":[
        "\u0641\u0631\u0648\u062f\u06af\u0627\u0647 \u0645\u0644\u06cc \u0633\u0627\u062f\u0648\u0631\u06cc\u0646\u06cc"
    ],
    "name:fin_x_preferred":[
        "Santor\u00ednin lentoasema"
    ],
    "name:fra_x_preferred":[
        "a\u00e9roport de Santorin"
    ],
    "name:hun_x_preferred":[
        "Szantorini nemzetk\u00f6zi rep\u00fcl\u0151t\u00e9r"
    ],
    "name:ind_x_preferred":[
        "Bandar Udara Nasional Santorini"
    ],
    "name:ita_x_preferred":[
        "Aeroporto nazionale di Santorini"
    ],
    "name:jpn_x_preferred":[
        "\u30b5\u30f3\u30c8\u30ea\u30fc\u30cb"
    ],
    "name:kor_x_preferred":[
        "\uc0b0\ud1a0\ub9ac\ub2c8 \uad6d\uc81c\uacf5\ud56d"
    ],
    "name:msa_x_preferred":[
        "Lapangan Terbang Santorini"
    ],
    "name:nld_x_preferred":[
        "Luchthaven Santorini"
    ],
    "name:nob_x_preferred":[
        "Santorini lufthavn"
    ],
    "name:pol_x_preferred":[
        "Port lotniczy Santoryn"
    ],
    "name:ron_x_preferred":[
        "Aeroportul Na\u021bional Santorini"
    ],
    "name:rus_x_preferred":[
        "\u0421\u0430\u043d\u0442\u043e\u0440\u0438\u043d\u0438"
    ],
    "name:spa_x_preferred":[
        "Aeropuerto Nacional de Santorini"
    ],
    "name:srp_x_preferred":[
        "\u0421\u0430\u043d\u0442\u043e\u0440\u0438\u043d\u0438"
    ],
    "name:swe_x_preferred":[
        "Santorini flygplats"
    ],
    "name:tgk_x_preferred":[
        "\u0424\u0443\u0440\u0443\u0434\u0433\u043e\u04b3\u0438 \u043c\u0438\u043b\u043b\u0438\u0438 \u0421\u043e\u043d\u0442\u043e\u0440\u0438\u043d\u0438"
    ],
    "name:tur_x_preferred":[
        "Santoron Ulusal Havaliman\u0131"
    ],
    "name:ukr_x_preferred":[
        "\u041d\u0430\u0446\u0456\u043e\u043d\u0430\u043b\u044c\u043d\u0438\u0439 \u0430\u0435\u0440\u043e\u043f\u043e\u0440\u0442 \u0421\u0430\u043d\u0442\u043e\u0440\u0456\u043d\u0456"
    ],
    "name:zho_x_preferred":[
        "\u5723\u6258\u91cc\u5c3c\u673a\u573a"
    ],
    "oa:elevation_ft":"127",
    "oa:type":"medium_airport",
    "woe:hierarchy":{
        "country_id":23424833,
        "county_id":12591117,
        "localadmin_id":24544380,
        "planet_id":1,
        "state_id":12577886
    },
    "wof:name":"Santorini Airport",
    "wof:placetype":"campus"
},
  "geometry": {"coordinates":[25.4793,36.3992],"type":"Point"}
}