{
  "type": "Feature",
  "properties": {
    "wof:name":"Olivenhain",
    "wof:placetype":"neighbourhood"
},
  "geometry": {"coordinates":[-117.2282048850408,33.05427458065998],"type":"Point"}
}