{
  "type": "Feature",
  "properties": {
    "name:ceb_x_preferred":[
        "Parker County Airport"
    ],
    "name:eng_x_preferred":[
        "Parker County Airport"
    ],
    "name:ron_x_preferred":[
        "Aeroportul Parker County"
    ],
    "oa:elevation_ft":"990",
    "oa:type":"small_airport",
    "woe:hierarchy":{
        "country_id":23424977,
        "county_id":12590190,
        "planet_id":1,
        "state_id":2347602
    },
    "wof:name":"Parker County Airport",
    "wof:placetype":"campus"
},
  "geometry": {"coordinates":[-97.68244,32.7463],"type":"Point"}
}