{
  "type": "Feature",
  "properties": {
    "name:ara_x_preferred":[
        "\u0627\u0644\u0645\u062c\u0627\u0632 3"
    ],
    "name:eng_x_preferred":[
        "Al Majaz 3"
    ],
    "name:eng_x_variant":[
        "Al Majaz 3"
    ],
    "qs:gn_adm0_cc":"AE",
    "qs:gn_local":292672,
    "qs:gn_nam_loc":"\u0627\u0644\u0634\u0627\u0631\u0642\u0629, \u0627\u0644\u0634\u0627\u0631\u0642\u0629, \u0627\u0644\u0634\u0627\u0631\u0642\u0629, AE",
    "qs:gn_namadm1":"06",
    "qs:local_max":385,
    "qs:local_sum":1326,
    "qs:localhoods":7,
    "qs:name":"\u0627\u0644\u0645\u062c\u0627\u0632 3",
    "qs:name_adm0":"\u0627\u0644\u0627\u0645\u0627\u0631\u0627\u062a",
    "qs:name_adm1":"\u0627\u0644\u0634\u0627\u0631\u0642\u0629",
    "qs:name_adm2":"\u0627\u0644\u0634\u0627\u0631\u0642\u0629",
    "qs:name_en":"Al Majaz 3",
    "qs:name_local":"\u0627\u0644\u0634\u0627\u0631\u0642\u0629",
    "qs:photo_max":110,
    "qs:photo_sum":360,
    "qs:placetype":"Suburb",
    "qs:quad_count":25,
    "qs:woe_adm0":23424738,
    "qs:woe_adm1":2347114,
    "qs:woe_adm2":55922644,
    "qs:woe_lau":0,
    "qs:woe_local":1940119,
    "qs:woe_ver":"7.10.0",
    "wof:lang":[
        "ara"
    ],
    "wof:name":"\u0627\u0644\u0645\u062c\u0627\u0632 3",
    "wof:placetype":"neighbourhood"
},
  "geometry": {"coordinates":[55.37874,25.330697],"type":"Point"}
}