{
  "type": "Feature",
  "properties": {
    "gn:admin1_code":"39.0",
    "gn:asciiname":"Omutima",
    "gn:dem":1231,
    "gn:feature_class":"P",
    "gn:feature_code":"PPL",
    "gn:name":"Omutima",
    "gn:population":0,
    "gn:timezone":"Africa/Windhoek",
    "wof:name":"Omutima",
    "wof:placetype":"locality"
},
  "geometry": {"coordinates":[18.83333,-19.71667],"type":"Point"}
}