{
  "type": "Feature",
  "properties": {
    "name:ceb_x_preferred":[
        "Chafei Amsei Airport"
    ],
    "name:deu_x_preferred":[
        "Flughafen Chafei Amsei"
    ],
    "name:eng_x_preferred":[
        "Barretos Airport"
    ],
    "name:eng_x_variant":[
        "BAT",
        "SBBT"
    ],
    "name:jpn_x_preferred":[
        "\u30d0\u30ec\u30c8\u30b9\u7a7a\u6e2f"
    ],
    "name:msa_x_preferred":[
        "Lapangan Terbang Chafei Amsei"
    ],
    "name:por_x_preferred":[
        "Aeroporto de Barretos"
    ],
    "name:swe_x_preferred":[
        "Chafei Amsei Airport"
    ],
    "name:zho_x_preferred":[
        "\u5df4\u96f7\u5716\u65af\u6a5f\u5834"
    ],
    "oa:elevation_ft":"1898",
    "oa:type":"medium_airport",
    "wd:wordcount":168,
    "woe:hierarchy":{
        "country_id":23424768,
        "county_id":12581868,
        "planet_id":1,
        "state_id":2344868
    },
    "wof:name":"Aeroporto Barretos",
    "wof:placetype":"campus"
},
  "geometry": {"coordinates":[-48.594101,-20.584499],"type":"Point"}
}