{
  "type": "Feature",
  "properties": {
    "name:pol_x_preferred":[
        "Salt Creek"
    ],
    "name:swe_x_preferred":[
        "Salt Creek"
    ],
    "wd:wordcount":115,
    "wof:name":"Salt Creek",
    "wof:placetype":"neighbourhood"
},
  "geometry": {"coordinates":[-96.72082349189822,40.80577352241169],"type":"Point"}
}