{
  "type": "Feature",
  "properties": {
    "name:deu_x_preferred":[
        "Flughafen Governador Jorge Teixeira De Oliveira"
    ],
    "name:eng_x_preferred":[
        "Governador Jorge Teixeira de Oliveira International Airport"
    ],
    "name:eng_x_variant":[
        "PVH",
        "SBPV"
    ],
    "name:fas_x_preferred":[
        "\u0641\u0631\u0648\u062f\u06af\u0627\u0647 \u0628\u06cc\u0646\u200c\u0627\u0644\u0645\u0644\u0644\u06cc \u06af\u0648\u0631\u0646\u0627\u062f\u0631 \u062e\u0648\u0632\u0647 \u062a\u06cc\u06a9\u0633\u06cc\u0631\u0627 \u062f\u0627 \u0644\u06cc\u0648\u06cc\u0631\u0627"
    ],
    "name:jpn_x_preferred":[
        "\u30dd\u30eb\u30c8\u30d9\u30ea\u30e7"
    ],
    "name:msa_x_preferred":[
        "Lapangan Terbang Gov J Teixeira De Oliveira Int"
    ],
    "name:nld_x_preferred":[
        "Luchthaven Jorge Teixeira de Oliveira International"
    ],
    "name:pol_x_preferred":[
        "Port lotniczy Porto Velho"
    ],
    "name:por_x_preferred":[
        "Aeroporto Internacional de Porto Velho"
    ],
    "name:rus_x_preferred":[
        "\u041f\u043e\u0440\u0442\u0443-\u0412\u0435\u043b\u044c\u044e"
    ],
    "name:swe_x_preferred":[
        "Governador Jorge Teixeira de Oliveira International Airport"
    ],
    "name:tgk_x_preferred":[
        "\u0424\u0443\u0440\u0443\u0434\u0433\u043e\u04b3\u0438 \u0431\u0438\u043d\u200c\u0430\u043b\u043c\u0438\u043b\u0430\u043b\u04e3 \u0433\u0443\u0440\u043d\u043e\u0434\u0440 \u0445\u0443\u0437\u0430 \u0442\u0438\u043a\u0441\u0438\u0440\u043e \u0434\u043e \u043b\u044e\u0438\u0440\u043e"
    ],
    "name:vie_x_preferred":[
        "S\u00e2n bay qu\u1ed1c t\u1ebf Governador Jorge Teixeira de Oliveira"
    ],
    "oa:elevation_ft":"290",
    "oa:type":"medium_airport",
    "woe:hierarchy":{
        "country_id":23424768,
        "county_id":12581581,
        "planet_id":1,
        "state_id":2344865
    },
    "wof:name":"Aeroporto Internacional Governador Jorge Teixeira de Oliveira",
    "wof:placetype":"campus"
},
  "geometry": {"coordinates":[-63.902302,-8.70929],"type":"Point"}
}