{
  "type": "Feature",
  "properties": {
    "name:deu_x_preferred":[
        "Flughafen Mbala"
    ],
    "name:eng_x_preferred":[
        "Mbala Airport"
    ],
    "name:eng_x_variant":[
        "MMQ",
        "FLBA"
    ],
    "name:jpn_x_preferred":[
        "\u30de\u30d0\u30e9\u7a7a\u6e2f"
    ],
    "name:msa_x_preferred":[
        "Lapangan Terbang Mbala"
    ],
    "name:pol_x_preferred":[
        "Port lotniczy Mbala"
    ],
    "name:ron_x_preferred":[
        "Aeroportul Mbala"
    ],
    "oa:elevation_ft":"5454",
    "oa:type":"small_airport",
    "wd:wordcount":49,
    "woe:hierarchy":{
        "country_id":23425003,
        "planet_id":1,
        "state_id":2347807
    },
    "wof:name":"Mbala Airport",
    "wof:placetype":"campus"
},
  "geometry": {"coordinates":[31.3364,-8.85917],"type":"Point"}
}