{
  "type": "Feature",
  "properties": {
    "gn:admin1_code":"32.0",
    "gn:asciiname":"Ombahe-Yakako",
    "gn:dem":1678,
    "gn:feature_class":"P",
    "gn:feature_code":"PPL",
    "gn:name":"Ombahe-Yakako",
    "gn:population":0,
    "gn:timezone":"Africa/Windhoek",
    "wof:name":"Ombahe-Yakako",
    "wof:placetype":"locality"
},
  "geometry": {"coordinates":[13.71667,-18.41667],"type":"Point"}
}