{
  "type": "Feature",
  "properties": {
    "gn:admin1_code":"28.0",
    "gn:asciiname":"Diyogha",
    "gn:dem":1036,
    "gn:feature_class":"P",
    "gn:feature_code":"PPL",
    "gn:name":"Diyogha",
    "gn:population":0,
    "gn:timezone":"Africa/Windhoek",
    "wof:name":"Diyogha",
    "wof:placetype":"locality"
},
  "geometry": {"coordinates":[21.46667,-18.08333],"type":"Point"}
}