{
  "type": "Feature",
  "properties": {
    "name:ceb_x_preferred":[
        "Fallon Municipal Airport"
    ],
    "name:eng_x_preferred":[
        "Fallon Municipal Airport"
    ],
    "name:fas_x_preferred":[
        "\u0641\u0631\u0648\u062f\u06af\u0627\u0647 \u0634\u0647\u0631\u0633\u062a\u0627\u0646 \u0641\u0627\u0644\u0646"
    ],
    "name:jpn_x_preferred":[
        "Fallon\u5e02\u55b6\u7a7a\u6e2f"
    ],
    "name:ron_x_preferred":[
        "Aeroportul Municipal Fallon"
    ],
    "name:tgk_x_preferred":[
        "\u0424\u0443\u0440\u0443\u0434\u0433\u043e\u04b3\u0438 \u0448\u0430\u04b3\u0440\u0438\u0438 \u0424\u043e\u043b\u043e\u043d"
    ],
    "name:tgk_x_variant":[
        "\u0424\u0443\u0440\u0443\u0434\u0433\u043e\u04b3\u0438 \u0448\u0430\u04b3\u0440\u0438\u0441\u0442\u043e\u043d \u0444\u043e\u043b\u043d"
    ],
    "name:zho_x_preferred":[
        "\u6cd5\u502b\u5e02\u7acb\u6a5f\u5834"
    ],
    "oa:elevation_ft":"3963",
    "oa:type":"small_airport",
    "wd:wordcount":183,
    "woe:hierarchy":{
        "country_id":23424977,
        "county_id":12589232,
        "planet_id":1,
        "state_id":2347587
    },
    "wof:name":"Fallon Municipal Airport",
    "wof:placetype":"campus"
},
  "geometry": {"coordinates":[-118.74888888888999,39.499166666667],"type":"Point"}
}