{
  "type": "Feature",
  "properties": {
    "name:ceb_x_preferred":[
        "Fort Frances Municipal Airport"
    ],
    "name:eng_x_preferred":[
        "Fort Frances Municipal Airport"
    ],
    "name:eng_x_variant":[
        "YAG",
        "CYAG"
    ],
    "name:fas_x_preferred":[
        "\u0641\u0631\u0648\u062f\u06af\u0627\u0647 \u0634\u0647\u0631\u06cc \u0641\u0648\u0631\u062a \u0641\u0631\u0627\u0646\u0633\u0633"
    ],
    "name:jpn_x_preferred":[
        "\u30d5\u30a9\u30fc\u30c8\u30d5\u30e9\u30f3\u30b7\u30b9\u753a\u55b6\u7a7a\u6e2f"
    ],
    "name:may_x_preferred":[
        "Lapangan Terbang Ft Frances Mun"
    ],
    "name:msa_x_preferred":[
        "Lapangan Terbang Ft Frances Mun"
    ],
    "name:per_x_preferred":[
        "\u0641\u0631\u0648\u062f\u06af\u0627\u0647 \u0634\u0647\u0631\u06cc \u0641\u0648\u0631\u062a \u0641\u0631\u0627\u0646\u0633\u0633"
    ],
    "name:pms_x_preferred":[
        "Fort Frances Municipal Airport"
    ],
    "name:spa_x_preferred":[
        "Aeropuerto Municipal de Fort Frances"
    ],
    "name:swe_x_preferred":[
        "Fort Frances Municipal Airport"
    ],
    "name:tgk_x_preferred":[
        "\u0424\u0443\u0440\u0443\u0434\u0433\u043e\u04b3\u0438 \u0448\u0430\u04b3\u0440\u0435 \u0444\u0443\u0440\u0442 \u0444\u0440\u043e\u043d\u0441\u0441"
    ],
    "oa:elevation_ft":"1125",
    "oa:type":"medium_airport",
    "wd:wordcount":106,
    "woe:hierarchy":{
        "country_id":23424775,
        "county_id":29375261,
        "planet_id":1,
        "state_id":2344922
    },
    "wof:name":"Fort Frances Municipal Airport",
    "wof:placetype":"campus"
},
  "geometry": {"coordinates":[-93.439697,48.654202],"type":"Point"}
}