{
  "type": "Feature",
  "properties": {
    "name:ceb_x_preferred":[
        "Gayndah Airport"
    ],
    "name:msa_x_preferred":[
        "Lapangan Terbang Gayndah"
    ],
    "name:swe_x_preferred":[
        "Gayndah Airport"
    ],
    "oa:elevation_ft":"369",
    "oa:type":"small_airport",
    "wd:wordcount":31,
    "woe:hierarchy":{
        "country_id":23424748,
        "county_id":56072994,
        "planet_id":1,
        "state_id":2344702
    },
    "wof:name":"Gayndah Airport",
    "wof:placetype":"campus"
},
  "geometry": {"coordinates":[151.62100000000001,-25.6153],"type":"Point"}
}