{
  "type": "Feature",
  "properties": {
    "name:eng_x_variant":[
        "VJI"
    ],
    "name:fas_x_preferred":[
        "\u0641\u0631\u0648\u062f\u06af\u0627\u0647 \u0648\u06cc\u0631\u062c\u06cc\u0646\u06cc\u0627 \u0647\u0627\u06cc\u0644\u0646\u062f\u0632"
    ],
    "name:tgk_x_preferred":[
        "\u0424\u0443\u0440\u0443\u0434\u0433\u043e\u04b3\u0438 \u0432\u0435\u0440\u04b7\u0435\u043d\u0435\u0451 \u04b3\u043e\u0438\u043b\u043d\u0434\u0437"
    ],
    "oa:elevation_ft":"2087",
    "oa:type":"small_airport",
    "wd:wordcount":281,
    "woe:hierarchy":{
        "country_id":23424977,
        "county_id":12590432,
        "planet_id":1,
        "state_id":2347605
    },
    "wof:name":"Virginia Highlands Airport",
    "wof:placetype":"campus"
},
  "geometry": {"coordinates":[-82.033327777778,36.687102777778],"type":"Point"}
}