{
  "type": "Feature",
  "properties": {
    "gn:admin1_code":"29.0",
    "gn:asciiname":"Bethal",
    "gn:dem":1084,
    "gn:feature_class":"P",
    "gn:feature_code":"PPL",
    "gn:name":"Bethal",
    "gn:population":0,
    "gn:timezone":"Africa/Windhoek",
    "name:afr_x_preferred":[
        "Bethal"
    ],
    "name:ben_x_preferred":[
        "\u09ac\u09c7\u09a5\u09c7\u09b2"
    ],
    "name:ceb_x_preferred":[
        "Bethal"
    ],
    "name:deu_x_preferred":[
        "Bethal"
    ],
    "name:ell_x_preferred":[
        "\u039c\u03c0\u03ad\u03b8\u03b1\u03bb"
    ],
    "name:epo_x_preferred":[
        "Bethal"
    ],
    "name:est_x_preferred":[
        "Bethal"
    ],
    "name:fas_x_preferred":[
        "\u0628\u062a\u0627\u0644"
    ],
    "name:fra_x_preferred":[
        "Bethal"
    ],
    "name:heb_x_preferred":[
        "\u05d1\u05ea\u05d0\u05dc"
    ],
    "name:hin_x_preferred":[
        "\u092c\u0947\u0925\u0932"
    ],
    "name:hun_x_preferred":[
        "Bethal"
    ],
    "name:ind_x_preferred":[
        "Bethal"
    ],
    "name:ita_x_preferred":[
        "Bethal"
    ],
    "name:jpn_x_preferred":[
        "\u30d9\u30b5\u30eb"
    ],
    "name:kor_x_preferred":[
        "\ubca0\ud0c8"
    ],
    "name:mlg_x_preferred":[
        "Bethal"
    ],
    "name:nld_x_preferred":[
        "Bethal"
    ],
    "name:nso_x_preferred":[
        "Bethal"
    ],
    "name:pol_x_preferred":[
        "Bethal"
    ],
    "name:por_x_preferred":[
        "Bethal"
    ],
    "name:ron_x_preferred":[
        "Bethal"
    ],
    "name:rus_x_preferred":[
        "\u0411\u0435\u0442\u0430\u043b"
    ],
    "name:spa_x_preferred":[
        "Bethal"
    ],
    "name:swe_x_preferred":[
        "Bethal"
    ],
    "name:tur_x_preferred":[
        "Bethal"
    ],
    "name:ukr_x_preferred":[
        "\u0411\u0435\u0442\u0430\u043b"
    ],
    "name:urd_x_preferred":[
        "\u0628\u06cc\u062a\u06be\u0644"
    ],
    "name:ven_x_preferred":[
        "Bethal"
    ],
    "name:vie_x_preferred":[
        "Bethal"
    ],
    "name:zho_cn_x_preferred":[
        "\u8d1d\u745f\u5c14"
    ],
    "name:zho_tw_x_preferred":[
        "\u8c9d\u745f\u723e"
    ],
    "wof:name":"Bethal",
    "wof:placetype":"locality"
},
  "geometry": {"coordinates":[15.86667,-22.56667],"type":"Point"}
}