{
  "type": "Feature",
  "properties": {
    "gn:admin1_code":"29.0",
    "gn:asciiname":"Bethal",
    "gn:dem":1084,
    "gn:feature_class":"P",
    "gn:feature_code":"PPL",
    "gn:name":"Bethal",
    "gn:population":0,
    "gn:timezone":"Africa/Windhoek",
    "wof:name":"Bethal",
    "wof:placetype":"locality"
},
  "geometry": {"coordinates":[15.86667,-22.56667],"type":"Point"}
}