{
  "type": "Feature",
  "properties": {
    "oa:elevation_ft":"732",
    "oa:type":"small_airport",
    "woe:hierarchy":{
        "country_id":23424819,
        "county_id":12597133,
        "localadmin_id":12645494,
        "planet_id":1,
        "state_id":7153312
    },
    "wof:name":"Joigny Airport",
    "wof:placetype":"campus"
},
  "geometry": {"coordinates":[3.39083,47.9944],"type":"Point"}
}