{
  "type": "Feature",
  "properties": {
    "name:ceb_x_preferred":[
        "Bloodvein River Airport"
    ],
    "name:eng_x_preferred":[
        "Bloodvein River Airport"
    ],
    "name:eng_x_variant":[
        "YDV",
        "CZTA"
    ],
    "name:fas_x_preferred":[
        "\u0641\u0631\u0648\u062f\u06af\u0627\u0647 \u0628\u0644\u0627\u062f\u0648\u06cc\u0646 \u0631\u06cc\u0648\u0631"
    ],
    "name:msa_x_preferred":[
        "Lapangan Terbang Bloodvein River"
    ],
    "name:pms_x_preferred":[
        "Bloodvein River Airport"
    ],
    "name:ron_x_preferred":[
        "Aeroportul Bloodvein River"
    ],
    "name:swe_x_preferred":[
        "Bloodvein River Airport"
    ],
    "name:tgk_x_preferred":[
        "\u0424\u0443\u0440\u0443\u0434\u0433\u043e\u04b3\u0438 \u0411\u043b\u0430\u0434\u0432\u0435\u0439\u043d \u0420\u0438\u0432\u0435\u0440"
    ],
    "name:tgk_x_variant":[
        "\u0424\u0443\u0440\u0443\u0434\u0433\u043e\u04b3\u0438 \u0431\u043b\u043e\u0434\u0443\u0438\u043d \u0440\u044e\u0440"
    ],
    "oa:elevation_ft":"721",
    "oa:type":"small_airport",
    "wd:wordcount":52,
    "woe:hierarchy":{
        "country_id":23424775,
        "county_id":29375231,
        "planet_id":1,
        "state_id":2344917
    },
    "wof:name":"Bloodvein River Airport",
    "wof:placetype":"campus"
},
  "geometry": {"coordinates":[-96.692305,51.784568],"type":"Point"}
}