{
  "type": "Feature",
  "properties": {
    "gn:admin1_code":"21.0",
    "gn:asciiname":"Falena",
    "gn:dem":1773,
    "gn:feature_class":"P",
    "gn:feature_code":"PPL",
    "gn:name":"Falena",
    "gn:population":0,
    "gn:timezone":"Africa/Windhoek",
    "wof:name":"Falena",
    "wof:placetype":"locality"
},
  "geometry": {"coordinates":[17.31667,-22.76667],"type":"Point"}
}