{
  "type": "Feature",
  "properties": {
    "oa:elevation_ft":"2211",
    "oa:type":"small_airport",
    "wd:wordcount":245,
    "woe:hierarchy":{
        "country_id":23424977,
        "county_id":12590471,
        "planet_id":1,
        "state_id":2347606
    },
    "wof:name":"Deer Park Municipal Airport",
    "wof:placetype":"campus"
},
  "geometry": {"coordinates":[-117.429,47.9669],"type":"Point"}
}