{
  "type": "Feature",
  "properties": {
    "name:ceb_x_preferred":[
        "Deer Park Airport"
    ],
    "name:eng_x_preferred":[
        "Deer Park Airport"
    ],
    "name:fas_x_preferred":[
        "\u0641\u0631\u0648\u062f\u06af\u0627\u0647 \u062f\u06cc\u0631 \u067e\u0627\u0631\u06a9"
    ],
    "name:ron_x_preferred":[
        "Aeroportul Deer Park"
    ],
    "name:tgk_x_preferred":[
        "\u0424\u0443\u0440\u0443\u0434\u0433\u043e\u04b3\u0438 \u0434\u0435\u0440 \u043f\u043e\u0440\u043a"
    ],
    "name:urd_x_preferred":[
        "\u0688\u06cc\u0626\u0631 \u067e\u0627\u0631\u06a9 \u0627\u06cc\u0626\u0631\u067e\u0648\u0631\u0679"
    ],
    "oa:elevation_ft":"2211",
    "oa:type":"small_airport",
    "wd:wordcount":245,
    "woe:hierarchy":{
        "country_id":23424977,
        "county_id":12590471,
        "planet_id":1,
        "state_id":2347606
    },
    "wof:name":"Deer Park Municipal Airport",
    "wof:placetype":"campus"
},
  "geometry": {"coordinates":[-117.429,47.9669],"type":"Point"}
}