{
  "type": "Feature",
  "properties": {
    "name:ceb_x_preferred":[
        "Pointe-\u00e0-Pitre Le Raizet Airport"
    ],
    "name:deu_x_preferred":[
        "Flughafen Pointe-\u00e0-Pitre"
    ],
    "name:eng_x_preferred":[
        "Pointe-\u00e0-Pitre International Airport"
    ],
    "name:eng_x_variant":[
        "PTP",
        "TFFR"
    ],
    "name:fas_x_preferred":[
        "\u0641\u0631\u0648\u062f\u06af\u0627\u0647 \u0628\u06cc\u0646\u200c\u0627\u0644\u0645\u0644\u0644\u06cc \u067e\u0648\u0627\u0646\u062a \u0622 \u067e\u06cc\u062a\u0631"
    ],
    "name:fra_x_preferred":[
        "a\u00e9roport de Guadeloupe - P\u00f4le Cara\u00efbes"
    ],
    "name:frc_x_preferred":[
        "Guadeloupe - P\u00f4le Cara\u00efbes"
    ],
    "name:heb_x_preferred":[
        "\u05e0\u05de\u05dc \u05d4\u05ea\u05e2\u05d5\u05e4\u05d4 \u05d2\u05d5\u05d0\u05d3\u05dc\u05d5\u05e4 \u05e4\u05d5\u05dc \u05e7\u05e8\u05d0\u05d9\u05d9\u05d1"
    ],
    "name:hun_x_preferred":[
        "Pointe-\u00e0-Pitre nemzetk\u00f6zi rep\u00fcl\u0151t\u00e9r"
    ],
    "name:ind_x_preferred":[
        "Bandar Udara Internasional Pointe-\u00e0-Pitre"
    ],
    "name:ita_x_preferred":[
        "Aeroporto Internazionale di Pointe-\u00e0-Pitre"
    ],
    "name:jpn_x_preferred":[
        "\u30dd\u30ef\u30f3\u30bf\u30d4\u30fc\u30c8\u30eb\u56fd\u969b\u7a7a\u6e2f"
    ],
    "name:kor_x_preferred":[
        "\ud478\uc575\ud0c0\ud53c\ud2b8\ub974 \uad6d\uc81c\uacf5\ud56d"
    ],
    "name:msa_x_preferred":[
        "Lapangan Terbang Le Raizet"
    ],
    "name:nld_x_preferred":[
        "Pointe-\u00e0-Pitre International Airport"
    ],
    "name:pol_x_preferred":[
        "Port lotniczy Pointe-\u00e0-Pitre"
    ],
    "name:por_x_preferred":[
        "Aeroporto Internacional de Pointe-\u00e0-Pitre"
    ],
    "name:ron_x_preferred":[
        "Aeroportul Interna\u021bional Pointe-\u00e0-Pitre"
    ],
    "name:rus_x_preferred":[
        "\u041c\u0435\u0436\u0434\u0443\u043d\u0430\u0440\u043e\u0434\u043d\u044b\u0439 \u0430\u044d\u0440\u043e\u043f\u043e\u0440\u0442 \u041f\u0443\u044d\u043d\u0442-\u0430-\u041f\u0438\u0442\u0440"
    ],
    "name:spa_x_preferred":[
        "Aeropuerto Internacional de Pointe-\u00e0-Pitre"
    ],
    "name:swe_x_preferred":[
        "Pointe-\u00e0-Pitre Le Raizet Airport"
    ],
    "name:tgk_x_preferred":[
        "\u0424\u0443\u0440\u0443\u0434\u0433\u043e\u04b3\u0438 \u0431\u0438\u043d\u200c\u0430\u043b\u043c\u0438\u043b\u0430\u043b\u04e3 \u043f\u0443\u043e\u043d\u0442 \u043c\u0435\u043e\u043c\u0430\u0434\u04e3 \u043f\u0435\u0442\u0438\u0440"
    ],
    "name:vie_x_preferred":[
        "S\u00e2n bay qu\u1ed1c t\u1ebf Pointe-\u00e0-Pitre"
    ],
    "name:zho_x_preferred":[
        "\u5f6d\u5fb7-\u96c5\u76ae\u7279\u570b\u969b\u6a5f\u5834"
    ],
    "oa:elevation_ft":"36",
    "oa:type":"medium_airport",
    "woe:hierarchy":{
        "country_id":23424831,
        "county_id":24551311,
        "planet_id":1,
        "state_id":28358256
    },
    "wof:name":"Le Raizet Airport",
    "wof:placetype":"campus"
},
  "geometry": {"coordinates":[-61.531799,16.265301],"type":"Point"}
}