{
  "type": "Feature",
  "properties": {
    "wof:name":"Foxtown",
    "wof:placetype":"neighbourhood"
},
  "geometry": {"coordinates":[-94.54365595333479,39.00185983599351],"type":"Point"}
}