{
  "type": "Feature",
  "properties": {
    "name:bul_x_preferred":[
        "\u0414\u0432\u0430\u0434\u0435\u0441\u0435\u0442 \u0438 \u0432\u0442\u043e\u0440\u0430 \u0449\u0443\u0440\u043c\u043e\u0432\u0430 \u0430\u0432\u0438\u043e\u0431\u0430\u0437\u0430"
    ],
    "name:ceb_x_preferred":[
        "Bezmer Air Base"
    ],
    "name:deu_x_preferred":[
        "Amerikanische Milit\u00e4rbasen in Bulgarien"
    ],
    "name:deu_x_variant":[
        "Luftwaffenst\u00fctzpunkt Besmer"
    ],
    "name:eng_x_preferred":[
        "Bezmer Air Base"
    ],
    "name:eng_x_variant":[
        "JAM",
        "BG-JAM"
    ],
    "name:fas_x_preferred":[
        "\u067e\u0627\u06cc\u06af\u0627\u0647 \u0647\u0648\u0627\u06cc\u06cc \u0628\u0632\u0645\u0631"
    ],
    "name:jpn_x_preferred":[
        "\u30d9\u30c4\u30e1\u30eb\u7a7a\u8ecd\u57fa\u5730"
    ],
    "name:msa_x_preferred":[
        "Lapangan Terbang Bezmer"
    ],
    "name:pol_x_preferred":[
        "Port lotniczy Jambo\u0142-Bezmer"
    ],
    "name:swe_x_preferred":[
        "Bezmer Air Base"
    ],
    "name:tgk_x_preferred":[
        "\u041f\u043e\u0439\u0433\u043e\u04b3\u0438 \u04b3\u0430\u0432\u043e\u0438\u0438 \u0411\u0435\u0437\u043c\u0435\u0440"
    ],
    "oa:elevation_ft":"509",
    "oa:type":"medium_airport",
    "wd:wordcount":387,
    "woe:hierarchy":{
        "country_id":23424771,
        "county_id":55873892,
        "planet_id":1,
        "state_id":20070074
    },
    "wof:name":"Jambol Airport",
    "wof:placetype":"campus"
},
  "geometry": {"coordinates":[26.3522,42.454899],"type":"Point"}
}