{
  "type": "Feature",
  "properties": {
    "name:ara_x_preferred":[
        "\u0645\u0637\u0627\u0631 \u0628\u0627\u0648\u062a\u0648 \u064a\u0631\u0644\u064a\u0628\u0627\u0646"
    ],
    "name:eng_x_preferred":[
        "Baotou Erliban Airport"
    ],
    "name:eng_x_variant":[
        "BAV",
        "ZBOW"
    ],
    "name:eus_x_preferred":[
        "Baotou aireportua"
    ],
    "name:fas_x_preferred":[
        "\u0641\u0631\u0648\u062f\u06af\u0627\u0647 \u0628\u0627\u0626\u0648\u062a\u0648 \u0627\u0631\u0644\u06cc\u0628\u0627\u0646"
    ],
    "name:fra_x_preferred":[
        "A\u00e9roport de Baotou Erliban"
    ],
    "name:fra_x_variant":[
        "a\u00e9roport de Baotou Erliban"
    ],
    "name:ind_x_preferred":[
        "Bandar Udara Erliban Baotou"
    ],
    "name:jpn_x_preferred":[
        "\u5305\u982d\u7a7a\u6e2f"
    ],
    "name:nld_x_preferred":[
        "Baotou Erliban Airport"
    ],
    "name:pol_x_preferred":[
        "Port lotniczy Baotou"
    ],
    "name:rus_x_preferred":[
        "\u0411\u0430\u043e\u0442\u043e\u0443 \u042d\u0440\u043b\u0438\u0431\u0430\u043d\u044c"
    ],
    "name:spa_x_preferred":[
        "Aeropuerto de Baotou Erliban"
    ],
    "name:swe_x_preferred":[
        "Baotou Erliban Airport"
    ],
    "name:tgk_x_preferred":[
        "\u0424\u0443\u0440\u0443\u0434\u0433\u043e\u04b3\u0438 \u0431\u043e\u0435\u04b3\u0432\u0442\u0443 \u043e\u0440\u043b\u0438\u0431\u043e\u043d"
    ],
    "name:vie_x_preferred":[
        "S\u00e2n bay Bao \u0110\u1ea7u"
    ],
    "name:zho_x_preferred":[
        "\u5305\u5934\u673a\u573a"
    ],
    "oa:elevation_ft":"3321",
    "oa:type":"medium_airport",
    "wd:wordcount":137,
    "woe:hierarchy":{
        "country_id":23424781,
        "county_id":26198284,
        "localadmin_id":12686817,
        "planet_id":1,
        "state_id":12578009
    },
    "wof:name":"Baotou Airport",
    "wof:placetype":"campus"
},
  "geometry": {"coordinates":[109.99700199999999,40.560001],"type":"Point"}
}