{
  "type": "Feature",
  "properties": {
    "name:afr_x_preferred":[
        "Fourways"
    ],
    "name:nso_x_preferred":[
        "Fourways"
    ],
    "wof:name":"Fourways",
    "wof:placetype":"neighbourhood"
},
  "geometry": {"coordinates":[28.00198605480943,-26.00286726255056],"type":"Point"}
}