{
  "type": "Feature",
  "properties": {
    "name:ceb_x_preferred":[
        "Vitim Airport"
    ],
    "name:eng_x_preferred":[
        "Vitim Airport"
    ],
    "name:eng_x_variant":[
        "UERT"
    ],
    "name:fas_x_preferred":[
        "\u0641\u0631\u0648\u062f\u06af\u0627\u0647 \u0648\u06cc\u062a\u06cc\u0645"
    ],
    "name:ron_x_preferred":[
        "Aeroportul Vitim"
    ],
    "name:rus_x_preferred":[
        "\u0412\u0438\u0442\u0438\u043c"
    ],
    "name:zho_x_preferred":[
        "\u7dad\u5b63\u59c6\u6a5f\u5834"
    ],
    "oa:elevation_ft":"610",
    "oa:type":"small_airport",
    "wd:wordcount":55,
    "woe:hierarchy":{
        "country_id":23424936,
        "county_id":12597633,
        "planet_id":1,
        "state_id":2346881
    },
    "wof:name":"Vitim Airport",
    "wof:placetype":"campus"
},
  "geometry": {"coordinates":[112.564167,59.458333],"type":"Point"}
}