{
  "type": "Feature",
  "properties": {
    "name:fas_x_preferred":[
        "\u0641\u0631\u0648\u062f\u06af\u0627\u0647 \u0648\u06cc\u062a\u06cc\u0645"
    ],
    "oa:elevation_ft":"610",
    "oa:type":"small_airport",
    "wd:wordcount":55,
    "woe:hierarchy":{
        "country_id":23424936,
        "county_id":12597633,
        "planet_id":1,
        "state_id":2346881
    },
    "wof:name":"Vitim Airport",
    "wof:placetype":"campus"
},
  "geometry": {"coordinates":[112.5641667,59.45833333],"type":"Point"}
}