{
  "type": "Feature",
  "properties": {
    "name:eng_x_preferred":[
        "Lingayen Airport"
    ],
    "name:fas_x_preferred":[
        "\u0641\u0631\u0648\u062f\u06af\u0627\u0647 \u0644\u06cc\u0646\u06af\u0627\u06cc\u0646"
    ],
    "name:jpn_x_preferred":[
        "\u30ea\u30f3\u30ac\u30a8\u30f3\u7a7a\u6e2f"
    ],
    "name:msa_x_preferred":[
        "Lapangan Terbang Lingayen Natl"
    ],
    "name:ron_x_preferred":[
        "Aeroportul Lingayen"
    ],
    "name:tgk_x_preferred":[
        "\u0424\u0443\u0440\u0443\u0434\u0433\u043e\u04b3\u0438 \u043b\u0438\u043d\u0433\u043e\u0438\u043d"
    ],
    "oa:elevation_ft":"7",
    "oa:type":"small_airport",
    "wd:wordcount":616,
    "woe:hierarchy":{
        "country_id":23424934,
        "county_id":2346705,
        "planet_id":1,
        "state_id":23424724
    },
    "wof:name":"Lingayen Airport",
    "wof:placetype":"campus"
},
  "geometry": {"coordinates":[120.24161388889,16.035058333333],"type":"Point"}
}