{
  "type": "Feature",
  "properties": {
    "wof:name":"Grasslyn Manor",
    "wof:placetype":"neighbourhood"
},
  "geometry": {"coordinates":[-87.98070088591122,43.08376193075105],"type":"Point"}
}