{
  "type": "Feature",
  "properties": {
    "name:chi_x_preferred":[
        "\u5967\u723e\u5eb7\u4f2f\u91cc\u7687\u5bb6\u7a7a\u8ecd\u57fa\u5730"
    ],
    "name:dut_x_preferred":[
        "RAF Alconbury"
    ],
    "name:eng_x_preferred":[
        "RAF Alconbury"
    ],
    "name:eng_x_variant":[
        "AYH",
        "EGWZ"
    ],
    "name:fre_x_preferred":[
        "RAF Alconbury"
    ],
    "name:ger_x_preferred":[
        "RAF Alconbury"
    ],
    "name:per_x_preferred":[
        "\u0641\u0631\u0648\u062f\u06af\u0627\u0647 \u0646\u06cc\u0631\u0648\u06cc \u0647\u0648\u0627\u06cc\u06cc \u0633\u0644\u0637\u0646\u062a\u06cc \u0627\u0644\u06a9\u0648\u0646\u0628\u0631\u06cc"
    ],
    "oa:elevation_ft":"157",
    "oa:type":"closed",
    "woe:hierarchy":{
        "country_id":23424975,
        "county_id":12602140,
        "localadmin_id":12695885,
        "planet_id":1,
        "state_id":24554868
    },
    "wof:name":"Alconbury Airport",
    "wof:placetype":"campus"
},
  "geometry": {"coordinates":[-0.219722,52.374401],"type":"Point"}
}