{
  "type": "Feature",
  "properties": {
    "name:ara_x_preferred":[
        "\u0645\u0637\u0627\u0631 \u0647\u0648\u0646"
    ],
    "name:ceb_x_preferred":[
        "Hon Airport"
    ],
    "name:deu_x_preferred":[
        "Flughafen Hun"
    ],
    "name:eng_x_preferred":[
        "Waddan Airport"
    ],
    "name:eng_x_variant":[
        "HUQ",
        "HLON",
        "Hun Airport"
    ],
    "name:fra_x_preferred":[
        "HUQ"
    ],
    "name:jpn_x_preferred":[
        "\u30d5\u30fc\u30f3\u7a7a\u6e2f"
    ],
    "name:msa_x_preferred":[
        "Lapangan Terbang Hon"
    ],
    "name:pol_x_preferred":[
        "Port lotniczy Hun"
    ],
    "name:ron_x_preferred":[
        "Aeroportul Hun"
    ],
    "name:swe_x_preferred":[
        "Hon Airport"
    ],
    "oa:elevation_ft":"919",
    "oa:type":"small_airport",
    "woe:hierarchy":{
        "country_id":23424882,
        "planet_id":1,
        "state_id":2346122
    },
    "wof:name":"Hon Airport",
    "wof:placetype":"campus"
},
  "geometry": {"coordinates":[15.9656,29.1101],"type":"Point"}
}