{
  "type": "Feature",
  "properties": {
    "name:fas_x_preferred":[
        "\u0641\u0631\u0648\u062f\u06af\u0627\u0647 \u0634\u0647\u0631\u06cc \u0634\u0627\u0648\u0627\u0646\u0648"
    ],
    "name:tgk_x_preferred":[
        "\u0424\u0443\u0440\u0443\u0434\u0433\u043e\u04b3\u0438 \u0448\u0430\u04b3\u0440\u0435 \u0448\u043e\u0432\u043e\u043d\u0443"
    ],
    "oa:elevation_ft":"813",
    "oa:type":"small_airport",
    "wd:wordcount":364,
    "woe:hierarchy":{
        "country_id":23424977,
        "county_id":12590591,
        "planet_id":1,
        "state_id":2347608
    },
    "wof:name":"Shawano Municipal Airport",
    "wof:placetype":"campus"
},
  "geometry": {"coordinates":[-88.56,44.787222222222],"type":"Point"}
}