{
  "type": "Feature",
  "properties": {
    "name:ara_x_preferred":[
        "\u0645\u0637\u0627\u0631 \u062f\u064a\u0628\u0631\u0648\u062c\u0627\u0631\u0647"
    ],
    "name:asm_x_preferred":[
        "\u09a1\u09bf\u09ac\u09cd\u09f0\u09c1\u0997\u09a1\u09bc \u09ac\u09bf\u09ae\u09be\u09a8\u09ac\u09a8\u09cd\u09a6\u09f0"
    ],
    "name:ben_x_preferred":[
        "\u09a1\u09bf\u09ac\u09cd\u09b0\u09c1\u0997\u09a1\u09bc \u09ac\u09bf\u09ae\u09be\u09a8\u09ac\u09a8\u09cd\u09a6\u09b0"
    ],
    "name:ceb_x_preferred":[
        "Dibrugarh Airport"
    ],
    "name:eng_x_preferred":[
        "Dibrugarh Airport"
    ],
    "name:eng_x_variant":[
        "DIB",
        "VEMN"
    ],
    "name:fas_x_preferred":[
        "\u0641\u0631\u0648\u062f\u06af\u0627\u0647 \u062f\u0627\u06cc\u0628\u0631\u0648\u06af\u0627\u0631"
    ],
    "name:hin_x_preferred":[
        "\u0921\u093f\u092c\u094d\u0930\u0941\u0917\u0922\u093c \u0935\u093f\u092e\u093e\u0928\u0915\u094d\u0937\u0947\u0924\u094d\u0930"
    ],
    "name:jpn_x_preferred":[
        "\u30c7\u30a3\u30d6\u30eb\u30ac\u30eb\u7a7a\u6e2f"
    ],
    "name:mar_x_preferred":[
        "\u0926\u093f\u092c\u094d\u0930\u0941\u0917\u0922 \u0935\u093f\u092e\u093e\u0928\u0924\u0933"
    ],
    "name:msa_x_preferred":[
        "Lapangan Terbang Dibrugarh"
    ],
    "name:ori_x_preferred":[
        "\u0b2c\u0b4d\u0b5f\u0b2c\u0b39\u0b3e\u0b30\u0b15\u0b3e\u0b30\u0b40:Runab WMF/Odia test page"
    ],
    "name:pol_x_preferred":[
        "Port lotniczy Dibrugarh"
    ],
    "name:ron_x_preferred":[
        "Aeroportul Dibrugarh"
    ],
    "name:spa_x_preferred":[
        "Aeropuerto de Dibrugarh"
    ],
    "name:swe_x_preferred":[
        "Dibrugarh Airport"
    ],
    "name:tam_x_preferred":[
        "\u0ba4\u0bbf\u0baa\u0bcd\u0bb0\u0bc1\u0b95\u0bb0\u0bcd \u0bb5\u0bbf\u0bae\u0bbe\u0ba9 \u0ba8\u0bbf\u0bb2\u0bc8\u0baf\u0bae\u0bcd"
    ],
    "name:tam_x_variant":[
        "\u0ba4\u0bbf\u0baa\u0bcd\u0bb0\u0bc1\u0b95\u0bbe\u0bb0\u0bcd \u0bb5\u0bbf\u0bae\u0bbe\u0ba9 \u0ba8\u0bbf\u0bb2\u0bc8\u0baf\u0bae\u0bcd"
    ],
    "name:tgk_x_preferred":[
        "\u0424\u0443\u0440\u0443\u0434\u0433\u043e\u04b3\u0438 \u0434\u043e\u0438\u0431\u0440\u0443\u0433\u043e\u0440"
    ],
    "name:vie_x_preferred":[
        "S\u00e2n bay Dibrugarh"
    ],
    "name:zho_x_preferred":[
        "\u8fea\u5e03\u9b6f\u52a0\u723e\u6a5f\u5834"
    ],
    "oa:elevation_ft":"362",
    "oa:type":"medium_airport",
    "wd:wordcount":203,
    "woe:hierarchy":{
        "country_id":23424848,
        "county_id":12586355,
        "planet_id":1,
        "state_id":2345741
    },
    "wof:name":"Dibrugarh Airport",
    "wof:placetype":"campus"
},
  "geometry": {"coordinates":[95.016899,27.4839],"type":"Point"}
}