{
  "type": "Feature",
  "properties": {
    "label:eng_x_preferred_longname":[
        "Dededo Village"
    ],
    "label:eng_x_preferred_placetype":[
        "village"
    ],
    "name:eng_x_preferred":[
        "Dededo"
    ],
    "qs:name":"Dededo",
    "qs:name_adm0":"Guam",
    "qs:name_adm1":"Dededo",
    "qs:photos":124,
    "qs:photos_1k":25,
    "qs:photos_9k":2,
    "qs:photos_9r":5,
    "qs:photos_all":468,
    "qs:photos_sr":3,
    "qs:placetype":"State",
    "qs:pop_sr":"0",
    "wd:wordcount":579,
    "wof:name":"Dededo",
    "wof:placetype":"region"
},
  "geometry": {"coordinates":[144.857043,13.652305],"type":"Point"}
}