{
  "type": "Feature",
  "properties": {
    "label:eng_x_preferred_longname":[
        "Dededo Village"
    ],
    "label:eng_x_preferred_placetype":[
        "village"
    ],
    "name:ara_x_preferred":[
        "\u062f\u064a\u062f\u064a\u062f\u0648"
    ],
    "name:arz_x_preferred":[
        "\u062f\u064a\u062f\u064a\u062f\u0648"
    ],
    "name:azb_x_preferred":[
        "\u062f\u062f\u062f\u0648"
    ],
    "name:ceb_x_preferred":[
        "Dededo Municipality"
    ],
    "name:cha_x_preferred":[
        "Dedidu"
    ],
    "name:cym_x_preferred":[
        "Dededo"
    ],
    "name:deu_x_preferred":[
        "Dededo"
    ],
    "name:eng_x_preferred":[
        "Dededo"
    ],
    "name:eus_x_preferred":[
        "Dededo"
    ],
    "name:fas_x_preferred":[
        "\u062f\u062f\u06cc\u062f\u0648"
    ],
    "name:fra_x_preferred":[
        "Dededo"
    ],
    "name:glg_x_preferred":[
        "Dededo"
    ],
    "name:heb_x_preferred":[
        "\u05d3\u05d3\u05d3\u05d5"
    ],
    "name:ita_x_preferred":[
        "Dededo"
    ],
    "name:jpn_x_preferred":[
        "\u30c7\u30c7\u30c9"
    ],
    "name:kor_x_preferred":[
        "\ub370\ub370\ub3c4"
    ],
    "name:lit_x_preferred":[
        "Dededas"
    ],
    "name:nld_x_preferred":[
        "Dededo"
    ],
    "name:nno_x_preferred":[
        "Dededo"
    ],
    "name:nob_x_preferred":[
        "Dededo"
    ],
    "name:pol_x_preferred":[
        "Dededo"
    ],
    "name:por_x_preferred":[
        "Dededo"
    ],
    "name:pus_x_preferred":[
        "\u062f\u062f\u06cc\u062f\u0648"
    ],
    "name:rus_x_preferred":[
        "\u0414\u0435\u0434\u0435\u0434\u043e"
    ],
    "name:spa_x_preferred":[
        "Dededo"
    ],
    "name:swe_x_preferred":[
        "Dededo"
    ],
    "name:ukr_x_preferred":[
        "\u0414\u0435\u0434\u0435\u0434\u043e"
    ],
    "name:urd_x_preferred":[
        "\u062f\u06cc\u062f\u06cc\u062f\u0648"
    ],
    "name:war_x_preferred":[
        "Dededo"
    ],
    "name:zho_x_preferred":[
        "\u8fea\u8fea\u591a"
    ],
    "name:zho_x_variant":[
        "\u5fb7\u5fb7\u591a"
    ],
    "qs:name":"Dededo",
    "qs:name_adm0":"Guam",
    "qs:name_adm1":"Dededo",
    "qs:photos":124,
    "qs:photos_1k":25,
    "qs:photos_9k":2,
    "qs:photos_9r":5,
    "qs:photos_all":468,
    "qs:photos_sr":3,
    "qs:placetype":"State",
    "qs:pop_sr":"0",
    "wd:wordcount":579,
    "wof:name":"Dededo",
    "wof:placetype":"region"
},
  "geometry": {"coordinates":[144.857043,13.652305],"type":"Point"}
}