{
  "type": "Feature",
  "properties": {
    "gn:admin1_code":"35.0",
    "gn:asciiname":"Sarie Mare",
    "gn:dem":1377,
    "gn:feature_class":"P",
    "gn:feature_code":"PPL",
    "gn:name":"Sarie Mar\u00e9",
    "gn:population":0,
    "gn:timezone":"Africa/Windhoek",
    "wof:name":"Sarie Mare",
    "wof:placetype":"locality"
},
  "geometry": {"coordinates":[19.28333,-23.08333],"type":"Point"}
}