{
  "type": "Feature",
  "properties": {
    "name:eng_x_preferred":[
        "Shionecho 8 Chome"
    ],
    "name:eng_x_variant":[
        "Shionechou 8 Choume",
        "Shionecho 8 Chome"
    ],
    "name:jpn_x_preferred":[
        "\uff18\u4e01\u76ee"
    ],
    "name:jpn_x_variant":[
        "\u3057\u304a\u306d\u3061\u3087\u3046 \uff18\u3061\u3087\u3046\u3081",
        "\u6f6e\u97f3\u753a \uff18\u4e01\u76ee",
        "\uff18\u3061\u3087\u3046\u3081"
    ],
    "qs:gn_local":0,
    "qs:local_max":18,
    "qs:local_sum":38,
    "qs:localhoods":3,
    "qs:name":"\uff18\u4e01\u76ee",
    "qs:name_adm0":"\u65e5\u672c",
    "qs:name_adm1":"\u5c71\u53e3\u770c",
    "qs:name_en":"Shionecho 8 Chome",
    "qs:name_lau":"\u6f6e\u97f3\u753a",
    "qs:name_local":"\u4e0b\u677e\u5e02",
    "qs:photo_max":6,
    "qs:photo_sum":7,
    "qs:placetype":"Suburb",
    "qs:quad_count":2,
    "qs:woe_adm0":23424856,
    "qs:woe_adm1":2345894,
    "qs:woe_adm2":0,
    "qs:woe_lau":28476619,
    "qs:woe_local":1117595,
    "qs:woe_ver":"7.10.0",
    "wof:lang":[
        "jpn"
    ],
    "wof:name":"\uff18\u4e01\u76ee",
    "wof:placetype":"neighbourhood"
},
  "geometry": {"coordinates":[131.84417500000001,34.011363],"type":"Point"}
}