{
  "type": "Feature",
  "properties": {
    "name:eng_x_preferred":[
        "Tanglewood"
    ],
    "name:fre_x_preferred":[
        "Tanglewood"
    ],
    "name:sco_x_preferred":[
        "Tanglewood"
    ],
    "wd:wordcount":1108,
    "wof:name":"Tanglewood",
    "wof:placetype":"neighbourhood"
},
  "geometry": {"coordinates":[-95.47295459544316,29.75573224710493],"type":"Point"}
}