{
  "type": "Feature",
  "properties": {
    "name:eng_x_preferred":[
        "Tanglewood"
    ],
    "name:fra_x_preferred":[
        "Tanglewood"
    ],
    "name:nld_x_preferred":[
        "Tanglewood"
    ],
    "name:sco_x_preferred":[
        "Tanglewood"
    ],
    "wd:wordcount":1108,
    "wof:name":"Tanglewood",
    "wof:placetype":"neighbourhood"
},
  "geometry": {"coordinates":[-95.472955,29.755732],"type":"Point"}
}