{
  "type": "Feature",
  "properties": {
    "name:ceb_x_preferred":[
        "Armstrong"
    ],
    "name:fas_x_preferred":[
        "\u0641\u0631\u0648\u062f\u06af\u0627\u0647 \u0622\u0631\u0645\u0633\u062a\u0631\u0627\u0646\u06af"
    ],
    "name:msa_x_preferred":[
        "Lapangan Terbang Armstrong"
    ],
    "name:pms_x_preferred":[
        "Armstrong Airport"
    ],
    "name:swe_x_preferred":[
        "Armstrong"
    ],
    "name:tgk_x_preferred":[
        "\u0424\u0443\u0440\u0443\u0434\u0433\u043e\u04b3\u0438 \u043e\u0440\u043c\u0441\u0442\u0440\u043e\u043d\u0433"
    ],
    "oa:elevation_ft":"1058",
    "oa:type":"medium_airport",
    "wd:wordcount":59,
    "woe:hierarchy":{
        "country_id":23424775,
        "county_id":29375089,
        "planet_id":1,
        "state_id":2344922
    },
    "wof:name":"Armstrong Airport",
    "wof:placetype":"campus"
},
  "geometry": {"coordinates":[-88.9097,50.2903],"type":"Point"}
}