{
  "type": "Feature",
  "properties": {
    "gn:admin1_code":"38.0",
    "gn:asciiname":"Onamutenya",
    "gn:dem":1106,
    "gn:feature_class":"P",
    "gn:feature_code":"PPL",
    "gn:name":"Onamutenya",
    "gn:population":0,
    "gn:timezone":"Africa/Windhoek",
    "wof:name":"Onamutenya",
    "wof:placetype":"locality"
},
  "geometry": {"coordinates":[16.28333,-17.86667000000001],"type":"Point"}
}