{
  "type": "Feature",
  "properties": {
    "gn:admin1_code":"33.0",
    "gn:asciiname":"Ondingwanyama",
    "gn:dem":1119,
    "gn:feature_class":"P",
    "gn:feature_code":"PPL",
    "gn:name":"Ondingwanyama",
    "gn:population":0,
    "gn:timezone":"Africa/Windhoek",
    "wof:name":"Ondingwanyama",
    "wof:placetype":"locality"
},
  "geometry": {"coordinates":[16.31667,-17.55],"type":"Point"}
}