{
  "type": "Feature",
  "properties": {
    "name:pol_x_preferred":[
        "Bulwar Las Olas"
    ],
    "wd:wordcount":708,
    "wof:name":"Las Olas Isles",
    "wof:placetype":"neighbourhood"
},
  "geometry": {"coordinates":[-80.12067618720614,26.11668974787034],"type":"Point"}
}