{
  "type": "Feature",
  "properties": {
    "name:eng_x_preferred":[
        "Port Nelson Airport"
    ],
    "name:eng_x_variant":[
        "RCY",
        "MYRP"
    ],
    "name:jpn_x_preferred":[
        "\u30dd\u30fc\u30c8\u30fb\u30cd\u30eb\u30bd\u30f3\u7a7a\u6e2f"
    ],
    "name:per_x_preferred":[
        "\u0641\u0631\u0648\u062f\u06af\u0627\u0647 \u067e\u0648\u0631\u062a \u0646\u0644\u0633\u0648\u0646"
    ],
    "name:swe_x_preferred":[
        "Port Nelson Airport"
    ],
    "name:tgk_x_preferred":[
        "\u0424\u0443\u0440\u0443\u0434\u0433\u043e\u04b3\u0438 \u043f\u04ef\u0440 \u043d\u043b\u0441\u0443\u043d"
    ],
    "oa:elevation_ft":"15",
    "oa:type":"small_airport",
    "woe:hierarchy":{
        "country_id":23424758,
        "planet_id":1,
        "state_id":24551252
    },
    "wof:name":"Rum Cay Airport",
    "wof:placetype":"campus"
},
  "geometry": {"coordinates":[-74.836197,23.684401],"type":"Point"}
}