{
  "type": "Feature",
  "properties": {
    "wof:name":"None",
    "wof:placetype":"neighbourhood"
},
  "geometry": {"coordinates":[-157.95235582430294,21.29567036969317],"type":"Point"}
}