{
  "type": "Feature",
  "properties": {
    "wof:name":"Village 5",
    "wof:placetype":"neighbourhood"
},
  "geometry": {"coordinates":[-121.50074224594431,38.65249913237493],"type":"Point"}
}