{
  "type": "Feature",
  "properties": {
    "wof:name":"Old Redford",
    "wof:placetype":"neighbourhood"
},
  "geometry": {"coordinates":[-83.26067952957473,42.42136165745205],"type":"Point"}
}