{
  "type": "Feature",
  "properties": {
    "wof:name":"Bow Ridge",
    "wof:placetype":"neighbourhood"
},
  "geometry": {"coordinates":[-114.50886945796306,51.18620597434926],"type":"Point"}
}