{
  "type": "Feature",
  "properties": {
    "gn:admin1_code":"41.0",
    "gn:asciiname":"Mayenzere",
    "gn:dem":1076,
    "gn:feature_class":"P",
    "gn:feature_code":"PPL",
    "gn:name":"Mayenzere",
    "gn:population":0,
    "gn:timezone":"Africa/Windhoek",
    "name:und_x_variant":[
        "Majenzele",
        "Maienzele",
        "Maenzere",
        "Mayenzere"
    ],
    "wof:name":"Mayenzere",
    "wof:placetype":"locality"
},
  "geometry": {"coordinates":[19.15,-17.81667000000001],"type":"Point"}
}