{
  "type": "Feature",
  "properties": {
    "oa:elevation_ft":"1690",
    "oa:type":"small_airport",
    "woe:hierarchy":{
        "country_id":23424829,
        "county_id":12596730,
        "localadmin_id":12622769,
        "planet_id":1,
        "state_id":2345482
    },
    "wof:name":"Flugplatz Bad Endorf",
    "wof:placetype":"campus"
},
  "geometry": {"coordinates":[12.288055555556,47.925277777778],"type":"Point"}
}