{
  "type": "Feature",
  "properties": {
    "gn:admin1_code":"35.0",
    "gn:asciiname":"Okomboha",
    "gn:dem":1282,
    "gn:feature_class":"P",
    "gn:feature_code":"PPL",
    "gn:name":"Okomboha",
    "gn:population":0,
    "gn:timezone":"Africa/Windhoek",
    "wof:name":"Okomboha",
    "wof:placetype":"locality"
},
  "geometry": {"coordinates":[19.78333,-23.05],"type":"Point"}
}