{
  "type": "Feature",
  "properties": {
    "name:ceb_x_preferred":[
        "Tiko Airport"
    ],
    "name:eng_x_preferred":[
        "Tiko Airport"
    ],
    "name:eng_x_variant":[
        "TKC",
        "FKKC"
    ],
    "name:fas_x_preferred":[
        "\u0641\u0631\u0648\u062f\u06af\u0627\u0647 \u062a\u06cc\u06a9\u0648"
    ],
    "name:fra_x_preferred":[
        "A\u00e9roport de Tiko"
    ],
    "name:fra_x_variant":[
        "a\u00e9roport de Tiko"
    ],
    "name:ind_x_preferred":[
        "Bandar Udara Tiko"
    ],
    "name:jpn_x_preferred":[
        "\u30c1\u30b3\u7a7a\u6e2f"
    ],
    "name:msa_x_preferred":[
        "Lapangan Terbang Tiko"
    ],
    "name:pol_x_preferred":[
        "Port lotniczy Tiko"
    ],
    "name:ron_x_preferred":[
        "Aeroportul Tiko"
    ],
    "name:swe_x_preferred":[
        "Tiko Airport"
    ],
    "name:tgk_x_preferred":[
        "\u0424\u0443\u0440\u0443\u0434\u0433\u043e\u04b3\u0438 \u0442\u0438\u043a\u0443"
    ],
    "oa:elevation_ft":"151",
    "oa:type":"medium_airport",
    "wd:wordcount":56,
    "woe:hierarchy":{
        "country_id":23424785,
        "planet_id":1,
        "state_id":2345037
    },
    "wof:name":"Tiko Airport",
    "wof:placetype":"campus"
},
  "geometry": {"coordinates":[9.36053,4.08919],"type":"Point"}
}