{
  "type": "Feature",
  "properties": {
    "name:ceb_x_preferred":[
        "Saint John"
    ],
    "name:eng_x_preferred":[
        "Saint John Airport"
    ],
    "name:eng_x_variant":[
        "YSJ",
        "CYSJ"
    ],
    "name:fas_x_preferred":[
        "\u0641\u0631\u0648\u062f\u06af\u0627\u0647 \u0633\u0646\u062a \u062c\u0627\u0646"
    ],
    "name:fin_x_preferred":[
        "Saint Johnin lentoasema"
    ],
    "name:fra_x_preferred":[
        "A\u00e9roport de Saint-Jean"
    ],
    "name:fra_x_variant":[
        "a\u00e9roport de Saint-Jean"
    ],
    "name:ind_x_preferred":[
        "Bandar Udara Saint John"
    ],
    "name:jpn_x_preferred":[
        "\u30bb\u30f3\u30c8\u30b8\u30e7\u30f3\u7a7a\u6e2f"
    ],
    "name:msa_x_preferred":[
        "Lapangan Terbang Saint John"
    ],
    "name:pms_x_preferred":[
        "Saint John Airport"
    ],
    "name:pol_x_preferred":[
        "Port lotniczy Saint John"
    ],
    "name:ron_x_preferred":[
        "Aeroportul Saint John"
    ],
    "name:spa_x_preferred":[
        "Aeropuerto de Saint John"
    ],
    "name:swe_x_preferred":[
        "Saint John"
    ],
    "name:tgk_x_preferred":[
        "\u0424\u0443\u0440\u0443\u0434\u0433\u043e\u04b3\u0438 \u0421\u0443\u043d\u043d\u0430\u0442 \u04b7\u043e\u043d"
    ],
    "oa:elevation_ft":"357",
    "oa:type":"medium_airport",
    "wd:wordcount":266,
    "woe:hierarchy":{
        "country_id":23424775,
        "county_id":29375162,
        "planet_id":1,
        "state_id":2344918
    },
    "wof:name":"Saint John Airport",
    "wof:placetype":"campus"
},
  "geometry": {"coordinates":[-65.890297,45.316101],"type":"Point"}
}