{
  "type": "Feature",
  "properties": {
    "label:eng_x_preferred_longname":[
        "Hao County"
    ],
    "label:eng_x_preferred_placetype":[
        "county"
    ],
    "name:ceb_x_preferred":[
        "Hao"
    ],
    "name:deu_x_preferred":[
        "Hao"
    ],
    "name:eng_x_preferred":[
        "Hao"
    ],
    "name:fra_x_preferred":[
        "Hao"
    ],
    "name:por_x_preferred":[
        "Hao"
    ],
    "name:rus_x_preferred":[
        "\u0425\u0430\u043e"
    ],
    "name:spa_x_preferred":[
        "Hao"
    ],
    "name:swe_x_preferred":[
        "Hao"
    ],
    "qs:name":"Hao",
    "qs:name_adm0":"Polyn\u00e9sie Fran\u00e7aise",
    "qs:name_adm1":"Tuamotu-Gambier",
    "qs:photos":37,
    "qs:photos_1k":7,
    "qs:photos_9k":1,
    "qs:photos_9r":2,
    "qs:photos_all":37,
    "qs:photos_sr":2,
    "qs:placetype":"County",
    "qs:pop_sr":"0",
    "wd:wordcount":101,
    "wof:name":"Hao",
    "wof:placetype":"county"
},
  "geometry": {"coordinates":[-140.90875600000001,-18.0832],"type":"Point"}
}