{
  "type": "Feature",
  "properties": {
    "name:eng_x_variant":[
        "MHB",
        "NZMB"
    ],
    "oa:elevation_ft":"5",
    "oa:type":"heliport",
    "woe:hierarchy":{
        "country_id":23424916,
        "county_id":55875921,
        "planet_id":1,
        "state_id":15021756,
        "suburb_id":2350082
    },
    "wof:name":"Auckland Mechanics Bay Seaplane Base",
    "wof:placetype":"campus"
},
  "geometry": {"coordinates":[174.78787199999999,-36.846526],"type":"Point"}
}