{
  "type": "Feature",
  "properties": {
    "name:bul_x_preferred":[
        "\u0422\u043e\u043c\u0430\u0441\u0442\u0430\u0443\u043d"
    ],
    "name:ceb_x_preferred":[
        "Thomastown"
    ],
    "name:deu_x_preferred":[
        "Thomastown"
    ],
    "name:eus_x_preferred":[
        "Thomastown"
    ],
    "name:fra_x_preferred":[
        "Thomastown"
    ],
    "name:ita_x_preferred":[
        "Thomastown"
    ],
    "name:mlg_x_preferred":[
        "Thomastown"
    ],
    "name:nld_x_preferred":[
        "Thomastown"
    ],
    "name:pol_x_preferred":[
        "Thomastown"
    ],
    "name:rus_x_preferred":[
        "\u0422\u043e\u043c\u0430\u0441\u0442\u0430\u0443\u043d"
    ],
    "name:spa_x_preferred":[
        "Thomastown"
    ],
    "name:swe_x_preferred":[
        "Thomastown"
    ],
    "wof:name":"Thomastown",
    "wof:placetype":"neighbourhood"
},
  "geometry": {"coordinates":[145.006985300227,-37.68392417705893],"type":"Point"}
}