{
  "type": "Feature",
  "properties": {
    "name:ceb_x_preferred":[
        "Lecce Galatina Airport"
    ],
    "name:deu_x_preferred":[
        "Milit\u00e4rflugplatz Lecce-Galatina"
    ],
    "name:eng_x_preferred":[
        "Lecce Galatina Airport"
    ],
    "name:eng_x_variant":[
        "LCC",
        "LIBN"
    ],
    "name:est_x_preferred":[
        "Lecce Galatina lennujaam"
    ],
    "name:ita_x_preferred":[
        "Aeroporto di Lecce-Galatina"
    ],
    "name:jpn_x_preferred":[
        "\u30ec\u30c3\u30c1\u30a7\u30fb\u30ac\u30e9\u30c6\u30a3\u30fc\u30ca\u7a7a\u8ecd\u57fa\u5730"
    ],
    "name:msa_x_preferred":[
        "Lapangan Terbang Lecce Mil"
    ],
    "name:nld_x_preferred":[
        "Lecce Galatina Airport"
    ],
    "oa:elevation_ft":"156",
    "oa:type":"medium_airport",
    "woe:hierarchy":{
        "country_id":23424853,
        "county_id":12591821,
        "localadmin_id":12678794,
        "planet_id":1,
        "state_id":7153342
    },
    "wof:name":"Galatina Air Force Base",
    "wof:placetype":"campus"
},
  "geometry": {"coordinates":[18.133301,40.239201],"type":"Point"}
}