{
  "type": "Feature",
  "properties": {
    "name:eng_x_preferred":[
        "Los Siete Samanes Airport"
    ],
    "name:msa_x_preferred":[
        "Lapangan Terbang Los Siete Samanes"
    ],
    "name:ron_x_preferred":[
        "Aeroportul Los Siete Samanes"
    ],
    "oa:elevation_ft":"394",
    "oa:type":"small_airport",
    "woe:hierarchy":{
        "country_id":23424982,
        "county_id":26804555,
        "localadmin_id":26805383,
        "planet_id":1,
        "state_id":2347688
    },
    "wof:name":"Los Siete Samanes Airport",
    "wof:placetype":"campus"
},
  "geometry": {"coordinates":[-66.839878,8.875247],"type":"Point"}
}