{
  "type": "Feature",
  "properties": {
    "name:ceb_x_preferred":[
        "Clarion County Airport"
    ],
    "name:eng_x_preferred":[
        "Clarion County Airport"
    ],
    "name:eng_x_variant":[
        "KAXQ"
    ],
    "name:fas_x_preferred":[
        "\u0641\u0631\u0648\u062f\u06af\u0627\u0647 \u0634\u0647\u0631\u0633\u062a\u0627\u0646 \u06a9\u0644\u0631\u06cc\u0627\u0646"
    ],
    "name:fas_x_variant":[
        "\u0641\u0631\u0648\u062f\u06af\u0627\u0647 \u06a9\u0644\u0631\u06cc\u0627\u0646 \u06a9\u0627\u0646\u062a\u06cc"
    ],
    "name:jpn_x_preferred":[
        "\u30af\u30e9\u30ea\u30aa\u30f3\u90e1\u7a7a\u6e2f"
    ],
    "name:ron_x_preferred":[
        "Aeroportul Clarion County"
    ],
    "name:tgk_x_preferred":[
        "\u0424\u0443\u0440\u0443\u0434\u0433\u043e\u04b3\u0438 \u043a\u043b\u0440\u0438\u043e\u043d \u043a\u043e\u043d"
    ],
    "name:urd_x_preferred":[
        "\u06a9\u0644\u06cc\u0631\u06cc\u0648\u0646 \u06a9\u0627\u0624\u0646\u0679\u06cc \u0627\u06cc\u0626\u0631\u067e\u0648\u0631\u0679"
    ],
    "oa:elevation_ft":"1458",
    "oa:type":"small_airport",
    "wd:wordcount":237,
    "woe:hierarchy":{
        "country_id":23424977,
        "county_id":12589743,
        "planet_id":1,
        "state_id":2347597
    },
    "wof:name":"Clarion County Airport",
    "wof:placetype":"campus"
},
  "geometry": {"coordinates":[-79.4422,41.225],"type":"Point"}
}