{
  "type": "Feature",
  "properties": {
    "gn:admin1_code":"41.0",
    "gn:asciiname":"Sikarosompo",
    "gn:dem":1133,
    "gn:feature_class":"P",
    "gn:feature_code":"PPL",
    "gn:name":"Sikarosompo",
    "gn:population":0,
    "gn:timezone":"Africa/Windhoek",
    "wof:name":"Sikarosompo",
    "wof:placetype":"locality"
},
  "geometry": {"coordinates":[18.51667,-17.88332999999999],"type":"Point"}
}