{
  "type": "Feature",
  "properties": {
    "name:deu_x_preferred":[
        "Manta Air Base"
    ],
    "name:eng_x_preferred":[
        "Eloy Alfaro International Airport"
    ],
    "name:eng_x_variant":[
        "MEC",
        "SEMT"
    ],
    "name:fas_x_preferred":[
        "\u067e\u0627\u06cc\u06af\u0627\u0647 \u0647\u0648\u0627\u06cc\u06cc \u0645\u0627\u0646\u062a\u0627"
    ],
    "name:fra_x_preferred":[
        "a\u00e9roport Eloy Alfaro de Manta"
    ],
    "name:ind_x_preferred":[
        "Bandar Udara Internasional Eloy Alfaro"
    ],
    "name:jpn_x_preferred":[
        "\u30de\u30f3\u30bf\u7a7a\u8ecd\u57fa\u5730"
    ],
    "name:msa_x_preferred":[
        "Lapangan Terbang Antarabangsa Eloy Alfaro"
    ],
    "name:pol_x_preferred":[
        "Port lotniczy Manta"
    ],
    "name:ron_x_preferred":[
        "Aeroportul Interna\u021bional Eloy Alfaro"
    ],
    "name:spa_x_preferred":[
        "Aeropuerto Internacional Eloy Alfaro - Manta"
    ],
    "name:swe_x_preferred":[
        "Eloy Alfaro International Airport"
    ],
    "oa:elevation_ft":"48",
    "oa:type":"medium_airport",
    "woe:hierarchy":{
        "country_id":23424801,
        "county_id":26809588,
        "localadmin_id":26810171,
        "planet_id":1,
        "state_id":2345215
    },
    "wof:name":"Eloy Alfaro Airport",
    "wof:placetype":"campus"
},
  "geometry": {"coordinates":[-80.678802,-0.946078],"type":"Point"}
}