{
  "type": "Feature",
  "properties": {
    "name:ceb_x_preferred":[
        "Palm Beach Water Airport"
    ],
    "name:eng_x_preferred":[
        "Palm Beach Water Airport"
    ],
    "name:eng_x_variant":[
        "LBH"
    ],
    "name:fas_x_preferred":[
        "\u0641\u0631\u0648\u062f\u06af\u0627\u0647 \u0622\u0628\u06cc \u067e\u0627\u0644\u0645 \u0628\u06cc\u0686"
    ],
    "name:spa_x_preferred":[
        "Palm Beach Water"
    ],
    "name:swe_x_preferred":[
        "Palm Beach Water Airport"
    ],
    "name:tgk_x_preferred":[
        "\u0424\u0443\u0440\u0443\u0434\u0433\u043e\u04b3\u0438 \u043e\u0431\u0435 \u043f\u043e\u043b\u043c \u0431\u0438\u0447"
    ],
    "name:urd_x_preferred":[
        "\u067e\u0627\u0645 \u0628\u06cc\u0686 \u0648\u0627\u0679\u0631 \u0627\u06cc\u0626\u0631\u067e\u0648\u0631\u0679"
    ],
    "oa:elevation_ft":"0",
    "oa:type":"seaplane_base",
    "woe:hierarchy":{
        "country_id":23424748,
        "planet_id":1,
        "state_id":2344700,
        "suburb_id":1104876
    },
    "wof:name":"Sydney Palm Beach Seaplane Base",
    "wof:placetype":"campus"
},
  "geometry": {"coordinates":[151.32339999999999,-33.5871],"type":"Point"}
}