{
  "type": "Feature",
  "properties": {
    "gn:admin1_code":"21.0",
    "gn:asciiname":"Gocheganas",
    "gn:dem":1715,
    "gn:feature_class":"P",
    "gn:feature_code":"PPL",
    "gn:name":"Gocheganas",
    "gn:population":0,
    "gn:timezone":"Africa/Windhoek",
    "wof:name":"Gocheganas",
    "wof:placetype":"locality"
},
  "geometry": {"coordinates":[17.18333,-22.83333],"type":"Point"}
}