{
  "type": "Feature",
  "properties": {
    "wof:name":"King Park",
    "wof:placetype":"neighbourhood"
},
  "geometry": {"coordinates":[-87.9309476717909,43.04912803767671],"type":"Point"}
}