{
  "type": "Feature",
  "properties": {
    "name:azb_x_preferred":[
        "\u0628\u06cc\u06a9\u0646\u0632\u0641\u06cc\u0644\u062f"
    ],
    "name:bul_x_preferred":[
        "\u0411\u0435\u043a\u044a\u043d\u0441\u0444\u0438\u0439\u043b\u0434"
    ],
    "name:cym_x_preferred":[
        "Beaconsfield"
    ],
    "name:deu_x_preferred":[
        "Beaconsfield"
    ],
    "name:fas_x_preferred":[
        "\u0628\u06cc\u06a9\u0646\u0632\u0641\u06cc\u0644\u062f"
    ],
    "name:fra_x_preferred":[
        "Beaconsfield"
    ],
    "name:fry_x_preferred":[
        "Beaconsfield"
    ],
    "name:gle_x_preferred":[
        "Beaconsfield"
    ],
    "name:ind_x_preferred":[
        "Beaconsfield"
    ],
    "name:ita_x_preferred":[
        "Beaconsfield"
    ],
    "name:kor_x_preferred":[
        "\ube44\ucee8\uc988\ud544\ub4dc"
    ],
    "name:ltz_x_preferred":[
        "Beaconsfield"
    ],
    "name:nld_x_preferred":[
        "Beaconsfield"
    ],
    "name:nno_x_preferred":[
        "Beaconsfield"
    ],
    "name:nor_x_preferred":[
        "Beaconsfield"
    ],
    "name:pol_x_preferred":[
        "Beaconsfield"
    ],
    "name:ron_x_preferred":[
        "Beaconsfield"
    ],
    "name:rus_x_preferred":[
        "\u0411\u0435\u043a\u043e\u043d\u0441\u0444\u0438\u043b\u0434"
    ],
    "name:spa_x_preferred":[
        "Beaconsfield"
    ],
    "name:swe_x_preferred":[
        "Beaconsfield"
    ],
    "name:tur_x_preferred":[
        "Beaconsfield"
    ],
    "name:vol_x_preferred":[
        "Beaconsfield"
    ],
    "name:zho_x_preferred":[
        "\u6bd4\u80af\u65af\u83f2\u5c14\u5fb7"
    ],
    "wof:name":"Beaconsfield",
    "wof:placetype":"neighbourhood"
},
  "geometry": {"coordinates":[151.20070523794379,-33.91109642303037],"type":"Point"}
}