{
  "type": "Feature",
  "properties": {
    "wof:name":"Beaconsfield",
    "wof:placetype":"neighbourhood"
},
  "geometry": {"coordinates":[151.20070523794379,-33.91109642303037],"type":"Point"}
}