{
  "type": "Feature",
  "properties": {
    "gn:admin1_code":"33.0",
    "gn:asciiname":"Onanghulo",
    "gn:dem":1099,
    "gn:feature_class":"P",
    "gn:feature_code":"PPL",
    "gn:name":"Onanghulo",
    "gn:population":0,
    "gn:timezone":"Africa/Windhoek",
    "name:und_x_variant":[
        "Onangulo",
        "Onanghulo"
    ],
    "wof:name":"Onanghulo",
    "wof:placetype":"locality"
},
  "geometry": {"coordinates":[15.81667,-17.56667],"type":"Point"}
}