{
  "type": "Feature",
  "properties": {
    "name:ceb_x_preferred":[
        "Ch\u00e2teauroux-Centre \"\"Marcel Dassault\"\" Airport"
    ],
    "name:deu_x_preferred":[
        "Flughafen Ch\u00e2teauroux"
    ],
    "name:eng_x_preferred":[
        "Ch\u00e2teauroux-Centre \"Marcel Dassault\" Airport"
    ],
    "name:eng_x_variant":[
        "CHR",
        "LFLX"
    ],
    "name:fas_x_preferred":[
        "\u0641\u0631\u0648\u062f\u06af\u0627\u0647 \u0634\u0627\u062a\u0631\u0648-\u0633\u0627\u0646\u062a\u0631"
    ],
    "name:fas_x_variant":[
        "\u0641\u0631\u0648\u062f\u06af\u0627\u0647 \u0634\u062a\u0648\u0631\u0648-\u0633\u0646\u062a\u0631 \"\u0645\u0627\u0631\u0633\u0644 \u062f\u0627\u0633\u0627\u0648\u0644\u062a\""
    ],
    "name:fra_x_preferred":[
        "A\u00e9roport de Ch\u00e2teauroux-Centre"
    ],
    "name:hun_x_preferred":[
        "Ch\u00e2teauroux rep\u00fcl\u0151t\u00e9r"
    ],
    "name:msa_x_preferred":[
        "Lapangan Terbang Deols"
    ],
    "name:ron_x_preferred":[
        "Aeroportul Ch\u00e2teauroux-Centre \"Marcel Dassault\""
    ],
    "name:tgk_x_preferred":[
        "\u0424\u0443\u0440\u0443\u0434\u0433\u043e\u04b3\u0438 \u0448\u0442\u0443\u0440\u0443-\u0441\u043d\u0442\u0440 \u043c\u043e\u0440\u0441\u0438\u043b \u0434\u043e\u0441\u043e\u0432\u043b\u0442"
    ],
    "name:vie_x_preferred":[
        "S\u00e2n bay Ch\u00e2teauroux-D\u00e9ols \"Marcel Dassault\""
    ],
    "name:zho_x_preferred":[
        "\u6c99\u6258\u9b6f-\u4e2d\u592e\"Marcel Dassault\"\u6a5f\u5834"
    ],
    "oa:elevation_ft":"529",
    "oa:type":"medium_airport",
    "woe:hierarchy":{
        "country_id":23424819,
        "county_id":12597125,
        "localadmin_id":12640653,
        "planet_id":1,
        "state_id":7153314
    },
    "wof:name":"A\u00e9roport Marcel Dassault-Ch\u00e2teauroux D\u00e9ols",
    "wof:placetype":"campus"
},
  "geometry": {"coordinates":[1.73067,46.862202],"type":"Point"}
}