{
  "type": "Feature",
  "properties": {
    "name:deu_x_preferred":[
        "Flughafen Ch\u00e2teauroux"
    ],
    "name:eng_x_variant":[
        "CHR",
        "LFLX"
    ],
    "name:fas_x_preferred":[
        "\u0641\u0631\u0648\u062f\u06af\u0627\u0647 \u0634\u0627\u062a\u0631\u0648-\u0633\u0627\u0646\u062a\u0631"
    ],
    "name:fra_x_preferred":[
        "A\u00e9roport de Ch\u00e2teauroux-Centre"
    ],
    "name:tgk_x_preferred":[
        "\u0424\u0443\u0440\u0443\u0434\u0433\u043e\u04b3\u0438 \u0448\u0442\u0443\u0440\u0443-\u0441\u043d\u0442\u0440 \u043c\u043e\u0440\u0441\u0438\u043b \u0434\u043e\u0441\u043e\u0432\u043b\u0442"
    ],
    "name:vie_x_preferred":[
        "S\u00e2n bay Ch\u00e2teauroux-D\u00e9ols \"Marcel Dassault\""
    ],
    "oa:elevation_ft":"529",
    "oa:type":"medium_airport",
    "woe:hierarchy":{
        "country_id":23424819,
        "county_id":12597125,
        "localadmin_id":12640653,
        "planet_id":1,
        "state_id":7153314
    },
    "wof:name":"A\u00e9roport Marcel Dassault-Ch\u00e2teauroux D\u00e9ols",
    "wof:placetype":"campus"
},
  "geometry": {"coordinates":[1.73067,46.862202],"type":"Point"}
}