{
  "type": "Feature",
  "properties": {
    "gn:admin1_code":"41.0",
    "gn:asciiname":"Ehafo",
    "gn:dem":1145,
    "gn:feature_class":"P",
    "gn:feature_code":"PPL",
    "gn:name":"Ehafo",
    "gn:population":0,
    "gn:timezone":"Africa/Windhoek",
    "wof:name":"Ehafo",
    "wof:placetype":"locality"
},
  "geometry": {"coordinates":[18.98333,-18.01667],"type":"Point"}
}