{
  "type": "Feature",
  "properties": {
    "name:eng_x_preferred":[
        "Onahamaokaona 1 Chome"
    ],
    "name:eng_x_variant":[
        "Onahamaokaona 1 Choume",
        "Onahamaokaona 1 Chome"
    ],
    "name:jpn_x_preferred":[
        "\uff11\u4e01\u76ee"
    ],
    "name:jpn_x_variant":[
        "\u304a\u306a\u306f\u307e\u304a\u304b\u304a\u306a \uff11\u3061\u3087\u3046\u3081",
        "\u5c0f\u540d\u6d5c\u5ca1\u5c0f\u540d \uff11\u4e01\u76ee",
        "\uff11\u3061\u3087\u3046\u3081"
    ],
    "qs:gn_adm0_cc":"JP",
    "qs:gn_local":2112539,
    "qs:local_max":1243,
    "qs:local_sum":1536,
    "qs:localhoods":10,
    "qs:name":"\uff11\u4e01\u76ee",
    "qs:name_adm0":"\u65e5\u672c",
    "qs:name_adm1":"\u798f\u5cf6\u770c",
    "qs:name_en":"Onahamaokaona 1 Chome",
    "qs:name_lau":"\u5c0f\u540d\u6d5c\u5ca1\u5c0f\u540d",
    "qs:name_local":"\u3044\u308f\u304d\u5e02",
    "qs:photo_max":1136,
    "qs:photo_sum":1243,
    "qs:placetype":"Suburb",
    "qs:quad_count":11,
    "qs:woe_adm0":23424856,
    "qs:woe_adm1":2345858,
    "qs:woe_adm2":0,
    "qs:woe_lau":28398677,
    "qs:woe_local":1117341,
    "qs:woe_ver":"7.10.0",
    "wof:lang":[
        "jpn"
    ],
    "wof:name":"\uff11\u4e01\u76ee",
    "wof:placetype":"neighbourhood"
},
  "geometry": {"coordinates":[140.90152900000001,36.942303],"type":"Point"}
}