{
  "type": "Feature",
  "properties": {
    "gn:admin1_code":"38.0",
    "gn:asciiname":"Kliprand",
    "gn:dem":1183,
    "gn:feature_class":"P",
    "gn:feature_code":"PPL",
    "gn:name":"Kliprand",
    "gn:population":0,
    "gn:timezone":"Africa/Windhoek",
    "name:afr_x_preferred":[
        "Kliprand"
    ],
    "name:fra_x_preferred":[
        "Kliprand"
    ],
    "name:nld_x_preferred":[
        "Kliprand"
    ],
    "name:nso_x_preferred":[
        "Kliprand"
    ],
    "wof:name":"Kliprand",
    "wof:placetype":"locality"
},
  "geometry": {"coordinates":[18.01667,-18.98333],"type":"Point"}
}