{
  "type": "Feature",
  "properties": {
    "name:eng_x_preferred":[
        "Dobson Ranch"
    ],
    "name:fre_x_preferred":[
        "Dobson Ranch"
    ],
    "wd:wordcount":122,
    "wof:name":"Dobson Ranch",
    "wof:placetype":"neighbourhood"
},
  "geometry": {"coordinates":[-111.87599041848472,33.3719807780234],"type":"Point"}
}