{
  "type": "Feature",
  "properties": {
    "name:eng_x_preferred":[
        "Dobson Ranch"
    ],
    "name:fra_x_preferred":[
        "Dobson Ranch"
    ],
    "name:nld_x_preferred":[
        "Dobson Ranch"
    ],
    "wd:wordcount":122,
    "wof:name":"Dobson Ranch",
    "wof:placetype":"neighbourhood"
},
  "geometry": {"coordinates":[-111.87599,33.371981],"type":"Point"}
}