{
  "type": "Feature",
  "properties": {
    "name:eng_x_preferred":[
        "Hermanos Ameijeiras Airport"
    ],
    "name:eng_x_variant":[
        "VTU",
        "MUVT"
    ],
    "name:fas_x_preferred":[
        "\u0641\u0631\u0648\u062f\u06af\u0627\u0647 \u0647\u0631\u0645\u0627\u0646\u0648\u0633 \u0627\u0645\u06cc\u062e\u06cc\u0631\u0627\u0633"
    ],
    "name:hun_x_preferred":[
        "Hermanos Ameijeiras rep\u00fcl\u0151t\u00e9r"
    ],
    "name:jpn_x_preferred":[
        "\u30a8\u30eb\u30de\u30ce\u30b9\u30fb\u30a2\u30e1\u30a4\u30d8\u30a4\u30e9\u30b9\u7a7a\u6e2f"
    ],
    "name:msa_x_preferred":[
        "Lapangan Terbang Hermanos Ameijeiras"
    ],
    "name:pol_x_preferred":[
        "Port lotniczy Hermanos Ameijeiras"
    ],
    "name:spa_x_preferred":[
        "Aeropuerto Hermanos Ameijeiras"
    ],
    "name:swe_x_preferred":[
        "Hermanos Ameijeiras Airport"
    ],
    "name:tgk_x_preferred":[
        "\u0424\u0443\u0440\u0443\u0434\u0433\u043e\u04b3\u0438 \u04b3\u0440\u043c\u043e\u043d\u0443\u0441 \u043e\u043c\u0438\u0445\u0438\u0440\u043e\u0441"
    ],
    "oa:elevation_ft":"328",
    "oa:type":"medium_airport",
    "woe:hierarchy":{
        "country_id":23424793,
        "planet_id":1,
        "state_id":2345117
    },
    "wof:name":"Las Tunas Airport",
    "wof:placetype":"campus"
},
  "geometry": {"coordinates":[-76.935799,20.9876],"type":"Point"}
}