{
  "type": "Feature",
  "properties": {
    "name:eng_x_preferred":[
        "Visitation Park"
    ],
    "name:fra_x_preferred":[
        "Visitation Park"
    ],
    "wd:wordcount":134,
    "wof:name":"Visitation Park",
    "wof:placetype":"neighbourhood"
},
  "geometry": {"coordinates":[-90.27557367506498,38.65632974607949],"type":"Point"}
}