{
  "type": "Feature",
  "properties": {
    "gn:admin1_code":"41.0",
    "gn:asciiname":"Kanyekama",
    "gn:dem":1115,
    "gn:feature_class":"P",
    "gn:feature_code":"PPL",
    "gn:name":"Kanyekama",
    "gn:population":0,
    "gn:timezone":"Africa/Windhoek",
    "name:und_x_variant":[
        "Kanyikama",
        "Kanyekama"
    ],
    "wof:name":"Kanyekama",
    "wof:placetype":"locality"
},
  "geometry": {"coordinates":[18.53333,-17.55],"type":"Point"}
}