{
  "type": "Feature",
  "properties": {
    "gn:admin1_code":"32.0",
    "gn:asciiname":"Fransfontein",
    "gn:dem":1087,
    "gn:feature_class":"P",
    "gn:feature_code":"PPL",
    "gn:name":"Fransfontein",
    "gn:population":0,
    "gn:timezone":"Africa/Windhoek",
    "name:afr_x_preferred":[
        "Fransfontein"
    ],
    "name:ceb_x_preferred":[
        "Fransfontein"
    ],
    "name:deu_x_preferred":[
        "Fransfontein"
    ],
    "name:fra_x_preferred":[
        "Fransfontein"
    ],
    "name:nld_x_preferred":[
        "Fransfontein"
    ],
    "name:ron_x_preferred":[
        "Fransfontein"
    ],
    "name:spa_x_preferred":[
        "Fransfontein"
    ],
    "name:und_x_variant":[
        "Franzfontein"
    ],
    "wof:name":"Fransfontein",
    "wof:placetype":"locality"
},
  "geometry": {"coordinates":[15.01667,-20.21667],"type":"Point"}
}