{
  "type": "Feature",
  "properties": {
    "name:chi_x_preferred":[
        "\u5091\u8332\u5361\u8332\u7518\u6a5f\u5834"
    ],
    "name:eng_x_preferred":[
        "Zhezkazgan Airport"
    ],
    "name:eng_x_variant":[
        "DZN",
        "UAKD"
    ],
    "name:fre_x_preferred":[
        "a\u00e9roport de Jezkazgan"
    ],
    "name:geo_x_preferred":[
        "\u10df\u10d4\u10d6\u10e7\u10d0\u10d6\u10e6\u10d0\u10dc\u10d8\u10e1 \u10d0\u10d4\u10e0\u10dd\u10de\u10dd\u10e0\u10e2\u10d8"
    ],
    "name:ind_x_preferred":[
        "Bandar Udara Zhezkazgan"
    ],
    "name:jpn_x_preferred":[
        "\u30b8\u30a7\u30b9\u30ab\u30ba\u30ac\u30f3\u7a7a\u6e2f"
    ],
    "name:may_x_preferred":[
        "Lapangan Terbang Zhezkazgan"
    ],
    "name:per_x_preferred":[
        "\u0641\u0631\u0648\u062f\u06af\u0627\u0647 \u0698\u0632\u0642\u0627\u0632\u063a\u0627\u0646"
    ],
    "name:pol_x_preferred":[
        "Port lotniczy \u017bezkazgan"
    ],
    "name:rus_x_preferred":[
        "\u0416\u0435\u0437\u043a\u0430\u0437\u0433\u0430\u043d"
    ],
    "name:swe_x_preferred":[
        "Zhezkazgan Airport"
    ],
    "name:tgk_x_preferred":[
        "\u0424\u0443\u0440\u0443\u0434\u0433\u043e\u04b3\u0438 \u0436\u0437\u049b\u043e\u0437\u0493\u043e\u043d"
    ],
    "name:ukr_x_preferred":[
        "\u0416\u0435\u0437\u043a\u0430\u0437\u0433\u0430\u043d"
    ],
    "oa:elevation_ft":"1250",
    "oa:type":"medium_airport",
    "woe:hierarchy":{
        "country_id":23424871,
        "planet_id":1,
        "state_id":20070178
    },
    "wof:name":"Dzhezkazgan South Airport",
    "wof:placetype":"campus"
},
  "geometry": {"coordinates":[67.733299,47.708302],"type":"Point"}
}