{
  "type": "Feature",
  "properties": {
    "name:deu_x_preferred":[
        "Flughafen Bursa Yeni\u015fehir"
    ],
    "name:eng_x_preferred":[
        "Yeni\u015fehir Airport"
    ],
    "name:eng_x_variant":[
        "YEI",
        "LTBR"
    ],
    "name:fas_x_preferred":[
        "\u0641\u0631\u0648\u062f\u06af\u0627\u0647 \u06cc\u0646\u06cc\u200c\u0634\u0647\u0631"
    ],
    "name:ger_x_preferred":[
        "Flughafen Bursa-Yeni\u015fehir"
    ],
    "name:ind_x_preferred":[
        "Bandar Udara Yeni\u015fehir"
    ],
    "name:jpn_x_preferred":[
        "\u30d6\u30eb\u30b5"
    ],
    "name:may_x_preferred":[
        "Pengkalan Udara Yenisehir"
    ],
    "name:per_x_preferred":[
        "\u0641\u0631\u0648\u062f\u06af\u0627\u0647 \u06cc\u0646\u06cc\u200c\u0634\u0647\u0631"
    ],
    "name:pol_x_preferred":[
        "Port lotniczy Yeni\u015fehir"
    ],
    "name:tgk_x_preferred":[
        "\u0424\u0443\u0440\u0443\u0434\u0433\u043e\u04b3\u0438 \u0438\u043d\u0438\u0448\u0438\u0440"
    ],
    "name:tur_x_preferred":[
        "Bursa Yeni\u015fehir Havaliman\u0131"
    ],
    "name:vie_x_preferred":[
        "S\u00e2n bay Yeni\u015fehir"
    ],
    "oa:elevation_ft":"764",
    "oa:type":"medium_airport",
    "woe:hierarchy":{
        "country_id":23424775,
        "county_id":29375231,
        "planet_id":1,
        "state_id":2344917
    },
    "wof:name":"Ennadai Lake Airport",
    "wof:placetype":"campus"
},
  "geometry": {"coordinates":[29.562599,40.255199],"type":"Point"}
}