{
  "type": "Feature",
  "properties": {
    "name:eng_x_variant":[
        "PTG",
        "FAPP"
    ],
    "oa:elevation_ft":"4076",
    "oa:type":"medium_airport",
    "wd:wordcount":142,
    "woe:hierarchy":{
        "country_id":23424942,
        "county_id":56189442,
        "localadmin_id":56189527,
        "planet_id":1,
        "state_id":2346986
    },
    "wof:name":"Polokwane International Airport",
    "wof:placetype":"campus"
},
  "geometry": {"coordinates":[29.458599,-23.845301],"type":"Point"}
}