{
  "type": "Feature",
  "properties": {
    "name:afr_x_preferred":[
        "Polokwane Internasionale Lughawe"
    ],
    "name:cym_x_preferred":[
        "Maes Awyr Rhyngwladol Polokwane"
    ],
    "name:eng_x_variant":[
        "PTG",
        "FAPP"
    ],
    "name:fas_x_preferred":[
        "\u0641\u0631\u0648\u062f\u06af\u0627\u0647 \u0628\u06cc\u0646\u200c\u0627\u0644\u0645\u0644\u0644\u06cc \u067e\u0648\u0644\u0648\u06a9\u200c\u0648\u06cc\u0646"
    ],
    "name:jpn_x_preferred":[
        "\u30dd\u30ed\u30af\u30ef\u30cd"
    ],
    "name:msa_x_preferred":[
        "Lapangan Terbang Antarabangsa Polokwane"
    ],
    "name:pol_x_preferred":[
        "Port lotniczy Polokwane"
    ],
    "name:ron_x_preferred":[
        "Aeroportul Polokwane"
    ],
    "name:tgk_x_preferred":[
        "\u0424\u0443\u0440\u0443\u0434\u0433\u043e\u04b3\u0438 \u0431\u0438\u043d\u200c\u0430\u043b\u043c\u0438\u043b\u0430\u043b\u04e3 \u043f\u0443\u043b\u0443\u043a\u200c\u0432\u0435\u0439\u0438\u043d"
    ],
    "name:vie_x_preferred":[
        "S\u00e2n bay qu\u1ed1c t\u1ebf Polokwane"
    ],
    "name:zho_x_preferred":[
        "\u6ce2\u7f85\u514b\u74e6\u5c3c\u570b\u969b\u6a5f\u5834"
    ],
    "oa:elevation_ft":"4076",
    "oa:type":"medium_airport",
    "wd:wordcount":142,
    "woe:hierarchy":{
        "country_id":23424942,
        "county_id":56189442,
        "localadmin_id":56189527,
        "planet_id":1,
        "state_id":2346986
    },
    "wof:name":"Polokwane International Airport",
    "wof:placetype":"campus"
},
  "geometry": {"coordinates":[29.458599,-23.845301],"type":"Point"}
}