{
  "type": "Feature",
  "properties": {
    "name:eng_x_preferred":[
        "Tutuka Power Station Airport"
    ],
    "name:eng_x_variant":[
        "FATT"
    ],
    "name:msa_x_preferred":[
        "Lapangan Terbang Tutuka Power Station"
    ],
    "name:ron_x_preferred":[
        "Aeroportul Tutuka Power Station"
    ],
    "oa:elevation_ft":"5313",
    "oa:type":"small_airport",
    "woe:hierarchy":{
        "country_id":23424942,
        "county_id":56189441,
        "localadmin_id":56189575,
        "planet_id":1,
        "state_id":2346983
    },
    "wof:name":"Tutuka Power Station Airport",
    "wof:placetype":"campus"
},
  "geometry": {"coordinates":[29.338778,-26.776557],"type":"Point"}
}