{
  "type": "Feature",
  "properties": {
    "gn:admin1_code":"33.0",
    "gn:asciiname":"Onhumba",
    "gn:dem":1158,
    "gn:feature_class":"P",
    "gn:feature_code":"PPL",
    "gn:name":"Onhumba",
    "gn:population":0,
    "gn:timezone":"Africa/Windhoek",
    "wof:name":"Onhumba",
    "wof:placetype":"locality"
},
  "geometry": {"coordinates":[17.13332999999999,-17.61667000000001],"type":"Point"}
}