{
  "type": "Feature",
  "properties": {
    "name:ceb_x_preferred":[
        "Pikwitonei Airport"
    ],
    "name:eng_x_preferred":[
        "Pikwitonei Airport"
    ],
    "name:eng_x_variant":[
        "PIW",
        "CZMN"
    ],
    "name:fas_x_preferred":[
        "\u0641\u0631\u0648\u062f\u06af\u0627\u0647 \u067e\u06cc\u06a9\u0648\u06cc\u062a\u0648\u0646\u06cc"
    ],
    "name:msa_x_preferred":[
        "Lapangan Terbang Pikwitonei"
    ],
    "name:pms_x_preferred":[
        "Pikwitonei Airport"
    ],
    "name:ron_x_preferred":[
        "Aeroportul Pikwitonei"
    ],
    "name:swe_x_preferred":[
        "Pikwitonei Airport"
    ],
    "name:tgk_x_preferred":[
        "\u0424\u0443\u0440\u0443\u0434\u0433\u043e\u04b3\u0438 \u043f\u0438\u043a\u0443\u0438\u0442\u0443\u043d\u0438"
    ],
    "oa:elevation_ft":"630",
    "oa:type":"medium_airport",
    "wd:wordcount":41,
    "woe:hierarchy":{
        "country_id":23424775,
        "county_id":29375231,
        "planet_id":1,
        "state_id":2344917
    },
    "wof:name":"Pikwitonei Airport",
    "wof:placetype":"campus"
},
  "geometry": {"coordinates":[-97.16419999999999,55.588902],"type":"Point"}
}