{
  "type": "Feature",
  "properties": {
    "name:eng_x_variant":[
        "ARO",
        "SK-005"
    ],
    "oa:elevation_ft":"13",
    "oa:type":"small_airport",
    "woe:hierarchy":{
        "country_id":23424787,
        "county_id":26796620,
        "planet_id":1,
        "state_id":2345048
    },
    "wof:name":"Arboletas Airport",
    "wof:placetype":"campus"
},
  "geometry": {"coordinates":[-76.42440000000001,8.85705],"type":"Point"}
}