{
  "type": "Feature",
  "properties": {
    "name:ceb_x_preferred":[
        "Devonport Airport"
    ],
    "name:deu_x_preferred":[
        "Devonport Airport"
    ],
    "name:eng_x_preferred":[
        "Devonport Airport"
    ],
    "name:eng_x_variant":[
        "DPO",
        "YDPO"
    ],
    "name:fas_x_preferred":[
        "\u0641\u0631\u0648\u062f\u06af\u0627\u0647 \u062f\u0648\u0646\u067e\u0631\u062a"
    ],
    "name:fra_x_preferred":[
        "a\u00e9roport de Devonport"
    ],
    "name:ita_x_preferred":[
        "aeroporto di Devonport"
    ],
    "name:msa_x_preferred":[
        "Lapangan Terbang Devonport"
    ],
    "name:msa_x_variant":[
        "Dong Tre Airport"
    ],
    "name:pol_x_preferred":[
        "Port lotniczy Devonport"
    ],
    "name:ron_x_preferred":[
        "Aeroportul Devonport"
    ],
    "name:rus_x_preferred":[
        "\u0414\u0435\u0432\u043e\u043d\u043f\u043e\u0440\u0442"
    ],
    "name:spa_x_preferred":[
        "Aeropuerto de Devonport"
    ],
    "name:swe_x_preferred":[
        "Devonport Airport"
    ],
    "name:tgk_x_preferred":[
        "\u0424\u0443\u0440\u0443\u0434\u0433\u043e\u04b3\u0438 \u0434\u0443\u043d\u043f\u0440\u0442"
    ],
    "name:zho_x_preferred":[
        "\u5fb7\u6587\u6e2f\u6a5f\u5834"
    ],
    "oa:elevation_ft":"33",
    "oa:type":"medium_airport",
    "wd:wordcount":212,
    "woe:hierarchy":{
        "country_id":23424748,
        "county_id":55864260,
        "planet_id":1,
        "state_id":2344704
    },
    "wof:name":"Devonport Airport",
    "wof:placetype":"campus"
},
  "geometry": {"coordinates":[146.429993,-41.169701],"type":"Point"}
}