{
  "type": "Feature",
  "properties": {
    "name:ceb_x_preferred":[
        "Gobernador Gregores Aerodrome"
    ],
    "name:eng_x_preferred":[
        "Gobernador Gregores Airport"
    ],
    "name:eng_x_variant":[
        "GGS",
        "SAWR"
    ],
    "name:fas_x_preferred":[
        "\u0641\u0631\u0648\u062f\u06af\u0627\u0647 \u06af\u0628\u0631\u0646\u06cc\u062f\u0631 \u06af\u0631\u06cc\u06af\u0631\u06cc\u0633"
    ],
    "name:ita_x_preferred":[
        "Aeroporto Governator Gregores"
    ],
    "name:jpn_x_preferred":[
        "\u30b4\u30d9\u30eb\u30ca\u30c9\u30eb\u30fb\u30b0\u30ec\u30b4\u30ec\u30b9\u7a7a\u6e2f"
    ],
    "name:msa_x_preferred":[
        "Lapangan Terbang Gobernador Gregores"
    ],
    "name:pol_x_preferred":[
        "Port lotniczy Gobernador Gregores"
    ],
    "name:spa_x_preferred":[
        "Aeropuerto N\u00e9stor Carlos Kirchner"
    ],
    "name:swe_x_preferred":[
        "Gobernador Gregores Aerodrome"
    ],
    "name:tgk_x_preferred":[
        "\u0424\u0443\u0440\u0443\u0434\u0433\u043e\u04b3\u0438 \u0433\u0431\u0440\u043d\u0438\u0434\u0440 \u0433\u0440\u0438\u0433\u0440\u0438\u0441"
    ],
    "name:vie_x_preferred":[
        "S\u00e2n bay Gobernador Gregores"
    ],
    "name:zho_x_preferred":[
        "\u683c\u96f7\u6208\u96f7\u65af\u7701\u9577\u93ae\u6a5f\u5834"
    ],
    "oa:elevation_ft":"356",
    "oa:type":"small_airport",
    "wd:wordcount":28,
    "woe:hierarchy":{
        "country_id":23424747,
        "county_id":20071074,
        "planet_id":1,
        "state_id":2344694
    },
    "wof:name":"Gobernador Gregores Airport",
    "wof:placetype":"campus"
},
  "geometry": {"coordinates":[-70.150002,-48.7831],"type":"Point"}
}