{
  "type": "Feature",
  "properties": {
    "name:ceb_x_preferred":[
        "Marion Municipal Airport"
    ],
    "name:eng_x_preferred":[
        "Marion Municipal Airport"
    ],
    "name:fas_x_preferred":[
        "\u0641\u0631\u0648\u062f\u06af\u0627\u0647 \u0645\u0627\u0631\u06cc\u0648\u0646"
    ],
    "name:ron_x_preferred":[
        "Aeroportul Municipal Marion"
    ],
    "name:urd_x_preferred":[
        "\u0645\u0627\u0631\u06cc\u0648\u0646 \u0645\u06cc\u0648\u0646\u0633\u067e\u0644 \u0627\u06cc\u0626\u0631\u067e\u0648\u0631\u0679"
    ],
    "name:zho_x_preferred":[
        "\u5370\u7b2c\u5b89\u7d0d\u5dde\u99ac\u91cc\u6069\u5e02\u6a5f\u5834"
    ],
    "oa:elevation_ft":"859",
    "oa:type":"small_airport",
    "wd:wordcount":41,
    "woe:hierarchy":{
        "country_id":23424977,
        "county_id":12588206,
        "planet_id":1,
        "state_id":2347573
    },
    "wof:name":"Marion Municipal Airport",
    "wof:placetype":"campus"
},
  "geometry": {"coordinates":[-85.6797,40.49],"type":"Point"}
}