{
  "type": "Feature",
  "properties": {
    "name:eng_x_variant":[
        "CLC"
    ],
    "oa:elevation_ft":"25",
    "oa:type":"closed",
    "woe:hierarchy":{
        "country_id":23424977,
        "county_id":12590107,
        "planet_id":1,
        "state_id":2347602,
        "suburb_id":28751203
    },
    "wof:name":"Clear Lake City Metroport Airport",
    "wof:placetype":"campus"
},
  "geometry": {"coordinates":[-95.1383,29.5555],"type":"Point"}
}