{
  "type": "Feature",
  "properties": {
    "name:ceb_x_preferred":[
        "Antonio Rold\u00e1n Betancourt Airport"
    ],
    "name:eng_x_preferred":[
        "Antonio Rold\u00e1n Betancourt Airport"
    ],
    "name:eng_x_variant":[
        "APO",
        "SKLC"
    ],
    "name:fas_x_preferred":[
        "\u0641\u0631\u0648\u062f\u06af\u0627\u0647 \u0622\u0646\u062a\u0648\u0646\u06cc\u0648 \u0631\u0648\u0644\u062f\u0646 \u0628\u062a\u0646\u06a9\u0648\u0631\u062a"
    ],
    "name:fra_x_preferred":[
        "A\u00e9roport Antonio Rold\u00e1n Betancourt"
    ],
    "name:jpn_x_preferred":[
        "\u30a2\u30f3\u30c8\u30cb\u30aa\u30fb\u30ed\u30eb\u30c0\u30f3\u30fb\u30d9\u30bf\u30f3\u30b3\u30a6\u30eb\u7a7a\u6e2f"
    ],
    "name:msa_x_preferred":[
        "Lapangan Terbang Antonio Roldan Betancourt"
    ],
    "name:nld_x_preferred":[
        "Aeropuerto Antonio Rold\u00e1n Betancourt"
    ],
    "name:nld_x_variant":[
        "Luchthaven Antonio Rold\u00e1n Betancourt"
    ],
    "name:pol_x_preferred":[
        "Port lotniczy Antonio Roldan Betancourt"
    ],
    "name:rus_x_preferred":[
        "\u0410\u043f\u0430\u0440\u0442\u0430\u0434\u043e"
    ],
    "name:spa_x_preferred":[
        "Aeropuerto Antonio Rold\u00e1n Betancourt"
    ],
    "name:swe_x_preferred":[
        "Antonio Rold\u00e1n Betancourt Airport"
    ],
    "name:tgk_x_preferred":[
        "\u0424\u0443\u0440\u0443\u0434\u0433\u043e\u04b3\u0438 \u043e\u043d\u0442\u0443\u043d\u0435\u044e \u0440\u0443\u043b\u0434\u043d \u0431\u0442\u043d\u043a\u0443\u0440\u0442"
    ],
    "name:vie_x_preferred":[
        "S\u00e2n bay Antonio Rold\u00e1n Betancourt"
    ],
    "name:zho_x_preferred":[
        "\u5b89\u6771\u5c3c\u5967\u00b7\u52de\u4e39\u00b7\u8c9d\u6ed5\u5404\u723e\u7279\u6a5f\u5834"
    ],
    "oa:elevation_ft":"46",
    "oa:type":"medium_airport",
    "woe:hierarchy":{
        "country_id":23424787,
        "county_id":26796619,
        "planet_id":1,
        "state_id":2345048
    },
    "wof:name":"Apartado Airport",
    "wof:placetype":"campus"
},
  "geometry": {"coordinates":[-76.71639999999999,7.81196],"type":"Point"}
}