{
  "type": "Feature",
  "properties": {
    "name:chi_x_preferred":[
        "\u5361\u5229"
    ],
    "name:dut_x_preferred":[
        "Alfonso Bonilla Arag\u00f3n International Airport"
    ],
    "name:eng_x_preferred":[
        "Alfonso Bonilla Arag\u00f3n International Airport"
    ],
    "name:eng_x_variant":[
        "CLO",
        "SKCL"
    ],
    "name:fre_x_preferred":[
        "a\u00e9roport international Alfonso Bonilla Arag\u00f3n"
    ],
    "name:ger_x_preferred":[
        "Flughafen Cali"
    ],
    "name:ind_x_preferred":[
        "Bandar Udara Internasional Alfonso Bonilla Arag\u00f3n"
    ],
    "name:ita_x_preferred":[
        "Aeroporto Internazionale Alfonso Bonilla Arag\u00f3n"
    ],
    "name:jpn_x_preferred":[
        "\u30ab\u30ea"
    ],
    "name:may_x_preferred":[
        "Lapangan Terbang Antarabangsa Alfonso Bonilla Aragon"
    ],
    "name:per_x_preferred":[
        "\u0641\u0631\u0648\u062f\u06af\u0627\u0647 \u0628\u06cc\u0646\u200c\u0627\u0644\u0645\u0644\u0644\u06cc \u0622\u0644\u0641\u0648\u0646\u0633\u0648 \u0628\u0648\u0646\u06cc\u06cc\u0627 \u0622\u0631\u0627\u06af\u0648\u0646"
    ],
    "name:pol_x_preferred":[
        "Port lotniczy Alfonso Bonilla Arag\u00f3n"
    ],
    "name:por_x_preferred":[
        "Aeroporto Internacional Alfonso Bonilla Arag\u00f3n"
    ],
    "name:rus_x_preferred":[
        "\u041c\u0435\u0436\u0434\u0443\u043d\u0430\u0440\u043e\u0434\u043d\u044b\u0439 \u0430\u044d\u0440\u043e\u043f\u043e\u0440\u0442 \u0438\u043c\u0435\u043d\u0438 \u0410\u043b\u044c\u0444\u043e\u043d\u0441\u043e \u0411\u043e\u043d\u0438\u043b\u044c\u044f \u0410\u0440\u0430\u0433\u043e\u043d\u0430"
    ],
    "name:spa_x_preferred":[
        "Aeropuerto Internacional Alfonso Bonilla Arag\u00f3n"
    ],
    "name:swe_x_preferred":[
        "Cali / Alfonso Bonillaaragon"
    ],
    "name:tgk_x_preferred":[
        "\u0424\u0443\u0440\u0443\u0434\u0433\u043e\u04b3\u0438 \u0431\u0438\u043d\u200c\u0430\u043b\u043c\u0438\u043b\u0430\u043b\u04e3 \u043e\u043b\u0444\u0443\u043d\u0441\u0443 \u0431\u0443\u043d\u0438\u0438\u043e \u043e\u0440\u043e\u0433\u0443\u043d"
    ],
    "name:vie_x_preferred":[
        "S\u00e2n bay qu\u1ed1c t\u1ebf Alfonso Bonilla Arag\u00f3n"
    ],
    "oa:elevation_ft":"3162",
    "oa:type":"medium_airport",
    "woe:hierarchy":{
        "country_id":23424787,
        "county_id":26797590,
        "planet_id":1,
        "state_id":2345074
    },
    "wof:name":"Alfonso Bonilla Aragon International Airport",
    "wof:placetype":"campus"
},
  "geometry": {"coordinates":[-76.38160000000001,3.54322],"type":"Point"}
}