{
  "type": "Feature",
  "properties": {
    "name:ceb_x_preferred":[
        "Windham Airport"
    ],
    "name:eng_x_preferred":[
        "Windham Airport"
    ],
    "name:fas_x_preferred":[
        "\u0641\u0631\u0648\u062f\u06af\u0627\u0647 \u0648\u06cc\u0646\u062f\u0647\u0627\u0645"
    ],
    "name:ron_x_preferred":[
        "Aeroportul Windham"
    ],
    "name:tgk_x_preferred":[
        "\u0424\u0443\u0440\u0443\u0434\u0433\u043e\u04b3\u0438 \u0432\u0438\u043d\u0434\u04b3\u043e\u043c"
    ],
    "name:urd_x_preferred":[
        "\u0648\u06cc\u0646\u0688\u0645 \u06c1\u0648\u0627\u0626\u06cc \u0627\u0688\u0627"
    ],
    "oa:elevation_ft":"247",
    "oa:type":"small_airport",
    "wd:wordcount":249,
    "woe:hierarchy":{
        "country_id":23424977,
        "county_id":12587798,
        "planet_id":1,
        "state_id":2347565
    },
    "wof:name":"Windham Airport",
    "wof:placetype":"campus"
},
  "geometry": {"coordinates":[-72.180277777778,41.744166666667],"type":"Point"}
}