{
  "type": "Feature",
  "properties": {
    "name:ara_x_preferred":[
        "\u0645\u0637\u0627\u0631 \u0622\u0644\u062a\u0627\u064a"
    ],
    "name:ceb_x_preferred":[
        "Altay Airport"
    ],
    "name:deu_x_preferred":[
        "Flughafen Altay"
    ],
    "name:eng_x_preferred":[
        "Altay Airport"
    ],
    "name:eng_x_variant":[
        "AAT",
        "CN-0113"
    ],
    "name:eus_x_preferred":[
        "Altay aireportua"
    ],
    "name:fas_x_preferred":[
        "\u0641\u0631\u0648\u062f\u06af\u0627\u0647 \u0622\u0644\u062a\u0627\u06cc"
    ],
    "name:fra_x_preferred":[
        "A\u00e9roport d'Altay"
    ],
    "name:fra_x_variant":[
        "a\u00e9roport d'Altay"
    ],
    "name:ita_x_preferred":[
        "Aeroporto di Altay"
    ],
    "name:jpn_x_preferred":[
        "\u30a2\u30eb\u30bf\u30a4\u7a7a\u6e2f"
    ],
    "name:nld_x_preferred":[
        "Altay Airport"
    ],
    "name:nob_x_preferred":[
        "Altay lufthavn"
    ],
    "name:pol_x_preferred":[
        "Port lotniczy Altay"
    ],
    "name:ron_x_preferred":[
        "Aeroportul Altay"
    ],
    "name:rus_x_preferred":[
        "\u0410\u043b\u0442\u0430\u0439"
    ],
    "name:spa_x_preferred":[
        "Aeropuerto de Altay"
    ],
    "name:swe_x_preferred":[
        "Altay Airport"
    ],
    "name:tgk_x_preferred":[
        "\u0424\u0443\u0440\u0443\u0434\u0433\u043e\u04b3\u0438 \u043e\u043b\u0442"
    ],
    "name:tur_x_preferred":[
        "Altay Havaliman\u0131"
    ],
    "name:vie_x_preferred":[
        "S\u00e2n bay Altay"
    ],
    "name:yue_x_preferred":[
        "\u963f\u52d2\u6cf0\u6a5f\u5834"
    ],
    "name:zho_x_preferred":[
        "\u963f\u52d2\u6cf0\u673a\u573a"
    ],
    "oa:elevation_ft":"2460",
    "oa:type":"medium_airport",
    "wd:wordcount":111,
    "woe:hierarchy":{
        "country_id":23424781,
        "county_id":26198047,
        "localadmin_id":12686334,
        "planet_id":1,
        "state_id":12578003
    },
    "wof:name":"Altay Airport",
    "wof:placetype":"campus"
},
  "geometry": {"coordinates":[88.085808,47.749886],"type":"Point"}
}