{
  "type": "Feature",
  "properties": {
    "qs:name":"Parea",
    "qs:name_adm0":"Polyn\u00e9sie Fran\u00e7aise",
    "qs:name_adm1":"\u00celes sous le Vent",
    "qs:photos":325,
    "qs:photos_1k":66,
    "qs:photos_9k":1,
    "qs:photos_9r":5,
    "qs:photos_all":325,
    "qs:photos_sr":5,
    "qs:placetype":"Town",
    "qs:pop_sr":"0",
    "wof:name":"Parea",
    "wof:placetype":"locality"
},
  "geometry": {"coordinates":[-150.98442,-16.812429],"type":"Point"}
}