{
  "type": "Feature",
  "properties": {
    "name:ceb_x_preferred":[
        "Bathurst Island Airport"
    ],
    "name:chi_x_preferred":[
        "\u5df4\u745f\u65af\u7279\u5cf6\u6a5f\u5834"
    ],
    "name:eng_x_preferred":[
        "Bathurst Island Airport"
    ],
    "name:eng_x_variant":[
        "BRT",
        "YBTI"
    ],
    "name:fas_x_preferred":[
        "\u0641\u0631\u0648\u062f\u06af\u0627\u0647 \u0628\u062a\u0631\u0633\u062a \u0622\u06cc\u0644\u0646\u062f"
    ],
    "name:fre_x_preferred":[
        "Bathurst Island Airport"
    ],
    "name:ger_x_preferred":[
        "Bathurst Island Airport"
    ],
    "name:ita_x_preferred":[
        "aeroporto di Bathurst Island"
    ],
    "name:jpn_x_preferred":[
        "\u30d0\u30b5\u30fc\u30b9\u30c8\u7a7a\u6e2f"
    ],
    "name:may_x_preferred":[
        "Lapangan Terbang Bathurst"
    ],
    "name:msa_x_preferred":[
        "Lapangan Terbang Bathurst I"
    ],
    "name:per_x_preferred":[
        "\u0641\u0631\u0648\u062f\u06af\u0627\u0647 \u0628\u062a\u0631\u0633\u062a \u0622\u06cc\u0644\u0646\u062f"
    ],
    "name:spa_x_preferred":[
        "aeropuerto de la isla Bathurst"
    ],
    "name:swe_x_preferred":[
        "Bathurst Island Airport"
    ],
    "name:tgk_x_preferred":[
        "\u0424\u0443\u0440\u0443\u0434\u0433\u043e\u04b3\u0438 \u0411\u0430\u0442\u0443\u0440\u0441\u0442 \u0410\u0439\u043b\u0435\u043d\u0434"
    ],
    "oa:elevation_ft":"67",
    "oa:type":"medium_airport",
    "wd:wordcount":109,
    "woe:hierarchy":{
        "country_id":23424748,
        "county_id":56072962,
        "planet_id":1,
        "state_id":2344701
    },
    "wof:name":"Bathurst Island Airport",
    "wof:placetype":"campus"
},
  "geometry": {"coordinates":[130.61999499999999,-11.7692],"type":"Point"}
}