{
  "type": "Feature",
  "properties": {
    "name:ara_x_preferred":[
        "\u0645\u0637\u0627\u0631 \u0628\u0648\u0633\u0639\u0627\u062f\u0629"
    ],
    "name:ceb_x_preferred":[
        "Bou Saada Airport"
    ],
    "name:eng_x_preferred":[
        "Ain Eddis Airport"
    ],
    "name:eng_x_variant":[
        "BUJ",
        "DAAD"
    ],
    "name:fas_x_preferred":[
        "\u0641\u0631\u0648\u062f\u06af\u0627\u0647 \u0639\u06cc\u0646 \u0627\u062f\u06cc\u0633"
    ],
    "name:fra_x_preferred":[
        "A\u00e9roport de Bou Sa\u00e2da"
    ],
    "name:fra_x_variant":[
        "a\u00e9roport de Bou Sa\u00e2da"
    ],
    "name:ind_x_preferred":[
        "Bandar Udara Ain Eddis"
    ],
    "name:jpn_x_preferred":[
        "\u30d6\u30fc\u30fb\u30b5\u30a2\u30fc\u30c0\u7a7a\u6e2f"
    ],
    "name:msa_x_preferred":[
        "Lapangan Terbang Bou Saada"
    ],
    "name:ron_x_preferred":[
        "Aeroportul Ain Eddis"
    ],
    "name:swe_x_preferred":[
        "Bou Saada Airport"
    ],
    "name:tgk_x_preferred":[
        "\u0424\u0443\u0440\u0443\u0434\u0433\u043e\u04b3\u0438 \u043e\u0438\u043d \u043e\u0434\u0434\u0438\u0441"
    ],
    "name:zho_x_preferred":[
        "\u5e03\u85a9\u9054\u6a5f\u5834"
    ],
    "oa:elevation_ft":"1506",
    "oa:type":"medium_airport",
    "wd:wordcount":91,
    "woe:hierarchy":{
        "country_id":23424740,
        "planet_id":1,
        "state_id":2344599
    },
    "wof:name":"Bou Saada Airport",
    "wof:placetype":"campus"
},
  "geometry": {"coordinates":[4.20639,35.3325],"type":"Point"}
}