{
  "type": "Feature",
  "properties": {
    "name:ara_x_preferred":[
        "\u0645\u0637\u0627\u0631 \u0644\u0648\u064a\u0627\u0646\u063a \u0627\u0644\u062f\u0648\u0644\u064a"
    ],
    "name:ceb_x_preferred":[
        "Luoyang Beijiao Airport"
    ],
    "name:eng_x_preferred":[
        "Luoyang Beijiao Airport"
    ],
    "name:eng_x_variant":[
        "LYA",
        "ZHLY"
    ],
    "name:eus_x_preferred":[
        "Luoyang aireportua"
    ],
    "name:fas_x_preferred":[
        "\u0641\u0631\u0648\u062f\u06af\u0627\u0647 \u0644\u0648\u06cc\u0627\u0646\u06af \u0628\u06cc\u062c\u06cc\u0627\u0626\u0648"
    ],
    "name:fra_x_preferred":[
        "ZHLY"
    ],
    "name:jpn_x_preferred":[
        "\u6d1b\u967d\u5317\u90ca\u7a7a\u6e2f"
    ],
    "name:nld_x_preferred":[
        "Luoyang Beijiao Airport"
    ],
    "name:nob_x_preferred":[
        "Luoyang Beijiao lufthavn"
    ],
    "name:nor_x_preferred":[
        "Luoyang Beijiao lufthavn"
    ],
    "name:pol_x_preferred":[
        "Port lotniczy Luoyang"
    ],
    "name:ron_x_preferred":[
        "Aeroportul Luoyang Beijiao"
    ],
    "name:rus_x_preferred":[
        "\u0411\u044d\u0439\u0446\u0437\u044f\u043e"
    ],
    "name:rus_x_variant":[
        "\u041b\u043e\u044f\u043d"
    ],
    "name:swe_x_preferred":[
        "Luoyang Beijiao Airport"
    ],
    "name:vie_x_preferred":[
        "S\u00e2n bay B\u1eafc Giao L\u1ea1c D\u01b0\u01a1ng"
    ],
    "name:vie_x_variant":[
        "S\u00e2n bay L\u1ea1c D\u01b0\u01a1ng"
    ],
    "name:yue_x_preferred":[
        "\u6d1b\u967d\u5317\u90ca\u6a5f\u5834"
    ],
    "name:zho_x_preferred":[
        "\u6d1b\u9633\u5317\u90ca\u673a\u573a"
    ],
    "oa:elevation_ft":"840",
    "oa:type":"small_airport",
    "wd:wordcount":85,
    "woe:hierarchy":{
        "country_id":23424781,
        "county_id":26198374,
        "localadmin_id":12685908,
        "planet_id":1,
        "state_id":12577999
    },
    "wof:name":"Luoyang Airport",
    "wof:placetype":"campus"
},
  "geometry": {"coordinates":[112.38800000000001,34.7411],"type":"Point"}
}