{
  "type": "Feature",
  "properties": {
    "name:ceb_x_preferred":[
        "Tumbes"
    ],
    "name:deu_x_preferred":[
        "Flughafen Tumbes"
    ],
    "name:eng_x_preferred":[
        "Cap. FAP Pedro Canga Rodr\u00edguez Airport"
    ],
    "name:eng_x_variant":[
        "TBP",
        "SPME"
    ],
    "name:fas_x_preferred":[
        "\u0641\u0631\u0648\u062f\u06af\u0627\u0647 \u06a9\u067e. \u0641\u0627\u067e \u067e\u06cc\u062f\u0631\u0648\u0648 \u06a9\u0646\u06af\u0627 \u0631\u0648\u062f\u0631\u06cc\u06af\u0648\u0632"
    ],
    "name:heb_x_preferred":[
        "\u05e0\u05de\u05dc \u05d4\u05ea\u05e2\u05d5\u05e4\u05d4 \u05e9\u05dc \u05d8\u05d5\u05de\u05d1\u05e1"
    ],
    "name:jpn_x_preferred":[
        "\u30ab\u30d4\u30bf\u30f3\u30fbFAP\u30fb\u30da\u30c9\u30ed\u30fb\u30ab\u30f3\u30ac\u30fb\u30ed\u30c9\u30ea\u30b2\u30b9\u56fd\u969b\u7a7a\u6e2f"
    ],
    "name:msa_x_preferred":[
        "Lapangan Terbang Pedro Canga"
    ],
    "name:pol_x_preferred":[
        "Port lotniczy Tumbes-Capit\u00e1n FAP Pedro Canga Rodr\u00edguez"
    ],
    "name:por_x_preferred":[
        "Aeroporto Capit\u00e1n FAP Pedro Canga Rodr\u00edguez"
    ],
    "name:spa_x_preferred":[
        "Aeropuerto Capit\u00e1n FAP Pedro Canga Rodr\u00edguez"
    ],
    "name:tgk_x_preferred":[
        "\u0424\u0443\u0440\u0443\u0434\u0433\u043e\u04b3\u0438 \u043a\u043f. \u0444\u043e\u043f \u043f\u0438\u0434\u0440\u0443\u0432 \u043a\u043d\u0433\u043e \u0440\u0443\u0434\u0440\u0438\u0433\u0443\u0437"
    ],
    "name:vie_x_preferred":[
        "S\u00e2n bay Cap. FAP Pedro Canga Rodr\u00edguez"
    ],
    "name:zho_x_preferred":[
        "\u901a\u8c9d\u65af\u6a5f\u5834"
    ],
    "oa:elevation_ft":"115",
    "oa:type":"medium_airport",
    "woe:hierarchy":{
        "country_id":23424919,
        "county_id":26805952,
        "planet_id":1,
        "state_id":2346491
    },
    "wof:name":"Pedro Canga Airport",
    "wof:placetype":"campus"
},
  "geometry": {"coordinates":[-80.381401,-3.55253],"type":"Point"}
}