{
  "type": "Feature",
  "properties": {
    "name:ceb_x_preferred":[
        "Ulsan Airport"
    ],
    "name:eng_x_preferred":[
        "Ulsan Airport"
    ],
    "name:eng_x_variant":[
        "USN",
        "RKPU"
    ],
    "name:fas_x_preferred":[
        "\u0641\u0631\u0648\u062f\u06af\u0627\u0647 \u0627\u0648\u0644\u0633\u0627\u0646"
    ],
    "name:fra_x_preferred":[
        "a\u00e9roport d'Ulsan"
    ],
    "name:ind_x_preferred":[
        "Bandar Udara Ulsan"
    ],
    "name:jpn_x_preferred":[
        "\u851a\u5c71\u7a7a\u6e2f"
    ],
    "name:kor_x_preferred":[
        "\uc6b8\uc0b0\uacf5\ud56d"
    ],
    "name:msa_x_preferred":[
        "Lapangan Terbang Ulsan"
    ],
    "name:pol_x_preferred":[
        "Port lotniczy Ulsan"
    ],
    "name:por_x_preferred":[
        "Aeroporto de Ulsan"
    ],
    "name:ron_x_preferred":[
        "Aeroportul Ulsan"
    ],
    "name:spa_x_preferred":[
        "Aeropuerto de Ulsan"
    ],
    "name:swe_x_preferred":[
        "Ulsan Airport"
    ],
    "name:tgk_x_preferred":[
        "\u0424\u0443\u0440\u0443\u0434\u0433\u043e\u04b3\u0438 \u043e\u0432\u043b\u0441\u043e\u043d"
    ],
    "name:vie_x_preferred":[
        "S\u00e2n bay Ulsan"
    ],
    "name:zho_x_preferred":[
        "\u851a\u5c71\u6a5f\u5834"
    ],
    "oa:elevation_ft":"45",
    "oa:type":"medium_airport",
    "woe:hierarchy":{
        "country_id":23424868,
        "county_id":28289121,
        "localadmin_id":28806641,
        "planet_id":1,
        "state_id":23701285
    },
    "wof:name":"\uc6b8\uc0b0\uacf5\ud56d",
    "wof:placetype":"campus"
},
  "geometry": {"coordinates":[129.35200499999999,35.593498],"type":"Point"}
}