{
  "type": "Feature",
  "properties": {
    "wof:name":"San Rafael",
    "wof:placetype":"neighbourhood"
},
  "geometry": {"coordinates":[-118.17504316254539,34.1349720695173],"type":"Point"}
}