{
  "type": "Feature",
  "properties": {
    "name:bar_x_preferred":[
        "Flughafen Del Baj\u00edo"
    ],
    "name:deu_x_preferred":[
        "Flughafen Del Baj\u00edo"
    ],
    "name:eng_x_preferred":[
        "Del Baj\u00edo International Airport"
    ],
    "name:eng_x_variant":[
        "BJX",
        "MMLO"
    ],
    "name:eus_x_preferred":[
        "Bajioko nazioarteko aireportua"
    ],
    "name:fas_x_preferred":[
        "\u0641\u0631\u0648\u062f\u06af\u0627\u0647 \u0628\u06cc\u0646\u200c\u0627\u0644\u0645\u0644\u0644\u06cc \u062f\u0644 \u0628\u0627\u06cc\u0648"
    ],
    "name:fra_x_preferred":[
        "a\u00e9roport international del Baj\u00edo"
    ],
    "name:ind_x_preferred":[
        "Bandar Udara Internasional Del Baj\u00edo"
    ],
    "name:jpn_x_preferred":[
        "\u30b0\u30a2\u30ca\u30d5\u30a2\u30c8\u56fd\u969b\u7a7a\u6e2f"
    ],
    "name:msa_x_preferred":[
        "Lapangan Terbang Antarabangsa De Guanajuato"
    ],
    "name:pol_x_preferred":[
        "Port lotniczy Le\u00f3n-Del Baj\u00edo"
    ],
    "name:ron_x_preferred":[
        "Aeroportul Interna\u021bional Del Baj\u00edo"
    ],
    "name:rus_x_preferred":[
        "\u0413\u0443\u0430\u043d\u0430\u0445\u0443\u0430\u0442\u043e"
    ],
    "name:spa_x_preferred":[
        "Aeropuerto Internacional Del Baj\u00edo"
    ],
    "name:swe_x_preferred":[
        "Del Baj\u00edo International Airport"
    ],
    "name:tgk_x_preferred":[
        "\u0424\u0443\u0440\u0443\u0434\u0433\u043e\u04b3\u0438 \u0431\u0438\u043d\u200c\u0430\u043b\u043c\u0438\u043b\u0430\u043b\u04e3 \u0434\u0438\u043b \u0431\u043e\u044e"
    ],
    "name:vie_x_preferred":[
        "S\u00e2n bay qu\u1ed1c t\u1ebf Del Baj\u00edo"
    ],
    "name:zho_x_preferred":[
        "Del Baj\u00edo\u570b\u969b\u6a5f\u5834"
    ],
    "name:zho_x_variant":[
        "\u5fb7\u723e\u5df4\u55ac\u570b\u969b\u6a5f\u5834"
    ],
    "oa:elevation_ft":"5956",
    "oa:type":"medium_airport",
    "woe:hierarchy":{
        "country_id":23424900,
        "county_id":12600025,
        "planet_id":1,
        "state_id":2346274
    },
    "wof:name":"Silao Airport",
    "wof:placetype":"campus"
},
  "geometry": {"coordinates":[-101.481003,20.9935],"type":"Point"}
}