{
  "type": "Feature",
  "properties": {
    "name:ceb_x_preferred":[
        "Sultan Abdul Halim Airport"
    ],
    "name:deu_x_preferred":[
        "Flughafen Sultan Abdul Halim"
    ],
    "name:eng_x_preferred":[
        "Sultan Abdul Halim Airport"
    ],
    "name:eng_x_variant":[
        "AOR",
        "WMKA"
    ],
    "name:fas_x_preferred":[
        "\u0641\u0631\u0648\u062f\u06af\u0627\u0647 \u0633\u0644\u0637\u0627\u0646 \u0639\u0628\u062f\u0627\u0644\u062d\u0644\u06cc\u0645"
    ],
    "name:fra_x_preferred":[
        "A\u00e9roport Sultan Abdul Halim"
    ],
    "name:fra_x_variant":[
        "a\u00e9roport Sultan Abdul Halim"
    ],
    "name:ind_x_preferred":[
        "Bandar Udara Sultan Abdul Halim"
    ],
    "name:ita_x_preferred":[
        "Aeroporto di Alor Star-Sultano Abdul Halim"
    ],
    "name:jpn_x_preferred":[
        "\u30b9\u30eb\u30bf\u30f3\u30fb\u30a2\u30d6\u30c9\u30a5\u30fb\u30cf\u30ea\u30e0\u7a7a\u6e2f"
    ],
    "name:msa_x_preferred":[
        "Lapangan Terbang Sultan Abdul Halim"
    ],
    "name:nld_x_preferred":[
        "Sultan Abdul Halim Airport"
    ],
    "name:nob_x_preferred":[
        "Sultan Abdul Halim lufthavn"
    ],
    "name:nor_x_preferred":[
        "Sultan Abdul Halim lufthavn"
    ],
    "name:pol_x_preferred":[
        "Port lotniczy Alor Setar-Su\u0142tan Abdul Halim"
    ],
    "name:ron_x_preferred":[
        "Aeroportul Sultan Abdul Halim"
    ],
    "name:tgk_x_preferred":[
        "\u0424\u0443\u0440\u0443\u0434\u0433\u043e\u04b3\u0438 \u0441\u0443\u043b\u0442\u043e\u043d \u044a\u0431\u0434\u043e\u043b\u0445\u043b\u0438\u043c"
    ],
    "name:vie_x_preferred":[
        "S\u00e2n bay Sultan Abdul Halim"
    ],
    "name:zho_x_preferred":[
        "\u82cf\u4e39\u963f\u90fd\u54c8\u6797\u673a\u573a"
    ],
    "oa:elevation_ft":"15",
    "oa:type":"medium_airport",
    "wd:wordcount":189,
    "woe:hierarchy":{
        "country_id":23424901,
        "county_id":56013580,
        "localadmin_id":56014030,
        "planet_id":1,
        "state_id":2346297
    },
    "wof:name":"Sultan Abdul Halim Airport",
    "wof:placetype":"campus"
},
  "geometry": {"coordinates":[100.398056,6.189444],"type":"Point"}
}