{
  "type": "Feature",
  "properties": {
    "name:eng_x_preferred":[
        "Cufar Airport"
    ],
    "name:msa_x_preferred":[
        "Lapangan Terbang Cufar"
    ],
    "name:pol_x_preferred":[
        "Port lotniczy Cufar"
    ],
    "name:pol_x_variant":[
        "Port lotniczy Bambadinca"
    ],
    "name:ron_x_preferred":[
        "Aeroportul Cufar"
    ],
    "oa:elevation_ft":"65",
    "oa:type":"small_airport",
    "wd:wordcount":32,
    "woe:hierarchy":{
        "country_id":23424929,
        "planet_id":1,
        "state_id":2346608
    },
    "wof:name":"Cufar Airport",
    "wof:placetype":"campus"
},
  "geometry": {"coordinates":[-15.1803,11.2878],"type":"Point"}
}