{
  "type": "Feature",
  "properties": {
    "name:gle_x_preferred":[
        "P\u00e1irc Sm\u00e1irgaid"
    ],
    "wof:name":"McGovern Park",
    "wof:placetype":"neighbourhood"
},
  "geometry": {"coordinates":[-87.97680989274252,43.1160163345165],"type":"Point"}
}