{
  "type": "Feature",
  "properties": {
    "name:eng_x_preferred":[
        "Inishmore Aerodrome"
    ],
    "name:eng_x_variant":[
        "IOR",
        "EIIM"
    ],
    "name:fre_x_preferred":[
        "a\u00e9rodrome d'Inis M\u00f3r"
    ],
    "name:gle_x_preferred":[
        "Aeradr\u00f3m Inis Me\u00e1in"
    ],
    "name:may_x_preferred":[
        "Lapangan Terbang Inishmore"
    ],
    "name:per_x_preferred":[
        "\u0641\u0631\u0648\u062f\u06af\u0627\u0647 \u0627\u06cc\u0646\u06cc\u0634\u0645\u0648\u0631"
    ],
    "name:pol_x_preferred":[
        "Port lotniczy Inis M\u00f3r"
    ],
    "name:swe_x_preferred":[
        "Inishmore Aerodrome"
    ],
    "name:tgk_x_preferred":[
        "\u0424\u0443\u0440\u0443\u0434\u0433\u043e\u04b3\u0438 \u043e\u0438\u043d\u0438\u0448\u043c\u0443\u0440"
    ],
    "oa:elevation_ft":"24",
    "oa:type":"small_airport",
    "woe:hierarchy":{
        "country_id":23424803,
        "localadmin_id":20071479,
        "planet_id":1,
        "state_id":2345251
    },
    "wof:name":"Inishmore Airport",
    "wof:placetype":"campus"
},
  "geometry": {"coordinates":[-9.65361,53.106701],"type":"Point"}
}