{
  "type": "Feature",
  "properties": {
    "gn:admin1_code":"39.0",
    "gn:asciiname":"Osona",
    "gn:dem":1258,
    "gn:feature_class":"P",
    "gn:feature_code":"PPL",
    "gn:name":"Osona",
    "gn:population":0,
    "gn:timezone":"Africa/Windhoek",
    "name:ara_x_preferred":[
        "\u0623\u0648\u0633\u0648\u0646\u0627"
    ],
    "name:arg_x_preferred":[
        "Osona"
    ],
    "name:ast_x_preferred":[
        "Osona"
    ],
    "name:cat_x_preferred":[
        "Osona"
    ],
    "name:deu_x_preferred":[
        "Osona"
    ],
    "name:eus_x_preferred":[
        "Osona"
    ],
    "name:fra_x_preferred":[
        "Osona"
    ],
    "name:glg_x_preferred":[
        "Osona"
    ],
    "name:hun_x_preferred":[
        "Osona"
    ],
    "name:hye_x_preferred":[
        "\u0555\u057d\u0578\u0576\u0561"
    ],
    "name:ita_x_preferred":[
        "Osona"
    ],
    "name:kaz_x_preferred":[
        "\u041e\u0441\u043e\u043d\u0430"
    ],
    "name:nld_x_preferred":[
        "Osona"
    ],
    "name:nor_x_preferred":[
        "Osona"
    ],
    "name:oci_x_preferred":[
        "Osona"
    ],
    "name:pol_x_preferred":[
        "Osona"
    ],
    "name:por_x_preferred":[
        "Osona"
    ],
    "name:ron_x_preferred":[
        "Osona"
    ],
    "name:rus_x_preferred":[
        "\u041e\u0441\u043e\u043d\u0430"
    ],
    "name:sco_x_preferred":[
        "Osona"
    ],
    "name:spa_x_preferred":[
        "Osona"
    ],
    "name:sqi_x_preferred":[
        "Osona"
    ],
    "name:swe_x_preferred":[
        "Osona"
    ],
    "name:ukr_x_preferred":[
        "\u0423\u0437\u043e\u043d\u0430"
    ],
    "name:vie_x_preferred":[
        "Osona"
    ],
    "name:war_x_preferred":[
        "Osona"
    ],
    "wof:name":"Osona",
    "wof:placetype":"locality"
},
  "geometry": {"coordinates":[16.83333,-22.11667000000001],"type":"Point"}
}