{
  "type": "Feature",
  "properties": {
    "name:ceb_x_preferred":[
        "Fleming-Mason Airport"
    ],
    "name:eng_x_preferred":[
        "Fleming-Mason Airport"
    ],
    "name:fas_x_preferred":[
        "\u0641\u0631\u0648\u062f\u06af\u0627\u0647 \u0641\u0644\u0645\u06cc\u0646\u06af-\u0645\u06cc\u0633\u0648\u0646"
    ],
    "name:ron_x_preferred":[
        "Aeroportul Fleming-Mason"
    ],
    "name:tgk_x_preferred":[
        "\u0424\u0443\u0440\u0443\u0434\u0433\u043e\u04b3\u0438 \u0444\u043b\u043c\u0438\u043d\u0433-\u043c\u0438\u0441\u0443\u043d"
    ],
    "name:urd_x_preferred":[
        "\u0641\u0644\u06cc\u0645\u0646\u06af-\u0645\u06cc\u0633\u0646 \u06c1\u0648\u0627\u0626\u06cc \u0627\u0688\u0627"
    ],
    "oa:elevation_ft":"913",
    "oa:type":"small_airport",
    "wd:wordcount":241,
    "woe:hierarchy":{
        "country_id":23424977,
        "county_id":12588553,
        "planet_id":1,
        "state_id":2347576
    },
    "wof:name":"Fleming-Mason Airport",
    "wof:placetype":"campus"
},
  "geometry": {"coordinates":[-83.743333333333,38.541666666667],"type":"Point"}
}