{
  "type": "Feature",
  "properties": {
    "name:deu_x_preferred":[
        "Caulfield"
    ],
    "name:fra_x_preferred":[
        "Caulfield"
    ],
    "name:ita_x_preferred":[
        "Caulfield"
    ],
    "wd:wordcount":101,
    "wof:name":"Caulfield",
    "wof:placetype":"neighbourhood"
},
  "geometry": {"coordinates":[145.02641165582668,-37.88389962176071],"type":"Point"}
}