{
  "type": "Feature",
  "properties": {
    "name:ceb_x_preferred":[
        "Nan"
    ],
    "name:deu_x_preferred":[
        "Flughafen Nan"
    ],
    "name:eng_x_preferred":[
        "Nan Nakhon Airport"
    ],
    "name:eng_x_variant":[
        "NNT",
        "VTCN"
    ],
    "name:fas_x_preferred":[
        "\u0641\u0631\u0648\u062f\u06af\u0627\u0647 \u0646\u0627\u0646"
    ],
    "name:ind_x_preferred":[
        "Bandar Udara Nan"
    ],
    "name:jpn_x_preferred":[
        "\u30ca\u30fc\u30f3\u30ca\u30b3\u30fc\u30f3\u7a7a\u6e2f"
    ],
    "name:kor_x_preferred":[
        "\ub09c \ub098\ucf58 \uacf5\ud56d"
    ],
    "name:msa_x_preferred":[
        "Lapangan Terbang Nan"
    ],
    "name:pol_x_preferred":[
        "Port lotniczy Nan"
    ],
    "name:ron_x_preferred":[
        "Aeroportul Nan Nakhon"
    ],
    "name:rus_x_preferred":[
        "\u041d\u0430\u043d"
    ],
    "name:tgk_x_preferred":[
        "\u0424\u0443\u0440\u0443\u0434\u0433\u043e\u04b3\u0438 \u043d\u043e\u043d"
    ],
    "name:tha_x_preferred":[
        "\u0e17\u0e48\u0e32\u0e2d\u0e32\u0e01\u0e32\u0e28\u0e22\u0e32\u0e19\u0e19\u0e48\u0e32\u0e19\u0e19\u0e04\u0e23"
    ],
    "name:vie_x_preferred":[
        "S\u00e2n bay Nan"
    ],
    "name:wuu_x_preferred":[
        "\u6960\u5e9c\u673a\u573a"
    ],
    "name:zho_x_preferred":[
        "\u6960\u5e9c\u6a5f\u5834"
    ],
    "oa:elevation_ft":"685",
    "oa:type":"medium_airport",
    "wd:wordcount":209,
    "woe:hierarchy":{
        "country_id":23424960,
        "county_id":28340905,
        "planet_id":1,
        "state_id":2347131
    },
    "wof:name":"Nan Airport",
    "wof:placetype":"campus"
},
  "geometry": {"coordinates":[100.78299699999999,18.807899],"type":"Point"}
}