{
  "type": "Feature",
  "properties": {
    "name:eng_x_preferred":[
        "Panguilemo Airport"
    ],
    "name:eng_x_variant":[
        "TLX",
        "SCTL"
    ],
    "name:jpn_x_preferred":[
        "\u30d1\u30f3\u30b0\u30a4\u30ec\u30e2\u7a7a\u6e2f"
    ],
    "name:may_x_preferred":[
        "Lapangan Terbang Panguilemo"
    ],
    "name:spa_x_preferred":[
        "Aer\u00f3dromo Panguilemo"
    ],
    "name:swe_x_preferred":[
        "Panguilemo Airport"
    ],
    "oa:elevation_ft":"371",
    "oa:type":"medium_airport",
    "woe:hierarchy":{
        "country_id":23424782,
        "county_id":26794017,
        "localadmin_id":26794262,
        "planet_id":1,
        "state_id":2345028
    },
    "wof:name":"Talca Airport",
    "wof:placetype":"campus"
},
  "geometry": {"coordinates":[-71.60169999999999,-35.3778],"type":"Point"}
}