{
  "type": "Feature",
  "properties": {
    "name:ara_x_preferred":[
        "\u0645\u0637\u0627\u0631 \u0648\u0627\u062f \u0625\u0631\u0627\u0631\u0629 - \u0643\u0631\u064a\u0645 \u0628\u0644\u0642\u0627\u0633\u0645"
    ],
    "name:ceb_x_preferred":[
        "Oued Irara-Krim Belkacem Airport"
    ],
    "name:deu_x_preferred":[
        "Flughafen Hassi Messaoud"
    ],
    "name:eng_x_preferred":[
        "Oued Irara\u2013Krim Belkacem Airport"
    ],
    "name:eng_x_variant":[
        "HME",
        "DAUH"
    ],
    "name:fas_x_preferred":[
        "\u0641\u0631\u0648\u062f\u06af\u0627\u0647 \u06a9\u0631\u06cc\u0645 \u0628\u0644\u0642\u0627\u0633\u0645"
    ],
    "name:fra_x_preferred":[
        "A\u00e9roport d'Hassi Messaoud - Oued Irara - Krim Belkacem"
    ],
    "name:fra_x_variant":[
        "a\u00e9roport d'Hassi Messaoud - Oued Irara - Krim Belkacem"
    ],
    "name:ind_x_preferred":[
        "Bandar Udara Oued Irara"
    ],
    "name:ita_x_preferred":[
        "Aeroporto di Hassi Messaoud-Oued Irara - Krim Belkacem"
    ],
    "name:jpn_x_preferred":[
        "\u30aa\u30a6\u30c9\u30fb\u30a4\u30e9\u30e9\u30fb\u30af\u30ea\u30e0\u30fb\u30d0\u30eb\u30b1\u30c3\u30b5\u30e0\u7a7a\u6e2f"
    ],
    "name:msa_x_preferred":[
        "Lapangan Terbang Oued Irara-Krim Belkacem"
    ],
    "name:nld_x_preferred":[
        "Luchthaven Oued Irara"
    ],
    "name:pol_x_preferred":[
        "Port lotniczy Oued Irara"
    ],
    "name:ron_x_preferred":[
        "Aeroportul Oued Irara\u2013Krim Belkacem"
    ],
    "name:spa_x_preferred":[
        "aeropuerto Oued Irara\u2013Krim Belkacem"
    ],
    "name:swe_x_preferred":[
        "Krim Belkacem Airport"
    ],
    "name:tgk_x_preferred":[
        "\u0424\u0443\u0440\u0443\u0434\u0433\u043e\u04b3\u0438 \u0643\u0440\u0438\u043c \u0431\u043b\u049b\u043e\u0441\u043c"
    ],
    "name:vie_x_preferred":[
        "S\u00e2n bay Oued Irara"
    ],
    "oa:elevation_ft":"463",
    "oa:type":"medium_airport",
    "wd:wordcount":187,
    "woe:hierarchy":{
        "country_id":23424740,
        "planet_id":1,
        "state_id":2344620
    },
    "wof:name":"Oued Irara Airport",
    "wof:placetype":"campus"
},
  "geometry": {"coordinates":[6.14044,31.673],"type":"Point"}
}