{
  "type": "Feature",
  "properties": {
    "name:ara_x_preferred":[
        "\u0645\u0637\u0627\u0631 \u0645\u062f\u064a\u0646\u0629 \u0627\u0644\u064a\u0648\u0631\u0627\u0646\u064a\u0648\u0645"
    ],
    "name:ceb_x_preferred":[
        "Uranium City Airport"
    ],
    "name:fas_x_preferred":[
        "\u0641\u0631\u0648\u062f\u06af\u0627\u0647 \u0634\u0647\u0631 \u0627\u0648\u0631\u0627\u0646\u06cc\u0648\u0645"
    ],
    "name:msa_x_preferred":[
        "Lapangan Terbang Uranium City"
    ],
    "name:pms_x_preferred":[
        "Uranium City Airport"
    ],
    "name:spa_x_preferred":[
        "Aeropuerto de Uranium City"
    ],
    "name:swe_x_preferred":[
        "Uranium City Airport"
    ],
    "name:tgk_x_preferred":[
        "\u0424\u0443\u0440\u0443\u0434\u0433\u043e\u04b3\u0438 \u0448\u0430\u04b3\u0440 \u0443\u0440\u043e\u043d\u0435\u044e\u043c"
    ],
    "oa:elevation_ft":"1044",
    "oa:type":"medium_airport",
    "wd:wordcount":161,
    "woe:hierarchy":{
        "country_id":23424775,
        "county_id":29375232,
        "planet_id":1,
        "state_id":2344925
    },
    "wof:name":"Uranium City Airport",
    "wof:placetype":"campus"
},
  "geometry": {"coordinates":[-108.48099999999999,59.5614],"type":"Point"}
}