{
  "type": "Feature",
  "properties": {
    "name:eng_x_preferred":[
        "El Bluff Airport"
    ],
    "name:eng_x_variant":[
        "MNFF"
    ],
    "name:ron_x_preferred":[
        "Aeroportul El Bluff"
    ],
    "oa:elevation_ft":"1",
    "oa:type":"small_airport",
    "wd:wordcount":146,
    "woe:hierarchy":{
        "country_id":23424915,
        "county_id":26813435,
        "planet_id":1,
        "state_id":20069832
    },
    "wof:name":"El Bluff Airport",
    "wof:placetype":"campus"
},
  "geometry": {"coordinates":[-83.68944399999999,11.991667],"type":"Point"}
}