{
  "type": "Feature",
  "properties": {
    "oa:elevation_ft":"1",
    "oa:type":"small_airport",
    "wd:wordcount":146,
    "woe:hierarchy":{
        "country_id":23424915,
        "county_id":26813435,
        "planet_id":1,
        "state_id":20069832
    },
    "wof:name":"El Bluff Airport",
    "wof:placetype":"campus"
},
  "geometry": {"coordinates":[-83.68944444,11.99166667],"type":"Point"}
}