{
  "type": "Feature",
  "properties": {
    "name:ceb_x_preferred":[
        "Akure Airport"
    ],
    "name:eng_x_preferred":[
        "Akure Airport"
    ],
    "name:eng_x_variant":[
        "AKR",
        "DNAK"
    ],
    "name:fas_x_preferred":[
        "\u0641\u0631\u0648\u062f\u06af\u0627\u0647 \u0627\u06a9\u0648\u0631"
    ],
    "name:fra_x_preferred":[
        "AKURE"
    ],
    "name:ita_x_preferred":[
        "Aeroporto di Akure"
    ],
    "name:jpn_x_preferred":[
        "\u30a2\u30af\u30ec\u7a7a\u6e2f"
    ],
    "name:pol_x_preferred":[
        "Port lotniczy Akure"
    ],
    "name:ron_x_preferred":[
        "Aeroportul Akure"
    ],
    "name:tgk_x_preferred":[
        "\u0424\u0443\u0440\u0443\u0434\u0433\u043e\u04b3\u0438 \u043e\u043a\u0443\u0440"
    ],
    "name:zho_x_preferred":[
        "\u963f\u5eab\u96f7\u6a5f\u5834"
    ],
    "oa:elevation_ft":"1100",
    "oa:type":"medium_airport",
    "wd:wordcount":62,
    "woe:hierarchy":{
        "country_id":23424908,
        "county_id":56057651,
        "planet_id":1,
        "state_id":2346347
    },
    "wof:name":"Akure Airport",
    "wof:placetype":"campus"
},
  "geometry": {"coordinates":[5.30101,7.24674],"type":"Point"}
}