{
  "type": "Feature",
  "properties": {
    "gn:admin1_code":"28.0",
    "gn:asciiname":"Ntonde",
    "gn:dem":933,
    "gn:feature_class":"P",
    "gn:feature_code":"PPL",
    "gn:name":"Ntonde",
    "gn:population":0,
    "gn:timezone":"Africa/Windhoek",
    "wof:name":"Ntonde",
    "wof:placetype":"locality"
},
  "geometry": {"coordinates":[24.85,-17.53333],"type":"Point"}
}