{
  "type": "Feature",
  "properties": {
    "wd:wordcount":141,
    "wof:name":"Fairmont",
    "wof:placetype":"neighbourhood"
},
  "geometry": {"coordinates":[-111.86723958309439,40.72270727776777],"type":"Point"}
}