{
  "type": "Feature",
  "properties": {
    "name:eng_x_variant":[
        "CXC"
    ],
    "oa:elevation_ft":"556",
    "oa:type":"small_airport",
    "woe:hierarchy":{
        "country_id":23424977,
        "county_id":12587576,
        "planet_id":1,
        "state_id":2347560
    },
    "wof:name":"Chitina Airport",
    "wof:placetype":"campus"
},
  "geometry": {"coordinates":[-144.42700199999999,61.582901],"type":"Point"}
}