{
  "type": "Feature",
  "properties": {
    "name:ara_x_preferred":[
        "\u062a\u0644\u0627\u0644 \u0628\u0644\u0648 \u0647\u064a\u0644\u0632"
    ],
    "name:ben_x_preferred":[
        "\u09ac\u09cd\u09b2\u09c1 \u09b9\u09bf\u09b2\u09b8"
    ],
    "name:ceb_x_preferred":[
        "Blue Hills"
    ],
    "name:deu_x_preferred":[
        "Blue Hills"
    ],
    "name:ell_x_preferred":[
        "\u039c\u03c0\u03bb\u03bf\u03c5 \u03a7\u03b9\u03bb\u03c2"
    ],
    "name:eng_x_preferred":[
        "Blue Hills"
    ],
    "name:fas_x_preferred":[
        "\u062a\u067e\u0647 \u0647\u0627\u06cc \u0628\u0644\u0648"
    ],
    "name:fra_x_preferred":[
        "Blue Hills"
    ],
    "name:heb_x_preferred":[
        "\u05d2\u05d1\u05e2\u05d5\u05ea \u05d1\u05dc\u05d5"
    ],
    "name:hin_x_preferred":[
        "\u092c\u094d\u0932\u0942 \u0939\u093f\u0932\u094d\u0938"
    ],
    "name:hun_x_preferred":[
        "Blue Hills"
    ],
    "name:ind_x_preferred":[
        "Blue Hills"
    ],
    "name:kor_x_preferred":[
        "\ube14\ub8e8 \ud790\uc2a4"
    ],
    "name:por_x_preferred":[
        "Blue Hills"
    ],
    "name:rus_x_preferred":[
        "\u0411\u043b\u044e-\u0425\u0438\u043b\u043b\u0437"
    ],
    "name:spa_x_preferred":[
        "Blue Hills"
    ],
    "name:swe_x_preferred":[
        "Blue Hills"
    ],
    "name:tur_x_preferred":[
        "Blue Hills"
    ],
    "name:ukr_x_preferred":[
        "\u0411\u043b\u0443-\u0425\u0456\u043b\u043b\u0441"
    ],
    "name:urd_x_preferred":[
        "\u0628\u0644\u0648 \u06c1\u0644\u0632"
    ],
    "name:vie_x_preferred":[
        "Blue Hills"
    ],
    "name:zho_cn_x_preferred":[
        "\u84dd\u5c71"
    ],
    "name:zho_tw_x_preferred":[
        "\u85cd\u5c71"
    ],
    "wd:wordcount":77,
    "wof:name":"Blue Hills",
    "wof:placetype":"neighbourhood"
},
  "geometry": {"coordinates":[-94.561881,39.027624],"type":"Point"}
}