{
  "type": "Feature",
  "properties": {
    "name:ceb_x_preferred":[
        "Blue Hills"
    ],
    "name:deu_x_preferred":[
        "Blue Hills"
    ],
    "name:eng_x_preferred":[
        "Blue Hills"
    ],
    "name:fra_x_preferred":[
        "Blue Hills"
    ],
    "name:swe_x_preferred":[
        "Blue Hills"
    ],
    "wd:wordcount":77,
    "wof:name":"Blue Hills",
    "wof:placetype":"neighbourhood"
},
  "geometry": {"coordinates":[-94.56188067869101,39.02762406028204],"type":"Point"}
}