{
  "type": "Feature",
  "properties": {
    "gn:admin1_code":"36.0",
    "gn:asciiname":"Uutsima",
    "gn:dem":1093,
    "gn:feature_class":"P",
    "gn:feature_code":"PPL",
    "gn:name":"Uutsima",
    "gn:population":0,
    "gn:timezone":"Africa/Windhoek",
    "wof:name":"Uutsima",
    "wof:placetype":"locality"
},
  "geometry": {"coordinates":[15.36667,-17.86667000000001],"type":"Point"}
}