{
  "type": "Feature",
  "properties": {
    "name:ceb_x_preferred":[
        "Tel\u00eamaco Borba Airport"
    ],
    "name:deu_x_preferred":[
        "Flughafen Tel\u00eamaco Borba"
    ],
    "name:eng_x_preferred":[
        "Tel\u00eamaco Borba Airport"
    ],
    "name:eng_x_variant":[
        "TEC",
        "SBTL"
    ],
    "name:fas_x_preferred":[
        "\u0641\u0631\u0648\u062f\u06af\u0627\u0647 \u0627\u0644\u0645\u0627\u06a9\u0648 \u0628\u0648\u0631\u0628\u0627"
    ],
    "name:fra_x_preferred":[
        "A\u00e9roport de Tel\u00eamaco Borba"
    ],
    "name:fra_x_variant":[
        "a\u00e9roport de Tel\u00eamaco Borba"
    ],
    "name:jpn_x_preferred":[
        "\u30c6\u30ec\u30de\u30b3\u30fb\u30dc\u30a2\u30d0\u7a7a\u6e2f"
    ],
    "name:msa_x_preferred":[
        "Lapangan Terbang Telemaco Borba"
    ],
    "name:nld_x_preferred":[
        "Aeroporto de Tel\u00eamaco Borba"
    ],
    "name:por_x_preferred":[
        "Aeroporto de Tel\u00eamaco Borba"
    ],
    "name:ron_x_preferred":[
        "Aeroportul Tel\u00eamaco Borba"
    ],
    "name:spa_x_preferred":[
        "Aeropuerto de Tel\u00eamaco Borba"
    ],
    "name:swe_x_preferred":[
        "Tel\u00eamaco Borba Airport"
    ],
    "name:tgk_x_preferred":[
        "\u0424\u0443\u0440\u0443\u0434\u0433\u043e\u04b3\u0438 \u043e\u043b\u043c\u043e\u043a\u0443 \u0431\u0443\u0440\u0431\u043e"
    ],
    "oa:elevation_ft":"2610",
    "oa:type":"medium_airport",
    "wd:wordcount":145,
    "woe:hierarchy":{
        "country_id":23424768,
        "county_id":12580704,
        "planet_id":1,
        "state_id":2344859
    },
    "wof:name":"Aeroporto Telemaco Borba",
    "wof:placetype":"campus"
},
  "geometry": {"coordinates":[-50.6516,-24.317801],"type":"Point"}
}