{
  "type": "Feature",
  "properties": {
    "oa:elevation_ft":"733",
    "oa:type":"small_airport",
    "woe:hierarchy":{
        "country_id":23424977,
        "county_id":12589680,
        "planet_id":1,
        "state_id":2347595
    },
    "wof:name":"Claremore Municipal Airport",
    "wof:placetype":"campus"
},
  "geometry": {"coordinates":[-95.47969999999999,36.2928],"type":"Point"}
}