{
  "type": "Feature",
  "properties": {
    "name:eng_x_variant":[
        "GRN",
        "KGRN"
    ],
    "oa:elevation_ft":"3562",
    "oa:type":"small_airport",
    "woe:hierarchy":{
        "country_id":23424977,
        "county_id":12589218,
        "planet_id":1,
        "state_id":2347586
    },
    "wof:name":"Gordon Municipal Airport",
    "wof:placetype":"campus"
},
  "geometry": {"coordinates":[-102.175003,42.806],"type":"Point"}
}