{
  "type": "Feature",
  "properties": {
    "name:eng_x_variant":[
        "MOF",
        "WATC"
    ],
    "oa:elevation_ft":"115",
    "oa:type":"small_airport",
    "woe:hierarchy":{
        "country_id":23424846,
        "county_id":56000062,
        "planet_id":1,
        "state_id":2345727
    },
    "wof:name":"Wai Oti Airport",
    "wof:placetype":"campus"
},
  "geometry": {"coordinates":[122.23699999999999,-8.64065],"type":"Point"}
}