{
  "type": "Feature",
  "properties": {
    "name:ast_x_preferred":[
        "Aeropuertu Frans Seda"
    ],
    "name:ceb_x_preferred":[
        "Frans Seda Airport"
    ],
    "name:eng_x_preferred":[
        "Frans Seda Airport"
    ],
    "name:eng_x_variant":[
        "MOF",
        "WATC"
    ],
    "name:fas_x_preferred":[
        "\u0641\u0631\u0648\u062f\u06af\u0627\u0647 \u0648\u0627\u06cc-\u0627\u0648\u062a\u06cc"
    ],
    "name:ind_x_preferred":[
        "Bandar Udara Wai Oti"
    ],
    "name:msa_x_preferred":[
        "Lapangan Terbang Wai Oti"
    ],
    "name:nld_x_preferred":[
        "Luchthaven Waioti"
    ],
    "name:ron_x_preferred":[
        "Aeroportul Frans Seda"
    ],
    "name:spa_x_preferred":[
        "Aeropuerto Frans Seda"
    ],
    "name:swe_x_preferred":[
        "Frans Seda Airport"
    ],
    "name:tgk_x_preferred":[
        "\u0424\u0443\u0440\u0443\u0434\u0433\u043e\u04b3\u0438 \u0432\u043e\u0439-\u0430\u0432\u0433\u0443\u0441\u0442\u0435"
    ],
    "name:zho_x_preferred":[
        "\u5f17\u5170\u65af\u00b7\u6cfd\u7ef4\u5c14\u00b7\u585e\u8fbe\u673a\u573a"
    ],
    "oa:elevation_ft":"115",
    "oa:type":"small_airport",
    "woe:hierarchy":{
        "country_id":23424846,
        "county_id":56000062,
        "planet_id":1,
        "state_id":2345727
    },
    "wof:name":"Wai Oti Airport",
    "wof:placetype":"campus"
},
  "geometry": {"coordinates":[122.23699999999999,-8.64065],"type":"Point"}
}