{
  "type": "Feature",
  "properties": {
    "wd:wordcount":5429,
    "wof:name":"Didsbury",
    "wof:placetype":"neighbourhood"
},
  "geometry": {"coordinates":[-2.23312593657212,53.41710655518518],"type":"Point"}
}