{
  "type": "Feature",
  "properties": {
    "name:ceb_x_preferred":[
        "Cherokee County Airport"
    ],
    "name:eng_x_preferred":[
        "Cherokee County Airport"
    ],
    "name:fas_x_preferred":[
        "\u0641\u0631\u0648\u062f\u06af\u0627\u0647 \u0686\u0631\u0648\u06a9\u06cc \u06a9\u0627\u0646\u062a\u06cc"
    ],
    "name:fra_x_preferred":[
        "CNI"
    ],
    "name:ind_x_preferred":[
        "Bandar Udara Kabupaten Cherokee"
    ],
    "name:ron_x_preferred":[
        "Aeroportul Cherokee County"
    ],
    "name:tgk_x_preferred":[
        "\u0424\u0443\u0440\u0443\u0434\u0433\u043e\u04b3\u0438 \u0447\u0440\u0443\u043a\u0438 \u043a\u043e\u043d"
    ],
    "name:urd_x_preferred":[
        "\u0686\u0631\u0648\u06a9\u06cc \u06a9\u0627\u0624\u0646\u0679\u06cc \u0631\u06cc\u062c\u0646\u0644 \u06c1\u0648\u0627\u0626\u06cc \u0627\u0688\u0627"
    ],
    "oa:elevation_ft":"1219",
    "oa:type":"small_airport",
    "wd:wordcount":55,
    "woe:hierarchy":{
        "country_id":23424977,
        "county_id":12587897,
        "planet_id":1,
        "state_id":2347569
    },
    "wof:name":"Cherokee County Airport",
    "wof:placetype":"campus"
},
  "geometry": {"coordinates":[-84.4239,34.3106],"type":"Point"}
}