{
  "type": "Feature",
  "properties": {
    "name:ind_x_preferred":[
        "Bandar Udara Kabupaten Cherokee"
    ],
    "oa:elevation_ft":"1219",
    "oa:type":"small_airport",
    "wd:wordcount":55,
    "woe:hierarchy":{
        "country_id":23424977,
        "county_id":12587897,
        "planet_id":1,
        "state_id":2347569
    },
    "wof:name":"Cherokee County Airport",
    "wof:placetype":"campus"
},
  "geometry": {"coordinates":[-84.4239,34.3106],"type":"Point"}
}