{
  "type": "Feature",
  "properties": {
    "name:ara_x_preferred":[
        "\u0645\u0637\u0627\u0631 \u0641\u0627\u0644\u064a\u0648\u0644\u0648 \u0627\u0644\u062f\u0648\u0644\u064a"
    ],
    "name:cym_x_preferred":[
        "Maes Awyr Rhyngwladol Faleolo"
    ],
    "name:deu_x_preferred":[
        "Flughafen Faleolo"
    ],
    "name:eng_x_preferred":[
        "Faleolo International Airport"
    ],
    "name:eng_x_variant":[
        "APW",
        "NSFA"
    ],
    "name:fas_x_preferred":[
        "\u0641\u0631\u0648\u062f\u06af\u0627\u0647 \u0628\u06cc\u0646\u200c\u0627\u0644\u0645\u0644\u0644\u06cc \u0641\u0627\u0644\u0626\u0648\u0644\u0648"
    ],
    "name:fra_x_preferred":[
        "a\u00e9roport d'Apia"
    ],
    "name:ind_x_preferred":[
        "Bandar Udara Internasional Faleolo"
    ],
    "name:ita_x_preferred":[
        "Aeroporto Internazionale di Faleolo"
    ],
    "name:jpn_x_preferred":[
        "\u30d5\u30a1\u30ec\u30aa\u30ed\u56fd\u969b\u7a7a\u6e2f"
    ],
    "name:kor_x_preferred":[
        "\ud314\ub808\uc62c\ub85c \uad6d\uc81c\uacf5\ud56d"
    ],
    "name:msa_x_preferred":[
        "Lapangan Terbang Antarabangsa Faleolo"
    ],
    "name:nld_x_preferred":[
        "Faleolo International Airport"
    ],
    "name:pol_x_preferred":[
        "Port lotniczy Faleolo"
    ],
    "name:ron_x_preferred":[
        "Aeroportul Interna\u021bional Faleolo"
    ],
    "name:rus_x_preferred":[
        "\u0424\u0430\u043b\u0435\u043e\u043b\u043e"
    ],
    "name:slk_x_preferred":[
        "Medzin\u00e1rodn\u00e9 letisko Faleolo"
    ],
    "name:spa_x_preferred":[
        "Aeropuerto Internacional Faleolo"
    ],
    "name:tgk_x_preferred":[
        "\u0424\u0443\u0440\u0443\u0434\u0433\u043e\u04b3\u0438 \u0431\u0438\u043d\u200c\u0430\u043b\u043c\u0438\u043b\u0430\u043b\u04e3 \u0444\u043e\u043b\u0435\u04b3\u0432\u043b\u0443"
    ],
    "name:zho_x_preferred":[
        "\u6cd5\u83b1\u5965\u6d1b\u56fd\u9645\u673a\u573a"
    ],
    "oa:elevation_ft":"58",
    "oa:type":"medium_airport",
    "woe:hierarchy":{
        "country_id":23424992,
        "planet_id":1,
        "state_id":20070340
    },
    "wof:name":"Faleolo Airport",
    "wof:placetype":"campus"
},
  "geometry": {"coordinates":[-172.00799599999999,-13.83],"type":"Point"}
}