{
  "type": "Feature",
  "properties": {
    "name:deu_x_preferred":[
        "Flughafen Bulawayo"
    ],
    "name:eng_x_preferred":[
        "Joshua Mqabuko Nkomo International Airport"
    ],
    "name:eng_x_variant":[
        "BUQ",
        "FVBU"
    ],
    "name:fas_x_preferred":[
        "\u0641\u0631\u0648\u062f\u06af\u0627\u0647 \u0628\u06cc\u0646\u200c\u0627\u0644\u0645\u0644\u0644\u06cc \u062c\u0627\u0634\u0648\u0627 \u0645\u06a9\u0627\u0628\u0648\u06a9\u0648 \u0627\u0646\u06a9\u0648\u0645\u0648"
    ],
    "name:jpn_x_preferred":[
        "\u30d6\u30e9\u30ef\u30fc\u30e8"
    ],
    "name:lit_x_preferred":[
        "D\u017eo\u0161ua Mkabuko Nkomo oro uostas"
    ],
    "name:msa_x_preferred":[
        "Lapangan Terbang J.M. Nkomo"
    ],
    "name:nob_x_preferred":[
        "Joshua Mqabuko Nkomo internasjonale lufthavn"
    ],
    "name:pol_x_preferred":[
        "Port lotniczy Bulawayo"
    ],
    "name:spa_x_preferred":[
        "Aeropuerto Internacional Joshua Mqabuko Nkomo"
    ],
    "name:tgk_x_preferred":[
        "\u0424\u0443\u0440\u0443\u0434\u0433\u043e\u04b3\u0438 \u0431\u0438\u043d\u200c\u0430\u043b\u043c\u0438\u043b\u0430\u043b\u04e3 \u04b7\u043e\u0448\u0443\u043e \u043c\u043a\u043e\u0431\u0443\u043a\u0443 \u043e\u043d\u043a\u0443\u043c\u0443"
    ],
    "name:tur_x_preferred":[
        "Uluslararas\u0131 Joshua Mqabuko Nkomo Havaalan\u0131"
    ],
    "name:vie_x_preferred":[
        "S\u00e2n bay qu\u1ed1c t\u1ebf Joshua Mqabuko Nkomo"
    ],
    "name:zho_x_preferred":[
        "Joshua Mqabuko Nkomo\u570b\u969b\u6a5f\u5834"
    ],
    "oa:elevation_ft":"4359",
    "oa:type":"medium_airport",
    "woe:hierarchy":{
        "country_id":23425004,
        "county_id":56048528,
        "planet_id":1,
        "state_id":24550730
    },
    "wof:name":"Bulawayo Airport",
    "wof:placetype":"campus"
},
  "geometry": {"coordinates":[28.617901,-20.017401],"type":"Point"}
}