{
  "type": "Feature",
  "properties": {
    "name:ceb_x_preferred":[
        "Big Trout Lake Airport"
    ],
    "name:eng_x_preferred":[
        "Big Trout Lake Airport"
    ],
    "name:eng_x_variant":[
        "YTL",
        "CYTL"
    ],
    "name:fas_x_preferred":[
        "\u0641\u0631\u0648\u062f\u06af\u0627\u0647 \u062f\u0631\u06cc\u0627\u0686 \u0628\u06cc\u06af \u062a\u0631\u0627\u0648\u062a"
    ],
    "name:msa_x_preferred":[
        "Lapangan Terbang Big Trout Lake"
    ],
    "name:pms_x_preferred":[
        "Big Trout Lake Airport"
    ],
    "name:swe_x_preferred":[
        "Big Trout Lake Airport"
    ],
    "name:tgk_x_preferred":[
        "\u0424\u0443\u0440\u0443\u0434\u0433\u043e\u04b3\u0438 \u0434\u0440\u0438\u043e\u0447 \u0431\u0438\u0439\u0433 \u0442\u0440\u043e\u0432\u0442"
    ],
    "oa:elevation_ft":"729",
    "oa:type":"medium_airport",
    "wd:wordcount":104,
    "woe:hierarchy":{
        "country_id":23424775,
        "county_id":29375238,
        "planet_id":1,
        "state_id":2344922
    },
    "wof:name":"Big Trout Lake Airport",
    "wof:placetype":"campus"
},
  "geometry": {"coordinates":[-89.896896,53.817799],"type":"Point"}
}