{
  "type": "Feature",
  "properties": {
    "name:ceb_x_preferred":[
        "Mackay Mo"
    ],
    "name:ces_x_preferred":[
        "Leti\u0161t\u011b Mackay"
    ],
    "name:eng_x_preferred":[
        "Mackay Airport"
    ],
    "name:eng_x_variant":[
        "MKY",
        "YBMK"
    ],
    "name:fas_x_preferred":[
        "\u0641\u0631\u0648\u062f\u06af\u0627\u0647 \u0645\u06a9\u06cc"
    ],
    "name:jpn_x_preferred":[
        "\u30de\u30c3\u30ab\u30a4\u7a7a\u6e2f"
    ],
    "name:msa_x_preferred":[
        "Lapangan Terbang Mackay"
    ],
    "name:pol_x_preferred":[
        "Port lotniczy Mackay"
    ],
    "name:ron_x_preferred":[
        "Aeroportul Mackay"
    ],
    "name:rus_x_preferred":[
        "\u041c\u0430\u043a\u043a\u0430\u0439"
    ],
    "name:swe_x_preferred":[
        "Mackay Mo"
    ],
    "name:zho_x_preferred":[
        "\u9ea5\u51f1\u6a5f\u5834"
    ],
    "oa:elevation_ft":"19",
    "oa:type":"medium_airport",
    "wd:wordcount":748,
    "woe:hierarchy":{
        "country_id":23424748,
        "county_id":56072973,
        "planet_id":1,
        "state_id":2344702,
        "suburb_id":28587273
    },
    "wof:name":"Mackay Airport",
    "wof:placetype":"campus"
},
  "geometry": {"coordinates":[149.179993,-21.1717],"type":"Point"}
}