{
  "type": "Feature",
  "properties": {
    "name:ceb_x_preferred":[
        "Jack Barstow Airport"
    ],
    "name:eng_x_preferred":[
        "Jack Barstow Municipal Airport"
    ],
    "name:fas_x_preferred":[
        "\u0641\u0631\u0648\u062f\u06af\u0627\u0647 \u0634\u0647\u0631\u06cc \u062c\u06a9 \u0628\u0627\u0631\u0633\u062a\u0648"
    ],
    "name:jpn_x_preferred":[
        "Jack Barstow\u5e02\u55b6\u7a7a\u6e2f"
    ],
    "name:ron_x_preferred":[
        "Aeroportul Municipal Jack Barstow"
    ],
    "name:tgk_x_preferred":[
        "\u0424\u0443\u0440\u0443\u0434\u0433\u043e\u04b3\u0438 \u0448\u0430\u04b3\u0440\u0435 \u04b7\u0430\u043a \u0431\u043e\u0440\u0441\u0442\u0443"
    ],
    "name:urd_x_preferred":[
        "\u062c\u06cc\u06a9 \u0628\u0627\u0631\u0633\u0679\u0648 \u0645\u06cc\u0648\u0646\u0633\u067e\u0644 \u0627\u06cc\u0626\u0631\u067e\u0648\u0631\u0679"
    ],
    "oa:elevation_ft":"635",
    "oa:type":"small_airport",
    "wd:wordcount":492,
    "woe:hierarchy":{
        "country_id":23424977,
        "county_id":12588769,
        "planet_id":1,
        "state_id":2347581
    },
    "wof:name":"Jack Barstow Airport",
    "wof:placetype":"campus"
},
  "geometry": {"coordinates":[-84.26139999999999,43.6628],"type":"Point"}
}