{
  "type": "Feature",
  "properties": {
    "name:eng_x_preferred":[
        "Mokpo Airport"
    ],
    "name:eng_x_variant":[
        "MPK",
        "RKJM"
    ],
    "name:fas_x_preferred":[
        "\u0641\u0631\u0648\u062f\u06af\u0627\u0647 \u0645\u0648\u06a9\u067e\u0648"
    ],
    "name:jpn_x_preferred":[
        "\u6728\u6d66\u7a7a\u6e2f"
    ],
    "name:kor_x_preferred":[
        "\ubaa9\ud3ec\uacf5\ud56d"
    ],
    "name:msa_x_preferred":[
        "Lapangan Terbang Mokpo"
    ],
    "name:pol_x_preferred":[
        "Port lotniczy Mokpo"
    ],
    "name:por_x_preferred":[
        "Aeroporto de Mokpo"
    ],
    "name:tgk_x_preferred":[
        "\u0424\u0443\u0440\u0443\u0434\u0433\u043e\u04b3\u0438 \u043c\u0443\u043a\u043f\u0443"
    ],
    "name:vie_x_preferred":[
        "S\u00e2n bay Mokpo"
    ],
    "name:zho_x_preferred":[
        "\u6728\u6d66\u6a5f\u5834"
    ],
    "oa:elevation_ft":"23",
    "oa:type":"heliport",
    "woe:hierarchy":{
        "country_id":23424868,
        "county_id":28289322,
        "localadmin_id":28808181,
        "planet_id":1,
        "state_id":2345972
    },
    "wof:name":"\ubaa9\ud3ec\uacf5\ud56d",
    "wof:placetype":"campus"
},
  "geometry": {"coordinates":[126.379997,34.7589],"type":"Point"}
}