{
  "type": "Feature",
  "properties": {
    "wof:name":"Quartier des villes et provinces de France",
    "wof:placetype":"neighbourhood"
},
  "geometry": {"coordinates":[-73.42637598584548,45.57678239193432],"type":"Point"}
}