{
  "type": "Feature",
  "properties": {
    "wof:name":"Yallambie",
    "wof:placetype":"neighbourhood"
},
  "geometry": {"coordinates":[145.09745089139923,-37.72580005789758],"type":"Point"}
}