{
  "type": "Feature",
  "properties": {
    "name:ast_x_preferred":[
        "Aeropuertu Rafael Cabrera"
    ],
    "name:ceb_x_preferred":[
        "Rafael Cabrera Mustelier Airport"
    ],
    "name:eng_x_preferred":[
        "Rafael Cabrera Mustelier Airport"
    ],
    "name:eng_x_variant":[
        "GER",
        "MUNG"
    ],
    "name:fas_x_preferred":[
        "\u0641\u0631\u0648\u062f\u06af\u0627\u0647 \u0631\u0627\u0641\u0627\u0626\u0644 \u06a9\u0627\u0628\u0631\u0631\u0627"
    ],
    "name:hun_x_preferred":[
        "Rafael Cabrera Mustelier rep\u00fcl\u0151t\u00e9r"
    ],
    "name:ita_x_preferred":[
        "Aeroporto Rafael Cabrera Mustelier"
    ],
    "name:jpn_x_preferred":[
        "\u30e9\u30d5\u30a1\u30a8\u30eb\u30fb\u30ab\u30d6\u30ec\u30e9\u7a7a\u6e2f"
    ],
    "name:msa_x_preferred":[
        "Lapangan Terbang Rafael Cabrera"
    ],
    "name:pol_x_preferred":[
        "Port lotniczy Rafael Cabrera"
    ],
    "name:ron_x_preferred":[
        "Aeroportul Rafael Cabrera Mustelier"
    ],
    "name:spa_x_preferred":[
        "Aeropuerto Rafael Cabrera"
    ],
    "name:swe_x_preferred":[
        "Rafael Cabrera Mustelier Airport"
    ],
    "name:tgk_x_preferred":[
        "\u0424\u0443\u0440\u0443\u0434\u0433\u043e\u04b3\u0438 \u0440\u043e\u0444\u043e\u0435\u04b3\u043b \u043a\u043e\u0431\u0440\u0440\u043e"
    ],
    "name:zho_x_preferred":[
        "Rafael Cabrera Mustelier\u6a5f\u5834"
    ],
    "oa:elevation_ft":"79",
    "oa:type":"medium_airport",
    "woe:hierarchy":{
        "country_id":23424793,
        "planet_id":1,
        "state_id":2345109
    },
    "wof:name":"Nueva Gerona Airport",
    "wof:placetype":"campus"
},
  "geometry": {"coordinates":[-82.783798,21.8347],"type":"Point"}
}