{
  "type": "Feature",
  "properties": {
    "name:eng_x_preferred":[
        "San Rafael Airport"
    ],
    "name:eng_x_variant":[
        "AFA",
        "SAMR"
    ],
    "name:fas_x_preferred":[
        "\u0641\u0631\u0648\u062f\u06af\u0627\u0647 \u0633\u0646 \u0631\u0627\u0641\u0627\u0626\u0644"
    ],
    "name:jpn_x_preferred":[
        "\u30b5\u30f3\u30fb\u30e9\u30d5\u30a1\u30a8\u30eb\u7a7a\u6e2f"
    ],
    "name:msa_x_preferred":[
        "Lapangan Terbang San Rafael"
    ],
    "name:nob_x_preferred":[
        "San Rafael lufthavn"
    ],
    "name:pol_x_preferred":[
        "Port lotniczy San Rafael"
    ],
    "name:por_x_preferred":[
        "Aeroporto Internacional Suboficial Ayudante Santiago Germano"
    ],
    "name:spa_x_preferred":[
        "Aeropuerto Internacional Suboficial Ayudante Santiago Germano"
    ],
    "name:swe_x_preferred":[
        "San Rafael Aerodrome"
    ],
    "name:tgk_x_preferred":[
        "\u0424\u0443\u0440\u0443\u0434\u0433\u043e\u04b3\u0438 \u0441\u0438\u043d \u0440\u043e\u0444\u043e\u0435\u04b3\u043b"
    ],
    "name:zho_x_preferred":[
        "\u8056\u62c9\u6590\u723e\u6a5f\u5834"
    ],
    "oa:elevation_ft":"2470",
    "oa:type":"medium_airport",
    "wd:wordcount":56,
    "woe:hierarchy":{
        "country_id":23424747,
        "county_id":20071013,
        "planet_id":1,
        "state_id":2344687
    },
    "wof:name":"San Rafael Airport",
    "wof:placetype":"campus"
},
  "geometry": {"coordinates":[-68.40389999999999,-34.588299],"type":"Point"}
}