{
  "type": "Feature",
  "properties": {
    "name:ara_x_preferred":[
        "\u0645\u0637\u0627\u0631 \u0634\u064a\u0644\u0648\u0646\u063a"
    ],
    "name:ben_x_preferred":[
        "\u09b6\u09bf\u09b2\u0982 \u09ac\u09bf\u09ae\u09be\u09a8\u09ac\u09a8\u09cd\u09a6\u09b0"
    ],
    "name:ceb_x_preferred":[
        "Shillong Airport"
    ],
    "name:eng_x_preferred":[
        "Shillong Airport"
    ],
    "name:fas_x_preferred":[
        "\u0641\u0631\u0648\u062f\u06af\u0627\u0647 \u0634\u06cc\u0644\u0627\u0646\u06af"
    ],
    "name:hin_x_preferred":[
        "\u0936\u093f\u0932\u093e\u0902\u0917 \u0939\u0935\u093e\u0908 \u0905\u0921\u094d\u0921\u093e"
    ],
    "name:jpn_x_preferred":[
        "\u30b7\u30ed\u30f3\u7a7a\u6e2f"
    ],
    "name:mar_x_preferred":[
        "\u0936\u093f\u0932\u093e\u0901\u0917 \u0935\u093f\u092e\u093e\u0928\u0924\u0933"
    ],
    "name:msa_x_preferred":[
        "Lapangan Terbang Barapani"
    ],
    "name:pol_x_preferred":[
        "Port lotniczy Shillong"
    ],
    "name:ron_x_preferred":[
        "Aeroportul Shillong"
    ],
    "name:swe_x_preferred":[
        "Shillong Airport"
    ],
    "name:tam_x_preferred":[
        "\u0bb7\u0bbf\u0bb2\u0bcd\u0bb2\u0bbe\u0b99\u0bcd \u0bb5\u0bbf\u0bae\u0bbe\u0ba9 \u0ba8\u0bbf\u0bb2\u0bc8\u0baf\u0bae\u0bcd"
    ],
    "name:tgk_x_preferred":[
        "\u0424\u0443\u0440\u0443\u0434\u0433\u043e\u04b3\u0438 \u0448\u0438\u043b\u043e\u043d\u0433"
    ],
    "name:vie_x_preferred":[
        "S\u00e2n bay Shillong"
    ],
    "name:zho_x_preferred":[
        "\u897f\u9686"
    ],
    "oa:elevation_ft":"2910",
    "oa:type":"medium_airport",
    "wd:wordcount":248,
    "woe:hierarchy":{
        "country_id":23424848,
        "county_id":28298860,
        "planet_id":1,
        "state_id":2345752
    },
    "wof:name":"Shillong Airport",
    "wof:placetype":"campus"
},
  "geometry": {"coordinates":[91.97861111111099,25.703611111111],"type":"Point"}
}