{
  "type": "Feature",
  "properties": {
    "gn:admin1_code":"33.0",
    "gn:asciiname":"Onghwiyu",
    "gn:dem":1145,
    "gn:feature_class":"P",
    "gn:feature_code":"PPL",
    "gn:name":"Onghwiyu",
    "gn:population":0,
    "gn:timezone":"Africa/Windhoek",
    "wof:name":"Onghwiyu",
    "wof:placetype":"locality"
},
  "geometry": {"coordinates":[16.85,-17.53333],"type":"Point"}
}