{
  "type": "Feature",
  "properties": {
    "name:ben_x_preferred":[
        "\u09b8\u09cb\u09a8\u09be\u09b0\u09c0 \u09ac\u09bf\u09ae\u09be\u09a8\u09ac\u09a8\u09cd\u09a6\u09b0"
    ],
    "name:ceb_x_preferred":[
        "Jamshedpur"
    ],
    "name:deu_x_preferred":[
        "Flughafen Jamshedpur"
    ],
    "name:eng_x_preferred":[
        "Sonari Airport"
    ],
    "name:eng_x_variant":[
        "IXW",
        "VEJS"
    ],
    "name:fas_x_preferred":[
        "\u0641\u0631\u0648\u062f\u06af\u0627\u0647 \u0633\u0627\u0646\u0631\u06cc"
    ],
    "name:hin_x_preferred":[
        "\u0938\u094b\u0928\u093e\u0930\u0940 \u0939\u0935\u093e\u0908-\u0905\u0921\u094d\u0921\u093e"
    ],
    "name:jpn_x_preferred":[
        "\u30bd\u30ca\u30ea\u7a7a\u6e2f"
    ],
    "name:mar_x_preferred":[
        "\u0938\u094b\u0928\u093e\u0930\u0940 \u0935\u093f\u092e\u093e\u0928\u0924\u0933"
    ],
    "name:msa_x_preferred":[
        "Lapangan Terbang Jamshedpur"
    ],
    "name:ron_x_preferred":[
        "Aeroportul Sonari"
    ],
    "name:rus_x_preferred":[
        "\u0410\u0435\u0440\u043e\u043f\u043e\u0440\u0442 \u0421\u043e\u043d\u0430\u0440\u0438"
    ],
    "name:swe_x_preferred":[
        "Jamshedpur"
    ],
    "name:tgk_x_preferred":[
        "\u0424\u0443\u0440\u0443\u0434\u0433\u043e\u04b3\u0438 \u0441\u043e\u043d\u0440\u0438"
    ],
    "oa:elevation_ft":"475",
    "oa:type":"medium_airport",
    "wd:wordcount":349,
    "woe:hierarchy":{
        "country_id":23424848,
        "county_id":12586403,
        "planet_id":1,
        "state_id":20070463
    },
    "wof:name":"Sonari Airport",
    "wof:placetype":"campus"
},
  "geometry": {"coordinates":[86.16805600000001,22.813611],"type":"Point"}
}