{
  "type": "Feature",
  "properties": {
    "wof:name":"Chadstone",
    "wof:placetype":"neighbourhood"
},
  "geometry": {"coordinates":[145.10011164408095,-37.88247701599245],"type":"Point"}
}