{
  "type": "Feature",
  "properties": {
    "name:ara_x_preferred":[
        "\u0642\u0627\u0639\u062f\u0629 \u062b\u0648\u0644 \u0627\u0644\u062c\u0648\u064a\u0629"
    ],
    "name:arm_x_preferred":[
        "\u054f\u0578\u0582\u056c\u0565"
    ],
    "name:ast_x_preferred":[
        "Base a\u00e9rea de Thule"
    ],
    "name:bel_x_variant":[
        "\u0422\u0443\u043b\u044d"
    ],
    "name:chi_x_preferred":[
        "\u56fe\u52d2\u7a7a\u519b\u57fa\u5730"
    ],
    "name:dan_x_preferred":[
        "Thule Air Base"
    ],
    "name:deu_x_preferred":[
        "Thule Air Base"
    ],
    "name:dut_x_preferred":[
        "Thule Air Base"
    ],
    "name:eng_x_preferred":[
        "Thule Air Base"
    ],
    "name:eng_x_variant":[
        "THU",
        "BGTL"
    ],
    "name:epo_x_preferred":[
        "Aerbazo Thule"
    ],
    "name:fas_x_preferred":[
        "\u067e\u0627\u06cc\u06af\u0627\u0647 \u0647\u0648\u0627\u06cc\u06cc \u062b\u0648\u0644"
    ],
    "name:fin_x_preferred":[
        "Thulen lentotukikohta"
    ],
    "name:fra_x_preferred":[
        "Base a\u00e9rienne de Thul\u00e9"
    ],
    "name:fre_x_preferred":[
        "Base a\u00e9rienne de Thul\u00e9"
    ],
    "name:ger_x_preferred":[
        "Thule Air Base"
    ],
    "name:hye_x_preferred":[
        "\u054f\u0578\u0582\u056c\u0565"
    ],
    "name:ice_x_preferred":[
        "Thule-herst\u00f6\u00f0in"
    ],
    "name:isl_x_preferred":[
        "Thule-herst\u00f6\u00f0in"
    ],
    "name:ita_x_preferred":[
        "Base aerea Thule"
    ],
    "name:jpn_x_preferred":[
        "\u30c1\u30e5\u30fc\u30ec\u7a7a\u8ecd\u57fa\u5730"
    ],
    "name:may_x_preferred":[
        "Lapangan Terbang Thule AB"
    ],
    "name:msa_x_preferred":[
        "Lapangan Terbang Thule AB"
    ],
    "name:nld_x_preferred":[
        "Thule Air Base"
    ],
    "name:nob_x_preferred":[
        "Thule Air Base"
    ],
    "name:nor_x_preferred":[
        "Thule Air Base"
    ],
    "name:per_x_preferred":[
        "\u067e\u0627\u06cc\u06af\u0627\u0647 \u0647\u0648\u0627\u06cc\u06cc \u062b\u0648\u0644"
    ],
    "name:por_x_preferred":[
        "Base A\u00e9rea de Thule"
    ],
    "name:rus_x_preferred":[
        "\u0422\u0443\u043b\u0435"
    ],
    "name:spa_x_preferred":[
        "Base a\u00e9rea de Thule"
    ],
    "name:swe_x_preferred":[
        "Thule Air Base"
    ],
    "name:tgk_x_preferred":[
        "\u041f\u043e\u0439\u0433\u043e\u04b3\u0438 \u04b3\u0430\u0432\u043e\u0438\u0438 \u0421\u0443\u043b"
    ],
    "name:tur_x_preferred":[
        "Thule Hava \u00dcss\u00fc"
    ],
    "name:ukr_x_preferred":[
        "\u0422\u0443\u043b\u0435"
    ],
    "name:vie_x_preferred":[
        "C\u0103n c\u1ee9 Kh\u00f4ng qu\u00e2n Thule"
    ],
    "name:zho_x_preferred":[
        "\u56fe\u52d2\u7a7a\u519b\u57fa\u5730"
    ],
    "oa:elevation_ft":"251",
    "oa:type":"medium_airport",
    "wd:wordcount":3410,
    "woe:hierarchy":{
        "country_id":23424828,
        "planet_id":1,
        "state_id":20069857
    },
    "wof:name":"Thule Air Base",
    "wof:placetype":"campus"
},
  "geometry": {"coordinates":[-68.70320100000001,76.53119700000001],"type":"Point"}
}