{
  "type": "Feature",
  "properties": {
    "name:dut_x_preferred":[
        "Camilo Ponce Enr\u00edquez Airport - Ciudad de Catamayo"
    ],
    "name:eng_x_preferred":[
        "Camilo Ponce Enr\u00edquez Airport - Ciudad de Catamayo"
    ],
    "name:eng_x_variant":[
        "LOH",
        "SETM"
    ],
    "name:fre_x_preferred":[
        "a\u00e9roport Camilo Ponce Enr\u00edquez"
    ],
    "name:ger_x_preferred":[
        "Flughafen Catamayo"
    ],
    "name:ita_x_preferred":[
        "Aeroporto Citt\u00e0 di Catamayo"
    ],
    "name:jpn_x_preferred":[
        "\u30ed\u30cf"
    ],
    "name:may_x_preferred":[
        "Lapangan Terbang Camilo Ponce Enriquez"
    ],
    "name:per_x_preferred":[
        "\u0641\u0631\u0648\u062f\u06af\u0627\u0647 \u06a9\u0645\u06cc\u0644\u0648 \u067e\u0627\u0646\u0633 \u0627\u0646\u0631\u06cc\u06a9\u0632"
    ],
    "name:pol_x_preferred":[
        "Port lotniczy Camilo Ponce Enriquez"
    ],
    "name:por_x_preferred":[
        "Aeroporto da Cidade de Catamayo"
    ],
    "name:spa_x_preferred":[
        "Aeropuerto Camilo Ponce Enr\u00edquez - Loja"
    ],
    "name:swe_x_preferred":[
        "Catamayo / Camilo Ponce Enriquez"
    ],
    "name:tgk_x_preferred":[
        "\u0424\u0443\u0440\u0443\u0434\u0433\u043e\u04b3\u0438 \u043a\u043c\u0438\u043b\u0443 \u043f\u043e\u043d\u0441 \u043e\u043d\u0440\u0438\u043a\u0437"
    ],
    "oa:elevation_ft":"4056",
    "oa:type":"small_airport",
    "woe:hierarchy":{
        "country_id":23424801,
        "county_id":26809581,
        "localadmin_id":26810141,
        "planet_id":1,
        "state_id":2345213
    },
    "wof:name":"Loja Airport",
    "wof:placetype":"campus"
},
  "geometry": {"coordinates":[-79.37190200000001,-3.99589],"type":"Point"}
}