{
  "type": "Feature",
  "properties": {
    "name:fas_x_preferred":[
        "\u0641\u0631\u0648\u062f\u06af\u0627\u0647 \u067e\u0627\u062a\u06cc\u0644\u0627"
    ],
    "name:mar_x_preferred":[
        "\u092a\u091f\u093f\u092f\u093e\u0932\u093e \u090f\u0935\u094d\u0939\u093f\u092f\u0947\u0936\u0928 \u0915\u094d\u0932\u092c"
    ],
    "name:tgk_x_preferred":[
        "\u0424\u0443\u0440\u0443\u0434\u0433\u043e\u04b3\u0438 \u043f\u043e\u0442\u0438\u043b\u043e"
    ],
    "oa:elevation_ft":"820",
    "oa:type":"small_airport",
    "wd:wordcount":15,
    "woe:hierarchy":{
        "country_id":23424848,
        "county_id":12586643,
        "planet_id":1,
        "state_id":2345756
    },
    "wof:name":"Patiala Airport",
    "wof:placetype":"campus"
},
  "geometry": {"coordinates":[76.363055555556,30.314722222222],"type":"Point"}
}