{
  "type": "Feature",
  "properties": {
    "gn:admin1_code":"32.0",
    "gn:asciiname":"Otjiu",
    "gn:dem":729,
    "gn:feature_class":"P",
    "gn:feature_code":"PPL",
    "gn:name":"Otjiu",
    "gn:population":0,
    "gn:timezone":"Africa/Windhoek",
    "name:und_x_variant":[
        "Otju",
        "Otjiu"
    ],
    "wof:name":"Otjiu",
    "wof:placetype":"locality"
},
  "geometry": {"coordinates":[13.25,-18.25],"type":"Point"}
}