{
  "type": "Feature",
  "properties": {
    "name:ceb_x_preferred":[
        "Vidja"
    ],
    "name:dan_x_preferred":[
        "Vidja"
    ],
    "name:deu_x_preferred":[
        "Vidja"
    ],
    "name:eng_x_preferred":[
        "Vidja"
    ],
    "name:fra_x_preferred":[
        "Vidja"
    ],
    "name:gle_x_preferred":[
        "Vidja"
    ],
    "name:ita_x_preferred":[
        "Vidja"
    ],
    "name:lld_x_preferred":[
        "Vidja"
    ],
    "name:nan_x_preferred":[
        "Vidja"
    ],
    "name:nds_x_preferred":[
        "Vidja"
    ],
    "name:nld_x_preferred":[
        "Vidja"
    ],
    "name:nno_x_preferred":[
        "Vidja"
    ],
    "name:nob_x_preferred":[
        "Vidja"
    ],
    "name:nor_x_preferred":[
        "Vidja"
    ],
    "name:pol_x_preferred":[
        "Vidja"
    ],
    "name:swe_x_preferred":[
        "Vidja"
    ],
    "name:zho_min_nan_x_preferred":[
        "Vidja"
    ],
    "wd:wordcount":53,
    "wof:name":"Vidja",
    "wof:placetype":"neighbourhood"
},
  "geometry": {"coordinates":[18.061306,59.196529],"type":"Point"}
}