{
  "type": "Feature",
  "properties": {
    "wof:name":"Chapel Hill-Ben Davis",
    "wof:placetype":"neighbourhood"
},
  "geometry": {"coordinates":[-86.2887398784161,39.75874342179083],"type":"Point"}
}