{
  "type": "Feature",
  "properties": {
    "wof:name":"Tipton",
    "wof:placetype":"neighbourhood"
},
  "geometry": {"coordinates":[-2.06960754980404,52.5287490062775],"type":"Point"}
}