{
  "type": "Feature",
  "properties": {
    "gn:admin1_code":"28.0",
    "gn:asciiname":"Linyanti",
    "gn:dem":937,
    "gn:feature_class":"P",
    "gn:feature_code":"PPL",
    "gn:name":"Linyanti",
    "gn:population":0,
    "gn:timezone":"Africa/Windhoek",
    "name:ben_x_preferred":[
        "\u09b2\u09bf\u09a8\u09cd\u09af\u09be\u09a8\u09a4\u09bf"
    ],
    "name:deu_x_preferred":[
        "Linyanti"
    ],
    "name:heb_x_preferred":[
        "\u05dc\u05d9\u05e0\u05d9\u05d0\u05e0\u05d8\u05d9"
    ],
    "name:ind_x_preferred":[
        "Linyanti"
    ],
    "name:kor_x_preferred":[
        "\ub9b0\uc580\ud2f0"
    ],
    "name:nld_x_preferred":[
        "Linyanti"
    ],
    "name:tur_x_preferred":[
        "Linyanti"
    ],
    "name:urd_x_preferred":[
        "\u0644\u06cc\u0646\u06cc\u0627\u0646\u062a\u06cc"
    ],
    "name:vie_x_preferred":[
        "S\u00f4ng Linyanti"
    ],
    "wof:name":"Linyanti",
    "wof:placetype":"locality"
},
  "geometry": {"coordinates":[24.01566,-18.07229],"type":"Point"}
}