{
  "type": "Feature",
  "properties": {
    "gn:admin1_code":"28.0",
    "gn:asciiname":"Linyanti",
    "gn:dem":937,
    "gn:feature_class":"P",
    "gn:feature_code":"PPL",
    "gn:name":"Linyanti",
    "gn:population":0,
    "gn:timezone":"Africa/Windhoek",
    "name:deu_x_preferred":[
        "Linyanti"
    ],
    "name:nld_x_preferred":[
        "Linyanti"
    ],
    "wof:name":"Linyanti",
    "wof:placetype":"locality"
},
  "geometry": {"coordinates":[24.01566,-18.07229],"type":"Point"}
}