{
  "type": "Feature",
  "properties": {
    "wof:name":"Colonial Park",
    "wof:placetype":"neighbourhood"
},
  "geometry": {"coordinates":[-78.88534880251949,36.02479191479447],"type":"Point"}
}