{
  "type": "Feature",
  "properties": {
    "gn:admin1_code":"33.0",
    "gn:asciiname":"Ohangwena",
    "gn:dem":1108,
    "gn:feature_class":"P",
    "gn:feature_code":"PPL",
    "gn:name":"Ohangwena",
    "gn:population":0,
    "gn:timezone":"Africa/Windhoek",
    "wof:name":"Ohangwena",
    "wof:placetype":"locality"
},
  "geometry": {"coordinates":[15.91667,-17.48333],"type":"Point"}
}