{
  "type": "Feature",
  "properties": {
    "gn:admin1_code":"31.0",
    "gn:asciiname":"Sonop",
    "gn:dem":919,
    "gn:feature_class":"P",
    "gn:feature_code":"PPL",
    "gn:name":"Sonop",
    "gn:population":0,
    "gn:timezone":"Africa/Windhoek",
    "name:afr_x_preferred":[
        "Sonop"
    ],
    "name:est_x_preferred":[
        "Sonop"
    ],
    "name:nso_x_preferred":[
        "Sonop"
    ],
    "wof:name":"Sonop",
    "wof:placetype":"locality"
},
  "geometry": {"coordinates":[18.96667,-28.45],"type":"Point"}
}