{
  "type": "Feature",
  "properties": {
    "name:ceb_x_preferred":[
        "Parauapebas Caraj\u00e1s Airport"
    ],
    "name:deu_x_preferred":[
        "Flughafen Caraj\u00e1s"
    ],
    "name:eng_x_preferred":[
        "Caraj\u00e1s Airport"
    ],
    "name:eng_x_variant":[
        "CKS",
        "SBCJ"
    ],
    "name:fas_x_preferred":[
        "\u0641\u0631\u0648\u062f\u06af\u0627\u0647 \u06a9\u0631\u0627\u06cc\u0633"
    ],
    "name:jpn_x_preferred":[
        "\u30ad\u30e3\u30e9\u30b8\u30e3\u30b9\u7a7a\u6e2f"
    ],
    "name:msa_x_preferred":[
        "Lapangan Terbang Carajas"
    ],
    "name:por_x_preferred":[
        "Aeroporto de Caraj\u00e1s"
    ],
    "name:ron_x_preferred":[
        "Aeroportul Caraj\u00e1s"
    ],
    "name:swe_x_preferred":[
        "Parauapebas Caraj\u00e1s Airport"
    ],
    "name:tgk_x_preferred":[
        "\u0424\u0443\u0440\u0443\u0434\u0433\u043e\u04b3\u0438 \u043a\u0440\u043e\u0438\u0441"
    ],
    "name:zho_x_preferred":[
        "\u5361\u62c9\u54c8\u65af\u6a5f\u5834"
    ],
    "oa:elevation_ft":"2064",
    "oa:type":"medium_airport",
    "woe:hierarchy":{
        "country_id":23424768,
        "county_id":12580192,
        "planet_id":1,
        "state_id":2344857
    },
    "wof:name":"Aeroporto Carajas",
    "wof:placetype":"campus"
},
  "geometry": {"coordinates":[-50.001389,-6.115278],"type":"Point"}
}