{
  "type": "Feature",
  "properties": {
    "wd:wordcount":116,
    "wof:name":"Meadowbrook",
    "wof:placetype":"neighbourhood"
},
  "geometry": {"coordinates":[-113.98530199482191,51.27438600733621],"type":"Point"}
}