{
  "type": "Feature",
  "properties": {
    "name:ara_x_preferred":[
        "\u0645\u0637\u0627\u0631 \u0633\u0646\u062f\u0627\u064a"
    ],
    "name:arz_x_preferred":[
        "\u0645\u0637\u0627\u0631 \u0633\u0646\u062f\u0627\u0649"
    ],
    "name:ceb_x_preferred":[
        "Sendai Airport"
    ],
    "name:dan_x_preferred":[
        "Sendai lufthavn"
    ],
    "name:deu_x_preferred":[
        "Flughafen Sendai"
    ],
    "name:eng_x_preferred":[
        "Sendai Airport"
    ],
    "name:eng_x_variant":[
        "SDJ",
        "RJSS"
    ],
    "name:fas_x_preferred":[
        "\u0641\u0631\u0648\u062f\u06af\u0627\u0647 \u0633\u0646\u062f\u0627\u06cc"
    ],
    "name:fra_x_preferred":[
        "a\u00e9roport de Sendai"
    ],
    "name:ind_x_preferred":[
        "Bandar Udara Sendai"
    ],
    "name:ita_x_preferred":[
        "aeroporto di Sendai"
    ],
    "name:jpn_x_preferred":[
        "\u4ed9\u53f0\u7a7a\u6e2f"
    ],
    "name:kor_x_preferred":[
        "\uc13c\ub2e4\uc774 \uacf5\ud56d"
    ],
    "name:msa_x_preferred":[
        "Lapangan Terbang Sendai"
    ],
    "name:nld_x_preferred":[
        "Luchthaven Sendai"
    ],
    "name:pol_x_preferred":[
        "Port lotniczy Sendai"
    ],
    "name:ron_x_preferred":[
        "Aeroportul Sendai"
    ],
    "name:rus_x_preferred":[
        "\u0421\u0435\u043d\u0434\u0430\u0439"
    ],
    "name:spa_x_preferred":[
        "Aeropuerto de Sendai"
    ],
    "name:tgk_x_preferred":[
        "\u0424\u0443\u0440\u0443\u0434\u0433\u043e\u04b3\u0438 \u0441\u043d\u0434"
    ],
    "name:tha_x_preferred":[
        "\u0e17\u0e48\u0e32\u0e2d\u0e32\u0e01\u0e32\u0e28\u0e22\u0e32\u0e19\u0e40\u0e0b\u0e47\u0e19\u0e44\u0e14"
    ],
    "name:tur_x_preferred":[
        "Sendai Havaliman\u0131"
    ],
    "name:ukr_x_preferred":[
        "\u0410\u0435\u0440\u043e\u043f\u043e\u0440\u0442 \u0421\u0435\u043d\u0434\u0430\u0439"
    ],
    "name:vie_x_preferred":[
        "S\u00e2n bay Sendai"
    ],
    "name:yue_x_preferred":[
        "\u4ed9\u53f0\u6a5f\u5834"
    ],
    "name:zho_x_preferred":[
        "\u4ed9\u53f0\u6a5f\u5834"
    ],
    "oa:elevation_ft":"15",
    "oa:type":"medium_airport",
    "woe:hierarchy":{
        "country_id":23424856,
        "planet_id":1,
        "state_id":2345873
    },
    "wof:name":"\u4ed9\u53f0\u7a7a\u6e2f",
    "wof:placetype":"campus"
},
  "geometry": {"coordinates":[140.91700700000001,38.139702],"type":"Point"}
}