{
  "type": "Feature",
  "properties": {
    "name:dan_x_preferred":[
        "Berlev\u00e5g Lufthavn"
    ],
    "name:deu_x_preferred":[
        "Flughafen Berlev\u00e5g"
    ],
    "name:eng_x_preferred":[
        "Berlev\u00e5g Airport"
    ],
    "name:eng_x_variant":[
        "BVG",
        "ENBV"
    ],
    "name:fas_x_preferred":[
        "\u0641\u0631\u0648\u062f\u06af\u0627\u0647 \u0628\u0631\u0644\u0648\u0627\u06af"
    ],
    "name:jpn_x_preferred":[
        "\u30d9\u30eb\u30ec\u30f4\u30a9\u30fc\u30b0\u7a7a\u6e2f"
    ],
    "name:msa_x_preferred":[
        "Lapangan Terbang Berlevag"
    ],
    "name:nld_x_preferred":[
        "Luchthaven Berlev\u00e5g"
    ],
    "name:nno_x_preferred":[
        "Berlev\u00e5g lufthamn"
    ],
    "name:nob_x_preferred":[
        "Berlev\u00e5g lufthavn"
    ],
    "name:nor_x_preferred":[
        "Berlev\u00e5g lufthavn"
    ],
    "name:pol_x_preferred":[
        "Port lotniczy Berlev\u00e5g"
    ],
    "name:rus_x_preferred":[
        "\u0411\u0435\u0440\u043b\u0435\u0432\u043e\u0433"
    ],
    "name:swe_x_preferred":[
        "Berlev\u00e5gs flygplats"
    ],
    "name:tgk_x_preferred":[
        "\u0424\u0443\u0440\u0443\u0434\u0433\u043e\u04b3\u0438 \u0411\u0435\u0440\u043b\u0435\u0432\u043e\u0433"
    ],
    "name:vie_x_preferred":[
        "S\u00e2n bay Berlev\u00e5g"
    ],
    "name:zho_x_preferred":[
        "\u8c9d\u52d2\u6c83\u683c\u6a5f\u5834"
    ],
    "oa:elevation_ft":"42",
    "oa:type":"medium_airport",
    "woe:hierarchy":{
        "country_id":23424910,
        "county_id":12592894,
        "planet_id":1,
        "state_id":2346388
    },
    "wof:name":"Berlev\u00e5g Lufthavn",
    "wof:placetype":"campus"
},
  "geometry": {"coordinates":[29.034201,70.871399],"type":"Point"}
}