{
  "type": "Feature",
  "properties": {
    "wof:name":"Macdonald Ranch",
    "wof:placetype":"neighbourhood"
},
  "geometry": {"coordinates":[-115.07116279337117,35.99970649692374],"type":"Point"}
}