{
  "type": "Feature",
  "properties": {
    "gn:admin1_code":"32.0",
    "gn:asciiname":"Otjikondo",
    "gn:dem":1280,
    "gn:feature_class":"P",
    "gn:feature_code":"PPL",
    "gn:name":"Otjikondo",
    "gn:population":0,
    "gn:timezone":"Africa/Windhoek",
    "name:deu_x_preferred":[
        "Otjikondo"
    ],
    "wof:name":"Otjikondo",
    "wof:placetype":"locality"
},
  "geometry": {"coordinates":[15.46667,-19.85],"type":"Point"}
}