{
  "type": "Feature",
  "properties": {
    "wof:name":"Windsor Square",
    "wof:placetype":"neighbourhood"
},
  "geometry": {"coordinates":[-112.0691095647253,33.5135024958276],"type":"Point"}
}