{
  "type": "Feature",
  "properties": {
    "name:eng_x_preferred":[
        "Fox Park"
    ],
    "name:fra_x_preferred":[
        "Fox Park"
    ],
    "wof:name":"Fox Park",
    "wof:placetype":"neighbourhood"
},
  "geometry": {"coordinates":[-90.22656432728567,38.60885976490032],"type":"Point"}
}