{
  "type": "Feature",
  "properties": {
    "wof:name":"Crooked Creek",
    "wof:placetype":"neighbourhood"
},
  "geometry": {"coordinates":[-78.92651894347394,35.91226825331324],"type":"Point"}
}