{
  "type": "Feature",
  "properties": {
    "name:ceb_x_preferred":[
        "Crooked Creek"
    ],
    "name:deu_x_preferred":[
        "Crooked Creek"
    ],
    "name:fra_x_preferred":[
        "Crooked Creek"
    ],
    "name:pol_x_preferred":[
        "Crooked Creek"
    ],
    "name:srp_x_preferred":[
        "\u041a\u0440\u0443\u043a\u0438\u0434 \u041a\u0440\u0438\u043a"
    ],
    "name:swe_x_preferred":[
        "Crooked Creek"
    ],
    "wof:name":"Crooked Creek",
    "wof:placetype":"neighbourhood"
},
  "geometry": {"coordinates":[-78.92651894347394,35.91226825331324],"type":"Point"}
}