{
  "type": "Feature",
  "properties": {
    "wof:name":"Southwest",
    "wof:placetype":"neighbourhood"
},
  "geometry": {"coordinates":[-87.70345331752235,42.02735796819115],"type":"Point"}
}