{
  "type": "Feature",
  "properties": {
    "name:ara_x_preferred":[
        "\u062c\u0646\u0648\u0628 \u063a\u0631\u0628\u064a"
    ],
    "name:azb_x_preferred":[
        "\u06af\u0648\u0646\u0626\u06cc \u0628\u0627\u062a\u06cc"
    ],
    "name:bjn_x_preferred":[
        "Barat daya"
    ],
    "name:bos_x_preferred":[
        "Jugozapad"
    ],
    "name:bre_x_preferred":[
        "Mervent"
    ],
    "name:bul_x_preferred":[
        "\u042e\u0433\u043e\u0437\u0430\u043f\u0430\u0434"
    ],
    "name:ces_x_preferred":[
        "Jihoz\u00e1pad"
    ],
    "name:ckb_x_preferred":[
        "\u0628\u0627\u0634\u0648\u0648\u0631\u06cc \u0695\u06c6\u0698\u0627\u0648\u0627"
    ],
    "name:deu_x_preferred":[
        "S\u00fcdwest"
    ],
    "name:diq_x_preferred":[
        "Veroc\u00ea rocawani"
    ],
    "name:epo_x_preferred":[
        "Sudokcidento"
    ],
    "name:est_x_preferred":[
        "Edel"
    ],
    "name:eus_x_preferred":[
        "Hego-mendebalde"
    ],
    "name:fin_x_preferred":[
        "Lounas"
    ],
    "name:frr_x_preferred":[
        "S\u00fc\u00fcdwaast"
    ],
    "name:glg_x_preferred":[
        "Suroeste"
    ],
    "name:hrv_x_preferred":[
        "Jugozapad"
    ],
    "name:ina_x_preferred":[
        "Sud-west"
    ],
    "name:jav_x_preferred":[
        "Kidul-Kulon"
    ],
    "name:kor_x_preferred":[
        "\ub0a8\uc11c\ucabd"
    ],
    "name:kur_x_preferred":[
        "Ba\u015f\u00fbr rojava"
    ],
    "name:mkd_x_preferred":[
        "\u0408\u0443\u0433\u043e\u0437\u0430\u043f\u0430\u0434"
    ],
    "name:msa_x_preferred":[
        "Barat daya"
    ],
    "name:myv_x_preferred":[
        "\u0427\u0438\u043a\u0443\u043d\u0448\u043a\u0430"
    ],
    "name:nld_x_preferred":[
        "Zuidwest"
    ],
    "name:nor_x_preferred":[
        "S\u00f8rvest"
    ],
    "name:pam_x_preferred":[
        "Mauli-albugan"
    ],
    "name:pol_x_preferred":[
        "Po\u0142udniowy zach\u00f3d"
    ],
    "name:por_x_preferred":[
        "Sudoeste"
    ],
    "name:srp_x_preferred":[
        "\u0408\u0443\u0433\u043e\u0437\u0430\u043f\u0430\u0434"
    ],
    "name:tcy_x_preferred":[
        "\u0ca8\u0cc8\u0cb0\u0cc1\u0ca4\u0ccd\u0caf\u0cca"
    ],
    "name:tel_x_preferred":[
        "\u0c28\u0c48\u0c0b\u0c24\u0c3f"
    ],
    "name:tur_x_preferred":[
        "G\u00fcneybat\u0131"
    ],
    "name:ukr_x_preferred":[
        "\u041f\u0456\u0432\u0434\u0435\u043d\u043d\u0438\u0439 \u0437\u0430\u0445\u0456\u0434"
    ],
    "name:vep_x_preferred":[
        "Ehtbok"
    ],
    "name:war_x_preferred":[
        "Habagatan"
    ],
    "wof:name":"Southwest",
    "wof:placetype":"neighbourhood"
},
  "geometry": {"coordinates":[-87.70345331752235,42.02735796819115],"type":"Point"}
}