{
  "type": "Feature",
  "properties": {
    "name:ceb_x_preferred":[
        "Porto Amboim Airport"
    ],
    "name:eng_x_preferred":[
        "Porto Amboim Airport"
    ],
    "name:fas_x_preferred":[
        "\u0641\u0631\u0648\u062f\u06af\u0627\u0647 \u067e\u0648\u0631\u062a\u0648 \u0627\u0645\u0628\u0648\u0627\u0645"
    ],
    "name:ind_x_preferred":[
        "Bandar Udara Porto Amboim"
    ],
    "name:jpn_x_preferred":[
        "\u30dd\u30eb\u30c8\u30fb\u30a2\u30f3\u30dc\u30a4\u30e0\u7a7a\u6e2f"
    ],
    "name:msa_x_preferred":[
        "Lapangan Terbang Porto Amboim"
    ],
    "name:ron_x_preferred":[
        "Aeroportul Porto Amboim"
    ],
    "name:swe_x_preferred":[
        "Porto Amboim Airport"
    ],
    "name:tgk_x_preferred":[
        "\u0424\u0443\u0440\u0443\u0434\u0433\u043e\u04b3\u0438 \u043f\u0443\u0440\u0442\u0443 \u043e\u043c\u0431\u0443\u043e\u043c"
    ],
    "oa:elevation_ft":"16",
    "oa:type":"medium_airport",
    "wd:wordcount":66,
    "woe:hierarchy":{
        "country_id":23424745,
        "planet_id":1,
        "state_id":2344661
    },
    "wof:name":"Porto Amboim Airport",
    "wof:placetype":"campus"
},
  "geometry": {"coordinates":[13.765694444444,-10.722027777778],"type":"Point"}
}