{
  "type": "Feature",
  "properties": {
    "name:ceb_x_preferred":[
        "Berkeley County Airport"
    ],
    "name:eng_x_preferred":[
        "Berkeley County Airport"
    ],
    "name:fas_x_preferred":[
        "\u0641\u0631\u0648\u062f\u06af\u0627\u0647 \u0634\u0647\u0631\u0633\u062a\u0627\u0646 \u0628\u0631\u06a9\u0644\u06cc"
    ],
    "name:ron_x_preferred":[
        "Aeroportul Berkeley County"
    ],
    "name:tgk_x_preferred":[
        "\u0424\u0443\u0440\u0443\u0434\u0433\u043e\u04b3\u0438 \u0448\u0430\u04b3\u0440\u0438\u0441\u0442\u043e\u043d \u0431\u0438\u0440\u043a\u0438\u043b\u04e3"
    ],
    "name:urd_x_preferred":[
        "\u0628\u0631\u06a9\u0644\u06d2 \u06a9\u0627\u0624\u0646\u0679\u06cc \u06c1\u0648\u0627\u0626\u06cc \u0627\u0688\u0627"
    ],
    "name:zho_x_preferred":[
        "\u4f2f\u514b\u5229\u53bf\u673a\u573a"
    ],
    "oa:elevation_ft":"73",
    "oa:type":"small_airport",
    "wd:wordcount":289,
    "woe:hierarchy":{
        "country_id":23424977,
        "county_id":12589807,
        "planet_id":1,
        "state_id":2347599
    },
    "wof:name":"Berkeley County Airport",
    "wof:placetype":"campus"
},
  "geometry": {"coordinates":[-80.0361,33.1856],"type":"Point"}
}