{
  "type": "Feature",
  "properties": {
    "gn:admin1_code":"32.0",
    "gn:asciiname":"Otjirova",
    "gn:dem":1047,
    "gn:feature_class":"P",
    "gn:feature_code":"PPL",
    "gn:name":"Otjirova",
    "gn:population":0,
    "gn:timezone":"Africa/Windhoek",
    "wof:name":"Otjirova",
    "wof:placetype":"locality"
},
  "geometry": {"coordinates":[13.25,-17.81667000000001],"type":"Point"}
}