{
  "type": "Feature",
  "properties": {
    "name:ceb_x_preferred":[
        "Morehouse Memorial Airport"
    ],
    "name:eng_x_preferred":[
        "Morehouse Memorial Airport"
    ],
    "name:ron_x_preferred":[
        "Aeroportul Morehouse Memorial"
    ],
    "name:urd_x_preferred":[
        "\u0645\u0648\u0631\u06cc\u06c1\u0627\u0648\u0633 \u0645\u06cc\u0645\u0648\u0631\u06cc\u0644 \u06c1\u0648\u0627\u0626\u06cc \u0627\u0688\u0627"
    ],
    "oa:elevation_ft":"168",
    "oa:type":"small_airport",
    "wd:wordcount":352,
    "woe:hierarchy":{
        "country_id":23424977,
        "county_id":12588629,
        "planet_id":1,
        "state_id":2347577
    },
    "wof:name":"Morehouse Memorial Airport",
    "wof:placetype":"campus"
},
  "geometry": {"coordinates":[-91.8806,32.7561],"type":"Point"}
}