{
  "type": "Feature",
  "properties": {
    "name:eng_x_preferred":[
        "Tingo Mar\u00eda Airport"
    ],
    "name:eng_x_variant":[
        "TGI",
        "SPGM"
    ],
    "name:fas_x_preferred":[
        "\u0641\u0631\u0648\u062f\u06af\u0627\u0647 \u062a\u06cc\u0646\u06af\u0648 \u0645\u0627\u0631\u06cc\u0627"
    ],
    "name:jpn_x_preferred":[
        "\u30c6\u30a3\u30f3\u30b4\u30fb\u30de\u30ea\u30fc\u30a2\u7a7a\u6e2f"
    ],
    "name:msa_x_preferred":[
        "Lapangan Terbang Tingo Maria"
    ],
    "name:pol_x_preferred":[
        "Port lotniczy Tingo Mar\u00eda"
    ],
    "name:que_x_preferred":[
        "Tinku Mariya antanka panpa"
    ],
    "name:spa_x_preferred":[
        "Aeropuerto de Tingo Mar\u00eda"
    ],
    "name:tgk_x_preferred":[
        "\u0424\u0443\u0440\u0443\u0434\u0433\u043e\u04b3\u0438 \u0442\u0438\u043d\u0433\u0443 \u043c\u043e\u0440\u0435\u0451"
    ],
    "name:zho_x_preferred":[
        "\u5ef7\u6208\u746a\u9e97\u4e9e"
    ],
    "oa:elevation_ft":"2010",
    "oa:type":"small_airport",
    "wd:wordcount":99,
    "woe:hierarchy":{
        "country_id":23424977,
        "county_id":12590304,
        "planet_id":1,
        "state_id":2347605
    },
    "wof:name":"Tangier Island Airport",
    "wof:placetype":"campus"
},
  "geometry": {"coordinates":[-75.949997,-9.133],"type":"Point"}
}