{
  "type": "Feature",
  "properties": {
    "gn:admin1_code":"29.0",
    "gn:asciiname":"Omutjenya",
    "gn:dem":1305,
    "gn:feature_class":"P",
    "gn:feature_code":"PPL",
    "gn:name":"Omutjenya",
    "gn:population":0,
    "gn:timezone":"Africa/Windhoek",
    "wof:name":"Omutjenya",
    "wof:placetype":"locality"
},
  "geometry": {"coordinates":[15.63333,-21.05],"type":"Point"}
}