{
  "type": "Feature",
  "properties": {
    "name:eng_x_variant":[
        "RZL"
    ],
    "oa:elevation_ft":"698",
    "oa:type":"small_airport",
    "wd:wordcount":31,
    "woe:hierarchy":{
        "country_id":23424977,
        "county_id":12588216,
        "planet_id":1,
        "state_id":2347573
    },
    "wof:name":"Jasper County Airport",
    "wof:placetype":"campus"
},
  "geometry": {"coordinates":[-87.1825,40.9478],"type":"Point"}
}