{
  "type": "Feature",
  "properties": {
    "wd:wordcount":10153,
    "wof:name":"Jewellery Quarter",
    "wof:placetype":"neighbourhood"
},
  "geometry": {"coordinates":[-1.91039154257018,52.48681674960514],"type":"Point"}
}