{
  "type": "Feature",
  "properties": {
    "gn:admin1_code":"40.0",
    "gn:asciiname":"Mukundu",
    "gn:dem":1126,
    "gn:feature_class":"P",
    "gn:feature_code":"PPL",
    "gn:name":"Mukundu",
    "gn:population":0,
    "gn:timezone":"Africa/Windhoek",
    "wof:name":"Mukundu",
    "wof:placetype":"locality"
},
  "geometry": {"coordinates":[19.55,-17.95],"type":"Point"}
}