{
  "type": "Feature",
  "properties": {
    "gn:admin1_code":"21.0",
    "gn:asciiname":"Binsenheim",
    "gn:dem":1730,
    "gn:feature_class":"P",
    "gn:feature_code":"PPL",
    "gn:name":"Binsenheim",
    "gn:population":0,
    "gn:timezone":"Africa/Windhoek",
    "wof:name":"Binsenheim",
    "wof:placetype":"locality"
},
  "geometry": {"coordinates":[17.38332999999999,-22.78333],"type":"Point"}
}