{
  "type": "Feature",
  "properties": {
    "name:ceb_x_preferred":[
        "Hearne Municipal Airport"
    ],
    "name:eng_x_preferred":[
        "Hearne Municipal Airport"
    ],
    "name:eng_x_variant":[
        "KLHB"
    ],
    "name:fas_x_preferred":[
        "\u0641\u0631\u0648\u062f\u06af\u0627\u0647 \u0634\u0647\u0631\u0633\u062a\u0627\u0646 \u0647\u0627\u0631\u0646"
    ],
    "name:jpn_x_preferred":[
        "Hearne\u5e02\u55b6\u7a7a\u6e2f"
    ],
    "name:ron_x_preferred":[
        "Aeroportul Municipal Hearne"
    ],
    "name:tgk_x_preferred":[
        "\u0424\u0443\u0440\u0443\u0434\u0433\u043e\u04b3\u0438 \u0448\u0430\u04b3\u0440\u0438\u0441\u0442\u043e\u043d \u04b3\u043e\u0440\u043d"
    ],
    "name:urd_x_preferred":[
        "\u06c1\u06cc\u0627\u0631\u0646 \u0645\u06cc\u0648\u0646\u0633\u067e\u0644 \u0627\u06cc\u0626\u0631\u067e\u0648\u0631\u0679"
    ],
    "oa:elevation_ft":"285",
    "oa:type":"small_airport",
    "wd:wordcount":219,
    "woe:hierarchy":{
        "country_id":23424977,
        "county_id":12590204,
        "planet_id":1,
        "state_id":2347602
    },
    "wof:name":"Hearne Municipal Airport",
    "wof:placetype":"campus"
},
  "geometry": {"coordinates":[-96.62222199999999,30.872222],"type":"Point"}
}