{
  "type": "Feature",
  "properties": {
    "name:fas_x_preferred":[
        "\u0641\u0631\u0648\u062f\u06af\u0627\u0647 \u0634\u0647\u0631\u0633\u062a\u0627\u0646 \u0647\u0627\u0631\u0646"
    ],
    "name:tgk_x_preferred":[
        "\u0424\u0443\u0440\u0443\u0434\u0433\u043e\u04b3\u0438 \u0448\u0430\u04b3\u0440\u0438\u0441\u0442\u043e\u043d \u04b3\u043e\u0440\u043d"
    ],
    "oa:elevation_ft":"285",
    "oa:type":"small_airport",
    "wd:wordcount":219,
    "woe:hierarchy":{
        "country_id":23424977,
        "county_id":12590204,
        "planet_id":1,
        "state_id":2347602
    },
    "wof:name":"Hearne Municipal Airport",
    "wof:placetype":"campus"
},
  "geometry": {"coordinates":[-96.62222222222201,30.872222222222],"type":"Point"}
}