{
  "type": "Feature",
  "properties": {
    "gn:admin1_code":"36.0",
    "gn:asciiname":"Oshimanya",
    "gn:dem":1109,
    "gn:feature_class":"P",
    "gn:feature_code":"PPL",
    "gn:name":"Oshimanya",
    "gn:population":0,
    "gn:timezone":"Africa/Windhoek",
    "name:und_x_variant":[
        "Ushimanya",
        "Oshimanya"
    ],
    "wof:name":"Oshimanya",
    "wof:placetype":"locality"
},
  "geometry": {"coordinates":[15.03333,-17.91667],"type":"Point"}
}