{
  "type": "Feature",
  "properties": {
    "oa:elevation_ft":"3337",
    "oa:type":"medium_airport",
    "wd:wordcount":2177,
    "woe:hierarchy":{
        "country_id":23424739,
        "county_id":56000686,
        "planet_id":1,
        "state_id":2344569
    },
    "wof:name":"Kandahar International Airport",
    "wof:placetype":"campus"
},
  "geometry": {"coordinates":[65.850277777778,31.507222222222],"type":"Point"}
}