{
  "type": "Feature",
  "properties": {
    "name:ara_x_preferred":[
        "\u0645\u0637\u0627\u0631 \u0642\u0646\u062f\u0647\u0627\u0631 \u0627\u0644\u062f\u0648\u0644\u064a"
    ],
    "name:deu_x_preferred":[
        "Flughafen Kandahar"
    ],
    "name:eng_x_variant":[
        "KDH",
        "OAKN"
    ],
    "name:fas_x_preferred":[
        "\u0645\u06cc\u062f\u0627\u0646 \u0647\u0648\u0627\u06cc\u06cc \u0628\u06cc\u0646\u200c\u0627\u0644\u0645\u0644\u0644\u06cc \u0642\u0646\u062f\u0647\u0627\u0631"
    ],
    "name:fin_x_preferred":[
        "Kandaharin kansainv\u00e4linen lentoasema"
    ],
    "name:hin_x_preferred":[
        "\u0915\u093e\u0902\u0927\u093e\u0930 \u0905\u0928\u094d\u0924\u0930\u094d\u0930\u093e\u0937\u094d\u091f\u094d\u0930\u0940\u092f \u0935\u093f\u092e\u093e\u0928\u0915\u094d\u0937\u0947\u0924\u094d\u0930"
    ],
    "name:ind_x_preferred":[
        "Bandar Udara Kandahar"
    ],
    "name:jpn_x_preferred":[
        "\u30ab\u30f3\u30c0\u30cf\u30fc\u30eb\u56fd\u969b\u7a7a\u6e2f"
    ],
    "name:kor_x_preferred":[
        "\uce78\ub2e4\ud558\ub974 \uad6d\uc81c\uacf5\ud56d"
    ],
    "name:mar_x_preferred":[
        "\u0915\u0902\u0926\u0939\u093e\u0930 \u0906\u0902\u0924\u0930\u0930\u093e\u0937\u094d\u091f\u094d\u0930\u0940\u092f \u0935\u093f\u092e\u093e\u0928\u0924\u0933"
    ],
    "name:msa_x_preferred":[
        "Lapangan Terbang Kandahar"
    ],
    "name:nob_x_preferred":[
        "Kandahar internasjonale lufthavn"
    ],
    "name:pol_x_preferred":[
        "Port lotniczy Kandahar"
    ],
    "name:pus_x_preferred":[
        "\u062f \u06a9\u0646\u062f\u0647\u0627\u0631 \u0646\u0693\u064a\u0648\u0627\u0644 \u0647\u0648\u0627\u064a\u064a \u0689\u06ab\u0631"
    ],
    "name:ron_x_preferred":[
        "Aeroportul Interna\u021bional Kandahar"
    ],
    "name:rus_x_preferred":[
        "\u041a\u0430\u043d\u0434\u0430\u0433\u0430\u0440"
    ],
    "name:tur_x_preferred":[
        "Kandehar Uluslararas\u0131 Havaliman\u0131"
    ],
    "name:zho_x_preferred":[
        "\u574e\u5927\u54c8\u56fd\u9645\u673a\u573a"
    ],
    "oa:elevation_ft":"3337",
    "oa:type":"medium_airport",
    "wd:wordcount":2177,
    "woe:hierarchy":{
        "country_id":23424739,
        "county_id":56000686,
        "planet_id":1,
        "state_id":2344569
    },
    "wof:name":"Kandahar International Airport",
    "wof:placetype":"campus"
},
  "geometry": {"coordinates":[65.850278,31.507222],"type":"Point"}
}