{
  "type": "Feature",
  "properties": {
    "wof:name":"Westgate",
    "wof:placetype":"neighbourhood"
},
  "geometry": {"coordinates":[-96.03289663627228,41.22582422010222],"type":"Point"}
}