{
  "type": "Feature",
  "properties": {
    "name:deu_x_preferred":[
        "Westgate"
    ],
    "name:fra_x_preferred":[
        "Westgate"
    ],
    "name:ita_x_preferred":[
        "Westgate"
    ],
    "name:kor_x_preferred":[
        "\uc6e8\uc2a4\ud2b8\uac8c\uc774\ud2b8"
    ],
    "name:nld_x_preferred":[
        "Westgate"
    ],
    "name:pol_x_preferred":[
        "Westgate"
    ],
    "name:por_x_preferred":[
        "Westgate"
    ],
    "name:srp_x_preferred":[
        "\u0412\u0435\u0441\u0442\u0433\u0435\u0458\u0442"
    ],
    "name:swe_x_preferred":[
        "Westgate"
    ],
    "wof:name":"Westgate",
    "wof:placetype":"neighbourhood"
},
  "geometry": {"coordinates":[-96.03289663627228,41.22582422010222],"type":"Point"}
}