{
  "type": "Feature",
  "properties": {
    "wd:wordcount":7396,
    "wof:name":"Cathedral",
    "wof:placetype":"neighbourhood"
},
  "geometry": {"coordinates":[-4.23743844083498,55.86270118910971],"type":"Point"}
}