{
  "type": "Feature",
  "properties": {
    "name:deu_x_preferred":[
        "Milit\u00e4rflugplatz Deelen"
    ],
    "name:eng_x_preferred":[
        "Deelen Air Base"
    ],
    "name:eng_x_variant":[
        "QAR",
        "EHDL"
    ],
    "name:fas_x_preferred":[
        "\u067e\u0627\u06cc\u06af\u0627\u0647 \u0647\u0648\u0627\u06cc\u06cc \u062f\u06cc\u0644\u0646"
    ],
    "name:jpn_x_preferred":[
        "\u30c7\u30a3\u30a8\u30e9\u30f3\u7a7a\u8ecd\u57fa\u5730"
    ],
    "name:msa_x_preferred":[
        "Lapangan Terbang Deelen AB"
    ],
    "name:nld_x_preferred":[
        "Vliegbasis Deelen"
    ],
    "name:pol_x_preferred":[
        "Port lotniczy Arnhem-Deelen"
    ],
    "name:zho_x_preferred":[
        "\u8fea\u502b\u6a5f\u5834"
    ],
    "oa:elevation_ft":"158",
    "oa:type":"medium_airport",
    "woe:hierarchy":{
        "country_id":23424909,
        "county_id":12592044,
        "planet_id":1,
        "state_id":2346375
    },
    "wof:name":"Deelen Airport",
    "wof:placetype":"campus"
},
  "geometry": {"coordinates":[5.87306,52.0606],"type":"Point"}
}