{
  "type": "Feature",
  "properties": {
    "gn:admin1_code":"21.0",
    "gn:asciiname":"Picadilly",
    "gn:dem":1174,
    "gn:feature_class":"P",
    "gn:feature_code":"PPL",
    "gn:name":"Picadilly",
    "gn:population":0,
    "gn:timezone":"Africa/Windhoek",
    "wof:name":"Picadilly",
    "wof:placetype":"locality"
},
  "geometry": {"coordinates":[16.13332999999999,-23.35],"type":"Point"}
}