{
  "type": "Feature",
  "properties": {
    "name:eng_x_preferred":[
        "Dorado Airport"
    ],
    "name:eng_x_variant":[
        "DDP",
        "PR-DDP"
    ],
    "name:fas_x_preferred":[
        "\u0641\u0631\u0648\u062f\u06af\u0627\u0647 \u062f\u0648\u0631\u06cc\u062f\u0648"
    ],
    "name:fas_x_variant":[
        "\u0641\u0631\u0648\u062f\u06af\u0627\u0647 \u062f\u0648\u0627\u062f\u0631\u0648"
    ],
    "name:pol_x_preferred":[
        "Port lotniczy Dorado"
    ],
    "name:spa_x_preferred":[
        "Aeropuerto de Dorado"
    ],
    "name:tgk_x_preferred":[
        "\u0424\u0443\u0440\u0443\u0434\u0433\u043e\u04b3\u0438 \u0434\u0443\u043e\u0434\u0440\u0443"
    ],
    "oa:elevation_ft":"75",
    "oa:type":"closed",
    "wd:wordcount":236,
    "woe:hierarchy":{
        "country_id":23424935,
        "county_id":26806257,
        "planet_id":1,
        "state_id":2346861
    },
    "wof:name":"Dorado Airport",
    "wof:placetype":"campus"
},
  "geometry": {"coordinates":[-66.295581,18.464966],"type":"Point"}
}