{
  "type": "Feature",
  "properties": {
    "name:deu_x_preferred":[
        "Flughafen Juliaca"
    ],
    "name:eng_x_preferred":[
        "Inca Manco C\u00e1pac International Airport"
    ],
    "name:eng_x_variant":[
        "JUL",
        "SPJL"
    ],
    "name:fas_x_preferred":[
        "\u0641\u0631\u0648\u062f\u06af\u0627\u0647 \u0628\u06cc\u0646\u200c\u0627\u0644\u0645\u0644\u0644\u06cc \u0627\u06cc\u0646\u06a9\u0627 \u0645\u0627\u0646\u06a9\u0648 \u06a9\u0627\u067e\u0627\u06a9"
    ],
    "name:fra_x_preferred":[
        "a\u00e9roport international Inca Manco C\u00e1pac"
    ],
    "name:jpn_x_preferred":[
        "\u30a4\u30f3\u30ab\u30fb\u30de\u30f3\u30b3\u30fb\u30ab\u30d1\u30c3\u30af\u56fd\u969b\u7a7a\u6e2f"
    ],
    "name:msa_x_preferred":[
        "Lapangan Terbang Antarabangsa Manco Capac"
    ],
    "name:pol_x_preferred":[
        "Port lotniczy Juliaca-Inca Manco Capac"
    ],
    "name:por_x_preferred":[
        "Aeroporto Internacional Inca Manco C\u00e1pac"
    ],
    "name:que_x_preferred":[
        "Inka Manqu Qhapaq antanka pampa"
    ],
    "name:spa_x_preferred":[
        "Aeropuerto Internacional Inca Manco C\u00e1pac"
    ],
    "name:tgk_x_preferred":[
        "\u0424\u0443\u0440\u0443\u0434\u0433\u043e\u04b3\u0438 \u0431\u0438\u043d\u200c\u0430\u043b\u043c\u0438\u043b\u0430\u043b\u04e3 \u043e\u0438\u043d\u043a\u043e \u043c\u043e\u043d\u043a\u0443 \u043a\u043e\u043f\u043e\u043a"
    ],
    "name:vie_x_preferred":[
        "S\u00e2n bay qu\u1ed1c t\u1ebf Inca Manco Capac"
    ],
    "name:zho_x_preferred":[
        "\u80e1\u5229\u4e9e\u5361"
    ],
    "oa:elevation_ft":"12552",
    "oa:type":"medium_airport",
    "woe:hierarchy":{
        "country_id":23424919,
        "county_id":26805931,
        "planet_id":1,
        "state_id":2346488
    },
    "wof:name":"Juliaca Airport",
    "wof:placetype":"campus"
},
  "geometry": {"coordinates":[-70.158203,-15.4671],"type":"Point"}
}