{
  "type": "Feature",
  "properties": {
    "gn:admin1_code":"31.0",
    "gn:asciiname":"Van Zylsrus",
    "gn:dem":857,
    "gn:feature_class":"P",
    "gn:feature_code":"PPL",
    "gn:name":"Van Zylsrus",
    "gn:population":0,
    "gn:timezone":"Africa/Windhoek",
    "name:afr_x_preferred":[
        "Van Zylsrus"
    ],
    "name:ara_x_preferred":[
        "\u0641\u0627\u0646 \u0632\u064a\u0644\u0633\u0631\u0648\u0633"
    ],
    "name:est_x_preferred":[
        "Van Zylsrus"
    ],
    "name:fas_x_preferred":[
        "\u0648\u0627\u0646 \u0632\u06cc\u0644\u0633\u0631\u0648\u0633"
    ],
    "name:nld_x_preferred":[
        "Van Zylsrus"
    ],
    "name:nso_x_preferred":[
        "Van Zylsrus"
    ],
    "wof:name":"Van Zylsrus",
    "wof:placetype":"locality"
},
  "geometry": {"coordinates":[18.98333,-28.35],"type":"Point"}
}