{
  "type": "Feature",
  "properties": {
    "gn:admin1_code":"31.0",
    "gn:asciiname":"La Gratia",
    "gn:dem":829,
    "gn:feature_class":"P",
    "gn:feature_code":"PPL",
    "gn:name":"La Gratia",
    "gn:population":0,
    "gn:timezone":"Africa/Windhoek",
    "wof:name":"La Gratia",
    "wof:placetype":"locality"
},
  "geometry": {"coordinates":[18.91667,-28.33333],"type":"Point"}
}