{
  "type": "Feature",
  "properties": {
    "gn:admin1_code":"35.0",
    "gn:asciiname":"Erindinoukambe",
    "gn:dem":1436,
    "gn:feature_class":"P",
    "gn:feature_code":"PPL",
    "gn:name":"Erindinoukambe",
    "gn:population":0,
    "gn:timezone":"Africa/Windhoek",
    "wof:name":"Erindinoukambe",
    "wof:placetype":"locality"
},
  "geometry": {"coordinates":[19.11667000000001,-21.11667000000001],"type":"Point"}
}