{
  "type": "Feature",
  "properties": {
    "name:ceb_x_preferred":[
        "Wels Airport"
    ],
    "name:deu_x_preferred":[
        "Flugplatz Wels"
    ],
    "name:eng_x_preferred":[
        "Wels Airport"
    ],
    "name:eng_x_variant":[
        "LOLW"
    ],
    "name:fas_x_preferred":[
        "\u0641\u0631\u0648\u062f\u06af\u0627\u0647 \u0648\u0644\u0633"
    ],
    "name:fas_x_variant":[
        "\u0641\u0631\u0648\u062f\u06af\u0627\u0647 \u0648\u0644\u0632"
    ],
    "name:hun_x_preferred":[
        "Wels rep\u00fcl\u0151t\u00e9r"
    ],
    "name:jpn_x_preferred":[
        "\u30f4\u30a7\u30eb\u30b9\u7a7a\u6e2f"
    ],
    "name:msa_x_preferred":[
        "Lapangan Terbang Wels"
    ],
    "name:pol_x_preferred":[
        "Lotnisko Wels"
    ],
    "name:ron_x_preferred":[
        "Aeroportul Wels"
    ],
    "name:swe_x_preferred":[
        "Flugplatz Wels"
    ],
    "name:swe_x_variant":[
        "Wels Airport"
    ],
    "name:tgk_x_preferred":[
        "\u0424\u0443\u0440\u0443\u0434\u0433\u043e\u04b3\u0438 \u0432\u0438\u043b\u0437"
    ],
    "oa:elevation_ft":"1043",
    "oa:type":"small_airport",
    "wd:wordcount":97,
    "woe:hierarchy":{
        "country_id":23424750,
        "county_id":12591720,
        "localadmin_id":12674344,
        "planet_id":1,
        "state_id":2344711
    },
    "wof:name":"Wels Airport",
    "wof:placetype":"campus"
},
  "geometry": {"coordinates":[14.040833,48.183056],"type":"Point"}
}