{
  "type": "Feature",
  "properties": {
    "gn:admin1_code":"28.0",
    "gn:asciiname":"Malimina",
    "gn:dem":937,
    "gn:feature_class":"P",
    "gn:feature_code":"PPL",
    "gn:name":"Malimina",
    "gn:population":0,
    "gn:timezone":"Africa/Windhoek",
    "wof:name":"Malimina",
    "wof:placetype":"locality"
},
  "geometry": {"coordinates":[24.68333,-17.75],"type":"Point"}
}