{
  "type": "Feature",
  "properties": {
    "name:chi_x_preferred":[
        "Biangabip\u6a5f\u5834"
    ],
    "name:eng_x_preferred":[
        "Biangabip Airport"
    ],
    "name:eng_x_variant":[
        "BPK",
        "PG-0022"
    ],
    "name:fas_x_preferred":[
        "\u0641\u0631\u0648\u062f\u06af\u0627\u0647 \u0645\u0646\u0637\u0642\u0647\u200c\u0627\u06cc \u0627\u0648\u0632\u0627\u0631\u06a9"
    ],
    "name:tgk_x_preferred":[
        "\u0424\u0443\u0440\u0443\u0434\u0433\u043e\u04b3\u0438 \u043c\u0430\u043d\u0442\u0430\u049b\u0430\u200c\u0438\u0439 \u043e\u0432\u0437\u043e\u0440\u043a"
    ],
    "oa:elevation_ft":"1069",
    "oa:type":"small_airport",
    "wd:wordcount":410,
    "woe:hierarchy":{
        "country_id":23424977,
        "county_id":12587597,
        "planet_id":1,
        "state_id":2347562
    },
    "wof:name":"Ozark Regional Airport",
    "wof:placetype":"campus"
},
  "geometry": {"coordinates":[141.74458300000001,-5.526389],"type":"Point"}
}