{
  "type": "Feature",
  "properties": {
    "name:ara_x_preferred":[
        "\u0645\u0637\u0627\u0631 \u0628\u0627\u0631\u0627"
    ],
    "name:ben_x_preferred":[
        "\u09ac\u09cd\u09af\u09be\u09b0\u09be \u09ac\u09bf\u09ae\u09be\u09a8\u09ac\u09a8\u09cd\u09a6\u09b0"
    ],
    "name:ceb_x_preferred":[
        "Barra North Bay Airport"
    ],
    "name:ces_x_preferred":[
        "Leti\u0161t\u011b Barra"
    ],
    "name:deu_x_preferred":[
        "Barra Airport"
    ],
    "name:eng_x_preferred":[
        "Barra Airport"
    ],
    "name:eng_x_variant":[
        "BRR",
        "EGPR"
    ],
    "name:fas_x_preferred":[
        "\u0641\u0631\u0648\u062f\u06af\u0627\u0647 \u0627\u0633\u06a9\u0627\u062a\u0644\u0646\u062f\u060c \u0628\u0627\u0631\u0627"
    ],
    "name:fas_x_variant":[
        "\u0641\u0631\u0648\u062f\u06af\u0627\u0647 \u0627\u0633\u06a9\u0627\u062a\u0644\u0646\u062f"
    ],
    "name:fin_x_preferred":[
        "Barran lentoasema"
    ],
    "name:fra_x_preferred":[
        "a\u00e9roport de Barra"
    ],
    "name:gla_x_preferred":[
        "Port-adhair Bharraigh"
    ],
    "name:ind_x_preferred":[
        "Bandar Udara Barra"
    ],
    "name:ita_x_preferred":[
        "Aeroporto di Barra"
    ],
    "name:jpn_x_preferred":[
        "\u30d0\u30e9\u7a7a\u6e2f"
    ],
    "name:kor_x_preferred":[
        "\ubc14\ub77c \uacf5\ud56d"
    ],
    "name:msa_x_preferred":[
        "Lapangan Terbang Barra"
    ],
    "name:nld_x_preferred":[
        "Barra Airport"
    ],
    "name:pms_x_preferred":[
        "Barra Airport"
    ],
    "name:pol_x_preferred":[
        "Port lotniczy Barra"
    ],
    "name:por_x_preferred":[
        "Aeroporto de Barra"
    ],
    "name:ron_x_preferred":[
        "Aeroportul Barra"
    ],
    "name:rus_x_preferred":[
        "\u0411\u0430\u0440\u0440\u0430"
    ],
    "name:spa_x_preferred":[
        "Aeropuerto de Barra"
    ],
    "name:swe_x_preferred":[
        "Barra Airport"
    ],
    "name:tgk_x_preferred":[
        "\u0424\u0443\u0440\u0443\u0434\u0433\u043e\u04b3\u0438 \u0438\u0441\u043a\u043e\u0442\u043b\u0430\u043d\u0434"
    ],
    "name:tur_x_preferred":[
        "Barra Havaliman\u0131"
    ],
    "name:ukr_x_preferred":[
        "\u0411\u0430\u0440\u0440\u0430"
    ],
    "name:vie_x_preferred":[
        "S\u00e2n bay Barra"
    ],
    "name:zho_x_preferred":[
        "\u5df4\u62c9\u6a5f\u5834"
    ],
    "oa:elevation_ft":"5",
    "oa:type":"medium_airport",
    "woe:hierarchy":{
        "country_id":23424975,
        "county_id":12602210,
        "localadmin_id":12696213,
        "planet_id":1,
        "state_id":12578048
    },
    "wof:name":"North Bay Airport",
    "wof:placetype":"campus"
},
  "geometry": {"coordinates":[-7.44306,57.0228],"type":"Point"}
}