{
  "type": "Feature",
  "properties": {
    "name:afr_x_preferred":[
        "Cyrildene"
    ],
    "name:eng_x_preferred":[
        "Cyrildene"
    ],
    "name:nld_x_preferred":[
        "Cyrildene"
    ],
    "wd:wordcount":156,
    "wof:name":"Cyrildene",
    "wof:placetype":"neighbourhood"
},
  "geometry": {"coordinates":[28.10328991021739,-26.17351733754241],"type":"Point"}
}