{
  "type": "Feature",
  "properties": {
    "name:afr_x_preferred":[
        "Khayelitsha"
    ],
    "name:ara_x_preferred":[
        "\u0643\u0627\u064a\u0644\u064a\u062a\u0634\u0627"
    ],
    "name:azb_x_preferred":[
        "\u06a9\u0627\u06cc\u0644\u06cc\u062a\u0634\u0627"
    ],
    "name:deu_x_preferred":[
        "Khayelitsha"
    ],
    "name:eng_x_preferred":[
        "Khayelitsha"
    ],
    "name:epo_x_preferred":[
        "Kajeli\u0109a"
    ],
    "name:fas_x_preferred":[
        "\u06a9\u0627\u06cc\u0644\u06cc\u062a\u0634\u0627"
    ],
    "name:fra_x_preferred":[
        "Khayelitsha"
    ],
    "name:ita_x_preferred":[
        "Khayelitsha"
    ],
    "name:jpn_x_preferred":[
        "\u30ab\u30e4\u30ea\u30b7\u30e3"
    ],
    "name:jpn_x_variant":[
        "\u30ab\u30a8\u30ea\u30c1\u30e3"
    ],
    "name:kor_x_preferred":[
        "\uce74\uc610\ub9ac\ucc28"
    ],
    "name:nld_x_preferred":[
        "Khayelitsha"
    ],
    "name:nob_x_preferred":[
        "Khayelitsha"
    ],
    "name:nso_x_preferred":[
        "Khayelitsha"
    ],
    "name:ron_x_preferred":[
        "Khayelitsha"
    ],
    "name:spa_x_preferred":[
        "Khayelitsha"
    ],
    "name:swe_x_preferred":[
        "Khayelitsha"
    ],
    "name:war_x_preferred":[
        "Khayelitsa"
    ],
    "name:xho_x_preferred":[
        "Khayelitsha"
    ],
    "name:zho_x_preferred":[
        "\u5361\u96c5\u5229\u6c99"
    ],
    "name:zul_x_preferred":[
        "Khayelitsha"
    ],
    "wd:wordcount":2875,
    "wof:name":"Khayelitsha",
    "wof:placetype":"neighbourhood"
},
  "geometry": {"coordinates":[18.670186,-34.041141],"type":"Point"}
}