{
  "type": "Feature",
  "properties": {
    "wd:wordcount":2875,
    "wof:name":"Khayelitsha",
    "wof:placetype":"neighbourhood"
},
  "geometry": {"coordinates":[18.67018644078152,-34.04114133843799],"type":"Point"}
}