{
  "type": "Feature",
  "properties": {
    "name:dan_x_preferred":[
        "Vard\u00f8 Lufthavn"
    ],
    "name:deu_x_preferred":[
        "Flughafen Vard\u00f8"
    ],
    "name:eng_x_preferred":[
        "Vard\u00f8 Airport"
    ],
    "name:eng_x_variant":[
        "VAW",
        "ENSS"
    ],
    "name:fas_x_preferred":[
        "\u0641\u0631\u0648\u062f\u06af\u0627\u0647 \u0633\u0648\u0627\u0631\u062a\u0646\u0633 \u0648\u0627\u0631\u062f\u0648"
    ],
    "name:fin_x_preferred":[
        "Vuoreijan lentoasema"
    ],
    "name:jpn_x_preferred":[
        "\u30f4\u30a1\u30fc\u30c9\u30fc\u7a7a\u6e2f"
    ],
    "name:msa_x_preferred":[
        "Lapangan Terbang Svartnes"
    ],
    "name:nld_x_preferred":[
        "Luchthaven Vard\u00f8 Svartnes"
    ],
    "name:nno_x_preferred":[
        "Vard\u00f8 lufthamn"
    ],
    "name:nob_x_preferred":[
        "Vard\u00f8 lufthavn"
    ],
    "name:nor_x_preferred":[
        "Vard\u00f8 lufthavn"
    ],
    "name:pol_x_preferred":[
        "Port lotniczy Vard\u00f8"
    ],
    "name:spa_x_preferred":[
        "Aeropuerto de Vard\u00f8-Svartnes"
    ],
    "name:swe_x_preferred":[
        "Vard\u00f8 flygplats"
    ],
    "name:tgk_x_preferred":[
        "\u0424\u0443\u0440\u0443\u0434\u0433\u043e\u04b3\u0438 \u0441\u0443\u043e\u0440\u0442\u043d\u0441 \u0432\u043e\u0440\u0434\u0443"
    ],
    "name:vie_x_preferred":[
        "S\u00e2n bay Vard\u00f8"
    ],
    "oa:elevation_ft":"42",
    "oa:type":"medium_airport",
    "wd:wordcount":1158,
    "woe:hierarchy":{
        "country_id":23424910,
        "county_id":12592985,
        "planet_id":1,
        "state_id":2346388
    },
    "wof:name":"Vard\u00f8 lufthavn Svartnes",
    "wof:placetype":"campus"
},
  "geometry": {"coordinates":[31.044901,70.3554],"type":"Point"}
}