{
  "type": "Feature",
  "properties": {
    "name:fas_x_preferred":[
        "\u0641\u0631\u0648\u062f\u06af\u0627\u0647 \u0645\u062d\u0644\u06cc \u0627\u0633\u06a9\u062c\u062a"
    ],
    "name:tgk_x_preferred":[
        "\u0424\u0443\u0440\u0443\u0434\u0433\u043e\u04b3\u0438 \u043c\u0430\u04b3\u0430\u043b \u043e\u0441\u043a\u04b7\u0442"
    ],
    "oa:elevation_ft":"144",
    "oa:type":"small_airport",
    "wd:wordcount":308,
    "woe:hierarchy":{
        "country_id":23424977,
        "county_id":12590468,
        "planet_id":1,
        "state_id":2347606
    },
    "wof:name":"Skagit Regional Bayview Airport",
    "wof:placetype":"campus"
},
  "geometry": {"coordinates":[-122.42100000000001,48.4708],"type":"Point"}
}