{
  "type": "Feature",
  "properties": {
    "name:cat_x_preferred":[
        "Sutton Coldfield"
    ],
    "name:ceb_x_preferred":[
        "Sutton Coldfield"
    ],
    "name:cym_x_preferred":[
        "Sutton Coldfield"
    ],
    "name:dan_x_preferred":[
        "Sutton Coldfield"
    ],
    "name:deu_x_preferred":[
        "Sutton Coldfield"
    ],
    "name:epo_x_preferred":[
        "Sutton Coldfield"
    ],
    "name:fas_x_preferred":[
        "\u0633\u0627\u062a\u0646 \u06a9\u0648\u0644\u062f\u0641\u06cc\u0644\u062f"
    ],
    "name:fin_x_preferred":[
        "Sutton Coldfield"
    ],
    "name:fra_x_preferred":[
        "Sutton Coldfield"
    ],
    "name:hbs_x_preferred":[
        "Sutton Coldfield"
    ],
    "name:ita_x_preferred":[
        "Sutton Coldfield"
    ],
    "name:jpn_x_preferred":[
        "\u30b5\u30c3\u30c8\u30f3\u30fb\u30b3\u30fc\u30eb\u30c9\u30d5\u30a3\u30fc\u30eb\u30c9"
    ],
    "name:kor_x_preferred":[
        "\uc11c\ud134\ucf5c\ub4dc\ud544\ub4dc"
    ],
    "name:lit_x_preferred":[
        "Saton Koldfildas"
    ],
    "name:nld_x_preferred":[
        "Sutton Coldfield"
    ],
    "name:nno_x_preferred":[
        "Sutton Coldfield"
    ],
    "name:pol_x_preferred":[
        "Sutton Coldfield"
    ],
    "name:ron_x_preferred":[
        "Sutton Coldfield"
    ],
    "name:spa_x_preferred":[
        "Sutton Coldfield"
    ],
    "name:srp_x_preferred":[
        "\u0421\u0430\u0442\u043e\u043d \u041a\u043e\u043b\u0434\u0444\u0438\u043b\u0434"
    ],
    "name:swe_x_preferred":[
        "Sutton Coldfield"
    ],
    "name:war_x_preferred":[
        "Sutton Coldfield"
    ],
    "wd:wordcount":11953,
    "wof:name":"Sutton Coldfield",
    "wof:placetype":"neighbourhood"
},
  "geometry": {"coordinates":[-1.82710712261371,52.5645199666056],"type":"Point"}
}