{
  "type": "Feature",
  "properties": {
    "name:ara_x_preferred":[
        "\u0645\u0637\u0627\u0631 \u0643\u0648\u064a\u062a\u0647 \u0627\u0644\u062f\u0648\u0644\u064a"
    ],
    "name:chi_x_preferred":[
        "\u594e\u8fbe\u56fd\u9645\u673a\u573a"
    ],
    "name:eng_x_preferred":[
        "Quetta International Airport"
    ],
    "name:eng_x_variant":[
        "UET",
        "OPQT"
    ],
    "name:fre_x_preferred":[
        "a\u00e9roport international de Quetta"
    ],
    "name:ind_x_preferred":[
        "Bandar Udara Internasional Quetta"
    ],
    "name:ita_x_preferred":[
        "aeroporto internazionale di Quetta"
    ],
    "name:jpn_x_preferred":[
        "\u30af\u30a8\u30c3\u30bf\u56fd\u969b\u7a7a\u6e2f"
    ],
    "name:kor_x_preferred":[
        "\ud018\ud0c0 \uad6d\uc81c\uacf5\ud56d"
    ],
    "name:may_x_preferred":[
        "Lapangan Terbang Samungli"
    ],
    "name:per_x_preferred":[
        "\u0641\u0631\u0648\u062f\u06af\u0627\u0647 \u0628\u06cc\u0646\u200c\u0627\u0644\u0645\u0644\u0644\u06cc \u06a9\u0648\u06cc\u062a\u0647"
    ],
    "name:pnb_x_preferred":[
        "\u06a9\u0648\u0626\u0679\u06c1 \u0627\u0646\u0679\u0631\u0646\u06cc\u0634\u0646\u0644 \u0627\u06cc\u0626\u0631 \u067e\u0648\u0631\u0679"
    ],
    "name:pol_x_preferred":[
        "Port lotniczy Kweta"
    ],
    "name:rus_x_preferred":[
        "\u041a\u0432\u0435\u0442\u0442\u0430"
    ],
    "name:spa_x_preferred":[
        "Aeropuerto Internacional de Quetta"
    ],
    "name:tgk_x_preferred":[
        "\u0424\u0443\u0440\u0443\u0434\u0433\u043e\u04b3\u0438 \u0431\u0438\u043d\u200c\u0430\u043b\u043c\u0438\u043b\u0430\u043b\u04e3 \u043a\u0443\u0438\u0442\u04b3"
    ],
    "name:urd_x_preferred":[
        "\u06a9\u0648\u0626\u0679\u06c1 \u0628\u06cc\u0646 \u0627\u0644\u0627\u0642\u0648\u0627\u0645\u06cc \u06c1\u0648\u0627\u0626\u06cc \u0627\u0688\u0627"
    ],
    "name:vie_x_preferred":[
        "S\u00e2n bay qu\u1ed1c t\u1ebf Quetta"
    ],
    "oa:elevation_ft":"5267",
    "oa:type":"medium_airport",
    "woe:hierarchy":{
        "country_id":23424922,
        "planet_id":1,
        "state_id":2346496
    },
    "wof:name":"Quetta Airport",
    "wof:placetype":"campus"
},
  "geometry": {"coordinates":[66.937798,30.2514],"type":"Point"}
}