{
  "type": "Feature",
  "properties": {
    "name:ara_x_preferred":[
        "\u0645\u0637\u0627\u0631 \u0633\u0631\u064a\u0646\u063a\u0631"
    ],
    "name:ben_x_preferred":[
        "\u09b6\u09cd\u09b0\u09c0\u09a8\u0997\u09b0 \u09ac\u09bf\u09ae\u09be\u09a8\u09ac\u09a8\u09cd\u09a6\u09b0"
    ],
    "name:ben_x_variant":[
        "\u09b6\u09cd\u09b0\u09c0\u09a8\u0997\u09b0 \u0986\u09a8\u09cd\u09a4\u09b0\u09cd\u099c\u09be\u09a4\u09bf\u0995 \u09ac\u09bf\u09ae\u09be\u09a8\u09ac\u09a8\u09cd\u09a6\u09b0"
    ],
    "name:ceb_x_preferred":[
        "Sheikh ul Alam Airport"
    ],
    "name:deu_x_preferred":[
        "Flughafen Srinagar"
    ],
    "name:eng_x_preferred":[
        "Srinagar Airport"
    ],
    "name:eng_x_variant":[
        "SXR",
        "VISR"
    ],
    "name:fas_x_preferred":[
        "\u0641\u0631\u0648\u062f\u06af\u0627\u0647 \u0633\u0631\u06cc\u0646\u06af\u0631"
    ],
    "name:hin_x_preferred":[
        "\u0936\u094d\u0930\u0940\u0928\u0917\u0930 \u0935\u093f\u092e\u093e\u0928\u0915\u094d\u0937\u0947\u0924\u094d\u0930"
    ],
    "name:jpn_x_preferred":[
        "\u30b7\u30e5\u30ea\u30fc\u30ca\u30ac\u30eb\u7a7a\u6e2f"
    ],
    "name:mar_x_preferred":[
        "\u0936\u094d\u0930\u0940\u0928\u0917\u0930 \u0935\u093f\u092e\u093e\u0928\u0924\u0933"
    ],
    "name:msa_x_preferred":[
        "Lapangan Terbang Srinagar"
    ],
    "name:ron_x_preferred":[
        "Aeroportul Srinagar"
    ],
    "name:rus_x_preferred":[
        "\u041c\u0435\u0436\u0434\u0443\u043d\u0430\u0440\u043e\u0434\u043d\u044b\u0439 \u0430\u044d\u0440\u043e\u043f\u043e\u0440\u0442 \u0421\u0440\u0438\u043d\u0430\u0433\u0430\u0440"
    ],
    "name:spa_x_preferred":[
        "Aeropuerto de Srinagar"
    ],
    "name:swe_x_preferred":[
        "Sheikh ul Alam Airport"
    ],
    "name:tam_x_preferred":[
        "\u0b9a\u0bbf\u0bb1\u0bc0\u0ba8\u0b95\u0bb0\u0bcd \u0bb5\u0bbe\u0ba9\u0bc2\u0bb0\u0bcd\u0ba4\u0bbf \u0ba8\u0bbf\u0bb2\u0bc8\u0baf\u0bae\u0bcd"
    ],
    "name:tgk_x_preferred":[
        "\u0424\u0443\u0440\u0443\u0434\u0433\u043e\u04b3\u0438 \u0441\u0440\u0438\u043d\u0433\u0440"
    ],
    "name:urd_x_preferred":[
        "\u0633\u0631\u06cc\u0646\u06af\u0631 \u06c1\u0648\u0627\u0626\u06cc \u0627\u0688\u06d2"
    ],
    "name:vie_x_preferred":[
        "S\u00e2n bay Srinagar"
    ],
    "name:zho_x_preferred":[
        "\u65af\u5229\u90a3\u52a0\u6a5f\u5834"
    ],
    "oa:elevation_ft":"5429",
    "oa:type":"medium_airport",
    "wd:wordcount":307,
    "woe:hierarchy":{
        "country_id":23424848,
        "county_id":28298853,
        "planet_id":1,
        "state_id":2345746
    },
    "wof:name":"Srinagar Airport",
    "wof:placetype":"campus"
},
  "geometry": {"coordinates":[74.77424999999999,33.987139],"type":"Point"}
}