{
  "type": "Feature",
  "properties": {
    "name:fas_x_preferred":[
        "\u0641\u0631\u0648\u062f\u06af\u0627\u0647 \u0633\u0631\u06cc\u0646\u06af\u0631"
    ],
    "name:mar_x_preferred":[
        "\u0936\u094d\u0930\u0940\u0928\u0917\u0930 \u0935\u093f\u092e\u093e\u0928\u0924\u0933"
    ],
    "name:msa_x_preferred":[
        "Lapangan Terbang Srinagar"
    ],
    "name:spa_x_preferred":[
        "Aeropuerto de Srinagar"
    ],
    "name:tgk_x_preferred":[
        "\u0424\u0443\u0440\u0443\u0434\u0433\u043e\u04b3\u0438 \u0441\u0440\u0438\u043d\u0433\u0440"
    ],
    "name:vie_x_preferred":[
        "S\u00e2n bay Srinagar"
    ],
    "name:zho_x_preferred":[
        "\u65af\u5229\u90a3\u52a0\u6a5f\u5834"
    ],
    "oa:elevation_ft":"5429",
    "oa:type":"medium_airport",
    "wd:wordcount":307,
    "woe:hierarchy":{
        "country_id":23424848,
        "county_id":28298853,
        "planet_id":1,
        "state_id":2345746
    },
    "wof:name":"Srinagar Airport",
    "wof:placetype":"campus"
},
  "geometry": {"coordinates":[74.77424999999999,33.987138888889],"type":"Point"}
}