{
  "type": "Feature",
  "properties": {
    "name:ceb_x_preferred":[
        "PAF Base Mushaf"
    ],
    "name:eng_x_preferred":[
        "PAF Base Mushaf"
    ],
    "name:eng_x_variant":[
        "SGI",
        "OPSR"
    ],
    "name:fas_x_preferred":[
        "\u067e\u0627\u06cc\u06af\u0627\u0647 \u0646\u06cc\u0631\u0648\u06cc \u0647\u0648\u0627\u06cc\u06cc \u067e\u0627\u06a9\u0633\u062a\u0627\u0646 \u062f\u0631 \u0645\u0648\u0634\u0627\u0641"
    ],
    "name:jpn_x_preferred":[
        "\u30e0\u30b7\u30e3\u30d5\u7a7a\u8ecd\u57fa\u5730"
    ],
    "name:msa_x_preferred":[
        "Lapangan Terbang Sargodha AB"
    ],
    "name:pnb_x_preferred":[
        "\u0645\u0635\u062d\u0641 \u0627\u06cc\u0626\u0631 \u0628\u06cc\u0633"
    ],
    "name:tgk_x_preferred":[
        "\u041f\u043e\u0439\u0433\u043e\u04b3\u0438 \u043d\u0435\u0440\u04ef\u0435 \u04b3\u0430\u0432\u043e \u041f\u043e\u043a\u0438\u0441\u0442\u043e\u043d \u0434\u0430\u0440 \u043c\u0443\u0448\u043e\u0444"
    ],
    "name:urd_x_preferred":[
        "\u0633\u0631\u06af\u0648\u062f\u06be\u0627 \u0627\u0626\u06cc\u0631 \u0628\u06cc\u0633"
    ],
    "oa:elevation_ft":"614",
    "oa:type":"medium_airport",
    "woe:hierarchy":{
        "country_id":23424922,
        "planet_id":1,
        "state_id":2346498
    },
    "wof:name":"Sargodha Airport",
    "wof:placetype":"campus"
},
  "geometry": {"coordinates":[72.665001,32.048599],"type":"Point"}
}