{
  "type": "Feature",
  "properties": {
    "name:ceb_x_preferred":[
        "Jwaneng Airport"
    ],
    "name:eng_x_preferred":[
        "Jwaneng Airport"
    ],
    "name:fas_x_preferred":[
        "\u0641\u0631\u0648\u062f\u06af\u0627\u0647 \u06cc\u0648\u0627\u0646\u0646\u06af"
    ],
    "name:jpn_x_preferred":[
        "\u30b8\u30a7\u30a4\u30f3\u30b0\u7a7a\u6e2f"
    ],
    "name:msa_x_preferred":[
        "Lapangan Terbang Jwaneng"
    ],
    "name:pol_x_preferred":[
        "Port lotniczy Jwaneng"
    ],
    "name:ron_x_preferred":[
        "Aeroportul Jwaneng"
    ],
    "name:rus_x_preferred":[
        "\u0414\u0436\u0432\u0430\u043d\u0435\u043d\u0433"
    ],
    "name:swe_x_preferred":[
        "Jwaneng Airport"
    ],
    "name:tgk_x_preferred":[
        "\u0424\u0443\u0440\u0443\u0434\u0433\u043e\u04b3\u0438 \u044e\u043e\u043d\u043d\u0433"
    ],
    "oa:elevation_ft":"3900",
    "oa:type":"medium_airport",
    "wd:wordcount":136,
    "woe:hierarchy":{
        "country_id":23424755,
        "planet_id":1,
        "state_id":2344750
    },
    "wof:name":"Jwaneng Airport",
    "wof:placetype":"campus"
},
  "geometry": {"coordinates":[24.698888888889,-24.598333333333],"type":"Point"}
}