{
  "type": "Feature",
  "properties": {
    "name:deu_x_preferred":[
        "Flughafen Bidar"
    ],
    "name:fas_x_preferred":[
        "\u0641\u0631\u0648\u062f\u06af\u0627\u0647 \u0628\u06cc\u062f\u0631"
    ],
    "name:tam_x_preferred":[
        "\u0baa\u0bc0\u0ba4\u0bb0\u0bcd \u0bb5\u0bbf\u0bae\u0bbe\u0ba9 \u0ba8\u0bbf\u0bb2\u0bc8\u0baf\u0bae\u0bcd"
    ],
    "name:tgk_x_preferred":[
        "\u0424\u0443\u0440\u0443\u0434\u0433\u043e\u04b3\u0438 \u0411\u0438\u0434\u0430\u0440"
    ],
    "oa:elevation_ft":"2178",
    "oa:type":"medium_airport",
    "wd:wordcount":378,
    "woe:hierarchy":{
        "country_id":23424848,
        "county_id":12586575,
        "planet_id":1,
        "state_id":2345753
    },
    "wof:name":"Bidar Airport",
    "wof:placetype":"campus"
},
  "geometry": {"coordinates":[77.47944443999999,17.90666667],"type":"Point"}
}