{
  "type": "Feature",
  "properties": {
    "name:ben_x_preferred":[
        "\u09ac\u09bf\u09a6\u09be\u09b0 \u09ac\u09bf\u09ae\u09be\u09a8\u09ac\u09a8\u09cd\u09a6\u09b0"
    ],
    "name:ceb_x_preferred":[
        "Bidar Airbase"
    ],
    "name:cym_x_preferred":[
        "Maes Awyr Bidar"
    ],
    "name:deu_x_preferred":[
        "Flughafen Bidar"
    ],
    "name:eng_x_preferred":[
        "Bidar Airport"
    ],
    "name:eng_x_variant":[
        "VOBR"
    ],
    "name:fas_x_preferred":[
        "\u0641\u0631\u0648\u062f\u06af\u0627\u0647 \u0628\u06cc\u062f\u0631"
    ],
    "name:hin_x_preferred":[
        "\u092c\u093f\u0926\u0930 \u0939\u0935\u093e\u0908 \u0905\u0921\u094d\u0921\u0947"
    ],
    "name:jpn_x_preferred":[
        "\u30d3\u30fc\u30c0\u30eb\u7a7a\u8ecd\u57fa\u5730"
    ],
    "name:kan_x_preferred":[
        "\u0cac\u0cc0\u0ca6\u0cb0\u0ccd \u0cb5\u0cbf\u0cae\u0cbe\u0ca8 \u0ca8\u0cbf\u0cb2\u0ccd\u0ca6\u0cbe\u0ca3"
    ],
    "name:kan_x_variant":[
        "\u0cac\u0cc0\u0ca6\u0cb0\u0ccd  \u0cb5\u0cbf\u0cae\u0cbe\u0ca8 \u0ca8\u0cbf\u0cb2\u0ccd\u0ca6\u0cbe\u0ca3"
    ],
    "name:msa_x_preferred":[
        "Lapangan Terbang Bidar"
    ],
    "name:ron_x_preferred":[
        "Aeroportul Bidar"
    ],
    "name:san_x_preferred":[
        "\u092c\u0940\u0926\u0930\u0935\u093f\u092e\u093e\u0928\u092a\u0924\u094d\u0924\u0928"
    ],
    "name:swe_x_preferred":[
        "Bidar Airbase"
    ],
    "name:tam_x_preferred":[
        "\u0baa\u0bc0\u0ba4\u0bb0\u0bcd \u0bb5\u0bbf\u0bae\u0bbe\u0ba9 \u0ba8\u0bbf\u0bb2\u0bc8\u0baf\u0bae\u0bcd"
    ],
    "name:tgk_x_preferred":[
        "\u0424\u0443\u0440\u0443\u0434\u0433\u043e\u04b3\u0438 \u0411\u0438\u0434\u0430\u0440"
    ],
    "name:tgk_x_variant":[
        "\u0424\u0443\u0440\u0443\u0434\u0433\u043e\u04b3\u0438 \u0431\u0438\u0434\u0440"
    ],
    "oa:elevation_ft":"2178",
    "oa:type":"medium_airport",
    "wd:wordcount":378,
    "woe:hierarchy":{
        "country_id":23424848,
        "county_id":12586575,
        "planet_id":1,
        "state_id":2345753
    },
    "wof:name":"Bidar Airport",
    "wof:placetype":"campus"
},
  "geometry": {"coordinates":[77.479444,17.906667],"type":"Point"}
}