{
  "type": "Feature",
  "properties": {
    "label:eng_x_preferred_longname":[
        "Asan Village"
    ],
    "label:eng_x_preferred_placetype":[
        "village"
    ],
    "name:ara_x_preferred":[
        "\u0622\u0633\u0627\u0646"
    ],
    "name:ceb_x_preferred":[
        "Asan"
    ],
    "name:ces_x_preferred":[
        "Asan"
    ],
    "name:deu_x_preferred":[
        "Asan"
    ],
    "name:eng_x_preferred":[
        "Asan"
    ],
    "name:epo_x_preferred":[
        "Asan"
    ],
    "name:est_x_preferred":[
        "Asan"
    ],
    "name:fas_x_preferred":[
        "\u0622\u0633\u0627\u0646"
    ],
    "name:fin_x_preferred":[
        "Asan"
    ],
    "name:fra_x_preferred":[
        "Asan"
    ],
    "name:hak_x_preferred":[
        "Asan S\u1e73"
    ],
    "name:hun_x_preferred":[
        "Aszan"
    ],
    "name:ind_x_preferred":[
        "Asan"
    ],
    "name:ita_x_preferred":[
        "Asan"
    ],
    "name:jav_x_preferred":[
        "Asan"
    ],
    "name:jpn_x_preferred":[
        "\u7259\u5c71\u5e02"
    ],
    "name:kat_x_preferred":[
        "\u10d0\u10e1\u10d0\u10dc\u10d8"
    ],
    "name:kor_x_preferred":[
        "\uc544\uc0b0\uc2dc"
    ],
    "name:mon_x_preferred":[
        "\u0410\u0441\u0430\u043d\u044c"
    ],
    "name:nld_x_preferred":[
        "Asan"
    ],
    "name:nor_x_preferred":[
        "Asan"
    ],
    "name:pol_x_preferred":[
        "Asan"
    ],
    "name:rus_x_preferred":[
        "\u0410\u0441\u0430\u043d"
    ],
    "name:sco_x_preferred":[
        "Asan"
    ],
    "name:spa_x_preferred":[
        "Asan"
    ],
    "name:swe_x_preferred":[
        "Asan"
    ],
    "name:tam_x_preferred":[
        "\u0b85\u0b9a\u0ba9\u0bcd"
    ],
    "name:tgl_x_preferred":[
        "Asan"
    ],
    "name:tha_x_preferred":[
        "\u0e2d\u0e32\u0e0b\u0e31\u0e19"
    ],
    "name:tur_x_preferred":[
        "Asan"
    ],
    "name:urd_x_preferred":[
        "\u0627\u0633\u0627\u0646"
    ],
    "name:vep_x_preferred":[
        "Asan"
    ],
    "name:vie_x_preferred":[
        "Asan"
    ],
    "name:war_x_preferred":[
        "Asan"
    ],
    "name:zho_x_preferred":[
        "\u7259\u5c71\u5e02"
    ],
    "qs:name":"Asan",
    "qs:name_adm0":"Guam",
    "qs:name_adm1":"Asan",
    "qs:photos":995,
    "qs:photos_1k":202,
    "qs:photos_9k":10,
    "qs:photos_9r":10,
    "qs:photos_all":2337,
    "qs:photos_sr":10,
    "qs:placetype":"State",
    "qs:pop_sr":"0",
    "wd:wordcount":530,
    "wof:name":"Asan",
    "wof:placetype":"region"
},
  "geometry": {"coordinates":[144.70916700000001,13.44973],"type":"Point"}
}