{
  "type": "Feature",
  "properties": {
    "label:eng_x_preferred_longname":[
        "Asan Village"
    ],
    "label:eng_x_preferred_placetype":[
        "village"
    ],
    "name:eng_x_preferred":[
        "Asan"
    ],
    "qs:name":"Asan",
    "qs:name_adm0":"Guam",
    "qs:name_adm1":"Asan",
    "qs:photos":995,
    "qs:photos_1k":202,
    "qs:photos_9k":10,
    "qs:photos_9r":10,
    "qs:photos_all":2337,
    "qs:photos_sr":10,
    "qs:placetype":"State",
    "qs:pop_sr":"0",
    "wd:wordcount":530,
    "wof:name":"Asan",
    "wof:placetype":"region"
},
  "geometry": {"coordinates":[144.70916700000001,13.44973],"type":"Point"}
}