{
  "type": "Feature",
  "properties": {
    "name:ceb_x_preferred":[
        "Hall Beach Airport"
    ],
    "name:eng_x_preferred":[
        "Hall Beach Airport"
    ],
    "name:fas_x_preferred":[
        "\u0641\u0631\u0648\u062f\u06af\u0627\u0647 \u0647\u0627\u0644 \u0628\u06cc\u0686"
    ],
    "name:fin_x_preferred":[
        "Hall Beachin lentoasema"
    ],
    "name:ind_x_preferred":[
        "Bandar Udara Hall Beach"
    ],
    "name:msa_x_preferred":[
        "Lapangan Terbang Hall Beach"
    ],
    "name:pms_x_preferred":[
        "Hall Beach Airport"
    ],
    "name:ron_x_preferred":[
        "Aeroportul Hall Beach"
    ],
    "name:spa_x_preferred":[
        "Aeropuerto de Hall Beach"
    ],
    "name:swe_x_preferred":[
        "Hall Beach Airport"
    ],
    "oa:elevation_ft":"30",
    "oa:type":"medium_airport",
    "wd:wordcount":80,
    "woe:hierarchy":{
        "country_id":23424775,
        "county_id":29375230,
        "planet_id":1,
        "state_id":20069920
    },
    "wof:name":"Hall Beach Airport",
    "wof:placetype":"campus"
},
  "geometry": {"coordinates":[-81.24250000000001,68.775833333333],"type":"Point"}
}