{
  "type": "Feature",
  "properties": {
    "gn:admin1_code":"33.0",
    "gn:asciiname":"Ombabi",
    "gn:dem":1164,
    "gn:feature_class":"P",
    "gn:feature_code":"PPL",
    "gn:name":"Ombabi",
    "gn:population":0,
    "gn:timezone":"Africa/Windhoek",
    "wof:name":"Ombabi",
    "wof:placetype":"locality"
},
  "geometry": {"coordinates":[17.46667,-17.38332999999999],"type":"Point"}
}